Workbook

Sheet README
A1: Six South — Chemicals, petrochemicals & fertilisers industry model
A2: Generated 2026-10-29T18:55:56+07:00 by the coverage engine. The engine (scripts/cov_engine.py) is the source of truth; this workbook is a live rendering of it.
A3: Colour key: blue = input or hard-coded history; black = formula; green = link to another sheet.
A4: Drivers: every deck variable these models read. Change one and every ticker tab and the Comps sheet recalculate (forecasts, cash flows, DCF value, base-case value, target, rating).
A5: Scenario (bear/bull) and sensitivity tables need full model re-runs and are engine values.
A6: Paper fund — research for education and process transparency, not investment advice.
A8: Tickers:
A9: TPIA.JK — PT Chandra Asri Pacific Tbk

Sheet Drivers
A1: Driver decks (state/drivers) — edit a blue cell to flow it through every ticker tab
A3: Variable | B3: Key | C3: Unit / status | D3: FY2022A | E3: FY2023A | F3: FY2024A | G3: FY2025A | H3: FY2026E | I3: FY2027E | J3: FY2028E | K3: FY2029E | L3: FY2030E | M3: FY2031E | N3: FY2032E | O3: FY2033E | P3: FY2034E | Q3: FY2035E
A4: IDR per USD | B4: m.usd_idr | C4: IDR/USD · reviewed | D4: 14843.177 | E4: 15228.8 | F4: 15846.238 | G4: 16448.093 | H4: 17570 | I4: 18350 | J4: 18600 | K4: 18850 | L4: 19093.137 | M4: 19186.731 | N4: 19280.784 | O4: 19375.297 | P4: 19470.274 | Q4: 19565.717
A5: Brent crude | B5: d.oil.brent | C5: USD/bbl · reviewed | D5: 98.9663 | E5: 82.1904 | F5: 79.8213 | G5: 68.1015 | H5: 96 | I5: 84 | J5: 80 | K5: 78 | L5: 76.5 | M5: 78.03 | N5: 79.5906 | O5: 81.182412 | P5: 82.80606 | Q5: 84.462181
A7: Cost-of-capital scalars (macro deck)
A8: 10-year Indonesian government bond yield (IDR) | B8: m.rf_idr | C8: 0.0745 | D8: investor.id — "Yield SUN 7,45%, Saatnya Borong atau Tunggu Lebih Tinggi?" (25 Okt 2026 20:58 WIB; deck source S3); corroborated by kalderanews S1 (10Y SUN 7.41%
A9: 10-year US Treasury yield | B9: m.rf_usd | C9: 0.05045 | D9: Yahoo Finance ^TNX (US 10-year Treasury yield)
A10: Indonesia sovereign default spread (Damodaran) | B10: m.default_spread_id | C10: 0.0162 | D10: Damodaran country risk premiums (https://pages.stern.nyu.edu/~adamodar/New_Home_Page/datafile/ctryprem.html), page dated January 5, 2026, read 2026-10-29
A11: Mature-market equity risk premium (Damodaran) | B11: m.erp_mature | C11: 0.0423 | D11: Damodaran country risk premiums (https://pages.stern.nyu.edu/~adamodar/New_Home_Page/datafile/ctryprem.html), page dated January 5, 2026, read 2026-10-29
A12: Indonesia country risk premium (Damodaran) | B12: m.crp_id | C12: 0.0246 | D12: Damodaran country risk premiums (https://pages.stern.nyu.edu/~adamodar/New_Home_Page/datafile/ctryprem.html), page dated January 5, 2026, read 2026-10-29
A13: House pre-tax corporate debt spread over the risk-free | B13: m.debt_spread_corp | C13: 0.02 | D13: SEED house assumption pending the macro desk: 200 bp over the risk-free rate for an average IDX corporate borrower
A14: Indonesia statutory corporate income tax rate | B14: m.tax_rate_id | C14: 0.22 | D14: Law 7/2021 on Harmonisation of Tax Regulations (UU HPP): 22% corporate income tax from fiscal 2022

Sheet Comps
A1: Ticker | B1: Company | C1: Rating | D1: Target (IDR) | E1: Price (IDR) | F1: Exp. 12m TR | G1: Value today | H1: P/E FY+0 | I1: EV/EBITDA FY+0 | J1: Div. yield FY+0
A2: TPIA.JK | B2: PT Chandra Asri Pacific Tbk | C2: ='TPIA'!$C$136 | D2: ='TPIA'!$C$134 | E2: ='TPIA'!$C$77 | F2: ='TPIA'!$C$135 | G2: ='TPIA'!$C$115 | H2: 15.366066 | I2: 8.673428 | J2: 0.006508

Sheet TPIA
A1: PT Chandra Asri Pacific Tbk (TPIA.JK) — Chemicals, petrochemicals & fertilisers
A2: Units: USD m; per-share in USD unless marked IDR. Model asof 2026-10-29 · data 2026-10-27
A4: Line | C4: Scalar | D4: FY2022A | E4: FY2023A | F4: FY2024A | G4: FY2025A | H4: FY2026E | I4: FY2027E | J4: FY2028E | K4: FY2029E | L4: FY2030E | M4: FY2031E | N4: FY2032E | O4: FY2033E | P4: FY2034E | Q4: FY2035E
A6: PARAMETERS
A7: ps_factor | C7: 1
A8: vp_factor | C8: 1
A10: INPUTS (company assumptions)
A11: Revenue growth | B11: a.revenue_growth | H11: 0.52 | I11: 0.03 | J11: 0.03 | K11: 0.03 | L11: 0.03 | M11: 0.03 | N11: 0.03 | O11: 0.03 | P11: 0.03 | Q11: 0.03
A12: Gross margin at base input costs | B12: a.gross_margin | H12: 0.191 | I12: 0.191 | J12: 0.191 | K12: 0.191 | L12: 0.191 | M12: 0.191 | N12: 0.191 | O12: 0.191 | P12: 0.191 | Q12: 0.191
A13: Cost link 1: share of COGS exposed | B13: a.link1_share | C13: 0.6
A14: Cost link 1: pass-through to prices | B14: a.link1_pass | C14: 0.8
A15: SG&A / revenue | B15: a.opex_pct | H15: 0.062 | I15: 0.062 | J15: 0.062 | K15: 0.062 | L15: 0.062 | M15: 0.062 | N15: 0.062 | O15: 0.062 | P15: 0.062 | Q15: 0.062
A16: D&A / revenue | B16: a.da_pct | H16: 0.0307 | I16: 0.0307 | J16: 0.0307 | K16: 0.0307 | L16: 0.0307 | M16: 0.0307 | N16: 0.0307 | O16: 0.0307 | P16: 0.0307 | Q16: 0.0307
A17: Capex / revenue | B17: a.capex_pct | H17: 0.055 | I17: 0.055 | J17: 0.045 | K17: 0.04 | L17: 0.04 | M17: 0.04 | N17: 0.04 | O17: 0.04 | P17: 0.04 | Q17: 0.04
A18: Operating working capital / revenue | B18: a.nwc_pct | H18: 0.1 | I18: 0.09 | J18: 0.09 | K18: 0.09 | L18: 0.09 | M18: 0.09 | N18: 0.09 | O18: 0.09 | P18: 0.09 | Q18: 0.09
A19: Effective tax rate | B19: a.tax_rate | H19: 0.145 | I19: 0.16 | J19: 0.18 | K19: 0.2 | L19: 0.2 | M19: 0.2 | N19: 0.2 | O19: 0.2 | P19: 0.2 | Q19: 0.2
A20: Cost of debt (on opening debt) | B20: a.cost_of_debt | C20: 0.064
A21: Yield on opening cash | B21: a.cash_yield | C21: 0.042
A22: Net new borrowing | B22: a.net_borrowing | H22: 496.707 | I22: 0 | J22: 0 | K22: 0 | L22: 0 | M22: 0 | N22: 0 | O22: 0 | P22: 0 | Q22: 0
A23: Other non-operating items | B23: a.other_nonop | H23: 0 | I23: 0 | J23: 0 | K23: 0 | L23: 0 | M23: 0 | N23: 0 | O23: 0 | P23: 0 | Q23: 0
A24: Minorities' share of net profit | B24: a.minority_pct | H24: 0.24 | I24: 0.24 | J24: 0.24 | K24: 0.24 | L24: 0.24 | M24: 0.24 | N24: 0.24 | O24: 0.24 | P24: 0.24 | Q24: 0.24
A25: Dividend payout | B25: a.payout | H25: 0.1 | I25: 0.1 | J25: 0.1 | K25: 0.1 | L25: 0.1 | M25: 0.1 | N25: 0.1 | O25: 0.1 | P25: 0.1 | Q25: 0.1
A26: Change in share count | B26: a.share_change | H26: 0 | I26: 0 | J26: 0 | K26: 0 | L26: 0 | M26: 0 | N26: 0 | O26: 0 | P26: 0 | Q26: 0
A27: Terminal growth (DCF) | B27: a.terminal_growth | C27: 0.025
A29: MODEL
A30: Revenue | B30: revenue | D30: 2384.591 | E30: 2159.932 | F30: 1785.364 | G30: 7000 | H30: =(G30*(1+H11)) | I30: =(H30*(1+I11)) | J30: =(I30*(1+J11)) | K30: =(J30*(1+K11)) | L30: =(K30*(1+L11)) | M30: =(L30*(1+M11)) | N30: =(M30*(1+N11)) | O30: =(N30*(1+O11)) | ... Q30: =(P30*(1+Q11))
A31: Cost of revenue | B31: cogs | D31: 2395.545 | E31: 2078.102 | F31: 1628.199 | G31: 7062.478 | H31: =((H30*(1-H12))*(1+(($C$13*(1-$C$14))*(IF(Drivers!$G$5=0,0,Drivers!$H$5/Drivers!$G$5)-1)))) | I31: =((I30*(1-I12))*(1+(($C$13*(1-$C$14))*(IF(Drivers!$G$5=0,0,Drivers!$I$5/Drivers!$G$5)-1)))) | J31: =((J30*(1-J12))*(1+(($C$13*(1-$C$14))*(IF(Drivers!$G$5=0,0,Drivers!$J$5/Drivers!$G$5)-1)))) | K31: =((K30*(1-K12))*(1+(($C$13*(1-$C$14))*(IF(Drivers!$G$5=0,0,Drivers!$K$5/Drivers!$G$5)-1)))) | L31: =((L30*(1-L12))*(1+(($C$13*(1-$C$14))*(IF(Drivers!$G$5=0,0,Drivers!$L$5/Drivers!$G$5)-1)))) | M31: =((M30*(1-M12))*(1+(($C$13*(1-$C$14))*(IF(Drivers!$G$5=0,0,Drivers!$M$5/Drivers!$G$5)-1)))) | N31: =((N30*(1-N12))*(1+(($C$13*(1-$C$14))*(IF(Drivers!$G$5=0,0,Drivers!$N$5/Drivers!$G$5)-1)))) | O31: =((O30*(1-O12))*(1+(($C$13*(1-$C$14))*(IF(Drivers!$G$5=0,0,Drivers!$O$5/Drivers!$G$5)-1)))) | P31: =((P30*(1-P12))*(1+(($C$13*(1-$C$14))*(IF(Drivers!$G$5=0,0,Drivers!$P$5/Drivers!$G$5)-1)))) | Q31: =((Q30*(1-Q12))*(1+(($C$13*(1-$C$14))*(IF(Drivers!$G$5=0,0,Drivers!$Q$5/Drivers!$G$5)-1))))
A32: Gross profit | B32: gross_profit | D32: -10.954 | E32: 81.83 | F32: 157.165 | G32: -42.471 | H32: =(H30-H31) | I32: =(I30-I31) | J32: =(J30-J31) | K32: =(K30-K31) | L32: =(L30-L31) | M32: =(M30-M31) | N32: =(N30-N31) | O32: =(O30-O31) | ... Q32: =(Q30-Q31)
A33: SG&A and other opex | B33: opex | D33: 105.266 | E33: 109.705 | F33: 213.897 | G33: 550.227 | H33: =(H30*H15) | I33: =(I30*I15) | J33: =(J30*J15) | K33: =(K30*K15) | L33: =(L30*L15) | M33: =(M30*M15) | N33: =(N30*N15) | O33: =(O30*O15) | ... Q33: =(Q30*Q15)
A34: EBIT | B34: ebit | D34: -116.22 | E34: -27.875 | F34: -56.732 | G34: -592.698 | H34: =(H32-H33) | I34: =(I32-I33) | J34: =(J32-J33) | K34: =(K32-K33) | L34: =(L32-L33) | M34: =(M32-M33) | N34: =(N32-N33) | O34: =(O32-O33) | ... Q34: =(Q32-Q33)
A35: Depreciation & amortisation | B35: da | D35: 2.224 | E35: 2.888 | F35: 114.976 | G35: 203.474 | H35: =(H30*H16) | I35: =(I30*I16) | J35: =(J30*J16) | K35: =(K30*K16) | L35: =(L30*L16) | M35: =(M30*M16) | N35: =(N30*N16) | O35: =(O30*O16) | ... Q35: =(Q30*Q16)
A36: EBITDA | B36: ebitda | D36: -113.996 | E36: -24.987 | F36: 58.244 | G36: -389.224 | H36: =(H34+H35) | I36: =(I34+I35) | J36: =(J34+J35) | K36: =(K34+K35) | L36: =(L34+L35) | M36: =(M34+M35) | N36: =(N34+N35) | O36: =(O34+O35) | ... Q36: =(Q34+Q35)
A37: Interest expense | B37: interest_expense | D37: 70.612 | E37: 115.633 | F37: 135.836 | G37: 238.4 | H37: =(G57*$C$20) | I37: =(H57*$C$20) | J37: =(I57*$C$20) | K37: =(J57*$C$20) | L37: =(K57*$C$20) | M37: =(L57*$C$20) | N37: =(M57*$C$20) | O37: =(N57*$C$20) | ... Q37: =(P57*$C$20)
A38: Interest income | B38: interest_income | E38: 75.508 | F38: 94.974 | G38: 122.376 | H38: =(G56*$C$21) | I38: =(H56*$C$21) | J38: =(I56*$C$21) | K38: =(J56*$C$21) | L38: =(K56*$C$21) | M38: =(L56*$C$21) | N38: =(M56*$C$21) | O38: =(N56*$C$21) | ... Q38: =(P56*$C$21)
A39: Other non-operating | B39: other_nonop | E39: 13.436 | F39: 6.655 | G39: 2002.931 | H39: =H23 | I39: =I23 | J39: =J23 | K39: =K23 | L39: =L23 | M39: =M23 | N39: =N23 | O39: =O23 | ... Q39: =Q23
A40: Profit before tax | B40: pbt | D40: -176.475 | E40: -54.564 | F40: -90.939 | G40: 1294.209 | H40: =(((H34-H37)+H38)+H39) | I40: =(((I34-I37)+I38)+I39) | J40: =(((J34-J37)+J38)+J39) | K40: =(((K34-K37)+K38)+K39) | L40: =(((L34-L37)+L38)+L39) | M40: =(((M34-M37)+M38)+M39) | N40: =(((N34-N37)+N38)+N39) | O40: =(((O34-O37)+O38)+O39) | ... Q40: =(((Q34-Q37)+Q38)+Q39)
A41: Tax | B41: tax | D41: -27.076 | E41: -23.017 | F41: -34.429 | G41: -153.777 | H41: =(MAX(H40,0)*H19) | I41: =(MAX(I40,0)*I19) | J41: =(MAX(J40,0)*J19) | K41: =(MAX(K40,0)*K19) | L41: =(MAX(L40,0)*L19) | M41: =(MAX(M40,0)*M19) | N41: =(MAX(N40,0)*N19) | O41: =(MAX(O40,0)*O19) | ... Q41: =(MAX(Q40,0)*Q19)
A42: Net profit (incl. minorities) | B42: np | D42: -149.399 | E42: -31.547 | F42: -56.51 | G42: 1447.986 | H42: =(H40-H41) | I42: =(I40-I41) | J42: =(J40-J41) | K42: =(K40-K41) | L42: =(L40-L41) | M42: =(M40-M41) | N42: =(N40-N41) | O42: =(O40-O41) | ... Q42: =(Q40-Q41)
A43: Minority interests | B43: minority | D43: 0.139 | E43: 2.029 | F43: 12.1 | G43: 357.895 | H43: =(H42*H24) | I43: =(I42*I24) | J43: =(J42*J24) | K43: =(K42*K24) | L43: =(L42*L24) | M43: =(M42*M24) | N43: =(N42*N24) | O43: =(O42*O24) | ... Q43: =(Q42*Q24)
A44: Net profit to parent | B44: np_parent | D44: -149.538 | E44: -33.576 | F44: -68.61 | G44: 1090.091 | H44: =(H42-H43) | I44: =(I42-I43) | J44: =(J42-J43) | K44: =(K42-K43) | L44: =(L42-L43) | M44: =(M42-M43) | N44: =(N42-N43) | O44: =(O42-O43) | ... Q44: =(Q42-Q43)
A45: Shares outstanding (m) | B45: shares | D45: 86511.545 | E45: 86511.545 | F45: 86511.545 | G45: 86503.906 | H45: =(G45*(1+H26)) | I45: =(H45*(1+I26)) | J45: =(I45*(1+J26)) | K45: =(J45*(1+K26)) | L45: =(K45*(1+L26)) | M45: =(L45*(1+M26)) | N45: =(M45*(1+N26)) | O45: =(N45*(1+O26)) | ... Q45: =(P45*(1+Q26))
A46: EPS | B46: eps | D46: -0.0017285323 | E46: -0.00038811005 | F46: -0.00079307334 | G46: 0.012601639 | H46: =(IF(H45=0,0,H44/H45)*$C$7) | I46: =(IF(I45=0,0,I44/I45)*$C$7) | J46: =(IF(J45=0,0,J44/J45)*$C$7) | K46: =(IF(K45=0,0,K44/K45)*$C$7) | L46: =(IF(L45=0,0,L44/L45)*$C$7) | M46: =(IF(M45=0,0,M44/M45)*$C$7) | N46: =(IF(N45=0,0,N44/N45)*$C$7) | O46: =(IF(O45=0,0,O44/O45)*$C$7) | ... Q46: =(IF(Q45=0,0,Q44/Q45)*$C$7)
A47: DPS (declared on the year) | B47: dps | D47: 0.00034286267 | E47: 0.0003436283 | F47: 0.00058178037 | G47: 0.00034089639 | H47: =(MAX(H46,0)*H25) | I47: =(MAX(I46,0)*I25) | J47: =(MAX(J46,0)*J25) | K47: =(MAX(K46,0)*K25) | L47: =(MAX(L46,0)*L25) | M47: =(MAX(M46,0)*M25) | N47: =(MAX(N46,0)*N25) | O47: =(MAX(O46,0)*O25) | ... Q47: =(MAX(Q46,0)*Q25)
A48: Dividends paid | B48: dividends_paid | D48: 11 | E48: 30 | F48: 30 | G48: 50 | H48: =IF($C$7=0,0,(G47*G45)/$C$7) | I48: =IF($C$7=0,0,(H47*H45)/$C$7) | J48: =IF($C$7=0,0,(I47*I45)/$C$7) | K48: =IF($C$7=0,0,(J47*J45)/$C$7) | L48: =IF($C$7=0,0,(K47*K45)/$C$7) | M48: =IF($C$7=0,0,(L47*L45)/$C$7) | N48: =IF($C$7=0,0,(M47*M45)/$C$7) | O48: =IF($C$7=0,0,(N47*N45)/$C$7) | ... Q48: =IF($C$7=0,0,(P47*P45)/$C$7)
A49: Capital expenditure | B49: capex | D49: 114.254 | E49: 96.305 | F49: 405.055 | G49: 736.416 | H49: =(H30*H17) | I49: =(I30*I17) | J49: =(J30*J17) | K49: =(K30*K17) | L49: =(L30*L17) | M49: =(M30*M17) | N49: =(N30*N17) | O49: =(O30*O17) | ... Q49: =(Q30*Q17)
A50: Change in working capital | B50: delta_nwc | E50: -48.464 | F50: 131.293 | G50: 396.163 | H50: =(H55-G55) | I50: =(I55-H55) | J50: =(J55-I55) | K50: =(K55-J55) | L50: =(L55-K55) | M50: =(M55-L55) | N50: =(N55-M55) | O50: =(O55-N55) | ... Q50: =(Q55-P55)
A51: Free cash flow to firm | B51: fcff | E51: -61.069352 | F51: -456.62558 | G51: -1592.227 | H51: =((((H34*(1-H19))+H35)-H49)-H50) | I51: =((((I34*(1-I19))+I35)-I49)-I50) | J51: =((((J34*(1-J19))+J35)-J49)-J50) | K51: =((((K34*(1-K19))+K35)-K49)-K50) | L51: =((((L34*(1-L19))+L35)-L49)-L50) | M51: =((((M34*(1-M19))+M35)-M49)-M50) | N51: =((((N34*(1-N19))+N35)-N49)-N50) | O51: =((((O34*(1-O19))+O35)-O49)-O50) | ... Q51: =((((Q34*(1-Q19))+Q35)-Q49)-Q50)
A52: Net borrowing | B52: net_borrowing | E52: 269.618 | F52: 259.915 | G52: 3413.614 | H52: =H22 | I52: =I22 | J52: =J22 | K52: =K22 | L52: =L22 | M52: =M22 | N52: =N22 | O52: =O22 | ... Q52: =Q22
A53: Dividends to minorities | B53: minority_div | H53: =(MAX(G43,0)*H25) | I53: =(MAX(H43,0)*I25) | J53: =(MAX(I43,0)*J25) | K53: =(MAX(J43,0)*K25) | L53: =(MAX(K43,0)*L25) | M53: =(MAX(L43,0)*M25) | N53: =(MAX(M43,0)*N25) | O53: =(MAX(N43,0)*O25) | ... Q53: =(MAX(P43,0)*Q25)
A54: Free cash flow to equity | B54: fcfe | H54: =(((((H42+H35)-H49)-H50)+H52)-H53) | I54: =(((((I42+I35)-I49)-I50)+I52)-I53) | J54: =(((((J42+J35)-J49)-J50)+J52)-J53) | K54: =(((((K42+K35)-K49)-K50)+K52)-K53) | L54: =(((((L42+L35)-L49)-L50)+L52)-L53) | M54: =(((((M42+M35)-M49)-M50)+M52)-M53) | N54: =(((((N42+N35)-N49)-N50)+N52)-N53) | O54: =(((((O42+O35)-O49)-O50)+O52)-O53) | ... Q54: =(((((Q42+Q35)-Q49)-Q50)+Q52)-Q53)
A55: Operating working capital | B55: nwc | D55: 70.933 | E55: 22.469 | F55: 153.762 | G55: 549.925 | H55: =(H30*H18) | I55: =(I30*I18) | J55: =(J30*J18) | K55: =(K30*K18) | L55: =(L30*L18) | M55: =(M30*M18) | N55: =(N30*N18) | O55: =(O30*O18) | ... Q55: =(Q30*Q18)
A56: Cash & equivalents | B56: cash | D56: 1736.804 | E56: 2087.654 | F56: 1724.086 | G56: 2739.796 | H56: =(((((((G56+H42)+H35)-H49)-H50)+H52)-H48)-H53) | I56: =(((((((H56+I42)+I35)-I49)-I50)+I52)-I48)-I53) | J56: =(((((((I56+J42)+J35)-J49)-J50)+J52)-J48)-J53) | K56: =(((((((J56+K42)+K35)-K49)-K50)+K52)-K48)-K53) | L56: =(((((((K56+L42)+L35)-L49)-L50)+L52)-L48)-L53) | M56: =(((((((L56+M42)+M35)-M49)-M50)+M52)-M48)-M53) | N56: =(((((((M56+N42)+N35)-N49)-N50)+N52)-N48)-N53) | O56: =(((((((N56+O42)+O35)-O49)-O50)+O52)-O48)-O53) | ... Q56: =(((((((P56+Q42)+Q35)-Q49)-Q50)+Q52)-Q48)-Q53)
A57: Total debt | B57: debt | D57: 1471.083 | E57: 1740.701 | F57: 2000.616 | G57: 5414.23 | H57: =(G57+H52) | I57: =(H57+I52) | J57: =(I57+J52) | K57: =(J57+K52) | L57: =(K57+L52) | M57: =(L57+M52) | N57: =(M57+N52) | O57: =(N57+O52) | ... Q57: =(P57+Q52)
A58: Fixed assets (net) | B58: ppe | D58: 2056.093 | E58: 2209.534 | F58: 2497.121 | G58: 5023.945 | H58: =((G58+H49)-H35) | I58: =((H58+I49)-I35) | J58: =((I58+J49)-J35) | K58: =((J58+K49)-K35) | L58: =((K58+L49)-L35) | M58: =((L58+M49)-M35) | N58: =((M58+N49)-N35) | O58: =((N58+O49)-O35) | ... Q58: =((P58+Q49)-Q35)
A59: Parent shareholders' equity | B59: equity | D59: 2805.474 | E59: 2739.132 | F59: 2638.165 | G59: 3729.646 | H59: =((G59+H44)-H48) | I59: =((H59+I44)-I48) | J59: =((I59+J44)-J48) | K59: =((J59+K44)-K48) | L59: =((K59+L44)-L48) | M59: =((L59+M44)-M48) | N59: =((M59+N44)-N48) | O59: =((N59+O44)-O48) | ... Q59: =((P59+Q44)-Q48)
A60: Minority interest (balance sheet) | B60: minority_bs | D60: 3.632 | E60: 254.768 | F60: 299.294 | G60: 927.269 | H60: =((G60+H43)-H53) | I60: =((H60+I43)-I53) | J60: =((I60+J43)-J53) | K60: =((J60+K43)-K53) | L60: =((K60+L43)-L53) | M60: =((L60+M43)-M53) | N60: =((M60+N43)-N53) | O60: =((N60+O43)-O53) | ... Q60: =((P60+Q43)-Q53)
A61: Other assets less other liabilities | B61: other_net | D61: 416.359 | E61: 414.944 | F61: 563.106 | G61: 1757.479 | H61: =G61 | I61: =H61 | J61: =I61 | K61: =J61 | L61: =K61 | M61: =L61 | N61: =M61 | O61: =N61 | ... Q61: =P61
A62: Balance check (should be zero) | B62: bs_check | H62: =((((((H56+H55)+H58)+H61)-H57)-H59)-H60) | I62: =((((((I56+I55)+I58)+I61)-I57)-I59)-I60) | J62: =((((((J56+J55)+J58)+J61)-J57)-J59)-J60) | K62: =((((((K56+K55)+K58)+K61)-K57)-K59)-K60) | L62: =((((((L56+L55)+L58)+L61)-L57)-L59)-L60) | M62: =((((((M56+M55)+M58)+M61)-M57)-M59)-M60) | N62: =((((((N56+N55)+N58)+N61)-N57)-N59)-N60) | O62: =((((((O56+O55)+O58)+O61)-O57)-O59)-O60) | ... Q62: =((((((Q56+Q55)+Q58)+Q61)-Q57)-Q59)-Q60)
A63: Net debt (cash) | B63: net_debt | D63: -265.721 | E63: -346.953 | F63: 276.53 | G63: 2674.434 | H63: =(H57-H56) | I63: =(I57-I56) | J63: =(J57-J56) | K63: =(K57-K56) | L63: =(L57-L56) | M63: =(M57-M56) | N63: =(N57-N56) | O63: =(O57-O56) | ... Q63: =(Q57-Q56)
A64: Book value per share | B64: bvps | D64: 0.032428897 | E64: 0.03166204 | F64: 0.030494947 | G64: 0.043115348 | H64: =(IF(H45=0,0,H59/H45)*$C$7) | I64: =(IF(I45=0,0,I59/I45)*$C$7) | J64: =(IF(J45=0,0,J59/J45)*$C$7) | K64: =(IF(K45=0,0,K59/K45)*$C$7) | L64: =(IF(L45=0,0,L59/L45)*$C$7) | M64: =(IF(M45=0,0,M59/M45)*$C$7) | N64: =(IF(N45=0,0,N59/N45)*$C$7) | O64: =(IF(O45=0,0,O59/O45)*$C$7) | ... Q64: =(IF(Q45=0,0,Q59/Q45)*$C$7)
A65: Revenue growth | B65: revenue_growth | E65: -0.094212802 | F65: -0.17341657 | G65: 2.9207691 | H65: =(IF(G30=0,0,H30/G30)-1) | I65: =(IF(H30=0,0,I30/H30)-1) | J65: =(IF(I30=0,0,J30/I30)-1) | K65: =(IF(J30=0,0,K30/J30)-1) | L65: =(IF(K30=0,0,L30/K30)-1) | M65: =(IF(L30=0,0,M30/L30)-1) | N65: =(IF(M30=0,0,N30/M30)-1) | O65: =(IF(N30=0,0,O30/N30)-1) | ... Q65: =(IF(P30=0,0,Q30/P30)-1)
A66: Gross margin | B66: gross_margin | D66: -0.0045936599 | E66: 0.037885452 | F66: 0.088029668 | G66: -0.0060672857 | H66: =IF(H30=0,0,H32/H30) | I66: =IF(I30=0,0,I32/I30) | J66: =IF(J30=0,0,J32/J30) | K66: =IF(K30=0,0,K32/K30) | L66: =IF(L30=0,0,L32/L30) | M66: =IF(M30=0,0,M32/M30) | N66: =IF(N30=0,0,N32/N30) | O66: =IF(O30=0,0,O32/O30) | ... Q66: =IF(Q30=0,0,Q32/Q30)
A67: EBITDA margin | B67: ebitda_margin | D67: -0.047805263 | E67: -0.01156842 | F67: 0.032623039 | G67: -0.055603429 | H67: =IF(H30=0,0,H36/H30) | I67: =IF(I30=0,0,I36/I30) | J67: =IF(J30=0,0,J36/J30) | K67: =IF(K30=0,0,K36/K30) | L67: =IF(L30=0,0,L36/L30) | M67: =IF(M30=0,0,M36/M30) | N67: =IF(N30=0,0,N36/N30) | O67: =IF(O30=0,0,O36/O30) | ... Q67: =IF(Q30=0,0,Q36/Q30)
A68: EBIT margin | B68: ebit_margin | D68: -0.048737918 | E68: -0.012905499 | F68: -0.031776153 | G68: -0.084671143 | H68: =IF(H30=0,0,H34/H30) | I68: =IF(I30=0,0,I34/I30) | J68: =IF(J30=0,0,J34/J30) | K68: =IF(K30=0,0,K34/K30) | L68: =IF(L30=0,0,L34/L30) | M68: =IF(M30=0,0,M34/M30) | N68: =IF(N30=0,0,N34/N30) | O68: =IF(O30=0,0,O34/O30) | ... Q68: =IF(Q30=0,0,Q34/Q30)
A69: Net margin | B69: np_margin | D69: -0.062710125 | E69: -0.015544934 | F69: -0.038429138 | G69: 0.15572729 | H69: =IF(H30=0,0,H44/H30) | I69: =IF(I30=0,0,I44/I30) | J69: =IF(J30=0,0,J44/J30) | K69: =IF(K30=0,0,K44/K30) | L69: =IF(L30=0,0,L44/L30) | M69: =IF(M30=0,0,M44/M30) | N69: =IF(N30=0,0,N44/N30) | O69: =IF(O30=0,0,O44/O30) | ... Q69: =IF(Q30=0,0,Q44/Q30)
A70: EPS growth | B70: eps_growth | E70: -0.77546844 | F70: 1.0434239 | G70: -16.889626 | H70: =(IF(G46=0,0,H46/G46)-1) | I70: =(IF(H46=0,0,I46/H46)-1) | J70: =(IF(I46=0,0,J46/I46)-1) | K70: =(IF(J46=0,0,K46/J46)-1) | L70: =(IF(K46=0,0,L46/K46)-1) | M70: =(IF(L46=0,0,M46/L46)-1) | N70: =(IF(M46=0,0,N46/M46)-1) | O70: =(IF(N46=0,0,O46/N46)-1) | ... Q70: =(IF(P46=0,0,Q46/P46)-1)
A71: ROE | B71: roe | E71: -0.01211123 | F71: -0.025518397 | G71: 0.34237543 | H71: =IF(IF(2=0,0,(H59+G59)/2)=0,0,H44/IF(2=0,0,(H59+G59)/2)) | I71: =IF(IF(2=0,0,(I59+H59)/2)=0,0,I44/IF(2=0,0,(I59+H59)/2)) | J71: =IF(IF(2=0,0,(J59+I59)/2)=0,0,J44/IF(2=0,0,(J59+I59)/2)) | K71: =IF(IF(2=0,0,(K59+J59)/2)=0,0,K44/IF(2=0,0,(K59+J59)/2)) | L71: =IF(IF(2=0,0,(L59+K59)/2)=0,0,L44/IF(2=0,0,(L59+K59)/2)) | M71: =IF(IF(2=0,0,(M59+L59)/2)=0,0,M44/IF(2=0,0,(M59+L59)/2)) | N71: =IF(IF(2=0,0,(N59+M59)/2)=0,0,N44/IF(2=0,0,(N59+M59)/2)) | O71: =IF(IF(2=0,0,(O59+N59)/2)=0,0,O44/IF(2=0,0,(O59+N59)/2)) | ... Q71: =IF(IF(2=0,0,(Q59+P59)/2)=0,0,Q44/IF(2=0,0,(Q59+P59)/2))
A72: Net debt / EBITDA | B72: net_debt_ebitda | D72: 2.3309678 | E72: 13.88534 | F72: 4.7477852 | G72: -6.871195 | H72: =IF(H36=0,0,H63/H36) | I72: =IF(I36=0,0,I63/I36) | J72: =IF(J36=0,0,J63/J36) | K72: =IF(K36=0,0,K63/K36) | L72: =IF(L36=0,0,L63/L36) | M72: =IF(M36=0,0,M63/M36) | N72: =IF(N36=0,0,N63/N36) | O72: =IF(O36=0,0,O63/O36) | ... Q72: =IF(Q36=0,0,Q63/Q36)
A73: Payout ratio | B73: payout_ratio | D73: -0.1983548 | E73: -0.88538882 | F73: -0.73357701 | G73: 0.02705175 | H73: =IF(H46=0,0,H47/H46) | I73: =IF(I46=0,0,I47/I46) | J73: =IF(J46=0,0,J47/J46) | K73: =IF(K46=0,0,K47/K46) | L73: =IF(L46=0,0,L47/L46) | M73: =IF(M46=0,0,M47/M46) | N73: =IF(N46=0,0,N47/N46) | O73: =IF(O46=0,0,O47/O46) | ... Q73: =IF(Q46=0,0,Q47/Q46)
A74: Capex / revenue | B74: capex_revenue | D74: 0.047913458 | E74: 0.044587052 | F74: 0.2268753 | G74: 0.10520229 | H74: =IF(H30=0,0,H49/H30) | I74: =IF(I30=0,0,I49/I30) | J74: =IF(J30=0,0,J49/J30) | K74: =IF(K30=0,0,K49/K30) | L74: =IF(L30=0,0,L49/L30) | M74: =IF(M30=0,0,M49/M30) | N74: =IF(N30=0,0,N49/N30) | O74: =IF(O30=0,0,O49/O30) | ... Q74: =IF(Q30=0,0,Q49/Q30)
A76: VALUATION
A77: Last price (IDR) | C77: 1500
A78: Shares outstanding (m) | C78: 86464.496
A79: IDR per USD (spot) | C79: 18100
A80: Debt at balance-sheet date | C80: 5910.937
A81: Cash at balance-sheet date | C81: 2921.331
A82: Minority interest (book) | C82: 1003.746
A83: Associates & investments (book) | C83: 174.831
A84: Post-balance-sheet & other items (sourced, probability-weighted) | C84: 935.5
A85: Parent equity at balance-sheet date | C85: 3960.569
A86: Per-share factor | C86: 1
A87: Risk-free rate | C87: =Drivers!$C$9
A88: Less: default spread (IDR only) | C88: 0
A89: Mature ERP + Indonesia CRP | C89: =Drivers!$C$11+Drivers!$C$12
A90: Tax rate | C90: =Drivers!$C$14
A91: Unlevered beta (industry default (config)) | C91: 0.9
A92: Debt / equity (market) | C92: 0.8249086
A93: Levered beta | C93: =$C$91*(1+(1-$C$90)*$C$92)
A94: Explicit company premium | C94: 0
A95: Cost of equity | C95: =$C$87-$C$88+$C$93*$C$89+$C$94
A96: Pre-tax cost of debt | C96: =$C$87+Drivers!$C$13
A97: WACC | C97: =1/(1+$C$92)*$C$95+$C$92/(1+$C$92)*$C$96*(1-$C$90)
A98: Terminal growth (capped) | C98: 0.025
A100: DCF (FCFF, terminal value)
A101: Share of year after balance-sheet date | H101: 0.503765 | I101: 0.996578 | J101: 0.999316 | K101: 0.996578 | L101: 0.996578 | M101: 0.996578 | N101: 0.999316 | O101: 0.996578 | P101: 0.996578 | Q101: 0.996578
A102: Discount time from valuation date (years) | H102: 0 | I102: 0.673511 | J102: 1.672827 | K102: 2.67488 | L102: 3.674196 | M102: 4.673511 | N102: 5.672827 | O102: 6.67488 | P102: 7.674196 | Q102: 8.673511
A103: Discount factor | H103: =1/(1+$C$97)^H102 | I103: =1/(1+$C$97)^I102 | J103: =1/(1+$C$97)^J102 | K103: =1/(1+$C$97)^K102 | L103: =1/(1+$C$97)^L102 | M103: =1/(1+$C$97)^M102 | N103: =1/(1+$C$97)^N102 | O103: =1/(1+$C$97)^O102 | ... Q103: =1/(1+$C$97)^Q102
A104: PV of FCFF | H104: =H51*H101*H103 | I104: =I51*I101*I103 | J104: =J51*J101*J103 | K104: =K51*K101*K103 | L104: =L51*L101*L103 | M104: =M51*M101*M103 | N104: =N51*N101*N103 | O104: =O51*O101*O103 | ... Q104: =Q51*Q101*Q103
A105: Sum of PV | C105: =SUM(H104:Q104)
A106: Years to end of horizon | C106: 9.1718
...
