Workbook

Sheet README
A1: Six South — Coal distribution, trading & logistics industry model
A2: Generated 2026-10-30T07:57:06+07:00 by the coverage engine. The engine (scripts/cov_engine.py) is the source of truth; this workbook is a live rendering of it.
A3: Colour key: blue = input or hard-coded history; black = formula; green = link to another sheet.
A4: Drivers: every deck variable these models read. Change one and every ticker tab and the Comps sheet recalculate (forecasts, cash flows, DCF value, base-case value, target, rating).
A5: Scenario (bear/bull) and sensitivity tables need full model re-runs and are engine values.
A6: Paper fund — research for education and process transparency, not investment advice.
A8: Tickers:
A9: ALII.JK — PT Ancara Logistics Indonesia Tbk
A10: BBRM.JK — PT Pelayaran Nasional Bina Buana Raya Tbk
A11: BESS.JK — PT Batulicin Nusantara Maritim Tbk
A12: DWGL.JK — PT Dwi Guna Laksana Tbk
A13: FIRE.JK — PT Alfa Energi Investama Tbk
A14: SGER.JK — PT Sumber Global Energy Tbk

Sheet Drivers
A1: Driver decks (state/drivers) — edit a blue cell to flow it through every ticker tab
A3: Variable | B3: Key | C3: Unit / status | D3: FY2022A | E3: FY2023A | F3: FY2024A | G3: FY2025A | H3: FY2026E | I3: FY2027E | J3: FY2028E | K3: FY2029E | L3: FY2030E | M3: FY2031E | N3: FY2032E | O3: FY2033E | P3: FY2034E | Q3: FY2035E
A4: Newcastle 6,000 kcal/kg NAR thermal coal | B4: d.coal.newc | C4: USD/t · reviewed | F4: 136.1 | G4: 108.4 | H4: 137 | I4: 118 | J4: 110 | K4: 105 | L4: 107.1 | M4: 109.242 | N4: 111.42684 | O4: 113.65538 | P4: 115.92848 | Q4: 118.24705
A5: IDR per USD | B5: m.usd_idr | C5: IDR/USD · reviewed | D5: 14843.177 | E5: 15228.8 | F5: 15846.238 | G5: 16448.093 | H5: 17570 | I5: 18350 | J5: 18600 | K5: 18850 | L5: 19093.137 | M5: 19186.731 | N5: 19280.784 | O5: 19375.297 | P5: 19470.274 | Q5: 19565.717
A6: Brent crude | B6: d.oil.brent | C6: USD/bbl · reviewed | D6: 98.9663 | E6: 82.1904 | F6: 79.8213 | G6: 68.1015 | H6: 96 | I6: 84 | J6: 80 | K6: 78 | L6: 76.5 | M6: 78.03 | N6: 79.5906 | O6: 81.182412 | P6: 82.80606 | Q6: 84.462181
A8: Cost-of-capital scalars (macro deck)
A9: 10-year Indonesian government bond yield (IDR) | B9: m.rf_idr | C9: 0.0745 | D9: investor.id — "Yield SUN 7,45%, Saatnya Borong atau Tunggu Lebih Tinggi?" (25 Okt 2026 20:58 WIB; deck source S3); corroborated by kalderanews S1 (10Y SUN 7.41%
A10: 10-year US Treasury yield | B10: m.rf_usd | C10: 0.04989 | D10: Yahoo Finance ^TNX (US 10-year Treasury yield)
A11: Indonesia sovereign default spread (Damodaran) | B11: m.default_spread_id | C11: 0.0162 | D11: Damodaran country risk premiums (https://pages.stern.nyu.edu/~adamodar/New_Home_Page/datafile/ctryprem.html), page dated January 5, 2026, read 2026-10-30
A12: Mature-market equity risk premium (Damodaran) | B12: m.erp_mature | C12: 0.0423 | D12: Damodaran country risk premiums (https://pages.stern.nyu.edu/~adamodar/New_Home_Page/datafile/ctryprem.html), page dated January 5, 2026, read 2026-10-30
A13: Indonesia country risk premium (Damodaran) | B13: m.crp_id | C13: 0.0246 | D13: Damodaran country risk premiums (https://pages.stern.nyu.edu/~adamodar/New_Home_Page/datafile/ctryprem.html), page dated January 5, 2026, read 2026-10-30
A14: House pre-tax corporate debt spread over the risk-free | B14: m.debt_spread_corp | C14: 0.02 | D14: SEED house assumption pending the macro desk: 200 bp over the risk-free rate for an average IDX corporate borrower
A15: Indonesia statutory corporate income tax rate | B15: m.tax_rate_id | C15: 0.22 | D15: Law 7/2021 on Harmonisation of Tax Regulations (UU HPP): 22% corporate income tax from fiscal 2022

Sheet Comps
A1: Ticker | B1: Company | C1: Rating | D1: Target (IDR) | E1: Price (IDR) | F1: Exp. 12m TR | G1: Value today | H1: P/E FY+0 | I1: EV/EBITDA FY+0 | J1: Div. yield FY+0
A2: ALII.JK | B2: PT Ancara Logistics Indonesia Tbk | C2: ='ALII'!$C$151 | D2: ='ALII'!$C$149 | E2: ='ALII'!$C$80 | F2: ='ALII'!$C$150 | G2: ='ALII'!$C$130 | H2: 30.913676 | I2: 28.567517 | J2: 0.017791
A3: BBRM.JK | B3: PT Pelayaran Nasional Bina Buana Raya Tbk | C3: ='BBRM'!$C$141 | D3: ='BBRM'!$C$139 | E3: ='BBRM'!$C$79 | F3: ='BBRM'!$C$140 | G3: ='BBRM'!$C$129 | H3: 8.560511 | I3: 4.591957 | J3: 0
A4: BESS.JK | B4: PT Batulicin Nusantara Maritim Tbk | C4: ='BESS'!$C$136 | D4: ='BESS'!$C$134 | E4: ='BESS'!$C$80 | F4: ='BESS'!$C$135 | G4: ='BESS'!$C$124 | I4: 84.551403 | J4: 0
A5: DWGL.JK | B5: PT Dwi Guna Laksana Tbk | C5: ='DWGL'!$C$142 | D5: ='DWGL'!$C$140 | E5: ='DWGL'!$C$80 | F5: ='DWGL'!$C$141 | G5: ='DWGL'!$C$130 | H5: 8.431587 | I5: 4.622804 | J5: 0
A6: FIRE.JK | B6: PT Alfa Energi Investama Tbk | C6: ='FIRE'!$C$152 | D6: ='FIRE'!$C$150 | E6: ='FIRE'!$C$83 | F6: ='FIRE'!$C$151 | G6: ='FIRE'!$C$140 | H6: 10.959457 | I6: 3.947332 | J6: 0
A7: SGER.JK | B7: PT Sumber Global Energy Tbk | C7: ='SGER'!$C$135 | D7: ='SGER'!$C$133 | E7: ='SGER'!$C$79 | F7: ='SGER'!$C$134 | G7: ='SGER'!$C$123 | H7: 64.637656 | I7: 31.814343 | J7: 0.002321

Sheet ALII
A1: PT Ancara Logistics Indonesia Tbk (ALII.JK) — Coal distribution, trading & logistics
A2: Units: IDR bn; per-share in IDR unless marked IDR. Model asof 2026-10-30 · data 2026-10-28
A4: Line | C4: Scalar | D4: FY2022A | E4: FY2023A | F4: FY2024A | G4: FY2025A | H4: FY2026E | I4: FY2027E | J4: FY2028E | K4: FY2029E | L4: FY2030E | M4: FY2031E | N4: FY2032E | O4: FY2033E | P4: FY2034E | Q4: FY2035E
A6: PARAMETERS
A7: horizon | C7: 10
A8: ps_factor | C8: 1000
A9: vp_factor | C9: 1
A11: INPUTS (company assumptions)
A12: Revenue growth | B12: a.revenue_growth | H12: -0.151 | I12: 0.08 | J12: 0.08 | K12: 0.06 | L12: 0.05 | M12: 0.04 | N12: 0.04 | O12: 0.04 | P12: 0.04 | Q12: 0.04
A13: Gross margin at base input costs | B13: a.gross_margin | H13: 0.452 | I13: 0.45 | J13: 0.45 | K13: 0.45 | L13: 0.45 | M13: 0.45 | N13: 0.45 | O13: 0.45 | P13: 0.45 | Q13: 0.45
A14: Cost link 1: share of COGS exposed | B14: a.link1_share | C14: 0
A15: Cost link 1: pass-through to prices | B15: a.link1_pass | C15: 0
A16: Cost link 2: share of COGS exposed | B16: a.link2_share | C16: 0.228
A17: Cost link 2: pass-through to prices | B17: a.link2_pass | C17: 1
A18: SG&A / revenue | B18: a.opex_pct | H18: 0.095 | I18: 0.09 | J18: 0.086 | K18: 0.085 | L18: 0.085 | M18: 0.085 | N18: 0.085 | O18: 0.085 | P18: 0.085 | Q18: 0.085
A19: D&A / revenue | B19: a.da_pct | H19: 0.07 | I19: 0.07 | J19: 0.069 | K19: 0.068 | L19: 0.067 | M19: 0.065 | N19: 0.065 | O19: 0.065 | P19: 0.065 | Q19: 0.065
A20: Capex / revenue | B20: a.capex_pct | H20: 0.14 | I20: 0.12 | J20: 0.1 | K20: 0.09 | L20: 0.09 | M20: 0.08 | N20: 0.08 | O20: 0.08 | P20: 0.08 | Q20: 0.08
A21: Operating working capital / revenue | B21: a.nwc_pct | H21: 0.38 | I21: 0.38 | J21: 0.38 | K21: 0.38 | L21: 0.38 | M21: 0.38 | N21: 0.38 | O21: 0.38 | P21: 0.38 | Q21: 0.38
A22: Effective tax rate | B22: a.tax_rate | H22: 0.182 | I22: 0.182 | J22: 0.182 | K22: 0.182 | L22: 0.182 | M22: 0.182 | N22: 0.182 | O22: 0.182 | P22: 0.182 | Q22: 0.182
A23: Cost of debt (on opening debt) | B23: a.cost_of_debt | C23: 0.075
A24: Yield on opening cash | B24: a.cash_yield | C24: 0.035
A25: Net new borrowing | B25: a.net_borrowing | H25: 30 | I25: 20 | J25: 10 | K25: 0 | L25: 0 | M25: 0 | N25: 0 | O25: 0 | P25: 0 | Q25: 0
A26: Other non-operating items | B26: a.other_nonop | H26: 160 | I26: 150 | J26: 140 | K26: 130 | L26: 120 | M26: 112.75 | N26: 115.56875 | O26: 118.45797 | P26: 121.41942 | Q26: 124.4549
A27: Minorities' share of net profit | B27: a.minority_pct | H27: 0.11 | I27: 0.11 | J27: 0.11 | K27: 0.11 | L27: 0.11 | M27: 0.11 | N27: 0.11 | O27: 0.11 | P27: 0.11 | Q27: 0.11
A28: Dividend payout | B28: a.payout | H28: 0.55 | I28: 0.55 | J28: 0.55 | K28: 0.55 | L28: 0.55 | M28: 0.55 | N28: 0.55 | O28: 0.55 | P28: 0.55 | Q28: 0.55
A29: Change in share count | B29: a.share_change | H29: 0 | I29: 0 | J29: 0 | K29: 0 | L29: 0 | M29: 0 | N29: 0 | O29: 0 | P29: 0 | Q29: 0
A30: Terminal growth (DCF) | B30: a.terminal_growth | C30: 0.035
A32: MODEL
A33: Revenue | B33: revenue | D33: 670.12038 | E33: 931.0058 | F33: 920.55202 | G33: 970.22898 | H33: =(G33*(1+H12)) | I33: =(H33*(1+I12)) | J33: =(I33*(1+J12)) | K33: =(J33*(1+K12)) | L33: =(K33*(1+L12)) | M33: =(L33*(1+M12)) | N33: =(M33*(1+N12)) | O33: =(N33*(1+O12)) | ... Q33: =(P33*(1+Q12))
A34: Cost of revenue | B34: cogs | D34: 368.90399 | E34: 554.12857 | F34: 519.62428 | G34: 529.83922 | H34: =((H33*(1-H13))*((1+(($C$14*(1-$C$15))*(IF(Drivers!$G$4=0,0,Drivers!$H$4/Drivers!$G$4)-1)))+(($C$16*(1-$C$17))*(IF(Drivers!$G$6=0,0,Drivers!$H$6/Drivers!$G$6)-1)))) | I34: =((I33*(1-I13))*((1+(($C$14*(1-$C$15))*(IF(Drivers!$G$4=0,0,Drivers!$I$4/Drivers!$G$4)-1)))+(($C$16*(1-$C$17))*(IF(Drivers!$G$6=0,0,Drivers!$I$6/Drivers!$G$6)-1)))) | J34: =((J33*(1-J13))*((1+(($C$14*(1-$C$15))*(IF(Drivers!$G$4=0,0,Drivers!$J$4/Drivers!$G$4)-1)))+(($C$16*(1-$C$17))*(IF(Drivers!$G$6=0,0,Drivers!$J$6/Drivers!$G$6)-1)))) | K34: =((K33*(1-K13))*((1+(($C$14*(1-$C$15))*(IF(Drivers!$G$4=0,0,Drivers!$K$4/Drivers!$G$4)-1)))+(($C$16*(1-$C$17))*(IF(Drivers!$G$6=0,0,Drivers!$K$6/Drivers!$G$6)-1)))) | L34: =((L33*(1-L13))*((1+(($C$14*(1-$C$15))*(IF(Drivers!$G$4=0,0,Drivers!$L$4/Drivers!$G$4)-1)))+(($C$16*(1-$C$17))*(IF(Drivers!$G$6=0,0,Drivers!$L$6/Drivers!$G$6)-1)))) | M34: =((M33*(1-M13))*((1+(($C$14*(1-$C$15))*(IF(Drivers!$G$4=0,0,Drivers!$M$4/Drivers!$G$4)-1)))+(($C$16*(1-$C$17))*(IF(Drivers!$G$6=0,0,Drivers!$M$6/Drivers!$G$6)-1)))) | N34: =((N33*(1-N13))*((1+(($C$14*(1-$C$15))*(IF(Drivers!$G$4=0,0,Drivers!$N$4/Drivers!$G$4)-1)))+(($C$16*(1-$C$17))*(IF(Drivers!$G$6=0,0,Drivers!$N$6/Drivers!$G$6)-1)))) | O34: =((O33*(1-O13))*((1+(($C$14*(1-$C$15))*(IF(Drivers!$G$4=0,0,Drivers!$O$4/Drivers!$G$4)-1)))+(($C$16*(1-$C$17))*(IF(Drivers!$G$6=0,0,Drivers!$O$6/Drivers!$G$6)-1)))) | P34: =((P33*(1-P13))*((1+(($C$14*(1-$C$15))*(IF(Drivers!$G$4=0,0,Drivers!$P$4/Drivers!$G$4)-1)))+(($C$16*(1-$C$17))*(IF(Drivers!$G$6=0,0,Drivers!$P$6/Drivers!$G$6)-1)))) | Q34: =((Q33*(1-Q13))*((1+(($C$14*(1-$C$15))*(IF(Drivers!$G$4=0,0,Drivers!$Q$4/Drivers!$G$4)-1)))+(($C$16*(1-$C$17))*(IF(Drivers!$G$6=0,0,Drivers!$Q$6/Drivers!$G$6)-1))))
A35: Gross profit | B35: gross_profit | D35: 301.21639 | E35: 376.87723 | F35: 400.92774 | G35: 440.38975 | H35: =(H33-H34) | I35: =(I33-I34) | J35: =(J33-J34) | K35: =(K33-K34) | L35: =(L33-L34) | M35: =(M33-M34) | N35: =(N33-N34) | O35: =(O33-O34) | ... Q35: =(Q33-Q34)
A36: SG&A and other opex | B36: opex | D36: 67.885024 | E36: 110.80738 | F36: 78.856851 | G36: 80.823571 | H36: =(H33*H18) | I36: =(I33*I18) | J36: =(J33*J18) | K36: =(K33*K18) | L36: =(L33*L18) | M36: =(M33*M18) | N36: =(N33*N18) | O36: =(O33*O18) | ... Q36: =(Q33*Q18)
A37: EBIT | B37: ebit | D37: 233.33137 | E37: 266.06985 | F37: 322.07089 | G37: 359.56618 | H37: =(H35-H36) | I37: =(I35-I36) | J37: =(J35-J36) | K37: =(K35-K36) | L37: =(L35-L36) | M37: =(M35-M36) | N37: =(N35-N36) | O37: =(O35-O36) | ... Q37: =(Q35-Q36)
A38: Depreciation & amortisation | B38: da | F38: 59.761053 | G38: 65.913717 | H38: =(H33*H19) | I38: =(I33*I19) | J38: =(J33*J19) | K38: =(K33*K19) | L38: =(L33*L19) | M38: =(M33*M19) | N38: =(N33*N19) | O38: =(O33*O19) | ... Q38: =(Q33*Q19)
A39: EBITDA | B39: ebitda | F39: 381.83194 | G39: 425.4799 | H39: =(H37+H38) | I39: =(I37+I38) | J39: =(J37+J38) | K39: =(K37+K38) | L39: =(L37+L38) | M39: =(M37+M38) | N39: =(N37+N38) | O39: =(O37+O38) | ... Q39: =(Q37+Q38)
A40: Interest expense | B40: interest_expense | D40: 178.49163 | E40: 193.49873 | F40: 96.39615 | G40: 34.479603 | H40: =(G60*$C$23) | I40: =(H60*$C$23) | J40: =(I60*$C$23) | K40: =(J60*$C$23) | L40: =(K60*$C$23) | M40: =(L60*$C$23) | N40: =(M60*$C$23) | O40: =(N60*$C$23) | ... Q40: =(P60*$C$23)
A41: Interest income | B41: interest_income | D41: 136.30771 | E41: 124.03175 | F41: 4.20412 | G41: 1.792778 | H41: =(G59*$C$24) | I41: =(H59*$C$24) | J41: =(I59*$C$24) | K41: =(J59*$C$24) | L41: =(K59*$C$24) | M41: =(L59*$C$24) | N41: =(M59*$C$24) | O41: =(N59*$C$24) | ... Q41: =(P59*$C$24)
A42: Other non-operating | B42: other_nonop | D42: -43.94857 | E42: -2.404654 | F42: 108.45776 | G42: 170.06969 | H42: =H26 | I42: =I26 | J42: =J26 | K42: =K26 | L42: =L26 | M42: =M26 | N42: =N26 | O42: =O26 | ... Q42: =Q26
A43: Profit before tax | B43: pbt | D43: 147.19887 | E43: 194.19821 | F43: 338.33661 | G43: 496.94905 | H43: =(((H37-H40)+H41)+H42) | I43: =(((I37-I40)+I41)+I42) | J43: =(((J37-J40)+J41)+J42) | K43: =(((K37-K40)+K41)+K42) | L43: =(((L37-L40)+L41)+L42) | M43: =(((M37-M40)+M41)+M42) | N43: =(((N37-N40)+N41)+N42) | O43: =(((O37-O40)+O41)+O42) | ... Q43: =(((Q37-Q40)+Q41)+Q42)
A44: Tax | B44: tax | D44: -4.617118 | E44: 11.287891 | F44: 38.736482 | G44: 74.073666 | H44: =(MAX(H43,0)*H22) | I44: =(MAX(I43,0)*I22) | J44: =(MAX(J43,0)*J22) | K44: =(MAX(K43,0)*K22) | L44: =(MAX(L43,0)*L22) | M44: =(MAX(M43,0)*M22) | N44: =(MAX(N43,0)*N22) | O44: =(MAX(O43,0)*O22) | ... Q44: =(MAX(Q43,0)*Q22)
A45: Net profit (incl. minorities) | B45: np | D45: 151.81599 | E45: 182.91032 | F45: 299.60013 | G45: 422.87538 | H45: =(H43-H44) | I45: =(I43-I44) | J45: =(J43-J44) | K45: =(K43-K44) | L45: =(L43-L44) | M45: =(M43-M44) | N45: =(N43-N44) | O45: =(O43-O44) | ... Q45: =(Q43-Q44)
A46: Minority interests | B46: minority | D46: -11.763217 | E46: -3.857393 | F46: 10.35189 | G46: 48.589578 | H46: =(H45*H27) | I46: =(I45*I27) | J46: =(J45*J27) | K46: =(K45*K27) | L46: =(L45*L27) | M46: =(M45*M27) | N46: =(N45*N27) | O46: =(O45*O27) | ... Q46: =(Q45*Q27)
A47: Net profit to parent | B47: np_parent | D47: 163.57921 | E47: 186.76771 | F47: 289.24824 | G47: 374.2858 | H47: =(H45-H46) | I47: =(I45-I46) | J47: =(J45-J46) | K47: =(K45-K46) | L47: =(L45-L46) | M47: =(M45-M46) | N47: =(N45-N46) | O47: =(O45-O46) | ... Q47: =(Q45-Q46)
A48: Shares outstanding (m) | B48: shares | D48: 15825.8 | E48: 15825.8 | F48: 15825.8 | G48: 15825.8 | H48: =(G48*(1+H29)) | I48: =(H48*(1+I29)) | J48: =(I48*(1+J29)) | K48: =(J48*(1+K29)) | L48: =(K48*(1+L29)) | M48: =(L48*(1+M29)) | N48: =(M48*(1+N29)) | O48: =(N48*(1+O29)) | ... Q48: =(P48*(1+Q29))
A49: EPS | B49: eps | D49: 10.336236 | E49: 11.80147 | F49: 18.277006 | G49: 23.650356 | H49: =(IF(H48=0,0,H47/H48)*$C$8) | I49: =(IF(I48=0,0,I47/I48)*$C$8) | J49: =(IF(J48=0,0,J47/J48)*$C$8) | K49: =(IF(K48=0,0,K47/K48)*$C$8) | L49: =(IF(L48=0,0,L47/L48)*$C$8) | M49: =(IF(M48=0,0,M47/M48)*$C$8) | N49: =(IF(N48=0,0,N47/N48)*$C$8) | O49: =(IF(O48=0,0,O47/O48)*$C$8) | ... Q49: =(IF(Q48=0,0,Q47/Q48)*$C$8)
A50: DPS (declared on the year) | B50: dps | F50: 4.5 | G50: 13 | H50: =(MAX(H49,0)*H28) | I50: =(MAX(I49,0)*I28) | J50: =(MAX(J49,0)*J28) | K50: =(MAX(K49,0)*K28) | L50: =(MAX(L49,0)*L28) | M50: =(MAX(M49,0)*M28) | N50: =(MAX(N49,0)*N28) | O50: =(MAX(O49,0)*O28) | ... Q50: =(MAX(Q49,0)*Q28)
A51: Dividends paid | B51: dividends_paid | G51: 71.2161 | H51: =IF($C$8=0,0,(G50*G48)/$C$8) | I51: =IF($C$8=0,0,(H50*H48)/$C$8) | J51: =IF($C$8=0,0,(I50*I48)/$C$8) | K51: =IF($C$8=0,0,(J50*J48)/$C$8) | L51: =IF($C$8=0,0,(K50*K48)/$C$8) | M51: =IF($C$8=0,0,(L50*L48)/$C$8) | N51: =IF($C$8=0,0,(M50*M48)/$C$8) | O51: =IF($C$8=0,0,(N50*N48)/$C$8) | ... Q51: =IF($C$8=0,0,(P50*P48)/$C$8)
A52: Capital expenditure | B52: capex | D52: 62.997376 | E52: 256.04711 | F52: 141.11697 | G52: 105.09649 | H52: =(H33*H20) | I52: =(I33*I20) | J52: =(J33*J20) | K52: =(K33*K20) | L52: =(L33*L20) | M52: =(M33*M20) | N52: =(N33*N20) | O52: =(O33*O20) | ... Q52: =(Q33*Q20)
A53: Change in working capital | B53: delta_nwc | E53: -43.361763 | F53: 189.72098 | G53: 111.76679 | H53: =(H58-G58) | I53: =(I58-H58) | J53: =(J58-I58) | K53: =(K58-J58) | L53: =(L58-K58) | M53: =(M58-L58) | N53: =(N58-M58) | O53: =(O58-N58) | ... Q53: =(Q58-P58)
A54: Free cash flow to firm | B54: fcff | F54: 14.119789 | G54: 155.02081 | H54: =((((H37*(1-H22))+H38)-H52)-H53) | I54: =((((I37*(1-I22))+I38)-I52)-I53) | J54: =((((J37*(1-J22))+J38)-J52)-J53) | K54: =((((K37*(1-K22))+K38)-K52)-K53) | L54: =((((L37*(1-L22))+L38)-L52)-L53) | M54: =((((M37*(1-M22))+M38)-M52)-M53) | N54: =((((N37*(1-N22))+N38)-N52)-N53) | O54: =((((O37*(1-O22))+O38)-O52)-O53) | ... Q54: =((((Q37*(1-Q22))+Q38)-Q52)-Q53)
A55: Net borrowing | B55: net_borrowing | E55: 103.38061 | F55: -623.05015 | G55: -157.6617 | H55: =H25 | I55: =I25 | J55: =J25 | K55: =K25 | L55: =L25 | M55: =M25 | N55: =N25 | O55: =O25 | ... Q55: =Q25
A56: Dividends to minorities | B56: minority_div | H56: =(MAX(G46,0)*H28) | I56: =(MAX(H46,0)*I28) | J56: =(MAX(I46,0)*J28) | K56: =(MAX(J46,0)*K28) | L56: =(MAX(K46,0)*L28) | M56: =(MAX(L46,0)*M28) | N56: =(MAX(M46,0)*N28) | O56: =(MAX(N46,0)*O28) | ... Q56: =(MAX(P46,0)*Q28)
A57: Free cash flow to equity | B57: fcfe | H57: =(((((H45+H38)-H52)-H53)+H55)-H56) | I57: =(((((I45+I38)-I52)-I53)+I55)-I56) | J57: =(((((J45+J38)-J52)-J53)+J55)-J56) | K57: =(((((K45+K38)-K52)-K53)+K55)-K56) | L57: =(((((L45+L38)-L52)-L53)+L55)-L56) | M57: =(((((M45+M38)-M52)-M53)+M55)-M56) | N57: =(((((N45+N38)-N52)-N53)+N55)-N56) | O57: =(((((O45+O38)-O52)-O53)+O55)-O56) | ... Q57: =(((((Q45+Q38)-Q52)-Q53)+Q55)-Q56)
A58: Operating working capital | B58: nwc | D58: 113.37759 | E58: 70.015828 | F58: 259.73681 | G58: 371.5036 | H58: =(H33*H21) | I58: =(I33*I21) | J58: =(J33*J21) | K58: =(K33*K21) | L58: =(L33*L21) | M58: =(M33*M21) | N58: =(N33*N21) | O58: =(O33*O21) | ... Q58: =(Q33*Q21)
A59: Cash & equivalents | B59: cash | D59: 36.428128 | E59: 1.232041 | F59: 67.025418 | G59: 8.512596 | H59: =(((((((G59+H45)+H38)-H52)-H53)+H55)-H51)-H56) | I59: =(((((((H59+I45)+I38)-I52)-I53)+I55)-I51)-I56) | J59: =(((((((I59+J45)+J38)-J52)-J53)+J55)-J51)-J56) | K59: =(((((((J59+K45)+K38)-K52)-K53)+K55)-K51)-K56) | L59: =(((((((K59+L45)+L38)-L52)-L53)+L55)-L51)-L56) | M59: =(((((((L59+M45)+M38)-M52)-M53)+M55)-M51)-M56) | N59: =(((((((M59+N45)+N38)-N52)-N53)+N55)-N51)-N56) | O59: =(((((((N59+O45)+O38)-O52)-O53)+O55)-O51)-O56) | ... Q59: =(((((((P59+Q45)+Q38)-Q52)-Q53)+Q55)-Q51)-Q56)
A60: Total debt | B60: debt | D60: 922.5409 | E60: 1025.9215 | F60: 402.87136 | G60: 245.20966 | H60: =(G60+H55) | I60: =(H60+I55) | J60: =(I60+J55) | K60: =(J60+K55) | L60: =(K60+L55) | M60: =(L60+M55) | N60: =(M60+N55) | O60: =(N60+O55) | ... Q60: =(P60+Q55)
A61: Fixed assets (net) | B61: ppe | D61: 411.23823 | E61: 806.59301 | F61: 965.40486 | G61: 957.04769 | H61: =((G61+H52)-H38) | I61: =((H61+I52)-I38) | J61: =((I61+J52)-J38) | K61: =((J61+K52)-K38) | L61: =((K61+L52)-L38) | M61: =((L61+M52)-M38) | N61: =((M61+N52)-N38) | O61: =((N61+O52)-O38) | ... Q61: =((P61+Q52)-Q38)
A62: Parent shareholders' equity | B62: equity | D62: 344.84815 | E62: 671.71973 | F62: 1809.9658 | G62: 2083.7061 | H62: =((G62+H47)-H51) | I62: =((H62+I47)-I51) | J62: =((I62+J47)-J51) | K62: =((J62+K47)-K51) | L62: =((K62+L47)-L51) | M62: =((L62+M47)-M51) | N62: =((M62+N47)-N51) | O62: =((N62+O47)-O51) | ... Q62: =((P62+Q47)-Q51)
A63: Minority interest (balance sheet) | B63: minority_bs | D63: 2.825947 | E63: -1.031446 | F63: 43.520444 | G63: 92.110022 | H63: =((G63+H46)-H56) | I63: =((H63+I46)-I56) | J63: =((I63+J46)-J56) | K63: =((J63+K46)-K56) | L63: =((K63+L46)-L56) | M63: =((L63+M46)-M56) | N63: =((M63+N46)-N56) | O63: =((N63+O46)-O56) | ... Q63: =((P63+Q46)-Q56)
A64: Other assets less other liabilities | B64: other_net | D64: 709.17105 | E64: 818.76891 | F64: 964.19056 | G64: 1083.9619 | H64: =G64 | I64: =H64 | J64: =I64 | K64: =J64 | L64: =K64 | M64: =L64 | N64: =M64 | O64: =N64 | ... Q64: =P64
A65: Balance check (should be zero) | B65: bs_check | H65: =((((((H59+H58)+H61)+H64)-H60)-H62)-H63) | I65: =((((((I59+I58)+I61)+I64)-I60)-I62)-I63) | J65: =((((((J59+J58)+J61)+J64)-J60)-J62)-J63) | K65: =((((((K59+K58)+K61)+K64)-K60)-K62)-K63) | L65: =((((((L59+L58)+L61)+L64)-L60)-L62)-L63) | M65: =((((((M59+M58)+M61)+M64)-M60)-M62)-M63) | N65: =((((((N59+N58)+N61)+N64)-N60)-N62)-N63) | O65: =((((((O59+O58)+O61)+O64)-O60)-O62)-O63) | ... Q65: =((((((Q59+Q58)+Q61)+Q64)-Q60)-Q62)-Q63)
A66: Net debt (cash) | B66: net_debt | D66: 886.11277 | E66: 1024.6895 | F66: 335.84594 | G66: 236.69707 | H66: =(H60-H59) | I66: =(I60-I59) | J66: =(J60-J59) | K66: =(K60-K59) | L66: =(L60-L59) | M66: =(M60-M59) | N66: =(N60-N59) | O66: =(O60-O59) | ... Q66: =(Q60-Q59)
A67: Book value per share | B67: bvps | D67: 21.790251 | E67: 42.444598 | F67: 114.36805 | G67: 131.66513 | H67: =(IF(H48=0,0,H62/H48)*$C$8) | I67: =(IF(I48=0,0,I62/I48)*$C$8) | J67: =(IF(J48=0,0,J62/J48)*$C$8) | K67: =(IF(K48=0,0,K62/K48)*$C$8) | L67: =(IF(L48=0,0,L62/L48)*$C$8) | M67: =(IF(M48=0,0,M62/M48)*$C$8) | N67: =(IF(N48=0,0,N62/N48)*$C$8) | O67: =(IF(O48=0,0,O62/O48)*$C$8) | ... Q67: =(IF(Q48=0,0,Q62/Q48)*$C$8)
A68: Revenue growth | B68: revenue_growth | E68: 0.38931127 | F68: -0.01122848 | G68: 0.053964309 | H68: =(IF(G33=0,0,H33/G33)-1) | I68: =(IF(H33=0,0,I33/H33)-1) | J68: =(IF(I33=0,0,J33/I33)-1) | K68: =(IF(J33=0,0,K33/J33)-1) | L68: =(IF(K33=0,0,L33/K33)-1) | M68: =(IF(L33=0,0,M33/L33)-1) | N68: =(IF(M33=0,0,N33/M33)-1) | O68: =(IF(N33=0,0,O33/N33)-1) | ... Q68: =(IF(P33=0,0,Q33/P33)-1)
A69: Gross margin | B69: gross_margin | D69: 0.44949594 | E69: 0.40480653 | F69: 0.43552969 | G69: 0.45390291 | H69: =IF(H33=0,0,H35/H33) | I69: =IF(I33=0,0,I35/I33) | J69: =IF(J33=0,0,J35/J33) | K69: =IF(K33=0,0,K35/K33) | L69: =IF(L33=0,0,L35/L33) | M69: =IF(M33=0,0,M35/M33) | N69: =IF(N33=0,0,N35/N33) | O69: =IF(O33=0,0,O35/O33) | ... Q69: =IF(Q33=0,0,Q35/Q33)
A70: EBITDA margin | B70: ebitda_margin | F70: 0.41478584 | G70: 0.43853555 | H70: =IF(H33=0,0,H39/H33) | I70: =IF(I33=0,0,I39/I33) | J70: =IF(J33=0,0,J39/J33) | K70: =IF(K33=0,0,K39/K33) | L70: =IF(L33=0,0,L39/L33) | M70: =IF(M33=0,0,M39/M33) | N70: =IF(N33=0,0,N39/N33) | O70: =IF(O33=0,0,O39/O33) | ... Q70: =IF(Q33=0,0,Q39/Q33)
A71: EBIT margin | B71: ebit_margin | D71: 0.34819321 | E71: 0.28578753 | F71: 0.34986713 | G71: 0.3705993 | H71: =IF(H33=0,0,H37/H33) | I71: =IF(I33=0,0,I37/I33) | J71: =IF(J33=0,0,J37/J33) | K71: =IF(K33=0,0,K37/K33) | L71: =IF(L33=0,0,L37/L33) | M71: =IF(M33=0,0,M37/M33) | N71: =IF(N33=0,0,N37/N33) | O71: =IF(O33=0,0,O37/O33) | ... Q71: =IF(Q33=0,0,Q37/Q33)
A72: Net margin | B72: np_margin | D72: 0.24410421 | E72: 0.20060853 | F72: 0.31421173 | G72: 0.38577059 | H72: =IF(H33=0,0,H47/H33) | I72: =IF(I33=0,0,I47/I33) | J72: =IF(J33=0,0,J47/J33) | K72: =IF(K33=0,0,K47/K33) | L72: =IF(L33=0,0,L47/L33) | M72: =IF(M33=0,0,M47/M33) | N72: =IF(N33=0,0,N47/N33) | O72: =IF(O33=0,0,O47/O33) | ... Q72: =IF(Q33=0,0,Q47/Q33)
A73: EPS growth | B73: eps_growth | E73: 0.14175705 | F73: 0.54870584 | G73: 0.29399508 | H73: =(IF(G49=0,0,H49/G49)-1) | I73: =(IF(H49=0,0,I49/H49)-1) | J73: =(IF(I49=0,0,J49/I49)-1) | K73: =(IF(J49=0,0,K49/J49)-1) | L73: =(IF(K49=0,0,L49/K49)-1) | M73: =(IF(L49=0,0,M49/L49)-1) | N73: =(IF(M49=0,0,N49/M49)-1) | O73: =(IF(N49=0,0,O49/N49)-1) | ... Q73: =(IF(P49=0,0,Q49/P49)-1)
A74: ROE | B74: roe | E74: 0.36744759 | F74: 0.23310628 | G74: 0.19225338 | H74: =IF(IF(2=0,0,(H62+G62)/2)=0,0,H47/IF(2=0,0,(H62+G62)/2)) | I74: =IF(IF(2=0,0,(I62+H62)/2)=0,0,I47/IF(2=0,0,(I62+H62)/2)) | J74: =IF(IF(2=0,0,(J62+I62)/2)=0,0,J47/IF(2=0,0,(J62+I62)/2)) | K74: =IF(IF(2=0,0,(K62+J62)/2)=0,0,K47/IF(2=0,0,(K62+J62)/2)) | L74: =IF(IF(2=0,0,(L62+K62)/2)=0,0,L47/IF(2=0,0,(L62+K62)/2)) | M74: =IF(IF(2=0,0,(M62+L62)/2)=0,0,M47/IF(2=0,0,(M62+L62)/2)) | N74: =IF(IF(2=0,0,(N62+M62)/2)=0,0,N47/IF(2=0,0,(N62+M62)/2)) | O74: =IF(IF(2=0,0,(O62+N62)/2)=0,0,O47/IF(2=0,0,(O62+N62)/2)) | ... Q74: =IF(IF(2=0,0,(Q62+P62)/2)=0,0,Q47/IF(2=0,0,(Q62+P62)/2))
A75: Net debt / EBITDA | B75: net_debt_ebitda | F75: 0.87956482 | G75: 0.55630611 | H75: =IF(H39=0,0,H66/H39) | I75: =IF(I39=0,0,I66/I39) | J75: =IF(J39=0,0,J66/J39) | K75: =IF(K39=0,0,K66/K39) | L75: =IF(L39=0,0,L66/L39) | M75: =IF(M39=0,0,M66/M39) | N75: =IF(N39=0,0,N66/N39) | O75: =IF(O39=0,0,O66/O39) | ... Q75: =IF(Q39=0,0,Q66/Q39)
A76: Payout ratio | B76: payout_ratio | F76: 0.246211 | G76: 0.5496746 | H76: =IF(H49=0,0,H50/H49) | I76: =IF(I49=0,0,I50/I49) | J76: =IF(J49=0,0,J50/J49) | K76: =IF(K49=0,0,K50/K49) | L76: =IF(L49=0,0,L50/L49) | M76: =IF(M49=0,0,M50/M49) | N76: =IF(N49=0,0,N50/N49) | O76: =IF(O49=0,0,O50/O49) | ... Q76: =IF(Q49=0,0,Q50/Q49)
A77: Capex / revenue | B77: capex_revenue | D77: 0.094009043 | E77: 0.27502203 | F77: 0.15329603 | G77: 0.10832133 | H77: =IF(H33=0,0,H52/H33) | I77: =IF(I33=0,0,I52/I33) | J77: =IF(J33=0,0,J52/J33) | K77: =IF(K33=0,0,K52/K33) | L77: =IF(L33=0,0,L52/L33) | M77: =IF(M33=0,0,M52/M33) | N77: =IF(N33=0,0,N52/N33) | O77: =IF(O33=0,0,O52/O33) | ... Q77: =IF(Q33=0,0,Q52/Q33)
A79: VALUATION
A80: Last price (IDR) | C80: 620
A81: Shares outstanding (m) | C81: 15825.8
A82: IDR per USD (spot) | C82: 18128
A83: Debt at balance-sheet date | C83: 310.54315
A84: Cash at balance-sheet date | C84: 58.59945
A85: Minority interest (book) | C85: 124.36568
A86: Associates & investments (book) | C86: 0
A87: Post-balance-sheet & other items (sourced, probability-weighted) | C87: 1262.7646
A88: Parent equity at balance-sheet date | C88: 2143.3925
A89: Per-share factor | C89: 1000
A90: Risk-free rate | C90: =Drivers!$C$9
A91: Less: default spread (IDR only) | C91: =Drivers!$C$11
A92: Mature ERP + Indonesia CRP | C92: =Drivers!$C$12+Drivers!$C$13
A93: Tax rate | C93: =Drivers!$C$15
A94: Unlevered beta (industry default (config)) | C94: 1
A95: Debt / equity (market) | C95: 0.031649335
A96: Levered beta | C96: =$C$94*(1+(1-$C$93)*$C$95)
A97: Explicit company premium | C97: 0
A98: Cost of equity | C98: =$C$90-$C$91+$C$96*$C$92+$C$97
A99: Pre-tax cost of debt | C99: =$C$90+Drivers!$C$14
A100: WACC | C100: =1/(1+$C$95)*$C$98+$C$95/(1+$C$95)*$C$99*(1-$C$93)
A101: Terminal growth (capped) | C101: 0.035
A103: DCF (FCFF, terminal value)
A104: Share of year after balance-sheet date | H104: 0.503765 | I104: 0.996578 | J104: 0.999316 | K104: 0.996578 | L104: 0.996578 | M104: 0.996578 | N104: 0.999316 | O104: 0.996578 | P104: 0.996578 | Q104: 0.996578
A105: Discount time from valuation date (years) | H105: 0 | I105: 0.670773 | J105: 1.670089 | K105: 2.672142 | L105: 3.671458 | M105: 4.670773 | N105: 5.670089 | O105: 6.672142 | P105: 7.671458 | Q105: 8.670773
A106: Discount factor | H106: =1/(1+$C$100)^H105 | I106: =1/(1+$C$100)^I105 | J106: =1/(1+$C$100)^J105 | K106: =1/(1+$C$100)^K105 | L106: =1/(1+$C$100)^L105 | M106: =1/(1+$C$100)^M105 | N106: =1/(1+$C$100)^N105 | O106: =1/(1+$C$100)^O105 | ... Q106: =1/(1+$C$100)^Q105
...

Sheet BBRM
A1: PT Pelayaran Nasional Bina Buana Raya Tbk (BBRM.JK) — Coal distribution, trading & logistics
A2: Units: USD m; per-share in USD unless marked IDR. Model asof 2026-10-30 · data 2026-10-28
A4: Line | C4: Scalar | D4: FY2022A | E4: FY2023A | F4: FY2024A | G4: FY2025A | H4: FY2026E | I4: FY2027E | J4: FY2028E | K4: FY2029E | L4: FY2030E | M4: FY2031E | N4: FY2032E | O4: FY2033E | P4: FY2034E | Q4: FY2035E
A6: PARAMETERS
A7: ps_factor | C7: 1
A8: vp_factor | C8: 1
A10: INPUTS (company assumptions)
A11: Revenue growth | B11: a.revenue_growth | H11: 0.0296 | I11: 0.1036 | J11: 0.03 | K11: 0.03 | L11: 0.03 | M11: 0.03 | N11: 0.03 | O11: 0.03 | P11: 0.03 | Q11: 0.03
A12: Gross margin at base input costs | B12: a.gross_margin | H12: 0.468 | I12: 0.475 | J12: 0.475 | K12: 0.475 | L12: 0.475 | M12: 0.475 | N12: 0.475 | O12: 0.475 | P12: 0.475 | Q12: 0.475
A13: Cost link 1: share of COGS exposed | B13: a.link1_share | C13: 0
A14: Cost link 1: pass-through to prices | B14: a.link1_pass | C14: 0
A15: Cost link 2: share of COGS exposed | B15: a.link2_share | C15: 0.12
A16: Cost link 2: pass-through to prices | B16: a.link2_pass | C16: 0
A17: SG&A / revenue | B17: a.opex_pct | H17: 0.085 | I17: 0.085 | J17: 0.085 | K17: 0.085 | L17: 0.085 | M17: 0.085 | N17: 0.085 | O17: 0.085 | P17: 0.085 | Q17: 0.085
A18: D&A / revenue | B18: a.da_pct | H18: 0.143 | I18: 0.155 | J18: 0.155 | K18: 0.155 | L18: 0.155 | M18: 0.155 | N18: 0.155 | O18: 0.155 | P18: 0.155 | Q18: 0.155
A19: Capex / revenue | B19: a.capex_pct | H19: 0.3965 | I19: 0.135 | J19: 0.15 | K19: 0.155 | L19: 0.155 | M19: 0.155 | N19: 0.155 | O19: 0.155 | P19: 0.155 | Q19: 0.155
A20: Operating working capital / revenue | B20: a.nwc_pct | H20: 0.2 | I20: 0.2 | J20: 0.2 | K20: 0.2 | L20: 0.2 | M20: 0.2 | N20: 0.2 | O20: 0.2 | P20: 0.2 | Q20: 0.2
A21: Effective tax rate | B21: a.tax_rate | H21: 0.025 | I21: 0.025 | J21: 0.025 | K21: 0.025 | L21: 0.025 | M21: 0.025 | N21: 0.025 | O21: 0.025 | P21: 0.025 | Q21: 0.025
A22: Cost of debt (on opening debt) | B22: a.cost_of_debt | C22: 0.09
A23: Yield on opening cash | B23: a.cash_yield | C23: 0.034
A24: Net new borrowing | B24: a.net_borrowing | H24: 5 | I24: -1 | J24: -1 | K24: -1 | L24: -1 | M24: -1.02 | N24: -1.0404 | O24: -1.061208 | P24: -1.0824322 | Q24: -1.1040808
A25: Other non-operating items | B25: a.other_nonop | H25: 0 | I25: 0 | J25: 0 | K25: 0 | L25: 0 | M25: 0 | N25: 0 | O25: 0 | P25: 0 | Q25: 0
A26: Minorities' share of net profit | B26: a.minority_pct | H26: 0 | I26: 0 | J26: 0 | K26: 0 | L26: 0 | M26: 0 | N26: 0 | O26: 0 | P26: 0 | Q26: 0
A27: Dividend payout | B27: a.payout | H27: 0 | I27: 0 | J27: 0 | K27: 0 | L27: 0 | M27: 0 | N27: 0 | O27: 0 | P27: 0 | Q27: 0
A28: Change in share count | B28: a.share_change | H28: 0 | I28: 0 | J28: 0 | K28: 0 | L28: 0 | M28: 0 | N28: 0 | O28: 0 | P28: 0 | Q28: 0
A29: Terminal growth (DCF) | B29: a.terminal_growth | C29: 0.02
A31: MODEL
A32: Revenue | B32: revenue | D32: 9.330724 | E32: 10.545555 | F32: 13.430614 | G32: 13.818874 | H32: =(G32*(1+H11)) | I32: =(H32*(1+I11)) | J32: =(I32*(1+J11)) | K32: =(J32*(1+K11)) | L32: =(K32*(1+L11)) | M32: =(L32*(1+M11)) | N32: =(M32*(1+N11)) | O32: =(N32*(1+O11)) | ... Q32: =(P32*(1+Q11))
A33: Cost of revenue | B33: cogs | D33: 6.711475 | E33: 5.879949 | F33: 6.930319 | G33: 7.166325 | H33: =((H32*(1-H12))*((1+(($C$13*(1-$C$14))*(IF(Drivers!$G$4=0,0,Drivers!$H$4/Drivers!$G$4)-1)))+(($C$15*(1-$C$16))*(IF(Drivers!$G$6=0,0,Drivers!$H$6/Drivers!$G$6)-1)))) | I33: =((I32*(1-I12))*((1+(($C$13*(1-$C$14))*(IF(Drivers!$G$4=0,0,Drivers!$I$4/Drivers!$G$4)-1)))+(($C$15*(1-$C$16))*(IF(Drivers!$G$6=0,0,Drivers!$I$6/Drivers!$G$6)-1)))) | J33: =((J32*(1-J12))*((1+(($C$13*(1-$C$14))*(IF(Drivers!$G$4=0,0,Drivers!$J$4/Drivers!$G$4)-1)))+(($C$15*(1-$C$16))*(IF(Drivers!$G$6=0,0,Drivers!$J$6/Drivers!$G$6)-1)))) | K33: =((K32*(1-K12))*((1+(($C$13*(1-$C$14))*(IF(Drivers!$G$4=0,0,Drivers!$K$4/Drivers!$G$4)-1)))+(($C$15*(1-$C$16))*(IF(Drivers!$G$6=0,0,Drivers!$K$6/Drivers!$G$6)-1)))) | L33: =((L32*(1-L12))*((1+(($C$13*(1-$C$14))*(IF(Drivers!$G$4=0,0,Drivers!$L$4/Drivers!$G$4)-1)))+(($C$15*(1-$C$16))*(IF(Drivers!$G$6=0,0,Drivers!$L$6/Drivers!$G$6)-1)))) | M33: =((M32*(1-M12))*((1+(($C$13*(1-$C$14))*(IF(Drivers!$G$4=0,0,Drivers!$M$4/Drivers!$G$4)-1)))+(($C$15*(1-$C$16))*(IF(Drivers!$G$6=0,0,Drivers!$M$6/Drivers!$G$6)-1)))) | N33: =((N32*(1-N12))*((1+(($C$13*(1-$C$14))*(IF(Drivers!$G$4=0,0,Drivers!$N$4/Drivers!$G$4)-1)))+(($C$15*(1-$C$16))*(IF(Drivers!$G$6=0,0,Drivers!$N$6/Drivers!$G$6)-1)))) | O33: =((O32*(1-O12))*((1+(($C$13*(1-$C$14))*(IF(Drivers!$G$4=0,0,Drivers!$O$4/Drivers!$G$4)-1)))+(($C$15*(1-$C$16))*(IF(Drivers!$G$6=0,0,Drivers!$O$6/Drivers!$G$6)-1)))) | P33: =((P32*(1-P12))*((1+(($C$13*(1-$C$14))*(IF(Drivers!$G$4=0,0,Drivers!$P$4/Drivers!$G$4)-1)))+(($C$15*(1-$C$16))*(IF(Drivers!$G$6=0,0,Drivers!$P$6/Drivers!$G$6)-1)))) | Q33: =((Q32*(1-Q12))*((1+(($C$13*(1-$C$14))*(IF(Drivers!$G$4=0,0,Drivers!$Q$4/Drivers!$G$4)-1)))+(($C$15*(1-$C$16))*(IF(Drivers!$G$6=0,0,Drivers!$Q$6/Drivers!$G$6)-1))))
A34: Gross profit | B34: gross_profit | D34: 2.619249 | E34: 4.665606 | F34: 6.500295 | G34: 6.652549 | H34: =(H32-H33) | I34: =(I32-I33) | J34: =(J32-J33) | K34: =(K32-K33) | L34: =(L32-L33) | M34: =(M32-M33) | N34: =(N32-N33) | O34: =(O32-O33) | ... Q34: =(Q32-Q33)
A35: SG&A and other opex | B35: opex | D35: 0.952259 | E35: 0.88157 | F35: 0.993209 | G35: 1.196047 | H35: =(H32*H17) | I35: =(I32*I17) | J35: =(J32*J17) | K35: =(K32*K17) | L35: =(L32*L17) | M35: =(M32*M17) | N35: =(N32*N17) | O35: =(O32*O17) | ... Q35: =(Q32*Q17)
A36: EBIT | B36: ebit | D36: 1.66699 | E36: 3.784036 | F36: 5.538222 | G36: 5.474846 | H36: =(H34-H35) | I36: =(I34-I35) | J36: =(J34-J35) | K36: =(K34-K35) | L36: =(L34-L35) | M36: =(M34-M35) | N36: =(N34-N35) | O36: =(O34-O35) | ... Q36: =(Q34-Q35)
A37: Depreciation & amortisation | B37: da | D37: 0.006442 | E37: 0.004011 | F37: 2.026606 | G37: 2.033029 | H37: =(H32*H18) | I37: =(I32*I18) | J37: =(J32*J18) | K37: =(K32*K18) | L37: =(L32*L18) | M37: =(M32*M18) | N37: =(N32*N18) | O37: =(O32*O18) | ... Q37: =(Q32*Q18)
A38: EBITDA | B38: ebitda | D38: 1.673432 | E38: 3.788047 | F38: 7.564828 | G38: 7.507875 | H38: =(H36+H37) | I38: =(I36+I37) | J38: =(J36+J37) | K38: =(K36+K37) | L38: =(L36+L37) | M38: =(M36+M37) | N38: =(N36+N37) | O38: =(O36+O37) | ... Q38: =(Q36+Q37)
A39: Interest expense | B39: interest_expense | D39: 0.263353 | E39: 0.163588 | F39: 0.177602 | G39: 0.371307 | H39: =(G59*$C$22) | I39: =(H59*$C$22) | J39: =(I59*$C$22) | K39: =(J59*$C$22) | L39: =(K59*$C$22) | M39: =(L59*$C$22) | N39: =(M59*$C$22) | O39: =(N59*$C$22) | ... Q39: =(P59*$C$22)
A40: Interest income | B40: interest_income | D40: 0.102216 | E40: 0.096194 | F40: 0.342523 | G40: 0.377128 | H40: =(G58*$C$23) | I40: =(H58*$C$23) | J40: =(I58*$C$23) | K40: =(J58*$C$23) | L40: =(K58*$C$23) | M40: =(L58*$C$23) | N40: =(M58*$C$23) | O40: =(N58*$C$23) | ... Q40: =(P58*$C$23)
A41: Other non-operating | B41: other_nonop | D41: -0.700542 | E41: 0.452509 | F41: 2.681484 | G41: 0.946434 | H41: =H25 | I41: =I25 | J41: =J25 | K41: =K25 | L41: =L25 | M41: =M25 | N41: =N25 | O41: =O25 | ... Q41: =Q25
A42: Profit before tax | B42: pbt | D42: 0.805311 | E42: 4.169151 | F42: 8.384627 | G42: 6.427101 | H42: =(((H36-H39)+H40)+H41) | I42: =(((I36-I39)+I40)+I41) | J42: =(((J36-J39)+J40)+J41) | K42: =(((K36-K39)+K40)+K41) | L42: =(((L36-L39)+L40)+L41) | M42: =(((M36-M39)+M40)+M41) | N42: =(((N36-N39)+N40)+N41) | O42: =(((O36-O39)+O40)+O41) | ... Q42: =(((Q36-Q39)+Q40)+Q41)
A43: Tax | B43: tax | D43: 0.112989 | E43: 0.129075 | F43: 0.151121 | G43: 0.1574 | H43: =(MAX(H42,0)*H21) | I43: =(MAX(I42,0)*I21) | J43: =(MAX(J42,0)*J21) | K43: =(MAX(K42,0)*K21) | L43: =(MAX(L42,0)*L21) | M43: =(MAX(M42,0)*M21) | N43: =(MAX(N42,0)*N21) | O43: =(MAX(O42,0)*O21) | ... Q43: =(MAX(Q42,0)*Q21)
A44: Net profit (incl. minorities) | B44: np | D44: 0.692322 | E44: 4.040076 | F44: 8.233506 | G44: 6.269701 | H44: =(H42-H43) | I44: =(I42-I43) | J44: =(J42-J43) | K44: =(K42-K43) | L44: =(L42-L43) | M44: =(M42-M43) | N44: =(N42-N43) | O44: =(O42-O43) | ... Q44: =(Q42-Q43)
A45: Minority interests | B45: minority | D45: 0 | E45: 0 | F45: 0 | G45: 0 | H45: =(H44*H26) | I45: =(I44*I26) | J45: =(J44*J26) | K45: =(K44*K26) | L45: =(L44*L26) | M45: =(M44*M26) | N45: =(N44*N26) | O45: =(O44*O26) | ... Q45: =(Q44*Q26)
A46: Net profit to parent | B46: np_parent | D46: 0.692322 | E46: 4.040076 | F46: 8.233506 | G46: 6.269701 | H46: =(H44-H45) | I46: =(I44-I45) | J46: =(J44-J45) | K46: =(K44-K45) | L46: =(L44-L45) | M46: =(M44-M45) | N46: =(N44-N45) | O46: =(O44-O45) | ... Q46: =(Q44-Q45)
A47: Shares outstanding (m) | B47: shares | D47: 8479.4903 | E47: 8479.4903 | F47: 8479.4903 | G47: 8479.4903 | H47: =(G47*(1+H28)) | I47: =(H47*(1+I28)) | J47: =(I47*(1+J28)) | K47: =(J47*(1+K28)) | L47: =(K47*(1+L28)) | M47: =(L47*(1+M28)) | N47: =(M47*(1+N28)) | O47: =(N47*(1+O28)) | ... Q47: =(P47*(1+Q28))
A48: EPS | B48: eps | D48: 8.1646652e-05 | E48: 0.00047645269 | F48: 0.00097099067 | G48: 0.00073939597 | H48: =(IF(H47=0,0,H46/H47)*$C$7) | I48: =(IF(I47=0,0,I46/I47)*$C$7) | J48: =(IF(J47=0,0,J46/J47)*$C$7) | K48: =(IF(K47=0,0,K46/K47)*$C$7) | L48: =(IF(L47=0,0,L46/L47)*$C$7) | M48: =(IF(M47=0,0,M46/M47)*$C$7) | N48: =(IF(N47=0,0,N46/N47)*$C$7) | O48: =(IF(O47=0,0,O46/O47)*$C$7) | ... Q48: =(IF(Q47=0,0,Q46/Q47)*$C$7)
A49: DPS (declared on the year) | B49: dps | D49: 0 | E49: 0 | F49: 0 | G49: 0 | H49: =(MAX(H48,0)*H27) | I49: =(MAX(I48,0)*I27) | J49: =(MAX(J48,0)*J27) | K49: =(MAX(K48,0)*K27) | L49: =(MAX(L48,0)*L27) | M49: =(MAX(M48,0)*M27) | N49: =(MAX(N48,0)*N27) | O49: =(MAX(O48,0)*O27) | ... Q49: =(MAX(Q48,0)*Q27)
A50: Dividends paid | B50: dividends_paid | H50: =IF($C$7=0,0,(G49*G47)/$C$7) | I50: =IF($C$7=0,0,(H49*H47)/$C$7) | J50: =IF($C$7=0,0,(I49*I47)/$C$7) | K50: =IF($C$7=0,0,(J49*J47)/$C$7) | L50: =IF($C$7=0,0,(K49*K47)/$C$7) | M50: =IF($C$7=0,0,(L49*L47)/$C$7) | N50: =IF($C$7=0,0,(M49*M47)/$C$7) | O50: =IF($C$7=0,0,(N49*N47)/$C$7) | ... Q50: =IF($C$7=0,0,(P49*P47)/$C$7)
A51: Capital expenditure | B51: capex | D51: 2.802736 | E51: 2.387196 | F51: 7.74846 | G51: 3.91391 | H51: =(H32*H19) | I51: =(I32*I19) | J51: =(J32*J19) | K51: =(K32*K19) | L51: =(L32*L19) | M51: =(M32*M19) | N51: =(N32*N19) | O51: =(O32*O19) | ... Q51: =(Q32*Q19)
A52: Change in working capital | B52: delta_nwc | E52: 0.485298 | F52: 3.852936 | G52: 0.428041 | H52: =(H57-G57) | I52: =(I57-H57) | J52: =(J57-I57) | K52: =(K57-J57) | L52: =(L57-K57) | M52: =(M57-L57) | N52: =(N57-M57) | O52: =(O57-N57) | ... Q52: =(Q57-P57)
A53: Free cash flow to firm | B53: fcff | E53: 0.79840098 | F53: -4.1363866 | G53: 3.0318448 | H53: =((((H36*(1-H21))+H37)-H51)-H52) | I53: =((((I36*(1-I21))+I37)-I51)-I52) | J53: =((((J36*(1-J21))+J37)-J51)-J52) | K53: =((((K36*(1-K21))+K37)-K51)-K52) | L53: =((((L36*(1-L21))+L37)-L51)-L52) | M53: =((((M36*(1-M21))+M37)-M51)-M52) | N53: =((((N36*(1-N21))+N37)-N51)-N52) | O53: =((((O36*(1-O21))+O37)-O51)-O52) | ... Q53: =((((Q36*(1-Q21))+Q37)-Q51)-Q52)
A54: Net borrowing | B54: net_borrowing | F54: 4.238586 | G54: -1.039775 | H54: =H24 | I54: =I24 | J54: =J24 | K54: =K24 | L54: =L24 | M54: =M24 | N54: =N24 | O54: =O24 | ... Q54: =Q24
A55: Dividends to minorities | B55: minority_div | H55: =(MAX(G45,0)*H27) | I55: =(MAX(H45,0)*I27) | J55: =(MAX(I45,0)*J27) | K55: =(MAX(J45,0)*K27) | L55: =(MAX(K45,0)*L27) | M55: =(MAX(L45,0)*M27) | N55: =(MAX(M45,0)*N27) | O55: =(MAX(N45,0)*O27) | ... Q55: =(MAX(P45,0)*Q27)
A56: Free cash flow to equity | B56: fcfe | H56: =(((((H44+H37)-H51)-H52)+H54)-H55) | I56: =(((((I44+I37)-I51)-I52)+I54)-I55) | J56: =(((((J44+J37)-J51)-J52)+J54)-J55) | K56: =(((((K44+K37)-K51)-K52)+K54)-K55) | L56: =(((((L44+L37)-L51)-L52)+L54)-L55) | M56: =(((((M44+M37)-M51)-M52)+M54)-M55) | N56: =(((((N44+N37)-N51)-N52)+N54)-N55) | O56: =(((((O44+O37)-O51)-O52)+O54)-O55) | ... Q56: =(((((Q44+Q37)-Q51)-Q52)+Q54)-Q55)
A57: Operating working capital | B57: nwc | D57: -1.782679 | E57: -1.297381 | F57: 2.555555 | G57: 2.983596 | H57: =(H32*H20) | I57: =(I32*I20) | J57: =(J32*J20) | K57: =(K32*K20) | L57: =(L32*L20) | M57: =(M32*M20) | N57: =(N32*N20) | O57: =(O32*O20) | ... Q57: =(Q32*Q20)
A58: Cash & equivalents | B58: cash | D58: 5.960501 | E58: 7.449947 | F58: 9.404021 | G58: 12.430298 | H58: =(((((((G58+H44)+H37)-H51)-H52)+H54)-H50)-H55) | I58: =(((((((H58+I44)+I37)-I51)-I52)+I54)-I50)-I55) | J58: =(((((((I58+J44)+J37)-J51)-J52)+J54)-J50)-J55) | K58: =(((((((J58+K44)+K37)-K51)-K52)+K54)-K50)-K55) | L58: =(((((((K58+L44)+L37)-L51)-L52)+L54)-L50)-L55) | M58: =(((((((L58+M44)+M37)-M51)-M52)+M54)-M50)-M55) | N58: =(((((((M58+N44)+N37)-N51)-N52)+N54)-N50)-N55) | O58: =(((((((N58+O44)+O37)-O51)-O52)+O54)-O50)-O55) | ... Q58: =(((((((P58+Q44)+Q37)-Q51)-Q52)+Q54)-Q50)-Q55)
A59: Total debt | B59: debt | E59: 0 | F59: 4.238586 | G59: 3.198811 | H59: =(G59+H54) | I59: =(H59+I54) | J59: =(I59+J54) | K59: =(J59+K54) | L59: =(K59+L54) | M59: =(L59+M54) | N59: =(M59+N54) | O59: =(N59+O54) | ... Q59: =(P59+Q54)
A60: Fixed assets (net) | B60: ppe | D60: 24.517336 | E60: 24.517355 | F60: 30.276054 | G60: 32.057335 | H60: =((G60+H51)-H37) | I60: =((H60+I51)-I37) | J60: =((I60+J51)-J37) | K60: =((J60+K51)-K37) | L60: =((K60+L51)-L37) | M60: =((L60+M51)-M37) | N60: =((M60+N51)-N37) | O60: =((N60+O51)-O37) | ... Q60: =((P60+Q51)-Q37)
A61: Parent shareholders' equity | B61: equity | D61: 25.713874 | E61: 29.763756 | F61: 37.999163 | G61: 44.270091 | H61: =((G61+H46)-H50) | I61: =((H61+I46)-I50) | J61: =((I61+J46)-J50) | K61: =((J61+K46)-K50) | L61: =((K61+L46)-L50) | M61: =((L61+M46)-M50) | N61: =((M61+N46)-N50) | O61: =((N61+O46)-O50) | ... Q61: =((P61+Q46)-Q50)
A62: Minority interest (balance sheet) | B62: minority_bs | D62: 0 | E62: 0 | F62: 0 | G62: 0 | H62: =((G62+H45)-H55) | I62: =((H62+I45)-I55) | J62: =((I62+J45)-J55) | K62: =((J62+K45)-K55) | L62: =((K62+L45)-L55) | M62: =((L62+M45)-M55) | N62: =((M62+N45)-N55) | O62: =((N62+O45)-O55) | ... Q62: =((P62+Q45)-Q55)
A63: Other assets less other liabilities | B63: other_net | E63: -0.906165 | F63: 0.002119 | G63: -0.002327 | H63: =G63 | I63: =H63 | J63: =I63 | K63: =J63 | L63: =K63 | M63: =L63 | N63: =M63 | O63: =N63 | ... Q63: =P63
A64: Balance check (should be zero) | B64: bs_check | H64: =((((((H58+H57)+H60)+H63)-H59)-H61)-H62) | I64: =((((((I58+I57)+I60)+I63)-I59)-I61)-I62) | J64: =((((((J58+J57)+J60)+J63)-J59)-J61)-J62) | K64: =((((((K58+K57)+K60)+K63)-K59)-K61)-K62) | L64: =((((((L58+L57)+L60)+L63)-L59)-L61)-L62) | M64: =((((((M58+M57)+M60)+M63)-M59)-M61)-M62) | N64: =((((((N58+N57)+N60)+N63)-N59)-N61)-N62) | O64: =((((((O58+O57)+O60)+O63)-O59)-O61)-O62) | ... Q64: =((((((Q58+Q57)+Q60)+Q63)-Q59)-Q61)-Q62)
A65: Net debt (cash) | B65: net_debt | E65: -7.449947 | F65: -5.165435 | G65: -9.231487 | H65: =(H59-H58) | I65: =(I59-I58) | J65: =(J59-J58) | K65: =(K59-K58) | L65: =(L59-L58) | M65: =(M59-M58) | N65: =(N59-N58) | O65: =(O59-O58) | ... Q65: =(Q59-Q58)
A66: Book value per share | B66: bvps | D66: 0.0030324787 | E66: 0.0035100879 | F66: 0.0044813027 | G66: 0.0052208434 | H66: =(IF(H47=0,0,H61/H47)*$C$7) | I66: =(IF(I47=0,0,I61/I47)*$C$7) | J66: =(IF(J47=0,0,J61/J47)*$C$7) | K66: =(IF(K47=0,0,K61/K47)*$C$7) | L66: =(IF(L47=0,0,L61/L47)*$C$7) | M66: =(IF(M47=0,0,M61/M47)*$C$7) | N66: =(IF(N47=0,0,N61/N47)*$C$7) | O66: =(IF(O47=0,0,O61/O47)*$C$7) | ... Q66: =(IF(Q47=0,0,Q61/Q47)*$C$7)
A67: Revenue growth | B67: revenue_growth | E67: 0.13019686 | F67: 0.27358057 | G67: 0.028908582 | H67: =(IF(G32=0,0,H32/G32)-1) | I67: =(IF(H32=0,0,I32/H32)-1) | J67: =(IF(I32=0,0,J32/I32)-1) | K67: =(IF(J32=0,0,K32/J32)-1) | L67: =(IF(K32=0,0,L32/K32)-1) | M67: =(IF(L32=0,0,M32/L32)-1) | N67: =(IF(M32=0,0,N32/M32)-1) | O67: =(IF(N32=0,0,O32/N32)-1) | ... Q67: =(IF(P32=0,0,Q32/P32)-1)
A68: Gross margin | B68: gross_margin | D68: 0.2807123 | E68: 0.44242394 | F68: 0.4839909 | G68: 0.48141035 | H68: =IF(H32=0,0,H34/H32) | I68: =IF(I32=0,0,I34/I32) | J68: =IF(J32=0,0,J34/J32) | K68: =IF(K32=0,0,K34/K32) | L68: =IF(L32=0,0,L34/L32) | M68: =IF(M32=0,0,M34/M32) | N68: =IF(N32=0,0,N34/N32) | O68: =IF(O32=0,0,O34/O32) | ... Q68: =IF(Q32=0,0,Q34/Q32)
A69: EBITDA margin | B69: ebitda_margin | D69: 0.17934643 | E69: 0.35920793 | F69: 0.56325258 | G69: 0.54330584 | H69: =IF(H32=0,0,H38/H32) | I69: =IF(I32=0,0,I38/I32) | J69: =IF(J32=0,0,J38/J32) | K69: =IF(K32=0,0,K38/K32) | L69: =IF(L32=0,0,L38/L32) | M69: =IF(M32=0,0,M38/M32) | N69: =IF(N32=0,0,N38/N32) | O69: =IF(O32=0,0,O38/O32) | ... Q69: =IF(Q32=0,0,Q38/Q32)
A70: EBIT margin | B70: ebit_margin | D70: 0.17865602 | E70: 0.35882758 | F70: 0.41235806 | G70: 0.39618611 | H70: =IF(H32=0,0,H36/H32) | I70: =IF(I32=0,0,I36/I32) | J70: =IF(J32=0,0,J36/J32) | K70: =IF(K32=0,0,K36/K32) | L70: =IF(L32=0,0,L36/L32) | M70: =IF(M32=0,0,M36/M32) | N70: =IF(N32=0,0,N36/N32) | O70: =IF(O32=0,0,O36/O32) | ... Q70: =IF(Q32=0,0,Q36/Q32)
A71: Net margin | B71: np_margin | D71: 0.074198101 | E71: 0.38310701 | F71: 0.61304018 | G71: 0.45370563 | H71: =IF(H32=0,0,H46/H32) | I71: =IF(I32=0,0,I46/I32) | J71: =IF(J32=0,0,J46/J32) | K71: =IF(K32=0,0,K46/K32) | L71: =IF(L32=0,0,L46/L32) | M71: =IF(M32=0,0,M46/M32) | N71: =IF(N32=0,0,N46/N32) | O71: =IF(O32=0,0,O46/O32) | ... Q71: =IF(Q32=0,0,Q46/Q32)
A72: EPS growth | B72: eps_growth | E72: 4.8355447 | F72: 1.0379582 | G72: -0.23851382 | H72: =(IF(G48=0,0,H48/G48)-1) | I72: =(IF(H48=0,0,I48/H48)-1) | J72: =(IF(I48=0,0,J48/I48)-1) | K72: =(IF(J48=0,0,K48/J48)-1) | L72: =(IF(K48=0,0,L48/K48)-1) | M72: =(IF(L48=0,0,M48/L48)-1) | N72: =(IF(M48=0,0,N48/M48)-1) | O72: =(IF(N48=0,0,O48/N48)-1) | ... Q72: =(IF(P48=0,0,Q48/P48)-1)
A73: ROE | B73: roe | E73: 0.14564703 | F73: 0.24300919 | G73: 0.15241906 | H73: =IF(IF(2=0,0,(H61+G61)/2)=0,0,H46/IF(2=0,0,(H61+G61)/2)) | I73: =IF(IF(2=0,0,(I61+H61)/2)=0,0,I46/IF(2=0,0,(I61+H61)/2)) | J73: =IF(IF(2=0,0,(J61+I61)/2)=0,0,J46/IF(2=0,0,(J61+I61)/2)) | K73: =IF(IF(2=0,0,(K61+J61)/2)=0,0,K46/IF(2=0,0,(K61+J61)/2)) | L73: =IF(IF(2=0,0,(L61+K61)/2)=0,0,L46/IF(2=0,0,(L61+K61)/2)) | M73: =IF(IF(2=0,0,(M61+L61)/2)=0,0,M46/IF(2=0,0,(M61+L61)/2)) | N73: =IF(IF(2=0,0,(N61+M61)/2)=0,0,N46/IF(2=0,0,(N61+M61)/2)) | O73: =IF(IF(2=0,0,(O61+N61)/2)=0,0,O46/IF(2=0,0,(O61+N61)/2)) | ... Q73: =IF(IF(2=0,0,(Q61+P61)/2)=0,0,Q46/IF(2=0,0,(Q61+P61)/2))
A74: Net debt / EBITDA | B74: net_debt_ebitda | E74: -1.9666987 | F74: -0.68282253 | G74: -1.2295739 | H74: =IF(H38=0,0,H65/H38) | I74: =IF(I38=0,0,I65/I38) | J74: =IF(J38=0,0,J65/J38) | K74: =IF(K38=0,0,K65/K38) | L74: =IF(L38=0,0,L65/L38) | M74: =IF(M38=0,0,M65/M38) | N74: =IF(N38=0,0,N65/N38) | O74: =IF(O38=0,0,O65/O38) | ... Q74: =IF(Q38=0,0,Q65/Q38)
A75: Payout ratio | B75: payout_ratio | D75: 0 | E75: 0 | F75: 0 | G75: 0 | H75: =IF(H48=0,0,H49/H48) | I75: =IF(I48=0,0,I49/I48) | J75: =IF(J48=0,0,J49/J48) | K75: =IF(K48=0,0,K49/K48) | L75: =IF(L48=0,0,L49/L48) | M75: =IF(M48=0,0,M49/M48) | N75: =IF(N48=0,0,N49/N48) | O75: =IF(O48=0,0,O49/O48) | ... Q75: =IF(Q48=0,0,Q49/Q48)
A76: Capex / revenue | B76: capex_revenue | D76: 0.30037712 | E76: 0.22636988 | F76: 0.57692522 | G76: 0.2832293 | H76: =IF(H32=0,0,H51/H32) | I76: =IF(I32=0,0,I51/I32) | J76: =IF(J32=0,0,J51/J32) | K76: =IF(K32=0,0,K51/K32) | L76: =IF(L32=0,0,L51/L32) | M76: =IF(M32=0,0,M51/M32) | N76: =IF(N32=0,0,N51/N32) | O76: =IF(O32=0,0,O51/O32) | ... Q76: =IF(Q32=0,0,Q51/Q32)
A78: VALUATION
A79: Last price (IDR) | C79: 93
A80: Shares outstanding (m) | C80: 8479.4903
A81: IDR per USD (spot) | C81: 18128
A82: Debt at balance-sheet date | C82: 7.110626
A83: Cash at balance-sheet date | C83: 13.638932
A84: Minority interest (book) | C84: 0
A85: Associates & investments (book) | C85: 0
A86: Post-balance-sheet & other items (sourced, probability-weighted) | C86: 0
A87: Parent equity at balance-sheet date | C87: 47.27953
A88: Per-share factor | C88: 1
A89: Risk-free rate | C89: =Drivers!$C$10
A90: Less: default spread (IDR only) | C90: 0
A91: Mature ERP + Indonesia CRP | C91: =Drivers!$C$12+Drivers!$C$13
A92: Tax rate | C92: =Drivers!$C$15
A93: Unlevered beta (industry default (config)) | C93: 1
A94: Debt / equity (market) | C94: 0.16345757
A95: Levered beta | C95: =$C$93*(1+(1-$C$92)*$C$94)
A96: Explicit company premium | C96: 0
A97: Cost of equity | C97: =$C$89-$C$90+$C$95*$C$91+$C$96
A98: Pre-tax cost of debt | C98: =$C$89+Drivers!$C$14
A99: WACC | C99: =1/(1+$C$94)*$C$97+$C$94/(1+$C$94)*$C$98*(1-$C$92)
A100: Terminal growth (capped) | C100: 0.02
A102: DCF (FCFF, terminal value)
A103: Share of year after balance-sheet date | H103: 0.503765 | I103: 0.996578 | J103: 0.999316 | K103: 0.996578 | L103: 0.996578 | M103: 0.996578 | N103: 0.999316 | O103: 0.996578 | P103: 0.996578 | Q103: 0.996578
A104: Discount time from valuation date (years) | H104: 0 | I104: 0.670773 | J104: 1.670089 | K104: 2.672142 | L104: 3.671458 | M104: 4.670773 | N104: 5.670089 | O104: 6.672142 | P104: 7.671458 | Q104: 8.670773
A105: Discount factor | H105: =1/(1+$C$99)^H104 | I105: =1/(1+$C$99)^I104 | J105: =1/(1+$C$99)^J104 | K105: =1/(1+$C$99)^K104 | L105: =1/(1+$C$99)^L104 | M105: =1/(1+$C$99)^M104 | N105: =1/(1+$C$99)^N104 | O105: =1/(1+$C$99)^O104 | ... Q105: =1/(1+$C$99)^Q104
A106: PV of FCFF | H106: =H53*H103*H105 | I106: =I53*I103*I105 | J106: =J53*J103*J105 | K106: =K53*K103*K105 | L106: =L53*L103*L105 | M106: =M53*M103*M105 | N106: =N53*N103*N105 | O106: =O53*O103*O105 | ... Q106: =Q53*Q103*Q105
...

Sheet BESS
A1: PT Batulicin Nusantara Maritim Tbk (BESS.JK) — Coal distribution, trading & logistics
A2: Units: IDR bn; per-share in IDR unless marked IDR. Model asof 2026-10-30 · data 2026-10-28
A4: Line | C4: Scalar | D4: FY2023A | E4: FY2024A | F4: FY2025A | G4: FY2026E | H4: FY2027E | I4: FY2028E | J4: FY2029E | K4: FY2030E | L4: FY2031E | M4: FY2032E | N4: FY2033E | O4: FY2034E | P4: FY2035E
A6: PARAMETERS
A7: horizon | C7: 10
A8: ps_factor | C8: 1000
A9: vp_factor | C9: 1
A11: INPUTS (company assumptions)
A12: Revenue growth | B12: a.revenue_growth | G12: -0.376 | H12: 0.16 | I12: 0.08 | J12: 0.04 | K12: 0.03 | L12: 0.03 | M12: 0.03 | N12: 0.03 | O12: 0.03 | P12: 0.03
A13: Gross margin at base input costs | B13: a.gross_margin | G13: 0.215 | H13: 0.28 | I13: 0.31 | J13: 0.33 | K13: 0.33 | L13: 0.33 | M13: 0.33 | N13: 0.33 | O13: 0.33 | P13: 0.33
A14: Cost link 1: share of COGS exposed | B14: a.link1_share | C14: 0.06
A15: Cost link 1: pass-through to prices | B15: a.link1_pass | C15: 0.6
A16: Cost link 2: share of COGS exposed | B16: a.link2_share | C16: 0.26
A17: Cost link 2: pass-through to prices | B17: a.link2_pass | C17: 0.5
A18: SG&A / revenue | B18: a.opex_pct | G18: 0.215 | H18: 0.185 | I18: 0.17 | J18: 0.16 | K18: 0.155 | L18: 0.155 | M18: 0.155 | N18: 0.155 | O18: 0.155 | P18: 0.155
A19: D&A / revenue | B19: a.da_pct | G19: 0.17 | H19: 0.148 | I19: 0.137 | J19: 0.131 | K19: 0.127 | L19: 0.127 | M19: 0.127 | N19: 0.127 | O19: 0.127 | P19: 0.127
A20: Capex / revenue | B20: a.capex_pct | G20: 0.08 | H20: 0.08 | I20: 0.08 | J20: 0.08 | K20: 0.08 | L20: 0.08 | M20: 0.08 | N20: 0.08 | O20: 0.08 | P20: 0.08
A21: Operating working capital / revenue | B21: a.nwc_pct | G21: 0.346 | H21: 0.346 | I21: 0.346 | J21: 0.346 | K21: 0.346 | L21: 0.346 | M21: 0.346 | N21: 0.346 | O21: 0.346 | P21: 0.346
A22: Effective tax rate | B22: a.tax_rate | G22: 0 | H22: 0.168 | I22: 0.097 | J22: 0.076 | K22: 0.073 | L22: 0.07 | M22: 0.07 | N22: 0.07 | O22: 0.07 | P22: 0.07
A23: Cost of debt (on opening debt) | B23: a.cost_of_debt | C23: 0.08
A24: Yield on opening cash | B24: a.cash_yield | C24: 0.025
A25: Net new borrowing | B25: a.net_borrowing | G25: 0 | H25: 0 | I25: 0 | J25: 0 | K25: 0 | L25: 0 | M25: 0 | N25: 0 | O25: 0 | P25: 0
A26: Other non-operating items | B26: a.other_nonop | G26: -6.5 | H26: -6.5 | I26: -6.5 | J26: -6.5 | K26: -6.5 | L26: -6.6625 | M26: -6.8290625 | N26: -6.9997891 | O26: -7.1747838 | P26: -7.3541534
A27: Minorities' share of net profit | B27: a.minority_pct | G27: 0.0008 | H27: 0.0008 | I27: 0.0008 | J27: 0.0008 | K27: 0.0008 | L27: 0.0008 | M27: 0.0008 | N27: 0.0008 | O27: 0.0008 | P27: 0.0008
A28: Dividend payout | B28: a.payout | G28: 0.25 | H28: 0.25 | I28: 0.25 | J28: 0.25 | K28: 0.25 | L28: 0.25 | M28: 0.25 | N28: 0.25 | O28: 0.25 | P28: 0.25
A29: Change in share count | B29: a.share_change | G29: 0 | H29: 0 | I29: 0 | J29: 0 | K29: 0 | L29: 0 | M29: 0 | N29: 0 | O29: 0 | P29: 0
A30: Terminal growth (DCF) | B30: a.terminal_growth | C30: 0.03
A32: MODEL
A33: Revenue | B33: revenue | D33: 363.74118 | E33: 318.86883 | F33: 353.69647 | G33: =(F33*(1+G12)) | H33: =(G33*(1+H12)) | I33: =(H33*(1+I12)) | J33: =(I33*(1+J12)) | K33: =(J33*(1+K12)) | L33: =(K33*(1+L12)) | M33: =(L33*(1+M12)) | N33: =(M33*(1+N12)) | ... P33: =(O33*(1+P12))
A34: Cost of revenue | B34: cogs | D34: 234.22518 | E34: 219.96301 | F34: 221.68918 | G34: =((G33*(1-G13))*((1+(($C$14*(1-$C$15))*(IF(Drivers!$G$4=0,0,Drivers!$H$4/Drivers!$G$4)-1)))+(($C$16*(1-$C$17))*(IF(Drivers!$G$6=0,0,Drivers!$H$6/Drivers!$G$6)-1)))) | H34: =((H33*(1-H13))*((1+(($C$14*(1-$C$15))*(IF(Drivers!$G$4=0,0,Drivers!$I$4/Drivers!$G$4)-1)))+(($C$16*(1-$C$17))*(IF(Drivers!$G$6=0,0,Drivers!$I$6/Drivers!$G$6)-1)))) | I34: =((I33*(1-I13))*((1+(($C$14*(1-$C$15))*(IF(Drivers!$G$4=0,0,Drivers!$J$4/Drivers!$G$4)-1)))+(($C$16*(1-$C$17))*(IF(Drivers!$G$6=0,0,Drivers!$J$6/Drivers!$G$6)-1)))) | J34: =((J33*(1-J13))*((1+(($C$14*(1-$C$15))*(IF(Drivers!$G$4=0,0,Drivers!$K$4/Drivers!$G$4)-1)))+(($C$16*(1-$C$17))*(IF(Drivers!$G$6=0,0,Drivers!$K$6/Drivers!$G$6)-1)))) | K34: =((K33*(1-K13))*((1+(($C$14*(1-$C$15))*(IF(Drivers!$G$4=0,0,Drivers!$L$4/Drivers!$G$4)-1)))+(($C$16*(1-$C$17))*(IF(Drivers!$G$6=0,0,Drivers!$L$6/Drivers!$G$6)-1)))) | L34: =((L33*(1-L13))*((1+(($C$14*(1-$C$15))*(IF(Drivers!$G$4=0,0,Drivers!$M$4/Drivers!$G$4)-1)))+(($C$16*(1-$C$17))*(IF(Drivers!$G$6=0,0,Drivers!$M$6/Drivers!$G$6)-1)))) | M34: =((M33*(1-M13))*((1+(($C$14*(1-$C$15))*(IF(Drivers!$G$4=0,0,Drivers!$N$4/Drivers!$G$4)-1)))+(($C$16*(1-$C$17))*(IF(Drivers!$G$6=0,0,Drivers!$N$6/Drivers!$G$6)-1)))) | N34: =((N33*(1-N13))*((1+(($C$14*(1-$C$15))*(IF(Drivers!$G$4=0,0,Drivers!$O$4/Drivers!$G$4)-1)))+(($C$16*(1-$C$17))*(IF(Drivers!$G$6=0,0,Drivers!$O$6/Drivers!$G$6)-1)))) | O34: =((O33*(1-O13))*((1+(($C$14*(1-$C$15))*(IF(Drivers!$G$4=0,0,Drivers!$P$4/Drivers!$G$4)-1)))+(($C$16*(1-$C$17))*(IF(Drivers!$G$6=0,0,Drivers!$P$6/Drivers!$G$6)-1)))) | P34: =((P33*(1-P13))*((1+(($C$14*(1-$C$15))*(IF(Drivers!$G$4=0,0,Drivers!$Q$4/Drivers!$G$4)-1)))+(($C$16*(1-$C$17))*(IF(Drivers!$G$6=0,0,Drivers!$Q$6/Drivers!$G$6)-1))))
A35: Gross profit | B35: gross_profit | D35: 129.516 | E35: 98.905824 | F35: 132.00729 | G35: =(G33-G34) | H35: =(H33-H34) | I35: =(I33-I34) | J35: =(J33-J34) | K35: =(K33-K34) | L35: =(L33-L34) | M35: =(M33-M34) | N35: =(N33-N34) | ... P35: =(P33-P34)
A36: SG&A and other opex | B36: opex | D36: 47.420397 | E36: 56.774903 | F36: 53.13861 | G36: =(G33*G18) | H36: =(H33*H18) | I36: =(I33*I18) | J36: =(J33*J18) | K36: =(K33*K18) | L36: =(L33*L18) | M36: =(M33*M18) | N36: =(N33*N18) | ... P36: =(P33*P18)
A37: EBIT | B37: ebit | D37: 82.095605 | E37: 42.130921 | F37: 78.868681 | G37: =(G35-G36) | H37: =(H35-H36) | I37: =(I35-I36) | J37: =(J35-J36) | K37: =(K35-K36) | L37: =(L35-L36) | M37: =(M35-M36) | N37: =(N35-N36) | ... P37: =(P35-P36)
A38: Depreciation & amortisation | B38: da | D38: 39.469601 | E38: 39.376499 | F38: 39.465717 | G38: =(G33*G19) | H38: =(H33*H19) | I38: =(I33*I19) | J38: =(J33*J19) | K38: =(K33*K19) | L38: =(L33*L19) | M38: =(M33*M19) | N38: =(N33*N19) | ... P38: =(P33*P19)
A39: EBITDA | B39: ebitda | D39: 121.56521 | E39: 81.50742 | F39: 118.3344 | G39: =(G37+G38) | H39: =(H37+H38) | I39: =(I37+I38) | J39: =(J37+J38) | K39: =(K37+K38) | L39: =(L37+L38) | M39: =(M37+M38) | N39: =(N37+N38) | ... P39: =(P37+P38)
A40: Interest expense | B40: interest_expense | D40: 14.376516 | E40: 6.5043221 | F40: 2.1308871 | G40: =(F60*$C$23) | H40: =(G60*$C$23) | I40: =(H60*$C$23) | J40: =(I60*$C$23) | K40: =(J60*$C$23) | L40: =(K60*$C$23) | M40: =(L60*$C$23) | N40: =(M60*$C$23) | ... P40: =(O60*$C$23)
A41: Interest income | B41: interest_income | D41: 1.2458955 | E41: 0.82070621 | F41: 2.1613818 | G41: =(F59*$C$24) | H41: =(G59*$C$24) | I41: =(H59*$C$24) | J41: =(I59*$C$24) | K41: =(J59*$C$24) | L41: =(K59*$C$24) | M41: =(L59*$C$24) | N41: =(M59*$C$24) | ... P41: =(O59*$C$24)
A42: Other non-operating | B42: other_nonop | D42: 12.129067 | E42: -6.2693303 | F42: -15.267172 | G42: =G26 | H42: =H26 | I42: =I26 | J42: =J26 | K42: =K26 | L42: =L26 | M42: =M26 | N42: =N26 | ... P42: =P26
A43: Profit before tax | B43: pbt | D43: 81.094052 | E43: 30.177974 | F43: 63.632004 | G43: =(((G37-G40)+G41)+G42) | H43: =(((H37-H40)+H41)+H42) | I43: =(((I37-I40)+I41)+I42) | J43: =(((J37-J40)+J41)+J42) | K43: =(((K37-K40)+K41)+K42) | L43: =(((L37-L40)+L41)+L42) | M43: =(((M37-M40)+M41)+M42) | N43: =(((N37-N40)+N41)+N42) | ... P43: =(((P37-P40)+P41)+P42)
A44: Tax | B44: tax | D44: 1.644017 | E44: 5.9364555 | F44: 0 | G44: =(MAX(G43,0)*G22) | H44: =(MAX(H43,0)*H22) | I44: =(MAX(I43,0)*I22) | J44: =(MAX(J43,0)*J22) | K44: =(MAX(K43,0)*K22) | L44: =(MAX(L43,0)*L22) | M44: =(MAX(M43,0)*M22) | N44: =(MAX(N43,0)*N22) | ... P44: =(MAX(P43,0)*P22)
A45: Net profit (incl. minorities) | B45: np | D45: 79.450035 | E45: 24.241519 | F45: 63.632004 | G45: =(G43-G44) | H45: =(H43-H44) | I45: =(I43-I44) | J45: =(J43-J44) | K45: =(K43-K44) | L45: =(L43-L44) | M45: =(M43-M44) | N45: =(N43-N44) | ... P45: =(P43-P44)
A46: Minority interests | B46: minority | D46: 0.026259944 | E46: 0.036541956 | F46: 0.029690611 | G46: =(G45*G27) | H46: =(H45*H27) | I46: =(I45*I27) | J46: =(J45*J27) | K46: =(K45*K27) | L46: =(L45*L27) | M46: =(M45*M27) | N46: =(N45*N27) | ... P46: =(P45*P27)
A47: Net profit to parent | B47: np_parent | D47: 79.423775 | E47: 24.204977 | F47: 63.602313 | G47: =(G45-G46) | H47: =(H45-H46) | I47: =(I45-I46) | J47: =(J45-J46) | K47: =(K45-K46) | L47: =(L45-L46) | M47: =(M45-M46) | N47: =(N45-N46) | ... P47: =(P45-P46)
A48: Shares outstanding (m) | B48: shares | D48: 3440.4555 | E48: 3440.4555 | F48: 3440.4555 | G48: =(F48*(1+G29)) | H48: =(G48*(1+H29)) | I48: =(H48*(1+I29)) | J48: =(I48*(1+J29)) | K48: =(J48*(1+K29)) | L48: =(K48*(1+L29)) | M48: =(L48*(1+M29)) | N48: =(M48*(1+N29)) | ... P48: =(O48*(1+P29))
A49: EPS | B49: eps | D49: 23.08525 | E49: 7.0353988 | F49: 18.486596 | G49: =(IF(G48=0,0,G47/G48)*$C$8) | H49: =(IF(H48=0,0,H47/H48)*$C$8) | I49: =(IF(I48=0,0,I47/I48)*$C$8) | J49: =(IF(J48=0,0,J47/J48)*$C$8) | K49: =(IF(K48=0,0,K47/K48)*$C$8) | L49: =(IF(L48=0,0,L47/L48)*$C$8) | M49: =(IF(M48=0,0,M47/M48)*$C$8) | N49: =(IF(N48=0,0,N47/N48)*$C$8) | ... P49: =(IF(P48=0,0,P47/P48)*$C$8)
A50: DPS (declared on the year) | B50: dps | D50: 0 | E50: 0 | F50: 4.36 | G50: =(MAX(G49,0)*G28) | H50: =(MAX(H49,0)*H28) | I50: =(MAX(I49,0)*I28) | J50: =(MAX(J49,0)*J28) | K50: =(MAX(K49,0)*K28) | L50: =(MAX(L49,0)*L28) | M50: =(MAX(M49,0)*M28) | N50: =(MAX(N49,0)*N28) | ... P50: =(MAX(P49,0)*P28)
A51: Dividends paid | B51: dividends_paid | G51: =IF($C$8=0,0,(F50*F48)/$C$8) | H51: =IF($C$8=0,0,(G50*G48)/$C$8) | I51: =IF($C$8=0,0,(H50*H48)/$C$8) | J51: =IF($C$8=0,0,(I50*I48)/$C$8) | K51: =IF($C$8=0,0,(J50*J48)/$C$8) | L51: =IF($C$8=0,0,(K50*K48)/$C$8) | M51: =IF($C$8=0,0,(L50*L48)/$C$8) | N51: =IF($C$8=0,0,(M50*M48)/$C$8) | ... P51: =IF($C$8=0,0,(O50*O48)/$C$8)
A52: Capital expenditure | B52: capex | D52: 0.55904166 | E52: 0.97826555 | F52: 2.5210506 | G52: =(G33*G20) | H52: =(H33*H20) | I52: =(I33*I20) | J52: =(J33*J20) | K52: =(K33*K20) | L52: =(L33*L20) | M52: =(M33*M20) | N52: =(N33*N20) | ... P52: =(P33*P20)
A53: Change in working capital | B53: delta_nwc | E53: 45.663616 | F53: -18.845623 | G53: =(G58-F58) | H53: =(H58-G58) | I53: =(I58-H58) | J53: =(J58-I58) | K53: =(K58-J58) | L53: =(L58-K58) | M53: =(M58-L58) | N53: =(N58-M58) | ... P53: =(P58-O58)
A54: Free cash flow to firm | B54: fcff | E54: 26.577761 | F54: 134.65897 | G54: =((((G37*(1-G22))+G38)-G52)-G53) | H54: =((((H37*(1-H22))+H38)-H52)-H53) | I54: =((((I37*(1-I22))+I38)-I52)-I53) | J54: =((((J37*(1-J22))+J38)-J52)-J53) | K54: =((((K37*(1-K22))+K38)-K52)-K53) | L54: =((((L37*(1-L22))+L38)-L52)-L53) | M54: =((((M37*(1-M22))+M38)-M52)-M53) | N54: =((((N37*(1-N22))+N38)-N52)-N53) | ... P54: =((((P37*(1-P22))+P38)-P52)-P53)
A55: Net borrowing | B55: net_borrowing | E55: -59.962378 | F55: -16.148721 | G55: =G25 | H55: =H25 | I55: =I25 | J55: =J25 | K55: =K25 | L55: =L25 | M55: =M25 | N55: =N25 | ... P55: =P25
A56: Dividends to minorities | B56: minority_div | G56: =(MAX(F46,0)*G28) | H56: =(MAX(G46,0)*H28) | I56: =(MAX(H46,0)*I28) | J56: =(MAX(I46,0)*J28) | K56: =(MAX(J46,0)*K28) | L56: =(MAX(K46,0)*L28) | M56: =(MAX(L46,0)*M28) | N56: =(MAX(M46,0)*N28) | ... P56: =(MAX(O46,0)*P28)
A57: Free cash flow to equity | B57: fcfe | G57: =(((((G45+G38)-G52)-G53)+G55)-G56) | H57: =(((((H45+H38)-H52)-H53)+H55)-H56) | I57: =(((((I45+I38)-I52)-I53)+I55)-I56) | J57: =(((((J45+J38)-J52)-J53)+J55)-J56) | K57: =(((((K45+K38)-K52)-K53)+K55)-K56) | L57: =(((((L45+L38)-L52)-L53)+L55)-L56) | M57: =(((((M45+M38)-M52)-M53)+M55)-M56) | N57: =(((((N45+N38)-N52)-N53)+N55)-N56) | ... P57: =(((((P45+P38)-P52)-P53)+P55)-P56)
A58: Operating working capital | B58: nwc | D58: 31.106687 | E58: 76.770303 | F58: 57.924681 | G58: =(G33*G21) | H58: =(H33*H21) | I58: =(I33*I21) | J58: =(J33*J21) | K58: =(K33*K21) | L58: =(L33*L21) | M58: =(M33*M21) | N58: =(N33*N21) | ... P58: =(P33*P21)
A59: Cash & equivalents | B59: cash | D59: 116.32852 | E59: 73.040391 | F59: 184.79051 | G59: =(((((((F59+G45)+G38)-G52)-G53)+G55)-G51)-G56) | H59: =(((((((G59+H45)+H38)-H52)-H53)+H55)-H51)-H56) | I59: =(((((((H59+I45)+I38)-I52)-I53)+I55)-I51)-I56) | J59: =(((((((I59+J45)+J38)-J52)-J53)+J55)-J51)-J56) | K59: =(((((((J59+K45)+K38)-K52)-K53)+K55)-K51)-K56) | L59: =(((((((K59+L45)+L38)-L52)-L53)+L55)-L51)-L56) | M59: =(((((((L59+M45)+M38)-M52)-M53)+M55)-M51)-M56) | N59: =(((((((M59+N45)+N38)-N52)-N53)+N55)-N51)-N56) | ... P59: =(((((((O59+P45)+P38)-P52)-P53)+P55)-P51)-P56)
A60: Total debt | B60: debt | D60: 90.673409 | E60: 30.711031 | F60: 14.56231 | G60: =(F60+G55) | H60: =(G60+H55) | I60: =(H60+I55) | J60: =(I60+J55) | K60: =(J60+K55) | L60: =(K60+L55) | M60: =(L60+M55) | N60: =(M60+N55) | ... P60: =(O60+P55)
A61: Fixed assets (net) | B61: ppe | D61: 514.74294 | E61: 476.34471 | F61: 439.40004 | G61: =((F61+G52)-G38) | H61: =((G61+H52)-H38) | I61: =((H61+I52)-I38) | J61: =((I61+J52)-J38) | K61: =((J61+K52)-K38) | L61: =((K61+L52)-L38) | M61: =((L61+M52)-M38) | N61: =((M61+N52)-N38) | ... P61: =((O61+P52)-P38)
A62: Parent shareholders' equity | B62: equity | D62: 569.2277 | E62: 595.80364 | F62: 660.53402 | G62: =((F62+G47)-G51) | H62: =((G62+H47)-H51) | I62: =((H62+I47)-I51) | J62: =((I62+J47)-J51) | K62: =((J62+K47)-K51) | L62: =((K62+L47)-L51) | M62: =((L62+M47)-M51) | N62: =((M62+N47)-N51) | ... P62: =((O62+P47)-P51)
A63: Minority interest (balance sheet) | B63: minority_bs | D63: 0.010509944 | E63: 0.0470519 | F63: 0.076742511 | G63: =((F63+G46)-G56) | H63: =((G63+H46)-H56) | I63: =((H63+I46)-I56) | J63: =((I63+J46)-J56) | K63: =((J63+K46)-K56) | L63: =((K63+L46)-L56) | M63: =((L63+M46)-M56) | N63: =((M63+N46)-N56) | ... P63: =((O63+P46)-P56)
A64: Other assets less other liabilities | B64: other_net | D64: -2.266532 | E64: 0.40632226 | F64: -6.9421643 | G64: =F64 | H64: =G64 | I64: =H64 | J64: =I64 | K64: =J64 | L64: =K64 | M64: =L64 | N64: =M64 | ... P64: =O64
A65: Balance check (should be zero) | B65: bs_check | G65: =((((((G59+G58)+G61)+G64)-G60)-G62)-G63) | H65: =((((((H59+H58)+H61)+H64)-H60)-H62)-H63) | I65: =((((((I59+I58)+I61)+I64)-I60)-I62)-I63) | J65: =((((((J59+J58)+J61)+J64)-J60)-J62)-J63) | K65: =((((((K59+K58)+K61)+K64)-K60)-K62)-K63) | L65: =((((((L59+L58)+L61)+L64)-L60)-L62)-L63) | M65: =((((((M59+M58)+M61)+M64)-M60)-M62)-M63) | N65: =((((((N59+N58)+N61)+N64)-N60)-N62)-N63) | ... P65: =((((((P59+P58)+P61)+P64)-P60)-P62)-P63)
A66: Net debt (cash) | B66: net_debt | D66: -25.655111 | E66: -42.32936 | F66: -170.2282 | G66: =(G60-G59) | H66: =(H60-H59) | I66: =(I60-I59) | J66: =(J60-J59) | K66: =(K60-K59) | L66: =(L60-L59) | M66: =(M60-M59) | N66: =(N60-N59) | ... P66: =(P60-P59)
A67: Book value per share | B67: bvps | D67: 165.45126 | E67: 173.1758 | F67: 191.99028 | G67: =(IF(G48=0,0,G62/G48)*$C$8) | H67: =(IF(H48=0,0,H62/H48)*$C$8) | I67: =(IF(I48=0,0,I62/I48)*$C$8) | J67: =(IF(J48=0,0,J62/J48)*$C$8) | K67: =(IF(K48=0,0,K62/K48)*$C$8) | L67: =(IF(L48=0,0,L62/L48)*$C$8) | M67: =(IF(M48=0,0,M62/M48)*$C$8) | N67: =(IF(N48=0,0,N62/N48)*$C$8) | ... P67: =(IF(P48=0,0,P62/P48)*$C$8)
A68: Revenue growth | B68: revenue_growth | E68: -0.12336339 | F68: 0.10922247 | G68: =(IF(F33=0,0,G33/F33)-1) | H68: =(IF(G33=0,0,H33/G33)-1) | I68: =(IF(H33=0,0,I33/H33)-1) | J68: =(IF(I33=0,0,J33/I33)-1) | K68: =(IF(J33=0,0,K33/J33)-1) | L68: =(IF(K33=0,0,L33/K33)-1) | M68: =(IF(L33=0,0,M33/L33)-1) | N68: =(IF(M33=0,0,N33/M33)-1) | ... P68: =(IF(O33=0,0,P33/O33)-1)
A69: Gross margin | B69: gross_margin | D69: 0.35606637 | E69: 0.31017714 | F69: 0.37322196 | G69: =IF(G33=0,0,G35/G33) | H69: =IF(H33=0,0,H35/H33) | I69: =IF(I33=0,0,I35/I33) | J69: =IF(J33=0,0,J35/J33) | K69: =IF(K33=0,0,K35/K33) | L69: =IF(L33=0,0,L35/L33) | M69: =IF(M33=0,0,M35/M33) | N69: =IF(N33=0,0,N35/N33) | ... P69: =IF(P33=0,0,P35/P33)
A70: EBITDA margin | B70: ebitda_margin | D70: 0.33420799 | E70: 0.25561426 | F70: 0.33456482 | G70: =IF(G33=0,0,G39/G33) | H70: =IF(H33=0,0,H39/H33) | I70: =IF(I33=0,0,I39/I33) | J70: =IF(J33=0,0,J39/J33) | K70: =IF(K33=0,0,K39/K33) | L70: =IF(L33=0,0,L39/L33) | M70: =IF(M33=0,0,M39/M33) | N70: =IF(N33=0,0,N39/N33) | ... P70: =IF(P33=0,0,P39/P33)
A71: EBIT margin | B71: ebit_margin | D71: 0.22569786 | E71: 0.13212618 | F71: 0.22298407 | G71: =IF(G33=0,0,G37/G33) | H71: =IF(H33=0,0,H37/H33) | I71: =IF(I33=0,0,I37/I33) | J71: =IF(J33=0,0,J37/J33) | K71: =IF(K33=0,0,K37/K33) | L71: =IF(L33=0,0,L37/L33) | M71: =IF(M33=0,0,M37/M33) | N71: =IF(N33=0,0,N37/N33) | ... P71: =IF(P33=0,0,P37/P33)
A72: Net margin | B72: np_margin | D72: 0.21835244 | E72: 0.075908882 | F72: 0.17982173 | G72: =IF(G33=0,0,G47/G33) | H72: =IF(H33=0,0,H47/H33) | I72: =IF(I33=0,0,I47/I33) | J72: =IF(J33=0,0,J47/J33) | K72: =IF(K33=0,0,K47/K33) | L72: =IF(L33=0,0,L47/L33) | M72: =IF(M33=0,0,M47/M33) | N72: =IF(N33=0,0,N47/N33) | ... P72: =IF(P33=0,0,P47/P33)
A73: EPS growth | B73: eps_growth | E73: -0.69524268 | F73: 1.6276544 | G73: =(IF(F49=0,0,G49/F49)-1) | H73: =(IF(G49=0,0,H49/G49)-1) | I73: =(IF(H49=0,0,I49/H49)-1) | J73: =(IF(I49=0,0,J49/I49)-1) | K73: =(IF(J49=0,0,K49/J49)-1) | L73: =(IF(K49=0,0,L49/K49)-1) | M73: =(IF(L49=0,0,M49/L49)-1) | N73: =(IF(M49=0,0,N49/M49)-1) | ... P73: =(IF(O49=0,0,P49/O49)-1)
A74: ROE | B74: roe | E74: 0.04155249 | F74: 0.10125035 | G74: =IF(IF(2=0,0,(G62+F62)/2)=0,0,G47/IF(2=0,0,(G62+F62)/2)) | H74: =IF(IF(2=0,0,(H62+G62)/2)=0,0,H47/IF(2=0,0,(H62+G62)/2)) | I74: =IF(IF(2=0,0,(I62+H62)/2)=0,0,I47/IF(2=0,0,(I62+H62)/2)) | J74: =IF(IF(2=0,0,(J62+I62)/2)=0,0,J47/IF(2=0,0,(J62+I62)/2)) | K74: =IF(IF(2=0,0,(K62+J62)/2)=0,0,K47/IF(2=0,0,(K62+J62)/2)) | L74: =IF(IF(2=0,0,(L62+K62)/2)=0,0,L47/IF(2=0,0,(L62+K62)/2)) | M74: =IF(IF(2=0,0,(M62+L62)/2)=0,0,M47/IF(2=0,0,(M62+L62)/2)) | N74: =IF(IF(2=0,0,(N62+M62)/2)=0,0,N47/IF(2=0,0,(N62+M62)/2)) | ... P74: =IF(IF(2=0,0,(P62+O62)/2)=0,0,P47/IF(2=0,0,(P62+O62)/2))
A75: Net debt / EBITDA | B75: net_debt_ebitda | D75: -0.21103992 | E75: -0.51933137 | F75: -1.4385352 | G75: =IF(G39=0,0,G66/G39) | H75: =IF(H39=0,0,H66/H39) | I75: =IF(I39=0,0,I66/I39) | J75: =IF(J39=0,0,J66/J39) | K75: =IF(K39=0,0,K66/K39) | L75: =IF(L39=0,0,L66/L39) | M75: =IF(M39=0,0,M66/M39) | N75: =IF(N39=0,0,N66/N39) | ... P75: =IF(P39=0,0,P66/P39)
A76: Payout ratio | B76: payout_ratio | D76: 0 | E76: 0 | F76: 0.23584655 | G76: =IF(G49=0,0,G50/G49) | H76: =IF(H49=0,0,H50/H49) | I76: =IF(I49=0,0,I50/I49) | J76: =IF(J49=0,0,J50/J49) | K76: =IF(K49=0,0,K50/K49) | L76: =IF(L49=0,0,L50/L49) | M76: =IF(M49=0,0,M50/M49) | N76: =IF(N49=0,0,N50/N49) | ... P76: =IF(P49=0,0,P50/P49)
A77: Capex / revenue | B77: capex_revenue | D77: 0.0015369216 | E77: 0.0030679246 | F77: 0.0071277234 | G77: =IF(G33=0,0,G52/G33) | H77: =IF(H33=0,0,H52/H33) | I77: =IF(I33=0,0,I52/I33) | J77: =IF(J33=0,0,J52/J33) | K77: =IF(K33=0,0,K52/K33) | L77: =IF(L33=0,0,L52/L33) | M77: =IF(M33=0,0,M52/M33) | N77: =IF(N33=0,0,N52/N33) | ... P77: =IF(P33=0,0,P52/P33)
A79: VALUATION
A80: Last price (IDR) | C80: 710
A81: Shares outstanding (m) | C81: 3440.4555
A82: IDR per USD (spot) | C82: 18128
A83: Debt at balance-sheet date | C83: 10.057255
A84: Cash at balance-sheet date | C84: 157.465
A85: Minority interest (book) | C85: 0.030675198
A86: Associates & investments (book) | C86: 0
A87: Post-balance-sheet & other items (sourced, probability-weighted) | C87: 0
A88: Parent equity at balance-sheet date | C88: 639.48752
A89: Per-share factor | C89: 1000
A90: Risk-free rate | C90: =Drivers!$C$9
A91: Less: default spread (IDR only) | C91: =Drivers!$C$11
A92: Mature ERP + Indonesia CRP | C92: =Drivers!$C$12+Drivers!$C$13
A93: Tax rate | C93: =Drivers!$C$15
A94: Unlevered beta (industry default (config)) | C94: 1
A95: Debt / equity (market) | C95: 0.0041172303
A96: Levered beta | C96: =$C$94*(1+(1-$C$93)*$C$95)
A97: Explicit company premium | C97: 0
A98: Cost of equity | C98: =$C$90-$C$91+$C$96*$C$92+$C$97
A99: Pre-tax cost of debt | C99: =$C$90+Drivers!$C$14
A100: WACC | C100: =1/(1+$C$95)*$C$98+$C$95/(1+$C$95)*$C$99*(1-$C$93)
A101: Terminal growth (capped) | C101: 0.03
A103: DCF (FCFF, terminal value)
A104: Share of year after balance-sheet date | G104: 0.503765 | H104: 0.996578 | I104: 0.999316 | J104: 0.996578 | K104: 0.996578 | L104: 0.996578 | M104: 0.999316 | N104: 0.996578 | O104: 0.996578 | P104: 0.996578
A105: Discount time from valuation date (years) | G105: 0 | H105: 0.670773 | I105: 1.670089 | J105: 2.672142 | K105: 3.671458 | L105: 4.670773 | M105: 5.670089 | N105: 6.672142 | O105: 7.671458 | P105: 8.670773
A106: Discount factor | G106: =1/(1+$C$100)^G105 | H106: =1/(1+$C$100)^H105 | I106: =1/(1+$C$100)^I105 | J106: =1/(1+$C$100)^J105 | K106: =1/(1+$C$100)^K105 | L106: =1/(1+$C$100)^L105 | M106: =1/(1+$C$100)^M105 | N106: =1/(1+$C$100)^N105 | ... P106: =1/(1+$C$100)^P105
...

Sheet DWGL
A1: PT Dwi Guna Laksana Tbk (DWGL.JK) — Coal distribution, trading & logistics
A2: Units: IDR bn; per-share in IDR unless marked IDR. Model asof 2026-10-30 · data 2026-10-30
A4: Line | C4: Scalar | D4: FY2022A | E4: FY2023A | F4: FY2024A | G4: FY2025A | H4: FY2026E | I4: FY2027E | J4: FY2028E | K4: FY2029E | L4: FY2030E | M4: FY2031E | N4: FY2032E | O4: FY2033E | P4: FY2034E | Q4: FY2035E
A6: PARAMETERS
A7: horizon | C7: 10
A8: ps_factor | C8: 1000
A9: vp_factor | C9: 1
A11: INPUTS (company assumptions)
A12: Revenue growth | B12: a.revenue_growth | H12: 0.05 | I12: 0.04 | J12: 0.03 | K12: 0.03 | L12: 0.03 | M12: 0.03 | N12: 0.03 | O12: 0.03 | P12: 0.03 | Q12: 0.03
A13: Gross margin at base input costs | B13: a.gross_margin | H13: 0.1164 | I13: 0.1164 | J13: 0.1164 | K13: 0.1164 | L13: 0.1164 | M13: 0.1164 | N13: 0.1164 | O13: 0.1164 | P13: 0.1164 | Q13: 0.1164
A14: Cost link 1: share of COGS exposed | B14: a.link1_share | C14: 0.837
A15: Cost link 1: pass-through to prices | B15: a.link1_pass | C15: 0.9
A16: Cost link 2: share of COGS exposed | B16: a.link2_share | C16: 0.04
A17: Cost link 2: pass-through to prices | B17: a.link2_pass | C17: 0.6
A18: SG&A / revenue | B18: a.opex_pct | H18: 0.0172 | I18: 0.0172 | J18: 0.0172 | K18: 0.0172 | L18: 0.0172 | M18: 0.0172 | N18: 0.0172 | O18: 0.0172 | P18: 0.0172 | Q18: 0.0172
A19: D&A / revenue | B19: a.da_pct | H19: 0.00091 | I19: 0.00091 | J19: 0.00091 | K19: 0.00091 | L19: 0.00091 | M19: 0.00091 | N19: 0.00091 | O19: 0.00091 | P19: 0.00091 | Q19: 0.00091
A20: Capex / revenue | B20: a.capex_pct | H20: 0.00029 | I20: 0.00029 | J20: 0.00029 | K20: 0.00029 | L20: 0.00029 | M20: 0.00029 | N20: 0.00029 | O20: 0.00029 | P20: 0.00029 | Q20: 0.00029
A21: Operating working capital / revenue | B21: a.nwc_pct | H21: -0.0903 | I21: -0.0903 | J21: -0.0903 | K21: -0.0903 | L21: -0.0903 | M21: -0.0903 | N21: -0.0903 | O21: -0.0903 | P21: -0.0903 | Q21: -0.0903
A22: Effective tax rate | B22: a.tax_rate | H22: 0.206 | I22: 0.206 | J22: 0.206 | K22: 0.206 | L22: 0.206 | M22: 0.206 | N22: 0.206 | O22: 0.206 | P22: 0.206 | Q22: 0.206
A23: Cost of debt (on opening debt) | B23: a.cost_of_debt | C23: 0.1
A24: Yield on opening cash | B24: a.cash_yield | C24: 0.0025
A25: Net new borrowing | B25: a.net_borrowing | H25: 0 | I25: 0 | J25: 0 | K25: 0 | L25: 0 | M25: 0 | N25: 0 | O25: 0 | P25: 0 | Q25: 0
A26: Other non-operating items | B26: a.other_nonop | H26: 0 | I26: 0 | J26: 0 | K26: 0 | L26: 0 | M26: 0 | N26: 0 | O26: 0 | P26: 0 | Q26: 0
A27: Minorities' share of net profit | B27: a.minority_pct | H27: 0 | I27: 0 | J27: 0 | K27: 0 | L27: 0 | M27: 0 | N27: 0 | O27: 0 | P27: 0 | Q27: 0
A28: Dividend payout | B28: a.payout | H28: 0 | I28: 0 | J28: 0 | K28: 0 | L28: 0 | M28: 0 | N28: 0 | O28: 0 | P28: 0 | Q28: 0
A29: Change in share count | B29: a.share_change | H29: 0 | I29: 0 | J29: 0 | K29: 0 | L29: 0 | M29: 0 | N29: 0 | O29: 0 | P29: 0 | Q29: 0
A30: Terminal growth (DCF) | B30: a.terminal_growth | C30: 0.04
A32: MODEL
A33: Revenue | B33: revenue | D33: 2784.8964 | E33: 3261.1837 | F33: 3337.3 | G33: 3496.8 | H33: =(G33*(1+H12)) | I33: =(H33*(1+I12)) | J33: =(I33*(1+J12)) | K33: =(J33*(1+K12)) | L33: =(K33*(1+L12)) | M33: =(L33*(1+M12)) | N33: =(M33*(1+N12)) | O33: =(N33*(1+O12)) | ... Q33: =(P33*(1+Q12))
A34: Cost of revenue | B34: cogs | D34: 2641.6019 | E34: 2991.658 | F34: 3014.5275 | G34: 3089.8009 | H34: =((H33*(1-H13))*((1+(($C$14*(1-$C$15))*(IF(Drivers!$G$4=0,0,Drivers!$H$4/Drivers!$G$4)-1)))+(($C$16*(1-$C$17))*(IF(Drivers!$G$6=0,0,Drivers!$H$6/Drivers!$G$6)-1)))) | I34: =((I33*(1-I13))*((1+(($C$14*(1-$C$15))*(IF(Drivers!$G$4=0,0,Drivers!$I$4/Drivers!$G$4)-1)))+(($C$16*(1-$C$17))*(IF(Drivers!$G$6=0,0,Drivers!$I$6/Drivers!$G$6)-1)))) | J34: =((J33*(1-J13))*((1+(($C$14*(1-$C$15))*(IF(Drivers!$G$4=0,0,Drivers!$J$4/Drivers!$G$4)-1)))+(($C$16*(1-$C$17))*(IF(Drivers!$G$6=0,0,Drivers!$J$6/Drivers!$G$6)-1)))) | K34: =((K33*(1-K13))*((1+(($C$14*(1-$C$15))*(IF(Drivers!$G$4=0,0,Drivers!$K$4/Drivers!$G$4)-1)))+(($C$16*(1-$C$17))*(IF(Drivers!$G$6=0,0,Drivers!$K$6/Drivers!$G$6)-1)))) | L34: =((L33*(1-L13))*((1+(($C$14*(1-$C$15))*(IF(Drivers!$G$4=0,0,Drivers!$L$4/Drivers!$G$4)-1)))+(($C$16*(1-$C$17))*(IF(Drivers!$G$6=0,0,Drivers!$L$6/Drivers!$G$6)-1)))) | M34: =((M33*(1-M13))*((1+(($C$14*(1-$C$15))*(IF(Drivers!$G$4=0,0,Drivers!$M$4/Drivers!$G$4)-1)))+(($C$16*(1-$C$17))*(IF(Drivers!$G$6=0,0,Drivers!$M$6/Drivers!$G$6)-1)))) | N34: =((N33*(1-N13))*((1+(($C$14*(1-$C$15))*(IF(Drivers!$G$4=0,0,Drivers!$N$4/Drivers!$G$4)-1)))+(($C$16*(1-$C$17))*(IF(Drivers!$G$6=0,0,Drivers!$N$6/Drivers!$G$6)-1)))) | O34: =((O33*(1-O13))*((1+(($C$14*(1-$C$15))*(IF(Drivers!$G$4=0,0,Drivers!$O$4/Drivers!$G$4)-1)))+(($C$16*(1-$C$17))*(IF(Drivers!$G$6=0,0,Drivers!$O$6/Drivers!$G$6)-1)))) | P34: =((P33*(1-P13))*((1+(($C$14*(1-$C$15))*(IF(Drivers!$G$4=0,0,Drivers!$P$4/Drivers!$G$4)-1)))+(($C$16*(1-$C$17))*(IF(Drivers!$G$6=0,0,Drivers!$P$6/Drivers!$G$6)-1)))) | Q34: =((Q33*(1-Q13))*((1+(($C$14*(1-$C$15))*(IF(Drivers!$G$4=0,0,Drivers!$Q$4/Drivers!$G$4)-1)))+(($C$16*(1-$C$17))*(IF(Drivers!$G$6=0,0,Drivers!$Q$6/Drivers!$G$6)-1))))
A35: Gross profit | B35: gross_profit | D35: 143.29443 | E35: 269.52575 | F35: 322.7444 | G35: 406.99546 | H35: =(H33-H34) | I35: =(I33-I34) | J35: =(J33-J34) | K35: =(K33-K34) | L35: =(L33-L34) | M35: =(M33-M34) | N35: =(N33-N34) | O35: =(O33-O34) | ... Q35: =(Q33-Q34)
A36: SG&A and other opex | B36: opex | D36: 83.77059 | E36: 95.948046 | F36: 82.256693 | G36: 58.925801 | H36: =(H33*H18) | I36: =(I33*I18) | J36: =(J33*J18) | K36: =(K33*K18) | L36: =(L33*L18) | M36: =(M33*M18) | N36: =(N33*N18) | O36: =(O33*O18) | ... Q36: =(Q33*Q18)
A37: EBIT | B37: ebit | D37: 59.523845 | E37: 173.57771 | F37: 240.48771 | G37: 348.06966 | H37: =(H35-H36) | I37: =(I35-I36) | J37: =(J35-J36) | K37: =(K35-K36) | L37: =(L35-L36) | M37: =(M35-M36) | N37: =(N35-N36) | O37: =(O35-O36) | ... Q37: =(Q35-Q36)
A38: Depreciation & amortisation | B38: da | D38: 1.545242 | E38: 1.622245 | F38: 1.308549 | G38: 3.121606 | H38: =(H33*H19) | I38: =(I33*I19) | J38: =(J33*J19) | K38: =(K33*K19) | L38: =(L33*L19) | M38: =(M33*M19) | N38: =(N33*N19) | O38: =(O33*O19) | ... Q38: =(Q33*Q19)
A39: EBITDA | B39: ebitda | D39: 61.069087 | E39: 175.19995 | F39: 241.79626 | G39: 351.19126 | H39: =(H37+H38) | I39: =(I37+I38) | J39: =(J37+J38) | K39: =(K37+K38) | L39: =(L37+L38) | M39: =(M37+M38) | N39: =(N37+N38) | O39: =(O37+O38) | ... Q39: =(Q37+Q38)
A40: Interest expense | B40: interest_expense | D40: 47.575361 | E40: 51.684894 | F40: 43.776619 | G40: 49.736655 | H40: =(G60*$C$23) | I40: =(H60*$C$23) | J40: =(I60*$C$23) | K40: =(J60*$C$23) | L40: =(K60*$C$23) | M40: =(L60*$C$23) | N40: =(M60*$C$23) | O40: =(N60*$C$23) | ... Q40: =(P60*$C$23)
A41: Interest income | B41: interest_income | D41: 1.686313 | E41: 1.638996 | F41: 2.022456 | G41: 1.447515 | H41: =(G59*$C$24) | I41: =(H59*$C$24) | J41: =(I59*$C$24) | K41: =(J59*$C$24) | L41: =(K59*$C$24) | M41: =(L59*$C$24) | N41: =(M59*$C$24) | O41: =(N59*$C$24) | ... Q41: =(P59*$C$24)
A42: Other non-operating | B42: other_nonop | D42: 3.301112 | E42: -100.02209 | F42: -48.879251 | G42: -16.693275 | H42: =H26 | I42: =I26 | J42: =J26 | K42: =K26 | L42: =L26 | M42: =M26 | N42: =N26 | O42: =O26 | ... Q42: =Q26
A43: Profit before tax | B43: pbt | D43: 16.935909 | E43: 23.509724 | F43: 149.85429 | G43: 283.08724 | H43: =(((H37-H40)+H41)+H42) | I43: =(((I37-I40)+I41)+I42) | J43: =(((J37-J40)+J41)+J42) | K43: =(((K37-K40)+K41)+K42) | L43: =(((L37-L40)+L41)+L42) | M43: =(((M37-M40)+M41)+M42) | N43: =(((N37-N40)+N41)+N42) | O43: =(((O37-O40)+O41)+O42) | ... Q43: =(((Q37-Q40)+Q41)+Q42)
A44: Tax | B44: tax | D44: 13.535751 | E44: 7.872249 | F44: 31.439482 | G44: 58.413094 | H44: =(MAX(H43,0)*H22) | I44: =(MAX(I43,0)*I22) | J44: =(MAX(J43,0)*J22) | K44: =(MAX(K43,0)*K22) | L44: =(MAX(L43,0)*L22) | M44: =(MAX(M43,0)*M22) | N44: =(MAX(N43,0)*N22) | O44: =(MAX(O43,0)*O22) | ... Q44: =(MAX(Q43,0)*Q22)
A45: Net profit (incl. minorities) | B45: np | D45: 3.400158 | E45: 15.637475 | F45: 118.41481 | G45: 224.67415 | H45: =(H43-H44) | I45: =(I43-I44) | J45: =(J43-J44) | K45: =(K43-K44) | L45: =(L43-L44) | M45: =(M43-M44) | N45: =(N43-N44) | O45: =(O43-O44) | ... Q45: =(Q43-Q44)
A46: Minority interests | B46: minority | D46: 1e-06 | E46: 3e-06 | F46: 2e-06 | G46: 5e-06 | H46: =(H45*H27) | I46: =(I45*I27) | J46: =(J45*J27) | K46: =(K45*K27) | L46: =(L45*L27) | M46: =(M45*M27) | N46: =(N45*N27) | O46: =(O45*O27) | ... Q46: =(Q45*Q27)
A47: Net profit to parent | B47: np_parent | D47: 3.400157 | E47: 15.637472 | F47: 118.41481 | G47: 224.67414 | H47: =(H45-H46) | I47: =(I45-I46) | J47: =(J45-J46) | K47: =(K45-K46) | L47: =(L45-L46) | M47: =(M45-M46) | N47: =(N45-N46) | O47: =(O45-O46) | ... Q47: =(Q45-Q46)
A48: Shares outstanding (m) | B48: shares | D48: 9252.821 | E48: 9252.821 | F48: 9252.821 | G48: 9252.821 | H48: =(G48*(1+H29)) | I48: =(H48*(1+I29)) | J48: =(I48*(1+J29)) | K48: =(J48*(1+K29)) | L48: =(K48*(1+L29)) | M48: =(L48*(1+M29)) | N48: =(M48*(1+N29)) | O48: =(N48*(1+O29)) | ... Q48: =(P48*(1+Q29))
A49: EPS | B49: eps | D49: 0.36747247 | E49: 1.6900221 | F49: 12.797698 | G49: 24.281691 | H49: =(IF(H48=0,0,H47/H48)*$C$8) | I49: =(IF(I48=0,0,I47/I48)*$C$8) | J49: =(IF(J48=0,0,J47/J48)*$C$8) | K49: =(IF(K48=0,0,K47/K48)*$C$8) | L49: =(IF(L48=0,0,L47/L48)*$C$8) | M49: =(IF(M48=0,0,M47/M48)*$C$8) | N49: =(IF(N48=0,0,N47/N48)*$C$8) | O49: =(IF(O48=0,0,O47/O48)*$C$8) | ... Q49: =(IF(Q48=0,0,Q47/Q48)*$C$8)
A50: DPS (declared on the year) | B50: dps | D50: 0 | E50: 0 | F50: 0 | G50: 0 | H50: =(MAX(H49,0)*H28) | I50: =(MAX(I49,0)*I28) | J50: =(MAX(J49,0)*J28) | K50: =(MAX(K49,0)*K28) | L50: =(MAX(L49,0)*L28) | M50: =(MAX(M49,0)*M28) | N50: =(MAX(N49,0)*N28) | O50: =(MAX(O49,0)*O28) | ... Q50: =(MAX(Q49,0)*Q28)
A51: Dividends paid | B51: dividends_paid | H51: =IF($C$8=0,0,(G50*G48)/$C$8) | I51: =IF($C$8=0,0,(H50*H48)/$C$8) | J51: =IF($C$8=0,0,(I50*I48)/$C$8) | K51: =IF($C$8=0,0,(J50*J48)/$C$8) | L51: =IF($C$8=0,0,(K50*K48)/$C$8) | M51: =IF($C$8=0,0,(L50*L48)/$C$8) | N51: =IF($C$8=0,0,(M50*M48)/$C$8) | O51: =IF($C$8=0,0,(N50*N48)/$C$8) | ... Q51: =IF($C$8=0,0,(P50*P48)/$C$8)
A52: Capital expenditure | B52: capex | D52: 0.299255 | E52: 0.382387 | F52: 0.57413 | G52: 1.018786 | H52: =(H33*H20) | I52: =(I33*I20) | J52: =(J33*J20) | K52: =(K33*K20) | L52: =(L33*L20) | M52: =(M33*M20) | N52: =(N33*N20) | O52: =(O33*O20) | ... Q52: =(Q33*Q20)
A53: Change in working capital | B53: delta_nwc | E53: -1.895479 | F53: -16.523637 | G53: 40.898379 | H53: =(H58-G58) | I53: =(I58-H58) | J53: =(J58-I58) | K53: =(K58-J58) | L53: =(L58-K58) | M53: =(M58-L58) | N53: =(N58-M58) | O53: =(O58-N58) | ... Q53: =(Q58-P58)
A54: Free cash flow to firm | B54: fcff | E54: 118.59042 | F54: 207.29136 | G54: 237.45233 | H54: =((((H37*(1-H22))+H38)-H52)-H53) | I54: =((((I37*(1-I22))+I38)-I52)-I53) | J54: =((((J37*(1-J22))+J38)-J52)-J53) | K54: =((((K37*(1-K22))+K38)-K52)-K53) | L54: =((((L37*(1-L22))+L38)-L52)-L53) | M54: =((((M37*(1-M22))+M38)-M52)-M53) | N54: =((((N37*(1-N22))+N38)-N52)-N53) | O54: =((((O37*(1-O22))+O38)-O52)-O53) | ... Q54: =((((Q37*(1-Q22))+Q38)-Q52)-Q53)
A55: Net borrowing | B55: net_borrowing | E55: -56.848806 | F55: -53.915124 | G55: 118.94822 | H55: =H25 | I55: =I25 | J55: =J25 | K55: =K25 | L55: =L25 | M55: =M25 | N55: =N25 | O55: =O25 | ... Q55: =Q25
A56: Dividends to minorities | B56: minority_div | H56: =(MAX(G46,0)*H28) | I56: =(MAX(H46,0)*I28) | J56: =(MAX(I46,0)*J28) | K56: =(MAX(J46,0)*K28) | L56: =(MAX(K46,0)*L28) | M56: =(MAX(L46,0)*M28) | N56: =(MAX(M46,0)*N28) | O56: =(MAX(N46,0)*O28) | ... Q56: =(MAX(P46,0)*Q28)
A57: Free cash flow to equity | B57: fcfe | H57: =(((((H45+H38)-H52)-H53)+H55)-H56) | I57: =(((((I45+I38)-I52)-I53)+I55)-I56) | J57: =(((((J45+J38)-J52)-J53)+J55)-J56) | K57: =(((((K45+K38)-K52)-K53)+K55)-K56) | L57: =(((((L45+L38)-L52)-L53)+L55)-L56) | M57: =(((((M45+M38)-M52)-M53)+M55)-M56) | N57: =(((((N45+N38)-N52)-N53)+N55)-N56) | O57: =(((((O45+O38)-O52)-O53)+O55)-O56) | ... Q57: =(((((Q45+Q38)-Q52)-Q53)+Q55)-Q56)
A58: Operating working capital | B58: nwc | D58: -303.90768 | E58: -305.80316 | F58: -322.3268 | G58: -281.42842 | H58: =(H33*H21) | I58: =(I33*I21) | J58: =(J33*J21) | K58: =(K33*K21) | L58: =(L33*L21) | M58: =(M33*M21) | N58: =(N33*N21) | O58: =(O33*O21) | ... Q58: =(Q33*Q21)
A59: Cash & equivalents | B59: cash | D59: 332.23258 | E59: 402.8066 | F59: 542.27553 | G59: 491.18516 | H59: =(((((((G59+H45)+H38)-H52)-H53)+H55)-H51)-H56) | I59: =(((((((H59+I45)+I38)-I52)-I53)+I55)-I51)-I56) | J59: =(((((((I59+J45)+J38)-J52)-J53)+J55)-J51)-J56) | K59: =(((((((J59+K45)+K38)-K52)-K53)+K55)-K51)-K56) | L59: =(((((((K59+L45)+L38)-L52)-L53)+L55)-L51)-L56) | M59: =(((((((L59+M45)+M38)-M52)-M53)+M55)-M51)-M56) | N59: =(((((((M59+N45)+N38)-N52)-N53)+N55)-N51)-N56) | O59: =(((((((N59+O45)+O38)-O52)-O53)+O55)-O51)-O56) | ... Q59: =(((((((P59+Q45)+Q38)-Q52)-Q53)+Q55)-Q51)-Q56)
A60: Total debt | B60: debt | D60: 492.07198 | E60: 435.22317 | F60: 381.30805 | G60: 500.25627 | H60: =(G60+H55) | I60: =(H60+I55) | J60: =(I60+J55) | K60: =(J60+K55) | L60: =(K60+L55) | M60: =(L60+M55) | N60: =(M60+N55) | O60: =(N60+O55) | ... Q60: =(P60+Q55)
A61: Fixed assets (net) | B61: ppe | D61: 12.643678 | E61: 11.33722 | F61: 14.104143 | G61: 16.260683 | H61: =((G61+H52)-H38) | I61: =((H61+I52)-I38) | J61: =((I61+J52)-J38) | K61: =((J61+K52)-K38) | L61: =((K61+L52)-L38) | M61: =((L61+M52)-M38) | N61: =((M61+N52)-N38) | O61: =((N61+O52)-O38) | ... Q61: =((P61+Q52)-Q38)
A62: Parent shareholders' equity | B62: equity | D62: 141.69444 | E62: 156.41533 | F62: 275.05879 | G62: 500.03023 | H62: =((G62+H47)-H51) | I62: =((H62+I47)-I51) | J62: =((I62+J47)-J51) | K62: =((J62+K47)-K51) | L62: =((K62+L47)-L51) | M62: =((L62+M47)-M51) | N62: =((M62+N47)-N51) | O62: =((N62+O47)-O51) | ... Q62: =((P62+Q47)-Q51)
A63: Minority interest (balance sheet) | B63: minority_bs | D63: 8e-06 | E63: 1.1e-05 | F63: 1.3e-05 | G63: 1.8e-05 | H63: =((G63+H46)-H56) | I63: =((H63+I46)-I56) | J63: =((I63+J46)-J56) | K63: =((J63+K46)-K56) | L63: =((K63+L46)-L56) | M63: =((L63+M46)-M56) | N63: =((M63+N46)-N56) | O63: =((N63+O46)-O56) | ... Q63: =((P63+Q46)-Q56)
A64: Other assets less other liabilities | B64: other_net | D64: 592.79785 | E64: 483.29785 | F64: 422.31397 | G64: 774.2691 | H64: =G64 | I64: =H64 | J64: =I64 | K64: =J64 | L64: =K64 | M64: =L64 | N64: =M64 | O64: =N64 | ... Q64: =P64
A65: Balance check (should be zero) | B65: bs_check | H65: =((((((H59+H58)+H61)+H64)-H60)-H62)-H63) | I65: =((((((I59+I58)+I61)+I64)-I60)-I62)-I63) | J65: =((((((J59+J58)+J61)+J64)-J60)-J62)-J63) | K65: =((((((K59+K58)+K61)+K64)-K60)-K62)-K63) | L65: =((((((L59+L58)+L61)+L64)-L60)-L62)-L63) | M65: =((((((M59+M58)+M61)+M64)-M60)-M62)-M63) | N65: =((((((N59+N58)+N61)+N64)-N60)-N62)-N63) | O65: =((((((O59+O58)+O61)+O64)-O60)-O62)-O63) | ... Q65: =((((((Q59+Q58)+Q61)+Q64)-Q60)-Q62)-Q63)
A66: Net debt (cash) | B66: net_debt | D66: 159.8394 | E66: 32.416573 | F66: -160.96749 | G66: 9.071117 | H66: =(H60-H59) | I66: =(I60-I59) | J66: =(J60-J59) | K66: =(K60-K59) | L66: =(L60-L59) | M66: =(M60-M59) | N66: =(N60-N59) | O66: =(O60-O59) | ... Q66: =(Q60-Q59)
A67: Book value per share | B67: bvps | D67: 15.313647 | E67: 16.90461 | F67: 29.72702 | G67: 54.040841 | H67: =(IF(H48=0,0,H62/H48)*$C$8) | I67: =(IF(I48=0,0,I62/I48)*$C$8) | J67: =(IF(J48=0,0,J62/J48)*$C$8) | K67: =(IF(K48=0,0,K62/K48)*$C$8) | L67: =(IF(L48=0,0,L62/L48)*$C$8) | M67: =(IF(M48=0,0,M62/M48)*$C$8) | N67: =(IF(N48=0,0,N62/N48)*$C$8) | O67: =(IF(O48=0,0,O62/O48)*$C$8) | ... Q67: =(IF(Q48=0,0,Q62/Q48)*$C$8)
A68: Revenue growth | B68: revenue_growth | E68: 0.17102516 | F68: 0.023340077 | G68: 0.047793126 | H68: =(IF(G33=0,0,H33/G33)-1) | I68: =(IF(H33=0,0,I33/H33)-1) | J68: =(IF(I33=0,0,J33/I33)-1) | K68: =(IF(J33=0,0,K33/J33)-1) | L68: =(IF(K33=0,0,L33/K33)-1) | M68: =(IF(L33=0,0,M33/L33)-1) | N68: =(IF(M33=0,0,N33/M33)-1) | O68: =(IF(N33=0,0,O33/N33)-1) | ... Q68: =(IF(P33=0,0,Q33/P33)-1)
A69: Gross margin | B69: gross_margin | D69: 0.051454135 | E69: 0.082646602 | F69: 0.096708237 | G69: 0.11639083 | H69: =IF(H33=0,0,H35/H33) | I69: =IF(I33=0,0,I35/I33) | J69: =IF(J33=0,0,J35/J33) | K69: =IF(K33=0,0,K35/K33) | L69: =IF(L33=0,0,L35/L33) | M69: =IF(M33=0,0,M35/M33) | N69: =IF(N33=0,0,N35/N33) | O69: =IF(O33=0,0,O35/O33) | ... Q69: =IF(Q33=0,0,Q35/Q33)
A70: EBITDA margin | B70: ebitda_margin | D70: 0.021928675 | E70: 0.05372281 | F70: 0.072452658 | G70: 0.10043218 | H70: =IF(H33=0,0,H39/H33) | I70: =IF(I33=0,0,I39/I33) | J70: =IF(J33=0,0,J39/J33) | K70: =IF(K33=0,0,K39/K33) | L70: =IF(L33=0,0,L39/L33) | M70: =IF(M33=0,0,M39/M33) | N70: =IF(N33=0,0,N39/N33) | O70: =IF(O33=0,0,O39/O33) | ... Q70: =IF(Q33=0,0,Q39/Q33)
A71: EBIT margin | B71: ebit_margin | D71: 0.02137381 | E71: 0.053225369 | F71: 0.07206056 | G71: 0.099539481 | H71: =IF(H33=0,0,H37/H33) | I71: =IF(I33=0,0,I37/I33) | J71: =IF(J33=0,0,J37/J33) | K71: =IF(K33=0,0,K37/K33) | L71: =IF(L33=0,0,L37/L33) | M71: =IF(M33=0,0,M37/M33) | N71: =IF(N33=0,0,N37/N33) | O71: =IF(O33=0,0,O37/O33) | ... Q71: =IF(Q33=0,0,Q37/Q33)
A72: Net margin | B72: np_margin | D72: 0.0012209277 | E72: 0.0047950295 | F72: 0.035482219 | G72: 0.064251357 | H72: =IF(H33=0,0,H47/H33) | I72: =IF(I33=0,0,I47/I33) | J72: =IF(J33=0,0,J47/J33) | K72: =IF(K33=0,0,K47/K33) | L72: =IF(L33=0,0,L47/L33) | M72: =IF(M33=0,0,M47/M33) | N72: =IF(N33=0,0,N47/N33) | O72: =IF(O33=0,0,O47/O33) | ... Q72: =IF(Q33=0,0,Q47/Q33)
A73: EPS growth | B73: eps_growth | E73: 3.5990441 | F73: 6.5725033 | G73: 0.89734838 | H73: =(IF(G49=0,0,H49/G49)-1) | I73: =(IF(H49=0,0,I49/H49)-1) | J73: =(IF(I49=0,0,J49/I49)-1) | K73: =(IF(J49=0,0,K49/J49)-1) | L73: =(IF(K49=0,0,L49/K49)-1) | M73: =(IF(L49=0,0,M49/L49)-1) | N73: =(IF(M49=0,0,N49/M49)-1) | O73: =(IF(N49=0,0,O49/N49)-1) | ... Q73: =(IF(P49=0,0,Q49/P49)-1)
A74: ROE | B74: roe | E74: 0.10491083 | F74: 0.54888487 | G74: 0.57973765 | H74: =IF(IF(2=0,0,(H62+G62)/2)=0,0,H47/IF(2=0,0,(H62+G62)/2)) | I74: =IF(IF(2=0,0,(I62+H62)/2)=0,0,I47/IF(2=0,0,(I62+H62)/2)) | J74: =IF(IF(2=0,0,(J62+I62)/2)=0,0,J47/IF(2=0,0,(J62+I62)/2)) | K74: =IF(IF(2=0,0,(K62+J62)/2)=0,0,K47/IF(2=0,0,(K62+J62)/2)) | L74: =IF(IF(2=0,0,(L62+K62)/2)=0,0,L47/IF(2=0,0,(L62+K62)/2)) | M74: =IF(IF(2=0,0,(M62+L62)/2)=0,0,M47/IF(2=0,0,(M62+L62)/2)) | N74: =IF(IF(2=0,0,(N62+M62)/2)=0,0,N47/IF(2=0,0,(N62+M62)/2)) | O74: =IF(IF(2=0,0,(O62+N62)/2)=0,0,O47/IF(2=0,0,(O62+N62)/2)) | ... Q74: =IF(IF(2=0,0,(Q62+P62)/2)=0,0,Q47/IF(2=0,0,(Q62+P62)/2))
A75: Net debt / EBITDA | B75: net_debt_ebitda | D75: 2.6173537 | E75: 0.18502615 | F75: -0.66571538 | G75: 0.025829563 | H75: =IF(H39=0,0,H66/H39) | I75: =IF(I39=0,0,I66/I39) | J75: =IF(J39=0,0,J66/J39) | K75: =IF(K39=0,0,K66/K39) | L75: =IF(L39=0,0,L66/L39) | M75: =IF(M39=0,0,M66/M39) | N75: =IF(N39=0,0,N66/N39) | O75: =IF(O39=0,0,O66/O39) | ... Q75: =IF(Q39=0,0,Q66/Q39)
A76: Payout ratio | B76: payout_ratio | D76: 0 | E76: 0 | F76: 0 | G76: 0 | H76: =IF(H49=0,0,H50/H49) | I76: =IF(I49=0,0,I50/I49) | J76: =IF(J49=0,0,J50/J49) | K76: =IF(K49=0,0,K50/K49) | L76: =IF(L49=0,0,L50/L49) | M76: =IF(M49=0,0,M50/M49) | N76: =IF(N49=0,0,N50/N49) | O76: =IF(O49=0,0,O50/O49) | ... Q76: =IF(Q49=0,0,Q50/Q49)
A77: Capex / revenue | B77: capex_revenue | D77: 0.00010745642 | E77: 0.00011725405 | F77: 0.00017203428 | G77: 0.00029134809 | H77: =IF(H33=0,0,H52/H33) | I77: =IF(I33=0,0,I52/I33) | J77: =IF(J33=0,0,J52/J33) | K77: =IF(K33=0,0,K52/K33) | L77: =IF(L33=0,0,L52/L33) | M77: =IF(M33=0,0,M52/M33) | N77: =IF(N33=0,0,N52/N33) | O77: =IF(O33=0,0,O52/O33) | ... Q77: =IF(Q33=0,0,Q52/Q33)
A79: VALUATION
A80: Last price (IDR) | C80: 161
A81: Shares outstanding (m) | C81: 9252.821
A82: IDR per USD (spot) | C82: 18128
A83: Debt at balance-sheet date | C83: 299.46915
A84: Cash at balance-sheet date | C84: 636.16324
A85: Minority interest (book) | C85: 2.4e-05
A86: Associates & investments (book) | C86: 86.481318
A87: Post-balance-sheet & other items (sourced, probability-weighted) | C87: 0
A88: Parent equity at balance-sheet date | C88: 597.84075
A89: Per-share factor | C89: 1000
A90: Risk-free rate | C90: =Drivers!$C$9
A91: Less: default spread (IDR only) | C91: =Drivers!$C$11
A92: Mature ERP + Indonesia CRP | C92: =Drivers!$C$12+Drivers!$C$13
A93: Tax rate | C93: =Drivers!$C$15
A94: Unlevered beta (industry default (config)) | C94: 1
A95: Debt / equity (market) | C95: 0.20102592
A96: Levered beta | C96: =$C$94*(1+(1-$C$93)*$C$95)
A97: Explicit company premium | C97: 0
A98: Cost of equity | C98: =$C$90-$C$91+$C$96*$C$92+$C$97
A99: Pre-tax cost of debt | C99: =$C$90+Drivers!$C$14
A100: WACC | C100: =1/(1+$C$95)*$C$98+$C$95/(1+$C$95)*$C$99*(1-$C$93)
A101: Terminal growth (capped) | C101: 0.04
A103: DCF (FCFF, terminal value)
A104: Share of year after balance-sheet date | H104: 0.503765 | I104: 0.996578 | J104: 0.999316 | K104: 0.996578 | L104: 0.996578 | M104: 0.996578 | N104: 0.999316 | O104: 0.996578 | P104: 0.996578 | Q104: 0.996578
A105: Discount time from valuation date (years) | H105: 0 | I105: 0.670773 | J105: 1.670089 | K105: 2.672142 | L105: 3.671458 | M105: 4.670773 | N105: 5.670089 | O105: 6.672142 | P105: 7.671458 | Q105: 8.670773
A106: Discount factor | H106: =1/(1+$C$100)^H105 | I106: =1/(1+$C$100)^I105 | J106: =1/(1+$C$100)^J105 | K106: =1/(1+$C$100)^K105 | L106: =1/(1+$C$100)^L105 | M106: =1/(1+$C$100)^M105 | N106: =1/(1+$C$100)^N105 | O106: =1/(1+$C$100)^O105 | ... Q106: =1/(1+$C$100)^Q105
...

Sheet FIRE
A1: PT Alfa Energi Investama Tbk (FIRE.JK) — Coal distribution, trading & logistics
A2: Units: IDR bn; per-share in IDR unless marked IDR. Model asof 2026-10-30 · data 2026-10-30
A4: Line | C4: Scalar | D4: FY2022A | E4: FY2023A | F4: FY2024A | G4: FY2025A | H4: FY2026E | I4: FY2027E | J4: FY2028E | K4: FY2029E | L4: FY2030E | M4: FY2031E | N4: FY2032E | O4: FY2033E | P4: FY2034E | Q4: FY2035E
A6: PARAMETERS
A7: horizon | C7: 10
A8: ps_factor | C8: 1000
A9: vp_factor | C9: 1e-06
A11: INPUTS (company assumptions)
A12: Volume | B12: a.volume | H12: 400 | I12: 400 | J12: 400 | K12: 400 | L12: 400 | M12: 400 | N12: 400 | O12: 400 | P12: 400 | Q12: 400
A13: Average price | B13: a.price | H13: 830376 | I13: 851135 | J13: 872414 | K13: 894224 | L13: 916580 | M13: 939494 | N13: 962982 | O13: 987056 | P13: 1011733 | Q13: 1037026
A14: Gross margin at base input costs | B14: a.gross_margin | H14: 0.214 | I14: 0.214 | J14: 0.214 | K14: 0.214 | L14: 0.214 | M14: 0.214 | N14: 0.214 | O14: 0.214 | P14: 0.214 | Q14: 0.214
A15: Cost link 1: share of COGS exposed | B15: a.link1_share | C15: 0.15
A16: Cost link 1: pass-through to prices | B16: a.link1_pass | C16: 0.8
A17: Cost link 2: share of COGS exposed | B17: a.link2_share | C17: 0.15
A18: Cost link 2: pass-through to prices | B18: a.link2_pass | C18: 0.5
A19: SG&A / revenue | B19: a.opex_pct | H19: 0.138 | I19: 0.138 | J19: 0.138 | K19: 0.138 | L19: 0.138 | M19: 0.138 | N19: 0.138 | O19: 0.138 | P19: 0.138 | Q19: 0.138
A20: D&A / revenue | B20: a.da_pct | H20: 0.035 | I20: 0.035 | J20: 0.035 | K20: 0.035 | L20: 0.035 | M20: 0.035 | N20: 0.035 | O20: 0.035 | P20: 0.035 | Q20: 0.035
A21: Capex / revenue | B21: a.capex_pct | H21: 0.015 | I21: 0.015 | J21: 0.015 | K21: 0.015 | L21: 0.015 | M21: 0.015 | N21: 0.015 | O21: 0.015 | P21: 0.015 | Q21: 0.015
A22: Operating working capital / revenue | B22: a.nwc_pct | H22: -0.06 | I22: -0.06 | J22: -0.06 | K22: -0.06 | L22: -0.06 | M22: -0.06 | N22: -0.06 | O22: -0.06 | P22: -0.06 | Q22: -0.06
A23: Effective tax rate | B23: a.tax_rate | H23: 0.22 | I23: 0.22 | J23: 0.22 | K23: 0.22 | L23: 0.22 | M23: 0.22 | N23: 0.22 | O23: 0.22 | P23: 0.22 | Q23: 0.22
A24: Cost of debt (on opening debt) | B24: a.cost_of_debt | C24: 0.095
A25: Yield on opening cash | B25: a.cash_yield | C25: 0.025
A26: Net new borrowing | B26: a.net_borrowing | H26: 0 | I26: 0 | J26: 0 | K26: 0 | L26: 0 | M26: 0 | N26: 0 | O26: 0 | P26: 0 | Q26: 0
A27: Other non-operating items | B27: a.other_nonop | H27: 0 | I27: 0 | J27: 0 | K27: 0 | L27: 0 | M27: 0 | N27: 0 | O27: 0 | P27: 0 | Q27: 0
A28: Minorities' share of net profit | B28: a.minority_pct | H28: 0.01 | I28: 0.01 | J28: 0.01 | K28: 0.01 | L28: 0.01 | M28: 0.01 | N28: 0.01 | O28: 0.01 | P28: 0.01 | Q28: 0.01
A29: Dividend payout | B29: a.payout | H29: 0 | I29: 0 | J29: 0 | K29: 0 | L29: 0 | M29: 0 | N29: 0 | O29: 0 | P29: 0 | Q29: 0
A30: Change in share count | B30: a.share_change | H30: 0 | I30: 0 | J30: 0 | K30: 0 | L30: 0 | M30: 0 | N30: 0 | O30: 0 | P30: 0 | Q30: 0
A31: Terminal growth (DCF) | B31: a.terminal_growth | C31: 0.03
A33: MODEL
A34: Volume | B34: volume | F34: 556.995 | G34: 375.167 | H34: =H12 | I34: =I12 | J34: =J12 | K34: =K12 | L34: =L12 | M34: =M12 | N34: =N12 | O34: =O12 | ... Q34: =Q12
A35: Average price | B35: price | H35: =H13 | I35: =I13 | J35: =J13 | K35: =K13 | L35: =L13 | M35: =M13 | N35: =N13 | O35: =O13 | ... Q35: =Q13
A36: Revenue | B36: revenue | D36: 250.18171 | E36: 264.36448 | F36: 473.5021 | G36: 311.5296 | H36: =((H12*H13)*$C$9) | I36: =((I12*I13)*$C$9) | J36: =((J12*J13)*$C$9) | K36: =((K12*K13)*$C$9) | L36: =((L12*L13)*$C$9) | M36: =((M12*M13)*$C$9) | N36: =((N12*N13)*$C$9) | O36: =((O12*O13)*$C$9) | ... Q36: =((Q12*Q13)*$C$9)
A37: Cost of revenue | B37: cogs | D37: 191.71121 | E37: 194.72102 | F37: 338.2158 | G37: 252.5344 | H37: =((H36*(1-H14))*((1+(($C$15*(1-$C$16))*(IF(Drivers!$G$4=0,0,Drivers!$H$4/Drivers!$G$4)-1)))+(($C$17*(1-$C$18))*(IF(Drivers!$G$6=0,0,Drivers!$H$6/Drivers!$G$6)-1)))) | I37: =((I36*(1-I14))*((1+(($C$15*(1-$C$16))*(IF(Drivers!$G$4=0,0,Drivers!$I$4/Drivers!$G$4)-1)))+(($C$17*(1-$C$18))*(IF(Drivers!$G$6=0,0,Drivers!$I$6/Drivers!$G$6)-1)))) | J37: =((J36*(1-J14))*((1+(($C$15*(1-$C$16))*(IF(Drivers!$G$4=0,0,Drivers!$J$4/Drivers!$G$4)-1)))+(($C$17*(1-$C$18))*(IF(Drivers!$G$6=0,0,Drivers!$J$6/Drivers!$G$6)-1)))) | K37: =((K36*(1-K14))*((1+(($C$15*(1-$C$16))*(IF(Drivers!$G$4=0,0,Drivers!$K$4/Drivers!$G$4)-1)))+(($C$17*(1-$C$18))*(IF(Drivers!$G$6=0,0,Drivers!$K$6/Drivers!$G$6)-1)))) | L37: =((L36*(1-L14))*((1+(($C$15*(1-$C$16))*(IF(Drivers!$G$4=0,0,Drivers!$L$4/Drivers!$G$4)-1)))+(($C$17*(1-$C$18))*(IF(Drivers!$G$6=0,0,Drivers!$L$6/Drivers!$G$6)-1)))) | M37: =((M36*(1-M14))*((1+(($C$15*(1-$C$16))*(IF(Drivers!$G$4=0,0,Drivers!$M$4/Drivers!$G$4)-1)))+(($C$17*(1-$C$18))*(IF(Drivers!$G$6=0,0,Drivers!$M$6/Drivers!$G$6)-1)))) | N37: =((N36*(1-N14))*((1+(($C$15*(1-$C$16))*(IF(Drivers!$G$4=0,0,Drivers!$N$4/Drivers!$G$4)-1)))+(($C$17*(1-$C$18))*(IF(Drivers!$G$6=0,0,Drivers!$N$6/Drivers!$G$6)-1)))) | O37: =((O36*(1-O14))*((1+(($C$15*(1-$C$16))*(IF(Drivers!$G$4=0,0,Drivers!$O$4/Drivers!$G$4)-1)))+(($C$17*(1-$C$18))*(IF(Drivers!$G$6=0,0,Drivers!$O$6/Drivers!$G$6)-1)))) | P37: =((P36*(1-P14))*((1+(($C$15*(1-$C$16))*(IF(Drivers!$G$4=0,0,Drivers!$P$4/Drivers!$G$4)-1)))+(($C$17*(1-$C$18))*(IF(Drivers!$G$6=0,0,Drivers!$P$6/Drivers!$G$6)-1)))) | Q37: =((Q36*(1-Q14))*((1+(($C$15*(1-$C$16))*(IF(Drivers!$G$4=0,0,Drivers!$Q$4/Drivers!$G$4)-1)))+(($C$17*(1-$C$18))*(IF(Drivers!$G$6=0,0,Drivers!$Q$6/Drivers!$G$6)-1))))
A38: Gross profit | B38: gross_profit | D38: 58.470498 | E38: 69.643457 | F38: 135.28635 | G38: 58.995224 | H38: =(H36-H37) | I38: =(I36-I37) | J38: =(J36-J37) | K38: =(K36-K37) | L38: =(L36-L37) | M38: =(M36-M37) | N38: =(N36-N37) | O38: =(O36-O37) | ... Q38: =(Q36-Q37)
A39: SG&A and other opex | B39: opex | D39: 78.45363 | E39: 59.345084 | F39: 96.8886 | G39: 61.3805 | H39: =(H36*H19) | I39: =(I36*I19) | J39: =(J36*J19) | K39: =(K36*K19) | L39: =(L36*L19) | M39: =(M36*M19) | N39: =(N36*N19) | O39: =(O36*O19) | ... Q39: =(Q36*Q19)
A40: EBIT | B40: ebit | D40: -19.983133 | E40: 10.298372 | F40: 38.39776 | G40: -2.3853236 | H40: =(H38-H39) | I40: =(I38-I39) | J40: =(J38-J39) | K40: =(K38-K39) | L40: =(L38-L39) | M40: =(M38-M39) | N40: =(N38-N39) | O40: =(O38-O39) | ... Q40: =(Q38-Q39)
A41: Depreciation & amortisation | B41: da | D41: 2.9737442 | E41: 3.5635278 | F41: 9.8517588 | G41: 9.4212526 | H41: =(H36*H20) | I41: =(I36*I20) | J41: =(J36*J20) | K41: =(K36*K20) | L41: =(L36*L20) | M41: =(M36*M20) | N41: =(N36*N20) | O41: =(O36*O20) | ... Q41: =(Q36*Q20)
A42: EBITDA | B42: ebitda | D42: -17.009388 | E42: 13.8619 | F42: 48.249518 | G42: 7.035929 | H42: =(H40+H41) | I42: =(I40+I41) | J42: =(J40+J41) | K42: =(K40+K41) | L42: =(L40+L41) | M42: =(M40+M41) | N42: =(N40+N41) | O42: =(O40+O41) | ... Q42: =(Q40+Q41)
A43: Interest expense | B43: interest_expense | D43: 4.8827931 | E43: 4.1007345 | F43: 1.6047098 | G43: 0.91339057 | H43: =(G63*$C$24) | I43: =(H63*$C$24) | J43: =(I63*$C$24) | K43: =(J63*$C$24) | L43: =(K63*$C$24) | M43: =(L63*$C$24) | N43: =(M63*$C$24) | O43: =(N63*$C$24) | ... Q43: =(P63*$C$24)
A44: Interest income | B44: interest_income | D44: 0.35623258 | E44: 0.35441447 | F44: 0.38586441 | G44: 0.39973604 | H44: =(G62*$C$25) | I44: =(H62*$C$25) | J44: =(I62*$C$25) | K44: =(J62*$C$25) | L44: =(K62*$C$25) | M44: =(L62*$C$25) | N44: =(M62*$C$25) | O44: =(N62*$C$25) | ... Q44: =(P62*$C$25)
A45: Other non-operating | B45: other_nonop | D45: -94.34293 | E45: -3.6876475 | F45: -2.5590111 | G45: 20.030939 | H45: =H27 | I45: =I27 | J45: =J27 | K45: =K27 | L45: =L27 | M45: =M27 | N45: =N27 | O45: =O27 | ... Q45: =Q27
A46: Profit before tax | B46: pbt | D46: -118.85262 | E46: 2.8644048 | F46: 34.619903 | G46: 17.13196 | H46: =(((H40-H43)+H44)+H45) | I46: =(((I40-I43)+I44)+I45) | J46: =(((J40-J43)+J44)+J45) | K46: =(((K40-K43)+K44)+K45) | L46: =(((L40-L43)+L44)+L45) | M46: =(((M40-M43)+M44)+M45) | N46: =(((N40-N43)+N44)+N45) | O46: =(((O40-O43)+O44)+O45) | ... Q46: =(((Q40-Q43)+Q44)+Q45)
A47: Tax | B47: tax | D47: -24.150518 | E47: 3.3806401 | F47: 9.1182861 | G47: 17.072872 | H47: =(MAX(H46,0)*H23) | I47: =(MAX(I46,0)*I23) | J47: =(MAX(J46,0)*J23) | K47: =(MAX(K46,0)*K23) | L47: =(MAX(L46,0)*L23) | M47: =(MAX(M46,0)*M23) | N47: =(MAX(N46,0)*N23) | O47: =(MAX(O46,0)*O23) | ... Q47: =(MAX(Q46,0)*Q23)
A48: Net profit (incl. minorities) | B48: np | D48: -94.702106 | E48: -0.51623529 | F48: 25.501617 | G48: 0.059088175 | H48: =(H46-H47) | I48: =(I46-I47) | J48: =(J46-J47) | K48: =(K46-K47) | L48: =(L46-L47) | M48: =(M46-M47) | N48: =(N46-N47) | O48: =(O46-O47) | ... Q48: =(Q46-Q47)
A49: Minority interests | B49: minority | D49: -0.023956165 | E49: -0.005901294 | F49: 0.001933973 | G49: 0.000624579 | H49: =(H48*H28) | I49: =(I48*I28) | J49: =(J48*J28) | K49: =(K48*K28) | L49: =(L48*L28) | M49: =(M48*M28) | N49: =(N48*N28) | O49: =(O48*O28) | ... Q49: =(Q48*Q28)
A50: Net profit to parent | B50: np_parent | D50: -94.678149 | E50: -0.510334 | F50: 25.499683 | G50: 0.058463596 | H50: =(H48-H49) | I50: =(I48-I49) | J50: =(J48-J49) | K50: =(K48-K49) | L50: =(L48-L49) | M50: =(M48-M49) | N50: =(N48-N49) | O50: =(O48-O49) | ... Q50: =(Q48-Q49)
A51: Shares outstanding (m) | B51: shares | D51: 1475.3632 | E51: 1475.3632 | F51: 1475.3632 | G51: 1475.3632 | H51: =(G51*(1+H30)) | I51: =(H51*(1+I30)) | J51: =(I51*(1+J30)) | K51: =(J51*(1+K30)) | L51: =(K51*(1+L30)) | M51: =(L51*(1+M30)) | N51: =(M51*(1+N30)) | O51: =(N51*(1+O30)) | ... Q51: =(P51*(1+Q30))
A52: EPS | B52: eps | D52: -64.172775 | E52: -0.34590398 | F52: 17.283665 | G52: 0.039626579 | H52: =(IF(H51=0,0,H50/H51)*$C$8) | I52: =(IF(I51=0,0,I50/I51)*$C$8) | J52: =(IF(J51=0,0,J50/J51)*$C$8) | K52: =(IF(K51=0,0,K50/K51)*$C$8) | L52: =(IF(L51=0,0,L50/L51)*$C$8) | M52: =(IF(M51=0,0,M50/M51)*$C$8) | N52: =(IF(N51=0,0,N50/N51)*$C$8) | O52: =(IF(O51=0,0,O50/O51)*$C$8) | ... Q52: =(IF(Q51=0,0,Q50/Q51)*$C$8)
A53: DPS (declared on the year) | B53: dps | D53: 0 | E53: 0 | F53: 0 | G53: 0 | H53: =(MAX(H52,0)*H29) | I53: =(MAX(I52,0)*I29) | J53: =(MAX(J52,0)*J29) | K53: =(MAX(K52,0)*K29) | L53: =(MAX(L52,0)*L29) | M53: =(MAX(M52,0)*M29) | N53: =(MAX(N52,0)*N29) | O53: =(MAX(O52,0)*O29) | ... Q53: =(MAX(Q52,0)*Q29)
A54: Dividends paid | B54: dividends_paid | H54: =IF($C$8=0,0,(G53*G51)/$C$8) | I54: =IF($C$8=0,0,(H53*H51)/$C$8) | J54: =IF($C$8=0,0,(I53*I51)/$C$8) | K54: =IF($C$8=0,0,(J53*J51)/$C$8) | L54: =IF($C$8=0,0,(K53*K51)/$C$8) | M54: =IF($C$8=0,0,(L53*L51)/$C$8) | N54: =IF($C$8=0,0,(M53*M51)/$C$8) | O54: =IF($C$8=0,0,(N53*N51)/$C$8) | ... Q54: =IF($C$8=0,0,(P53*P51)/$C$8)
A55: Capital expenditure | B55: capex | D55: 5.6173397 | E55: 1.5294384 | F55: 1.1463451 | G55: 3.1452536 | H55: =(H36*H21) | I55: =(I36*I21) | J55: =(J36*J21) | K55: =(K36*K21) | L55: =(L36*L21) | M55: =(M36*M21) | N55: =(N36*N21) | O55: =(O36*O21) | ... Q55: =(Q36*Q21)
A56: Change in working capital | B56: delta_nwc | E56: 10.010951 | F56: -3.4177325 | G56: 7.1074735 | H56: =(H61-G61) | I56: =(I61-H61) | J56: =(J61-I61) | K56: =(K61-J61) | L56: =(L61-K61) | M56: =(M61-L61) | N56: =(N61-M61) | O56: =(O61-N61) | ... Q56: =(Q61-P61)
A57: Free cash flow to firm | B57: fcff | E57: -9.8328782 | F57: 40.407597 | G57: -0.83970145 | H57: =((((H40*(1-H23))+H41)-H55)-H56) | I57: =((((I40*(1-I23))+I41)-I55)-I56) | J57: =((((J40*(1-J23))+J41)-J55)-J56) | K57: =((((K40*(1-K23))+K41)-K55)-K56) | L57: =((((L40*(1-L23))+L41)-L55)-L56) | M57: =((((M40*(1-M23))+M41)-M55)-M56) | N57: =((((N40*(1-N23))+N41)-N55)-N56) | O57: =((((O40*(1-O23))+O41)-O55)-O56) | ... Q57: =((((Q40*(1-Q23))+Q41)-Q55)-Q56)
A58: Net borrowing | B58: net_borrowing | E58: 8.1810734 | F58: -41.260816 | G58: 1.9567503 | H58: =H26 | I58: =I26 | J58: =J26 | K58: =K26 | L58: =L26 | M58: =M26 | N58: =N26 | O58: =O26 | ... Q58: =Q26
A59: Dividends to minorities | B59: minority_div | H59: =(MAX(G49,0)*H29) | I59: =(MAX(H49,0)*I29) | J59: =(MAX(I49,0)*J29) | K59: =(MAX(J49,0)*K29) | L59: =(MAX(K49,0)*L29) | M59: =(MAX(L49,0)*M29) | N59: =(MAX(M49,0)*N29) | O59: =(MAX(N49,0)*O29) | ... Q59: =(MAX(P49,0)*Q29)
A60: Free cash flow to equity | B60: fcfe | H60: =(((((H48+H41)-H55)-H56)+H58)-H59) | I60: =(((((I48+I41)-I55)-I56)+I58)-I59) | J60: =(((((J48+J41)-J55)-J56)+J58)-J59) | K60: =(((((K48+K41)-K55)-K56)+K58)-K59) | L60: =(((((L48+L41)-L55)-L56)+L58)-L59) | M60: =(((((M48+M41)-M55)-M56)+M58)-M59) | N60: =(((((N48+N41)-N55)-N56)+N58)-N59) | O60: =(((((O48+O41)-O55)-O56)+O58)-O59) | ... Q60: =(((((Q48+Q41)-Q55)-Q56)+Q58)-Q59)
A61: Operating working capital | B61: nwc | D61: -37.237886 | E61: -27.226935 | F61: -30.644668 | G61: -23.537194 | H61: =(H36*H22) | I61: =(I36*I22) | J61: =(J36*J22) | K61: =(K36*K22) | L61: =(L36*L22) | M61: =(M36*M22) | N61: =(N36*N22) | O61: =(O36*O22) | ... Q61: =(Q36*Q22)
A62: Cash & equivalents | B62: cash | D62: 1.5664224 | E62: 10.710614 | F62: 16.350008 | G62: 11.091476 | H62: =(((((((G62+H48)+H41)-H55)-H56)+H58)-H54)-H59) | I62: =(((((((H62+I48)+I41)-I55)-I56)+I58)-I54)-I59) | J62: =(((((((I62+J48)+J41)-J55)-J56)+J58)-J54)-J59) | K62: =(((((((J62+K48)+K41)-K55)-K56)+K58)-K54)-K59) | L62: =(((((((K62+L48)+L41)-L55)-L56)+L58)-L54)-L59) | M62: =(((((((L62+M48)+M41)-M55)-M56)+M58)-M54)-M59) | N62: =(((((((M62+N48)+N41)-N55)-N56)+N58)-N54)-N59) | O62: =(((((((N62+O48)+O41)-O55)-O56)+O58)-O54)-O59) | ... Q62: =(((((((P62+Q48)+Q41)-Q55)-Q56)+Q58)-Q54)-Q59)
A63: Total debt | B63: debt | D63: 35.758719 | E63: 43.939792 | F63: 2.6789761 | G63: 4.6357263 | H63: =(G63+H58) | I63: =(H63+I58) | J63: =(I63+J58) | K63: =(J63+K58) | L63: =(K63+L58) | M63: =(L63+M58) | N63: =(M63+N58) | O63: =(N63+O58) | ... Q63: =(P63+Q58)
A64: Fixed assets (net) | B64: ppe | D64: 211.95601 | E64: 200.73675 | F64: 185.55606 | G64: 197.23838 | H64: =((G64+H55)-H41) | I64: =((H64+I55)-I41) | J64: =((I64+J55)-J41) | K64: =((J64+K55)-K41) | L64: =((K64+L55)-L41) | M64: =((L64+M55)-M41) | N64: =((M64+N55)-N41) | O64: =((N64+O55)-O41) | ... Q64: =((P64+Q55)-Q41)
A65: Parent shareholders' equity | B65: equity | D65: 214.07346 | E65: 213.50924 | F65: 239.57074 | G65: 239.79507 | H65: =((G65+H50)-H54) | I65: =((H65+I50)-I54) | J65: =((I65+J50)-J54) | K65: =((J65+K50)-K54) | L65: =((K65+L50)-L54) | M65: =((L65+M50)-M54) | N65: =((M65+N50)-N54) | O65: =((N65+O50)-O54) | ... Q65: =((P65+Q50)-Q54)
A66: Minority interest (balance sheet) | B66: minority_bs | D66: 0.017272926 | E66: 0.011334662 | F66: 0.013529976 | G66: 0.014236218 | H66: =((G66+H49)-H59) | I66: =((H66+I49)-I59) | J66: =((I66+J49)-J59) | K66: =((J66+K49)-K59) | L66: =((K66+L49)-L59) | M66: =((L66+M49)-M59) | N66: =((M66+N49)-N59) | O66: =((N66+O49)-O59) | ... Q66: =((P66+Q49)-Q59)
A67: Other assets less other liabilities | B67: other_net | D67: 73.56491 | E67: 73.239937 | F67: 71.001844 | G67: 59.652367 | H67: =G67 | I67: =H67 | J67: =I67 | K67: =J67 | L67: =K67 | M67: =L67 | N67: =M67 | O67: =N67 | ... Q67: =P67
A68: Balance check (should be zero) | B68: bs_check | H68: =((((((H62+H61)+H64)+H67)-H63)-H65)-H66) | I68: =((((((I62+I61)+I64)+I67)-I63)-I65)-I66) | J68: =((((((J62+J61)+J64)+J67)-J63)-J65)-J66) | K68: =((((((K62+K61)+K64)+K67)-K63)-K65)-K66) | L68: =((((((L62+L61)+L64)+L67)-L63)-L65)-L66) | M68: =((((((M62+M61)+M64)+M67)-M63)-M65)-M66) | N68: =((((((N62+N61)+N64)+N67)-N63)-N65)-N66) | O68: =((((((O62+O61)+O64)+O67)-O63)-O65)-O66) | ... Q68: =((((((Q62+Q61)+Q64)+Q67)-Q63)-Q65)-Q66)
A69: Net debt (cash) | B69: net_debt | D69: 34.192297 | E69: 33.229178 | F69: -13.671032 | G69: -6.45575 | H69: =(H63-H62) | I69: =(I63-I62) | J69: =(J63-J62) | K69: =(K63-K62) | L69: =(L63-L62) | M69: =(M63-M62) | N69: =(N63-N62) | O69: =(O63-O62) | ... Q69: =(Q63-Q62)
A70: Book value per share | B70: bvps | D70: 145.09882 | E70: 144.71639 | F70: 162.38086 | G70: 162.53291 | H70: =(IF(H51=0,0,H65/H51)*$C$8) | I70: =(IF(I51=0,0,I65/I51)*$C$8) | J70: =(IF(J51=0,0,J65/J51)*$C$8) | K70: =(IF(K51=0,0,K65/K51)*$C$8) | L70: =(IF(L51=0,0,L65/L51)*$C$8) | M70: =(IF(M51=0,0,M65/M51)*$C$8) | N70: =(IF(N51=0,0,N65/N51)*$C$8) | O70: =(IF(O51=0,0,O65/O51)*$C$8) | ... Q70: =(IF(Q51=0,0,Q65/Q51)*$C$8)
A71: Revenue growth | B71: revenue_growth | E71: 0.056689901 | F71: 0.79109575 | G71: -0.34207346 | H71: =(IF(G36=0,0,H36/G36)-1) | I71: =(IF(H36=0,0,I36/H36)-1) | J71: =(IF(I36=0,0,J36/I36)-1) | K71: =(IF(J36=0,0,K36/J36)-1) | L71: =(IF(K36=0,0,L36/K36)-1) | M71: =(IF(L36=0,0,M36/L36)-1) | N71: =(IF(M36=0,0,N36/M36)-1) | O71: =(IF(N36=0,0,O36/N36)-1) | ... Q71: =(IF(P36=0,0,Q36/P36)-1)
A72: Gross margin | B72: gross_margin | D72: 0.23371212 | E72: 0.26343727 | F72: 0.28571437 | G72: 0.18937277 | H72: =IF(H36=0,0,H38/H36) | I72: =IF(I36=0,0,I38/I36) | J72: =IF(J36=0,0,J38/J36) | K72: =IF(K36=0,0,K38/K36) | L72: =IF(L36=0,0,L38/L36) | M72: =IF(M36=0,0,M38/M36) | N72: =IF(N36=0,0,N38/N36) | O72: =IF(O36=0,0,O38/O36) | ... Q72: =IF(Q36=0,0,Q38/Q36)
A73: EBITDA margin | B73: ebitda_margin | D73: -0.067988138 | E73: 0.052434805 | F73: 0.10189927 | G73: 0.022585106 | H73: =IF(H36=0,0,H42/H36) | I73: =IF(I36=0,0,I42/I36) | J73: =IF(J36=0,0,J42/J36) | K73: =IF(K36=0,0,K42/K36) | L73: =IF(L36=0,0,L42/L36) | M73: =IF(M36=0,0,M42/M36) | N73: =IF(N36=0,0,N42/N36) | O73: =IF(O36=0,0,O42/O36) | ... Q73: =IF(Q36=0,0,Q42/Q36)
A74: EBIT margin | B74: ebit_margin | D74: -0.079874476 | E74: 0.038955204 | F74: 0.081093114 | G74: -0.007656812 | H74: =IF(H36=0,0,H40/H36) | I74: =IF(I36=0,0,I40/I36) | J74: =IF(J36=0,0,J40/J36) | K74: =IF(K36=0,0,K40/K36) | L74: =IF(L36=0,0,L40/L36) | M74: =IF(M36=0,0,M40/M36) | N74: =IF(N36=0,0,N40/N36) | O74: =IF(O36=0,0,O40/O36) | ... Q74: =IF(Q36=0,0,Q40/Q36)
A75: Net margin | B75: np_margin | D75: -0.37843754 | E75: -0.0019304182 | F75: 0.053853368 | G75: 0.00018766626 | H75: =IF(H36=0,0,H50/H36) | I75: =IF(I36=0,0,I50/I36) | J75: =IF(J36=0,0,J50/J36) | K75: =IF(K36=0,0,K50/K36) | L75: =IF(L36=0,0,L50/L36) | M75: =IF(M36=0,0,M50/M36) | N75: =IF(N36=0,0,N50/N36) | O75: =IF(O36=0,0,O50/O36) | ... Q75: =IF(Q36=0,0,Q50/Q36)
A76: EPS growth | B76: eps_growth | E76: -0.9946098 | F76: -50.966655 | G76: -0.99770728 | H76: =(IF(G52=0,0,H52/G52)-1) | I76: =(IF(H52=0,0,I52/H52)-1) | J76: =(IF(I52=0,0,J52/I52)-1) | K76: =(IF(J52=0,0,K52/J52)-1) | L76: =(IF(K52=0,0,L52/K52)-1) | M76: =(IF(L52=0,0,M52/L52)-1) | N76: =(IF(M52=0,0,N52/M52)-1) | O76: =(IF(N52=0,0,O52/N52)-1) | ... Q76: =(IF(P52=0,0,Q52/P52)-1)
A77: ROE | B77: roe | E77: -0.0023870657 | F77: 0.11256151 | G77: 0.00024392059 | H77: =IF(IF(2=0,0,(H65+G65)/2)=0,0,H50/IF(2=0,0,(H65+G65)/2)) | I77: =IF(IF(2=0,0,(I65+H65)/2)=0,0,I50/IF(2=0,0,(I65+H65)/2)) | J77: =IF(IF(2=0,0,(J65+I65)/2)=0,0,J50/IF(2=0,0,(J65+I65)/2)) | K77: =IF(IF(2=0,0,(K65+J65)/2)=0,0,K50/IF(2=0,0,(K65+J65)/2)) | L77: =IF(IF(2=0,0,(L65+K65)/2)=0,0,L50/IF(2=0,0,(L65+K65)/2)) | M77: =IF(IF(2=0,0,(M65+L65)/2)=0,0,M50/IF(2=0,0,(M65+L65)/2)) | N77: =IF(IF(2=0,0,(N65+M65)/2)=0,0,N50/IF(2=0,0,(N65+M65)/2)) | O77: =IF(IF(2=0,0,(O65+N65)/2)=0,0,O50/IF(2=0,0,(O65+N65)/2)) | ... Q77: =IF(IF(2=0,0,(Q65+P65)/2)=0,0,Q50/IF(2=0,0,(Q65+P65)/2))
A78: Net debt / EBITDA | B78: net_debt_ebitda | D78: -2.0102014 | E78: 2.397159 | F78: -0.28334028 | G78: -0.91754052 | H78: =IF(H42=0,0,H69/H42) | I78: =IF(I42=0,0,I69/I42) | J78: =IF(J42=0,0,J69/J42) | K78: =IF(K42=0,0,K69/K42) | L78: =IF(L42=0,0,L69/L42) | M78: =IF(M42=0,0,M69/M42) | N78: =IF(N42=0,0,N69/N42) | O78: =IF(O42=0,0,O69/O42) | ... Q78: =IF(Q42=0,0,Q69/Q42)
A79: Payout ratio | B79: payout_ratio | D79: 0 | E79: 0 | F79: 0 | G79: 0 | H79: =IF(H52=0,0,H53/H52) | I79: =IF(I52=0,0,I53/I52) | J79: =IF(J52=0,0,J53/J52) | K79: =IF(K52=0,0,K53/K52) | L79: =IF(L52=0,0,L53/L52) | M79: =IF(M52=0,0,M53/M52) | N79: =IF(N52=0,0,N53/N52) | O79: =IF(O52=0,0,O53/O52) | ... Q79: =IF(Q52=0,0,Q53/Q52)
A80: Capex / revenue | B80: capex_revenue | D80: 0.022453039 | E80: 0.00578534 | F80: 0.0024209926 | G80: 0.010096163 | H80: =IF(H36=0,0,H55/H36) | I80: =IF(I36=0,0,I55/I36) | J80: =IF(J36=0,0,J55/J36) | K80: =IF(K36=0,0,K55/K36) | L80: =IF(L36=0,0,L55/L36) | M80: =IF(M36=0,0,M55/M36) | N80: =IF(N36=0,0,N55/N36) | O80: =IF(O36=0,0,O55/O36) | ... Q80: =IF(Q36=0,0,Q55/Q36)
A82: VALUATION
A83: Last price (IDR) | C83: 86
A84: Shares outstanding (m) | C84: 1475.3632
A85: IDR per USD (spot) | C85: 18128
A86: Debt at balance-sheet date | C86: 14.881776
A87: Cash at balance-sheet date | C87: 9.936685
A88: Minority interest (book) | C88: 0.017240083
A89: Associates & investments (book) | C89: 0
A90: Post-balance-sheet & other items (sourced, probability-weighted) | C90: -6.02
A91: Parent equity at balance-sheet date | C91: 241.74916
A92: Per-share factor | C92: 1000
A93: Risk-free rate | C93: =Drivers!$C$9
A94: Less: default spread (IDR only) | C94: =Drivers!$C$11
A95: Mature ERP + Indonesia CRP | C95: =Drivers!$C$12+Drivers!$C$13
A96: Tax rate | C96: =Drivers!$C$15
A97: Unlevered beta (industry default (config)) | C97: 1
A98: Debt / equity (market) | C98: 0.11728902
A99: Levered beta | C99: =$C$97*(1+(1-$C$96)*$C$98)
A100: Explicit company premium | C100: 0
A101: Cost of equity | C101: =$C$93-$C$94+$C$99*$C$95+$C$100
A102: Pre-tax cost of debt | C102: =$C$93+Drivers!$C$14
A103: WACC | C103: =1/(1+$C$98)*$C$101+$C$98/(1+$C$98)*$C$102*(1-$C$96)
A104: Terminal growth (capped) | C104: 0.03
A106: DCF to end of life (no terminal value)
...

Sheet SGER
A1: PT Sumber Global Energy Tbk (SGER.JK) — Coal distribution, trading & logistics
A2: Units: IDR bn; per-share in IDR unless marked IDR. Model asof 2026-10-30 · data 2026-10-27
A4: Line | C4: Scalar | D4: FY2022A | E4: FY2023A | F4: FY2024A | G4: FY2025A | H4: FY2026E | I4: FY2027E | J4: FY2028E | K4: FY2029E | L4: FY2030E | M4: FY2031E | N4: FY2032E | O4: FY2033E | P4: FY2034E | Q4: FY2035E
A6: PARAMETERS
A7: ps_factor | C7: 1000
A8: vp_factor | C8: 1
A10: INPUTS (company assumptions)
A11: Revenue growth | B11: a.revenue_growth | H11: 0.067 | I11: -0.05 | J11: -0.02 | K11: 0 | L11: 0.015 | M11: 0.0328 | N11: 0.0328 | O11: 0.0328 | P11: 0.0328 | Q11: 0.0328
A12: Gross margin at base input costs | B12: a.gross_margin | H12: 0.08 | I12: 0.08 | J12: 0.08 | K12: 0.08 | L12: 0.08 | M12: 0.08 | N12: 0.08 | O12: 0.08 | P12: 0.08 | Q12: 0.08
A13: Cost link 1: share of COGS exposed | B13: a.link1_share | C13: 0.732
A14: Cost link 1: pass-through to prices | B14: a.link1_pass | C14: 1
A15: Cost link 2: share of COGS exposed | B15: a.link2_share | C15: 0
A16: Cost link 2: pass-through to prices | B16: a.link2_pass | C16: 0
A17: SG&A / revenue | B17: a.opex_pct | H17: 0.0233 | I17: 0.0233 | J17: 0.0233 | K17: 0.0233 | L17: 0.0233 | M17: 0.0233 | N17: 0.0233 | O17: 0.0233 | P17: 0.0233 | Q17: 0.0233
A18: D&A / revenue | B18: a.da_pct | H18: 0.003 | I18: 0.003 | J18: 0.003 | K18: 0.003 | L18: 0.003 | M18: 0.003 | N18: 0.003 | O18: 0.003 | P18: 0.003 | Q18: 0.003
A19: Capex / revenue | B19: a.capex_pct | H19: 0.035 | I19: 0.025 | J19: 0.02 | K19: 0.015 | L19: 0.012 | M19: 0.01 | N19: 0.01 | O19: 0.01 | P19: 0.01 | Q19: 0.01
A20: Operating working capital / revenue | B20: a.nwc_pct | H20: 0.35 | I20: 0.35 | J20: 0.35 | K20: 0.35 | L20: 0.35 | M20: 0.35 | N20: 0.35 | O20: 0.35 | P20: 0.35 | Q20: 0.35
A21: Effective tax rate | B21: a.tax_rate | H21: 0.1279 | I21: 0.1279 | J21: 0.1279 | K21: 0.1279 | L21: 0.1279 | M21: 0.1279 | N21: 0.1279 | O21: 0.1279 | P21: 0.1279 | Q21: 0.1279
A22: Cost of debt (on opening debt) | B22: a.cost_of_debt | C22: 0.085
A23: Yield on opening cash | B23: a.cash_yield | C23: 0.025
A24: Net new borrowing | B24: a.net_borrowing | H24: -352 | I24: 0 | J24: 0 | K24: 0 | L24: 0 | M24: 0 | N24: 0 | O24: 0 | P24: 0 | Q24: 0
A25: Other non-operating items | B25: a.other_nonop | H25: 0 | I25: 0 | J25: 0 | K25: 0 | L25: 0 | M25: 0 | N25: 0 | O25: 0 | P25: 0 | Q25: 0
A26: Minorities' share of net profit | B26: a.minority_pct | H26: 0 | I26: 0 | J26: 0 | K26: 0 | L26: 0 | M26: 0 | N26: 0 | O26: 0 | P26: 0 | Q26: 0
A27: Dividend payout | B27: a.payout | H27: 0.15 | I27: 0.15 | J27: 0.15 | K27: 0.15 | L27: 0.15 | M27: 0.15 | N27: 0.15 | O27: 0.15 | P27: 0.15 | Q27: 0.15
A28: Change in share count | B28: a.share_change | H28: 0 | I28: 0 | J28: 0 | K28: 0 | L28: 0 | M28: 0 | N28: 0 | O28: 0 | P28: 0 | Q28: 0
A29: Terminal growth (DCF) | B29: a.terminal_growth | C29: 0.0328
A31: MODEL
A32: Revenue | B32: revenue | D32: 10448.875 | E32: 12312.862 | F32: 14762.475 | G32: 6739.5203 | H32: =(G32*(1+H11)) | I32: =(H32*(1+I11)) | J32: =(I32*(1+J11)) | K32: =(J32*(1+K11)) | L32: =(K32*(1+L11)) | M32: =(L32*(1+M11)) | N32: =(M32*(1+N11)) | O32: =(N32*(1+O11)) | ... Q32: =(P32*(1+Q11))
A33: Cost of revenue | B33: cogs | D33: 9718.9054 | E33: 11254.656 | F33: 13732.694 | G33: 6202.5784 | H33: =((H32*(1-H12))*((1+(($C$13*(1-$C$14))*(IF(Drivers!$G$4=0,0,Drivers!$H$4/Drivers!$G$4)-1)))+(($C$15*(1-$C$16))*(IF(Drivers!$G$6=0,0,Drivers!$H$6/Drivers!$G$6)-1)))) | I33: =((I32*(1-I12))*((1+(($C$13*(1-$C$14))*(IF(Drivers!$G$4=0,0,Drivers!$I$4/Drivers!$G$4)-1)))+(($C$15*(1-$C$16))*(IF(Drivers!$G$6=0,0,Drivers!$I$6/Drivers!$G$6)-1)))) | J33: =((J32*(1-J12))*((1+(($C$13*(1-$C$14))*(IF(Drivers!$G$4=0,0,Drivers!$J$4/Drivers!$G$4)-1)))+(($C$15*(1-$C$16))*(IF(Drivers!$G$6=0,0,Drivers!$J$6/Drivers!$G$6)-1)))) | K33: =((K32*(1-K12))*((1+(($C$13*(1-$C$14))*(IF(Drivers!$G$4=0,0,Drivers!$K$4/Drivers!$G$4)-1)))+(($C$15*(1-$C$16))*(IF(Drivers!$G$6=0,0,Drivers!$K$6/Drivers!$G$6)-1)))) | L33: =((L32*(1-L12))*((1+(($C$13*(1-$C$14))*(IF(Drivers!$G$4=0,0,Drivers!$L$4/Drivers!$G$4)-1)))+(($C$15*(1-$C$16))*(IF(Drivers!$G$6=0,0,Drivers!$L$6/Drivers!$G$6)-1)))) | M33: =((M32*(1-M12))*((1+(($C$13*(1-$C$14))*(IF(Drivers!$G$4=0,0,Drivers!$M$4/Drivers!$G$4)-1)))+(($C$15*(1-$C$16))*(IF(Drivers!$G$6=0,0,Drivers!$M$6/Drivers!$G$6)-1)))) | N33: =((N32*(1-N12))*((1+(($C$13*(1-$C$14))*(IF(Drivers!$G$4=0,0,Drivers!$N$4/Drivers!$G$4)-1)))+(($C$15*(1-$C$16))*(IF(Drivers!$G$6=0,0,Drivers!$N$6/Drivers!$G$6)-1)))) | O33: =((O32*(1-O12))*((1+(($C$13*(1-$C$14))*(IF(Drivers!$G$4=0,0,Drivers!$O$4/Drivers!$G$4)-1)))+(($C$15*(1-$C$16))*(IF(Drivers!$G$6=0,0,Drivers!$O$6/Drivers!$G$6)-1)))) | P33: =((P32*(1-P12))*((1+(($C$13*(1-$C$14))*(IF(Drivers!$G$4=0,0,Drivers!$P$4/Drivers!$G$4)-1)))+(($C$15*(1-$C$16))*(IF(Drivers!$G$6=0,0,Drivers!$P$6/Drivers!$G$6)-1)))) | Q33: =((Q32*(1-Q12))*((1+(($C$13*(1-$C$14))*(IF(Drivers!$G$4=0,0,Drivers!$Q$4/Drivers!$G$4)-1)))+(($C$15*(1-$C$16))*(IF(Drivers!$G$6=0,0,Drivers!$Q$6/Drivers!$G$6)-1))))
A34: Gross profit | B34: gross_profit | D34: 729.96975 | E34: 1058.2061 | F34: 1029.7812 | G34: 536.94193 | H34: =(H32-H33) | I34: =(I32-I33) | J34: =(J32-J33) | K34: =(K32-K33) | L34: =(L32-L33) | M34: =(M32-M33) | N34: =(N32-N33) | O34: =(O32-O33) | ... Q34: =(Q32-Q33)
A35: SG&A and other opex | B35: opex | D35: 113.71253 | E35: 165.21331 | F35: 115.99653 | G35: 157.13156 | H35: =(H32*H17) | I35: =(I32*I17) | J35: =(J32*J17) | K35: =(K32*K17) | L35: =(L32*L17) | M35: =(M32*M17) | N35: =(N32*N17) | O35: =(O32*O17) | ... Q35: =(Q32*Q17)
A36: EBIT | B36: ebit | D36: 616.25722 | E36: 892.99282 | F36: 913.78466 | G36: 379.81036 | H36: =(H34-H35) | I36: =(I34-I35) | J36: =(J34-J35) | K36: =(K34-K35) | L36: =(L34-L35) | M36: =(M34-M35) | N36: =(N34-N35) | O36: =(O34-O35) | ... Q36: =(Q34-Q35)
A37: Depreciation & amortisation | B37: da | D37: 3.6351996 | E37: 5.7042662 | F37: 13.040679 | G37: 17.740539 | H37: =(H32*H18) | I37: =(I32*I18) | J37: =(J32*J18) | K37: =(K32*K18) | L37: =(L32*L18) | M37: =(M32*M18) | N37: =(N32*N18) | O37: =(O32*O18) | ... Q37: =(Q32*Q18)
A38: EBITDA | B38: ebitda | D38: 619.89242 | E38: 898.69709 | F38: 926.82534 | G38: 397.5509 | H38: =(H36+H37) | I38: =(I36+I37) | J38: =(J36+J37) | K38: =(K36+K37) | L38: =(L36+L37) | M38: =(M36+M37) | N38: =(N36+N37) | O38: =(O36+O37) | ... Q38: =(Q36+Q37)
A39: Interest expense | B39: interest_expense | D39: 33.217496 | E39: 42.482409 | F39: 106.49781 | G39: 151.15052 | H39: =(G59*$C$22) | I39: =(H59*$C$22) | J39: =(I59*$C$22) | K39: =(J59*$C$22) | L39: =(K59*$C$22) | M39: =(L59*$C$22) | N39: =(M59*$C$22) | O39: =(N59*$C$22) | ... Q39: =(P59*$C$22)
A40: Interest income | B40: interest_income | H40: =(G58*$C$23) | I40: =(H58*$C$23) | J40: =(I58*$C$23) | K40: =(J58*$C$23) | L40: =(K58*$C$23) | M40: =(L58*$C$23) | N40: =(M58*$C$23) | O40: =(N58*$C$23) | ... Q40: =(P58*$C$23)
A41: Other non-operating | B41: other_nonop | H41: =H25 | I41: =I25 | J41: =J25 | K41: =K25 | L41: =L25 | M41: =M25 | N41: =N25 | O41: =O25 | ... Q41: =Q25
A42: Profit before tax | B42: pbt | D42: 748.25049 | E42: 840.91049 | F42: 810.94346 | G42: 238.25612 | H42: =(((H36-H39)+H40)+H41) | I42: =(((I36-I39)+I40)+I41) | J42: =(((J36-J39)+J40)+J41) | K42: =(((K36-K39)+K40)+K41) | L42: =(((L36-L39)+L40)+L41) | M42: =(((M36-M39)+M40)+M41) | N42: =(((N36-N39)+N40)+N41) | O42: =(((O36-O39)+O40)+O41) | ... Q42: =(((Q36-Q39)+Q40)+Q41)
A43: Tax | B43: tax | D43: 157.31943 | E43: 159.60399 | F43: 156.2847 | G43: 30.467122 | H43: =(MAX(H42,0)*H21) | I43: =(MAX(I42,0)*I21) | J43: =(MAX(J42,0)*J21) | K43: =(MAX(K42,0)*K21) | L43: =(MAX(L42,0)*L21) | M43: =(MAX(M42,0)*M21) | N43: =(MAX(N42,0)*N21) | O43: =(MAX(O42,0)*O21) | ... Q43: =(MAX(Q42,0)*Q21)
A44: Net profit (incl. minorities) | B44: np | D44: 590.93106 | E44: 681.30649 | F44: 654.65876 | G44: 207.78899 | H44: =(H42-H43) | I44: =(I42-I43) | J44: =(J42-J43) | K44: =(K42-K43) | L44: =(L42-L43) | M44: =(M42-M43) | N44: =(N42-N43) | O44: =(O42-O43) | ... Q44: =(Q42-Q43)
A45: Minority interests | B45: minority | D45: -14.734762 | E45: -6.6391405 | F45: -4.037467 | G45: -5.4800216 | H45: =(H44*H26) | I45: =(I44*I26) | J45: =(J44*J26) | K45: =(K44*K26) | L45: =(L44*L26) | M45: =(M44*M26) | N45: =(N44*N26) | O45: =(O44*O26) | ... Q45: =(Q44*Q26)
A46: Net profit to parent | B46: np_parent | D46: 605.66582 | E46: 687.94564 | F46: 658.69623 | G46: 213.26902 | H46: =(H44-H45) | I46: =(I44-I45) | J46: =(J44-J45) | K46: =(K44-K45) | L46: =(L44-L45) | M46: =(M44-M45) | N46: =(N44-N45) | O46: =(O44-O45) | ... Q46: =(Q44-Q45)
A47: Shares outstanding (m) | B47: shares | D47: 14143.779 | E47: 15586.913 | F47: 15586.909 | G47: 15586.909 | H47: =(G47*(1+H28)) | I47: =(H47*(1+I28)) | J47: =(I47*(1+J28)) | K47: =(J47*(1+K28)) | L47: =(K47*(1+L28)) | M47: =(L47*(1+M28)) | N47: =(M47*(1+N28)) | O47: =(N47*(1+O28)) | ... Q47: =(P47*(1+Q28))
A48: EPS | B48: eps | D48: 42.822066 | E48: 44.136105 | F48: 42.259579 | G48: 13.682572 | H48: =(IF(H47=0,0,H46/H47)*$C$7) | I48: =(IF(I47=0,0,I46/I47)*$C$7) | J48: =(IF(J47=0,0,J46/J47)*$C$7) | K48: =(IF(K47=0,0,K46/K47)*$C$7) | L48: =(IF(L47=0,0,L46/L47)*$C$7) | M48: =(IF(M47=0,0,M46/M47)*$C$7) | N48: =(IF(N47=0,0,N46/N47)*$C$7) | O48: =(IF(O47=0,0,O46/O47)*$C$7) | ... Q48: =(IF(Q47=0,0,Q46/Q47)*$C$7)
A49: DPS (declared on the year) | B49: dps | D49: 17.149783 | E49: 28 | F49: 9 | G49: 0 | H49: =(MAX(H48,0)*H27) | I49: =(MAX(I48,0)*I27) | J49: =(MAX(J48,0)*J27) | K49: =(MAX(K48,0)*K27) | L49: =(MAX(L48,0)*L27) | M49: =(MAX(M48,0)*M27) | N49: =(MAX(N48,0)*N27) | O49: =(MAX(O48,0)*O27) | ... Q49: =(MAX(Q48,0)*Q27)
A50: Dividends paid | B50: dividends_paid | D50: 33.317417 | E50: 267.31231 | F50: 122.2014 | G50: 140.28218 | H50: =IF($C$7=0,0,(G49*G47)/$C$7) | I50: =IF($C$7=0,0,(H49*H47)/$C$7) | J50: =IF($C$7=0,0,(I49*I47)/$C$7) | K50: =IF($C$7=0,0,(J49*J47)/$C$7) | L50: =IF($C$7=0,0,(K49*K47)/$C$7) | M50: =IF($C$7=0,0,(L49*L47)/$C$7) | N50: =IF($C$7=0,0,(M49*M47)/$C$7) | O50: =IF($C$7=0,0,(N49*N47)/$C$7) | ... Q50: =IF($C$7=0,0,(P49*P47)/$C$7)
A51: Capital expenditure | B51: capex | D51: 1.1838071 | E51: 73.806514 | F51: 292.86941 | G51: 475.35382 | H51: =(H32*H19) | I51: =(I32*I19) | J51: =(J32*J19) | K51: =(K32*K19) | L51: =(L32*L19) | M51: =(M32*M19) | N51: =(N32*N19) | O51: =(O32*O19) | ... Q51: =(Q32*Q19)
A52: Change in working capital | B52: delta_nwc | E52: 916.62698 | F52: 1131.3927 | G52: 505.73114 | H52: =(H57-G57) | I52: =(I57-H57) | J52: =(J57-I57) | K52: =(K57-J57) | L52: =(L57-K57) | M52: =(M57-L57) | N52: =(N57-M57) | O52: =(O57-N57) | ... Q52: =(Q57-P57)
A53: Free cash flow to firm | B53: fcff | E53: -261.22558 | F53: -673.54101 | G53: -632.10251 | H53: =((((H36*(1-H21))+H37)-H51)-H52) | I53: =((((I36*(1-I21))+I37)-I51)-I52) | J53: =((((J36*(1-J21))+J37)-J51)-J52) | K53: =((((K36*(1-K21))+K37)-K51)-K52) | L53: =((((L36*(1-L21))+L37)-L51)-L52) | M53: =((((M36*(1-M21))+M37)-M51)-M52) | N53: =((((N36*(1-N21))+N37)-N51)-N52) | O53: =((((O36*(1-O21))+O37)-O51)-O52) | ... Q53: =((((Q36*(1-Q21))+Q37)-Q51)-Q52)
A54: Net borrowing | B54: net_borrowing | E54: 444.00716 | F54: 493.74975 | G54: 1049.6655 | H54: =H24 | I54: =I24 | J54: =J24 | K54: =K24 | L54: =L24 | M54: =M24 | N54: =N24 | O54: =O24 | ... Q54: =Q24
A55: Dividends to minorities | B55: minority_div | H55: =(MAX(G45,0)*H27) | I55: =(MAX(H45,0)*I27) | J55: =(MAX(I45,0)*J27) | K55: =(MAX(J45,0)*K27) | L55: =(MAX(K45,0)*L27) | M55: =(MAX(L45,0)*M27) | N55: =(MAX(M45,0)*N27) | O55: =(MAX(N45,0)*O27) | ... Q55: =(MAX(P45,0)*Q27)
A56: Free cash flow to equity | B56: fcfe | H56: =(((((H44+H37)-H51)-H52)+H54)-H55) | I56: =(((((I44+I37)-I51)-I52)+I54)-I55) | J56: =(((((J44+J37)-J51)-J52)+J54)-J55) | K56: =(((((K44+K37)-K51)-K52)+K54)-K55) | L56: =(((((L44+L37)-L51)-L52)+L54)-L55) | M56: =(((((M44+M37)-M51)-M52)+M54)-M55) | N56: =(((((N44+N37)-N51)-N52)+N54)-N55) | O56: =(((((O44+O37)-O51)-O52)+O54)-O55) | ... Q56: =(((((Q44+Q37)-Q51)-Q52)+Q54)-Q55)
A57: Operating working capital | B57: nwc | D57: 884.89598 | E57: 1801.523 | F57: 2932.9157 | G57: 3438.6468 | H57: =(H32*H20) | I57: =(I32*I20) | J57: =(J32*J20) | K57: =(K32*K20) | L57: =(L32*L20) | M57: =(M32*M20) | N57: =(N32*N20) | O57: =(O32*O20) | ... Q57: =(Q32*Q20)
A58: Cash & equivalents | B58: cash | D58: 388.54509 | E58: 295.96265 | F58: 150.24423 | G58: 361.27269 | H58: =(((((((G58+H44)+H37)-H51)-H52)+H54)-H50)-H55) | I58: =(((((((H58+I44)+I37)-I51)-I52)+I54)-I50)-I55) | J58: =(((((((I58+J44)+J37)-J51)-J52)+J54)-J50)-J55) | K58: =(((((((J58+K44)+K37)-K51)-K52)+K54)-K50)-K55) | L58: =(((((((K58+L44)+L37)-L51)-L52)+L54)-L50)-L55) | M58: =(((((((L58+M44)+M37)-M51)-M52)+M54)-M50)-M55) | N58: =(((((((M58+N44)+N37)-N51)-N52)+N54)-N50)-N55) | O58: =(((((((N58+O44)+O37)-O51)-O52)+O54)-O50)-O55) | ... Q58: =(((((((P58+Q44)+Q37)-Q51)-Q52)+Q54)-Q50)-Q55)
A59: Total debt | B59: debt | D59: 313.26895 | E59: 757.27611 | F59: 1251.0259 | G59: 2300.6914 | H59: =(G59+H54) | I59: =(H59+I54) | J59: =(I59+J54) | K59: =(J59+K54) | L59: =(K59+L54) | M59: =(L59+M54) | N59: =(M59+N54) | O59: =(N59+O54) | ... Q59: =(P59+Q54)
A60: Fixed assets (net) | B60: ppe | D60: 39.973687 | E60: 131.12921 | F60: 402.93754 | G60: 862.10501 | H60: =((G60+H51)-H37) | I60: =((H60+I51)-I37) | J60: =((I60+J51)-J37) | K60: =((J60+K51)-K37) | L60: =((K60+L51)-L37) | M60: =((L60+M51)-M37) | N60: =((M60+N51)-N37) | O60: =((N60+O51)-O37) | ... Q60: =((P60+Q51)-Q37)
A61: Parent shareholders' equity | B61: equity | D61: 983.17686 | E61: 1449.8784 | F61: 2125.9696 | G61: 2233.9137 | H61: =((G61+H46)-H50) | I61: =((H61+I46)-I50) | J61: =((I61+J46)-J50) | K61: =((J61+K46)-K50) | L61: =((K61+L46)-L50) | M61: =((L61+M46)-M50) | N61: =((M61+N46)-N50) | O61: =((N61+O46)-O50) | ... Q61: =((P61+Q46)-Q50)
A62: Minority interest (balance sheet) | B62: minority_bs | D62: 28.95602 | E62: 31.889428 | F62: 115.16655 | G62: 131.60868 | H62: =((G62+H45)-H55) | I62: =((H62+I45)-I55) | J62: =((I62+J45)-J55) | K62: =((J62+K45)-K55) | L62: =((K62+L45)-L55) | M62: =((L62+M45)-M55) | N62: =((M62+N45)-N55) | O62: =((N62+O45)-O55) | ... Q62: =((P62+Q45)-Q55)
A63: Other assets less other liabilities | B63: other_net | D63: 11.987075 | E63: 10.42908 | F63: 6.0645851 | G63: 4.1891958 | H63: =G63 | I63: =H63 | J63: =I63 | K63: =J63 | L63: =K63 | M63: =L63 | N63: =M63 | O63: =N63 | ... Q63: =P63
A64: Balance check (should be zero) | B64: bs_check | H64: =((((((H58+H57)+H60)+H63)-H59)-H61)-H62) | I64: =((((((I58+I57)+I60)+I63)-I59)-I61)-I62) | J64: =((((((J58+J57)+J60)+J63)-J59)-J61)-J62) | K64: =((((((K58+K57)+K60)+K63)-K59)-K61)-K62) | L64: =((((((L58+L57)+L60)+L63)-L59)-L61)-L62) | M64: =((((((M58+M57)+M60)+M63)-M59)-M61)-M62) | N64: =((((((N58+N57)+N60)+N63)-N59)-N61)-N62) | O64: =((((((O58+O57)+O60)+O63)-O59)-O61)-O62) | ... Q64: =((((((Q58+Q57)+Q60)+Q63)-Q59)-Q61)-Q62)
A65: Net debt (cash) | B65: net_debt | D65: -75.27614 | E65: 461.31346 | F65: 1100.7816 | G65: 1939.4187 | H65: =(H59-H58) | I65: =(I59-I58) | J65: =(J59-J58) | K65: =(K59-K58) | L65: =(L59-L58) | M65: =(M59-M58) | N65: =(N59-N58) | O65: =(O59-O58) | ... Q65: =(Q59-Q58)
A66: Book value per share | B66: bvps | D66: 69.513026 | E66: 93.018954 | F66: 136.39456 | G66: 143.31986 | H66: =(IF(H47=0,0,H61/H47)*$C$7) | I66: =(IF(I47=0,0,I61/I47)*$C$7) | J66: =(IF(J47=0,0,J61/J47)*$C$7) | K66: =(IF(K47=0,0,K61/K47)*$C$7) | L66: =(IF(L47=0,0,L61/L47)*$C$7) | M66: =(IF(M47=0,0,M61/M47)*$C$7) | N66: =(IF(N47=0,0,N61/N47)*$C$7) | O66: =(IF(O47=0,0,O61/O47)*$C$7) | ... Q66: =(IF(Q47=0,0,Q61/Q47)*$C$7)
A67: Revenue growth | B67: revenue_growth | E67: 0.17839112 | F67: 0.19894753 | G67: -0.54346949 | H67: =(IF(G32=0,0,H32/G32)-1) | I67: =(IF(H32=0,0,I32/H32)-1) | J67: =(IF(I32=0,0,J32/I32)-1) | K67: =(IF(J32=0,0,K32/J32)-1) | L67: =(IF(K32=0,0,L32/K32)-1) | M67: =(IF(L32=0,0,M32/L32)-1) | N67: =(IF(M32=0,0,N32/M32)-1) | O67: =(IF(N32=0,0,O32/N32)-1) | ... Q67: =(IF(P32=0,0,Q32/P32)-1)
A68: Gross margin | B68: gross_margin | D68: 0.069861085 | E68: 0.085943151 | F68: 0.069756676 | G68: 0.079670645 | H68: =IF(H32=0,0,H34/H32) | I68: =IF(I32=0,0,I34/I32) | J68: =IF(J32=0,0,J34/J32) | K68: =IF(K32=0,0,K34/K32) | L68: =IF(L32=0,0,L34/L32) | M68: =IF(M32=0,0,M34/M32) | N68: =IF(N32=0,0,N34/N32) | O68: =IF(O32=0,0,O34/O32) | ... Q68: =IF(Q32=0,0,Q34/Q32)
A69: EBITDA margin | B69: ebitda_margin | D69: 0.059326235 | E69: 0.072988482 | F69: 0.062782517 | G69: 0.058988012 | H69: =IF(H32=0,0,H38/H32) | I69: =IF(I32=0,0,I38/I32) | J69: =IF(J32=0,0,J38/J32) | K69: =IF(K32=0,0,K38/K32) | L69: =IF(L32=0,0,L38/L32) | M69: =IF(M32=0,0,M38/M32) | N69: =IF(N32=0,0,N38/N32) | O69: =IF(O32=0,0,O38/O32) | ... Q69: =IF(Q32=0,0,Q38/Q32)
A70: EBIT margin | B70: ebit_margin | D70: 0.058978331 | E70: 0.072525205 | F70: 0.06189915 | G70: 0.056355697 | H70: =IF(H32=0,0,H36/H32) | I70: =IF(I32=0,0,I36/I32) | J70: =IF(J32=0,0,J36/J32) | K70: =IF(K32=0,0,K36/K32) | L70: =IF(L32=0,0,L36/L32) | M70: =IF(M32=0,0,M36/M32) | N70: =IF(N32=0,0,N36/N32) | O70: =IF(O32=0,0,O36/O32) | ... Q70: =IF(Q32=0,0,Q36/Q32)
A71: Net margin | B71: np_margin | D71: 0.057964691 | E71: 0.055872116 | F71: 0.044619633 | G71: 0.031644539 | H71: =IF(H32=0,0,H46/H32) | I71: =IF(I32=0,0,I46/I32) | J71: =IF(J32=0,0,J46/J32) | K71: =IF(K32=0,0,K46/K32) | L71: =IF(L32=0,0,L46/L32) | M71: =IF(M32=0,0,M46/M32) | N71: =IF(N32=0,0,N46/N32) | O71: =IF(O32=0,0,O46/O32) | ... Q71: =IF(Q32=0,0,Q46/Q32)
A72: EPS growth | B72: eps_growth | E72: 0.030686022 | F72: -0.042516802 | G72: -0.67622554 | H72: =(IF(G48=0,0,H48/G48)-1) | I72: =(IF(H48=0,0,I48/H48)-1) | J72: =(IF(I48=0,0,J48/I48)-1) | K72: =(IF(J48=0,0,K48/J48)-1) | L72: =(IF(K48=0,0,L48/K48)-1) | M72: =(IF(L48=0,0,M48/L48)-1) | N72: =(IF(M48=0,0,N48/M48)-1) | O72: =(IF(N48=0,0,O48/N48)-1) | ... Q72: =(IF(P48=0,0,Q48/P48)-1)
A73: ROE | B73: roe | E73: 0.5654994 | F73: 0.368414 | G73: 0.097832442 | H73: =IF(IF(2=0,0,(H61+G61)/2)=0,0,H46/IF(2=0,0,(H61+G61)/2)) | I73: =IF(IF(2=0,0,(I61+H61)/2)=0,0,I46/IF(2=0,0,(I61+H61)/2)) | J73: =IF(IF(2=0,0,(J61+I61)/2)=0,0,J46/IF(2=0,0,(J61+I61)/2)) | K73: =IF(IF(2=0,0,(K61+J61)/2)=0,0,K46/IF(2=0,0,(K61+J61)/2)) | L73: =IF(IF(2=0,0,(L61+K61)/2)=0,0,L46/IF(2=0,0,(L61+K61)/2)) | M73: =IF(IF(2=0,0,(M61+L61)/2)=0,0,M46/IF(2=0,0,(M61+L61)/2)) | N73: =IF(IF(2=0,0,(N61+M61)/2)=0,0,N46/IF(2=0,0,(N61+M61)/2)) | O73: =IF(IF(2=0,0,(O61+N61)/2)=0,0,O46/IF(2=0,0,(O61+N61)/2)) | ... Q73: =IF(IF(2=0,0,(Q61+P61)/2)=0,0,Q46/IF(2=0,0,(Q61+P61)/2))
A74: Net debt / EBITDA | B74: net_debt_ebitda | D74: -0.1214342 | E74: 0.51331362 | F74: 1.1876905 | G74: 4.878416 | H74: =IF(H38=0,0,H65/H38) | I74: =IF(I38=0,0,I65/I38) | J74: =IF(J38=0,0,J65/J38) | K74: =IF(K38=0,0,K65/K38) | L74: =IF(L38=0,0,L65/L38) | M74: =IF(M38=0,0,M65/M38) | N74: =IF(N38=0,0,N65/N38) | O74: =IF(O38=0,0,O65/O38) | ... Q74: =IF(Q38=0,0,Q65/Q38)
A75: Payout ratio | B75: payout_ratio | D75: 0.40048939 | E75: 0.63440125 | F75: 0.21296947 | G75: 0 | H75: =IF(H48=0,0,H49/H48) | I75: =IF(I48=0,0,I49/I48) | J75: =IF(J48=0,0,J49/J48) | K75: =IF(K48=0,0,K49/K48) | L75: =IF(L48=0,0,L49/L48) | M75: =IF(M48=0,0,M49/M48) | N75: =IF(N48=0,0,N49/N48) | O75: =IF(O48=0,0,O49/O48) | ... Q75: =IF(Q48=0,0,Q49/Q48)
A76: Capex / revenue | B76: capex_revenue | D76: 0.00011329517 | E76: 0.0059942615 | F76: 0.019838774 | G76: 0.070532294 | H76: =IF(H32=0,0,H51/H32) | I76: =IF(I32=0,0,I51/I32) | J76: =IF(J32=0,0,J51/J32) | K76: =IF(K32=0,0,K51/K32) | L76: =IF(L32=0,0,L51/L32) | M76: =IF(M32=0,0,M51/M32) | N76: =IF(N32=0,0,N51/N32) | O76: =IF(O32=0,0,O51/O32) | ... Q76: =IF(Q32=0,0,Q51/Q32)
A78: VALUATION
A79: Last price (IDR) | C79: 800
A80: Shares outstanding (m) | C80: 15586.909
A81: IDR per USD (spot) | C81: 18128
A82: Debt at balance-sheet date | C82: 2222.3167
A83: Cash at balance-sheet date | C83: 270.021
A84: Minority interest (book) | C84: 133.73975
A85: Associates & investments (book) | C85: 4.3654369
A86: Post-balance-sheet & other items (sourced, probability-weighted) | C86: 0
A87: Parent equity at balance-sheet date | C87: 2447.0121
A88: Per-share factor | C88: 1000
A89: Risk-free rate | C89: =Drivers!$C$9
A90: Less: default spread (IDR only) | C90: =Drivers!$C$11
A91: Mature ERP + Indonesia CRP | C91: =Drivers!$C$12+Drivers!$C$13
A92: Tax rate | C92: =Drivers!$C$15
A93: Unlevered beta (industry default (config)) | C93: 1
A94: Debt / equity (market) | C94: 0.1782198
A95: Levered beta | C95: =$C$93*(1+(1-$C$92)*$C$94)
A96: Explicit company premium | C96: 0
A97: Cost of equity | C97: =$C$89-$C$90+$C$95*$C$91+$C$96
A98: Pre-tax cost of debt | C98: =$C$89+Drivers!$C$14
A99: WACC | C99: =1/(1+$C$94)*$C$97+$C$94/(1+$C$94)*$C$98*(1-$C$92)
A100: Terminal growth (capped) | C100: 0.0328
A102: DCF (FCFF, terminal value)
A103: Share of year after balance-sheet date | H103: 0.503765 | I103: 0.996578 | J103: 0.999316 | K103: 0.996578 | L103: 0.996578 | M103: 0.996578 | N103: 0.999316 | O103: 0.996578 | P103: 0.996578 | Q103: 0.996578
A104: Discount time from valuation date (years) | H104: 0 | I104: 0.670773 | J104: 1.670089 | K104: 2.672142 | L104: 3.671458 | M104: 4.670773 | N104: 5.670089 | O104: 6.672142 | P104: 7.671458 | Q104: 8.670773
A105: Discount factor | H105: =1/(1+$C$99)^H104 | I105: =1/(1+$C$99)^I104 | J105: =1/(1+$C$99)^J104 | K105: =1/(1+$C$99)^K104 | L105: =1/(1+$C$99)^L104 | M105: =1/(1+$C$99)^M104 | N105: =1/(1+$C$99)^N104 | O105: =1/(1+$C$99)^O104 | ... Q105: =1/(1+$C$99)^Q104
A106: PV of FCFF | H106: =H53*H103*H105 | I106: =I53*I103*I105 | J106: =J53*J103*J105 | K106: =K53*K103*K105 | L106: =L53*L103*L105 | M106: =M53*M103*M105 | N106: =N53*N103*N105 | O106: =O53*O103*O105 | ... Q106: =Q53*Q103*Q105
...
