Workbook

Sheet README
A1: Six South — Coal producers industry model
A2: Generated 2026-10-30T23:33:13+07:00 by the coverage engine. The engine (scripts/cov_engine.py) is the source of truth; this workbook is a live rendering of it.
A3: Colour key: blue = input or hard-coded history; black = formula; green = link to another sheet.
A4: Drivers: every deck variable these models read. Change one and every ticker tab and the Comps sheet recalculate (forecasts, cash flows, DCF value, base-case value, target, rating).
A5: Scenario (bear/bull) and sensitivity tables need full model re-runs and are engine values.
A6: Paper fund — research for education and process transparency, not investment advice.
A8: Tickers:
A9: AADI.JK — PT Adaro Andalan Indonesia Tbk
A10: ADMR.JK — PT Alamtri Minerals Indonesia Tbk
A11: ARII.JK — PT Atlas Resources Tbk
A12: BOSS.JK — PT. Borneo Olah Sarana Sukses Tbk
A13: BSSR.JK — PT Baramulti Suksessarana Tbk
... A26: SMMT.JK — PT Golden Eagle Energy Tbk

Sheet Drivers
A1: Driver decks (state/drivers) — edit a blue cell to flow it through every ticker tab
A3: Variable | B3: Key | C3: Unit / status | D3: FY2021A | E3: FY2022A | F3: FY2023A | G3: FY2023E | H3: FY2024A | I3: FY2024E | J3: FY2025A | K3: FY2025E | L3: FY2026E | M3: FY2027E | N3: FY2028E | O3: FY2029E | P3: FY2030E | Q3: FY2031E | R3: FY2032E | S3: FY2033E | T3: FY2034E | U3: FY2035E | V3: FY2036E | W3: FY2037E | X3: FY2038E | Y3: FY2039E | Z3: FY2040E | AA3: FY2041E | AB3: FY2042E | AC3: FY2043E | AD3: FY2044E | AE3: FY2045E | AF3: FY2046E | AG3: FY2047E | AH3: FY2048E | AI3: FY2049E | AJ3: FY2050E | AK3: FY2051E | AL3: FY2052E | AM3: FY2053E | AN3: FY2054E | AO3: FY2055E | AP3: FY2056E | AQ3: FY2057E | AR3: FY2058E | AS3: FY2059E | AT3: FY2060E | AU3: FY2061E | AV3: FY2062E | AW3: FY2063E | AX3: FY2064E | AY3: FY2065E | AZ3: FY2066E | BA3: FY2067E | BB3: FY2068E | BC3: FY2069E | BD3: FY2070E | BE3: FY2071E | BF3: FY2072E | BG3: FY2073E | BH3: FY2074E | BI3: FY2075E | BJ3: FY2076E | BK3: FY2077E | BL3: FY2078E | BM3: FY2079E | BN3: FY2080E | BO3: FY2081E | BP3: FY2082E | BQ3: FY2083E | BR3: FY2084E | BS3: FY2085E | BT3: FY2086E | BU3: FY2087E | BV3: FY2088E | BW3: FY2089E | BX3: FY2090E | BY3: FY2091E | BZ3: FY2092E | CA3: FY2093E | CB3: FY2094E | CC3: FY2095E
A4: DMO price cap for coal sold to power plants | B4: d.coal.dmo_cap | C4: USD/t · reviewed | G4: 70 | I4: 70 | K4: 70 | L4: 70 | M4: 70 | N4: 70 | O4: 70 | P4: 70 | Q4: 70 | R4: 70 | S4: 70 | T4: 70 | U4: 70 | V4: 70 | W4: 70 | X4: 70 | Y4: 70 | Z4: 70 | AA4: 70 | AB4: 70 | AC4: 70 | AD4: 70 | AE4: 70 | AF4: 70 | AG4: 70 | AH4: 70 | AI4: 70 | AJ4: 70 | AK4: 70 | AL4: 70 | AM4: 70 | AN4: 70 | AO4: 70 | AP4: 70 | AQ4: 70 | AR4: 70 | AS4: 70 | AT4: 70 | AU4: 70 | AV4: 70 | AW4: 70 | AX4: 70 | AY4: 70 | AZ4: 70 | BA4: 70 | BB4: 70 | BC4: 70 | BD4: 70 | BE4: 70 | BF4: 70 | BG4: 70 | BH4: 70 | BI4: 70 | BJ4: 70 | BK4: 70 | BL4: 70 | BM4: 70 | BN4: 70 | BO4: 70 | BP4: 70 | BQ4: 70 | BR4: 70 | BS4: 70 | BT4: 70 | BU4: 70 | BV4: 70 | BW4: 70 | BX4: 70 | BY4: 70 | BZ4: 70 | CA4: 70 | CB4: 70 | CC4: 70
A5: Harga Batubara Acuan (government reference price) | B5: d.coal.hba | C5: USD/t · reviewed | G5: 105 | I5: 105 | K5: 105 | L5: 118 | M5: 112 | N5: 108 | O5: 105 | P5: 107.1 | Q5: 109.242 | R5: 111.42684 | S5: 113.65538 | T5: 115.92848 | U5: 118.24705 | V5: 120.612 | W5: 123.02424 | X5: 125.48472 | Y5: 127.99441 | Z5: 130.5543 | AA5: 133.16539 | AB5: 135.8287 | AC5: 138.54527 | AD5: 141.31618 | AE5: 144.1425 | AF5: 147.02535 | AG5: 149.96586 | AH5: 152.96517 | AI5: 156.02448 | AJ5: 159.14497 | AK5: 162.32787 | AL5: 165.57442 | AM5: 168.88591 | AN5: 172.26363 | AO5: 175.7089 | AP5: 179.22308 | AQ5: 182.80754 | AR5: 186.46369 | AS5: 190.19297 | AT5: 193.99683 | AU5: 197.87676 | AV5: 201.8343 | AW5: 205.87098 | AX5: 209.9884 | AY5: 214.18817 | AZ5: 218.47193 | BA5: 222.84137 | BB5: 227.2982 | BC5: 231.84416 | BD5: 236.48105 | BE5: 241.21067 | BF5: 246.03488 | BG5: 250.95558 | BH5: 255.97469 | BI5: 261.09419 | BJ5: 266.31607 | BK5: 271.64239 | BL5: 277.07524 | BM5: 282.61674 | BN5: 288.26908 | BO5: 294.03446 | BP5: 299.91515 | BQ5: 305.91345 | BR5: 312.03172 | BS5: 318.27236 | BT5: 324.6378 | BU5: 331.13056 | BV5: 337.75317 | BW5: 344.50823 | BX5: 351.3984 | BY5: 358.42637 | BZ5: 365.59489 | CA5: 372.90679 | CB5: 380.36493 | CC5: 387.97222
A6: Newcastle 6,000 kcal/kg NAR thermal coal | B6: d.coal.newc | C6: USD/t · reviewed | G6: 105 | H6: 136.1 | I6: 105 | J6: 108.4 | K6: 105 | L6: 137 | M6: 118 | N6: 110 | O6: 105 | P6: 107.1 | Q6: 109.242 | R6: 111.42684 | S6: 113.65538 | T6: 115.92848 | U6: 118.24705 | V6: 120.612 | W6: 123.02424 | X6: 125.48472 | Y6: 127.99441 | Z6: 130.5543 | AA6: 133.16539 | AB6: 135.8287 | AC6: 138.54527 | AD6: 141.31618 | AE6: 144.1425 | AF6: 147.02535 | AG6: 149.96586 | AH6: 152.96517 | AI6: 156.02448 | AJ6: 159.14497 | AK6: 162.32787 | AL6: 165.57442 | AM6: 168.88591 | AN6: 172.26363 | AO6: 175.7089 | AP6: 179.22308 | AQ6: 182.80754 | AR6: 186.46369 | AS6: 190.19297 | AT6: 193.99683 | AU6: 197.87676 | AV6: 201.8343 | AW6: 205.87098 | AX6: 209.9884 | AY6: 214.18817 | AZ6: 218.47193 | BA6: 222.84137 | BB6: 227.2982 | BC6: 231.84416 | BD6: 236.48105 | BE6: 241.21067 | BF6: 246.03488 | BG6: 250.95558 | BH6: 255.97469 | BI6: 261.09419 | BJ6: 266.31607 | BK6: 271.64239 | BL6: 277.07524 | BM6: 282.61674 | BN6: 288.26908 | BO6: 294.03446 | BP6: 299.91515 | BQ6: 305.91345 | BR6: 312.03172 | BS6: 318.27236 | BT6: 324.6378 | BU6: 331.13056 | BV6: 337.75317 | BW6: 344.50823 | BX6: 351.3984 | BY6: 358.42637 | BZ6: 365.59489 | CA6: 372.90679 | CB6: 380.36493 | CC6: 387.97222
A7: IDR per USD | B7: m.usd_idr | C7: IDR/USD · reviewed | D7: 14310.54 | E7: 14843.177 | F7: 15228.8 | G7: 19000 | H7: 15846.238 | I7: 19000 | J7: 16448.093 | K7: 19000 | L7: 17570 | M7: 18350 | N7: 18600 | O7: 18850 | P7: 19093.137 | Q7: 19186.731 | R7: 19280.784 | S7: 19375.297 | T7: 19470.274 | U7: 19565.717 | V7: 19661.627 | W7: 19758.008 | X7: 19854.861 | Y7: 19952.188 | Z7: 20049.993 | AA7: 20148.278 | AB7: 20247.044 | AC7: 20346.294 | AD7: 20446.031 | AE7: 20546.256 | AF7: 20646.973 | AG7: 20748.184 | AH7: 20849.891 | AI7: 20952.096 | AJ7: 21054.802 | AK7: 21158.012 | AL7: 21261.728 | AM7: 21365.952 | AN7: 21470.687 | AO7: 21575.936 | AP7: 21681.7 | AQ7: 21787.983 | AR7: 21894.787 | AS7: 22002.114 | AT7: 22109.967 | AU7: 22218.35 | AV7: 22327.263 | AW7: 22436.711 | AX7: 22546.694 | AY7: 22657.217 | AZ7: 22768.282 | BA7: 22879.891 | BB7: 22992.048 | BC7: 23104.754 | BD7: 23218.012 | BE7: 23331.826 | BF7: 23446.198 | BG7: 23561.13 | BH7: 23676.626 | BI7: 23792.688 | BJ7: 23909.319 | BK7: 24026.521 | BL7: 24144.298 | BM7: 24262.653 | BN7: 24381.587 | BO7: 24501.105 | BP7: 24621.208 | BQ7: 24741.901 | BR7: 24863.184 | BS7: 24985.063 | BT7: 25107.539 | BU7: 25230.615 | BV7: 25354.294 | BW7: 25478.58 | BX7: 25603.475 | BY7: 25728.982 | BZ7: 25855.105 | CA7: 25981.845 | CB7: 26109.207 | CC7: 26237.194
A8: Brent crude | B8: d.oil.brent | C8: USD/bbl · reviewed | D8: 70.9538 | E8: 98.9663 | F8: 82.1904 | G8: 75 | H8: 79.8213 | I8: 75 | J8: 68.1015 | K8: 75 | L8: 96 | M8: 84 | N8: 80 | O8: 78 | P8: 76.5 | Q8: 78.03 | R8: 79.5906 | S8: 81.182412 | T8: 82.80606 | U8: 84.462181 | V8: 86.151425 | W8: 87.874454 | X8: 89.631943 | Y8: 91.424581 | Z8: 93.253073 | AA8: 95.118135 | AB8: 97.020497 | AC8: 98.960907 | AD8: 100.94013 | AE8: 102.95893 | AF8: 105.01811 | AG8: 107.11847 | AH8: 109.26084 | AI8: 111.44605 | AJ8: 113.67498 | AK8: 115.94848 | AL8: 118.26744 | AM8: 120.63279 | AN8: 123.04545 | AO8: 125.50636 | AP8: 128.01649 | AQ8: 130.57682 | AR8: 133.18835 | AS8: 135.85212 | AT8: 138.56916 | AU8: 141.34054 | AV8: 144.16736 | AW8: 147.0507 | AX8: 149.99172 | AY8: 152.99155 | AZ8: 156.05138 | BA8: 159.17241 | BB8: 162.35586 | BC8: 165.60297 | BD8: 168.91503 | BE8: 172.29333 | BF8: 175.7392 | BG8: 179.25399 | BH8: 182.83907 | BI8: 186.49585 | BJ8: 190.22576 | BK8: 194.03028 | BL8: 197.91088 | BM8: 201.8691 | BN8: 205.90648 | BO8: 210.02461 | BP8: 214.22511 | BQ8: 218.50961 | BR8: 222.8798 | BS8: 227.3374 | BT8: 231.88414 | BU8: 236.52183 | BV8: 241.25226 | BW8: 246.07731 | BX8: 250.99886 | BY8: 256.01883 | BZ8: 261.13921 | CA8: 266.36199 | CB8: 271.68923 | CC8: 277.12302
A10: Cost-of-capital scalars (macro deck)
A11: 10-year Indonesian government bond yield (IDR) | B11: m.rf_idr | C11: 0.0745 | D11: investor.id — "Yield SUN 7,45%, Saatnya Borong atau Tunggu Lebih Tinggi?" (25 Okt 2026 20:58 WIB; deck source S3); corroborated by kalderanews S1 (10Y SUN 7.41%
A12: 10-year US Treasury yield | B12: m.rf_usd | C12: 0.04989 | D12: Yahoo Finance ^TNX (US 10-year Treasury yield)
A13: Indonesia sovereign default spread (Damodaran) | B13: m.default_spread_id | C13: 0.0162 | D13: Damodaran country risk premiums (https://pages.stern.nyu.edu/~adamodar/New_Home_Page/datafile/ctryprem.html), page dated January 5, 2026, read 2026-10-30
A14: Mature-market equity risk premium (Damodaran) | B14: m.erp_mature | C14: 0.0423 | D14: Damodaran country risk premiums (https://pages.stern.nyu.edu/~adamodar/New_Home_Page/datafile/ctryprem.html), page dated January 5, 2026, read 2026-10-30
A15: Indonesia country risk premium (Damodaran) | B15: m.crp_id | C15: 0.0246 | D15: Damodaran country risk premiums (https://pages.stern.nyu.edu/~adamodar/New_Home_Page/datafile/ctryprem.html), page dated January 5, 2026, read 2026-10-30
A16: House pre-tax corporate debt spread over the risk-free | B16: m.debt_spread_corp | C16: 0.02 | D16: SEED house assumption pending the macro desk: 200 bp over the risk-free rate for an average IDX corporate borrower
A17: Indonesia statutory corporate income tax rate | B17: m.tax_rate_id | C17: 0.22 | D17: Law 7/2021 on Harmonisation of Tax Regulations (UU HPP): 22% corporate income tax from fiscal 2022
A19: Table coal.royalty_iup_high: IUP open-pit coal royalty by HBA band — above 5,200 kcal/kg GAR
B20: 0 | C20: 0.095
B21: 70 | C21: 0.115
B22: 90 | C22: 0.135
A24: Table coal.royalty_iupk: IUPK (ex-PKP2B) coal royalty rate by HBA band
B25: 0 | C25: 0.15
B26: 70 | C26: 0.18
B27: 120 | C27: 0.19
B28: 140 | C28: 0.22
B29: 160 | C29: 0.25
B30: 180 | C30: 0.28

Sheet Comps
A1: Ticker | B1: Company | C1: Rating | D1: Target (IDR) | E1: Price (IDR) | F1: Exp. 12m TR | G1: Value today | H1: P/E FY+0 | I1: EV/EBITDA FY+0 | J1: Div. yield FY+0
A2: AADI.JK | B2: PT Adaro Andalan Indonesia Tbk | C2: ='AADI'!$C$157 | D2: ='AADI'!$C$155 | E2: ='AADI'!$C$102 | F2: ='AADI'!$C$156 | G2: ='AADI'!$C$145 | H2: 3.903612 | I2: 2.2336 | J2: 0.217747
A3: ADMR.JK | B3: PT Alamtri Minerals Indonesia Tbk | C3: ='ADMR'!$C$163 | D3: ='ADMR'!$C$161 | E3: ='ADMR'!$C$102 | F3: ='ADMR'!$C$162 | G3: ='ADMR'!$C$151 | H3: 7.973483 | I3: 6.058408 | J3: 0.043895
A4: ARII.JK | B4: PT Atlas Resources Tbk | C4: ='ARII'!$C$151 | D4: ='ARII'!$C$149 | E4: ='ARII'!$C$102 | F4: ='ARII'!$C$150 | G4: ='ARII'!$C$139 | H4: 5.500113 | I4: 1.41805 | J4: 0
A5: BOSS.JK | B5: PT. Borneo Olah Sarana Sukses Tbk | C5: ='BOSS'!$C$151 | D5: ='BOSS'!$C$149 | E5: ='BOSS'!$C$102 | F5: ='BOSS'!$C$150 | G5: ='BOSS'!$C$139 | J5: 0
A6: BSSR.JK | B6: PT Baramulti Suksessarana Tbk | C6: ='BSSR'!$C$163 | D6: ='BSSR'!$C$161 | E6: ='BSSR'!$C$102 | F6: ='BSSR'!$C$162 | G6: ='BSSR'!$C$151 | H6: 5.839242 | I6: 3.920091 | J6: 0.119879
A7: BUMI.JK | B7: PT Bumi Resources Tbk | C7: ='BUMI'!$C$166 | D7: ='BUMI'!$C$164 | E7: ='BUMI'!$C$102 | F7: ='BUMI'!$C$165 | G7: ='BUMI'!$C$145 | H7: 11.188124 | I7: 3.575106 | J7: 0
A8: BYAN.JK | B8: PT Bayan Resources Tbk. | C8: ='BYAN'!$C$172 | D8: ='BYAN'!$C$170 | E8: ='BYAN'!$C$102 | F8: ='BYAN'!$C$171 | G8: ='BYAN'!$C$151 | H8: 17.228205 | I8: 11.497956 | J8: 0.042372
A9: GEMS.JK | B9: PT Golden Energy Mines Tbk | C9: ='GEMS'!$C$166 | D9: ='GEMS'!$C$164 | E9: ='GEMS'!$C$102 | F9: ='GEMS'!$C$165 | G9: ='GEMS'!$C$145 | H9: 4.149274 | I9: 2.604119 | J9: 0.109176
A10: GTBO.JK | B10: PT Garda Tujuh Buana Tbk | C10: ='GTBO'!$C$151 | D10: ='GTBO'!$C$149 | E10: ='GTBO'!$C$102 | F10: ='GTBO'!$C$150 | G10: ='GTBO'!$C$139 | I10: 7.994147 | J10: 0
A11: IATA.JK | B11: PT MNC Energy Investments Tbk | C11: ='IATA'!$C$157 | D11: ='IATA'!$C$155 | E11: ='IATA'!$C$102 | F11: ='IATA'!$C$156 | G11: ='IATA'!$C$145 | H11: 58.502712 | I11: 20.321764 | J11: 0
A12: INDY.JK | B12: PT. Indika Energy Tbk | C12: ='INDY'!$C$163 | D12: ='INDY'!$C$161 | E12: ='INDY'!$C$102 | F12: ='INDY'!$C$162 | G12: ='INDY'!$C$151 | H12: 5.988004 | I12: 2.649006 | J12: 0.0501
A13: ITMG.JK | B13: PT Indo Tambangraya Megah Tbk | C13: ='ITMG'!$C$163 | D13: ='ITMG'!$C$161 | E13: ='ITMG'!$C$102 | F13: ='ITMG'!$C$162 | G13: ='ITMG'!$C$151 | H13: 5.557101 | I13: 1.715011 | J13: 0.10797
A14: KKGI.JK | B14: PT Resource Alam Indonesia Tbk | C14: ='KKGI'!$C$151 | D14: ='KKGI'!$C$149 | E14: ='KKGI'!$C$102 | F14: ='KKGI'!$C$150 | G14: ='KKGI'!$C$139 | H14: 8.401706 | I14: 1.803794 | J14: 0.040468
A15: MBAP.JK | B15: PT Mitrabara Adiperdana Tbk | C15: ='MBAP'!$C$157 | D15: ='MBAP'!$C$155 | E15: ='MBAP'!$C$102 | F15: ='MBAP'!$C$156 | G15: ='MBAP'!$C$145 | H15: 9.039776 | I15: 1.427961 | J15: 0
A16: MCOL.JK | B16: PT Prima Andalan Mandiri Tbk | C16: ='MCOL'!$C$172 | D16: ='MCOL'!$C$170 | E16: ='MCOL'!$C$102 | F16: ='MCOL'!$C$171 | G16: ='MCOL'!$C$151 | H16: 6.336065 | I16: 2.513936 | J16: 0.089193
A17: PTBA.JK | B17: PT Bukit Asam (Persero) Tbk | C17: ='PTBA'!$C$163 | D17: ='PTBA'!$C$161 | E17: ='PTBA'!$C$102 | F17: ='PTBA'!$C$162 | G17: ='PTBA'!$C$151 | H17: 4.618029 | I17: 2.724873 | J17: 0.129926
A18: SINI.JK | B18: PT Singaraja Putra Tbk | C18: ='SINI'!$C$166 | D18: ='SINI'!$C$164 | E18: ='SINI'!$C$102 | F18: ='SINI'!$C$165 | G18: ='SINI'!$C$145 | I18: 97.625959 | J18: 0
A19: SMMT.JK | B19: PT Golden Eagle Energy Tbk | C19: ='SMMT'!$C$166 | D19: ='SMMT'!$C$164 | E19: ='SMMT'!$C$102 | F19: ='SMMT'!$C$165 | G19: ='SMMT'!$C$145 | H19: 25.343029 | I19: 16.45252 | J19: 0.009865

Sheet AADI
A1: PT Adaro Andalan Indonesia Tbk (AADI.JK) — Coal producers
A2: Units: USD m; per-share in USD unless marked IDR. Model asof 2026-10-30 · data 2026-10-26
A4: Line | C4: Scalar | D4: FY2022A | E4: FY2023A | F4: FY2024A | G4: FY2025A | H4: FY2026E | I4: FY2027E | J4: FY2028E | K4: FY2029E | L4: FY2030E | M4: FY2031E | N4: FY2032E | O4: FY2033E | P4: FY2034E | Q4: FY2035E | R4: FY2036E | S4: FY2037E
A6: PARAMETERS
A7: horizon | C7: 12
A8: ps_factor | C8: 1
A9: reserves | C9: 1000
A10: unit_factor | C10: 1
A11: vp_factor | C11: 1
A13: INPUTS (company assumptions)
A14: Sales volume plan | B14: a.volume | H14: 71.94 | I14: 71.94 | J14: 71.94 | K14: 71.94 | L14: 71.94 | M14: 71.94 | N14: 71.94 | O14: 71.94 | P14: 71.94 | Q14: 71.94 | R14: 71.94 | S14: 71.94
A15: Realised price / benchmark | B15: a.realisation | H15: 0.63 | I15: 0.63 | J15: 0.63 | K15: 0.63 | L15: 0.63 | M15: 0.63 | N15: 0.63 | O15: 0.63 | P15: 0.63 | Q15: 0.63 | R15: 0.63 | S15: 0.63
A16: Share of volume under a price cap (e.g. DMO) | B16: a.capped_share | H16: 0.25 | I16: 0.25 | J16: 0.25 | K16: 0.25 | L16: 0.25 | M16: 0.25 | N16: 0.25 | O16: 0.25 | P16: 0.25 | Q16: 0.25 | R16: 0.25 | S16: 0.25
A17: Strip ratio (bcm per tonne) or cost-intensity factor | B17: a.strip_ratio | H17: 4.35 | I17: 4.35 | J17: 4.35 | K17: 4.35 | L17: 4.35 | M17: 4.35 | N17: 4.35 | O17: 4.35 | P17: 4.35 | Q17: 4.35 | R17: 4.35 | S17: 4.35
A18: Mining cost per bcm (or per unit when intensity is 1) | B18: a.cost_per_bcm | H18: 3 | I18: 3 | J18: 3 | K18: 3 | L18: 3 | M18: 3.06 | N18: 3.1212 | O18: 3.183624 | P18: 3.2472965 | Q18: 3.3122424 | R18: 3.3784873 | S18: 3.446057
A19: Fuel share of mining cost | B19: a.fuel_share | C19: 0.3
A20: Other cash cost per unit (haul, barge, process) | B20: a.other_cost_unit | H20: 26.4 | I20: 26.4 | J20: 26.4 | K20: 26.4 | L20: 26.4 | M20: 26.928 | N20: 27.46656 | O20: 28.015891 | P20: 28.576209 | Q20: 29.147733 | R20: 29.730688 | S20: 30.325302
A21: Royalty rate (flat regimes) | B21: a.royalty_rate | H21: 0.142 | I21: 0.142 | J21: 0.142 | K21: 0.142 | L21: 0.142 | M21: 0.142 | N21: 0.142 | O21: 0.142 | P21: 0.142 | Q21: 0.142 | R21: 0.142 | S21: 0.142
A22: Other revenue | B22: a.other_revenue | H22: 0 | I22: 0 | J22: 0 | K22: 0 | L22: 0 | M22: 0 | N22: 0 | O22: 0 | P22: 0 | Q22: 0 | R22: 0 | S22: 0
A23: Gross margin on other revenue | B23: a.other_margin | C23: 0.1
A24: D&A per unit (reporting currency) | B24: a.da_unit | H24: 1.73 | I24: 1.73 | J24: 1.73 | K24: 1.73 | L24: 1.73 | M24: 1.7646 | N24: 1.799892 | O24: 1.8358898 | P24: 1.8726076 | Q24: 1.9100598 | R24: 1.948261 | S24: 1.9872262
A25: Sustaining capex per unit (reporting currency) | B25: a.capex_unit | H25: 5 | I25: 5 | J25: 5 | K25: 5 | L25: 5 | M25: 5.1 | N25: 5.202 | O25: 5.30604 | P25: 5.4121608 | Q25: 5.520404 | R25: 5.6308121 | S25: 5.7434283
A26: Other capex (expansion projects) | B26: a.capex_other | H26: 0 | I26: 0 | J26: 0 | K26: 0 | L26: 0 | M26: 0 | N26: 0 | O26: 0 | P26: 0 | Q26: 0 | R26: 0 | S26: 0
A27: Operating working capital / revenue | B27: a.nwc_pct | H27: -0.034701 | I27: -0.034701 | J27: -0.034701 | K27: -0.034701 | L27: -0.034701 | M27: -0.034701 | N27: -0.034701 | O27: -0.034701 | P27: -0.034701 | Q27: -0.034701 | R27: -0.034701 | S27: -0.034701
A28: Effective tax rate | B28: a.tax_rate | H28: 0.169858 | I28: 0.169858 | J28: 0.169858 | K28: 0.169858 | L28: 0.169858 | M28: 0.169858 | N28: 0.169858 | O28: 0.169858 | P28: 0.169858 | Q28: 0.169858 | R28: 0.169858 | S28: 0.169858
A29: Cost of debt (on opening debt) | B29: a.cost_of_debt | C29: 0.05544
A30: Yield on opening cash | B30: a.cash_yield | C30: 0.032987
A31: Net new borrowing | B31: a.net_borrowing | H31: 0 | I31: 0 | J31: 0 | K31: 0 | L31: 0 | M31: 0 | N31: 0 | O31: 0 | P31: 0 | Q31: 0 | R31: 0 | S31: 0
A32: Other non-operating items | B32: a.other_nonop | H32: 0 | I32: 0 | J32: 0 | K32: 0 | L32: 0 | M32: 0 | N32: 0 | O32: 0 | P32: 0 | Q32: 0 | R32: 0 | S32: 0
A33: Minorities' share of net profit | B33: a.minority_pct | H33: 0.100896 | I33: 0.100896 | J33: 0.100896 | K33: 0.100896 | L33: 0.100896 | M33: 0.100896 | N33: 0.100896 | O33: 0.100896 | P33: 0.100896 | Q33: 0.100896 | R33: 0.100896 | S33: 0.100896
A34: Dividend payout | B34: a.payout | H34: 0.85 | I34: 0.7 | J34: 0.6 | K34: 0.6 | L34: 0.6 | M34: 0.55 | N34: 0.55 | O34: 0.55 | P34: 0.55 | Q34: 0.55 | R34: 0.55 | S34: 0.55
A35: Change in share count | B35: a.share_change | H35: 0 | I35: 0 | J35: 0 | K35: 0 | L35: 0 | M35: 0 | N35: 0 | O35: 0 | P35: 0 | Q35: 0 | R35: 0 | S35: 0
A36: Terminal growth (DCF) | B36: a.terminal_growth | C36: 0
A37: SG&A / revenue | B37: a.opex_pct | H37: 0.052 | I37: 0.052 | J37: 0.052 | K37: 0.052 | L37: 0.052 | M37: 0.052 | N37: 0.052 | O37: 0.052 | P37: 0.052 | Q37: 0.052 | R37: 0.052 | S37: 0.052
A39: MODEL
A40: Reserves remaining (close) | B40: reserves | G40: 1000 | H40: =MAX((G40-H41),0) | I40: =MAX((H40-I41),0) | J40: =MAX((I40-J41),0) | K40: =MAX((J40-K41),0) | L40: =MAX((K40-L41),0) | M40: =MAX((L40-M41),0) | N40: =MAX((M40-N41),0) | O40: =MAX((N40-O41),0) | ... S40: =MAX((R40-S41),0)
A41: Sales volume | B41: volume | E41: 63.4 | F41: 68.06 | G41: 71.94 | H41: =IF(($C$9>0),MIN(H14,MAX(G40,0)),H14) | I41: =IF(($C$9>0),MIN(I14,MAX(H40,0)),I14) | J41: =IF(($C$9>0),MIN(J14,MAX(I40,0)),J14) | K41: =IF(($C$9>0),MIN(K14,MAX(J40,0)),K14) | L41: =IF(($C$9>0),MIN(L14,MAX(K40,0)),L14) | M41: =IF(($C$9>0),MIN(M14,MAX(L40,0)),M14) | N41: =IF(($C$9>0),MIN(N14,MAX(M40,0)),N14) | O41: =IF(($C$9>0),MIN(O14,MAX(N40,0)),O14) | ... S41: =IF(($C$9>0),MIN(S14,MAX(R40,0)),S14)
A42: Benchmark price | B42: benchmark | H42: =Drivers!$L$6 | I42: =Drivers!$M$6 | J42: =Drivers!$N$6 | K42: =Drivers!$O$6 | L42: =Drivers!$P$6 | M42: =Drivers!$Q$6 | N42: =Drivers!$R$6 | O42: =Drivers!$S$6 | P42: =Drivers!$T$6 | Q42: =Drivers!$U$6 | R42: =Drivers!$V$6 | S42: =Drivers!$W$6
A43: Average selling price | B43: asp | H43: =(((H15*H42)*(1-H16))+(MIN(Drivers!$L$4,(H15*H42))*H16)) | I43: =(((I15*I42)*(1-I16))+(MIN(Drivers!$M$4,(I15*I42))*I16)) | J43: =(((J15*J42)*(1-J16))+(MIN(Drivers!$N$4,(J15*J42))*J16)) | K43: =(((K15*K42)*(1-K16))+(MIN(Drivers!$O$4,(K15*K42))*K16)) | L43: =(((L15*L42)*(1-L16))+(MIN(Drivers!$P$4,(L15*L42))*L16)) | M43: =(((M15*M42)*(1-M16))+(MIN(Drivers!$Q$4,(M15*M42))*M16)) | N43: =(((N15*N42)*(1-N16))+(MIN(Drivers!$R$4,(N15*N42))*N16)) | O43: =(((O15*O42)*(1-O16))+(MIN(Drivers!$S$4,(O15*O42))*O16)) | P43: =(((P15*P42)*(1-P16))+(MIN(Drivers!$T$4,(P15*P42))*P16)) | Q43: =(((Q15*Q42)*(1-Q16))+(MIN(Drivers!$U$4,(Q15*Q42))*Q16)) | R43: =(((R15*R42)*(1-R16))+(MIN(Drivers!$V$4,(R15*R42))*R16)) | S43: =(((S15*S42)*(1-S16))+(MIN(Drivers!$W$4,(S15*S42))*S16))
A44: Realisation vs benchmark | B44: realisation_line | H44: =IF(H42=0,0,H43/H42) | I44: =IF(I42=0,0,I43/I42) | J44: =IF(J42=0,0,J43/J42) | K44: =IF(K42=0,0,K43/K42) | L44: =IF(L42=0,0,L43/L42) | M44: =IF(M42=0,0,M43/M42) | N44: =IF(N42=0,0,N43/N42) | O44: =IF(O42=0,0,O43/O42) | ... S44: =IF(S42=0,0,S43/S42)
A45: Cash cost per unit (ex-royalty) | B45: unit_cost | H45: =(((H17*H18)*(1+($C$19*(IF(Drivers!$J$8=0,0,Drivers!$L$8/Drivers!$J$8)-1))))+H20) | I45: =(((I17*I18)*(1+($C$19*(IF(Drivers!$J$8=0,0,Drivers!$M$8/Drivers!$J$8)-1))))+I20) | J45: =(((J17*J18)*(1+($C$19*(IF(Drivers!$J$8=0,0,Drivers!$N$8/Drivers!$J$8)-1))))+J20) | K45: =(((K17*K18)*(1+($C$19*(IF(Drivers!$J$8=0,0,Drivers!$O$8/Drivers!$J$8)-1))))+K20) | L45: =(((L17*L18)*(1+($C$19*(IF(Drivers!$J$8=0,0,Drivers!$P$8/Drivers!$J$8)-1))))+L20) | M45: =(((M17*M18)*(1+($C$19*(IF(Drivers!$J$8=0,0,Drivers!$Q$8/Drivers!$J$8)-1))))+M20) | N45: =(((N17*N18)*(1+($C$19*(IF(Drivers!$J$8=0,0,Drivers!$R$8/Drivers!$J$8)-1))))+N20) | O45: =(((O17*O18)*(1+($C$19*(IF(Drivers!$J$8=0,0,Drivers!$S$8/Drivers!$J$8)-1))))+O20) | P45: =(((P17*P18)*(1+($C$19*(IF(Drivers!$J$8=0,0,Drivers!$T$8/Drivers!$J$8)-1))))+P20) | Q45: =(((Q17*Q18)*(1+($C$19*(IF(Drivers!$J$8=0,0,Drivers!$U$8/Drivers!$J$8)-1))))+Q20) | R45: =(((R17*R18)*(1+($C$19*(IF(Drivers!$J$8=0,0,Drivers!$V$8/Drivers!$J$8)-1))))+R20) | S45: =(((S17*S18)*(1+($C$19*(IF(Drivers!$J$8=0,0,Drivers!$W$8/Drivers!$J$8)-1))))+S20)
A46: Strip ratio | B46: strip_ratio_line | F46: 4.35 | H46: =H17 | I46: =I17 | J46: =J17 | K46: =K17 | L46: =L17 | M46: =M17 | N46: =N17 | O46: =O17 | ... S46: =S17
A47: Royalty rate | B47: royalty_rate | H47: =H21 | I47: =I21 | J47: =J21 | K47: =K21 | L47: =L21 | M47: =M21 | N47: =N21 | O47: =O21 | ... S47: =S21
A48: EBITDA per unit (price currency) | B48: ebitda_per_unit | E48: 22.418502 | F48: 18.432177 | G48: 15.83186 | H48: =IF((H41*$C$10)=0,0,H61/(H41*$C$10)) | I48: =IF((I41*$C$10)=0,0,I61/(I41*$C$10)) | J48: =IF((J41*$C$10)=0,0,J61/(J41*$C$10)) | K48: =IF((K41*$C$10)=0,0,K61/(K41*$C$10)) | L48: =IF((L41*$C$10)=0,0,L61/(L41*$C$10)) | M48: =IF((M41*$C$10)=0,0,M61/(M41*$C$10)) | N48: =IF((N41*$C$10)=0,0,N61/(N41*$C$10)) | O48: =IF((O41*$C$10)=0,0,O61/(O41*$C$10)) | ... S48: =IF((S41*$C$10)=0,0,S61/(S41*$C$10))
A49: Cash cost + royalty per unit (price currency) | B49: cash_cost_money_per_unit | H49: =IF((H41*$C$10)=0,0,(H53+H52)/(H41*$C$10)) | I49: =IF((I41*$C$10)=0,0,(I53+I52)/(I41*$C$10)) | J49: =IF((J41*$C$10)=0,0,(J53+J52)/(J41*$C$10)) | K49: =IF((K41*$C$10)=0,0,(K53+K52)/(K41*$C$10)) | L49: =IF((L41*$C$10)=0,0,(L53+L52)/(L41*$C$10)) | M49: =IF((M41*$C$10)=0,0,(M53+M52)/(M41*$C$10)) | N49: =IF((N41*$C$10)=0,0,(N53+N52)/(N41*$C$10)) | O49: =IF((O41*$C$10)=0,0,(O53+O52)/(O41*$C$10)) | ... S49: =IF((S41*$C$10)=0,0,(S53+S52)/(S41*$C$10))
A50: Main product revenue | B50: revenue_main | H50: =((H41*H43)*$C$10) | I50: =((I41*I43)*$C$10) | J50: =((J41*J43)*$C$10) | K50: =((K41*K43)*$C$10) | L50: =((L41*L43)*$C$10) | M50: =((M41*M43)*$C$10) | N50: =((N41*N43)*$C$10) | O50: =((O41*O43)*$C$10) | ... S50: =((S41*S43)*$C$10)
A51: Other revenue | B51: other_revenue | H51: =H22 | I51: =I22 | J51: =J22 | K51: =K22 | L51: =L22 | M51: =M22 | N51: =N22 | O51: =O22 | ... S51: =S22
A52: Royalty | B52: royalty | H52: =(H50*H47) | I52: =(I50*I47) | J52: =(J50*J47) | K52: =(K50*K47) | L52: =(L50*L47) | M52: =(M50*M47) | N52: =(N50*N47) | O52: =(O50*O47) | ... S52: =(S50*S47)
A53: Cash costs | B53: cash_cost | H53: =((H41*H45)*$C$10) | I53: =((I41*I45)*$C$10) | J53: =((J41*J45)*$C$10) | K53: =((K41*K45)*$C$10) | L53: =((L41*L45)*$C$10) | M53: =((M41*M45)*$C$10) | N53: =((N41*N45)*$C$10) | O53: =((O41*O45)*$C$10) | ... S53: =((S41*S45)*$C$10)
A54: Cost of other revenue | B54: other_cogs | H54: =(H51*(1-$C$23)) | I54: =(I51*(1-$C$23)) | J54: =(J51*(1-$C$23)) | K54: =(K51*(1-$C$23)) | L54: =(L51*(1-$C$23)) | M54: =(M51*(1-$C$23)) | N54: =(N51*(1-$C$23)) | O54: =(O51*(1-$C$23)) | ... S54: =(S51*(1-$C$23))
A55: Revenue | B55: revenue | D55: 7725.933 | E55: 5915.408 | F55: 5319.582 | G55: 4910.263 | H55: =(H50+H51) | I55: =(I50+I51) | J55: =(J50+J51) | K55: =(K50+K51) | L55: =(L50+L51) | M55: =(M50+M51) | N55: =(N50+N51) | O55: =(O50+O51) | ... S55: =(S50+S51)
A56: Cost of revenue | B56: cogs | D56: 3776.856 | E56: 4186.532 | F56: 3853.631 | G56: 3648.568 | H56: =(((H53+H52)+H54)+H60) | I56: =(((I53+I52)+I54)+I60) | J56: =(((J53+J52)+J54)+J60) | K56: =(((K53+K52)+K54)+K60) | L56: =(((L53+L52)+L54)+L60) | M56: =(((M53+M52)+M54)+M60) | N56: =(((N53+N52)+N54)+N60) | O56: =(((O53+O52)+O54)+O60) | ... S56: =(((S53+S52)+S54)+S60)
A57: Gross profit | B57: gross_profit | D57: 3949.077 | E57: 1728.876 | F57: 1465.951 | G57: 1261.695 | H57: =(H55-H56) | I57: =(I55-I56) | J57: =(J55-J56) | K57: =(K55-K56) | L57: =(L55-L56) | M57: =(M55-M56) | N57: =(N55-N56) | O57: =(O55-O56) | ... S57: =(S55-S56)
A58: SG&A and other opex | B58: opex | D58: 290.352 | E58: 311.777 | F58: 315.504 | G58: 247.086 | H58: =(H55*H37) | I58: =(I55*I37) | J58: =(J55*J37) | K58: =(K55*K37) | L58: =(L55*L37) | M58: =(M55*M37) | N58: =(N55*N37) | O58: =(O55*O37) | ... S58: =(S55*S37)
A59: EBIT | B59: ebit | D59: 3658.725 | E59: 1417.099 | F59: 1150.447 | G59: 1014.609 | H59: =(H57-H58) | I59: =(I57-I58) | J59: =(J57-J58) | K59: =(K57-K58) | L59: =(L57-L58) | M59: =(M57-M58) | N59: =(N57-N58) | O59: =(O57-O58) | ... S59: =(S57-S58)
A60: Depreciation & amortisation | B60: da | D60: 3.2 | E60: 4.234 | F60: 104.047 | G60: 124.335 | H60: =((H41*H24)*$C$10) | I60: =((I41*I24)*$C$10) | J60: =((J41*J24)*$C$10) | K60: =((K41*K24)*$C$10) | L60: =((L41*L24)*$C$10) | M60: =((M41*M24)*$C$10) | N60: =((N41*N24)*$C$10) | O60: =((O41*O24)*$C$10) | ... S60: =((S41*S24)*$C$10)
A61: EBITDA | B61: ebitda | D61: 3661.925 | E61: 1421.333 | F61: 1254.494 | G61: 1138.944 | H61: =(H59+H60) | I61: =(I59+I60) | J61: =(J59+J60) | K61: =(K59+K60) | L61: =(L59+L60) | M61: =(M59+M60) | N61: =(N59+N60) | O61: =(O59+O60) | ... S61: =(S59+S60)
A62: Interest expense | B62: interest_expense | D62: 60.325 | E62: 66.429 | F62: 73.213 | G62: 51.485 | H62: =(G82*$C$29) | I62: =(H82*$C$29) | J62: =(I82*$C$29) | K62: =(J82*$C$29) | L62: =(K82*$C$29) | M62: =(L82*$C$29) | N62: =(M82*$C$29) | O62: =(N82*$C$29) | ... S62: =(R82*$C$29)
A63: Interest income | B63: interest_income | D63: 55.73 | E63: 111.088 | F63: 85.553 | G63: 53.703 | H63: =(G81*$C$30) | I63: =(H81*$C$30) | J63: =(I81*$C$30) | K63: =(J81*$C$30) | L63: =(K81*$C$30) | M63: =(L81*$C$30) | N63: =(M81*$C$30) | O63: =(N81*$C$30) | ... S63: =(R81*$C$30)
A64: Other non-operating | B64: other_nonop | D64: 193.944 | E64: 98.217 | F64: 377.289 | G64: 38.519 | H64: =H32 | I64: =I32 | J64: =J32 | K64: =K32 | L64: =L32 | M64: =M32 | N64: =N32 | O64: =O32 | ... S64: =S32
A65: Profit before tax | B65: pbt | D65: 3848.074 | E65: 1559.975 | F65: 1540.076 | G65: 1055.346 | H65: =(((H59-H62)+H63)+H64) | I65: =(((I59-I62)+I63)+I64) | J65: =(((J59-J62)+J63)+J64) | K65: =(((K59-K62)+K63)+K64) | L65: =(((L59-L62)+L63)+L64) | M65: =(((M59-M62)+M63)+M64) | N65: =(((N59-N62)+N63)+N64) | O65: =(((O59-O62)+O63)+O64) | ... S65: =(((S59-S62)+S63)+S64)
A66: Tax | B66: tax | D66: 1498.502 | E66: 274.084 | F66: 213.34 | G66: 206.162 | H66: =(MAX(H65,0)*H28) | I66: =(MAX(I65,0)*I28) | J66: =(MAX(J65,0)*J28) | K66: =(MAX(K65,0)*K28) | L66: =(MAX(L65,0)*L28) | M66: =(MAX(M65,0)*M28) | N66: =(MAX(N65,0)*N28) | O66: =(MAX(O65,0)*O28) | ... S66: =(MAX(S65,0)*S28)
A67: Net profit (incl. minorities) | B67: np | D67: 2349.572 | E67: 1285.891 | F67: 1326.736 | G67: 849.184 | H67: =(H65-H66) | I67: =(I65-I66) | J67: =(J65-J66) | K67: =(K65-K66) | L67: =(L65-L66) | M67: =(M65-M66) | N67: =(N65-N66) | O67: =(O65-O66) | ... S67: =(S65-S66)
A68: Minority interests | B68: minority | D68: 0 | E68: 142.078 | F68: 115.938 | G68: 89.004 | H68: =(H67*H33) | I68: =(I67*I33) | J68: =(J67*J33) | K68: =(K67*K33) | L68: =(L67*L33) | M68: =(M67*M33) | N68: =(N67*N33) | O68: =(O67*O33) | ... S68: =(S67*S33)
A69: Net profit to parent | B69: np_parent | D69: 2349.572 | E69: 1143.813 | F69: 1210.798 | G69: 760.18 | H69: =(H67-H68) | I69: =(I67-I68) | J69: =(J67-J68) | K69: =(K67-K68) | L69: =(L67-L68) | M69: =(M67-M68) | N69: =(N67-N68) | O69: =(O67-O68) | ... S69: =(S67-S68)
A70: Shares outstanding (m) | B70: shares | D70: 7786.8918 | E70: 7786.8918 | F70: 7786.8918 | G70: 7786.8918 | H70: =(G70*(1+H35)) | I70: =(H70*(1+I35)) | J70: =(I70*(1+J35)) | K70: =(J70*(1+K35)) | L70: =(K70*(1+L35)) | M70: =(L70*(1+M35)) | N70: =(M70*(1+N35)) | O70: =(N70*(1+O35)) | ... S70: =(R70*(1+S35))
A71: EPS | B71: eps | D71: 0.30173426 | E71: 0.14688955 | F71: 0.15549182 | G71: 0.097623034 | H71: =(IF(H70=0,0,H69/H70)*$C$8) | I71: =(IF(I70=0,0,I69/I70)*$C$8) | J71: =(IF(J70=0,0,J69/J70)*$C$8) | K71: =(IF(K70=0,0,K69/K70)*$C$8) | L71: =(IF(L70=0,0,L69/L70)*$C$8) | M71: =(IF(M70=0,0,M69/M70)*$C$8) | N71: =(IF(N70=0,0,N69/N70)*$C$8) | O71: =(IF(O70=0,0,O69/O70)*$C$8) | ... S71: =(IF(S70=0,0,S69/S70)*$C$8)
A72: DPS (declared on the year) | B72: dps | F72: 0.032346258 | G72: 0.025847699 | H72: =(MAX(H71,0)*H34) | I72: =(MAX(I71,0)*I34) | J72: =(MAX(J71,0)*J34) | K72: =(MAX(K71,0)*K34) | L72: =(MAX(L71,0)*L34) | M72: =(MAX(M71,0)*M34) | N72: =(MAX(N71,0)*N34) | O72: =(MAX(O71,0)*O34) | ... S72: =(MAX(S71,0)*S34)
A73: Dividends paid | B73: dividends_paid | D73: 1511.144 | E73: 1013.78 | F73: 2971.696 | G73: 250 | H73: =IF($C$8=0,0,(G72*G70)/$C$8) | I73: =IF($C$8=0,0,(H72*H70)/$C$8) | J73: =IF($C$8=0,0,(I72*I70)/$C$8) | K73: =IF($C$8=0,0,(J72*J70)/$C$8) | L73: =IF($C$8=0,0,(K72*K70)/$C$8) | M73: =IF($C$8=0,0,(L72*L70)/$C$8) | N73: =IF($C$8=0,0,(M72*M70)/$C$8) | O73: =IF($C$8=0,0,(N72*N70)/$C$8) | ... S73: =IF($C$8=0,0,(R72*R70)/$C$8)
A74: Capital expenditure | B74: capex | D74: 120.09 | E74: 272.203 | F74: 371.117 | G74: 324.613 | H74: =(((H41*H25)*$C$10)+H26) | I74: =(((I41*I25)*$C$10)+I26) | J74: =(((J41*J25)*$C$10)+J26) | K74: =(((K41*K25)*$C$10)+K26) | L74: =(((L41*L25)*$C$10)+L26) | M74: =(((M41*M25)*$C$10)+M26) | N74: =(((N41*N25)*$C$10)+N26) | O74: =(((O41*O25)*$C$10)+O26) | ... S74: =(((S41*S25)*$C$10)+S26)
A75: Change in working capital | B75: delta_nwc | E75: 817.198 | F75: 152.243 | G75: 155.645 | H75: =(H80-G80) | I75: =(I80-H80) | J75: =(J80-I80) | K75: =(K80-J80) | L75: =(L80-K80) | M75: =(M80-L80) | N75: =(N80-M80) | O75: =(O80-N80) | ... S75: =(S80-R80)
A76: Free cash flow to firm | B76: fcff | E76: 82.950983 | F76: 571.7676 | G76: 460.48198 | H76: =((((H59*(1-H28))+H60)-H74)-H75) | I76: =((((I59*(1-I28))+I60)-I74)-I75) | J76: =((((J59*(1-J28))+J60)-J74)-J75) | K76: =((((K59*(1-K28))+K60)-K74)-K75) | L76: =((((L59*(1-L28))+L60)-L74)-L75) | M76: =((((M59*(1-M28))+M60)-M74)-M75) | N76: =((((N59*(1-N28))+N60)-N74)-N75) | O76: =((((O59*(1-O28))+O60)-O74)-O75) | ... S76: =((((S59*(1-S28))+S60)-S74)-S75)
A77: Net borrowing | B77: net_borrowing | E77: -241.032 | F77: 527.003 | G77: -660.04 | H77: =H31 | I77: =I31 | J77: =J31 | K77: =K31 | L77: =L31 | M77: =M31 | N77: =N31 | O77: =O31 | ... S77: =S31
A78: Dividends to minorities | B78: minority_div | H78: =(MAX(G68,0)*H34) | I78: =(MAX(H68,0)*I34) | J78: =(MAX(I68,0)*J34) | K78: =(MAX(J68,0)*K34) | L78: =(MAX(K68,0)*L34) | M78: =(MAX(L68,0)*M34) | N78: =(MAX(M68,0)*N34) | O78: =(MAX(N68,0)*O34) | ... S78: =(MAX(R68,0)*S34)
A79: Free cash flow to equity | B79: fcfe | H79: =(((((H67+H60)-H74)-H75)+H77)-H78) | I79: =(((((I67+I60)-I74)-I75)+I77)-I78) | J79: =(((((J67+J60)-J74)-J75)+J77)-J78) | K79: =(((((K67+K60)-K74)-K75)+K77)-K78) | L79: =(((((L67+L60)-L74)-L75)+L77)-L78) | M79: =(((((M67+M60)-M74)-M75)+M77)-M78) | N79: =(((((N67+N60)-N74)-N75)+N77)-N78) | O79: =(((((O67+O60)-O74)-O75)+O77)-O78) | ... S79: =(((((S67+S60)-S74)-S75)+S77)-S78)
A80: Operating working capital | B80: nwc | D80: -1165.742 | E80: -348.544 | F80: -196.301 | G80: -40.656 | H80: =(H55*H27) | I80: =(I55*I27) | J80: =(J55*J27) | K80: =(K55*K27) | L80: =(L55*L27) | M80: =(M55*M27) | N80: =(N55*N27) | O80: =(O55*O27) | ... S80: =(S55*S27)
A81: Cash & equivalents | B81: cash | D81: 3485.262 | E81: 2582.751 | F81: 1581.194 | G81: 958.528 | H81: =(((((((G81+H67)+H60)-H74)-H75)+H77)-H73)-H78) | I81: =(((((((H81+I67)+I60)-I74)-I75)+I77)-I73)-I78) | J81: =(((((((I81+J67)+J60)-J74)-J75)+J77)-J73)-J78) | K81: =(((((((J81+K67)+K60)-K74)-K75)+K77)-K73)-K78) | L81: =(((((((K81+L67)+L60)-L74)-L75)+L77)-L73)-L78) | M81: =(((((((L81+M67)+M60)-M74)-M75)+M77)-M73)-M78) | N81: =(((((((M81+N67)+N60)-N74)-N75)+N77)-N73)-N78) | O81: =(((((((N81+O67)+O60)-O74)-O75)+O77)-O73)-O78) | ... S81: =(((((((R81+S67)+S60)-S74)-S75)+S77)-S73)-S78)
A82: Total debt | B82: debt | D82: 1200.209 | E82: 959.177 | F82: 1486.18 | G82: 826.14 | H82: =(G82+H77) | I82: =(H82+I77) | J82: =(I82+J77) | K82: =(J82+K77) | L82: =(K82+L77) | M82: =(L82+M77) | N82: =(M82+N77) | O82: =(N82+O77) | ... S82: =(R82+S77)
A83: Fixed assets (net) | B83: ppe | D83: 885.497 | E83: 970.728 | F83: 1390.949 | G83: 1685.015 | H83: =((G83+H74)-H60) | I83: =((H83+I74)-I60) | J83: =((I83+J74)-J60) | K83: =((J83+K74)-K60) | L83: =((K83+L74)-L60) | M83: =((L83+M74)-M60) | N83: =((M83+N74)-N60) | O83: =((N83+O74)-O60) | ... S83: =((R83+S74)-S60)
A84: Parent shareholders' equity | B84: equity | D84: 4115.713 | E84: 4366 | F84: 2998.891 | G84: 3333.55 | H84: =((G84+H69)-H73) | I84: =((H84+I69)-I73) | J84: =((I84+J69)-J73) | K84: =((J84+K69)-K73) | L84: =((K84+L69)-L73) | M84: =((L84+M69)-M73) | N84: =((M84+N69)-N73) | O84: =((N84+O69)-O73) | ... S84: =((R84+S69)-S73)
A85: Minority interest (balance sheet) | B85: minority_bs | D85: 392.503 | E85: 424.464 | F85: 364.591 | G85: 316.078 | H85: =((G85+H68)-H78) | I85: =((H85+I68)-I78) | J85: =((I85+J68)-J78) | K85: =((J85+K68)-K78) | L85: =((K85+L68)-L78) | M85: =((L85+M68)-M78) | N85: =((M85+N68)-N78) | O85: =((N85+O68)-O78) | ... S85: =((R85+S68)-S78)
A86: Other assets less other liabilities | B86: other_net | D86: 2503.408 | E86: 2544.706 | F86: 2073.82 | G86: 1872.881 | H86: =G86 | I86: =H86 | J86: =I86 | K86: =J86 | L86: =K86 | M86: =L86 | N86: =M86 | O86: =N86 | ... S86: =R86
A87: Balance check (should be zero) | B87: bs_check | H87: =((((((H81+H80)+H83)+H86)-H82)-H84)-H85) | I87: =((((((I81+I80)+I83)+I86)-I82)-I84)-I85) | J87: =((((((J81+J80)+J83)+J86)-J82)-J84)-J85) | K87: =((((((K81+K80)+K83)+K86)-K82)-K84)-K85) | L87: =((((((L81+L80)+L83)+L86)-L82)-L84)-L85) | M87: =((((((M81+M80)+M83)+M86)-M82)-M84)-M85) | N87: =((((((N81+N80)+N83)+N86)-N82)-N84)-N85) | O87: =((((((O81+O80)+O83)+O86)-O82)-O84)-O85) | ... S87: =((((((S81+S80)+S83)+S86)-S82)-S84)-S85)
A88: Net debt (cash) | B88: net_debt | D88: -2285.053 | E88: -1623.574 | F88: -95.014 | G88: -132.388 | H88: =(H82-H81) | I88: =(I82-I81) | J88: =(J82-J81) | K88: =(K82-K81) | L88: =(L82-L81) | M88: =(M82-M81) | N88: =(N82-N81) | O88: =(O82-O81) | ... S88: =(S82-S81)
A89: Book value per share | B89: bvps | D89: 0.52854375 | E89: 0.56068585 | F89: 0.38512042 | G89: 0.42809764 | H89: =(IF(H70=0,0,H84/H70)*$C$8) | I89: =(IF(I70=0,0,I84/I70)*$C$8) | J89: =(IF(J70=0,0,J84/J70)*$C$8) | K89: =(IF(K70=0,0,K84/K70)*$C$8) | L89: =(IF(L70=0,0,L84/L70)*$C$8) | M89: =(IF(M70=0,0,M84/M70)*$C$8) | N89: =(IF(N70=0,0,N84/N70)*$C$8) | O89: =(IF(O70=0,0,O84/O70)*$C$8) | ... S89: =(IF(S70=0,0,S84/S70)*$C$8)
A90: Revenue growth | B90: revenue_growth | E90: -0.23434387 | F90: -0.10072441 | G90: -0.076945707 | H90: =(IF(G55=0,0,H55/G55)-1) | I90: =(IF(H55=0,0,I55/H55)-1) | J90: =(IF(I55=0,0,J55/I55)-1) | K90: =(IF(J55=0,0,K55/J55)-1) | L90: =(IF(K55=0,0,L55/K55)-1) | M90: =(IF(L55=0,0,M55/L55)-1) | N90: =(IF(M55=0,0,N55/M55)-1) | O90: =(IF(N55=0,0,O55/N55)-1) | ... S90: =(IF(R55=0,0,S55/R55)-1)
A91: Gross margin | B91: gross_margin | D91: 0.51114564 | E91: 0.29226657 | F91: 0.27557635 | G91: 0.2569506 | H91: =IF(H55=0,0,H57/H55) | I91: =IF(I55=0,0,I57/I55) | J91: =IF(J55=0,0,J57/J55) | K91: =IF(K55=0,0,K57/K55) | L91: =IF(L55=0,0,L57/L55) | M91: =IF(M55=0,0,M57/M55) | N91: =IF(N55=0,0,N57/N55) | O91: =IF(O55=0,0,O57/O55) | ... S91: =IF(S55=0,0,S57/S55)
A92: EBITDA margin | B92: ebitda_margin | D92: 0.47397835 | E92: 0.24027641 | F92: 0.23582567 | G92: 0.23195173 | H92: =IF(H55=0,0,H61/H55) | I92: =IF(I55=0,0,I61/I55) | J92: =IF(J55=0,0,J61/J55) | K92: =IF(K55=0,0,K61/K55) | L92: =IF(L55=0,0,L61/L55) | M92: =IF(M55=0,0,M61/M55) | N92: =IF(N55=0,0,N61/N55) | O92: =IF(O55=0,0,O61/O55) | ... S92: =IF(S55=0,0,S61/S55)
A93: EBIT margin | B93: ebit_margin | D93: 0.47356416 | E93: 0.23956065 | F93: 0.21626643 | G93: 0.20663028 | H93: =IF(H55=0,0,H59/H55) | I93: =IF(I55=0,0,I59/I55) | J93: =IF(J55=0,0,J59/J55) | K93: =IF(K55=0,0,K59/K55) | L93: =IF(L55=0,0,L59/L55) | M93: =IF(M55=0,0,M59/M55) | N93: =IF(N55=0,0,N59/N55) | O93: =IF(O55=0,0,O59/O55) | ... S93: =IF(S55=0,0,S59/S55)
A94: Net margin | B94: np_margin | D94: 0.30411499 | E94: 0.19336164 | F94: 0.22761149 | G94: 0.15481452 | H94: =IF(H55=0,0,H69/H55) | I94: =IF(I55=0,0,I69/I55) | J94: =IF(J55=0,0,J69/J55) | K94: =IF(K55=0,0,K69/K55) | L94: =IF(L55=0,0,L69/L55) | M94: =IF(M55=0,0,M69/M55) | N94: =IF(N55=0,0,N69/N55) | O94: =IF(O55=0,0,O69/O55) | ... S94: =IF(S55=0,0,S69/S55)
A95: EPS growth | B95: eps_growth | E95: -0.5131824 | F95: 0.058562894 | G95: -0.37216613 | H95: =(IF(G71=0,0,H71/G71)-1) | I95: =(IF(H71=0,0,I71/H71)-1) | J95: =(IF(I71=0,0,J71/I71)-1) | K95: =(IF(J71=0,0,K71/J71)-1) | L95: =(IF(K71=0,0,L71/K71)-1) | M95: =(IF(L71=0,0,M71/L71)-1) | N95: =(IF(M71=0,0,N71/M71)-1) | O95: =(IF(N71=0,0,O71/N71)-1) | ... S95: =(IF(R71=0,0,S71/R71)-1)
A96: ROE | B96: roe | E96: 0.26971273 | F96: 0.32880269 | G96: 0.24009067 | H96: =IF(IF(2=0,0,(H84+G84)/2)=0,0,H69/IF(2=0,0,(H84+G84)/2)) | I96: =IF(IF(2=0,0,(I84+H84)/2)=0,0,I69/IF(2=0,0,(I84+H84)/2)) | J96: =IF(IF(2=0,0,(J84+I84)/2)=0,0,J69/IF(2=0,0,(J84+I84)/2)) | K96: =IF(IF(2=0,0,(K84+J84)/2)=0,0,K69/IF(2=0,0,(K84+J84)/2)) | L96: =IF(IF(2=0,0,(L84+K84)/2)=0,0,L69/IF(2=0,0,(L84+K84)/2)) | M96: =IF(IF(2=0,0,(M84+L84)/2)=0,0,M69/IF(2=0,0,(M84+L84)/2)) | N96: =IF(IF(2=0,0,(N84+M84)/2)=0,0,N69/IF(2=0,0,(N84+M84)/2)) | O96: =IF(IF(2=0,0,(O84+N84)/2)=0,0,O69/IF(2=0,0,(O84+N84)/2)) | ... S96: =IF(IF(2=0,0,(S84+R84)/2)=0,0,S69/IF(2=0,0,(S84+R84)/2))
A97: Net debt / EBITDA | B97: net_debt_ebitda | D97: -0.62400322 | E97: -1.1422897 | F97: -0.075738903 | G97: -0.1162375 | H97: =IF(H61=0,0,H88/H61) | I97: =IF(I61=0,0,I88/I61) | J97: =IF(J61=0,0,J88/J61) | K97: =IF(K61=0,0,K88/K61) | L97: =IF(L61=0,0,L88/L61) | M97: =IF(M61=0,0,M88/M61) | N97: =IF(N61=0,0,N88/N61) | O97: =IF(O61=0,0,O88/O61) | ... S97: =IF(S61=0,0,S88/S61)
A98: Payout ratio | B98: payout_ratio | F98: 0.20802546 | G98: 0.26477049 | H98: =IF(H71=0,0,H72/H71) | I98: =IF(I71=0,0,I72/I71) | J98: =IF(J71=0,0,J72/J71) | K98: =IF(K71=0,0,K72/K71) | L98: =IF(L71=0,0,L72/L71) | M98: =IF(M71=0,0,M72/M71) | N98: =IF(N71=0,0,N72/N71) | O98: =IF(O71=0,0,O72/O71) | ... S98: =IF(S71=0,0,S72/S71)
A99: Capex / revenue | B99: capex_revenue | D99: 0.015543754 | E99: 0.04601593 | F99: 0.069764316 | G99: 0.066109086 | H99: =IF(H55=0,0,H74/H55) | I99: =IF(I55=0,0,I74/I55) | J99: =IF(J55=0,0,J74/J55) | K99: =IF(K55=0,0,K74/K55) | L99: =IF(L55=0,0,L74/L55) | M99: =IF(M55=0,0,M74/M55) | N99: =IF(N55=0,0,N74/N55) | O99: =IF(O55=0,0,O74/O55) | ... S99: =IF(S55=0,0,S74/S55)
A101: VALUATION
A102: Last price (IDR) | C102: 11375
A103: Shares outstanding (m) | C103: 7786.8918
A104: IDR per USD (spot) | C104: 18138
A105: Debt at balance-sheet date | C105: 1010.001
...

Sheet ADMR
A1: PT Alamtri Minerals Indonesia Tbk (ADMR.JK) — Coal producers
A2: Units: USD m; per-share in USD unless marked IDR. Model asof 2026-10-30 · data 2026-10-26
A4: Line | C4: Scalar | D4: FY2022A | E4: FY2023A | F4: FY2024A | G4: FY2025A | H4: FY2026E | I4: FY2027E | J4: FY2028E | K4: FY2029E | L4: FY2030E | M4: FY2031E | N4: FY2032E | O4: FY2033E | P4: FY2034E | Q4: FY2035E | R4: FY2036E | S4: FY2037E | T4: FY2038E | U4: FY2039E | V4: FY2040E | W4: FY2041E | X4: FY2042E | Y4: FY2043E | Z4: FY2044E | AA4: FY2045E | AB4: FY2046E | AC4: FY2047E | AD4: FY2048E | AE4: FY2049E | AF4: FY2050E
A6: PARAMETERS
A7: horizon | C7: 25
A8: ps_factor | C8: 1
A9: reserves | C9: 178.1
A10: unit_factor | C10: 1
A11: vp_factor | C11: 1
A13: INPUTS (company assumptions)
A14: Sales volume plan | B14: a.volume | H14: 6.5 | I14: 7.1 | J14: 7.3 | K14: 7.3 | L14: 7.3 | M14: 7.3 | N14: 7.3 | O14: 7.3 | P14: 7.3 | Q14: 7.3 | R14: 7.3 | S14: 7.3 | T14: 7.3 | U14: 7.3 | V14: 7.3 | W14: 7.3 | X14: 7.3 | Y14: 7.3 | Z14: 7.3 | AA14: 7.3 | AB14: 7.3 | AC14: 7.3 | AD14: 7.3 | AE14: 7.3 | AF14: 7.3
A15: Realised price / benchmark | B15: a.realisation | H15: 1.43 | I15: 1.43 | J15: 1.43 | K15: 1.43 | L15: 1.43 | M15: 1.43 | N15: 1.43 | O15: 1.43 | P15: 1.43 | Q15: 1.43 | R15: 1.43 | S15: 1.43 | T15: 1.43 | U15: 1.43 | V15: 1.43 | W15: 1.43 | X15: 1.43 | Y15: 1.43 | Z15: 1.43 | AA15: 1.43 | AB15: 1.43 | AC15: 1.43 | AD15: 1.43 | AE15: 1.43 | AF15: 1.43
A16: Share of volume under a price cap (e.g. DMO) | B16: a.capped_share | H16: 0 | I16: 0 | J16: 0 | K16: 0 | L16: 0 | M16: 0 | N16: 0 | O16: 0 | P16: 0 | Q16: 0 | R16: 0 | S16: 0 | T16: 0 | U16: 0 | V16: 0 | W16: 0 | X16: 0 | Y16: 0 | Z16: 0 | AA16: 0 | AB16: 0 | AC16: 0 | AD16: 0 | AE16: 0 | AF16: 0
A17: Strip ratio (bcm per tonne) or cost-intensity factor | B17: a.strip_ratio | H17: 3.55 | I17: 3.55 | J17: 3.55 | K17: 3.55 | L17: 3.55 | M17: 3.55 | N17: 3.55 | O17: 3.55 | P17: 3.55 | Q17: 3.55 | R17: 3.55 | S17: 3.55 | T17: 3.55 | U17: 3.55 | V17: 3.55 | W17: 3.55 | X17: 3.55 | Y17: 3.55 | Z17: 3.55 | AA17: 3.55 | AB17: 3.55 | AC17: 3.55 | AD17: 3.55 | AE17: 3.55 | AF17: 3.55
A18: Mining cost per bcm (or per unit when intensity is 1) | B18: a.cost_per_bcm | H18: 8 | I18: 8 | J18: 8 | K18: 8 | L18: 8 | M18: 8.16 | N18: 8.3232 | O18: 8.489664 | P18: 8.6594573 | Q18: 8.8326464 | R18: 9.0092994 | S18: 9.1894853 | T18: 9.373275 | U18: 9.5607405 | V18: 9.7519554 | W18: 9.9469945 | X18: 10.145934 | Y18: 10.348853 | Z18: 10.55583 | AA18: 10.766947 | AB18: 10.982286 | AC18: 11.201931 | AD18: 11.42597 | AE18: 11.654489 | AF18: 11.887579
A19: Fuel share of mining cost | B19: a.fuel_share | C19: 0.3
A20: Other cash cost per unit (haul, barge, process) | B20: a.other_cost_unit | H20: 36.8 | I20: 36.8 | J20: 36.8 | K20: 36.8 | L20: 36.8 | M20: 37.536 | N20: 38.28672 | O20: 39.052454 | P20: 39.833503 | Q20: 40.630174 | R20: 41.442777 | S20: 42.271633 | T20: 43.117065 | U20: 43.979407 | V20: 44.858995 | W20: 45.756175 | X20: 46.671298 | Y20: 47.604724 | Z20: 48.556818 | AA20: 49.527955 | AB20: 50.518514 | AC20: 51.528884 | AD20: 52.559462 | AE20: 53.610651 | AF20: 54.682864
A21: Royalty rate (flat regimes) | B21: a.royalty_rate | H21: 0.128 | I21: 0.128 | J21: 0.128 | K21: 0.128 | L21: 0.128 | M21: 0.128 | N21: 0.128 | O21: 0.128 | P21: 0.128 | Q21: 0.128 | R21: 0.128 | S21: 0.128 | T21: 0.128 | U21: 0.128 | V21: 0.128 | W21: 0.128 | X21: 0.128 | Y21: 0.128 | Z21: 0.128 | AA21: 0.128 | AB21: 0.128 | AC21: 0.128 | AD21: 0.128 | AE21: 0.128 | AF21: 0.128
A22: Other revenue | B22: a.other_revenue | H22: 0 | I22: 0 | J22: 0 | K22: 0 | L22: 0 | M22: 0 | N22: 0 | O22: 0 | P22: 0 | Q22: 0 | R22: 0 | S22: 0 | T22: 0 | U22: 0 | V22: 0 | W22: 0 | X22: 0 | Y22: 0 | Z22: 0 | AA22: 0 | AB22: 0 | AC22: 0 | AD22: 0 | AE22: 0 | AF22: 0
A23: Gross margin on other revenue | B23: a.other_margin | C23: 0.1
A24: D&A per unit (reporting currency) | B24: a.da_unit | H24: 7 | I24: 7 | J24: 7 | K24: 7 | L24: 7 | M24: 7.14 | N24: 7.2828 | O24: 7.428456 | P24: 7.5770251 | Q24: 7.7285656 | R24: 7.8831369 | S24: 8.0407997 | T24: 8.2016157 | U24: 8.365648 | V24: 8.5329609 | W24: 8.7036202 | X24: 8.8776926 | Y24: 9.0552464 | Z24: 9.2363513 | AA24: 9.4210784 | AB24: 9.6094999 | AC24: 9.8016899 | AD24: 9.9977237 | AE24: 10.197678 | AF24: 10.401632
A25: Sustaining capex per unit (reporting currency) | B25: a.capex_unit | H25: 7 | I25: 7 | J25: 7 | K25: 7 | L25: 7 | M25: 7.14 | N25: 7.2828 | O25: 7.428456 | P25: 7.5770251 | Q25: 7.7285656 | R25: 7.8831369 | S25: 8.0407997 | T25: 8.2016157 | U25: 8.365648 | V25: 8.5329609 | W25: 8.7036202 | X25: 8.8776926 | Y25: 9.0552464 | Z25: 9.2363513 | AA25: 9.4210784 | AB25: 9.6094999 | AC25: 9.8016899 | AD25: 9.9977237 | AE25: 10.197678 | AF25: 10.401632
A26: Other capex (expansion projects) | B26: a.capex_other | H26: 100 | I26: 0 | J26: 0 | K26: 0 | L26: 0 | M26: 0 | N26: 0 | O26: 0 | P26: 0 | Q26: 0 | R26: 0 | S26: 0 | T26: 0 | U26: 0 | V26: 0 | W26: 0 | X26: 0 | Y26: 0 | Z26: 0 | AA26: 0 | AB26: 0 | AC26: 0 | AD26: 0 | AE26: 0 | AF26: 29.26
A27: Operating working capital / revenue | B27: a.nwc_pct | H27: -0.014934 | I27: -0.014934 | J27: -0.014934 | K27: -0.014934 | L27: -0.014934 | M27: -0.014934 | N27: -0.014934 | O27: -0.014934 | P27: -0.014934 | Q27: -0.014934 | R27: -0.014934 | S27: -0.014934 | T27: -0.014934 | U27: -0.014934 | V27: -0.014934 | W27: -0.014934 | X27: -0.014934 | Y27: -0.014934 | Z27: -0.014934 | AA27: -0.014934 | AB27: -0.014934 | AC27: -0.014934 | AD27: -0.014934 | AE27: -0.014934 | AF27: -0.014934
A28: Effective tax rate | B28: a.tax_rate | H28: 0.221746 | I28: 0.221746 | J28: 0.221746 | K28: 0.221746 | L28: 0.221746 | M28: 0.221746 | N28: 0.221746 | O28: 0.221746 | P28: 0.221746 | Q28: 0.221746 | R28: 0.221746 | S28: 0.221746 | T28: 0.221746 | U28: 0.221746 | V28: 0.221746 | W28: 0.221746 | X28: 0.221746 | Y28: 0.221746 | Z28: 0.221746 | AA28: 0.221746 | AB28: 0.221746 | AC28: 0.221746 | AD28: 0.221746 | AE28: 0.221746 | AF28: 0.221746
A29: Cost of debt (on opening debt) | B29: a.cost_of_debt | C29: 0.08
A30: Yield on opening cash | B30: a.cash_yield | C30: 0.043065
A31: Net new borrowing | B31: a.net_borrowing | H31: 1136.351 | I31: 0 | J31: 0 | K31: 0 | L31: 0 | M31: 0 | N31: 0 | O31: 0 | P31: 0 | Q31: 0 | R31: 0 | S31: 0 | T31: 0 | U31: 0 | V31: 0 | W31: 0 | X31: 0 | Y31: 0 | Z31: 0 | AA31: 0 | AB31: 0 | AC31: 0 | AD31: 0 | AE31: 0 | AF31: 0
A32: Other non-operating items | B32: a.other_nonop | H32: 0 | I32: 0 | J32: 0 | K32: 0 | L32: 0 | M32: 0 | N32: 0 | O32: 0 | P32: 0 | Q32: 0 | R32: 0 | S32: 0 | T32: 0 | U32: 0 | V32: 0 | W32: 0 | X32: 0 | Y32: 0 | Z32: 0 | AA32: 0 | AB32: 0 | AC32: 0 | AD32: 0 | AE32: 0 | AF32: 0
A33: Minorities' share of net profit | B33: a.minority_pct | H33: 0 | I33: 0 | J33: 0 | K33: 0 | L33: 0 | M33: 0 | N33: 0 | O33: 0 | P33: 0 | Q33: 0 | R33: 0 | S33: 0 | T33: 0 | U33: 0 | V33: 0 | W33: 0 | X33: 0 | Y33: 0 | Z33: 0 | AA33: 0 | AB33: 0 | AC33: 0 | AD33: 0 | AE33: 0 | AF33: 0
A34: Dividend payout | B34: a.payout | H34: 0.35 | I34: 0.35 | J34: 0.35 | K34: 0.35 | L34: 0.35 | M34: 0.35 | N34: 0.35 | O34: 0.35 | P34: 0.35 | Q34: 0.35 | R34: 0.35 | S34: 0.35 | T34: 0.35 | U34: 0.35 | V34: 0.35 | W34: 0.35 | X34: 0.35 | Y34: 0.35 | Z34: 0.35 | AA34: 0.35 | AB34: 0.35 | AC34: 0.35 | AD34: 0.35 | AE34: 0.35 | AF34: 0.35
A35: Change in share count | B35: a.share_change | H35: 0 | I35: 0 | J35: 0 | K35: 0 | L35: 0 | M35: 0 | N35: 0 | O35: 0 | P35: 0 | Q35: 0 | R35: 0 | S35: 0 | T35: 0 | U35: 0 | V35: 0 | W35: 0 | X35: 0 | Y35: 0 | Z35: 0 | AA35: 0 | AB35: 0 | AC35: 0 | AD35: 0 | AE35: 0 | AF35: 0
A36: Terminal growth (DCF) | B36: a.terminal_growth | C36: 0
A37: SG&A / revenue | B37: a.opex_pct | H37: 0.0811 | I37: 0.0811 | J37: 0.0811 | K37: 0.0811 | L37: 0.0811 | M37: 0.0811 | N37: 0.0811 | O37: 0.0811 | P37: 0.0811 | Q37: 0.0811 | R37: 0.0811 | S37: 0.0811 | T37: 0.0811 | U37: 0.0811 | V37: 0.0811 | W37: 0.0811 | X37: 0.0811 | Y37: 0.0811 | Z37: 0.0811 | AA37: 0.0811 | AB37: 0.0811 | AC37: 0.0811 | AD37: 0.0811 | AE37: 0.0811 | AF37: 0.0811
A39: MODEL
A40: Reserves remaining (close) | B40: reserves | G40: 178.1 | H40: =MAX((G40-H41),0) | I40: =MAX((H40-I41),0) | J40: =MAX((I40-J41),0) | K40: =MAX((J40-K41),0) | L40: =MAX((K40-L41),0) | M40: =MAX((L40-M41),0) | N40: =MAX((M40-N41),0) | O40: =MAX((N40-O41),0) | ... AF40: =MAX((AE40-AF41),0)
A41: Sales volume | B41: volume | F41: 5.62 | G41: 6.28 | H41: =IF(($C$9>0),MIN(H14,MAX(G40,0)),H14) | I41: =IF(($C$9>0),MIN(I14,MAX(H40,0)),I14) | J41: =IF(($C$9>0),MIN(J14,MAX(I40,0)),J14) | K41: =IF(($C$9>0),MIN(K14,MAX(J40,0)),K14) | L41: =IF(($C$9>0),MIN(L14,MAX(K40,0)),L14) | M41: =IF(($C$9>0),MIN(M14,MAX(L40,0)),M14) | N41: =IF(($C$9>0),MIN(N14,MAX(M40,0)),N14) | O41: =IF(($C$9>0),MIN(O14,MAX(N40,0)),O14) | ... AF41: =IF(($C$9>0),MIN(AF14,MAX(AE40,0)),AF14)
A42: Benchmark price | B42: benchmark | H42: =Drivers!$L$6 | I42: =Drivers!$M$6 | J42: =Drivers!$N$6 | K42: =Drivers!$O$6 | L42: =Drivers!$P$6 | M42: =Drivers!$Q$6 | N42: =Drivers!$R$6 | O42: =Drivers!$S$6 | P42: =Drivers!$T$6 | Q42: =Drivers!$U$6 | R42: =Drivers!$V$6 | S42: =Drivers!$W$6 | T42: =Drivers!$X$6 | U42: =Drivers!$Y$6 | V42: =Drivers!$Z$6 | W42: =Drivers!$AA$6 | X42: =Drivers!$AB$6 | Y42: =Drivers!$AC$6 | Z42: =Drivers!$AD$6 | AA42: =Drivers!$AE$6 | AB42: =Drivers!$AF$6 | AC42: =Drivers!$AG$6 | AD42: =Drivers!$AH$6 | AE42: =Drivers!$AI$6 | AF42: =Drivers!$AJ$6
A43: Average selling price | B43: asp | H43: =(((H15*H42)*(1-H16))+(MIN(Drivers!$L$4,(H15*H42))*H16)) | I43: =(((I15*I42)*(1-I16))+(MIN(Drivers!$M$4,(I15*I42))*I16)) | J43: =(((J15*J42)*(1-J16))+(MIN(Drivers!$N$4,(J15*J42))*J16)) | K43: =(((K15*K42)*(1-K16))+(MIN(Drivers!$O$4,(K15*K42))*K16)) | L43: =(((L15*L42)*(1-L16))+(MIN(Drivers!$P$4,(L15*L42))*L16)) | M43: =(((M15*M42)*(1-M16))+(MIN(Drivers!$Q$4,(M15*M42))*M16)) | N43: =(((N15*N42)*(1-N16))+(MIN(Drivers!$R$4,(N15*N42))*N16)) | O43: =(((O15*O42)*(1-O16))+(MIN(Drivers!$S$4,(O15*O42))*O16)) | P43: =(((P15*P42)*(1-P16))+(MIN(Drivers!$T$4,(P15*P42))*P16)) | Q43: =(((Q15*Q42)*(1-Q16))+(MIN(Drivers!$U$4,(Q15*Q42))*Q16)) | R43: =(((R15*R42)*(1-R16))+(MIN(Drivers!$V$4,(R15*R42))*R16)) | S43: =(((S15*S42)*(1-S16))+(MIN(Drivers!$W$4,(S15*S42))*S16)) | T43: =(((T15*T42)*(1-T16))+(MIN(Drivers!$X$4,(T15*T42))*T16)) | U43: =(((U15*U42)*(1-U16))+(MIN(Drivers!$Y$4,(U15*U42))*U16)) | V43: =(((V15*V42)*(1-V16))+(MIN(Drivers!$Z$4,(V15*V42))*V16)) | W43: =(((W15*W42)*(1-W16))+(MIN(Drivers!$AA$4,(W15*W42))*W16)) | X43: =(((X15*X42)*(1-X16))+(MIN(Drivers!$AB$4,(X15*X42))*X16)) | Y43: =(((Y15*Y42)*(1-Y16))+(MIN(Drivers!$AC$4,(Y15*Y42))*Y16)) | Z43: =(((Z15*Z42)*(1-Z16))+(MIN(Drivers!$AD$4,(Z15*Z42))*Z16)) | AA43: =(((AA15*AA42)*(1-AA16))+(MIN(Drivers!$AE$4,(AA15*AA42))*AA16)) | AB43: =(((AB15*AB42)*(1-AB16))+(MIN(Drivers!$AF$4,(AB15*AB42))*AB16)) | AC43: =(((AC15*AC42)*(1-AC16))+(MIN(Drivers!$AG$4,(AC15*AC42))*AC16)) | AD43: =(((AD15*AD42)*(1-AD16))+(MIN(Drivers!$AH$4,(AD15*AD42))*AD16)) | AE43: =(((AE15*AE42)*(1-AE16))+(MIN(Drivers!$AI$4,(AE15*AE42))*AE16)) | AF43: =(((AF15*AF42)*(1-AF16))+(MIN(Drivers!$AJ$4,(AF15*AF42))*AF16))
A44: Realisation vs benchmark | B44: realisation_line | H44: =IF(H42=0,0,H43/H42) | I44: =IF(I42=0,0,I43/I42) | J44: =IF(J42=0,0,J43/J42) | K44: =IF(K42=0,0,K43/K42) | L44: =IF(L42=0,0,L43/L42) | M44: =IF(M42=0,0,M43/M42) | N44: =IF(N42=0,0,N43/N42) | O44: =IF(O42=0,0,O43/O42) | ... AF44: =IF(AF42=0,0,AF43/AF42)
A45: Cash cost per unit (ex-royalty) | B45: unit_cost | H45: =(((H17*H18)*(1+($C$19*(IF(Drivers!$J$8=0,0,Drivers!$L$8/Drivers!$J$8)-1))))+H20) | I45: =(((I17*I18)*(1+($C$19*(IF(Drivers!$J$8=0,0,Drivers!$M$8/Drivers!$J$8)-1))))+I20) | J45: =(((J17*J18)*(1+($C$19*(IF(Drivers!$J$8=0,0,Drivers!$N$8/Drivers!$J$8)-1))))+J20) | K45: =(((K17*K18)*(1+($C$19*(IF(Drivers!$J$8=0,0,Drivers!$O$8/Drivers!$J$8)-1))))+K20) | L45: =(((L17*L18)*(1+($C$19*(IF(Drivers!$J$8=0,0,Drivers!$P$8/Drivers!$J$8)-1))))+L20) | M45: =(((M17*M18)*(1+($C$19*(IF(Drivers!$J$8=0,0,Drivers!$Q$8/Drivers!$J$8)-1))))+M20) | N45: =(((N17*N18)*(1+($C$19*(IF(Drivers!$J$8=0,0,Drivers!$R$8/Drivers!$J$8)-1))))+N20) | O45: =(((O17*O18)*(1+($C$19*(IF(Drivers!$J$8=0,0,Drivers!$S$8/Drivers!$J$8)-1))))+O20) | P45: =(((P17*P18)*(1+($C$19*(IF(Drivers!$J$8=0,0,Drivers!$T$8/Drivers!$J$8)-1))))+P20) | Q45: =(((Q17*Q18)*(1+($C$19*(IF(Drivers!$J$8=0,0,Drivers!$U$8/Drivers!$J$8)-1))))+Q20) | R45: =(((R17*R18)*(1+($C$19*(IF(Drivers!$J$8=0,0,Drivers!$V$8/Drivers!$J$8)-1))))+R20) | S45: =(((S17*S18)*(1+($C$19*(IF(Drivers!$J$8=0,0,Drivers!$W$8/Drivers!$J$8)-1))))+S20) | T45: =(((T17*T18)*(1+($C$19*(IF(Drivers!$J$8=0,0,Drivers!$X$8/Drivers!$J$8)-1))))+T20) | U45: =(((U17*U18)*(1+($C$19*(IF(Drivers!$J$8=0,0,Drivers!$Y$8/Drivers!$J$8)-1))))+U20) | V45: =(((V17*V18)*(1+($C$19*(IF(Drivers!$J$8=0,0,Drivers!$Z$8/Drivers!$J$8)-1))))+V20) | W45: =(((W17*W18)*(1+($C$19*(IF(Drivers!$J$8=0,0,Drivers!$AA$8/Drivers!$J$8)-1))))+W20) | X45: =(((X17*X18)*(1+($C$19*(IF(Drivers!$J$8=0,0,Drivers!$AB$8/Drivers!$J$8)-1))))+X20) | Y45: =(((Y17*Y18)*(1+($C$19*(IF(Drivers!$J$8=0,0,Drivers!$AC$8/Drivers!$J$8)-1))))+Y20) | Z45: =(((Z17*Z18)*(1+($C$19*(IF(Drivers!$J$8=0,0,Drivers!$AD$8/Drivers!$J$8)-1))))+Z20) | AA45: =(((AA17*AA18)*(1+($C$19*(IF(Drivers!$J$8=0,0,Drivers!$AE$8/Drivers!$J$8)-1))))+AA20) | AB45: =(((AB17*AB18)*(1+($C$19*(IF(Drivers!$J$8=0,0,Drivers!$AF$8/Drivers!$J$8)-1))))+AB20) | AC45: =(((AC17*AC18)*(1+($C$19*(IF(Drivers!$J$8=0,0,Drivers!$AG$8/Drivers!$J$8)-1))))+AC20) | AD45: =(((AD17*AD18)*(1+($C$19*(IF(Drivers!$J$8=0,0,Drivers!$AH$8/Drivers!$J$8)-1))))+AD20) | AE45: =(((AE17*AE18)*(1+($C$19*(IF(Drivers!$J$8=0,0,Drivers!$AI$8/Drivers!$J$8)-1))))+AE20) | AF45: =(((AF17*AF18)*(1+($C$19*(IF(Drivers!$J$8=0,0,Drivers!$AJ$8/Drivers!$J$8)-1))))+AF20)
A46: Strip ratio | B46: strip_ratio_line | G46: 3.55 | H46: =H17 | I46: =I17 | J46: =J17 | K46: =K17 | L46: =L17 | M46: =M17 | N46: =N17 | O46: =O17 | ... AF46: =AF17
A47: Royalty rate | B47: royalty_rate | H47: =H21 | I47: =I21 | J47: =J21 | K47: =K21 | L47: =L21 | M47: =M21 | N47: =N21 | O47: =O21 | ... AF47: =AF21
A48: EBITDA per unit (price currency) | B48: ebitda_per_unit | F48: 102.52028 | G48: 57.394427 | H48: =IF((H41*$C$10)=0,0,H61/(H41*$C$10)) | I48: =IF((I41*$C$10)=0,0,I61/(I41*$C$10)) | J48: =IF((J41*$C$10)=0,0,J61/(J41*$C$10)) | K48: =IF((K41*$C$10)=0,0,K61/(K41*$C$10)) | L48: =IF((L41*$C$10)=0,0,L61/(L41*$C$10)) | M48: =IF((M41*$C$10)=0,0,M61/(M41*$C$10)) | N48: =IF((N41*$C$10)=0,0,N61/(N41*$C$10)) | O48: =IF((O41*$C$10)=0,0,O61/(O41*$C$10)) | ... AF48: =IF((AF41*$C$10)=0,0,AF61/(AF41*$C$10))
A49: Cash cost + royalty per unit (price currency) | B49: cash_cost_money_per_unit | H49: =IF((H41*$C$10)=0,0,(H53+H52)/(H41*$C$10)) | I49: =IF((I41*$C$10)=0,0,(I53+I52)/(I41*$C$10)) | J49: =IF((J41*$C$10)=0,0,(J53+J52)/(J41*$C$10)) | K49: =IF((K41*$C$10)=0,0,(K53+K52)/(K41*$C$10)) | L49: =IF((L41*$C$10)=0,0,(L53+L52)/(L41*$C$10)) | M49: =IF((M41*$C$10)=0,0,(M53+M52)/(M41*$C$10)) | N49: =IF((N41*$C$10)=0,0,(N53+N52)/(N41*$C$10)) | O49: =IF((O41*$C$10)=0,0,(O53+O52)/(O41*$C$10)) | ... AF49: =IF((AF41*$C$10)=0,0,(AF53+AF52)/(AF41*$C$10))
A50: Main product revenue | B50: revenue_main | H50: =((H41*H43)*$C$10) | I50: =((I41*I43)*$C$10) | J50: =((J41*J43)*$C$10) | K50: =((K41*K43)*$C$10) | L50: =((L41*L43)*$C$10) | M50: =((M41*M43)*$C$10) | N50: =((N41*N43)*$C$10) | O50: =((O41*O43)*$C$10) | ... AF50: =((AF41*AF43)*$C$10)
A51: Other revenue | B51: other_revenue | H51: =H22 | I51: =I22 | J51: =J22 | K51: =K22 | L51: =L22 | M51: =M22 | N51: =N22 | O51: =O22 | ... AF51: =AF22
A52: Royalty | B52: royalty | H52: =(H50*H47) | I52: =(I50*I47) | J52: =(J50*J47) | K52: =(K50*K47) | L52: =(L50*L47) | M52: =(M50*M47) | N52: =(N50*N47) | O52: =(O50*O47) | ... AF52: =(AF50*AF47)
A53: Cash costs | B53: cash_cost | H53: =((H41*H45)*$C$10) | I53: =((I41*I45)*$C$10) | J53: =((J41*J45)*$C$10) | K53: =((K41*K45)*$C$10) | L53: =((L41*L45)*$C$10) | M53: =((M41*M45)*$C$10) | N53: =((N41*N45)*$C$10) | O53: =((O41*O45)*$C$10) | ... AF53: =((AF41*AF45)*$C$10)
A54: Cost of other revenue | B54: other_cogs | H54: =(H51*(1-$C$23)) | I54: =(I51*(1-$C$23)) | J54: =(J51*(1-$C$23)) | K54: =(K51*(1-$C$23)) | L54: =(L51*(1-$C$23)) | M54: =(M51*(1-$C$23)) | N54: =(N51*(1-$C$23)) | O54: =(O51*(1-$C$23)) | ... AF54: =(AF51*(1-$C$23))
A55: Revenue | B55: revenue | D55: 908.14205 | E55: 1085.9619 | F55: 1154.183 | G55: 972.948 | H55: =(H50+H51) | I55: =(I50+I51) | J55: =(J50+J51) | K55: =(K50+K51) | L55: =(L50+L51) | M55: =(M50+M51) | N55: =(N50+N51) | O55: =(O50+O51) | ... AF55: =(AF50+AF51)
A56: Cost of revenue | B56: cogs | D56: 373.22739 | E56: 502.75001 | F56: 576.393 | G56: 577.682 | H56: =(((H53+H52)+H54)+H60) | I56: =(((I53+I52)+I54)+I60) | J56: =(((J53+J52)+J54)+J60) | K56: =(((K53+K52)+K54)+K60) | L56: =(((L53+L52)+L54)+L60) | M56: =(((M53+M52)+M54)+M60) | N56: =(((N53+N52)+N54)+N60) | O56: =(((O53+O52)+O54)+O60) | ... AF56: =(((AF53+AF52)+AF54)+AF60)
A57: Gross profit | B57: gross_profit | D57: 534.91466 | E57: 583.21191 | F57: 577.79 | G57: 395.266 | H57: =(H55-H56) | I57: =(I55-I56) | J57: =(J55-J56) | K57: =(K55-K56) | L57: =(L55-L56) | M57: =(M55-M56) | N57: =(N55-N56) | O57: =(O55-O56) | ... AF57: =(AF55-AF56)
A58: SG&A and other opex | B58: opex | D58: 75.089023 | E58: 9.473972 | F58: 39.197 | G58: 78.867 | H58: =(H55*H37) | I58: =(I55*I37) | J58: =(J55*J37) | K58: =(K55*K37) | L58: =(L55*L37) | M58: =(M55*M37) | N58: =(N55*N37) | O58: =(O55*O37) | ... AF58: =(AF55*AF37)
A59: EBIT | B59: ebit | D59: 459.82564 | E59: 573.73794 | F59: 538.593 | G59: 316.399 | H59: =(H57-H58) | I59: =(I57-I58) | J59: =(J57-J58) | K59: =(K57-K58) | L59: =(L57-L58) | M59: =(M57-M58) | N59: =(N57-N58) | O59: =(O57-O58) | ... AF59: =(AF57-AF58)
A60: Depreciation & amortisation | B60: da | D60: 1.64892 | E60: 1.07785 | F60: 37.571 | G60: 44.038 | H60: =((H41*H24)*$C$10) | I60: =((I41*I24)*$C$10) | J60: =((J41*J24)*$C$10) | K60: =((K41*K24)*$C$10) | L60: =((L41*L24)*$C$10) | M60: =((M41*M24)*$C$10) | N60: =((N41*N24)*$C$10) | O60: =((O41*O24)*$C$10) | ... AF60: =((AF41*AF24)*$C$10)
A61: EBITDA | B61: ebitda | D61: 461.47456 | E61: 574.81579 | F61: 576.164 | G61: 360.437 | H61: =(H59+H60) | I61: =(I59+I60) | J61: =(J59+J60) | K61: =(K59+K60) | L61: =(L59+L60) | M61: =(M59+M60) | N61: =(N59+N60) | O61: =(O59+O60) | ... AF61: =(AF59+AF60)
A62: Interest expense | B62: interest_expense | D62: 24.043135 | E62: 30.209061 | F62: 11.091 | G62: 0.133 | H62: =(G82*$C$29) | I62: =(H82*$C$29) | J62: =(I82*$C$29) | K62: =(J82*$C$29) | L62: =(K82*$C$29) | M62: =(L82*$C$29) | N62: =(M82*$C$29) | O62: =(N82*$C$29) | ... AF62: =(AE82*$C$29)
A63: Interest income | B63: interest_income | D63: 4.148643 | E63: 19.732349 | F63: 29.104 | G63: 25.104 | H63: =(G81*$C$30) | I63: =(H81*$C$30) | J63: =(I81*$C$30) | K63: =(J81*$C$30) | L63: =(K81*$C$30) | M63: =(L81*$C$30) | N63: =(M81*$C$30) | O63: =(N81*$C$30) | ... AF63: =(AE81*$C$30)
A64: Other non-operating | B64: other_nonop | D64: -2.138073 | E64: 0.166664 | F64: 0.896 | G64: 0.766 | H64: =H32 | I64: =I32 | J64: =J32 | K64: =K32 | L64: =L32 | M64: =M32 | N64: =N32 | O64: =O32 | ... AF64: =AF32
A65: Profit before tax | B65: pbt | D65: 437.79307 | E65: 563.42789 | F65: 557.502 | G65: 342.136 | H65: =(((H59-H62)+H63)+H64) | I65: =(((I59-I62)+I63)+I64) | J65: =(((J59-J62)+J63)+J64) | K65: =(((K59-K62)+K63)+K64) | L65: =(((L59-L62)+L63)+L64) | M65: =(((M59-M62)+M63)+M64) | N65: =(((N59-N62)+N63)+N64) | O65: =(((O59-O62)+O63)+O64) | ... AF65: =(((AF59-AF62)+AF63)+AF64)
A66: Tax | B66: tax | D66: 102.05433 | E66: 122.58475 | F66: 122.733 | G66: 77.843 | H66: =(MAX(H65,0)*H28) | I66: =(MAX(I65,0)*I28) | J66: =(MAX(J65,0)*J28) | K66: =(MAX(K65,0)*K28) | L66: =(MAX(L65,0)*L28) | M66: =(MAX(M65,0)*M28) | N66: =(MAX(N65,0)*N28) | O66: =(MAX(O65,0)*O28) | ... AF66: =(MAX(AF65,0)*AF28)
A67: Net profit (incl. minorities) | B67: np | D67: 335.73874 | E67: 440.84314 | F67: 434.769 | G67: 264.293 | H67: =(H65-H66) | I67: =(I65-I66) | J67: =(J65-J66) | K67: =(K65-K66) | L67: =(L65-L66) | M67: =(M65-M66) | N67: =(N65-N66) | O67: =(O65-O66) | ... AF67: =(AF65-AF66)
A68: Minority interests | B68: minority | D68: 3.52823 | E68: -0.178755 | F68: -1.887 | G68: -6.919 | H68: =(H67*H33) | I68: =(I67*I33) | J68: =(J67*J33) | K68: =(K67*K33) | L68: =(L67*L33) | M68: =(M67*M33) | N68: =(N67*N33) | O68: =(O67*O33) | ... AF68: =(AF67*AF33)
A69: Net profit to parent | B69: np_parent | D69: 332.21051 | E69: 441.0219 | F69: 436.656 | G69: 271.212 | H69: =(H67-H68) | I69: =(I67-I68) | J69: =(J67-J68) | K69: =(K67-K68) | L69: =(L67-L68) | M69: =(M67-M68) | N69: =(N67-N68) | O69: =(O67-O68) | ... AF69: =(AF67-AF68)
A70: Shares outstanding (m) | B70: shares | D70: 40882.332 | E70: 40882.332 | F70: 40882.332 | G70: 40882.332 | H70: =(G70*(1+H35)) | I70: =(H70*(1+I35)) | J70: =(I70*(1+J35)) | K70: =(J70*(1+K35)) | L70: =(K70*(1+L35)) | M70: =(L70*(1+M35)) | N70: =(M70*(1+N35)) | O70: =(N70*(1+O35)) | ... AF70: =(AE70*(1+AF35))
A71: EPS | B71: eps | D71: 0.0081260167 | E71: 0.010787592 | F71: 0.0106808 | G71: 0.0066339661 | H71: =(IF(H70=0,0,H69/H70)*$C$8) | I71: =(IF(I70=0,0,I69/I70)*$C$8) | J71: =(IF(J70=0,0,J69/J70)*$C$8) | K71: =(IF(K70=0,0,K69/K70)*$C$8) | L71: =(IF(L70=0,0,L69/L70)*$C$8) | M71: =(IF(M70=0,0,M69/M70)*$C$8) | N71: =(IF(N70=0,0,N69/N70)*$C$8) | O71: =(IF(O70=0,0,O69/O70)*$C$8) | ... AF71: =(IF(AF70=0,0,AF69/AF70)*$C$8)
A72: DPS (declared on the year) | B72: dps | D72: 0 | E72: 0 | F72: 0.0029465771 | G72: 0.0029202387 | H72: =(MAX(H71,0)*H34) | I72: =(MAX(I71,0)*I34) | J72: =(MAX(J71,0)*J34) | K72: =(MAX(K71,0)*K34) | L72: =(MAX(L71,0)*L34) | M72: =(MAX(M71,0)*M34) | N72: =(MAX(N71,0)*N34) | O72: =(MAX(O71,0)*O34) | ... AF72: =(MAX(AF71,0)*AF34)
A73: Dividends paid | B73: dividends_paid | G73: 120 | H73: =IF($C$8=0,0,(G72*G70)/$C$8) | I73: =IF($C$8=0,0,(H72*H70)/$C$8) | J73: =IF($C$8=0,0,(I72*I70)/$C$8) | K73: =IF($C$8=0,0,(J72*J70)/$C$8) | L73: =IF($C$8=0,0,(K72*K70)/$C$8) | M73: =IF($C$8=0,0,(L72*L70)/$C$8) | N73: =IF($C$8=0,0,(M72*M70)/$C$8) | O73: =IF($C$8=0,0,(N72*N70)/$C$8) | ... AF73: =IF($C$8=0,0,(AE72*AE70)/$C$8)
A74: Capital expenditure | B74: capex | D74: 21.27469 | E74: 134.72787 | F74: 405.683 | G74: 661.66 | H74: =(((H41*H25)*$C$10)+H26) | I74: =(((I41*I25)*$C$10)+I26) | J74: =(((J41*J25)*$C$10)+J26) | K74: =(((K41*K25)*$C$10)+K26) | L74: =(((L41*L25)*$C$10)+L26) | M74: =(((M41*M25)*$C$10)+M26) | N74: =(((N41*N25)*$C$10)+N26) | O74: =(((O41*O25)*$C$10)+O26) | ... AF74: =(((AF41*AF25)*$C$10)+AF26)
A75: Change in working capital | B75: delta_nwc | E75: 156.1146 | F75: -98.649858 | G75: -121.364 | H75: =(H80-G80) | I75: =(I80-H80) | J75: =(J80-I80) | K75: =(K80-J80) | L75: =(L80-K80) | M75: =(M80-L80) | N75: =(N80-M80) | O75: =(O80-N80) | ... AF75: =(AF80-AE80)
A76: Free cash flow to firm | B76: fcff | E76: 159.14541 | F76: 150.56064 | G76: -251.8463 | H76: =((((H59*(1-H28))+H60)-H74)-H75) | I76: =((((I59*(1-I28))+I60)-I74)-I75) | J76: =((((J59*(1-J28))+J60)-J74)-J75) | K76: =((((K59*(1-K28))+K60)-K74)-K75) | L76: =((((L59*(1-L28))+L60)-L74)-L75) | M76: =((((M59*(1-M28))+M60)-M74)-M75) | N76: =((((N59*(1-N28))+N60)-N74)-N75) | O76: =((((O59*(1-O28))+O60)-O74)-O75) | ... AF76: =((((AF59*(1-AF28))+AF60)-AF74)-AF75)
A77: Net borrowing | B77: net_borrowing | E77: -65.740753 | F77: -127.98403 | G77: 417.254 | H77: =H31 | I77: =I31 | J77: =J31 | K77: =K31 | L77: =L31 | M77: =M31 | N77: =N31 | O77: =O31 | ... AF77: =AF31
A78: Dividends to minorities | B78: minority_div | H78: =(MAX(G68,0)*H34) | I78: =(MAX(H68,0)*I34) | J78: =(MAX(I68,0)*J34) | K78: =(MAX(J68,0)*K34) | L78: =(MAX(K68,0)*L34) | M78: =(MAX(L68,0)*M34) | N78: =(MAX(M68,0)*N34) | O78: =(MAX(N68,0)*O34) | ... AF78: =(MAX(AE68,0)*AF34)
A79: Free cash flow to equity | B79: fcfe | H79: =(((((H67+H60)-H74)-H75)+H77)-H78) | I79: =(((((I67+I60)-I74)-I75)+I77)-I78) | J79: =(((((J67+J60)-J74)-J75)+J77)-J78) | K79: =(((((K67+K60)-K74)-K75)+K77)-K78) | L79: =(((((L67+L60)-L74)-L75)+L77)-L78) | M79: =(((((M67+M60)-M74)-M75)+M77)-M78) | N79: =(((((N67+N60)-N74)-N75)+N77)-N78) | O79: =(((((O67+O60)-O74)-O75)+O77)-O78) | ... AF79: =(((((AF67+AF60)-AF74)-AF75)+AF77)-AF78)
A80: Operating working capital | B80: nwc | D80: -61.338741 | E80: 94.775858 | F80: -3.874 | G80: -125.238 | H80: =(H55*H27) | I80: =(I55*I27) | J80: =(J55*J27) | K80: =(K55*K27) | L80: =(L55*L27) | M80: =(M55*M27) | N80: =(N55*N27) | O80: =(O55*O27) | ... AF80: =(AF55*AF27)
A81: Cash & equivalents | B81: cash | D81: 511.38217 | E81: 586.42253 | F81: 612.605 | G81: 369.087 | H81: =(((((((G81+H67)+H60)-H74)-H75)+H77)-H73)-H78) | I81: =(((((((H81+I67)+I60)-I74)-I75)+I77)-I73)-I78) | J81: =(((((((I81+J67)+J60)-J74)-J75)+J77)-J73)-J78) | K81: =(((((((J81+K67)+K60)-K74)-K75)+K77)-K73)-K78) | L81: =(((((((K81+L67)+L60)-L74)-L75)+L77)-L73)-L78) | M81: =(((((((L81+M67)+M60)-M74)-M75)+M77)-M73)-M78) | N81: =(((((((M81+N67)+N60)-N74)-N75)+N77)-N73)-N78) | O81: =(((((((N81+O67)+O60)-O74)-O75)+O77)-O73)-O78) | ... AF81: =(((((((AE81+AF67)+AF60)-AF74)-AF75)+AF77)-AF73)-AF78)
A82: Total debt | B82: debt | D82: 489.49378 | E82: 423.75303 | F82: 295.769 | G82: 713.023 | H82: =(G82+H77) | I82: =(H82+I77) | J82: =(I82+J77) | K82: =(J82+K77) | L82: =(K82+L77) | M82: =(L82+M77) | N82: =(M82+N77) | O82: =(N82+O77) | ... AF82: =(AE82+AF77)
A83: Fixed assets (net) | B83: ppe | D83: 610.39088 | E83: 744.10873 | F83: 1085.561 | G83: 1986.933 | H83: =((G83+H74)-H60) | I83: =((H83+I74)-I60) | J83: =((I83+J74)-J60) | K83: =((J83+K74)-K60) | L83: =((K83+L74)-L60) | M83: =((L83+M74)-M60) | N83: =((M83+N74)-N60) | O83: =((N83+O74)-O60) | ... AF83: =((AE83+AF74)-AF60)
A84: Parent shareholders' equity | B84: equity | D84: 534.50388 | E84: 976.3312 | F84: 1411.313 | G84: 1561.514 | H84: =((G84+H69)-H73) | I84: =((H84+I69)-I73) | J84: =((I84+J69)-J73) | K84: =((J84+K69)-K73) | L84: =((K84+L69)-L73) | M84: =((L84+M69)-M73) | N84: =((M84+N69)-N73) | O84: =((N84+O69)-O73) | ... AF84: =((AE84+AF69)-AF73)
A85: Minority interest (balance sheet) | B85: minority_bs | D85: 34.803748 | E85: 61.717998 | F85: 90.95 | G85: 155.897 | H85: =((G85+H68)-H78) | I85: =((H85+I68)-I78) | J85: =((I85+J68)-J78) | K85: =((J85+K68)-K78) | L85: =((K85+L68)-L78) | M85: =((L85+M68)-M78) | N85: =((M85+N68)-N78) | O85: =((N85+O68)-O78) | ... AF85: =((AE85+AF68)-AF78)
A86: Other assets less other liabilities | B86: other_net | D86: -1.632894 | E86: 36.495112 | F86: 103.74 | G86: 199.652 | H86: =G86 | I86: =H86 | J86: =I86 | K86: =J86 | L86: =K86 | M86: =L86 | N86: =M86 | O86: =N86 | ... AF86: =AE86
A87: Balance check (should be zero) | B87: bs_check | H87: =((((((H81+H80)+H83)+H86)-H82)-H84)-H85) | I87: =((((((I81+I80)+I83)+I86)-I82)-I84)-I85) | J87: =((((((J81+J80)+J83)+J86)-J82)-J84)-J85) | K87: =((((((K81+K80)+K83)+K86)-K82)-K84)-K85) | L87: =((((((L81+L80)+L83)+L86)-L82)-L84)-L85) | M87: =((((((M81+M80)+M83)+M86)-M82)-M84)-M85) | N87: =((((((N81+N80)+N83)+N86)-N82)-N84)-N85) | O87: =((((((O81+O80)+O83)+O86)-O82)-O84)-O85) | ... AF87: =((((((AF81+AF80)+AF83)+AF86)-AF82)-AF84)-AF85)
A88: Net debt (cash) | B88: net_debt | D88: -21.888383 | E88: -162.6695 | F88: -316.836 | G88: 343.936 | H88: =(H82-H81) | I88: =(I82-I81) | J88: =(J82-J81) | K88: =(K82-K81) | L88: =(L82-L81) | M88: =(M82-M81) | N88: =(N82-N81) | O88: =(O82-O81) | ... AF88: =(AF82-AF81)
A89: Book value per share | B89: bvps | D89: 0.013074202 | E89: 0.023881495 | F89: 0.034521343 | G89: 0.038195327 | H89: =(IF(H70=0,0,H84/H70)*$C$8) | I89: =(IF(I70=0,0,I84/I70)*$C$8) | J89: =(IF(J70=0,0,J84/J70)*$C$8) | K89: =(IF(K70=0,0,K84/K70)*$C$8) | L89: =(IF(L70=0,0,L84/L70)*$C$8) | M89: =(IF(M70=0,0,M84/M70)*$C$8) | N89: =(IF(N70=0,0,N84/N70)*$C$8) | O89: =(IF(O70=0,0,O84/O70)*$C$8) | ... AF89: =(IF(AF70=0,0,AF84/AF70)*$C$8)
A90: Revenue growth | B90: revenue_growth | E90: 0.19580624 | F90: 0.062820876 | G90: -0.15702449 | H90: =(IF(G55=0,0,H55/G55)-1) | I90: =(IF(H55=0,0,I55/H55)-1) | J90: =(IF(I55=0,0,J55/I55)-1) | K90: =(IF(J55=0,0,K55/J55)-1) | L90: =(IF(K55=0,0,L55/K55)-1) | M90: =(IF(L55=0,0,M55/L55)-1) | N90: =(IF(M55=0,0,N55/M55)-1) | O90: =(IF(N55=0,0,O55/N55)-1) | ... AF90: =(IF(AE55=0,0,AF55/AE55)-1)
A91: Gross margin | B91: gross_margin | D91: 0.58902092 | E91: 0.53704637 | F91: 0.50060519 | G91: 0.40625604 | H91: =IF(H55=0,0,H57/H55) | I91: =IF(I55=0,0,I57/I55) | J91: =IF(J55=0,0,J57/J55) | K91: =IF(K55=0,0,K57/K55) | L91: =IF(L55=0,0,L57/L55) | M91: =IF(M55=0,0,M57/M55) | N91: =IF(N55=0,0,N57/N55) | O91: =IF(O55=0,0,O57/O55) | ... AF91: =IF(AF55=0,0,AF57/AF55)
A92: EBITDA margin | B92: ebitda_margin | D92: 0.5081524 | E92: 0.52931487 | F92: 0.4991964 | G92: 0.37045865 | H92: =IF(H55=0,0,H61/H55) | I92: =IF(I55=0,0,I61/I55) | J92: =IF(J55=0,0,J61/J55) | K92: =IF(K55=0,0,K61/K55) | L92: =IF(L55=0,0,L61/L55) | M92: =IF(M55=0,0,M61/M55) | N92: =IF(N55=0,0,N61/N55) | O92: =IF(O55=0,0,O61/O55) | ... AF92: =IF(AF55=0,0,AF61/AF55)
A93: EBIT margin | B93: ebit_margin | D93: 0.50633669 | E93: 0.52832234 | F93: 0.46664437 | G93: 0.32519621 | H93: =IF(H55=0,0,H59/H55) | I93: =IF(I55=0,0,I59/I55) | J93: =IF(J55=0,0,J59/J55) | K93: =IF(K55=0,0,K59/K55) | L93: =IF(L55=0,0,L59/L55) | M93: =IF(M55=0,0,M59/M55) | N93: =IF(N55=0,0,N59/N55) | O93: =IF(O55=0,0,O59/O55) | ... AF93: =IF(AF55=0,0,AF59/AF55)
A94: Net margin | B94: np_margin | D94: 0.36581338 | E94: 0.40611175 | F94: 0.37832475 | G94: 0.27875282 | H94: =IF(H55=0,0,H69/H55) | I94: =IF(I55=0,0,I69/I55) | J94: =IF(J55=0,0,J69/J55) | K94: =IF(K55=0,0,K69/K55) | L94: =IF(L55=0,0,L69/L55) | M94: =IF(M55=0,0,M69/M55) | N94: =IF(N55=0,0,N69/N55) | O94: =IF(O55=0,0,O69/O55) | ... AF94: =IF(AF55=0,0,AF69/AF55)
A95: EPS growth | B95: eps_growth | E95: 0.32753747 | F95: -0.0098994994 | G95: -0.37888864 | H95: =(IF(G71=0,0,H71/G71)-1) | I95: =(IF(H71=0,0,I71/H71)-1) | J95: =(IF(I71=0,0,J71/I71)-1) | K95: =(IF(J71=0,0,K71/J71)-1) | L95: =(IF(K71=0,0,L71/K71)-1) | M95: =(IF(L71=0,0,M71/L71)-1) | N95: =(IF(M71=0,0,N71/M71)-1) | O95: =(IF(N71=0,0,O71/N71)-1) | ... AF95: =(IF(AE71=0,0,AF71/AE71)-1)
A96: ROE | B96: roe | E96: 0.5838121 | F96: 0.36576304 | G96: 0.18246067 | H96: =IF(IF(2=0,0,(H84+G84)/2)=0,0,H69/IF(2=0,0,(H84+G84)/2)) | I96: =IF(IF(2=0,0,(I84+H84)/2)=0,0,I69/IF(2=0,0,(I84+H84)/2)) | J96: =IF(IF(2=0,0,(J84+I84)/2)=0,0,J69/IF(2=0,0,(J84+I84)/2)) | K96: =IF(IF(2=0,0,(K84+J84)/2)=0,0,K69/IF(2=0,0,(K84+J84)/2)) | L96: =IF(IF(2=0,0,(L84+K84)/2)=0,0,L69/IF(2=0,0,(L84+K84)/2)) | M96: =IF(IF(2=0,0,(M84+L84)/2)=0,0,M69/IF(2=0,0,(M84+L84)/2)) | N96: =IF(IF(2=0,0,(N84+M84)/2)=0,0,N69/IF(2=0,0,(N84+M84)/2)) | O96: =IF(IF(2=0,0,(O84+N84)/2)=0,0,O69/IF(2=0,0,(O84+N84)/2)) | ... AF96: =IF(IF(2=0,0,(AF84+AE84)/2)=0,0,AF69/IF(2=0,0,(AF84+AE84)/2))
A97: Net debt / EBITDA | B97: net_debt_ebitda | D97: -0.047431397 | E97: -0.28299414 | F97: -0.54990593 | G97: 0.95421946 | H97: =IF(H61=0,0,H88/H61) | I97: =IF(I61=0,0,I88/I61) | J97: =IF(J61=0,0,J88/J61) | K97: =IF(K61=0,0,K88/K61) | L97: =IF(L61=0,0,L88/L61) | M97: =IF(M61=0,0,M88/M61) | N97: =IF(N61=0,0,N88/N61) | O97: =IF(O61=0,0,O88/O61) | ... AF97: =IF(AF61=0,0,AF88/AF61)
A98: Payout ratio | B98: payout_ratio | D98: 0 | E98: 0 | F98: 0.27587607 | G98: 0.44019501 | H98: =IF(H71=0,0,H72/H71) | I98: =IF(I71=0,0,I72/I71) | J98: =IF(J71=0,0,J72/J71) | K98: =IF(K71=0,0,K72/K71) | L98: =IF(L71=0,0,L72/L71) | M98: =IF(M71=0,0,M72/M71) | N98: =IF(N71=0,0,N72/N71) | O98: =IF(O71=0,0,O72/O71) | ... AF98: =IF(AF71=0,0,AF72/AF71)
A99: Capex / revenue | B99: capex_revenue | D99: 0.023426611 | E99: 0.12406317 | F99: 0.35148932 | G99: 0.6800569 | H99: =IF(H55=0,0,H74/H55) | I99: =IF(I55=0,0,I74/I55) | J99: =IF(J55=0,0,J74/J55) | K99: =IF(K55=0,0,K74/K55) | L99: =IF(L55=0,0,L74/L55) | M99: =IF(M55=0,0,M74/M55) | N99: =IF(N55=0,0,N74/N55) | O99: =IF(O55=0,0,O74/O55) | ... AF99: =IF(AF55=0,0,AF74/AF55)
A101: VALUATION
A102: Last price (IDR) | C102: 1305
A103: Shares outstanding (m) | C103: 40882.332
A104: IDR per USD (spot) | C104: 18138
A105: Debt at balance-sheet date | C105: 1849.374
...

Sheet ARII
A1: PT Atlas Resources Tbk (ARII.JK) — Coal producers
A2: Units: USD m; per-share in USD unless marked IDR. Model asof 2026-10-30 · data 2026-10-29
A4: Line | C4: Scalar | D4: FY2022A | E4: FY2023A | F4: FY2024A | G4: FY2025A | H4: FY2026E | I4: FY2027E | J4: FY2028E | K4: FY2029E
A6: PARAMETERS
A7: horizon | C7: 4
A8: ps_factor | C8: 1
A9: reserves | C9: 268.43
A10: unit_factor | C10: 1
A11: vp_factor | C11: 1
A13: INPUTS (company assumptions)
A14: Sales volume plan | B14: a.volume | H14: 7.535464 | I14: 7.535464 | J14: 7.535464 | K14: 7.535464
A15: Realised price / benchmark | B15: a.realisation | H15: 0.4453 | I15: 0.4453 | J15: 0.4453 | K15: 0.4453
A16: Share of volume under a price cap (e.g. DMO) | B16: a.capped_share | H16: 0.504 | I16: 0.504 | J16: 0.504 | K16: 0.504
A17: Strip ratio (bcm per tonne) or cost-intensity factor | B17: a.strip_ratio | H17: 6.62 | I17: 6.62 | J17: 6.62 | K17: 6.62
A18: Mining cost per bcm (or per unit when intensity is 1) | B18: a.cost_per_bcm | H18: 2.398 | I18: 2.398 | J18: 2.398 | K18: 2.398
A19: Fuel share of mining cost | B19: a.fuel_share | C19: 0.3
A20: Other cash cost per unit (haul, barge, process) | B20: a.other_cost_unit | H20: 20.56 | I20: 20.56 | J20: 20.56 | K20: 20.56
A21: Royalty rate (flat regimes) | B21: a.royalty_rate | H21: 0.0883 | I21: 0.0883 | J21: 0.0883 | K21: 0.0883
A22: Other revenue | B22: a.other_revenue | H22: 0 | I22: 0 | J22: 0 | K22: 0
A23: Gross margin on other revenue | B23: a.other_margin | C23: 0.1
A24: D&A per unit (reporting currency) | B24: a.da_unit | H24: 4.469 | I24: 4.469 | J24: 4.469 | K24: 4.469
A25: Sustaining capex per unit (reporting currency) | B25: a.capex_unit | H25: 3.975 | I25: 3.975 | J25: 3.975 | K25: 3.975
A26: Other capex (expansion projects) | B26: a.capex_other | H26: 0 | I26: 0 | J26: 0 | K26: 0
A27: Operating working capital / revenue | B27: a.nwc_pct | H27: -0.15894 | I27: -0.15894 | J27: -0.15894 | K27: -0.15894
A28: Effective tax rate | B28: a.tax_rate | H28: 0.356 | I28: 0.356 | J28: 0.356 | K28: 0.356
A29: Cost of debt (on opening debt) | B29: a.cost_of_debt | C29: 0.043895
A30: Yield on opening cash | B30: a.cash_yield | C30: 0.024954
A31: Net new borrowing | B31: a.net_borrowing | H31: 0 | I31: 0 | J31: 0 | K31: 0
A32: Other non-operating items | B32: a.other_nonop | H32: 0 | I32: 0 | J32: 0 | K32: 0
A33: Minorities' share of net profit | B33: a.minority_pct | H33: 0.45 | I33: 0.45 | J33: 0.45 | K33: 0.45
A34: Dividend payout | B34: a.payout | H34: 0 | I34: 0 | J34: 0 | K34: 0
A35: Change in share count | B35: a.share_change | H35: 0 | I35: 0 | J35: 0 | K35: 0
A36: Terminal growth (DCF) | B36: a.terminal_growth | C36: 0
A37: SG&A / revenue | B37: a.opex_pct | H37: 0.08687 | I37: 0.08687 | J37: 0.08687 | K37: 0.08687
A39: MODEL
A40: Reserves remaining (close) | B40: reserves | G40: 268.43 | H40: =MAX((G40-H41),0) | I40: =MAX((H40-I41),0) | J40: =MAX((I40-J41),0) | K40: =MAX((J40-K41),0)
A41: Sales volume | B41: volume | F41: 5.445246 | G41: 7.535464 | H41: =IF(($C$9>0),MIN(H14,MAX(G40,0)),H14) | I41: =IF(($C$9>0),MIN(I14,MAX(H40,0)),I14) | J41: =IF(($C$9>0),MIN(J14,MAX(I40,0)),J14) | K41: =IF(($C$9>0),MIN(K14,MAX(J40,0)),K14)
A42: Benchmark price | B42: benchmark | H42: =Drivers!$L$6 | I42: =Drivers!$M$6 | J42: =Drivers!$N$6 | K42: =Drivers!$O$6
A43: Average selling price | B43: asp | H43: =(((H15*H42)*(1-H16))+(MIN(Drivers!$L$4,(H15*H42))*H16)) | I43: =(((I15*I42)*(1-I16))+(MIN(Drivers!$M$4,(I15*I42))*I16)) | J43: =(((J15*J42)*(1-J16))+(MIN(Drivers!$N$4,(J15*J42))*J16)) | K43: =(((K15*K42)*(1-K16))+(MIN(Drivers!$O$4,(K15*K42))*K16))
A44: Realisation vs benchmark | B44: realisation_line | H44: =IF(H42=0,0,H43/H42) | I44: =IF(I42=0,0,I43/I42) | J44: =IF(J42=0,0,J43/J42) | K44: =IF(K42=0,0,K43/K42)
A45: Cash cost per unit (ex-royalty) | B45: unit_cost | H45: =(((H17*H18)*(1+($C$19*(IF(Drivers!$J$8=0,0,Drivers!$L$8/Drivers!$J$8)-1))))+H20) | I45: =(((I17*I18)*(1+($C$19*(IF(Drivers!$J$8=0,0,Drivers!$M$8/Drivers!$J$8)-1))))+I20) | J45: =(((J17*J18)*(1+($C$19*(IF(Drivers!$J$8=0,0,Drivers!$N$8/Drivers!$J$8)-1))))+J20) | K45: =(((K17*K18)*(1+($C$19*(IF(Drivers!$J$8=0,0,Drivers!$O$8/Drivers!$J$8)-1))))+K20)
A46: Strip ratio | B46: strip_ratio_line | G46: 6.62 | H46: =H17 | I46: =I17 | J46: =J17 | K46: =K17
A47: Royalty rate | B47: royalty_rate | H47: =H21 | I47: =I21 | J47: =J21 | K47: =K21
A48: EBITDA per unit (price currency) | B48: ebitda_per_unit | F48: 3.836374 | G48: 3.4475647 | H48: =IF((H41*$C$10)=0,0,H61/(H41*$C$10)) | I48: =IF((I41*$C$10)=0,0,I61/(I41*$C$10)) | J48: =IF((J41*$C$10)=0,0,J61/(J41*$C$10)) | K48: =IF((K41*$C$10)=0,0,K61/(K41*$C$10))
A49: Cash cost + royalty per unit (price currency) | B49: cash_cost_money_per_unit | H49: =IF((H41*$C$10)=0,0,(H53+H52)/(H41*$C$10)) | I49: =IF((I41*$C$10)=0,0,(I53+I52)/(I41*$C$10)) | J49: =IF((J41*$C$10)=0,0,(J53+J52)/(J41*$C$10)) | K49: =IF((K41*$C$10)=0,0,(K53+K52)/(K41*$C$10))
A50: Main product revenue | B50: revenue_main | H50: =((H41*H43)*$C$10) | I50: =((I41*I43)*$C$10) | J50: =((J41*J43)*$C$10) | K50: =((K41*K43)*$C$10)
A51: Other revenue | B51: other_revenue | H51: =H22 | I51: =I22 | J51: =J22 | K51: =K22
A52: Royalty | B52: royalty | H52: =(H50*H47) | I52: =(I50*I47) | J52: =(J50*J47) | K52: =(K50*K47)
A53: Cash costs | B53: cash_cost | H53: =((H41*H45)*$C$10) | I53: =((I41*I45)*$C$10) | J53: =((J41*J45)*$C$10) | K53: =((K41*K45)*$C$10)
A54: Cost of other revenue | B54: other_cogs | H54: =(H51*(1-$C$23)) | I54: =(I51*(1-$C$23)) | J54: =(J51*(1-$C$23)) | K54: =(K51*(1-$C$23))
A55: Revenue | B55: revenue | D55: 245.981 | E55: 280.609 | F55: 315.151 | G55: 363.677 | H55: =(H50+H51) | I55: =(I50+I51) | J55: =(J50+J51) | K55: =(K50+K51)
A56: Cost of revenue | B56: cogs | D56: 189.515 | E56: 254.659 | F56: 298.584 | G56: 337.366 | H56: =(((H53+H52)+H54)+H60) | I56: =(((I53+I52)+I54)+I60) | J56: =(((J53+J52)+J54)+J60) | K56: =(((K53+K52)+K54)+K60)
A57: Gross profit | B57: gross_profit | D57: 56.466 | E57: 25.95 | F57: 16.567 | G57: 26.311 | H57: =(H55-H56) | I57: =(I55-I56) | J57: =(J55-J56) | K57: =(K55-K56)
A58: SG&A and other opex | B58: opex | D58: 14.864 | E58: 19.211 | F58: 21.004 | G58: 34.509 | H58: =(H55*H37) | I58: =(I55*I37) | J58: =(J55*J37) | K58: =(K55*K37)
A59: EBIT | B59: ebit | D59: 41.602 | E59: 6.739 | F59: -5.545 | G59: -7.696 | H59: =(H57-H58) | I59: =(I57-I58) | J59: =(J57-J58) | K59: =(K57-K58)
A60: Depreciation & amortisation | B60: da | D60: 2.07 | E60: 2.382 | F60: 26.435 | G60: 33.675 | H60: =((H41*H24)*$C$10) | I60: =((I41*I24)*$C$10) | J60: =((J41*J24)*$C$10) | K60: =((K41*K24)*$C$10)
A61: EBITDA | B61: ebitda | D61: 43.672 | E61: 9.121 | F61: 20.89 | G61: 25.979 | H61: =(H59+H60) | I61: =(I59+I60) | J61: =(J59+J60) | K61: =(K59+K60)
A62: Interest expense | B62: interest_expense | D62: 3.662 | E62: 4.32 | F62: 3.419 | G62: 5.07 | H62: =(G82*$C$29) | I62: =(H82*$C$29) | J62: =(I82*$C$29) | K62: =(J82*$C$29)
A63: Interest income | B63: interest_income | D63: 0.103 | E63: 0.144 | F63: 0.419 | G63: 0.332 | H63: =(G81*$C$30) | I63: =(H81*$C$30) | J63: =(I81*$C$30) | K63: =(J81*$C$30)
A64: Other non-operating | B64: other_nonop | D64: -2.212 | E64: 0.648 | F64: 10.54 | G64: 19.212 | H64: =H32 | I64: =I32 | J64: =J32 | K64: =K32
A65: Profit before tax | B65: pbt | D65: 35.831 | E65: 3.211 | F65: 1.995 | G65: 6.778 | H65: =(((H59-H62)+H63)+H64) | I65: =(((I59-I62)+I63)+I64) | J65: =(((J59-J62)+J63)+J64) | K65: =(((K59-K62)+K63)+K64)
A66: Tax | B66: tax | D66: 9.756 | E66: 2.483 | F66: 1.179 | G66: 4.417 | H66: =(MAX(H65,0)*H28) | I66: =(MAX(I65,0)*I28) | J66: =(MAX(J65,0)*J28) | K66: =(MAX(K65,0)*K28)
A67: Net profit (incl. minorities) | B67: np | D67: 26.075 | E67: 0.728 | F67: 0.816 | G67: 2.361 | H67: =(H65-H66) | I67: =(I65-I66) | J67: =(J65-J66) | K67: =(K65-K66)
A68: Minority interests | B68: minority | D68: 3.742 | E68: 1.682 | F68: -0.508 | G68: 1.069 | H68: =(H67*H33) | I68: =(I67*I33) | J68: =(J67*J33) | K68: =(K67*K33)
A69: Net profit to parent | B69: np_parent | D69: 22.333 | E69: -0.954 | F69: 1.324 | G69: 1.292 | H69: =(H67-H68) | I69: =(I67-I68) | J69: =(J67-J68) | K69: =(K67-K68)
A70: Shares outstanding (m) | B70: shares | D70: 3431 | E70: 3431 | F70: 3431 | G70: 3750 | H70: =(G70*(1+H35)) | I70: =(H70*(1+I35)) | J70: =(I70*(1+J35)) | K70: =(J70*(1+K35))
A71: EPS | B71: eps | D71: 0.006509181 | E71: -0.00027805305 | F71: 0.00038589333 | G71: 0.00034453333 | H71: =(IF(H70=0,0,H69/H70)*$C$8) | I71: =(IF(I70=0,0,I69/I70)*$C$8) | J71: =(IF(J70=0,0,J69/J70)*$C$8) | K71: =(IF(K70=0,0,K69/K70)*$C$8)
A72: DPS (declared on the year) | B72: dps | D72: 0 | E72: 0 | F72: 0 | G72: 0 | H72: =(MAX(H71,0)*H34) | I72: =(MAX(I71,0)*I34) | J72: =(MAX(J71,0)*J34) | K72: =(MAX(K71,0)*K34)
A73: Dividends paid | B73: dividends_paid | H73: =IF($C$8=0,0,(G72*G70)/$C$8) | I73: =IF($C$8=0,0,(H72*H70)/$C$8) | J73: =IF($C$8=0,0,(I72*I70)/$C$8) | K73: =IF($C$8=0,0,(J72*J70)/$C$8)
A74: Capital expenditure | B74: capex | D74: 24.284 | E74: 33.337 | F74: 52.579 | G74: 32.731 | H74: =(((H41*H25)*$C$10)+H26) | I74: =(((I41*I25)*$C$10)+I26) | J74: =(((J41*J25)*$C$10)+J26) | K74: =(((K41*K25)*$C$10)+K26)
A75: Change in working capital | B75: delta_nwc | E75: -47.638 | F75: -26.244 | G75: 63.164 | H75: =(H80-G80) | I75: =(I80-H80) | J75: =(J80-I80) | K75: =(K80-J80)
A76: Free cash flow to firm | B76: fcff | E76: 18.21087 | F76: -2.1680301 | G76: -64.90077 | H76: =((((H59*(1-H28))+H60)-H74)-H75) | I76: =((((I59*(1-I28))+I60)-I74)-I75) | J76: =((((J59*(1-J28))+J60)-J74)-J75) | K76: =((((K59*(1-K28))+K60)-K74)-K75)
A77: Net borrowing | B77: net_borrowing | E77: -5.091 | F77: -3.3 | G77: -13.723 | H77: =H31 | I77: =I31 | J77: =J31 | K77: =K31
A78: Dividends to minorities | B78: minority_div | H78: =(MAX(G68,0)*H34) | I78: =(MAX(H68,0)*I34) | J78: =(MAX(I68,0)*J34) | K78: =(MAX(J68,0)*K34)
A79: Free cash flow to equity | B79: fcfe | H79: =(((((H67+H60)-H74)-H75)+H77)-H78) | I79: =(((((I67+I60)-I74)-I75)+I77)-I78) | J79: =(((((J67+J60)-J74)-J75)+J77)-J78) | K79: =(((((K67+K60)-K74)-K75)+K77)-K78)
A80: Operating working capital | B80: nwc | D80: -47.087 | E80: -94.725 | F80: -120.969 | G80: -57.805 | H80: =(H55*H27) | I80: =(I55*I27) | J80: =(J55*J27) | K80: =(K55*K27)
A81: Cash & equivalents | B81: cash | D81: 4.756 | E81: 15.325 | F81: 19.255 | G81: 12.885 | H81: =(((((((G81+H67)+H60)-H74)-H75)+H77)-H73)-H78) | I81: =(((((((H81+I67)+I60)-I74)-I75)+I77)-I73)-I78) | J81: =(((((((I81+J67)+J60)-J74)-J75)+J77)-J73)-J78) | K81: =(((((((J81+K67)+K60)-K74)-K75)+K77)-K73)-K78)
A82: Total debt | B82: debt | D82: 102.082 | E82: 96.991 | F82: 93.691 | G82: 79.968 | H82: =(G82+H77) | I82: =(H82+I77) | J82: =(I82+J77) | K82: =(J82+K77)
A83: Fixed assets (net) | B83: ppe | D83: 196.972 | E83: 213.742 | F83: 242.789 | G83: 227.275 | H83: =((G83+H74)-H60) | I83: =((H83+I74)-I60) | J83: =((I83+J74)-J60) | K83: =((J83+K74)-K60)
A84: Parent shareholders' equity | B84: equity | D84: 67.038 | E84: 66.168 | F84: 67.371 | G84: 73.532 | H84: =((G84+H69)-H73) | I84: =((H84+I69)-I73) | J84: =((I84+J69)-J73) | K84: =((J84+K69)-K73)
A85: Minority interest (balance sheet) | B85: minority_bs | D85: 3.195 | E85: 4.885 | F85: 4.286 | G85: 5.338 | H85: =((G85+H68)-H78) | I85: =((H85+I68)-I78) | J85: =((I85+J68)-J78) | K85: =((J85+K68)-K78)
A86: Other assets less other liabilities | B86: other_net | D86: 17.674 | E86: 33.702 | F86: 24.273 | G86: -23.517 | H86: =G86 | I86: =H86 | J86: =I86 | K86: =J86
A87: Balance check (should be zero) | B87: bs_check | H87: =((((((H81+H80)+H83)+H86)-H82)-H84)-H85) | I87: =((((((I81+I80)+I83)+I86)-I82)-I84)-I85) | J87: =((((((J81+J80)+J83)+J86)-J82)-J84)-J85) | K87: =((((((K81+K80)+K83)+K86)-K82)-K84)-K85)
A88: Net debt (cash) | B88: net_debt | D88: 97.326 | E88: 81.666 | F88: 74.436 | G88: 67.083 | H88: =(H82-H81) | I88: =(I82-I81) | J88: =(J82-J81) | K88: =(K82-K81)
A89: Book value per share | B89: bvps | D89: 0.01953891 | E89: 0.01928534 | F89: 0.019635966 | G89: 0.019608533 | H89: =(IF(H70=0,0,H84/H70)*$C$8) | I89: =(IF(I70=0,0,I84/I70)*$C$8) | J89: =(IF(J70=0,0,J84/J70)*$C$8) | K89: =(IF(K70=0,0,K84/K70)*$C$8)
A90: Revenue growth | B90: revenue_growth | E90: 0.1407751 | F90: 0.12309655 | G90: 0.15397698 | H90: =(IF(G55=0,0,H55/G55)-1) | I90: =(IF(H55=0,0,I55/H55)-1) | J90: =(IF(I55=0,0,J55/I55)-1) | K90: =(IF(J55=0,0,K55/J55)-1)
A91: Gross margin | B91: gross_margin | D91: 0.22955432 | E91: 0.092477433 | F91: 0.052568451 | G91: 0.072347165 | H91: =IF(H55=0,0,H57/H55) | I91: =IF(I55=0,0,I57/I55) | J91: =IF(J55=0,0,J57/J55) | K91: =IF(K55=0,0,K57/K55)
A92: EBITDA margin | B92: ebitda_margin | D92: 0.17754217 | E92: 0.032504303 | F92: 0.066285685 | G92: 0.071434267 | H92: =IF(H55=0,0,H61/H55) | I92: =IF(I55=0,0,I61/I55) | J92: =IF(J55=0,0,J61/J55) | K92: =IF(K55=0,0,K61/K55)
A93: EBIT margin | B93: ebit_margin | D93: 0.16912688 | E93: 0.024015623 | F93: -0.01759474 | G93: -0.021161635 | H93: =IF(H55=0,0,H59/H55) | I93: =IF(I55=0,0,I59/I55) | J93: =IF(J55=0,0,J59/J55) | K93: =IF(K55=0,0,K59/K55)
A94: Net margin | B94: np_margin | D94: 0.090791565 | E94: -0.0033997484 | F94: 0.0042011607 | G94: 0.003552603 | H94: =IF(H55=0,0,H69/H55) | I94: =IF(I55=0,0,I69/I55) | J94: =IF(J55=0,0,J69/J55) | K94: =IF(K55=0,0,K69/K55)
A95: EPS growth | B95: eps_growth | E95: -1.0427171 | F95: -2.3878407 | G95: -0.10717986 | H95: =(IF(G71=0,0,H71/G71)-1) | I95: =(IF(H71=0,0,I71/H71)-1) | J95: =(IF(I71=0,0,J71/I71)-1) | K95: =(IF(J71=0,0,K71/J71)-1)
A96: ROE | B96: roe | E96: -0.014323679 | F96: 0.019829413 | G96: 0.018338857 | H96: =IF(IF(2=0,0,(H84+G84)/2)=0,0,H69/IF(2=0,0,(H84+G84)/2)) | I96: =IF(IF(2=0,0,(I84+H84)/2)=0,0,I69/IF(2=0,0,(I84+H84)/2)) | J96: =IF(IF(2=0,0,(J84+I84)/2)=0,0,J69/IF(2=0,0,(J84+I84)/2)) | K96: =IF(IF(2=0,0,(K84+J84)/2)=0,0,K69/IF(2=0,0,(K84+J84)/2))
A97: Net debt / EBITDA | B97: net_debt_ebitda | D97: 2.2285675 | E97: 8.9536235 | F97: 3.563236 | G97: 2.582201 | H97: =IF(H61=0,0,H88/H61) | I97: =IF(I61=0,0,I88/I61) | J97: =IF(J61=0,0,J88/J61) | K97: =IF(K61=0,0,K88/K61)
A98: Payout ratio | B98: payout_ratio | D98: 0 | E98: 0 | F98: 0 | G98: 0 | H98: =IF(H71=0,0,H72/H71) | I98: =IF(I71=0,0,I72/I71) | J98: =IF(J71=0,0,J72/J71) | K98: =IF(K71=0,0,K72/K71)
A99: Capex / revenue | B99: capex_revenue | D99: 0.098723072 | E99: 0.11880232 | F99: 0.16683748 | G99: 0.090000192 | H99: =IF(H55=0,0,H74/H55) | I99: =IF(I55=0,0,I74/I55) | J99: =IF(J55=0,0,J74/J55) | K99: =IF(K55=0,0,K74/K55)
A101: VALUATION
A102: Last price (IDR) | C102: 500
A103: Shares outstanding (m) | C103: 3750
A104: IDR per USD (spot) | C104: 18138
A105: Debt at balance-sheet date | C105: 75.462
...

Sheet BOSS
A1: PT. Borneo Olah Sarana Sukses Tbk (BOSS.JK) — Coal producers
A2: Units: IDR bn; per-share in IDR unless marked IDR. Model asof 2026-10-30 · data 2026-10-27
A4: Line | C4: Scalar | D4: FY2021A | E4: FY2022A | F4: FY2023E | G4: FY2024E | H4: FY2025E | I4: FY2026E | J4: FY2027E | K4: FY2028E | L4: FY2029E | M4: FY2030E | N4: FY2031E | O4: FY2032E
A6: PARAMETERS
A7: horizon | C7: 10
A8: ps_factor | C8: 1000
A9: reserves | C9: 10.83
A10: unit_factor | C10: 1
A11: vp_factor | C11: 1
A13: INPUTS (company assumptions)
A14: Sales volume plan | B14: a.volume | F14: 0.0765 | G14: 0.0765 | H14: 0.0765 | I14: 0.15 | J14: 0.4 | K14: 0.48 | L14: 0.48 | M14: 0.48 | N14: 0.48 | O14: 0.48
A15: Realised price / benchmark | B15: a.realisation | F15: 0.93 | G15: 0.93 | H15: 0.93 | I15: 0.93 | J15: 0.93 | K15: 0.93 | L15: 0.93 | M15: 0.93 | N15: 0.93 | O15: 0.93
A16: Share of volume under a price cap (e.g. DMO) | B16: a.capped_share | F16: 0 | G16: 0 | H16: 0 | I16: 0 | J16: 0 | K16: 0 | L16: 0 | M16: 0 | N16: 0 | O16: 0
A17: Strip ratio (bcm per tonne) or cost-intensity factor | B17: a.strip_ratio | F17: 1 | G17: 1 | H17: 1 | I17: 1 | J17: 1 | K17: 1 | L17: 1 | M17: 1 | N17: 1 | O17: 1
A18: Mining cost per bcm (or per unit when intensity is 1) | B18: a.cost_per_bcm | F18: 104.55 | G18: 104.55 | H18: 104.55 | I18: 62.1 | J18: 62.1 | K18: 63.342 | L18: 64.60884 | M18: 65.901017 | N18: 67.219037 | O18: 68.563418
A19: Fuel share of mining cost | B19: a.fuel_share | C19: 0
A20: Other cash cost per unit (haul, barge, process) | B20: a.other_cost_unit | F20: 34.1 | G20: 34.1 | H20: 34.1 | I20: 20.3 | J20: 20.3 | K20: 20.706 | L20: 21.12012 | M20: 21.542522 | N20: 21.973373 | O20: 22.41284
A21: Royalty rate (flat regimes) | B21: a.royalty_rate | F21: 0.121 | G21: 0.121 | H21: 0.121 | I21: 0.121 | J21: 0.121 | K21: 0.121 | L21: 0.121 | M21: 0.121 | N21: 0.121 | O21: 0.121
A22: Other revenue | B22: a.other_revenue | F22: 0 | G22: 0 | H22: 0 | I22: 0 | J22: 0 | K22: 0 | L22: 0 | M22: 0 | N22: 0 | O22: 0
A23: Gross margin on other revenue | B23: a.other_margin | C23: 0.1
A24: D&A per unit (reporting currency) | B24: a.da_unit | F24: 236431 | G24: 236431 | H24: 236431 | I24: 91942 | J24: 91942 | K24: 93780.84 | L24: 95656.457 | M24: 97569.586 | N24: 99520.978 | O24: 101511.4
A25: Sustaining capex per unit (reporting currency) | B25: a.capex_unit | F25: 26664 | G25: 26664 | H25: 26664 | I25: 26664 | J25: 26664 | K25: 27197.28 | L25: 27741.226 | M25: 28296.05 | N25: 28861.971 | O25: 29439.211
A26: Other capex (expansion projects) | B26: a.capex_other | F26: 0 | G26: 0 | H26: 0 | I26: 0 | J26: 0 | K26: 0 | L26: 0 | M26: 0 | N26: 0 | O26: 0
A27: Operating working capital / revenue | B27: a.nwc_pct | F27: -0.1123 | G27: -0.1123 | H27: -0.1123 | I27: -0.1123 | J27: -0.1123 | K27: -0.1123 | L27: -0.1123 | M27: -0.1123 | N27: -0.1123 | O27: -0.1123
A28: Effective tax rate | B28: a.tax_rate | F28: 0.22 | G28: 0.22 | H28: 0.22 | I28: 0.22 | J28: 0.22 | K28: 0.22 | L28: 0.22 | M28: 0.22 | N28: 0.22 | O28: 0.22
A29: Cost of debt (on opening debt) | B29: a.cost_of_debt | C29: 0.1432
A30: Yield on opening cash | B30: a.cash_yield | C30: 0
A31: Net new borrowing | B31: a.net_borrowing | F31: 0 | G31: 0 | H31: 0 | I31: 0 | J31: 0 | K31: 0 | L31: 0 | M31: 0 | N31: 0 | O31: 0
A32: Other non-operating items | B32: a.other_nonop | F32: 0 | G32: 0 | H32: 0 | I32: 0 | J32: 0 | K32: 0 | L32: 0 | M32: 0 | N32: 0 | O32: 0
A33: Minorities' share of net profit | B33: a.minority_pct | F33: 0 | G33: 0 | H33: 0 | I33: 0 | J33: 0 | K33: 0 | L33: 0 | M33: 0 | N33: 0 | O33: 0
A34: Dividend payout | B34: a.payout | F34: 0 | G34: 0 | H34: 0 | I34: 0 | J34: 0 | K34: 0 | L34: 0 | M34: 0 | N34: 0 | O34: 0
A35: Change in share count | B35: a.share_change | F35: 0 | G35: 0 | H35: 0 | I35: 0 | J35: 0 | K35: 0 | L35: 0 | M35: 0 | N35: 0 | O35: 0
A36: Terminal growth (DCF) | B36: a.terminal_growth | C36: 0.04
A37: SG&A / revenue | B37: a.opex_pct | F37: 0.1736 | G37: 0.1736 | H37: 0.1736 | I37: 0.096 | J37: 0.096 | K37: 0.096 | L37: 0.096 | M37: 0.096 | N37: 0.096 | O37: 0.096
A39: MODEL
A40: Reserves remaining (close) | B40: reserves | E40: 10.83 | F40: =MAX((E40-F41),0) | G40: =MAX((F40-G41),0) | H40: =MAX((G40-H41),0) | I40: =MAX((H40-I41),0) | J40: =MAX((I40-J41),0) | K40: =MAX((J40-K41),0) | L40: =MAX((K40-L41),0) | M40: =MAX((L40-M41),0) | ... O40: =MAX((N40-O41),0)
A41: Sales volume | B41: volume | D41: 0.061026 | E41: 0.109322 | F41: =IF(($C$9>0),MIN(F14,MAX(E40,0)),F14) | G41: =IF(($C$9>0),MIN(G14,MAX(F40,0)),G14) | H41: =IF(($C$9>0),MIN(H14,MAX(G40,0)),H14) | I41: =IF(($C$9>0),MIN(I14,MAX(H40,0)),I14) | J41: =IF(($C$9>0),MIN(J14,MAX(I40,0)),J14) | K41: =IF(($C$9>0),MIN(K14,MAX(J40,0)),K14) | L41: =IF(($C$9>0),MIN(L14,MAX(K40,0)),L14) | M41: =IF(($C$9>0),MIN(M14,MAX(L40,0)),M14) | ... O41: =IF(($C$9>0),MIN(O14,MAX(N40,0)),O14)
A42: Benchmark price | B42: benchmark | F42: =Drivers!$G$6 | G42: =Drivers!$I$6 | H42: =Drivers!$K$6 | I42: =Drivers!$L$6 | J42: =Drivers!$M$6 | K42: =Drivers!$N$6 | L42: =Drivers!$O$6 | M42: =Drivers!$P$6 | N42: =Drivers!$Q$6 | O42: =Drivers!$R$6
A43: Average selling price | B43: asp | E43: 175 | F43: =(((F15*F42)*(1-F16))+(MIN(Drivers!$G$4,(F15*F42))*F16)) | G43: =(((G15*G42)*(1-G16))+(MIN(Drivers!$I$4,(G15*G42))*G16)) | H43: =(((H15*H42)*(1-H16))+(MIN(Drivers!$K$4,(H15*H42))*H16)) | I43: =(((I15*I42)*(1-I16))+(MIN(Drivers!$L$4,(I15*I42))*I16)) | J43: =(((J15*J42)*(1-J16))+(MIN(Drivers!$M$4,(J15*J42))*J16)) | K43: =(((K15*K42)*(1-K16))+(MIN(Drivers!$N$4,(K15*K42))*K16)) | L43: =(((L15*L42)*(1-L16))+(MIN(Drivers!$O$4,(L15*L42))*L16)) | M43: =(((M15*M42)*(1-M16))+(MIN(Drivers!$P$4,(M15*M42))*M16)) | N43: =(((N15*N42)*(1-N16))+(MIN(Drivers!$Q$4,(N15*N42))*N16)) | O43: =(((O15*O42)*(1-O16))+(MIN(Drivers!$R$4,(O15*O42))*O16))
A44: Realisation vs benchmark | B44: realisation_line | F44: =IF(F42=0,0,F43/F42) | G44: =IF(G42=0,0,G43/G42) | H44: =IF(H42=0,0,H43/H42) | I44: =IF(I42=0,0,I43/I42) | J44: =IF(J42=0,0,J43/J42) | K44: =IF(K42=0,0,K43/K42) | L44: =IF(L42=0,0,L43/L42) | M44: =IF(M42=0,0,M43/M42) | ... O44: =IF(O42=0,0,O43/O42)
A45: Cash cost per unit (ex-royalty) | B45: unit_cost | F45: =(((F17*F18)*(1+($C$19*(IF(Drivers!$E$8=0,0,Drivers!$G$8/Drivers!$E$8)-1))))+F20) | G45: =(((G17*G18)*(1+($C$19*(IF(Drivers!$E$8=0,0,Drivers!$I$8/Drivers!$E$8)-1))))+G20) | H45: =(((H17*H18)*(1+($C$19*(IF(Drivers!$E$8=0,0,Drivers!$K$8/Drivers!$E$8)-1))))+H20) | I45: =(((I17*I18)*(1+($C$19*(IF(Drivers!$E$8=0,0,Drivers!$L$8/Drivers!$E$8)-1))))+I20) | J45: =(((J17*J18)*(1+($C$19*(IF(Drivers!$E$8=0,0,Drivers!$M$8/Drivers!$E$8)-1))))+J20) | K45: =(((K17*K18)*(1+($C$19*(IF(Drivers!$E$8=0,0,Drivers!$N$8/Drivers!$E$8)-1))))+K20) | L45: =(((L17*L18)*(1+($C$19*(IF(Drivers!$E$8=0,0,Drivers!$O$8/Drivers!$E$8)-1))))+L20) | M45: =(((M17*M18)*(1+($C$19*(IF(Drivers!$E$8=0,0,Drivers!$P$8/Drivers!$E$8)-1))))+M20) | N45: =(((N17*N18)*(1+($C$19*(IF(Drivers!$E$8=0,0,Drivers!$Q$8/Drivers!$E$8)-1))))+N20) | O45: =(((O17*O18)*(1+($C$19*(IF(Drivers!$E$8=0,0,Drivers!$R$8/Drivers!$E$8)-1))))+O20)
A46: Strip ratio | B46: strip_ratio_line | F46: =F17 | G46: =G17 | H46: =H17 | I46: =I17 | J46: =J17 | K46: =K17 | L46: =L17 | M46: =M17 | ... O46: =O17
A47: Royalty rate | B47: royalty_rate | F47: =F21 | G47: =G21 | H47: =H21 | I47: =I21 | J47: =J21 | K47: =K21 | L47: =L21 | M47: =M21 | ... O47: =O21
A48: EBITDA per unit (price currency) | B48: ebitda_per_unit | D48: -72.17871 | E48: 49.368745 | F48: =IF(IF(1000=0,0,((F41*$C$10)*Drivers!$G$7)/1000)=0,0,F61/IF(1000=0,0,((F41*$C$10)*Drivers!$G$7)/1000)) | G48: =IF(IF(1000=0,0,((G41*$C$10)*Drivers!$I$7)/1000)=0,0,G61/IF(1000=0,0,((G41*$C$10)*Drivers!$I$7)/1000)) | H48: =IF(IF(1000=0,0,((H41*$C$10)*Drivers!$K$7)/1000)=0,0,H61/IF(1000=0,0,((H41*$C$10)*Drivers!$K$7)/1000)) | I48: =IF(IF(1000=0,0,((I41*$C$10)*Drivers!$L$7)/1000)=0,0,I61/IF(1000=0,0,((I41*$C$10)*Drivers!$L$7)/1000)) | J48: =IF(IF(1000=0,0,((J41*$C$10)*Drivers!$M$7)/1000)=0,0,J61/IF(1000=0,0,((J41*$C$10)*Drivers!$M$7)/1000)) | K48: =IF(IF(1000=0,0,((K41*$C$10)*Drivers!$N$7)/1000)=0,0,K61/IF(1000=0,0,((K41*$C$10)*Drivers!$N$7)/1000)) | L48: =IF(IF(1000=0,0,((L41*$C$10)*Drivers!$O$7)/1000)=0,0,L61/IF(1000=0,0,((L41*$C$10)*Drivers!$O$7)/1000)) | M48: =IF(IF(1000=0,0,((M41*$C$10)*Drivers!$P$7)/1000)=0,0,M61/IF(1000=0,0,((M41*$C$10)*Drivers!$P$7)/1000)) | N48: =IF(IF(1000=0,0,((N41*$C$10)*Drivers!$Q$7)/1000)=0,0,N61/IF(1000=0,0,((N41*$C$10)*Drivers!$Q$7)/1000)) | O48: =IF(IF(1000=0,0,((O41*$C$10)*Drivers!$R$7)/1000)=0,0,O61/IF(1000=0,0,((O41*$C$10)*Drivers!$R$7)/1000))
A49: Cash cost + royalty per unit (price currency) | B49: cash_cost_money_per_unit | F49: =IF(IF(1000=0,0,((F41*$C$10)*Drivers!$G$7)/1000)=0,0,(F53+F52)/IF(1000=0,0,((F41*$C$10)*Drivers!$G$7)/1000)) | G49: =IF(IF(1000=0,0,((G41*$C$10)*Drivers!$I$7)/1000)=0,0,(G53+G52)/IF(1000=0,0,((G41*$C$10)*Drivers!$I$7)/1000)) | H49: =IF(IF(1000=0,0,((H41*$C$10)*Drivers!$K$7)/1000)=0,0,(H53+H52)/IF(1000=0,0,((H41*$C$10)*Drivers!$K$7)/1000)) | I49: =IF(IF(1000=0,0,((I41*$C$10)*Drivers!$L$7)/1000)=0,0,(I53+I52)/IF(1000=0,0,((I41*$C$10)*Drivers!$L$7)/1000)) | J49: =IF(IF(1000=0,0,((J41*$C$10)*Drivers!$M$7)/1000)=0,0,(J53+J52)/IF(1000=0,0,((J41*$C$10)*Drivers!$M$7)/1000)) | K49: =IF(IF(1000=0,0,((K41*$C$10)*Drivers!$N$7)/1000)=0,0,(K53+K52)/IF(1000=0,0,((K41*$C$10)*Drivers!$N$7)/1000)) | L49: =IF(IF(1000=0,0,((L41*$C$10)*Drivers!$O$7)/1000)=0,0,(L53+L52)/IF(1000=0,0,((L41*$C$10)*Drivers!$O$7)/1000)) | M49: =IF(IF(1000=0,0,((M41*$C$10)*Drivers!$P$7)/1000)=0,0,(M53+M52)/IF(1000=0,0,((M41*$C$10)*Drivers!$P$7)/1000)) | N49: =IF(IF(1000=0,0,((N41*$C$10)*Drivers!$Q$7)/1000)=0,0,(N53+N52)/IF(1000=0,0,((N41*$C$10)*Drivers!$Q$7)/1000)) | O49: =IF(IF(1000=0,0,((O41*$C$10)*Drivers!$R$7)/1000)=0,0,(O53+O52)/IF(1000=0,0,((O41*$C$10)*Drivers!$R$7)/1000))
A50: Main product revenue | B50: revenue_main | F50: =IF(1000=0,0,(((F41*F43)*$C$10)*Drivers!$G$7)/1000) | G50: =IF(1000=0,0,(((G41*G43)*$C$10)*Drivers!$I$7)/1000) | H50: =IF(1000=0,0,(((H41*H43)*$C$10)*Drivers!$K$7)/1000) | I50: =IF(1000=0,0,(((I41*I43)*$C$10)*Drivers!$L$7)/1000) | J50: =IF(1000=0,0,(((J41*J43)*$C$10)*Drivers!$M$7)/1000) | K50: =IF(1000=0,0,(((K41*K43)*$C$10)*Drivers!$N$7)/1000) | L50: =IF(1000=0,0,(((L41*L43)*$C$10)*Drivers!$O$7)/1000) | M50: =IF(1000=0,0,(((M41*M43)*$C$10)*Drivers!$P$7)/1000) | N50: =IF(1000=0,0,(((N41*N43)*$C$10)*Drivers!$Q$7)/1000) | O50: =IF(1000=0,0,(((O41*O43)*$C$10)*Drivers!$R$7)/1000)
A51: Other revenue | B51: other_revenue | F51: =F22 | G51: =G22 | H51: =H22 | I51: =I22 | J51: =J22 | K51: =K22 | L51: =L22 | M51: =M22 | ... O51: =O22
A52: Royalty | B52: royalty | F52: =(F50*F47) | G52: =(G50*G47) | H52: =(H50*H47) | I52: =(I50*I47) | J52: =(J50*J47) | K52: =(K50*K47) | L52: =(L50*L47) | M52: =(M50*M47) | ... O52: =(O50*O47)
A53: Cash costs | B53: cash_cost | F53: =IF(1000=0,0,(((F41*F45)*$C$10)*Drivers!$G$7)/1000) | G53: =IF(1000=0,0,(((G41*G45)*$C$10)*Drivers!$I$7)/1000) | H53: =IF(1000=0,0,(((H41*H45)*$C$10)*Drivers!$K$7)/1000) | I53: =IF(1000=0,0,(((I41*I45)*$C$10)*Drivers!$L$7)/1000) | J53: =IF(1000=0,0,(((J41*J45)*$C$10)*Drivers!$M$7)/1000) | K53: =IF(1000=0,0,(((K41*K45)*$C$10)*Drivers!$N$7)/1000) | L53: =IF(1000=0,0,(((L41*L45)*$C$10)*Drivers!$O$7)/1000) | M53: =IF(1000=0,0,(((M41*M45)*$C$10)*Drivers!$P$7)/1000) | N53: =IF(1000=0,0,(((N41*N45)*$C$10)*Drivers!$Q$7)/1000) | O53: =IF(1000=0,0,(((O41*O45)*$C$10)*Drivers!$R$7)/1000)
A54: Cost of other revenue | B54: other_cogs | F54: =(F51*(1-$C$23)) | G54: =(G51*(1-$C$23)) | H54: =(H51*(1-$C$23)) | I54: =(I51*(1-$C$23)) | J54: =(J51*(1-$C$23)) | K54: =(K51*(1-$C$23)) | L54: =(L51*(1-$C$23)) | M54: =(M51*(1-$C$23)) | ... O54: =(O51*(1-$C$23))
A55: Revenue | B55: revenue | D55: 43.523306 | E55: 456.75107 | F55: =(F50+F51) | G55: =(G50+G51) | H55: =(H50+H51) | I55: =(I50+I51) | J55: =(J50+J51) | K55: =(K50+K51) | L55: =(L50+L51) | M55: =(M50+M51) | ... O55: =(O50+O51)
A56: Cost of revenue | B56: cogs | D56: 68.532144 | E56: 272.10682 | F56: =(((F53+F52)+F54)+F60) | G56: =(((G53+G52)+G54)+G60) | H56: =(((H53+H52)+H54)+H60) | I56: =(((I53+I52)+I54)+I60) | J56: =(((J53+J52)+J54)+J60) | K56: =(((K53+K52)+K54)+K60) | L56: =(((L53+L52)+L54)+L60) | M56: =(((M53+M52)+M54)+M60) | ... O56: =(((O53+O52)+O54)+O60)
A57: Gross profit | B57: gross_profit | D57: -25.008838 | E57: 184.64425 | F57: =(F55-F56) | G57: =(G55-G56) | H57: =(H55-H56) | I57: =(I55-I56) | J57: =(J55-J56) | K57: =(K55-K56) | L57: =(L55-L56) | M57: =(M55-M56) | ... O57: =(O55-O56)
A58: SG&A and other opex | B58: opex | D58: 46.846851 | E58: 116.02409 | F58: =(F55*F37) | G58: =(G55*G37) | H58: =(H55*H37) | I58: =(I55*I37) | J58: =(J55*J37) | K58: =(K55*K37) | L58: =(L55*L37) | M58: =(M55*M37) | ... O58: =(O55*O37)
A59: EBIT | B59: ebit | D59: -71.855688 | E59: 68.62016 | F59: =(F57-F58) | G59: =(G57-G58) | H59: =(H57-H58) | I59: =(I57-I58) | J59: =(J57-J58) | K59: =(K57-K58) | L59: =(L57-L58) | M59: =(M57-M58) | ... O59: =(O57-O58)
A60: Depreciation & amortisation | B60: da | D60: 8.8209387 | E60: 11.489804 | F60: =IF(1000=0,0,((F41*F24)*$C$10)/1000) | G60: =IF(1000=0,0,((G41*G24)*$C$10)/1000) | H60: =IF(1000=0,0,((H41*H24)*$C$10)/1000) | I60: =IF(1000=0,0,((I41*I24)*$C$10)/1000) | J60: =IF(1000=0,0,((J41*J24)*$C$10)/1000) | K60: =IF(1000=0,0,((K41*K24)*$C$10)/1000) | L60: =IF(1000=0,0,((L41*L24)*$C$10)/1000) | M60: =IF(1000=0,0,((M41*M24)*$C$10)/1000) | ... O60: =IF(1000=0,0,((O41*O24)*$C$10)/1000)
A61: EBITDA | B61: ebitda | D61: -63.03475 | E61: 80.109964 | F61: =(F59+F60) | G61: =(G59+G60) | H61: =(H59+H60) | I61: =(I59+I60) | J61: =(J59+J60) | K61: =(K59+K60) | L61: =(L59+L60) | M61: =(M59+M60) | ... O61: =(O59+O60)
A62: Interest expense | B62: interest_expense | D62: 9.1045538 | E62: 31.257291 | F62: =(E82*$C$29) | G62: =(F82*$C$29) | H62: =(G82*$C$29) | I62: =(H82*$C$29) | J62: =(I82*$C$29) | K62: =(J82*$C$29) | L62: =(K82*$C$29) | M62: =(L82*$C$29) | ... O62: =(N82*$C$29)
A63: Interest income | B63: interest_income | F63: =(E81*$C$30) | G63: =(F81*$C$30) | H63: =(G81*$C$30) | I63: =(H81*$C$30) | J63: =(I81*$C$30) | K63: =(J81*$C$30) | L63: =(K81*$C$30) | M63: =(L81*$C$30) | ... O63: =(N81*$C$30)
A64: Other non-operating | B64: other_nonop | F64: =F32 | G64: =G32 | H64: =H32 | I64: =I32 | J64: =J32 | K64: =K32 | L64: =L32 | M64: =M32 | ... O64: =O32
A65: Profit before tax | B65: pbt | D65: -165.28261 | E65: 37.694028 | F65: =(((F59-F62)+F63)+F64) | G65: =(((G59-G62)+G63)+G64) | H65: =(((H59-H62)+H63)+H64) | I65: =(((I59-I62)+I63)+I64) | J65: =(((J59-J62)+J63)+J64) | K65: =(((K59-K62)+K63)+K64) | L65: =(((L59-L62)+L63)+L64) | M65: =(((M59-M62)+M63)+M64) | ... O65: =(((O59-O62)+O63)+O64)
A66: Tax | B66: tax | D66: 0.0819621 | E66: -1.3340259 | F66: =(MAX(F65,0)*F28) | G66: =(MAX(G65,0)*G28) | H66: =(MAX(H65,0)*H28) | I66: =(MAX(I65,0)*I28) | J66: =(MAX(J65,0)*J28) | K66: =(MAX(K65,0)*K28) | L66: =(MAX(L65,0)*L28) | M66: =(MAX(M65,0)*M28) | ... O66: =(MAX(O65,0)*O28)
A67: Net profit (incl. minorities) | B67: np | D67: -165.36457 | E67: 39.028054 | F67: =(F65-F66) | G67: =(G65-G66) | H67: =(H65-H66) | I67: =(I65-I66) | J67: =(J65-J66) | K67: =(K65-K66) | L67: =(L65-L66) | M67: =(M65-M66) | ... O67: =(O65-O66)
A68: Minority interests | B68: minority | D68: -0.001248674 | E68: -0.001729044 | F68: =(F67*F33) | G68: =(G67*G33) | H68: =(H67*H33) | I68: =(I67*I33) | J68: =(J67*J33) | K68: =(K67*K33) | L68: =(L67*L33) | M68: =(M67*M33) | ... O68: =(O67*O33)
A69: Net profit to parent | B69: np_parent | D69: -165.36332 | E69: 39.029783 | F69: =(F67-F68) | G69: =(G67-G68) | H69: =(H67-H68) | I69: =(I67-I68) | J69: =(J67-J68) | K69: =(K67-K68) | L69: =(L67-L68) | M69: =(M67-M68) | ... O69: =(O67-O68)
A70: Shares outstanding (m) | B70: shares | D70: 1400 | E70: 1400 | F70: =(E70*(1+F35)) | G70: =(F70*(1+G35)) | H70: =(G70*(1+H35)) | I70: =(H70*(1+I35)) | J70: =(I70*(1+J35)) | K70: =(J70*(1+K35)) | L70: =(K70*(1+L35)) | M70: =(L70*(1+M35)) | ... O70: =(N70*(1+O35))
A71: EPS | B71: eps | D71: -118.11666 | E71: 27.878416 | F71: =(IF(F70=0,0,F69/F70)*$C$8) | G71: =(IF(G70=0,0,G69/G70)*$C$8) | H71: =(IF(H70=0,0,H69/H70)*$C$8) | I71: =(IF(I70=0,0,I69/I70)*$C$8) | J71: =(IF(J70=0,0,J69/J70)*$C$8) | K71: =(IF(K70=0,0,K69/K70)*$C$8) | L71: =(IF(L70=0,0,L69/L70)*$C$8) | M71: =(IF(M70=0,0,M69/M70)*$C$8) | ... O71: =(IF(O70=0,0,O69/O70)*$C$8)
A72: DPS (declared on the year) | B72: dps | D72: 0 | E72: 0 | F72: =(MAX(F71,0)*F34) | G72: =(MAX(G71,0)*G34) | H72: =(MAX(H71,0)*H34) | I72: =(MAX(I71,0)*I34) | J72: =(MAX(J71,0)*J34) | K72: =(MAX(K71,0)*K34) | L72: =(MAX(L71,0)*L34) | M72: =(MAX(M71,0)*M34) | ... O72: =(MAX(O71,0)*O34)
A73: Dividends paid | B73: dividends_paid | F73: =IF($C$8=0,0,(E72*E70)/$C$8) | G73: =IF($C$8=0,0,(F72*F70)/$C$8) | H73: =IF($C$8=0,0,(G72*G70)/$C$8) | I73: =IF($C$8=0,0,(H72*H70)/$C$8) | J73: =IF($C$8=0,0,(I72*I70)/$C$8) | K73: =IF($C$8=0,0,(J72*J70)/$C$8) | L73: =IF($C$8=0,0,(K72*K70)/$C$8) | M73: =IF($C$8=0,0,(L72*L70)/$C$8) | ... O73: =IF($C$8=0,0,(N72*N70)/$C$8)
A74: Capital expenditure | B74: capex | D74: 7.1912544 | E74: 6.9941602 | F74: =(IF(1000=0,0,((F41*F25)*$C$10)/1000)+F26) | G74: =(IF(1000=0,0,((G41*G25)*$C$10)/1000)+G26) | H74: =(IF(1000=0,0,((H41*H25)*$C$10)/1000)+H26) | I74: =(IF(1000=0,0,((I41*I25)*$C$10)/1000)+I26) | J74: =(IF(1000=0,0,((J41*J25)*$C$10)/1000)+J26) | K74: =(IF(1000=0,0,((K41*K25)*$C$10)/1000)+K26) | L74: =(IF(1000=0,0,((L41*L25)*$C$10)/1000)+L26) | M74: =(IF(1000=0,0,((M41*M25)*$C$10)/1000)+M26) | ... O74: =(IF(1000=0,0,((O41*O25)*$C$10)/1000)+O26)
A75: Change in working capital | B75: delta_nwc | E75: -27.445509 | F75: =(F80-E80) | G75: =(G80-F80) | H75: =(H80-G80) | I75: =(I80-H80) | J75: =(J80-I80) | K75: =(K80-J80) | L75: =(L80-K80) | M75: =(M80-L80) | ... O75: =(O80-N80)
A76: Free cash flow to firm | B76: fcff | E76: 102.98984 | F76: =((((F59*(1-F28))+F60)-F74)-F75) | G76: =((((G59*(1-G28))+G60)-G74)-G75) | H76: =((((H59*(1-H28))+H60)-H74)-H75) | I76: =((((I59*(1-I28))+I60)-I74)-I75) | J76: =((((J59*(1-J28))+J60)-J74)-J75) | K76: =((((K59*(1-K28))+K60)-K74)-K75) | L76: =((((L59*(1-L28))+L60)-L74)-L75) | M76: =((((M59*(1-M28))+M60)-M74)-M75) | ... O76: =((((O59*(1-O28))+O60)-O74)-O75)
A77: Net borrowing | B77: net_borrowing | E77: -18.069463 | F77: =F31 | G77: =G31 | H77: =H31 | I77: =I31 | J77: =J31 | K77: =K31 | L77: =L31 | M77: =M31 | ... O77: =O31
A78: Dividends to minorities | B78: minority_div | F78: =(MAX(E68,0)*F34) | G78: =(MAX(F68,0)*G34) | H78: =(MAX(G68,0)*H34) | I78: =(MAX(H68,0)*I34) | J78: =(MAX(I68,0)*J34) | K78: =(MAX(J68,0)*K34) | L78: =(MAX(K68,0)*L34) | M78: =(MAX(L68,0)*M34) | ... O78: =(MAX(N68,0)*O34)
A79: Free cash flow to equity | B79: fcfe | F79: =(((((F67+F60)-F74)-F75)+F77)-F78) | G79: =(((((G67+G60)-G74)-G75)+G77)-G78) | H79: =(((((H67+H60)-H74)-H75)+H77)-H78) | I79: =(((((I67+I60)-I74)-I75)+I77)-I78) | J79: =(((((J67+J60)-J74)-J75)+J77)-J78) | K79: =(((((K67+K60)-K74)-K75)+K77)-K78) | L79: =(((((L67+L60)-L74)-L75)+L77)-L78) | M79: =(((((M67+M60)-M74)-M75)+M77)-M78) | ... O79: =(((((O67+O60)-O74)-O75)+O77)-O78)
A80: Operating working capital | B80: nwc | D80: -23.863049 | E80: -51.308558 | F80: =(F55*F27) | G80: =(G55*G27) | H80: =(H55*H27) | I80: =(I55*I27) | J80: =(J55*J27) | K80: =(K55*K27) | L80: =(L55*L27) | M80: =(M55*M27) | ... O80: =(O55*O27)
A81: Cash & equivalents | B81: cash | D81: 1.9425434 | E81: 15.31405 | F81: =(((((((E81+F67)+F60)-F74)-F75)+F77)-F73)-F78) | G81: =(((((((F81+G67)+G60)-G74)-G75)+G77)-G73)-G78) | H81: =(((((((G81+H67)+H60)-H74)-H75)+H77)-H73)-H78) | I81: =(((((((H81+I67)+I60)-I74)-I75)+I77)-I73)-I78) | J81: =(((((((I81+J67)+J60)-J74)-J75)+J77)-J73)-J78) | K81: =(((((((J81+K67)+K60)-K74)-K75)+K77)-K73)-K78) | L81: =(((((((K81+L67)+L60)-L74)-L75)+L77)-L73)-L78) | M81: =(((((((L81+M67)+M60)-M74)-M75)+M77)-M73)-M78) | ... O81: =(((((((N81+O67)+O60)-O74)-O75)+O77)-O73)-O78)
A82: Total debt | B82: debt | D82: 218.27615 | E82: 200.20668 | F82: =(E82+F77) | G82: =(F82+G77) | H82: =(G82+H77) | I82: =(H82+I77) | J82: =(I82+J77) | K82: =(J82+K77) | L82: =(K82+L77) | M82: =(L82+M77) | ... O82: =(N82+O77)
A83: Fixed assets (net) | B83: ppe | D83: 362.9828 | E83: 354.19444 | F83: =((E83+F74)-F60) | G83: =((F83+G74)-G60) | H83: =((G83+H74)-H60) | I83: =((H83+I74)-I60) | J83: =((I83+J74)-J60) | K83: =((J83+K74)-K60) | L83: =((K83+L74)-L60) | M83: =((L83+M74)-M60) | ... O83: =((N83+O74)-O60)
A84: Parent shareholders' equity | B84: equity | D84: -78.016565 | E84: -39.38325 | F84: =((E84+F69)-F73) | G84: =((F84+G69)-G73) | H84: =((G84+H69)-H73) | I84: =((H84+I69)-I73) | J84: =((I84+J69)-J73) | K84: =((J84+K69)-K73) | L84: =((K84+L69)-L73) | M84: =((L84+M69)-M73) | ... O84: =((N84+O69)-O73)
A85: Minority interest (balance sheet) | B85: minority_bs | D85: 0.002301699 | E85: 0.000569324 | F85: =((E85+F68)-F78) | G85: =((F85+G68)-G78) | H85: =((G85+H68)-H78) | I85: =((H85+I68)-I78) | J85: =((I85+J68)-J78) | K85: =((J85+K68)-K78) | L85: =((K85+L68)-L78) | M85: =((L85+M68)-M78) | ... O85: =((N85+O68)-O78)
A86: Other assets less other liabilities | B86: other_net | D86: -200.80041 | E86: -157.37593 | F86: =E86 | G86: =F86 | H86: =G86 | I86: =H86 | J86: =I86 | K86: =J86 | L86: =K86 | M86: =L86 | ... O86: =N86
A87: Balance check (should be zero) | B87: bs_check | F87: =((((((F81+F80)+F83)+F86)-F82)-F84)-F85) | G87: =((((((G81+G80)+G83)+G86)-G82)-G84)-G85) | H87: =((((((H81+H80)+H83)+H86)-H82)-H84)-H85) | I87: =((((((I81+I80)+I83)+I86)-I82)-I84)-I85) | J87: =((((((J81+J80)+J83)+J86)-J82)-J84)-J85) | K87: =((((((K81+K80)+K83)+K86)-K82)-K84)-K85) | L87: =((((((L81+L80)+L83)+L86)-L82)-L84)-L85) | M87: =((((((M81+M80)+M83)+M86)-M82)-M84)-M85) | ... O87: =((((((O81+O80)+O83)+O86)-O82)-O84)-O85)
A88: Net debt (cash) | B88: net_debt | D88: 216.3336 | E88: 184.89263 | F88: =(F82-F81) | G88: =(G82-G81) | H88: =(H82-H81) | I88: =(I82-I81) | J88: =(J82-J81) | K88: =(K82-K81) | L88: =(L82-L81) | M88: =(M82-M81) | ... O88: =(O82-O81)
A89: Book value per share | B89: bvps | D89: -55.726118 | E89: -28.130893 | F89: =(IF(F70=0,0,F84/F70)*$C$8) | G89: =(IF(G70=0,0,G84/G70)*$C$8) | H89: =(IF(H70=0,0,H84/H70)*$C$8) | I89: =(IF(I70=0,0,I84/I70)*$C$8) | J89: =(IF(J70=0,0,J84/J70)*$C$8) | K89: =(IF(K70=0,0,K84/K70)*$C$8) | L89: =(IF(L70=0,0,L84/L70)*$C$8) | M89: =(IF(M70=0,0,M84/M70)*$C$8) | ... O89: =(IF(O70=0,0,O84/O70)*$C$8)
A90: Revenue growth | B90: revenue_growth | E90: 9.4944019 | F90: =(IF(E55=0,0,F55/E55)-1) | G90: =(IF(F55=0,0,G55/F55)-1) | H90: =(IF(G55=0,0,H55/G55)-1) | I90: =(IF(H55=0,0,I55/H55)-1) | J90: =(IF(I55=0,0,J55/I55)-1) | K90: =(IF(J55=0,0,K55/J55)-1) | L90: =(IF(K55=0,0,L55/K55)-1) | M90: =(IF(L55=0,0,M55/L55)-1) | ... O90: =(IF(N55=0,0,O55/N55)-1)
A91: Gross margin | B91: gross_margin | D91: -0.57460795 | E91: 0.40425576 | F91: =IF(F55=0,0,F57/F55) | G91: =IF(G55=0,0,G57/G55) | H91: =IF(H55=0,0,H57/H55) | I91: =IF(I55=0,0,I57/I55) | J91: =IF(J55=0,0,J57/J55) | K91: =IF(K55=0,0,K57/K55) | L91: =IF(L55=0,0,L57/L55) | M91: =IF(M55=0,0,M57/M55) | ... O91: =IF(O55=0,0,O57/O55)
A92: EBITDA margin | B92: ebitda_margin | D92: -1.4482987 | E92: 0.17539086 | F92: =IF(F55=0,0,F61/F55) | G92: =IF(G55=0,0,G61/G55) | H92: =IF(H55=0,0,H61/H55) | I92: =IF(I55=0,0,I61/I55) | J92: =IF(J55=0,0,J61/J55) | K92: =IF(K55=0,0,K61/K55) | L92: =IF(L55=0,0,L61/L55) | M92: =IF(M55=0,0,M61/M55) | ... O92: =IF(O55=0,0,O61/O55)
A93: EBIT margin | B93: ebit_margin | D93: -1.6509704 | E93: 0.15023536 | F93: =IF(F55=0,0,F59/F55) | G93: =IF(G55=0,0,G59/G55) | H93: =IF(H55=0,0,H59/H55) | I93: =IF(I55=0,0,I59/I55) | J93: =IF(J55=0,0,J59/J55) | K93: =IF(K55=0,0,K59/K55) | L93: =IF(L55=0,0,L59/L55) | M93: =IF(M55=0,0,M59/M55) | ... O93: =IF(O55=0,0,O59/O55)
A94: Net margin | B94: np_margin | D94: -3.7994201 | E94: 0.085450885 | F94: =IF(F55=0,0,F69/F55) | G94: =IF(G55=0,0,G69/G55) | H94: =IF(H55=0,0,H69/H55) | I94: =IF(I55=0,0,I69/I55) | J94: =IF(J55=0,0,J69/J55) | K94: =IF(K55=0,0,K69/K55) | L94: =IF(L55=0,0,L69/L55) | M94: =IF(M55=0,0,M69/M55) | ... O94: =IF(O55=0,0,O69/O55)
A95: EPS growth | B95: eps_growth | E95: -1.2360244 | F95: =(IF(E71=0,0,F71/E71)-1) | G95: =(IF(F71=0,0,G71/F71)-1) | H95: =(IF(G71=0,0,H71/G71)-1) | I95: =(IF(H71=0,0,I71/H71)-1) | J95: =(IF(I71=0,0,J71/I71)-1) | K95: =(IF(J71=0,0,K71/J71)-1) | L95: =(IF(K71=0,0,L71/K71)-1) | M95: =(IF(L71=0,0,M71/L71)-1) | ... O95: =(IF(N71=0,0,O71/N71)-1)
A96: ROE | B96: roe | E96: -0.66490365 | F96: =IF(IF(2=0,0,(F84+E84)/2)=0,0,F69/IF(2=0,0,(F84+E84)/2)) | G96: =IF(IF(2=0,0,(G84+F84)/2)=0,0,G69/IF(2=0,0,(G84+F84)/2)) | H96: =IF(IF(2=0,0,(H84+G84)/2)=0,0,H69/IF(2=0,0,(H84+G84)/2)) | I96: =IF(IF(2=0,0,(I84+H84)/2)=0,0,I69/IF(2=0,0,(I84+H84)/2)) | J96: =IF(IF(2=0,0,(J84+I84)/2)=0,0,J69/IF(2=0,0,(J84+I84)/2)) | K96: =IF(IF(2=0,0,(K84+J84)/2)=0,0,K69/IF(2=0,0,(K84+J84)/2)) | L96: =IF(IF(2=0,0,(L84+K84)/2)=0,0,L69/IF(2=0,0,(L84+K84)/2)) | M96: =IF(IF(2=0,0,(M84+L84)/2)=0,0,M69/IF(2=0,0,(M84+L84)/2)) | ... O96: =IF(IF(2=0,0,(O84+N84)/2)=0,0,O69/IF(2=0,0,(O84+N84)/2))
A97: Net debt / EBITDA | B97: net_debt_ebitda | D97: -3.4319737 | E97: 2.3079855 | F97: =IF(F61=0,0,F88/F61) | G97: =IF(G61=0,0,G88/G61) | H97: =IF(H61=0,0,H88/H61) | I97: =IF(I61=0,0,I88/I61) | J97: =IF(J61=0,0,J88/J61) | K97: =IF(K61=0,0,K88/K61) | L97: =IF(L61=0,0,L88/L61) | M97: =IF(M61=0,0,M88/M61) | ... O97: =IF(O61=0,0,O88/O61)
A98: Payout ratio | B98: payout_ratio | D98: 0 | E98: 0 | F98: =IF(F71=0,0,F72/F71) | G98: =IF(G71=0,0,G72/G71) | H98: =IF(H71=0,0,H72/H71) | I98: =IF(I71=0,0,I72/I71) | J98: =IF(J71=0,0,J72/J71) | K98: =IF(K71=0,0,K72/K71) | L98: =IF(L71=0,0,L72/L71) | M98: =IF(M71=0,0,M72/M71) | ... O98: =IF(O71=0,0,O72/O71)
A99: Capex / revenue | B99: capex_revenue | D99: 0.16522767 | E99: 0.015312849 | F99: =IF(F55=0,0,F74/F55) | G99: =IF(G55=0,0,G74/G55) | H99: =IF(H55=0,0,H74/H55) | I99: =IF(I55=0,0,I74/I55) | J99: =IF(J55=0,0,J74/J55) | K99: =IF(K55=0,0,K74/K55) | L99: =IF(L55=0,0,L74/L55) | M99: =IF(M55=0,0,M74/M55) | ... O99: =IF(O55=0,0,O74/O55)
A101: VALUATION
A102: Last price (IDR) | C102: 50
A103: Shares outstanding (m) | C103: 1400
A104: IDR per USD (spot) | C104: 18138
A105: Debt at balance-sheet date | C105: 200.20668
...

Sheet BSSR
A1: PT Baramulti Suksessarana Tbk (BSSR.JK) — Coal producers
A2: Units: USD m; per-share in USD unless marked IDR. Model asof 2026-10-30 · data 2026-10-26
A4: Line | C4: Scalar | D4: FY2022A | E4: FY2023A | F4: FY2024A | G4: FY2025A | H4: FY2026E | I4: FY2027E | J4: FY2028E | K4: FY2029E | L4: FY2030E | M4: FY2031E | N4: FY2032E | O4: FY2033E | P4: FY2034E | Q4: FY2035E
A6: PARAMETERS
A7: horizon | C7: 10
A8: ps_factor | C8: 1
A9: reserves | C9: 0
A10: unit_factor | C10: 1
A11: vp_factor | C11: 1
A13: INPUTS (company assumptions)
A14: Sales volume plan | B14: a.volume | H14: 17 | I14: 17 | J14: 17 | K14: 17 | L14: 17 | M14: 17 | N14: 17 | O14: 17 | P14: 17 | Q14: 17
A15: Realised price / benchmark | B15: a.realisation | H15: 0.369 | I15: 0.369 | J15: 0.369 | K15: 0.369 | L15: 0.369 | M15: 0.369 | N15: 0.369 | O15: 0.369 | P15: 0.369 | Q15: 0.369
A16: Share of volume under a price cap (e.g. DMO) | B16: a.capped_share | H16: 0.3 | I16: 0.3 | J16: 0.3 | K16: 0.3 | L16: 0.3 | M16: 0.3 | N16: 0.3 | O16: 0.3 | P16: 0.3 | Q16: 0.3
A17: Strip ratio (bcm per tonne) or cost-intensity factor | B17: a.strip_ratio | H17: 1 | I17: 1 | J17: 1 | K17: 1 | L17: 1 | M17: 1 | N17: 1 | O17: 1 | P17: 1 | Q17: 1
A18: Mining cost per bcm (or per unit when intensity is 1) | B18: a.cost_per_bcm | H18: 22.26 | I18: 22.26 | J18: 22.26 | K18: 22.26 | L18: 22.26 | M18: 22.7052 | N18: 23.159304 | O18: 23.62249 | P18: 24.09494 | Q18: 24.576839
A19: Fuel share of mining cost | B19: a.fuel_share | C19: 0.3
A20: Other cash cost per unit (haul, barge, process) | B20: a.other_cost_unit | H20: 0 | I20: 0 | J20: 0 | K20: 0 | L20: 0 | M20: 0 | N20: 0 | O20: 0 | P20: 0 | Q20: 0
A21: Royalty rate (flat regimes) | B21: a.royalty_rate | H21: 0.1475 | I21: 0.1475 | J21: 0.1475 | K21: 0.1475 | L21: 0.1475 | M21: 0.1475 | N21: 0.1475 | O21: 0.1475 | P21: 0.1475 | Q21: 0.1475
A22: Other revenue | B22: a.other_revenue | H22: 0 | I22: 0 | J22: 0 | K22: 0 | L22: 0 | M22: 0 | N22: 0 | O22: 0 | P22: 0 | Q22: 0
A23: Gross margin on other revenue | B23: a.other_margin | C23: 0.1
A24: D&A per unit (reporting currency) | B24: a.da_unit | H24: 0.68815 | I24: 0.68815 | J24: 0.68815 | K24: 0.68815 | L24: 0.68815 | M24: 0.701913 | N24: 0.71595126 | O24: 0.73027029 | P24: 0.74487569 | Q24: 0.7597732
A25: Sustaining capex per unit (reporting currency) | B25: a.capex_unit | H25: 1.55 | I25: 1.55 | J25: 1.55 | K25: 1.55 | L25: 1.55 | M25: 1.581 | N25: 1.61262 | O25: 1.6448724 | P25: 1.6777698 | Q25: 1.7113252
A26: Other capex (expansion projects) | B26: a.capex_other | H26: 0 | I26: 0 | J26: 0 | K26: 0 | L26: 0 | M26: 0 | N26: 0 | O26: 0 | P26: 0 | Q26: 0
A27: Operating working capital / revenue | B27: a.nwc_pct | H27: 0.055363 | I27: 0.055363 | J27: 0.055363 | K27: 0.055363 | L27: 0.055363 | M27: 0.055363 | N27: 0.055363 | O27: 0.055363 | P27: 0.055363 | Q27: 0.055363
A28: Effective tax rate | B28: a.tax_rate | H28: 0.231966 | I28: 0.231966 | J28: 0.231966 | K28: 0.231966 | L28: 0.231966 | M28: 0.231966 | N28: 0.231966 | O28: 0.231966 | P28: 0.231966 | Q28: 0.231966
A29: Cost of debt (on opening debt) | B29: a.cost_of_debt | C29: 0.040524
A30: Yield on opening cash | B30: a.cash_yield | C30: 0.042371
A31: Net new borrowing | B31: a.net_borrowing | H31: 0 | I31: 0 | J31: 0 | K31: 0 | L31: 0 | M31: 0 | N31: 0 | O31: 0 | P31: 0 | Q31: 0
A32: Other non-operating items | B32: a.other_nonop | H32: 0 | I32: 0 | J32: 0 | K32: 0 | L32: 0 | M32: 0 | N32: 0 | O32: 0 | P32: 0 | Q32: 0
A33: Minorities' share of net profit | B33: a.minority_pct | H33: 3e-06 | I33: 3e-06 | J33: 3e-06 | K33: 3e-06 | L33: 3e-06 | M33: 3e-06 | N33: 3e-06 | O33: 3e-06 | P33: 3e-06 | Q33: 3e-06
A34: Dividend payout | B34: a.payout | H34: 0.7 | I34: 0.7 | J34: 0.7 | K34: 0.7 | L34: 0.7 | M34: 0.7 | N34: 0.7 | O34: 0.7 | P34: 0.7 | Q34: 0.7
A35: Change in share count | B35: a.share_change | H35: 0 | I35: 0 | J35: 0 | K35: 0 | L35: 0 | M35: 0 | N35: 0 | O35: 0 | P35: 0 | Q35: 0
A36: Terminal growth (DCF) | B36: a.terminal_growth | C36: 0
A37: SG&A / revenue | B37: a.opex_pct | H37: 0.151 | I37: 0.151 | J37: 0.151 | K37: 0.151 | L37: 0.151 | M37: 0.151 | N37: 0.151 | O37: 0.151 | P37: 0.151 | Q37: 0.151
A39: MODEL
A40: Reserves remaining (close) | B40: reserves | H40: =MAX((G40-H41),0) | I40: =MAX((H40-I41),0) | J40: =MAX((I40-J41),0) | K40: =MAX((J40-K41),0) | L40: =MAX((K40-L41),0) | M40: =MAX((L40-M41),0) | N40: =MAX((M40-N41),0) | O40: =MAX((N40-O41),0) | ... Q40: =MAX((P40-Q41),0)
A41: Sales volume | B41: volume | F41: 20.79 | G41: 17.579 | H41: =IF(($C$9>0),MIN(H14,MAX(G40,0)),H14) | I41: =IF(($C$9>0),MIN(I14,MAX(H40,0)),I14) | J41: =IF(($C$9>0),MIN(J14,MAX(I40,0)),J14) | K41: =IF(($C$9>0),MIN(K14,MAX(J40,0)),K14) | L41: =IF(($C$9>0),MIN(L14,MAX(K40,0)),L14) | M41: =IF(($C$9>0),MIN(M14,MAX(L40,0)),M14) | N41: =IF(($C$9>0),MIN(N14,MAX(M40,0)),N14) | O41: =IF(($C$9>0),MIN(O14,MAX(N40,0)),O14) | ... Q41: =IF(($C$9>0),MIN(Q14,MAX(P40,0)),Q14)
A42: Benchmark price | B42: benchmark | H42: =Drivers!$L$6 | I42: =Drivers!$M$6 | J42: =Drivers!$N$6 | K42: =Drivers!$O$6 | L42: =Drivers!$P$6 | M42: =Drivers!$Q$6 | N42: =Drivers!$R$6 | O42: =Drivers!$S$6 | P42: =Drivers!$T$6 | Q42: =Drivers!$U$6
A43: Average selling price | B43: asp | H43: =(((H15*H42)*(1-H16))+(MIN(Drivers!$L$4,(H15*H42))*H16)) | I43: =(((I15*I42)*(1-I16))+(MIN(Drivers!$M$4,(I15*I42))*I16)) | J43: =(((J15*J42)*(1-J16))+(MIN(Drivers!$N$4,(J15*J42))*J16)) | K43: =(((K15*K42)*(1-K16))+(MIN(Drivers!$O$4,(K15*K42))*K16)) | L43: =(((L15*L42)*(1-L16))+(MIN(Drivers!$P$4,(L15*L42))*L16)) | M43: =(((M15*M42)*(1-M16))+(MIN(Drivers!$Q$4,(M15*M42))*M16)) | N43: =(((N15*N42)*(1-N16))+(MIN(Drivers!$R$4,(N15*N42))*N16)) | O43: =(((O15*O42)*(1-O16))+(MIN(Drivers!$S$4,(O15*O42))*O16)) | P43: =(((P15*P42)*(1-P16))+(MIN(Drivers!$T$4,(P15*P42))*P16)) | Q43: =(((Q15*Q42)*(1-Q16))+(MIN(Drivers!$U$4,(Q15*Q42))*Q16))
A44: Realisation vs benchmark | B44: realisation_line | H44: =IF(H42=0,0,H43/H42) | I44: =IF(I42=0,0,I43/I42) | J44: =IF(J42=0,0,J43/J42) | K44: =IF(K42=0,0,K43/K42) | L44: =IF(L42=0,0,L43/L42) | M44: =IF(M42=0,0,M43/M42) | N44: =IF(N42=0,0,N43/N42) | O44: =IF(O42=0,0,O43/O42) | ... Q44: =IF(Q42=0,0,Q43/Q42)
A45: Cash cost per unit (ex-royalty) | B45: unit_cost | H45: =(((H17*H18)*(1+($C$19*(IF(Drivers!$J$8=0,0,Drivers!$L$8/Drivers!$J$8)-1))))+H20) | I45: =(((I17*I18)*(1+($C$19*(IF(Drivers!$J$8=0,0,Drivers!$M$8/Drivers!$J$8)-1))))+I20) | J45: =(((J17*J18)*(1+($C$19*(IF(Drivers!$J$8=0,0,Drivers!$N$8/Drivers!$J$8)-1))))+J20) | K45: =(((K17*K18)*(1+($C$19*(IF(Drivers!$J$8=0,0,Drivers!$O$8/Drivers!$J$8)-1))))+K20) | L45: =(((L17*L18)*(1+($C$19*(IF(Drivers!$J$8=0,0,Drivers!$P$8/Drivers!$J$8)-1))))+L20) | M45: =(((M17*M18)*(1+($C$19*(IF(Drivers!$J$8=0,0,Drivers!$Q$8/Drivers!$J$8)-1))))+M20) | N45: =(((N17*N18)*(1+($C$19*(IF(Drivers!$J$8=0,0,Drivers!$R$8/Drivers!$J$8)-1))))+N20) | O45: =(((O17*O18)*(1+($C$19*(IF(Drivers!$J$8=0,0,Drivers!$S$8/Drivers!$J$8)-1))))+O20) | P45: =(((P17*P18)*(1+($C$19*(IF(Drivers!$J$8=0,0,Drivers!$T$8/Drivers!$J$8)-1))))+P20) | Q45: =(((Q17*Q18)*(1+($C$19*(IF(Drivers!$J$8=0,0,Drivers!$U$8/Drivers!$J$8)-1))))+Q20)
A46: Strip ratio | B46: strip_ratio_line | H46: =H17 | I46: =I17 | J46: =J17 | K46: =K17 | L46: =L17 | M46: =M17 | N46: =N17 | O46: =O17 | ... Q46: =Q17
A47: Royalty rate | B47: royalty_rate | H47: =H21 | I47: =I21 | J47: =J21 | K47: =K21 | L47: =L21 | M47: =M21 | N47: =N21 | O47: =O21 | ... Q47: =Q21
A48: EBITDA per unit (price currency) | B48: ebitda_per_unit | F48: 8.170989 | G48: 5.8282939 | H48: =IF((H41*$C$10)=0,0,H61/(H41*$C$10)) | I48: =IF((I41*$C$10)=0,0,I61/(I41*$C$10)) | J48: =IF((J41*$C$10)=0,0,J61/(J41*$C$10)) | K48: =IF((K41*$C$10)=0,0,K61/(K41*$C$10)) | L48: =IF((L41*$C$10)=0,0,L61/(L41*$C$10)) | M48: =IF((M41*$C$10)=0,0,M61/(M41*$C$10)) | N48: =IF((N41*$C$10)=0,0,N61/(N41*$C$10)) | O48: =IF((O41*$C$10)=0,0,O61/(O41*$C$10)) | ... Q48: =IF((Q41*$C$10)=0,0,Q61/(Q41*$C$10))
A49: Cash cost + royalty per unit (price currency) | B49: cash_cost_money_per_unit | H49: =IF((H41*$C$10)=0,0,(H53+H52)/(H41*$C$10)) | I49: =IF((I41*$C$10)=0,0,(I53+I52)/(I41*$C$10)) | J49: =IF((J41*$C$10)=0,0,(J53+J52)/(J41*$C$10)) | K49: =IF((K41*$C$10)=0,0,(K53+K52)/(K41*$C$10)) | L49: =IF((L41*$C$10)=0,0,(L53+L52)/(L41*$C$10)) | M49: =IF((M41*$C$10)=0,0,(M53+M52)/(M41*$C$10)) | N49: =IF((N41*$C$10)=0,0,(N53+N52)/(N41*$C$10)) | O49: =IF((O41*$C$10)=0,0,(O53+O52)/(O41*$C$10)) | ... Q49: =IF((Q41*$C$10)=0,0,(Q53+Q52)/(Q41*$C$10))
A50: Main product revenue | B50: revenue_main | H50: =((H41*H43)*$C$10) | I50: =((I41*I43)*$C$10) | J50: =((J41*J43)*$C$10) | K50: =((K41*K43)*$C$10) | L50: =((L41*L43)*$C$10) | M50: =((M41*M43)*$C$10) | N50: =((N41*N43)*$C$10) | O50: =((O41*O43)*$C$10) | ... Q50: =((Q41*Q43)*$C$10)
A51: Other revenue | B51: other_revenue | H51: =H22 | I51: =I22 | J51: =J22 | K51: =K22 | L51: =L22 | M51: =M22 | N51: =N22 | O51: =O22 | ... Q51: =Q22
A52: Royalty | B52: royalty | H52: =(H50*H47) | I52: =(I50*I47) | J52: =(J50*J47) | K52: =(K50*K47) | L52: =(L50*L47) | M52: =(M50*M47) | N52: =(N50*N47) | O52: =(O50*O47) | ... Q52: =(Q50*Q47)
A53: Cash costs | B53: cash_cost | H53: =((H41*H45)*$C$10) | I53: =((I41*I45)*$C$10) | J53: =((J41*J45)*$C$10) | K53: =((K41*K45)*$C$10) | L53: =((L41*L45)*$C$10) | M53: =((M41*M45)*$C$10) | N53: =((N41*N45)*$C$10) | O53: =((O41*O45)*$C$10) | ... Q53: =((Q41*Q45)*$C$10)
A54: Cost of other revenue | B54: other_cogs | H54: =(H51*(1-$C$23)) | I54: =(I51*(1-$C$23)) | J54: =(J51*(1-$C$23)) | K54: =(K51*(1-$C$23)) | L54: =(L51*(1-$C$23)) | M54: =(M51*(1-$C$23)) | N54: =(N51*(1-$C$23)) | O54: =(O51*(1-$C$23)) | ... Q54: =(Q51*(1-$C$23))
A55: Revenue | B55: revenue | D55: 1029.0159 | E55: 1134.3366 | F55: 947.76946 | G55: 703.77374 | H55: =(H50+H51) | I55: =(I50+I51) | J55: =(J50+J51) | K55: =(K50+K51) | L55: =(L50+L51) | M55: =(M50+M51) | N55: =(N50+N51) | O55: =(O50+O51) | ... Q55: =(Q50+Q51)
A56: Cost of revenue | B56: cogs | D56: 565.71483 | E56: 783.05536 | F56: 638.60863 | G56: 495.17976 | H56: =(((H53+H52)+H54)+H60) | I56: =(((I53+I52)+I54)+I60) | J56: =(((J53+J52)+J54)+J60) | K56: =(((K53+K52)+K54)+K60) | L56: =(((L53+L52)+L54)+L60) | M56: =(((M53+M52)+M54)+M60) | N56: =(((N53+N52)+N54)+N60) | O56: =(((O53+O52)+O54)+O60) | ... Q56: =(((Q53+Q52)+Q54)+Q60)
A57: Gross profit | B57: gross_profit | D57: 463.30103 | E57: 351.28125 | F57: 309.16083 | G57: 208.59398 | H57: =(H55-H56) | I57: =(I55-I56) | J57: =(J55-J56) | K57: =(K55-K56) | L57: =(L55-L56) | M57: =(M55-M56) | N57: =(N55-N56) | O57: =(O55-O56) | ... Q57: =(Q55-Q56)
A58: SG&A and other opex | B58: opex | D58: 157.68718 | E58: 130.72486 | F58: 139.3997 | G58: 106.26324 | H58: =(H55*H37) | I58: =(I55*I37) | J58: =(J55*J37) | K58: =(K55*K37) | L58: =(L55*L37) | M58: =(M55*M37) | N58: =(N55*N37) | O58: =(O55*O37) | ... Q58: =(Q55*Q37)
A59: EBIT | B59: ebit | D59: 305.61385 | E59: 220.55639 | F59: 169.76113 | G59: 102.33074 | H59: =(H57-H58) | I59: =(I57-I58) | J59: =(J57-J58) | K59: =(K57-K58) | L59: =(L57-L58) | M59: =(M57-M58) | N59: =(N57-N58) | O59: =(O57-O58) | ... Q59: =(Q57-Q58)
A60: Depreciation & amortisation | B60: da | F60: 0.113731 | G60: 0.124837 | H60: =((H41*H24)*$C$10) | I60: =((I41*I24)*$C$10) | J60: =((J41*J24)*$C$10) | K60: =((K41*K24)*$C$10) | L60: =((L41*L24)*$C$10) | M60: =((M41*M24)*$C$10) | N60: =((N41*N24)*$C$10) | O60: =((O41*O24)*$C$10) | ... Q60: =((Q41*Q24)*$C$10)
A61: EBITDA | B61: ebitda | F61: 169.87486 | G61: 102.45558 | H61: =(H59+H60) | I61: =(I59+I60) | J61: =(J59+J60) | K61: =(K59+K60) | L61: =(L59+L60) | M61: =(M59+M60) | N61: =(N59+N60) | O61: =(O59+O60) | ... Q61: =(Q59+Q60)
A62: Interest expense | B62: interest_expense | D62: 0.473804 | E62: 0.370239 | F62: 0.228144 | G62: 0.101082 | H62: =(G82*$C$29) | I62: =(H82*$C$29) | J62: =(I82*$C$29) | K62: =(J82*$C$29) | L62: =(K82*$C$29) | M62: =(L82*$C$29) | N62: =(M82*$C$29) | O62: =(N82*$C$29) | ... Q62: =(P82*$C$29)
A63: Interest income | B63: interest_income | D63: 0.975606 | E63: 2.669803 | F63: 2.130542 | G63: 1.790177 | H63: =(G81*$C$30) | I63: =(H81*$C$30) | J63: =(I81*$C$30) | K63: =(J81*$C$30) | L63: =(K81*$C$30) | M63: =(L81*$C$30) | N63: =(M81*$C$30) | O63: =(N81*$C$30) | ... Q63: =(P81*$C$30)
A64: Other non-operating | B64: other_nonop | D64: 2.665519 | E64: -2.266003 | F64: -0.033223 | G64: 0.69946 | H64: =H32 | I64: =I32 | J64: =J32 | K64: =K32 | L64: =L32 | M64: =M32 | N64: =N32 | O64: =O32 | ... Q64: =Q32
A65: Profit before tax | B65: pbt | D65: 308.78118 | E65: 220.58995 | F65: 171.63031 | G65: 104.7193 | H65: =(((H59-H62)+H63)+H64) | I65: =(((I59-I62)+I63)+I64) | J65: =(((J59-J62)+J63)+J64) | K65: =(((K59-K62)+K63)+K64) | L65: =(((L59-L62)+L63)+L64) | M65: =(((M59-M62)+M63)+M64) | N65: =(((N59-N62)+N63)+N64) | O65: =(((O59-O62)+O63)+O64) | ... Q65: =(((Q59-Q62)+Q63)+Q64)
A66: Tax | B66: tax | D66: 68.885156 | E66: 58.320495 | F66: 40.078628 | G66: 20.733919 | H66: =(MAX(H65,0)*H28) | I66: =(MAX(I65,0)*I28) | J66: =(MAX(J65,0)*J28) | K66: =(MAX(K65,0)*K28) | L66: =(MAX(L65,0)*L28) | M66: =(MAX(M65,0)*M28) | N66: =(MAX(N65,0)*N28) | O66: =(MAX(O65,0)*O28) | ... Q66: =(MAX(Q65,0)*Q28)
A67: Net profit (incl. minorities) | B67: np | D67: 239.89602 | E67: 162.26946 | F67: 131.55168 | G67: 83.985377 | H67: =(H65-H66) | I67: =(I65-I66) | J67: =(J65-J66) | K67: =(K65-K66) | L67: =(L65-L66) | M67: =(M65-M66) | N67: =(N65-N66) | O67: =(O65-O66) | ... Q67: =(Q65-Q66)
A68: Minority interests | B68: minority | D68: 0.000415 | E68: 0.000379 | F68: 0.00033 | G68: 0.000235 | H68: =(H67*H33) | I68: =(I67*I33) | J68: =(J67*J33) | K68: =(K67*K33) | L68: =(L67*L33) | M68: =(M67*M33) | N68: =(N67*N33) | O68: =(O67*O33) | ... Q68: =(Q67*Q33)
A69: Net profit to parent | B69: np_parent | D69: 239.8956 | E69: 162.26908 | F69: 131.55135 | G69: 83.98 | H69: =(H67-H68) | I69: =(I67-I68) | J69: =(J67-J68) | K69: =(K67-K68) | L69: =(L67-L68) | M69: =(M67-M68) | N69: =(N67-N68) | O69: =(O67-O68) | ... Q69: =(Q67-Q68)
A70: Shares outstanding (m) | B70: shares | D70: 2616.5 | E70: 2616.5 | F70: 2616.5 | G70: 2616.5 | H70: =(G70*(1+H35)) | I70: =(H70*(1+I35)) | J70: =(I70*(1+J35)) | K70: =(J70*(1+K35)) | L70: =(K70*(1+L35)) | M70: =(L70*(1+M35)) | N70: =(M70*(1+N35)) | O70: =(N70*(1+O35)) | ... Q70: =(P70*(1+Q35))
A71: EPS | B71: eps | D71: 0.091685689 | E71: 0.062017611 | F71: 0.050277603 | G71: 0.032096312 | H71: =(IF(H70=0,0,H69/H70)*$C$8) | I71: =(IF(I70=0,0,I69/I70)*$C$8) | J71: =(IF(J70=0,0,J69/J70)*$C$8) | K71: =(IF(K70=0,0,K69/K70)*$C$8) | L71: =(IF(L70=0,0,L69/L70)*$C$8) | M71: =(IF(M70=0,0,M69/M70)*$C$8) | N71: =(IF(N70=0,0,N69/N70)*$C$8) | O71: =(IF(O70=0,0,O69/O70)*$C$8) | ... Q71: =(IF(Q70=0,0,Q69/Q70)*$C$8)
A72: DPS (declared on the year) | B72: dps | D72: 0.045258467 | E72: 0.039958712 | F72: 0.030496841 | G72: 0.047773 | H72: =(MAX(H71,0)*H34) | I72: =(MAX(I71,0)*I34) | J72: =(MAX(J71,0)*J34) | K72: =(MAX(K71,0)*K34) | L72: =(MAX(L71,0)*L34) | M72: =(MAX(M71,0)*M34) | N72: =(MAX(N71,0)*N34) | O72: =(MAX(O71,0)*O34) | ... Q72: =(MAX(Q71,0)*Q34)
A73: Dividends paid | B73: dividends_paid | D73: 336 | E73: 120 | F73: 105 | G73: 80 | H73: =IF($C$8=0,0,(G72*G70)/$C$8) | I73: =IF($C$8=0,0,(H72*H70)/$C$8) | J73: =IF($C$8=0,0,(I72*I70)/$C$8) | K73: =IF($C$8=0,0,(J72*J70)/$C$8) | L73: =IF($C$8=0,0,(K72*K70)/$C$8) | M73: =IF($C$8=0,0,(L72*L70)/$C$8) | N73: =IF($C$8=0,0,(M72*M70)/$C$8) | O73: =IF($C$8=0,0,(N72*N70)/$C$8) | ... Q73: =IF($C$8=0,0,(P72*P70)/$C$8)
A74: Capital expenditure | B74: capex | D74: 48.337064 | E74: 34.777342 | F74: 35.526853 | G74: 33.889158 | H74: =(((H41*H25)*$C$10)+H26) | I74: =(((I41*I25)*$C$10)+I26) | J74: =(((J41*J25)*$C$10)+J26) | K74: =(((K41*K25)*$C$10)+K26) | L74: =(((L41*L25)*$C$10)+L26) | M74: =(((M41*M25)*$C$10)+M26) | N74: =(((N41*N25)*$C$10)+N26) | O74: =(((O41*O25)*$C$10)+O26) | ... Q74: =(((Q41*Q25)*$C$10)+Q26)
A75: Change in working capital | B75: delta_nwc | E75: 58.131892 | F75: 33.089287 | G75: 22.909263 | H75: =(H80-G80) | I75: =(I80-H80) | J75: =(J80-I80) | K75: =(K80-J80) | L75: =(L80-K80) | M75: =(M80-L80) | N75: =(N80-M80) | O75: =(O80-N80) | ... Q75: =(Q80-P80)
A76: Free cash flow to firm | B76: fcff | F76: 61.616579 | G76: 25.39616 | H76: =((((H59*(1-H28))+H60)-H74)-H75) | I76: =((((I59*(1-I28))+I60)-I74)-I75) | J76: =((((J59*(1-J28))+J60)-J74)-J75) | K76: =((((K59*(1-K28))+K60)-K74)-K75) | L76: =((((L59*(1-L28))+L60)-L74)-L75) | M76: =((((M59*(1-M28))+M60)-M74)-M75) | N76: =((((N59*(1-N28))+N60)-N74)-N75) | O76: =((((O59*(1-O28))+O60)-O74)-O75) | ... Q76: =((((Q59*(1-Q28))+Q60)-Q74)-Q75)
A77: Net borrowing | B77: net_borrowing | E77: -2.728702 | F77: -2.70326 | G77: -1.549148 | H77: =H31 | I77: =I31 | J77: =J31 | K77: =K31 | L77: =L31 | M77: =M31 | N77: =N31 | O77: =O31 | ... Q77: =Q31
A78: Dividends to minorities | B78: minority_div | H78: =(MAX(G68,0)*H34) | I78: =(MAX(H68,0)*I34) | J78: =(MAX(I68,0)*J34) | K78: =(MAX(J68,0)*K34) | L78: =(MAX(K68,0)*L34) | M78: =(MAX(L68,0)*M34) | N78: =(MAX(M68,0)*N34) | O78: =(MAX(N68,0)*O34) | ... Q78: =(MAX(P68,0)*Q34)
A79: Free cash flow to equity | B79: fcfe | H79: =(((((H67+H60)-H74)-H75)+H77)-H78) | I79: =(((((I67+I60)-I74)-I75)+I77)-I78) | J79: =(((((J67+J60)-J74)-J75)+J77)-J78) | K79: =(((((K67+K60)-K74)-K75)+K77)-K78) | L79: =(((((L67+L60)-L74)-L75)+L77)-L78) | M79: =(((((M67+M60)-M74)-M75)+M77)-M78) | N79: =(((((N67+N60)-N74)-N75)+N77)-N78) | O79: =(((((O67+O60)-O74)-O75)+O77)-O78) | ... Q79: =(((((Q67+Q60)-Q74)-Q75)+Q77)-Q78)
A80: Operating working capital | B80: nwc | D80: -42.761353 | E80: 15.370539 | F80: 48.459826 | G80: 71.369089 | H80: =(H55*H27) | I80: =(I55*I27) | J80: =(J55*J27) | K80: =(K55*K27) | L80: =(L55*L27) | M80: =(M55*M27) | N80: =(N55*N27) | O80: =(O55*O27) | ... Q80: =(Q55*Q27)
A81: Cash & equivalents | B81: cash | D81: 87.540447 | E81: 45.591329 | F81: 35.886262 | G81: 44.249952 | H81: =(((((((G81+H67)+H60)-H74)-H75)+H77)-H73)-H78) | I81: =(((((((H81+I67)+I60)-I74)-I75)+I77)-I73)-I78) | J81: =(((((((I81+J67)+J60)-J74)-J75)+J77)-J73)-J78) | K81: =(((((((J81+K67)+K60)-K74)-K75)+K77)-K73)-K78) | L81: =(((((((K81+L67)+L60)-L74)-L75)+L77)-L73)-L78) | M81: =(((((((L81+M67)+M60)-M74)-M75)+M77)-M73)-M78) | N81: =(((((((M81+N67)+N60)-N74)-N75)+N77)-N73)-N78) | O81: =(((((((N81+O67)+O60)-O74)-O75)+O77)-O73)-O78) | ... Q81: =(((((((P81+Q67)+Q60)-Q74)-Q75)+Q77)-Q73)-Q78)
A82: Total debt | B82: debt | D82: 8.269431 | E82: 5.540729 | F82: 2.837469 | G82: 1.288321 | H82: =(G82+H77) | I82: =(H82+I77) | J82: =(I82+J77) | K82: =(J82+K77) | L82: =(K82+L77) | M82: =(L82+M77) | N82: =(M82+N77) | O82: =(N82+O77) | ... Q82: =(P82+Q77)
A83: Fixed assets (net) | B83: ppe | D83: 156.73431 | E83: 152.33724 | F83: 143.94657 | G83: 117.03028 | H83: =((G83+H74)-H60) | I83: =((H83+I74)-I60) | J83: =((I83+J74)-J60) | K83: =((J83+K74)-K60) | L83: =((K83+L74)-L60) | M83: =((L83+M74)-M60) | N83: =((M83+N74)-N60) | O83: =((N83+O74)-O60) | ... Q83: =((P83+Q74)-Q60)
A84: Parent shareholders' equity | B84: equity | D84: 220.47668 | E84: 242.48229 | F84: 264.06816 | G84: 273.02463 | H84: =((G84+H69)-H73) | I84: =((H84+I69)-I73) | J84: =((I84+J69)-J73) | K84: =((J84+K69)-K73) | L84: =((K84+L69)-L73) | M84: =((L84+M69)-M73) | N84: =((M84+N69)-N73) | O84: =((N84+O69)-O73) | ... Q84: =((P84+Q69)-Q73)
A85: Minority interest (balance sheet) | B85: minority_bs | D85: 0.001092 | E85: 0.001173 | F85: 0.00142 | G85: 0.001448 | H85: =((G85+H68)-H78) | I85: =((H85+I68)-I78) | J85: =((I85+J68)-J78) | K85: =((J85+K68)-K78) | L85: =((K85+L68)-L78) | M85: =((L85+M68)-M78) | N85: =((M85+N68)-N78) | O85: =((N85+O68)-O78) | ... Q85: =((P85+Q68)-Q78)
A86: Other assets less other liabilities | B86: other_net | D86: 27.233797 | E86: 34.72508 | F86: 38.614388 | G86: 41.665084 | H86: =G86 | I86: =H86 | J86: =I86 | K86: =J86 | L86: =K86 | M86: =L86 | N86: =M86 | O86: =N86 | ... Q86: =P86
A87: Balance check (should be zero) | B87: bs_check | H87: =((((((H81+H80)+H83)+H86)-H82)-H84)-H85) | I87: =((((((I81+I80)+I83)+I86)-I82)-I84)-I85) | J87: =((((((J81+J80)+J83)+J86)-J82)-J84)-J85) | K87: =((((((K81+K80)+K83)+K86)-K82)-K84)-K85) | L87: =((((((L81+L80)+L83)+L86)-L82)-L84)-L85) | M87: =((((((M81+M80)+M83)+M86)-M82)-M84)-M85) | N87: =((((((N81+N80)+N83)+N86)-N82)-N84)-N85) | O87: =((((((O81+O80)+O83)+O86)-O82)-O84)-O85) | ... Q87: =((((((Q81+Q80)+Q83)+Q86)-Q82)-Q84)-Q85)
A88: Net debt (cash) | B88: net_debt | D88: -79.271016 | E88: -40.0506 | F88: -33.048793 | G88: -42.961631 | H88: =(H82-H81) | I88: =(I82-I81) | J88: =(J82-J81) | K88: =(K82-K81) | L88: =(L82-L81) | M88: =(M82-M81) | N88: =(N82-N81) | O88: =(O82-O81) | ... Q88: =(Q82-Q81)
A89: Book value per share | B89: bvps | D89: 0.084263972 | E89: 0.092674293 | F89: 0.1009242 | G89: 0.10434727 | H89: =(IF(H70=0,0,H84/H70)*$C$8) | I89: =(IF(I70=0,0,I84/I70)*$C$8) | J89: =(IF(J70=0,0,J84/J70)*$C$8) | K89: =(IF(K70=0,0,K84/K70)*$C$8) | L89: =(IF(L70=0,0,L84/L70)*$C$8) | M89: =(IF(M70=0,0,M84/M70)*$C$8) | N89: =(IF(N70=0,0,N84/N70)*$C$8) | O89: =(IF(O70=0,0,O84/O70)*$C$8) | ... Q89: =(IF(Q70=0,0,Q84/Q70)*$C$8)
A90: Revenue growth | B90: revenue_growth | E90: 0.10235094 | F90: -0.16447247 | G90: -0.25744206 | H90: =(IF(G55=0,0,H55/G55)-1) | I90: =(IF(H55=0,0,I55/H55)-1) | J90: =(IF(I55=0,0,J55/I55)-1) | K90: =(IF(J55=0,0,K55/J55)-1) | L90: =(IF(K55=0,0,L55/K55)-1) | M90: =(IF(L55=0,0,M55/L55)-1) | N90: =(IF(M55=0,0,N55/M55)-1) | O90: =(IF(N55=0,0,O55/N55)-1) | ... Q90: =(IF(P55=0,0,Q55/P55)-1)
A91: Gross margin | B91: gross_margin | D91: 0.45023702 | E91: 0.3096799 | F91: 0.32619834 | G91: 0.29639353 | H91: =IF(H55=0,0,H57/H55) | I91: =IF(I55=0,0,I57/I55) | J91: =IF(J55=0,0,J57/J55) | K91: =IF(K55=0,0,K57/K55) | L91: =IF(L55=0,0,L57/L55) | M91: =IF(M55=0,0,M57/M55) | N91: =IF(N55=0,0,N57/N55) | O91: =IF(O55=0,0,O57/O55) | ... Q91: =IF(Q55=0,0,Q57/Q55)
A92: EBITDA margin | B92: ebitda_margin | F92: 0.17923648 | G92: 0.14558028 | H92: =IF(H55=0,0,H61/H55) | I92: =IF(I55=0,0,I61/I55) | J92: =IF(J55=0,0,J61/J55) | K92: =IF(K55=0,0,K61/K55) | L92: =IF(L55=0,0,L61/L55) | M92: =IF(M55=0,0,M61/M55) | N92: =IF(N55=0,0,N61/N55) | O92: =IF(O55=0,0,O61/O55) | ... Q92: =IF(Q55=0,0,Q61/Q55)
A93: EBIT margin | B93: ebit_margin | D93: 0.29699625 | E93: 0.19443646 | F93: 0.17911648 | G93: 0.1454029 | H93: =IF(H55=0,0,H59/H55) | I93: =IF(I55=0,0,I59/I55) | J93: =IF(J55=0,0,J59/J55) | K93: =IF(K55=0,0,K59/K55) | L93: =IF(L55=0,0,L59/L55) | M93: =IF(M55=0,0,M59/M55) | N93: =IF(N55=0,0,N59/N55) | O93: =IF(O55=0,0,O59/O55) | ... Q93: =IF(Q55=0,0,Q59/Q55)
A94: Net margin | B94: np_margin | D94: 0.2331311 | E94: 0.14305196 | F94: 0.138801 | G94: 0.11932812 | H94: =IF(H55=0,0,H69/H55) | I94: =IF(I55=0,0,I69/I55) | J94: =IF(J55=0,0,J69/J55) | K94: =IF(K55=0,0,K69/K55) | L94: =IF(L55=0,0,L69/L55) | M94: =IF(M55=0,0,M69/M55) | N94: =IF(N55=0,0,N69/N55) | O94: =IF(O55=0,0,O69/O55) | ... Q94: =IF(Q55=0,0,Q69/Q55)
A95: EPS growth | B95: eps_growth | E95: -0.3235846 | F95: -0.1893012 | G95: -0.3616181 | H95: =(IF(G71=0,0,H71/G71)-1) | I95: =(IF(H71=0,0,I71/H71)-1) | J95: =(IF(I71=0,0,J71/I71)-1) | K95: =(IF(J71=0,0,K71/J71)-1) | L95: =(IF(K71=0,0,L71/K71)-1) | M95: =(IF(L71=0,0,M71/L71)-1) | N95: =(IF(M71=0,0,N71/M71)-1) | O95: =(IF(N71=0,0,O71/N71)-1) | ... Q95: =(IF(P71=0,0,Q71/P71)-1)
A96: ROE | B96: roe | E96: 0.70100847 | F96: 0.51940078 | G96: 0.31272064 | H96: =IF(IF(2=0,0,(H84+G84)/2)=0,0,H69/IF(2=0,0,(H84+G84)/2)) | I96: =IF(IF(2=0,0,(I84+H84)/2)=0,0,I69/IF(2=0,0,(I84+H84)/2)) | J96: =IF(IF(2=0,0,(J84+I84)/2)=0,0,J69/IF(2=0,0,(J84+I84)/2)) | K96: =IF(IF(2=0,0,(K84+J84)/2)=0,0,K69/IF(2=0,0,(K84+J84)/2)) | L96: =IF(IF(2=0,0,(L84+K84)/2)=0,0,L69/IF(2=0,0,(L84+K84)/2)) | M96: =IF(IF(2=0,0,(M84+L84)/2)=0,0,M69/IF(2=0,0,(M84+L84)/2)) | N96: =IF(IF(2=0,0,(N84+M84)/2)=0,0,N69/IF(2=0,0,(N84+M84)/2)) | O96: =IF(IF(2=0,0,(O84+N84)/2)=0,0,O69/IF(2=0,0,(O84+N84)/2)) | ... Q96: =IF(IF(2=0,0,(Q84+P84)/2)=0,0,Q69/IF(2=0,0,(Q84+P84)/2))
A97: Net debt / EBITDA | B97: net_debt_ebitda | F97: -0.19454787 | G97: -0.41931959 | H97: =IF(H61=0,0,H88/H61) | I97: =IF(I61=0,0,I88/I61) | J97: =IF(J61=0,0,J88/J61) | K97: =IF(K61=0,0,K88/K61) | L97: =IF(L61=0,0,L88/L61) | M97: =IF(M61=0,0,M88/M61) | N97: =IF(N61=0,0,N88/N61) | O97: =IF(O61=0,0,O88/O61) | ... Q97: =IF(Q61=0,0,Q88/Q61)
A98: Payout ratio | B98: payout_ratio | D98: 0.4936263 | E98: 0.64431233 | F98: 0.60656912 | G98: 1.4884265 | H98: =IF(H71=0,0,H72/H71) | I98: =IF(I71=0,0,I72/I71) | J98: =IF(J71=0,0,J72/J71) | K98: =IF(K71=0,0,K72/K71) | L98: =IF(L71=0,0,L72/L71) | M98: =IF(M71=0,0,M72/M71) | N98: =IF(N71=0,0,N72/N71) | O98: =IF(O71=0,0,O72/O71) | ... Q98: =IF(Q71=0,0,Q72/Q71)
A99: Capex / revenue | B99: capex_revenue | D99: 0.046974071 | E99: 0.03065875 | F99: 0.037484699 | G99: 0.048153485 | H99: =IF(H55=0,0,H74/H55) | I99: =IF(I55=0,0,I74/I55) | J99: =IF(J55=0,0,J74/J55) | K99: =IF(K55=0,0,K74/K55) | L99: =IF(L55=0,0,L74/L55) | M99: =IF(M55=0,0,M74/M55) | N99: =IF(N55=0,0,N74/N55) | O99: =IF(O55=0,0,O74/O55) | ... Q99: =IF(Q55=0,0,Q74/Q55)
A101: VALUATION
A102: Last price (IDR) | C102: 5225
A103: Shares outstanding (m) | C103: 2616.5
A104: IDR per USD (spot) | C104: 18138
A105: Debt at balance-sheet date | C105: 0
...

Sheet BUMI
A1: PT Bumi Resources Tbk (BUMI.JK) — Coal producers
A2: Units: USD m; per-share in USD unless marked IDR. Model asof 2026-10-30 · data 2026-10-27
A4: Line | C4: Scalar | D4: FY2022A | E4: FY2023A | F4: FY2024A | G4: FY2025A | H4: FY2026E | I4: FY2027E | J4: FY2028E | K4: FY2029E | L4: FY2030E | M4: FY2031E | N4: FY2032E | O4: FY2033E | P4: FY2034E | Q4: FY2035E | R4: FY2036E | S4: FY2037E | T4: FY2038E | U4: FY2039E | V4: FY2040E | W4: FY2041E | X4: FY2042E | Y4: FY2043E | Z4: FY2044E | AA4: FY2045E | AB4: FY2046E | AC4: FY2047E | AD4: FY2048E | AE4: FY2049E | AF4: FY2050E | AG4: FY2051E | AH4: FY2052E | AI4: FY2053E | AJ4: FY2054E | AK4: FY2055E | AL4: FY2056E | AM4: FY2057E | AN4: FY2058E
A6: PARAMETERS
A7: horizon | C7: 33
A8: ps_factor | C8: 1
A9: reserves | C9: 2500
A10: unit_factor | C10: 1
A11: vp_factor | C11: 1
A13: INPUTS (company assumptions)
A14: Sales volume plan | B14: a.volume | H14: 77 | I14: 77 | J14: 77 | K14: 77 | L14: 77 | M14: 77 | N14: 77 | O14: 77 | P14: 77 | Q14: 77 | R14: 77 | S14: 77 | T14: 77 | U14: 77 | V14: 77 | W14: 77 | X14: 77 | Y14: 77 | Z14: 77 | AA14: 77 | AB14: 77 | AC14: 77 | AD14: 77 | AE14: 77 | AF14: 77 | AG14: 77 | AH14: 77 | AI14: 77 | AJ14: 77 | AK14: 77 | AL14: 77 | AM14: 77 | AN14: 77
A15: Realised price / benchmark | B15: a.realisation | H15: 0.5946 | I15: 0.5946 | J15: 0.5946 | K15: 0.5946 | L15: 0.5946 | M15: 0.5946 | N15: 0.5946 | O15: 0.5946 | P15: 0.5946 | Q15: 0.5946 | R15: 0.5946 | S15: 0.5946 | T15: 0.5946 | U15: 0.5946 | V15: 0.5946 | W15: 0.5946 | X15: 0.5946 | Y15: 0.5946 | Z15: 0.5946 | AA15: 0.5946 | AB15: 0.5946 | AC15: 0.5946 | AD15: 0.5946 | AE15: 0.5946 | AF15: 0.5946 | AG15: 0.5946 | AH15: 0.5946 | AI15: 0.5946 | AJ15: 0.5946 | AK15: 0.5946 | AL15: 0.5946 | AM15: 0.5946 | AN15: 0.5946
A16: Share of volume under a price cap (e.g. DMO) | B16: a.capped_share | H16: 0.3 | I16: 0.3 | J16: 0.3 | K16: 0.3 | L16: 0.3 | M16: 0.3 | N16: 0.3 | O16: 0.3 | P16: 0.3 | Q16: 0.3 | R16: 0.3 | S16: 0.3 | T16: 0.3 | U16: 0.3 | V16: 0.3 | W16: 0.3 | X16: 0.3 | Y16: 0.3 | Z16: 0.3 | AA16: 0.3 | AB16: 0.3 | AC16: 0.3 | AD16: 0.3 | AE16: 0.3 | AF16: 0.3 | AG16: 0.3 | AH16: 0.3 | AI16: 0.3 | AJ16: 0.3 | AK16: 0.3 | AL16: 0.3 | AM16: 0.3 | AN16: 0.3
A17: Strip ratio (bcm per tonne) or cost-intensity factor | B17: a.strip_ratio | H17: 8 | I17: 8 | J17: 8 | K17: 8 | L17: 8 | M17: 8 | N17: 8 | O17: 8 | P17: 8 | Q17: 8 | R17: 8 | S17: 8 | T17: 8 | U17: 8 | V17: 8 | W17: 8 | X17: 8 | Y17: 8 | Z17: 8 | AA17: 8 | AB17: 8 | AC17: 8 | AD17: 8 | AE17: 8 | AF17: 8 | AG17: 8 | AH17: 8 | AI17: 8 | AJ17: 8 | AK17: 8 | AL17: 8 | AM17: 8 | AN17: 8
A18: Mining cost per bcm (or per unit when intensity is 1) | B18: a.cost_per_bcm | H18: 2.6 | I18: 2.6 | J18: 2.6 | K18: 2.6 | L18: 2.6 | M18: 2.652 | N18: 2.70504 | O18: 2.7591408 | P18: 2.8143236 | Q18: 2.8706101 | R18: 2.9280223 | S18: 2.9865827 | T18: 3.0463144 | U18: 3.1072407 | V18: 3.1693855 | W18: 3.2327732 | X18: 3.2974287 | Y18: 3.3633772 | Z18: 3.4306448 | AA18: 3.4992577 | AB18: 3.5692428 | AC18: 3.6406277 | AD18: 3.7134402 | AE18: 3.787709 | AF18: 3.8634632 | AG18: 3.9407325 | AH18: 4.0195471 | AI18: 4.0999381 | AJ18: 4.1819368 | AK18: 4.2655756 | AL18: 4.3508871 | AM18: 4.4379048 | AN18: 4.5266629
A19: Fuel share of mining cost | B19: a.fuel_share | C19: 0.3
A20: Other cash cost per unit (haul, barge, process) | B20: a.other_cost_unit | H20: 22.5 | I20: 22.5 | J20: 22.5 | K20: 22.5 | L20: 22.5 | M20: 22.95 | N20: 23.409 | O20: 23.87718 | P20: 24.354724 | Q20: 24.841818 | R20: 25.338654 | S20: 25.845428 | T20: 26.362336 | U20: 26.889583 | V20: 27.427374 | W20: 27.975922 | X20: 28.53544 | Y20: 29.106149 | Z20: 29.688272 | AA20: 30.282038 | AB20: 30.887678 | AC20: 31.505432 | AD20: 32.135541 | AE20: 32.778251 | AF20: 33.433816 | AG20: 34.102493 | AH20: 34.784543 | AI20: 35.480233 | AJ20: 36.189838 | AK20: 36.913635 | AL20: 37.651908 | AM20: 38.404946 | AN20: 39.173045
A21: Royalty rate (flat regimes) | B21: a.royalty_rate | H21: 0.18 | I21: 0.18 | J21: 0.18 | K21: 0.18 | L21: 0.18 | M21: 0.18 | N21: 0.18 | O21: 0.18 | P21: 0.18 | Q21: 0.18 | R21: 0.18 | S21: 0.18 | T21: 0.18 | U21: 0.18 | V21: 0.18 | W21: 0.18 | X21: 0.18 | Y21: 0.18 | Z21: 0.18 | AA21: 0.18 | AB21: 0.18 | AC21: 0.18 | AD21: 0.18 | AE21: 0.18 | AF21: 0.18 | AG21: 0.18 | AH21: 0.18 | AI21: 0.18 | AJ21: 0.18 | AK21: 0.18 | AL21: 0.18 | AM21: 0.18 | AN21: 0.18
A22: Other revenue | B22: a.other_revenue | H22: 0 | I22: 0 | J22: 0 | K22: 0 | L22: 0 | M22: 0 | N22: 0 | O22: 0 | P22: 0 | Q22: 0 | R22: 0 | S22: 0 | T22: 0 | U22: 0 | V22: 0 | W22: 0 | X22: 0 | Y22: 0 | Z22: 0 | AA22: 0 | AB22: 0 | AC22: 0 | AD22: 0 | AE22: 0 | AF22: 0 | AG22: 0 | AH22: 0 | AI22: 0 | AJ22: 0 | AK22: 0 | AL22: 0 | AM22: 0 | AN22: 0
A23: Gross margin on other revenue | B23: a.other_margin | C23: 0.1
A24: D&A per unit (reporting currency) | B24: a.da_unit | H24: 2.24 | I24: 2.24 | J24: 2.24 | K24: 2.24 | L24: 2.24 | M24: 2.2848 | N24: 2.330496 | O24: 2.3771059 | P24: 2.424648 | Q24: 2.473141 | R24: 2.5226038 | S24: 2.5730559 | T24: 2.624517 | U24: 2.6770074 | V24: 2.7305475 | W24: 2.7851585 | X24: 2.8408616 | Y24: 2.8976789 | Z24: 2.9556324 | AA24: 3.0147451 | AB24: 3.07504 | AC24: 3.1365408 | AD24: 3.1992716 | AE24: 3.263257 | AF24: 3.3285222 | AG24: 3.3950926 | AH24: 3.4629945 | AI24: 3.5322544 | AJ24: 3.6028994 | AK24: 3.6749574 | AL24: 3.7484566 | AM24: 3.8234257 | AN24: 3.8998942
A25: Sustaining capex per unit (reporting currency) | B25: a.capex_unit | H25: 2 | I25: 2 | J25: 2 | K25: 2 | L25: 2 | M25: 2.04 | N25: 2.0808 | O25: 2.122416 | P25: 2.1648643 | Q25: 2.2081616 | R25: 2.2523248 | S25: 2.2973713 | T25: 2.3433188 | U25: 2.3901851 | V25: 2.4379888 | W25: 2.4867486 | X25: 2.5364836 | Y25: 2.5872133 | Z25: 2.6389575 | AA25: 2.6917367 | AB25: 2.7455714 | AC25: 2.8004828 | AD25: 2.8564925 | AE25: 2.9136223 | AF25: 2.9718948 | AG25: 3.0313327 | AH25: 3.0919593 | AI25: 3.1537985 | AJ25: 3.2168745 | AK25: 3.281212 | AL25: 3.3468362 | AM25: 3.413773 | AN25: 3.4820484
A26: Other capex (expansion projects) | B26: a.capex_other | H26: 0 | I26: 0 | J26: 0 | K26: 0 | L26: 0 | M26: 0 | N26: 0 | O26: 0 | P26: 0 | Q26: 0 | R26: 0 | S26: 0 | T26: 0 | U26: 0 | V26: 0 | W26: 0 | X26: 0 | Y26: 0 | Z26: 0 | AA26: 0 | AB26: 0 | AC26: 0 | AD26: 0 | AE26: 0 | AF26: 0 | AG26: 0 | AH26: 0 | AI26: 0 | AJ26: 0 | AK26: 0 | AL26: 0 | AM26: 0 | AN26: 0
A27: Operating working capital / revenue | B27: a.nwc_pct | H27: 0.0168 | I27: 0.0168 | J27: 0.0168 | K27: 0.0168 | L27: 0.0168 | M27: 0.0168 | N27: 0.0168 | O27: 0.0168 | P27: 0.0168 | Q27: 0.0168 | R27: 0.0168 | S27: 0.0168 | T27: 0.0168 | U27: 0.0168 | V27: 0.0168 | W27: 0.0168 | X27: 0.0168 | Y27: 0.0168 | Z27: 0.0168 | AA27: 0.0168 | AB27: 0.0168 | AC27: 0.0168 | AD27: 0.0168 | AE27: 0.0168 | AF27: 0.0168 | AG27: 0.0168 | AH27: 0.0168 | AI27: 0.0168 | AJ27: 0.0168 | AK27: 0.0168 | AL27: 0.0168 | AM27: 0.0168 | AN27: 0.0168
A28: Effective tax rate | B28: a.tax_rate | H28: 0.435 | I28: 0.435 | J28: 0.435 | K28: 0.435 | L28: 0.435 | M28: 0.435 | N28: 0.435 | O28: 0.435 | P28: 0.435 | Q28: 0.435 | R28: 0.435 | S28: 0.435 | T28: 0.435 | U28: 0.435 | V28: 0.435 | W28: 0.435 | X28: 0.435 | Y28: 0.435 | Z28: 0.435 | AA28: 0.435 | AB28: 0.435 | AC28: 0.435 | AD28: 0.435 | AE28: 0.435 | AF28: 0.435 | AG28: 0.435 | AH28: 0.435 | AI28: 0.435 | AJ28: 0.435 | AK28: 0.435 | AL28: 0.435 | AM28: 0.435 | AN28: 0.435
A29: Cost of debt (on opening debt) | B29: a.cost_of_debt | C29: 0.082003
A30: Yield on opening cash | B30: a.cash_yield | C30: 0.067159
A31: Net new borrowing | B31: a.net_borrowing | H31: 298.1 | I31: 0 | J31: 0 | K31: 0 | L31: 0 | M31: 0 | N31: 0 | O31: 0 | P31: 0 | Q31: 0 | R31: 0 | S31: 0 | T31: 0 | U31: 0 | V31: 0 | W31: 0 | X31: 0 | Y31: 0 | Z31: 0 | AA31: 0 | AB31: 0 | AC31: 0 | AD31: 0 | AE31: 0 | AF31: 0 | AG31: 0 | AH31: 0 | AI31: 0 | AJ31: 0 | AK31: 0 | AL31: 0 | AM31: 0 | AN31: 0
A32: Other non-operating items | B32: a.other_nonop | H32: 0 | I32: 0 | J32: 0 | K32: 0 | L32: 0 | M32: 0 | N32: 0 | O32: 0 | P32: 0 | Q32: 0 | R32: 0 | S32: 0 | T32: 0 | U32: 0 | V32: 0 | W32: 0 | X32: 0 | Y32: 0 | Z32: 0 | AA32: 0 | AB32: 0 | AC32: 0 | AD32: 0 | AE32: 0 | AF32: 0 | AG32: 0 | AH32: 0 | AI32: 0 | AJ32: 0 | AK32: 0 | AL32: 0 | AM32: 0 | AN32: 0
A33: Minorities' share of net profit | B33: a.minority_pct | H33: 0.5 | I33: 0.5 | J33: 0.5 | K33: 0.5 | L33: 0.5 | M33: 0.5 | N33: 0.5 | O33: 0.5 | P33: 0.5 | Q33: 0.5 | R33: 0.5 | S33: 0.5 | T33: 0.5 | U33: 0.5 | V33: 0.5 | W33: 0.5 | X33: 0.5 | Y33: 0.5 | Z33: 0.5 | AA33: 0.5 | AB33: 0.5 | AC33: 0.5 | AD33: 0.5 | AE33: 0.5 | AF33: 0.5 | AG33: 0.5 | AH33: 0.5 | AI33: 0.5 | AJ33: 0.5 | AK33: 0.5 | AL33: 0.5 | AM33: 0.5 | AN33: 0.5
A34: Dividend payout | B34: a.payout | H34: 0 | I34: 0 | J34: 0 | K34: 0 | L34: 0 | M34: 0 | N34: 0 | O34: 0 | P34: 0 | Q34: 0 | R34: 0 | S34: 0 | T34: 0 | U34: 0 | V34: 0 | W34: 0 | X34: 0 | Y34: 0 | Z34: 0 | AA34: 0 | AB34: 0 | AC34: 0 | AD34: 0 | AE34: 0 | AF34: 0 | AG34: 0 | AH34: 0 | AI34: 0 | AJ34: 0 | AK34: 0 | AL34: 0 | AM34: 0 | AN34: 0
A35: Change in share count | B35: a.share_change | H35: 0 | I35: 0 | J35: 0 | K35: 0 | L35: 0 | M35: 0 | N35: 0 | O35: 0 | P35: 0 | Q35: 0 | R35: 0 | S35: 0 | T35: 0 | U35: 0 | V35: 0 | W35: 0 | X35: 0 | Y35: 0 | Z35: 0 | AA35: 0 | AB35: 0 | AC35: 0 | AD35: 0 | AE35: 0 | AF35: 0 | AG35: 0 | AH35: 0 | AI35: 0 | AJ35: 0 | AK35: 0 | AL35: 0 | AM35: 0 | AN35: 0
A36: Terminal growth (DCF) | B36: a.terminal_growth | C36: 0
A37: SG&A / revenue | B37: a.opex_pct | H37: 0.048 | I37: 0.048 | J37: 0.048 | K37: 0.048 | L37: 0.048 | M37: 0.048 | N37: 0.048 | O37: 0.048 | P37: 0.048 | Q37: 0.048 | R37: 0.048 | S37: 0.048 | T37: 0.048 | U37: 0.048 | V37: 0.048 | W37: 0.048 | X37: 0.048 | Y37: 0.048 | Z37: 0.048 | AA37: 0.048 | AB37: 0.048 | AC37: 0.048 | AD37: 0.048 | AE37: 0.048 | AF37: 0.048 | AG37: 0.048 | AH37: 0.048 | AI37: 0.048 | AJ37: 0.048 | AK37: 0.048 | AL37: 0.048 | AM37: 0.048 | AN37: 0.048
A39: MODEL
A40: Reserves remaining (close) | B40: reserves | G40: 2500 | H40: =MAX((G40-H41),0) | I40: =MAX((H40-I41),0) | J40: =MAX((I40-J41),0) | K40: =MAX((J40-K41),0) | L40: =MAX((K40-L41),0) | M40: =MAX((L40-M41),0) | N40: =MAX((M40-N41),0) | O40: =MAX((N40-O41),0) | ... AN40: =MAX((AM40-AN41),0)
A41: Sales volume | B41: volume | G41: 74.6 | H41: =IF(($C$9>0),MIN(H14,MAX(G40,0)),H14) | I41: =IF(($C$9>0),MIN(I14,MAX(H40,0)),I14) | J41: =IF(($C$9>0),MIN(J14,MAX(I40,0)),J14) | K41: =IF(($C$9>0),MIN(K14,MAX(J40,0)),K14) | L41: =IF(($C$9>0),MIN(L14,MAX(K40,0)),L14) | M41: =IF(($C$9>0),MIN(M14,MAX(L40,0)),M14) | N41: =IF(($C$9>0),MIN(N14,MAX(M40,0)),N14) | O41: =IF(($C$9>0),MIN(O14,MAX(N40,0)),O14) | ... AN41: =IF(($C$9>0),MIN(AN14,MAX(AM40,0)),AN14)
A42: Benchmark price | B42: benchmark | H42: =Drivers!$L$6 | I42: =Drivers!$M$6 | J42: =Drivers!$N$6 | K42: =Drivers!$O$6 | L42: =Drivers!$P$6 | M42: =Drivers!$Q$6 | N42: =Drivers!$R$6 | O42: =Drivers!$S$6 | P42: =Drivers!$T$6 | Q42: =Drivers!$U$6 | R42: =Drivers!$V$6 | S42: =Drivers!$W$6 | T42: =Drivers!$X$6 | U42: =Drivers!$Y$6 | V42: =Drivers!$Z$6 | W42: =Drivers!$AA$6 | X42: =Drivers!$AB$6 | Y42: =Drivers!$AC$6 | Z42: =Drivers!$AD$6 | AA42: =Drivers!$AE$6 | AB42: =Drivers!$AF$6 | AC42: =Drivers!$AG$6 | AD42: =Drivers!$AH$6 | AE42: =Drivers!$AI$6 | AF42: =Drivers!$AJ$6 | AG42: =Drivers!$AK$6 | AH42: =Drivers!$AL$6 | AI42: =Drivers!$AM$6 | AJ42: =Drivers!$AN$6 | AK42: =Drivers!$AO$6 | AL42: =Drivers!$AP$6 | AM42: =Drivers!$AQ$6 | AN42: =Drivers!$AR$6
A43: Average selling price | B43: asp | G43: 59.7 | H43: =(((H15*H42)*(1-H16))+(MIN(Drivers!$L$4,(H15*H42))*H16)) | I43: =(((I15*I42)*(1-I16))+(MIN(Drivers!$M$4,(I15*I42))*I16)) | J43: =(((J15*J42)*(1-J16))+(MIN(Drivers!$N$4,(J15*J42))*J16)) | K43: =(((K15*K42)*(1-K16))+(MIN(Drivers!$O$4,(K15*K42))*K16)) | L43: =(((L15*L42)*(1-L16))+(MIN(Drivers!$P$4,(L15*L42))*L16)) | M43: =(((M15*M42)*(1-M16))+(MIN(Drivers!$Q$4,(M15*M42))*M16)) | N43: =(((N15*N42)*(1-N16))+(MIN(Drivers!$R$4,(N15*N42))*N16)) | O43: =(((O15*O42)*(1-O16))+(MIN(Drivers!$S$4,(O15*O42))*O16)) | P43: =(((P15*P42)*(1-P16))+(MIN(Drivers!$T$4,(P15*P42))*P16)) | Q43: =(((Q15*Q42)*(1-Q16))+(MIN(Drivers!$U$4,(Q15*Q42))*Q16)) | R43: =(((R15*R42)*(1-R16))+(MIN(Drivers!$V$4,(R15*R42))*R16)) | S43: =(((S15*S42)*(1-S16))+(MIN(Drivers!$W$4,(S15*S42))*S16)) | T43: =(((T15*T42)*(1-T16))+(MIN(Drivers!$X$4,(T15*T42))*T16)) | U43: =(((U15*U42)*(1-U16))+(MIN(Drivers!$Y$4,(U15*U42))*U16)) | V43: =(((V15*V42)*(1-V16))+(MIN(Drivers!$Z$4,(V15*V42))*V16)) | W43: =(((W15*W42)*(1-W16))+(MIN(Drivers!$AA$4,(W15*W42))*W16)) | X43: =(((X15*X42)*(1-X16))+(MIN(Drivers!$AB$4,(X15*X42))*X16)) | Y43: =(((Y15*Y42)*(1-Y16))+(MIN(Drivers!$AC$4,(Y15*Y42))*Y16)) | Z43: =(((Z15*Z42)*(1-Z16))+(MIN(Drivers!$AD$4,(Z15*Z42))*Z16)) | AA43: =(((AA15*AA42)*(1-AA16))+(MIN(Drivers!$AE$4,(AA15*AA42))*AA16)) | AB43: =(((AB15*AB42)*(1-AB16))+(MIN(Drivers!$AF$4,(AB15*AB42))*AB16)) | AC43: =(((AC15*AC42)*(1-AC16))+(MIN(Drivers!$AG$4,(AC15*AC42))*AC16)) | AD43: =(((AD15*AD42)*(1-AD16))+(MIN(Drivers!$AH$4,(AD15*AD42))*AD16)) | AE43: =(((AE15*AE42)*(1-AE16))+(MIN(Drivers!$AI$4,(AE15*AE42))*AE16)) | AF43: =(((AF15*AF42)*(1-AF16))+(MIN(Drivers!$AJ$4,(AF15*AF42))*AF16)) | AG43: =(((AG15*AG42)*(1-AG16))+(MIN(Drivers!$AK$4,(AG15*AG42))*AG16)) | AH43: =(((AH15*AH42)*(1-AH16))+(MIN(Drivers!$AL$4,(AH15*AH42))*AH16)) | AI43: =(((AI15*AI42)*(1-AI16))+(MIN(Drivers!$AM$4,(AI15*AI42))*AI16)) | AJ43: =(((AJ15*AJ42)*(1-AJ16))+(MIN(Drivers!$AN$4,(AJ15*AJ42))*AJ16)) | AK43: =(((AK15*AK42)*(1-AK16))+(MIN(Drivers!$AO$4,(AK15*AK42))*AK16)) | AL43: =(((AL15*AL42)*(1-AL16))+(MIN(Drivers!$AP$4,(AL15*AL42))*AL16)) | AM43: =(((AM15*AM42)*(1-AM16))+(MIN(Drivers!$AQ$4,(AM15*AM42))*AM16)) | AN43: =(((AN15*AN42)*(1-AN16))+(MIN(Drivers!$AR$4,(AN15*AN42))*AN16))
A44: Realisation vs benchmark | B44: realisation_line | H44: =IF(H42=0,0,H43/H42) | I44: =IF(I42=0,0,I43/I42) | J44: =IF(J42=0,0,J43/J42) | K44: =IF(K42=0,0,K43/K42) | L44: =IF(L42=0,0,L43/L42) | M44: =IF(M42=0,0,M43/M42) | N44: =IF(N42=0,0,N43/N42) | O44: =IF(O42=0,0,O43/O42) | ... AN44: =IF(AN42=0,0,AN43/AN42)
A45: Cash cost per unit (ex-royalty) | B45: unit_cost | H45: =(((H17*H18)*(1+($C$19*(IF(Drivers!$J$8=0,0,Drivers!$L$8/Drivers!$J$8)-1))))+H20) | I45: =(((I17*I18)*(1+($C$19*(IF(Drivers!$J$8=0,0,Drivers!$M$8/Drivers!$J$8)-1))))+I20) | J45: =(((J17*J18)*(1+($C$19*(IF(Drivers!$J$8=0,0,Drivers!$N$8/Drivers!$J$8)-1))))+J20) | K45: =(((K17*K18)*(1+($C$19*(IF(Drivers!$J$8=0,0,Drivers!$O$8/Drivers!$J$8)-1))))+K20) | L45: =(((L17*L18)*(1+($C$19*(IF(Drivers!$J$8=0,0,Drivers!$P$8/Drivers!$J$8)-1))))+L20) | M45: =(((M17*M18)*(1+($C$19*(IF(Drivers!$J$8=0,0,Drivers!$Q$8/Drivers!$J$8)-1))))+M20) | N45: =(((N17*N18)*(1+($C$19*(IF(Drivers!$J$8=0,0,Drivers!$R$8/Drivers!$J$8)-1))))+N20) | O45: =(((O17*O18)*(1+($C$19*(IF(Drivers!$J$8=0,0,Drivers!$S$8/Drivers!$J$8)-1))))+O20) | P45: =(((P17*P18)*(1+($C$19*(IF(Drivers!$J$8=0,0,Drivers!$T$8/Drivers!$J$8)-1))))+P20) | Q45: =(((Q17*Q18)*(1+($C$19*(IF(Drivers!$J$8=0,0,Drivers!$U$8/Drivers!$J$8)-1))))+Q20) | R45: =(((R17*R18)*(1+($C$19*(IF(Drivers!$J$8=0,0,Drivers!$V$8/Drivers!$J$8)-1))))+R20) | S45: =(((S17*S18)*(1+($C$19*(IF(Drivers!$J$8=0,0,Drivers!$W$8/Drivers!$J$8)-1))))+S20) | T45: =(((T17*T18)*(1+($C$19*(IF(Drivers!$J$8=0,0,Drivers!$X$8/Drivers!$J$8)-1))))+T20) | U45: =(((U17*U18)*(1+($C$19*(IF(Drivers!$J$8=0,0,Drivers!$Y$8/Drivers!$J$8)-1))))+U20) | V45: =(((V17*V18)*(1+($C$19*(IF(Drivers!$J$8=0,0,Drivers!$Z$8/Drivers!$J$8)-1))))+V20) | W45: =(((W17*W18)*(1+($C$19*(IF(Drivers!$J$8=0,0,Drivers!$AA$8/Drivers!$J$8)-1))))+W20) | X45: =(((X17*X18)*(1+($C$19*(IF(Drivers!$J$8=0,0,Drivers!$AB$8/Drivers!$J$8)-1))))+X20) | Y45: =(((Y17*Y18)*(1+($C$19*(IF(Drivers!$J$8=0,0,Drivers!$AC$8/Drivers!$J$8)-1))))+Y20) | Z45: =(((Z17*Z18)*(1+($C$19*(IF(Drivers!$J$8=0,0,Drivers!$AD$8/Drivers!$J$8)-1))))+Z20) | AA45: =(((AA17*AA18)*(1+($C$19*(IF(Drivers!$J$8=0,0,Drivers!$AE$8/Drivers!$J$8)-1))))+AA20) | AB45: =(((AB17*AB18)*(1+($C$19*(IF(Drivers!$J$8=0,0,Drivers!$AF$8/Drivers!$J$8)-1))))+AB20) | AC45: =(((AC17*AC18)*(1+($C$19*(IF(Drivers!$J$8=0,0,Drivers!$AG$8/Drivers!$J$8)-1))))+AC20) | AD45: =(((AD17*AD18)*(1+($C$19*(IF(Drivers!$J$8=0,0,Drivers!$AH$8/Drivers!$J$8)-1))))+AD20) | AE45: =(((AE17*AE18)*(1+($C$19*(IF(Drivers!$J$8=0,0,Drivers!$AI$8/Drivers!$J$8)-1))))+AE20) | AF45: =(((AF17*AF18)*(1+($C$19*(IF(Drivers!$J$8=0,0,Drivers!$AJ$8/Drivers!$J$8)-1))))+AF20) | AG45: =(((AG17*AG18)*(1+($C$19*(IF(Drivers!$J$8=0,0,Drivers!$AK$8/Drivers!$J$8)-1))))+AG20) | AH45: =(((AH17*AH18)*(1+($C$19*(IF(Drivers!$J$8=0,0,Drivers!$AL$8/Drivers!$J$8)-1))))+AH20) | AI45: =(((AI17*AI18)*(1+($C$19*(IF(Drivers!$J$8=0,0,Drivers!$AM$8/Drivers!$J$8)-1))))+AI20) | AJ45: =(((AJ17*AJ18)*(1+($C$19*(IF(Drivers!$J$8=0,0,Drivers!$AN$8/Drivers!$J$8)-1))))+AJ20) | AK45: =(((AK17*AK18)*(1+($C$19*(IF(Drivers!$J$8=0,0,Drivers!$AO$8/Drivers!$J$8)-1))))+AK20) | AL45: =(((AL17*AL18)*(1+($C$19*(IF(Drivers!$J$8=0,0,Drivers!$AP$8/Drivers!$J$8)-1))))+AL20) | AM45: =(((AM17*AM18)*(1+($C$19*(IF(Drivers!$J$8=0,0,Drivers!$AQ$8/Drivers!$J$8)-1))))+AM20) | AN45: =(((AN17*AN18)*(1+($C$19*(IF(Drivers!$J$8=0,0,Drivers!$AR$8/Drivers!$J$8)-1))))+AN20)
A46: Strip ratio | B46: strip_ratio_line | G46: 8 | H46: =H17 | I46: =I17 | J46: =J17 | K46: =K17 | L46: =L17 | M46: =M17 | N46: =N17 | O46: =O17 | ... AN46: =AN17
A47: Royalty rate | B47: royalty_rate | H47: =VLOOKUP(Drivers!$L$5,Drivers!$B$25:$C$30,2,TRUE) | I47: =VLOOKUP(Drivers!$M$5,Drivers!$B$25:$C$30,2,TRUE) | J47: =VLOOKUP(Drivers!$N$5,Drivers!$B$25:$C$30,2,TRUE) | K47: =VLOOKUP(Drivers!$O$5,Drivers!$B$25:$C$30,2,TRUE) | L47: =VLOOKUP(Drivers!$P$5,Drivers!$B$25:$C$30,2,TRUE) | M47: =VLOOKUP(Drivers!$Q$5,Drivers!$B$25:$C$30,2,TRUE) | N47: =VLOOKUP(Drivers!$R$5,Drivers!$B$25:$C$30,2,TRUE) | O47: =VLOOKUP(Drivers!$S$5,Drivers!$B$25:$C$30,2,TRUE) | P47: =VLOOKUP(Drivers!$T$5,Drivers!$B$25:$C$30,2,TRUE) | Q47: =VLOOKUP(Drivers!$U$5,Drivers!$B$25:$C$30,2,TRUE) | R47: =VLOOKUP(Drivers!$V$5,Drivers!$B$25:$C$30,2,TRUE) | S47: =VLOOKUP(Drivers!$W$5,Drivers!$B$25:$C$30,2,TRUE) | T47: =VLOOKUP(Drivers!$X$5,Drivers!$B$25:$C$30,2,TRUE) | U47: =VLOOKUP(Drivers!$Y$5,Drivers!$B$25:$C$30,2,TRUE) | V47: =VLOOKUP(Drivers!$Z$5,Drivers!$B$25:$C$30,2,TRUE) | W47: =VLOOKUP(Drivers!$AA$5,Drivers!$B$25:$C$30,2,TRUE) | X47: =VLOOKUP(Drivers!$AB$5,Drivers!$B$25:$C$30,2,TRUE) | Y47: =VLOOKUP(Drivers!$AC$5,Drivers!$B$25:$C$30,2,TRUE) | Z47: =VLOOKUP(Drivers!$AD$5,Drivers!$B$25:$C$30,2,TRUE) | AA47: =VLOOKUP(Drivers!$AE$5,Drivers!$B$25:$C$30,2,TRUE) | AB47: =VLOOKUP(Drivers!$AF$5,Drivers!$B$25:$C$30,2,TRUE) | AC47: =VLOOKUP(Drivers!$AG$5,Drivers!$B$25:$C$30,2,TRUE) | AD47: =VLOOKUP(Drivers!$AH$5,Drivers!$B$25:$C$30,2,TRUE) | AE47: =VLOOKUP(Drivers!$AI$5,Drivers!$B$25:$C$30,2,TRUE) | AF47: =VLOOKUP(Drivers!$AJ$5,Drivers!$B$25:$C$30,2,TRUE) | AG47: =VLOOKUP(Drivers!$AK$5,Drivers!$B$25:$C$30,2,TRUE) | AH47: =VLOOKUP(Drivers!$AL$5,Drivers!$B$25:$C$30,2,TRUE) | AI47: =VLOOKUP(Drivers!$AM$5,Drivers!$B$25:$C$30,2,TRUE) | AJ47: =VLOOKUP(Drivers!$AN$5,Drivers!$B$25:$C$30,2,TRUE) | AK47: =VLOOKUP(Drivers!$AO$5,Drivers!$B$25:$C$30,2,TRUE) | AL47: =VLOOKUP(Drivers!$AP$5,Drivers!$B$25:$C$30,2,TRUE) | AM47: =VLOOKUP(Drivers!$AQ$5,Drivers!$B$25:$C$30,2,TRUE) | AN47: =VLOOKUP(Drivers!$AR$5,Drivers!$B$25:$C$30,2,TRUE)
A48: EBITDA per unit (price currency) | B48: ebitda_per_unit | G48: 4.2328496 | H48: =IF((H41*$C$10)=0,0,H61/(H41*$C$10)) | I48: =IF((I41*$C$10)=0,0,I61/(I41*$C$10)) | J48: =IF((J41*$C$10)=0,0,J61/(J41*$C$10)) | K48: =IF((K41*$C$10)=0,0,K61/(K41*$C$10)) | L48: =IF((L41*$C$10)=0,0,L61/(L41*$C$10)) | M48: =IF((M41*$C$10)=0,0,M61/(M41*$C$10)) | N48: =IF((N41*$C$10)=0,0,N61/(N41*$C$10)) | O48: =IF((O41*$C$10)=0,0,O61/(O41*$C$10)) | ... AN48: =IF((AN41*$C$10)=0,0,AN61/(AN41*$C$10))
A49: Cash cost + royalty per unit (price currency) | B49: cash_cost_money_per_unit | H49: =IF((H41*$C$10)=0,0,(H53+H52)/(H41*$C$10)) | I49: =IF((I41*$C$10)=0,0,(I53+I52)/(I41*$C$10)) | J49: =IF((J41*$C$10)=0,0,(J53+J52)/(J41*$C$10)) | K49: =IF((K41*$C$10)=0,0,(K53+K52)/(K41*$C$10)) | L49: =IF((L41*$C$10)=0,0,(L53+L52)/(L41*$C$10)) | M49: =IF((M41*$C$10)=0,0,(M53+M52)/(M41*$C$10)) | N49: =IF((N41*$C$10)=0,0,(N53+N52)/(N41*$C$10)) | O49: =IF((O41*$C$10)=0,0,(O53+O52)/(O41*$C$10)) | ... AN49: =IF((AN41*$C$10)=0,0,(AN53+AN52)/(AN41*$C$10))
A50: Main product revenue | B50: revenue_main | H50: =((H41*H43)*$C$10) | I50: =((I41*I43)*$C$10) | J50: =((J41*J43)*$C$10) | K50: =((K41*K43)*$C$10) | L50: =((L41*L43)*$C$10) | M50: =((M41*M43)*$C$10) | N50: =((N41*N43)*$C$10) | O50: =((O41*O43)*$C$10) | ... AN50: =((AN41*AN43)*$C$10)
A51: Other revenue | B51: other_revenue | H51: =H22 | I51: =I22 | J51: =J22 | K51: =K22 | L51: =L22 | M51: =M22 | N51: =N22 | O51: =O22 | ... AN51: =AN22
A52: Royalty | B52: royalty | H52: =(H50*H47) | I52: =(I50*I47) | J52: =(J50*J47) | K52: =(K50*K47) | L52: =(L50*L47) | M52: =(M50*M47) | N52: =(N50*N47) | O52: =(O50*O47) | ... AN52: =(AN50*AN47)
A53: Cash costs | B53: cash_cost | H53: =((H41*H45)*$C$10) | I53: =((I41*I45)*$C$10) | J53: =((J41*J45)*$C$10) | K53: =((K41*K45)*$C$10) | L53: =((L41*L45)*$C$10) | M53: =((M41*M45)*$C$10) | N53: =((N41*N45)*$C$10) | O53: =((O41*O45)*$C$10) | ... AN53: =((AN41*AN45)*$C$10)
A54: Cost of other revenue | B54: other_cogs | H54: =(H51*(1-$C$23)) | I54: =(I51*(1-$C$23)) | J54: =(J51*(1-$C$23)) | K54: =(K51*(1-$C$23)) | L54: =(L51*(1-$C$23)) | M54: =(M51*(1-$C$23)) | N54: =(N51*(1-$C$23)) | O54: =(O51*(1-$C$23)) | ... AN54: =(AN51*(1-$C$23))
A55: Revenue | B55: revenue | D55: 1830.0799 | E55: 1679.9488 | F55: 1359.6795 | G55: 4808.8 | H55: =(H50+H51) | I55: =(I50+I51) | J55: =(J50+J51) | K55: =(K50+K51) | L55: =(L50+L51) | M55: =(M50+M51) | N55: =(N50+N51) | O55: =(O50+O51) | ... AN55: =(AN50+AN51)
A56: Cost of revenue | B56: cogs | D56: 1459.439 | E56: 1542.6538 | F56: 1190.3894 | G56: 4262.2 | H56: =(((H53+H52)+H54)+H60) | I56: =(((I53+I52)+I54)+I60) | J56: =(((J53+J52)+J54)+J60) | K56: =(((K53+K52)+K54)+K60) | L56: =(((L53+L52)+L54)+L60) | M56: =(((M53+M52)+M54)+M60) | N56: =(((N53+N52)+N54)+N60) | O56: =(((O53+O52)+O54)+O60) | ... AN56: =(((AN53+AN52)+AN54)+AN60)
A57: Gross profit | B57: gross_profit | D57: 370.64095 | E57: 137.29493 | F57: 169.29005 | G57: 546.6 | H57: =(H55-H56) | I57: =(I55-I56) | J57: =(J55-J56) | K57: =(K55-K56) | L57: =(L55-L56) | M57: =(M55-M56) | N57: =(N55-N56) | O57: =(O55-O56) | ... AN57: =(AN55-AN56)
A58: SG&A and other opex | B58: opex | D58: 158.17182 | E58: 135.16693 | F58: 122.71771 | G58: 232.6 | H58: =(H55*H37) | I58: =(I55*I37) | J58: =(J55*J37) | K58: =(K55*K37) | L58: =(L55*L37) | M58: =(M55*M37) | N58: =(N55*N37) | O58: =(O55*O37) | ... AN58: =(AN55*AN37)
A59: EBIT | B59: ebit | D59: 212.46913 | E59: 2.128003 | F59: 46.572341 | G59: 314 | H59: =(H57-H58) | I59: =(I57-I58) | J59: =(J57-J58) | K59: =(K57-K58) | L59: =(L57-L58) | M59: =(M57-M58) | N59: =(N57-N58) | O59: =(O57-O58) | ... AN59: =(AN57-AN58)
A60: Depreciation & amortisation | B60: da | D60: 1.397852 | E60: 1.016239 | F60: 1.119301 | G60: 1.770582 | H60: =((H41*H24)*$C$10) | I60: =((I41*I24)*$C$10) | J60: =((J41*J24)*$C$10) | K60: =((K41*K24)*$C$10) | L60: =((L41*L24)*$C$10) | M60: =((M41*M24)*$C$10) | N60: =((N41*N24)*$C$10) | O60: =((O41*O24)*$C$10) | ... AN60: =((AN41*AN24)*$C$10)
A61: EBITDA | B61: ebitda | D61: 213.86698 | E61: 3.144242 | F61: 47.691642 | G61: 315.77058 | H61: =(H59+H60) | I61: =(I59+I60) | J61: =(J59+J60) | K61: =(K59+K60) | L61: =(L59+L60) | M61: =(M59+M60) | N61: =(N59+N60) | O61: =(O59+O60) | ... AN61: =(AN59+AN60)
A62: Interest expense | B62: interest_expense | D62: 161.651 | E62: 22.543597 | F62: 21.07534 | G62: 26.697162 | H62: =(G82*$C$29) | I62: =(H82*$C$29) | J62: =(I82*$C$29) | K62: =(J82*$C$29) | L62: =(K82*$C$29) | M62: =(L82*$C$29) | N62: =(M82*$C$29) | O62: =(N82*$C$29) | ... AN62: =(AM82*$C$29)
A63: Interest income | B63: interest_income | D63: 3.941868 | E63: 5.185511 | F63: 7.653116 | G63: 3.836104 | H63: =(G81*$C$30) | I63: =(H81*$C$30) | J63: =(I81*$C$30) | K63: =(J81*$C$30) | L63: =(K81*$C$30) | M63: =(L81*$C$30) | N63: =(M81*$C$30) | O63: =(N81*$C$30) | ... AN63: =(AM81*$C$30)
A64: Other non-operating | B64: other_nonop | D64: 639.38491 | E64: 97.580297 | F64: 88.751103 | G64: -5.038942 | H64: =H32 | I64: =I32 | J64: =J32 | K64: =K32 | L64: =L32 | M64: =M32 | N64: =N32 | O64: =O32 | ... AN64: =AN32
A65: Profit before tax | B65: pbt | D65: 694.14491 | E65: 82.350214 | F65: 121.90122 | G65: 286.1 | H65: =(((H59-H62)+H63)+H64) | I65: =(((I59-I62)+I63)+I64) | J65: =(((J59-J62)+J63)+J64) | K65: =(((K59-K62)+K63)+K64) | L65: =(((L59-L62)+L63)+L64) | M65: =(((M59-M62)+M63)+M64) | N65: =(((N59-N62)+N63)+N64) | O65: =(((O59-O62)+O63)+O64) | ... AN65: =(((AN59-AN62)+AN63)+AN64)
A66: Tax | B66: tax | D66: 115.59024 | E66: 49.924476 | F66: 28.222308 | G66: 55.558551 | H66: =(MAX(H65,0)*H28) | I66: =(MAX(I65,0)*I28) | J66: =(MAX(J65,0)*J28) | K66: =(MAX(K65,0)*K28) | L66: =(MAX(L65,0)*L28) | M66: =(MAX(M65,0)*M28) | N66: =(MAX(N65,0)*N28) | O66: =(MAX(O65,0)*O28) | ... AN66: =(MAX(AN65,0)*AN28)
A67: Net profit (incl. minorities) | B67: np | D67: 578.55466 | E67: 32.425738 | F67: 93.678912 | G67: 161.8 | H67: =(H65-H66) | I67: =(I65-I66) | J67: =(J65-J66) | K67: =(K65-K66) | L67: =(L65-L66) | M67: =(M65-M66) | N67: =(N65-N66) | O67: =(O65-O66) | ... AN67: =(AN65-AN66)
A68: Minority interests | B68: minority | D68: 53.280324 | E68: 21.502288 | F68: 26.200833 | G68: 44.521586 | H68: =(H67*H33) | I68: =(I67*I33) | J68: =(J67*J33) | K68: =(K67*K33) | L68: =(L67*L33) | M68: =(M67*M33) | N68: =(N67*N33) | O68: =(O67*O33) | ... AN68: =(AN67*AN33)
A69: Net profit to parent | B69: np_parent | D69: 525.27434 | E69: 10.92345 | F69: 67.478079 | G69: 81 | H69: =(H67-H68) | I69: =(I67-I68) | J69: =(J67-J68) | K69: =(K67-K68) | L69: =(L67-L68) | M69: =(M67-M68) | N69: =(N67-N68) | O69: =(O67-O68) | ... AN69: =(AN67-AN68)
A70: Shares outstanding (m) | B70: shares | D70: 371320.68 | E70: 371320.71 | F70: 371335.39 | G70: 371335.39 | H70: =(G70*(1+H35)) | I70: =(H70*(1+I35)) | J70: =(I70*(1+J35)) | K70: =(J70*(1+K35)) | L70: =(K70*(1+L35)) | M70: =(L70*(1+M35)) | N70: =(M70*(1+N35)) | O70: =(N70*(1+O35)) | ... AN70: =(AM70*(1+AN35))
A71: EPS | B71: eps | D71: 0.0014146111 | E71: 2.9417832e-05 | F71: 0.00018171734 | G71: 0.00021813165 | H71: =(IF(H70=0,0,H69/H70)*$C$8) | I71: =(IF(I70=0,0,I69/I70)*$C$8) | J71: =(IF(J70=0,0,J69/J70)*$C$8) | K71: =(IF(K70=0,0,K69/K70)*$C$8) | L71: =(IF(L70=0,0,L69/L70)*$C$8) | M71: =(IF(M70=0,0,M69/M70)*$C$8) | N71: =(IF(N70=0,0,N69/N70)*$C$8) | O71: =(IF(O70=0,0,O69/O70)*$C$8) | ... AN71: =(IF(AN70=0,0,AN69/AN70)*$C$8)
A72: DPS (declared on the year) | B72: dps | D72: 0 | E72: 0 | F72: 0 | G72: 0 | H72: =(MAX(H71,0)*H34) | I72: =(MAX(I71,0)*I34) | J72: =(MAX(J71,0)*J34) | K72: =(MAX(K71,0)*K34) | L72: =(MAX(L71,0)*L34) | M72: =(MAX(M71,0)*M34) | N72: =(MAX(N71,0)*N34) | O72: =(MAX(O71,0)*O34) | ... AN72: =(MAX(AN71,0)*AN34)
A73: Dividends paid | B73: dividends_paid | H73: =IF($C$8=0,0,(G72*G70)/$C$8) | I73: =IF($C$8=0,0,(H72*H70)/$C$8) | J73: =IF($C$8=0,0,(I72*I70)/$C$8) | K73: =IF($C$8=0,0,(J72*J70)/$C$8) | L73: =IF($C$8=0,0,(K72*K70)/$C$8) | M73: =IF($C$8=0,0,(L72*L70)/$C$8) | N73: =IF($C$8=0,0,(M72*M70)/$C$8) | O73: =IF($C$8=0,0,(N72*N70)/$C$8) | ... AN73: =IF($C$8=0,0,(AM72*AM70)/$C$8)
A74: Capital expenditure | B74: capex | D74: 129.31663 | E74: 51.944912 | F74: 25.047837 | G74: 124.85781 | H74: =(((H41*H25)*$C$10)+H26) | I74: =(((I41*I25)*$C$10)+I26) | J74: =(((J41*J25)*$C$10)+J26) | K74: =(((K41*K25)*$C$10)+K26) | L74: =(((L41*L25)*$C$10)+L26) | M74: =(((M41*M25)*$C$10)+M26) | N74: =(((N41*N25)*$C$10)+N26) | O74: =(((O41*O25)*$C$10)+O26) | ... AN74: =(((AN41*AN25)*$C$10)+AN26)
A75: Change in working capital | B75: delta_nwc | E75: 264.61588 | F75: 167.19804 | G75: -58.537948 | H75: =(H80-G80) | I75: =(I80-H80) | J75: =(J80-I80) | K75: =(K80-J80) | L75: =(L80-K80) | M75: =(M80-L80) | N75: =(N80-M80) | O75: =(O80-N80) | ... AN75: =(AN80-AM80)
A76: Free cash flow to firm | B76: fcff | E76: -314.70665 | F76: -155.33656 | G76: 188.47419 | H76: =((((H59*(1-H28))+H60)-H74)-H75) | I76: =((((I59*(1-I28))+I60)-I74)-I75) | J76: =((((J59*(1-J28))+J60)-J74)-J75) | K76: =((((K59*(1-K28))+K60)-K74)-K75) | L76: =((((L59*(1-L28))+L60)-L74)-L75) | M76: =((((M59*(1-M28))+M60)-M74)-M75) | N76: =((((N59*(1-N28))+N60)-N74)-N75) | O76: =((((O59*(1-O28))+O60)-O74)-O75) | ... AN76: =((((AN59*(1-AN28))+AN60)-AN74)-AN75)
A77: Net borrowing | B77: net_borrowing | E77: 61.029167 | F77: 5.823387 | G77: 122.47993 | H77: =H31 | I77: =I31 | J77: =J31 | K77: =K31 | L77: =L31 | M77: =M31 | N77: =N31 | O77: =O31 | ... AN77: =AN31
A78: Dividends to minorities | B78: minority_div | H78: =(MAX(G68,0)*H34) | I78: =(MAX(H68,0)*I34) | J78: =(MAX(I68,0)*J34) | K78: =(MAX(J68,0)*K34) | L78: =(MAX(K68,0)*L34) | M78: =(MAX(L68,0)*M34) | N78: =(MAX(M68,0)*N34) | O78: =(MAX(N68,0)*O34) | ... AN78: =(MAX(AM68,0)*AN34)
A79: Free cash flow to equity | B79: fcfe | H79: =(((((H67+H60)-H74)-H75)+H77)-H78) | I79: =(((((I67+I60)-I74)-I75)+I77)-I78) | J79: =(((((J67+J60)-J74)-J75)+J77)-J78) | K79: =(((((K67+K60)-K74)-K75)+K77)-K78) | L79: =(((((L67+L60)-L74)-L75)+L77)-L78) | M79: =(((((M67+M60)-M74)-M75)+M77)-M78) | N79: =(((((N67+N60)-N74)-N75)+N77)-N78) | O79: =(((((O67+O60)-O74)-O75)+O77)-O78) | ... AN79: =(((((AN67+AN60)-AN74)-AN75)+AN77)-AN78)
A80: Operating working capital | B80: nwc | D80: -292.47915 | E80: -27.86327 | F80: 139.33477 | G80: 80.796818 | H80: =(H55*H27) | I80: =(I55*I27) | J80: =(J55*J27) | K80: =(K55*K27) | L80: =(L55*L27) | M80: =(M55*M27) | N80: =(N55*N27) | O80: =(O55*O27) | ... AN80: =(AN55*AN27)
A81: Cash & equivalents | B81: cash | D81: 180.30718 | E81: 76.806887 | F81: 52.494887 | G81: 118.59189 | H81: =(((((((G81+H67)+H60)-H74)-H75)+H77)-H73)-H78) | I81: =(((((((H81+I67)+I60)-I74)-I75)+I77)-I73)-I78) | J81: =(((((((I81+J67)+J60)-J74)-J75)+J77)-J73)-J78) | K81: =(((((((J81+K67)+K60)-K74)-K75)+K77)-K73)-K78) | L81: =(((((((K81+L67)+L60)-L74)-L75)+L77)-L73)-L78) | M81: =(((((((L81+M67)+M60)-M74)-M75)+M77)-M73)-M78) | N81: =(((((((M81+N67)+N60)-N74)-N75)+N77)-N73)-N78) | O81: =(((((((N81+O67)+O60)-O74)-O75)+O77)-O73)-O78) | ... AN81: =(((((((AM81+AN67)+AN60)-AN74)-AN75)+AN77)-AN73)-AN78)
A82: Total debt | B82: debt | D82: 245.55168 | E82: 306.58085 | F82: 312.40423 | G82: 434.88416 | H82: =(G82+H77) | I82: =(H82+I77) | J82: =(I82+J77) | K82: =(J82+K77) | L82: =(K82+L77) | M82: =(L82+M77) | N82: =(M82+N77) | O82: =(N82+O77) | ... AN82: =(AM82+AN77)
A83: Fixed assets (net) | B83: ppe | D83: 2042.756 | E83: 2067.1018 | F83: 2046.6978 | G83: 2115.362 | H83: =((G83+H74)-H60) | I83: =((H83+I74)-I60) | J83: =((I83+J74)-J60) | K83: =((J83+K74)-K60) | L83: =((K83+L74)-L60) | M83: =((L83+M74)-M60) | N83: =((M83+N74)-N60) | O83: =((N83+O74)-O60) | ... AN83: =((AM83+AN74)-AN60)
A84: Parent shareholders' equity | B84: equity | D84: 1578.3629 | E84: 1543.137 | F84: 1610.0279 | G84: 1615.3196 | H84: =((G84+H69)-H73) | I84: =((H84+I69)-I73) | J84: =((I84+J69)-J73) | K84: =((J84+K69)-K73) | L84: =((K84+L69)-L73) | M84: =((L84+M69)-M73) | N84: =((M84+N69)-N73) | O84: =((N84+O69)-O73) | ... AN84: =((AM84+AN69)-AN73)
A85: Minority interest (balance sheet) | B85: minority_bs | D85: 1240.1454 | E85: 1231.6391 | F85: 1254.2165 | G85: 1272.603 | H85: =((G85+H68)-H78) | I85: =((H85+I68)-I78) | J85: =((I85+J68)-J78) | K85: =((J85+K68)-K78) | L85: =((K85+L68)-L78) | M85: =((L85+M68)-M78) | N85: =((M85+N68)-N78) | O85: =((N85+O68)-O78) | ... AN85: =((AM85+AN68)-AN78)
A86: Other assets less other liabilities | B86: other_net | D86: 1133.4759 | E86: 965.3115 | F86: 938.12116 | G86: 1008.0561 | H86: =G86 | I86: =H86 | J86: =I86 | K86: =J86 | L86: =K86 | M86: =L86 | N86: =M86 | O86: =N86 | ... AN86: =AM86
A87: Balance check (should be zero) | B87: bs_check | H87: =((((((H81+H80)+H83)+H86)-H82)-H84)-H85) | I87: =((((((I81+I80)+I83)+I86)-I82)-I84)-I85) | J87: =((((((J81+J80)+J83)+J86)-J82)-J84)-J85) | K87: =((((((K81+K80)+K83)+K86)-K82)-K84)-K85) | L87: =((((((L81+L80)+L83)+L86)-L82)-L84)-L85) | M87: =((((((M81+M80)+M83)+M86)-M82)-M84)-M85) | N87: =((((((N81+N80)+N83)+N86)-N82)-N84)-N85) | O87: =((((((O81+O80)+O83)+O86)-O82)-O84)-O85) | ... AN87: =((((((AN81+AN80)+AN83)+AN86)-AN82)-AN84)-AN85)
A88: Net debt (cash) | B88: net_debt | D88: 65.2445 | E88: 229.77396 | F88: 259.90935 | G88: 316.29228 | H88: =(H82-H81) | I88: =(I82-I81) | J88: =(J82-J81) | K88: =(K82-K81) | L88: =(L82-L81) | M88: =(M82-M81) | N88: =(N82-N81) | O88: =(O82-O81) | ... AN88: =(AN82-AN81)
A89: Book value per share | B89: bvps | D89: 0.0042506732 | E89: 0.0041558064 | F89: 0.0043357782 | G89: 0.0043500287 | H89: =(IF(H70=0,0,H84/H70)*$C$8) | I89: =(IF(I70=0,0,I84/I70)*$C$8) | J89: =(IF(J70=0,0,J84/J70)*$C$8) | K89: =(IF(K70=0,0,K84/K70)*$C$8) | L89: =(IF(L70=0,0,L84/L70)*$C$8) | M89: =(IF(M70=0,0,M84/M70)*$C$8) | N89: =(IF(N70=0,0,N84/N70)*$C$8) | O89: =(IF(O70=0,0,O84/O70)*$C$8) | ... AN89: =(IF(AN70=0,0,AN84/AN70)*$C$8)
A90: Revenue growth | B90: revenue_growth | E90: -0.082035303 | F90: -0.1906423 | G90: 2.5367159 | H90: =(IF(G55=0,0,H55/G55)-1) | I90: =(IF(H55=0,0,I55/H55)-1) | J90: =(IF(I55=0,0,J55/I55)-1) | K90: =(IF(J55=0,0,K55/J55)-1) | L90: =(IF(K55=0,0,L55/K55)-1) | M90: =(IF(L55=0,0,M55/L55)-1) | N90: =(IF(M55=0,0,N55/M55)-1) | O90: =(IF(N55=0,0,O55/N55)-1) | ... AN90: =(IF(AM55=0,0,AN55/AM55)-1)
A91: Gross margin | B91: gross_margin | D91: 0.20252719 | E91: 0.081725664 | F91: 0.12450732 | G91: 0.11366661 | H91: =IF(H55=0,0,H57/H55) | I91: =IF(I55=0,0,I57/I55) | J91: =IF(J55=0,0,J57/J55) | K91: =IF(K55=0,0,K57/K55) | L91: =IF(L55=0,0,L57/L55) | M91: =IF(M55=0,0,M57/M55) | N91: =IF(N55=0,0,N57/N55) | O91: =IF(O55=0,0,O57/O55) | ... AN91: =IF(AN55=0,0,AN57/AN55)
A92: EBITDA margin | B92: ebitda_margin | D92: 0.1168621 | E92: 0.0018716297 | F92: 0.035075651 | G92: 0.065665152 | H92: =IF(H55=0,0,H61/H55) | I92: =IF(I55=0,0,I61/I55) | J92: =IF(J55=0,0,J61/J55) | K92: =IF(K55=0,0,K61/K55) | L92: =IF(L55=0,0,L61/L55) | M92: =IF(M55=0,0,M61/M55) | N92: =IF(N55=0,0,N61/N55) | O92: =IF(O55=0,0,O61/O55) | ... AN92: =IF(AN55=0,0,AN61/AN55)
A93: EBIT margin | B93: ebit_margin | D93: 0.11609828 | E93: 0.0012667071 | F93: 0.034252441 | G93: 0.065296956 | H93: =IF(H55=0,0,H59/H55) | I93: =IF(I55=0,0,I59/I55) | J93: =IF(J55=0,0,J59/J55) | K93: =IF(K55=0,0,K59/K55) | L93: =IF(L55=0,0,L59/L55) | M93: =IF(M55=0,0,M59/M55) | N93: =IF(N55=0,0,N59/N55) | O93: =IF(O55=0,0,O59/O55) | ... AN93: =IF(AN55=0,0,AN59/AN55)
A94: Net margin | B94: np_margin | D94: 0.28702262 | E94: 0.0065022519 | F94: 0.049627931 | G94: 0.016844119 | H94: =IF(H55=0,0,H69/H55) | I94: =IF(I55=0,0,I69/I55) | J94: =IF(J55=0,0,J69/J55) | K94: =IF(K55=0,0,K69/K55) | L94: =IF(L55=0,0,L69/L55) | M94: =IF(M55=0,0,M69/M55) | N94: =IF(N55=0,0,N69/N55) | O94: =IF(O55=0,0,O69/O55) | ... AN94: =IF(AN55=0,0,AN69/AN55)
A95: EPS growth | B95: eps_growth | E95: -0.9792043 | F95: 5.1771153 | G95: 0.20038983 | H95: =(IF(G71=0,0,H71/G71)-1) | I95: =(IF(H71=0,0,I71/H71)-1) | J95: =(IF(I71=0,0,J71/I71)-1) | K95: =(IF(J71=0,0,K71/J71)-1) | L95: =(IF(K71=0,0,L71/K71)-1) | M95: =(IF(L71=0,0,M71/L71)-1) | N95: =(IF(M71=0,0,N71/M71)-1) | O95: =(IF(N71=0,0,O71/N71)-1) | ... AN95: =(IF(AM71=0,0,AN71/AM71)-1)
A96: ROE | B96: roe | E96: 0.0069988471 | F96: 0.042800223 | G96: 0.050227146 | H96: =IF(IF(2=0,0,(H84+G84)/2)=0,0,H69/IF(2=0,0,(H84+G84)/2)) | I96: =IF(IF(2=0,0,(I84+H84)/2)=0,0,I69/IF(2=0,0,(I84+H84)/2)) | J96: =IF(IF(2=0,0,(J84+I84)/2)=0,0,J69/IF(2=0,0,(J84+I84)/2)) | K96: =IF(IF(2=0,0,(K84+J84)/2)=0,0,K69/IF(2=0,0,(K84+J84)/2)) | L96: =IF(IF(2=0,0,(L84+K84)/2)=0,0,L69/IF(2=0,0,(L84+K84)/2)) | M96: =IF(IF(2=0,0,(M84+L84)/2)=0,0,M69/IF(2=0,0,(M84+L84)/2)) | N96: =IF(IF(2=0,0,(N84+M84)/2)=0,0,N69/IF(2=0,0,(N84+M84)/2)) | O96: =IF(IF(2=0,0,(O84+N84)/2)=0,0,O69/IF(2=0,0,(O84+N84)/2)) | ... AN96: =IF(IF(2=0,0,(AN84+AM84)/2)=0,0,AN69/IF(2=0,0,(AN84+AM84)/2))
A97: Net debt / EBITDA | B97: net_debt_ebitda | D97: 0.30507047 | E97: 73.077696 | F97: 5.4497882 | G97: 1.0016521 | H97: =IF(H61=0,0,H88/H61) | I97: =IF(I61=0,0,I88/I61) | J97: =IF(J61=0,0,J88/J61) | K97: =IF(K61=0,0,K88/K61) | L97: =IF(L61=0,0,L88/L61) | M97: =IF(M61=0,0,M88/M61) | N97: =IF(N61=0,0,N88/N61) | O97: =IF(O61=0,0,O88/O61) | ... AN97: =IF(AN61=0,0,AN88/AN61)
A98: Payout ratio | B98: payout_ratio | D98: 0 | E98: 0 | F98: 0 | G98: 0 | H98: =IF(H71=0,0,H72/H71) | I98: =IF(I71=0,0,I72/I71) | J98: =IF(J71=0,0,J72/J71) | K98: =IF(K71=0,0,K72/K71) | L98: =IF(L71=0,0,L72/L71) | M98: =IF(M71=0,0,M72/M71) | N98: =IF(N71=0,0,N72/N71) | O98: =IF(O71=0,0,O72/O71) | ... AN98: =IF(AN71=0,0,AN72/AN71)
A99: Capex / revenue | B99: capex_revenue | D99: 0.070661737 | E99: 0.030920533 | F99: 0.018421869 | G99: 0.025964443 | H99: =IF(H55=0,0,H74/H55) | I99: =IF(I55=0,0,I74/I55) | J99: =IF(J55=0,0,J74/J55) | K99: =IF(K55=0,0,K74/K55) | L99: =IF(L55=0,0,L74/L55) | M99: =IF(M55=0,0,M74/M55) | N99: =IF(N55=0,0,N74/N55) | O99: =IF(O55=0,0,O74/O55) | ... AN99: =IF(AN55=0,0,AN74/AN55)
A101: VALUATION
A102: Last price (IDR) | C102: 140
A103: Shares outstanding (m) | C103: 371335.39
A104: IDR per USD (spot) | C104: 18138
A105: Debt at balance-sheet date | C105: 732.99298
...

Sheet BYAN
A1: PT Bayan Resources Tbk. (BYAN.JK) — Coal producers
A2: Units: USD m; per-share in USD unless marked IDR. Model asof 2026-10-30 · data 2026-10-30
A4: Line | C4: Scalar | D4: FY2022A | E4: FY2023A | F4: FY2024A | G4: FY2025A | H4: FY2026E | I4: FY2027E | J4: FY2028E | K4: FY2029E | L4: FY2030E | M4: FY2031E | N4: FY2032E | O4: FY2033E | P4: FY2034E | Q4: FY2035E | R4: FY2036E | S4: FY2037E | T4: FY2038E | U4: FY2039E | V4: FY2040E | W4: FY2041E | X4: FY2042E | Y4: FY2043E | Z4: FY2044E | AA4: FY2045E | AB4: FY2046E | AC4: FY2047E | AD4: FY2048E | AE4: FY2049E | AF4: FY2050E
A6: PARAMETERS
A7: horizon | C7: 25
A8: ps_factor | C8: 1
A9: reserves | C9: 2030
A10: unit_factor | C10: 1
A11: vp_factor | C11: 1
A13: INPUTS (company assumptions)
A14: Sales volume plan | B14: a.volume | H14: 67 | I14: 77 | J14: 80 | K14: 80 | L14: 80 | M14: 80 | N14: 80 | O14: 80 | P14: 80 | Q14: 80 | R14: 80 | S14: 80 | T14: 80 | U14: 80 | V14: 80 | W14: 80 | X14: 80 | Y14: 80 | Z14: 80 | AA14: 80 | AB14: 80 | AC14: 80 | AD14: 80 | AE14: 80 | AF14: 80
A15: Realised price / benchmark | B15: a.realisation | H15: 0.4 | I15: 0.4465 | J15: 0.4465 | K15: 0.4465 | L15: 0.4465 | M15: 0.4465 | N15: 0.4465 | O15: 0.4465 | P15: 0.4465 | Q15: 0.4465 | R15: 0.4465 | S15: 0.4465 | T15: 0.4465 | U15: 0.4465 | V15: 0.4465 | W15: 0.4465 | X15: 0.4465 | Y15: 0.4465 | Z15: 0.4465 | AA15: 0.4465 | AB15: 0.4465 | AC15: 0.4465 | AD15: 0.4465 | AE15: 0.4465 | AF15: 0.4465
A16: Share of volume under a price cap (e.g. DMO) | B16: a.capped_share | H16: 0.25 | I16: 0.25 | J16: 0.25 | K16: 0.25 | L16: 0.25 | M16: 0.25 | N16: 0.25 | O16: 0.25 | P16: 0.25 | Q16: 0.25 | R16: 0.25 | S16: 0.25 | T16: 0.25 | U16: 0.25 | V16: 0.25 | W16: 0.25 | X16: 0.25 | Y16: 0.25 | Z16: 0.25 | AA16: 0.25 | AB16: 0.25 | AC16: 0.25 | AD16: 0.25 | AE16: 0.25 | AF16: 0.25
A17: Strip ratio (bcm per tonne) or cost-intensity factor | B17: a.strip_ratio | H17: 1 | I17: 1 | J17: 1 | K17: 1.01 | L17: 1.02 | M17: 1.05 | N17: 1.05 | O17: 1.05 | P17: 1.05 | Q17: 1.05 | R17: 1.05 | S17: 1.05 | T17: 1.05 | U17: 1.05 | V17: 1.05 | W17: 1.05 | X17: 1.05 | Y17: 1.05 | Z17: 1.05 | AA17: 1.05 | AB17: 1.05 | AC17: 1.05 | AD17: 1.05 | AE17: 1.05 | AF17: 1.05
A18: Mining cost per bcm (or per unit when intensity is 1) | B18: a.cost_per_bcm | H18: 22 | I18: 22.3 | J18: 22.6 | K18: 22.8 | L18: 23 | M18: 21.93 | N18: 22.3686 | O18: 22.815972 | P18: 23.272291 | Q18: 23.737737 | R18: 24.212492 | S18: 24.696742 | T18: 25.190677 | U18: 25.69449 | V18: 26.20838 | W18: 26.732548 | X18: 27.267199 | Y18: 27.812543 | Z18: 28.368793 | AA18: 28.936169 | AB18: 29.514893 | AC18: 30.105191 | AD18: 30.707294 | AE18: 31.32144 | AF18: 31.947869
A19: Fuel share of mining cost | B19: a.fuel_share | C19: 0.1
A20: Other cash cost per unit (haul, barge, process) | B20: a.other_cost_unit | H20: 5.5 | I20: 5.6 | J20: 5.7 | K20: 5.8 | L20: 5.9 | M20: 6.12 | N20: 6.2424 | O20: 6.367248 | P20: 6.494593 | Q20: 6.6244848 | R20: 6.7569745 | S20: 6.892114 | T20: 7.0299563 | U20: 7.1705554 | V20: 7.3139665 | W20: 7.4602459 | X20: 7.6094508 | Y20: 7.7616398 | Z20: 7.9168726 | AA20: 8.07521 | AB20: 8.2367142 | AC20: 8.4014485 | AD20: 8.5694775 | AE20: 8.740867 | AF20: 8.9156844
A21: Royalty rate (flat regimes) | B21: a.royalty_rate | H21: 0.08 | I21: 0.08 | J21: 0.08 | K21: 0.08 | L21: 0.08 | M21: 0.08 | N21: 0.08 | O21: 0.08 | P21: 0.08 | Q21: 0.08 | R21: 0.08 | S21: 0.08 | T21: 0.08 | U21: 0.08 | V21: 0.08 | W21: 0.08 | X21: 0.08 | Y21: 0.08 | Z21: 0.08 | AA21: 0.08 | AB21: 0.08 | AC21: 0.08 | AD21: 0.08 | AE21: 0.08 | AF21: 0.08
A22: Other revenue | B22: a.other_revenue | H22: 20 | I22: 20 | J22: 20 | K22: 20 | L22: 20 | M22: 20.4 | N22: 20.808 | O22: 21.22416 | P22: 21.648643 | Q22: 22.081616 | R22: 22.523248 | S22: 22.973713 | T22: 23.433188 | U22: 23.901851 | V22: 24.379888 | W22: 24.867486 | X22: 25.364836 | Y22: 25.872133 | Z22: 26.389575 | AA22: 26.917367 | AB22: 27.455714 | AC22: 28.004828 | AD22: 28.564925 | AE22: 29.136223 | AF22: 29.718948
A23: Gross margin on other revenue | B23: a.other_margin | C23: 0.1
A24: D&A per unit (reporting currency) | B24: a.da_unit | H24: 1.57 | I24: 1.57 | J24: 1.57 | K24: 1.57 | L24: 1.57 | M24: 1.6014 | N24: 1.633428 | O24: 1.6660966 | P24: 1.6994185 | Q24: 1.7334069 | R24: 1.768075 | S24: 1.8034365 | T24: 1.8395052 | U24: 1.8762953 | V24: 1.9138212 | W24: 1.9520977 | X24: 1.9911396 | Y24: 2.0309624 | Z24: 2.0715817 | AA24: 2.1130133 | AB24: 2.1552736 | AC24: 2.198379 | AD24: 2.2423466 | AE24: 2.2871935 | AF24: 2.3329374
A25: Sustaining capex per unit (reporting currency) | B25: a.capex_unit | H25: 2.4 | I25: 2.45 | J25: 2.5 | K25: 2.55 | L25: 2.6 | M25: 2.652 | N25: 2.70504 | O25: 2.7591408 | P25: 2.8143236 | Q25: 2.8706101 | R25: 2.9280223 | S25: 2.9865827 | T25: 3.0463144 | U25: 3.1072407 | V25: 3.1693855 | W25: 3.2327732 | X25: 3.2974287 | Y25: 3.3633772 | Z25: 3.4306448 | AA25: 3.4992577 | AB25: 3.5692428 | AC25: 3.6406277 | AD25: 3.7134402 | AE25: 3.787709 | AF25: 3.8634632
A26: Other capex (expansion projects) | B26: a.capex_other | H26: 40 | I26: 40 | J26: 30 | K26: 20 | L26: 20 | M26: 15.3 | N26: 15.606 | O26: 15.91812 | P26: 16.236482 | Q26: 16.561212 | R26: 16.892436 | S26: 17.230285 | T26: 17.574891 | U26: 17.926389 | V26: 18.284916 | W26: 18.650615 | X26: 19.023627 | Y26: 19.404099 | Z26: 19.792181 | AA26: 20.188025 | AB26: 20.591786 | AC26: 21.003621 | AD26: 21.423694 | AE26: 21.852168 | AF26: 22.289211
A27: Operating working capital / revenue | B27: a.nwc_pct | H27: 0.047097 | I27: 0.047097 | J27: 0.047097 | K27: 0.047097 | L27: 0.047097 | M27: 0.047097 | N27: 0.047097 | O27: 0.047097 | P27: 0.047097 | Q27: 0.047097 | R27: 0.047097 | S27: 0.047097 | T27: 0.047097 | U27: 0.047097 | V27: 0.047097 | W27: 0.047097 | X27: 0.047097 | Y27: 0.047097 | Z27: 0.047097 | AA27: 0.047097 | AB27: 0.047097 | AC27: 0.047097 | AD27: 0.047097 | AE27: 0.047097 | AF27: 0.047097
A28: Effective tax rate | B28: a.tax_rate | H28: 0.219708 | I28: 0.219708 | J28: 0.219708 | K28: 0.219708 | L28: 0.219708 | M28: 0.219708 | N28: 0.219708 | O28: 0.219708 | P28: 0.219708 | Q28: 0.219708 | R28: 0.219708 | S28: 0.219708 | T28: 0.219708 | U28: 0.219708 | V28: 0.219708 | W28: 0.219708 | X28: 0.219708 | Y28: 0.219708 | Z28: 0.219708 | AA28: 0.219708 | AB28: 0.219708 | AC28: 0.219708 | AD28: 0.219708 | AE28: 0.219708 | AF28: 0.219708
A29: Cost of debt (on opening debt) | B29: a.cost_of_debt | C29: 0.03
A30: Yield on opening cash | B30: a.cash_yield | C30: 0.024951
A31: Net new borrowing | B31: a.net_borrowing | H31: 0 | I31: 0 | J31: 0 | K31: 0 | L31: 0 | M31: 0 | N31: 0 | O31: 0 | P31: 0 | Q31: 0 | R31: 0 | S31: 0 | T31: 0 | U31: 0 | V31: 0 | W31: 0 | X31: 0 | Y31: 0 | Z31: 0 | AA31: 0 | AB31: 0 | AC31: 0 | AD31: 0 | AE31: 0 | AF31: 0
A32: Other non-operating items | B32: a.other_nonop | H32: 0 | I32: 0 | J32: 0 | K32: 0 | L32: 0 | M32: 0 | N32: 0 | O32: 0 | P32: 0 | Q32: 0 | R32: 0 | S32: 0 | T32: 0 | U32: 0 | V32: 0 | W32: 0 | X32: 0 | Y32: 0 | Z32: 0 | AA32: 0 | AB32: 0 | AC32: 0 | AD32: 0 | AE32: 0 | AF32: 0
A33: Minorities' share of net profit | B33: a.minority_pct | H33: 0.024865 | I33: 0.024865 | J33: 0.024865 | K33: 0.024865 | L33: 0.024865 | M33: 0.024865 | N33: 0.024865 | O33: 0.024865 | P33: 0.024865 | Q33: 0.024865 | R33: 0.024865 | S33: 0.024865 | T33: 0.024865 | U33: 0.024865 | V33: 0.024865 | W33: 0.024865 | X33: 0.024865 | Y33: 0.024865 | Z33: 0.024865 | AA33: 0.024865 | AB33: 0.024865 | AC33: 0.024865 | AD33: 0.024865 | AE33: 0.024865 | AF33: 0.024865
A34: Dividend payout | B34: a.payout | H34: 0.73 | I34: 0.73 | J34: 0.73 | K34: 0.73 | L34: 0.73 | M34: 0.73 | N34: 0.73 | O34: 0.73 | P34: 0.73 | Q34: 0.73 | R34: 0.73 | S34: 0.73 | T34: 0.73 | U34: 0.73 | V34: 0.73 | W34: 0.73 | X34: 0.73 | Y34: 0.73 | Z34: 0.73 | AA34: 0.73 | AB34: 0.73 | AC34: 0.73 | AD34: 0.73 | AE34: 0.73 | AF34: 0.73
A35: Change in share count | B35: a.share_change | H35: 0 | I35: 0 | J35: 0 | K35: 0 | L35: 0 | M35: 0 | N35: 0 | O35: 0 | P35: 0 | Q35: 0 | R35: 0 | S35: 0 | T35: 0 | U35: 0 | V35: 0 | W35: 0 | X35: 0 | Y35: 0 | Z35: 0 | AA35: 0 | AB35: 0 | AC35: 0 | AD35: 0 | AE35: 0 | AF35: 0
A36: Terminal growth (DCF) | B36: a.terminal_growth | C36: 0
A37: SG&A / revenue | B37: a.opex_pct | H37: 0.028 | I37: 0.028 | J37: 0.029 | K37: 0.029 | L37: 0.03 | M37: 0.03 | N37: 0.03 | O37: 0.03 | P37: 0.03 | Q37: 0.03 | R37: 0.03 | S37: 0.03 | T37: 0.03 | U37: 0.03 | V37: 0.03 | W37: 0.03 | X37: 0.03 | Y37: 0.03 | Z37: 0.03 | AA37: 0.03 | AB37: 0.03 | AC37: 0.03 | AD37: 0.03 | AE37: 0.03 | AF37: 0.03
A39: MODEL
A40: Reserves remaining (close) | B40: reserves | D40: 2030 | G40: 2030 | H40: =MAX((G40-H41),0) | I40: =MAX((H40-I41),0) | J40: =MAX((I40-J41),0) | K40: =MAX((J40-K41),0) | L40: =MAX((K40-L41),0) | M40: =MAX((L40-M41),0) | N40: =MAX((M40-N41),0) | O40: =MAX((N40-O41),0) | ... AF40: =MAX((AE40-AF41),0)
A41: Sales volume | B41: volume | F41: 56.2 | G41: 70.8 | H41: =IF(($C$9>0),MIN(H14,MAX(G40,0)),H14) | I41: =IF(($C$9>0),MIN(I14,MAX(H40,0)),I14) | J41: =IF(($C$9>0),MIN(J14,MAX(I40,0)),J14) | K41: =IF(($C$9>0),MIN(K14,MAX(J40,0)),K14) | L41: =IF(($C$9>0),MIN(L14,MAX(K40,0)),L14) | M41: =IF(($C$9>0),MIN(M14,MAX(L40,0)),M14) | N41: =IF(($C$9>0),MIN(N14,MAX(M40,0)),N14) | O41: =IF(($C$9>0),MIN(O14,MAX(N40,0)),O14) | ... AF41: =IF(($C$9>0),MIN(AF14,MAX(AE40,0)),AF14)
A42: Benchmark price | B42: benchmark | H42: =Drivers!$L$6 | I42: =Drivers!$M$6 | J42: =Drivers!$N$6 | K42: =Drivers!$O$6 | L42: =Drivers!$P$6 | M42: =Drivers!$Q$6 | N42: =Drivers!$R$6 | O42: =Drivers!$S$6 | P42: =Drivers!$T$6 | Q42: =Drivers!$U$6 | R42: =Drivers!$V$6 | S42: =Drivers!$W$6 | T42: =Drivers!$X$6 | U42: =Drivers!$Y$6 | V42: =Drivers!$Z$6 | W42: =Drivers!$AA$6 | X42: =Drivers!$AB$6 | Y42: =Drivers!$AC$6 | Z42: =Drivers!$AD$6 | AA42: =Drivers!$AE$6 | AB42: =Drivers!$AF$6 | AC42: =Drivers!$AG$6 | AD42: =Drivers!$AH$6 | AE42: =Drivers!$AI$6 | AF42: =Drivers!$AJ$6
A43: Average selling price | B43: asp | F43: 61.3 | G43: 48.4 | H43: =(((H15*H42)*(1-H16))+(MIN(Drivers!$L$4,(H15*H42))*H16)) | I43: =(((I15*I42)*(1-I16))+(MIN(Drivers!$M$4,(I15*I42))*I16)) | J43: =(((J15*J42)*(1-J16))+(MIN(Drivers!$N$4,(J15*J42))*J16)) | K43: =(((K15*K42)*(1-K16))+(MIN(Drivers!$O$4,(K15*K42))*K16)) | L43: =(((L15*L42)*(1-L16))+(MIN(Drivers!$P$4,(L15*L42))*L16)) | M43: =(((M15*M42)*(1-M16))+(MIN(Drivers!$Q$4,(M15*M42))*M16)) | N43: =(((N15*N42)*(1-N16))+(MIN(Drivers!$R$4,(N15*N42))*N16)) | O43: =(((O15*O42)*(1-O16))+(MIN(Drivers!$S$4,(O15*O42))*O16)) | P43: =(((P15*P42)*(1-P16))+(MIN(Drivers!$T$4,(P15*P42))*P16)) | Q43: =(((Q15*Q42)*(1-Q16))+(MIN(Drivers!$U$4,(Q15*Q42))*Q16)) | R43: =(((R15*R42)*(1-R16))+(MIN(Drivers!$V$4,(R15*R42))*R16)) | S43: =(((S15*S42)*(1-S16))+(MIN(Drivers!$W$4,(S15*S42))*S16)) | T43: =(((T15*T42)*(1-T16))+(MIN(Drivers!$X$4,(T15*T42))*T16)) | U43: =(((U15*U42)*(1-U16))+(MIN(Drivers!$Y$4,(U15*U42))*U16)) | V43: =(((V15*V42)*(1-V16))+(MIN(Drivers!$Z$4,(V15*V42))*V16)) | W43: =(((W15*W42)*(1-W16))+(MIN(Drivers!$AA$4,(W15*W42))*W16)) | X43: =(((X15*X42)*(1-X16))+(MIN(Drivers!$AB$4,(X15*X42))*X16)) | Y43: =(((Y15*Y42)*(1-Y16))+(MIN(Drivers!$AC$4,(Y15*Y42))*Y16)) | Z43: =(((Z15*Z42)*(1-Z16))+(MIN(Drivers!$AD$4,(Z15*Z42))*Z16)) | AA43: =(((AA15*AA42)*(1-AA16))+(MIN(Drivers!$AE$4,(AA15*AA42))*AA16)) | AB43: =(((AB15*AB42)*(1-AB16))+(MIN(Drivers!$AF$4,(AB15*AB42))*AB16)) | AC43: =(((AC15*AC42)*(1-AC16))+(MIN(Drivers!$AG$4,(AC15*AC42))*AC16)) | AD43: =(((AD15*AD42)*(1-AD16))+(MIN(Drivers!$AH$4,(AD15*AD42))*AD16)) | AE43: =(((AE15*AE42)*(1-AE16))+(MIN(Drivers!$AI$4,(AE15*AE42))*AE16)) | AF43: =(((AF15*AF42)*(1-AF16))+(MIN(Drivers!$AJ$4,(AF15*AF42))*AF16))
A44: Realisation vs benchmark | B44: realisation_line | H44: =IF(H42=0,0,H43/H42) | I44: =IF(I42=0,0,I43/I42) | J44: =IF(J42=0,0,J43/J42) | K44: =IF(K42=0,0,K43/K42) | L44: =IF(L42=0,0,L43/L42) | M44: =IF(M42=0,0,M43/M42) | N44: =IF(N42=0,0,N43/N42) | O44: =IF(O42=0,0,O43/O42) | ... AF44: =IF(AF42=0,0,AF43/AF42)
A45: Cash cost per unit (ex-royalty) | B45: unit_cost | F45: 37.8 | G45: 32.5 | H45: =(((H17*H18)*(1+($C$19*(IF(Drivers!$J$8=0,0,Drivers!$L$8/Drivers!$J$8)-1))))+H20) | I45: =(((I17*I18)*(1+($C$19*(IF(Drivers!$J$8=0,0,Drivers!$M$8/Drivers!$J$8)-1))))+I20) | J45: =(((J17*J18)*(1+($C$19*(IF(Drivers!$J$8=0,0,Drivers!$N$8/Drivers!$J$8)-1))))+J20) | K45: =(((K17*K18)*(1+($C$19*(IF(Drivers!$J$8=0,0,Drivers!$O$8/Drivers!$J$8)-1))))+K20) | L45: =(((L17*L18)*(1+($C$19*(IF(Drivers!$J$8=0,0,Drivers!$P$8/Drivers!$J$8)-1))))+L20) | M45: =(((M17*M18)*(1+($C$19*(IF(Drivers!$J$8=0,0,Drivers!$Q$8/Drivers!$J$8)-1))))+M20) | N45: =(((N17*N18)*(1+($C$19*(IF(Drivers!$J$8=0,0,Drivers!$R$8/Drivers!$J$8)-1))))+N20) | O45: =(((O17*O18)*(1+($C$19*(IF(Drivers!$J$8=0,0,Drivers!$S$8/Drivers!$J$8)-1))))+O20) | P45: =(((P17*P18)*(1+($C$19*(IF(Drivers!$J$8=0,0,Drivers!$T$8/Drivers!$J$8)-1))))+P20) | Q45: =(((Q17*Q18)*(1+($C$19*(IF(Drivers!$J$8=0,0,Drivers!$U$8/Drivers!$J$8)-1))))+Q20) | R45: =(((R17*R18)*(1+($C$19*(IF(Drivers!$J$8=0,0,Drivers!$V$8/Drivers!$J$8)-1))))+R20) | S45: =(((S17*S18)*(1+($C$19*(IF(Drivers!$J$8=0,0,Drivers!$W$8/Drivers!$J$8)-1))))+S20) | T45: =(((T17*T18)*(1+($C$19*(IF(Drivers!$J$8=0,0,Drivers!$X$8/Drivers!$J$8)-1))))+T20) | U45: =(((U17*U18)*(1+($C$19*(IF(Drivers!$J$8=0,0,Drivers!$Y$8/Drivers!$J$8)-1))))+U20) | V45: =(((V17*V18)*(1+($C$19*(IF(Drivers!$J$8=0,0,Drivers!$Z$8/Drivers!$J$8)-1))))+V20) | W45: =(((W17*W18)*(1+($C$19*(IF(Drivers!$J$8=0,0,Drivers!$AA$8/Drivers!$J$8)-1))))+W20) | X45: =(((X17*X18)*(1+($C$19*(IF(Drivers!$J$8=0,0,Drivers!$AB$8/Drivers!$J$8)-1))))+X20) | Y45: =(((Y17*Y18)*(1+($C$19*(IF(Drivers!$J$8=0,0,Drivers!$AC$8/Drivers!$J$8)-1))))+Y20) | Z45: =(((Z17*Z18)*(1+($C$19*(IF(Drivers!$J$8=0,0,Drivers!$AD$8/Drivers!$J$8)-1))))+Z20) | AA45: =(((AA17*AA18)*(1+($C$19*(IF(Drivers!$J$8=0,0,Drivers!$AE$8/Drivers!$J$8)-1))))+AA20) | AB45: =(((AB17*AB18)*(1+($C$19*(IF(Drivers!$J$8=0,0,Drivers!$AF$8/Drivers!$J$8)-1))))+AB20) | AC45: =(((AC17*AC18)*(1+($C$19*(IF(Drivers!$J$8=0,0,Drivers!$AG$8/Drivers!$J$8)-1))))+AC20) | AD45: =(((AD17*AD18)*(1+($C$19*(IF(Drivers!$J$8=0,0,Drivers!$AH$8/Drivers!$J$8)-1))))+AD20) | AE45: =(((AE17*AE18)*(1+($C$19*(IF(Drivers!$J$8=0,0,Drivers!$AI$8/Drivers!$J$8)-1))))+AE20) | AF45: =(((AF17*AF18)*(1+($C$19*(IF(Drivers!$J$8=0,0,Drivers!$AJ$8/Drivers!$J$8)-1))))+AF20)
A46: Strip ratio | B46: strip_ratio_line | G46: 4.5 | H46: =H17 | I46: =I17 | J46: =J17 | K46: =K17 | L46: =L17 | M46: =M17 | N46: =N17 | O46: =O17 | ... AF46: =AF17
A47: Royalty rate | B47: royalty_rate | H47: =H21 | I47: =I21 | J47: =J21 | K47: =K21 | L47: =L21 | M47: =M21 | N47: =N21 | O47: =O21 | ... AF47: =AF21
A48: EBITDA per unit (price currency) | B48: ebitda_per_unit | F48: 23.297168 | G48: 15.726693 | H48: =IF((H41*$C$10)=0,0,H61/(H41*$C$10)) | I48: =IF((I41*$C$10)=0,0,I61/(I41*$C$10)) | J48: =IF((J41*$C$10)=0,0,J61/(J41*$C$10)) | K48: =IF((K41*$C$10)=0,0,K61/(K41*$C$10)) | L48: =IF((L41*$C$10)=0,0,L61/(L41*$C$10)) | M48: =IF((M41*$C$10)=0,0,M61/(M41*$C$10)) | N48: =IF((N41*$C$10)=0,0,N61/(N41*$C$10)) | O48: =IF((O41*$C$10)=0,0,O61/(O41*$C$10)) | ... AF48: =IF((AF41*$C$10)=0,0,AF61/(AF41*$C$10))
A49: Cash cost + royalty per unit (price currency) | B49: cash_cost_money_per_unit | H49: =IF((H41*$C$10)=0,0,(H53+H52)/(H41*$C$10)) | I49: =IF((I41*$C$10)=0,0,(I53+I52)/(I41*$C$10)) | J49: =IF((J41*$C$10)=0,0,(J53+J52)/(J41*$C$10)) | K49: =IF((K41*$C$10)=0,0,(K53+K52)/(K41*$C$10)) | L49: =IF((L41*$C$10)=0,0,(L53+L52)/(L41*$C$10)) | M49: =IF((M41*$C$10)=0,0,(M53+M52)/(M41*$C$10)) | N49: =IF((N41*$C$10)=0,0,(N53+N52)/(N41*$C$10)) | O49: =IF((O41*$C$10)=0,0,(O53+O52)/(O41*$C$10)) | ... AF49: =IF((AF41*$C$10)=0,0,(AF53+AF52)/(AF41*$C$10))
A50: Main product revenue | B50: revenue_main | H50: =((H41*H43)*$C$10) | I50: =((I41*I43)*$C$10) | J50: =((J41*J43)*$C$10) | K50: =((K41*K43)*$C$10) | L50: =((L41*L43)*$C$10) | M50: =((M41*M43)*$C$10) | N50: =((N41*N43)*$C$10) | O50: =((O41*O43)*$C$10) | ... AF50: =((AF41*AF43)*$C$10)
A51: Other revenue | B51: other_revenue | H51: =H22 | I51: =I22 | J51: =J22 | K51: =K22 | L51: =L22 | M51: =M22 | N51: =N22 | O51: =O22 | ... AF51: =AF22
A52: Royalty | B52: royalty | H52: =(H50*H47) | I52: =(I50*I47) | J52: =(J50*J47) | K52: =(K50*K47) | L52: =(L50*L47) | M52: =(M50*M47) | N52: =(N50*N47) | O52: =(O50*O47) | ... AF52: =(AF50*AF47)
A53: Cash costs | B53: cash_cost | H53: =((H41*H45)*$C$10) | I53: =((I41*I45)*$C$10) | J53: =((J41*J45)*$C$10) | K53: =((K41*K45)*$C$10) | L53: =((L41*L45)*$C$10) | M53: =((M41*M45)*$C$10) | N53: =((N41*N45)*$C$10) | O53: =((O41*O45)*$C$10) | ... AF53: =((AF41*AF45)*$C$10)
A54: Cost of other revenue | B54: other_cogs | H54: =(H51*(1-$C$23)) | I54: =(I51*(1-$C$23)) | J54: =(J51*(1-$C$23)) | K54: =(K51*(1-$C$23)) | L54: =(L51*(1-$C$23)) | M54: =(M51*(1-$C$23)) | N54: =(N51*(1-$C$23)) | O54: =(O51*(1-$C$23)) | ... AF54: =(AF51*(1-$C$23))
A55: Revenue | B55: revenue | D55: 4703.622 | E55: 3581.3754 | F55: 3446.215 | G55: 3427.5765 | H55: =(H50+H51) | I55: =(I50+I51) | J55: =(J50+J51) | K55: =(K50+K51) | L55: =(L50+L51) | M55: =(M50+M51) | N55: =(N50+N51) | O55: =(O50+O51) | ... AF55: =(AF50+AF51)
A56: Cost of revenue | B56: cogs | D56: 1543.5532 | E56: 1917.1521 | F56: 2113.4295 | G56: 2321.275 | H56: =(((H53+H52)+H54)+H60) | I56: =(((I53+I52)+I54)+I60) | J56: =(((J53+J52)+J54)+J60) | K56: =(((K53+K52)+K54)+K60) | L56: =(((L53+L52)+L54)+L60) | M56: =(((M53+M52)+M54)+M60) | N56: =(((N53+N52)+N54)+N60) | O56: =(((O53+O52)+O54)+O60) | ... AF56: =(((AF53+AF52)+AF54)+AF60)
A57: Gross profit | B57: gross_profit | D57: 3160.0689 | E57: 1664.2233 | F57: 1332.7855 | G57: 1106.3015 | H57: =(H55-H56) | I57: =(I55-I56) | J57: =(J55-J56) | K57: =(K55-K56) | L57: =(L55-L56) | M57: =(M55-M56) | N57: =(N55-N56) | O57: =(O55-O56) | ... AF57: =(AF55-AF56)
A58: SG&A and other opex | B58: opex | D58: 217.9127 | E58: 57.049163 | F58: 120.05254 | G58: 103.927 | H58: =(H55*H37) | I58: =(I55*I37) | J58: =(J55*J37) | K58: =(K55*K37) | L58: =(L55*L37) | M58: =(M55*M37) | N58: =(N55*N37) | O58: =(O55*O37) | ... AF58: =(AF55*AF37)
A59: EBIT | B59: ebit | D59: 2942.1562 | E59: 1607.1741 | F59: 1212.733 | G59: 1002.3745 | H59: =(H57-H58) | I59: =(I57-I58) | J59: =(J57-J58) | K59: =(K57-K58) | L59: =(L57-L58) | M59: =(M57-M58) | N59: =(N57-N58) | O59: =(O57-O58) | ... AF59: =(AF57-AF58)
A60: Depreciation & amortisation | B60: da | D60: 1.185346 | E60: 1.641577 | F60: 96.567872 | G60: 111.07537 | H60: =((H41*H24)*$C$10) | I60: =((I41*I24)*$C$10) | J60: =((J41*J24)*$C$10) | K60: =((K41*K24)*$C$10) | L60: =((L41*L24)*$C$10) | M60: =((M41*M24)*$C$10) | N60: =((N41*N24)*$C$10) | O60: =((O41*O24)*$C$10) | ... AF60: =((AF41*AF24)*$C$10)
A61: EBITDA | B61: ebitda | D61: 2943.3415 | E61: 1608.8157 | F61: 1309.3008 | G61: 1113.4499 | H61: =(H59+H60) | I61: =(I59+I60) | J61: =(J59+J60) | K61: =(K59+K60) | L61: =(L59+L60) | M61: =(M59+M60) | N61: =(N59+N60) | O61: =(O59+O60) | ... AF61: =(AF59+AF60)
A62: Interest expense | B62: interest_expense | D62: 0.311888 | E62: 4.266055 | F62: 15.012262 | G62: 4.24644 | H62: =(G82*$C$29) | I62: =(H82*$C$29) | J62: =(I82*$C$29) | K62: =(J82*$C$29) | L62: =(K82*$C$29) | M62: =(L82*$C$29) | N62: =(M82*$C$29) | O62: =(N82*$C$29) | ... AF62: =(AE82*$C$29)
A63: Interest income | B63: interest_income | D63: 14.791554 | E63: 25.388234 | F63: 27.805486 | G63: 27.95309 | H63: =(G81*$C$30) | I63: =(H81*$C$30) | J63: =(I81*$C$30) | K63: =(J81*$C$30) | L63: =(K81*$C$30) | M63: =(L81*$C$30) | N63: =(M81*$C$30) | O63: =(N81*$C$30) | ... AF63: =(AE81*$C$30)
A64: Other non-operating | B64: other_nonop | D64: -11.325791 | E64: 4.672217 | F64: -20.003653 | G64: -14.061892 | H64: =H32 | I64: =I32 | J64: =J32 | K64: =K32 | L64: =L32 | M64: =M32 | N64: =N32 | O64: =O32 | ... AF64: =AF32
A65: Profit before tax | B65: pbt | D65: 2945.3101 | E65: 1632.9685 | F65: 1205.5225 | G65: 1012.0193 | H65: =(((H59-H62)+H63)+H64) | I65: =(((I59-I62)+I63)+I64) | J65: =(((J59-J62)+J63)+J64) | K65: =(((K59-K62)+K63)+K64) | L65: =(((L59-L62)+L63)+L64) | M65: =(((M59-M62)+M63)+M64) | N65: =(((N59-N62)+N63)+N64) | O65: =(((O59-O62)+O63)+O64) | ... AF65: =(((AF59-AF62)+AF63)+AF64)
A66: Tax | B66: tax | D66: 643.70451 | E66: 353.38765 | F66: 262.14746 | G66: 227.96808 | H66: =(MAX(H65,0)*H28) | I66: =(MAX(I65,0)*I28) | J66: =(MAX(J65,0)*J28) | K66: =(MAX(K65,0)*K28) | L66: =(MAX(L65,0)*L28) | M66: =(MAX(M65,0)*M28) | N66: =(MAX(N65,0)*N28) | O66: =(MAX(O65,0)*O28) | ... AF66: =(MAX(AF65,0)*AF28)
A67: Net profit (incl. minorities) | B67: np | D67: 2301.6055 | E67: 1279.5808 | F67: 943.37507 | G67: 784.05119 | H67: =(H65-H66) | I67: =(I65-I66) | J67: =(J65-J66) | K67: =(K65-K66) | L67: =(L65-L66) | M67: =(M65-M66) | N67: =(N65-N66) | O67: =(O65-O66) | ... AF67: =(AF65-AF66)
A68: Minority interests | B68: minority | D68: 123.13093 | E68: 40.997756 | F68: 20.732197 | G68: 16.135672 | H68: =(H67*H33) | I68: =(I67*I33) | J68: =(J67*J33) | K68: =(K67*K33) | L68: =(L67*L33) | M68: =(M67*M33) | N68: =(N67*N33) | O68: =(O67*O33) | ... AF68: =(AF67*AF33)
A69: Net profit to parent | B69: np_parent | D69: 2178.4746 | E69: 1238.5831 | F69: 922.64287 | G69: 767.91551 | H69: =(H67-H68) | I69: =(I67-I68) | J69: =(J67-J68) | K69: =(K67-K68) | L69: =(L67-L68) | M69: =(M67-M68) | N69: =(N67-N68) | O69: =(O67-O68) | ... AF69: =(AF67-AF68)
A70: Shares outstanding (m) | B70: shares | D70: 33333.335 | E70: 33333.335 | F70: 33333.335 | G70: 33333.335 | H70: =(G70*(1+H35)) | I70: =(H70*(1+I35)) | J70: =(I70*(1+J35)) | K70: =(J70*(1+K35)) | L70: =(K70*(1+L35)) | M70: =(L70*(1+M35)) | N70: =(M70*(1+N35)) | O70: =(N70*(1+O35)) | ... AF70: =(AE70*(1+AF35))
A71: EPS | B71: eps | D71: 0.065354235 | E71: 0.037157491 | F71: 0.027679285 | G71: 0.023037464 | H71: =(IF(H70=0,0,H69/H70)*$C$8) | I71: =(IF(I70=0,0,I69/I70)*$C$8) | J71: =(IF(J70=0,0,J69/J70)*$C$8) | K71: =(IF(K70=0,0,K69/K70)*$C$8) | L71: =(IF(L70=0,0,L69/L70)*$C$8) | M71: =(IF(M70=0,0,M69/M70)*$C$8) | N71: =(IF(N70=0,0,N69/N70)*$C$8) | O71: =(IF(O70=0,0,O69/O70)*$C$8) | ... AF71: =(IF(AF70=0,0,AF69/AF70)*$C$8)
A72: DPS (declared on the year) | B72: dps | D72: 0.038773893 | E72: 0.017973057 | F72: 0.011861104 | G72: 0.014911297 | H72: =(MAX(H71,0)*H34) | I72: =(MAX(I71,0)*I34) | J72: =(MAX(J71,0)*J34) | K72: =(MAX(K71,0)*K34) | L72: =(MAX(L71,0)*L34) | M72: =(MAX(M71,0)*M34) | N72: =(MAX(N71,0)*N34) | O72: =(MAX(O71,0)*O34) | ... AF72: =(MAX(AF71,0)*AF34)
A73: Dividends paid | B73: dividends_paid | D73: 1000 | E73: 1800.0001 | F73: 800.00004 | G73: 700.00004 | H73: =IF($C$8=0,0,(G72*G70)/$C$8) | I73: =IF($C$8=0,0,(H72*H70)/$C$8) | J73: =IF($C$8=0,0,(I72*I70)/$C$8) | K73: =IF($C$8=0,0,(J72*J70)/$C$8) | L73: =IF($C$8=0,0,(K72*K70)/$C$8) | M73: =IF($C$8=0,0,(L72*L70)/$C$8) | N73: =IF($C$8=0,0,(M72*M70)/$C$8) | O73: =IF($C$8=0,0,(N72*N70)/$C$8) | ... AF73: =IF($C$8=0,0,(AE72*AE70)/$C$8)
A74: Capital expenditure | B74: capex | D74: 198.00014 | E74: 215.76932 | F74: 179.60625 | G74: 170.93365 | H74: =(((H41*H25)*$C$10)+H26) | I74: =(((I41*I25)*$C$10)+I26) | J74: =(((J41*J25)*$C$10)+J26) | K74: =(((K41*K25)*$C$10)+K26) | L74: =(((L41*L25)*$C$10)+L26) | M74: =(((M41*M25)*$C$10)+M26) | N74: =(((N41*N25)*$C$10)+N26) | O74: =(((O41*O25)*$C$10)+O26) | ... AF74: =(((AF41*AF25)*$C$10)+AF26)
A75: Change in working capital | B75: delta_nwc | E75: 1300.1007 | F75: 72.528124 | G75: 215.27605 | H75: =(H80-G80) | I75: =(I80-H80) | J75: =(J80-I80) | K75: =(K80-J80) | L75: =(L80-K80) | M75: =(M80-L80) | N75: =(N80-M80) | O75: =(O80-N80) | ... AF75: =(AF80-AE80)
A76: Free cash flow to firm | B76: fcff | E76: -254.85985 | F76: 793.45104 | G76: 501.44468 | H76: =((((H59*(1-H28))+H60)-H74)-H75) | I76: =((((I59*(1-I28))+I60)-I74)-I75) | J76: =((((J59*(1-J28))+J60)-J74)-J75) | K76: =((((K59*(1-K28))+K60)-K74)-K75) | L76: =((((L59*(1-L28))+L60)-L74)-L75) | M76: =((((M59*(1-M28))+M60)-M74)-M75) | N76: =((((N59*(1-N28))+N60)-N74)-N75) | O76: =((((O59*(1-O28))+O60)-O74)-O75) | ... AF76: =((((AF59*(1-AF28))+AF60)-AF74)-AF75)
A77: Net borrowing | B77: net_borrowing | E77: 396.87432 | F77: -59.332566 | G77: -337.54176 | H77: =H31 | I77: =I31 | J77: =J31 | K77: =K31 | L77: =L31 | M77: =M31 | N77: =N31 | O77: =O31 | ... AF77: =AF31
A78: Dividends to minorities | B78: minority_div | H78: =(MAX(G68,0)*H34) | I78: =(MAX(H68,0)*I34) | J78: =(MAX(I68,0)*J34) | K78: =(MAX(J68,0)*K34) | L78: =(MAX(K68,0)*L34) | M78: =(MAX(L68,0)*M34) | N78: =(MAX(M68,0)*N34) | O78: =(MAX(N68,0)*O34) | ... AF78: =(MAX(AE68,0)*AF34)
A79: Free cash flow to equity | B79: fcfe | H79: =(((((H67+H60)-H74)-H75)+H77)-H78) | I79: =(((((I67+I60)-I74)-I75)+I77)-I78) | J79: =(((((J67+J60)-J74)-J75)+J77)-J78) | K79: =(((((K67+K60)-K74)-K75)+K77)-K78) | L79: =(((((L67+L60)-L74)-L75)+L77)-L78) | M79: =(((((M67+M60)-M74)-M75)+M77)-M78) | N79: =(((((N67+N60)-N74)-N75)+N77)-N78) | O79: =(((((O67+O60)-O74)-O75)+O77)-O78) | ... AF79: =(((((AF67+AF60)-AF74)-AF75)+AF77)-AF78)
A80: Operating working capital | B80: nwc | D80: -1257.9742 | E80: 42.126496 | F80: 114.65462 | G80: 329.93067 | H80: =(H55*H27) | I80: =(I55*I27) | J80: =(J55*J27) | K80: =(K55*K27) | L80: =(L55*L27) | M80: =(M55*M27) | N80: =(N55*N27) | O80: =(O55*O27) | ... AF80: =(AF55*AF27)
