Workbook

Sheet README
A1: Six South — Conglomerates & multi-sector holdings industry model
A2: Generated 2026-10-29T10:26:30+07:00 by the coverage engine. The engine (scripts/cov_engine.py) is the source of truth; this workbook is a live rendering of it.
A3: Colour key: blue = input or hard-coded history; black = formula; green = link to another sheet.
A4: Drivers: every deck variable these models read. Change one and every ticker tab and the Comps sheet recalculate (forecasts, cash flows, DCF value, base-case value, target, rating).
A5: Scenario (bear/bull) and sensitivity tables need full model re-runs and are engine values.
A6: Paper fund — research for education and process transparency, not investment advice.
A8: Tickers:
A9: ABMM.JK — PT ABM Investama Tbk
A10: ADRO.JK — PT Alamtri Resources Indonesia Tbk
A11: ASII.JK — PT Astra International Tbk
A12: BHIT.JK — PT MNC Asia Holding Tbk
A13: BNBR.JK — PT Bakrie & Brothers Tbk
... A20: ZBRA.JK — PT Dosni Roha Indonesia Tbk

Sheet Drivers
A1: Driver decks (state/drivers) — edit a blue cell to flow it through every ticker tab
A3: Variable | B3: Key | C3: Unit / status | D3: FY2021A | E3: FY2022A | F3: FY2023A | G3: FY2024A | H3: FY2024E | I3: FY2025A | J3: FY2025E | K3: FY2026E | L3: FY2027E | M3: FY2028E | N3: FY2029E | O3: FY2030E | P3: FY2031E | Q3: FY2032E | R3: FY2033E | S3: FY2034E | T3: FY2035E
A4: IDR per USD | B4: m.usd_idr | C4: IDR/USD · reviewed | D4: 14310.54 | E4: 14843.177 | F4: 15228.8 | G4: 15846.238 | H4: 19000 | I4: 16448.093 | J4: 19000 | K4: 17570 | L4: 18350 | M4: 18600 | N4: 18850 | O4: 19093.137 | P4: 19186.731 | Q4: 19280.784 | R4: 19375.297 | S4: 19470.274 | T4: 19565.717
A6: Cost-of-capital scalars (macro deck)
A7: 10-year Indonesian government bond yield (IDR) | B7: m.rf_idr | C7: 0.0745 | D7: investor.id — "Yield SUN 7,45%, Saatnya Borong atau Tunggu Lebih Tinggi?" (25 Okt 2026 20:58 WIB; deck source S3); corroborated by kalderanews S1 (10Y SUN 7.41%
A8: 10-year US Treasury yield | B8: m.rf_usd | C8: 0.05045 | D8: Yahoo Finance ^TNX (US 10-year Treasury yield)
A9: Indonesia sovereign default spread (Damodaran) | B9: m.default_spread_id | C9: 0.0162 | D9: Damodaran country risk premiums (https://pages.stern.nyu.edu/~adamodar/New_Home_Page/datafile/ctryprem.html), page dated January 5, 2026, read 2026-10-29
A10: Mature-market equity risk premium (Damodaran) | B10: m.erp_mature | C10: 0.0423 | D10: Damodaran country risk premiums (https://pages.stern.nyu.edu/~adamodar/New_Home_Page/datafile/ctryprem.html), page dated January 5, 2026, read 2026-10-29
A11: Indonesia country risk premium (Damodaran) | B11: m.crp_id | C11: 0.0246 | D11: Damodaran country risk premiums (https://pages.stern.nyu.edu/~adamodar/New_Home_Page/datafile/ctryprem.html), page dated January 5, 2026, read 2026-10-29
A12: House pre-tax corporate debt spread over the risk-free | B12: m.debt_spread_corp | C12: 0.02 | D12: SEED house assumption pending the macro desk: 200 bp over the risk-free rate for an average IDX corporate borrower
A13: Indonesia statutory corporate income tax rate | B13: m.tax_rate_id | C13: 0.22 | D13: Law 7/2021 on Harmonisation of Tax Regulations (UU HPP): 22% corporate income tax from fiscal 2022

Sheet Comps
A1: Ticker | B1: Company | C1: Rating | D1: Target (IDR) | E1: Price (IDR) | F1: Exp. 12m TR | G1: Value today | H1: P/E FY+0 | I1: EV/EBITDA FY+0 | J1: Div. yield FY+0
A2: ABMM.JK | B2: PT ABM Investama Tbk | C2: ='ABMM'!$C$128 | D2: ='ABMM'!$C$126 | E2: ='ABMM'!$C$76 | F2: ='ABMM'!$C$127 | G2: ='ABMM'!$C$116 | H2: 5.148453 | I2: 3.920208 | J2: 0.041236
A3: ADRO.JK | B3: PT Alamtri Resources Indonesia Tbk | C3: ='ADRO'!$C$128 | D3: ='ADRO'!$C$126 | E3: ='ADRO'!$C$76 | F3: ='ADRO'!$C$127 | G3: ='ADRO'!$C$116 | H3: 8.30708 | I3: 4.405562 | J3: 0.120331
A4: ASII.JK | B4: PT Astra International Tbk | C4: ='ASII'!$C$128 | D4: ='ASII'!$C$126 | E4: ='ASII'!$C$76 | F4: ='ASII'!$C$127 | G4: ='ASII'!$C$116 | H4: 5.401133 | I4: 5.201985 | J4: 0.092573
A5: BHIT.JK | B5: PT MNC Asia Holding Tbk | C5: ='BHIT'!$C$128 | D5: ='BHIT'!$C$126 | E5: ='BHIT'!$C$76 | F5: ='BHIT'!$C$127 | G5: ='BHIT'!$C$116 | H5: 8.902137 | I5: 7.317416 | J5: 0
A6: BNBR.JK | B6: PT Bakrie & Brothers Tbk | C6: ='BNBR'!$C$131 | D6: ='BNBR'!$C$129 | E6: ='BNBR'!$C$76 | F6: ='BNBR'!$C$130 | G6: ='BNBR'!$C$110 | I6: 33.24141 | J6: 0
A7: BRPT.JK | B7: PT Barito Pacific Tbk | C7: ='BRPT'!$C$137 | D7: ='BRPT'!$C$135 | E7: ='BRPT'!$C$76 | F7: ='BRPT'!$C$136 | G7: ='BRPT'!$C$116 | H7: 84.339622 | I7: 15.053141 | J7: 0.011857
A8: CUAN.JK | B8: PT Petrindo Jaya Kreasi Tbk | C8: ='CUAN'!$C$131 | D8: ='CUAN'!$C$129 | E8: ='CUAN'!$C$76 | F8: ='CUAN'!$C$130 | G8: ='CUAN'!$C$110 | H8: 1705.7116 | I8: 14.393063 | J8: 1.2e-05
A9: DSSA.JK | B9: PT Dian Swastatika Sentosa Tbk | C9: ='DSSA'!$C$125 | D9: ='DSSA'!$C$123 | E9: ='DSSA'!$C$76 | F9: ='DSSA'!$C$124 | G9: ='DSSA'!$C$104 | H9: 38.835833 | I9: 15.660056 | J9: 0
A10: FOLK.JK | B10: PT Multi Garam Utama Tbk | C10: ='FOLK'!$C$116 | D10: ='FOLK'!$C$114 | E10: ='FOLK'!$C$76 | F10: ='FOLK'!$C$115 | G10: ='FOLK'!$C$104 | J10: 0
A11: IMJS.JK | B11: PT Indomobil Multi Jasa Tbk | C11: ='IMJS'!$C$122 | D11: ='IMJS'!$C$120 | E11: ='IMJS'!$C$76 | F11: ='IMJS'!$C$121 | G11: ='IMJS'!$C$110 | H11: 9.724263 | I11: 12.554759 | J11: 0.002333
A12: TOBA.JK | B12: PT TBS Energi Utama Tbk | C12: ='TOBA'!$C$128 | D12: ='TOBA'!$C$126 | E12: ='TOBA'!$C$76 | F12: ='TOBA'!$C$127 | G12: ='TOBA'!$C$116 | I12: 10.714611 | J12: 0
A13: ZBRA.JK | B13: PT Dosni Roha Indonesia Tbk | C13: ='ZBRA'!$C$116 | D13: ='ZBRA'!$C$114 | E13: ='ZBRA'!$C$76 | F13: ='ZBRA'!$C$115 | G13: ='ZBRA'!$C$104 | I13: 36.065089 | J13: 0

Sheet ABMM
A1: PT ABM Investama Tbk (ABMM.JK) — Conglomerates & multi-sector holdings
A2: Units: USD m; per-share in USD unless marked IDR. Model asof 2026-10-29 · data 2026-10-26
A4: Line | C4: Scalar | D4: FY2022A | E4: FY2023A | F4: FY2024A | G4: FY2025A | H4: FY2026E | I4: FY2027E | J4: FY2028E | K4: FY2029E | L4: FY2030E | M4: FY2031E | N4: FY2032E | O4: FY2033E | P4: FY2034E | Q4: FY2035E
A6: PARAMETERS
A7: ps_factor | C7: 1
A8: vp_factor | C8: 1
A10: INPUTS (company assumptions)
A11: Revenue growth | B11: a.revenue_growth | H11: 0 | I11: 0 | J11: 0 | K11: 0 | L11: 0 | M11: 0 | N11: 0 | O11: 0 | P11: 0 | Q11: 0
A12: Gross margin at base input costs | B12: a.gross_margin | H12: 0.09986 | I12: 0.09986 | J12: 0.09986 | K12: 0.09986 | L12: 0.09986 | M12: 0.09986 | N12: 0.09986 | O12: 0.09986 | P12: 0.09986 | Q12: 0.09986
A13: SG&A / revenue | B13: a.opex_pct | H13: 0.058785 | I13: 0.058785 | J13: 0.058785 | K13: 0.058785 | L13: 0.058785 | M13: 0.058785 | N13: 0.058785 | O13: 0.058785 | P13: 0.058785 | Q13: 0.058785
A14: D&A / revenue | B14: a.da_pct | H14: 0.20379 | I14: 0.20379 | J14: 0.20379 | K14: 0.20379 | L14: 0.20379 | M14: 0.20379 | N14: 0.20379 | O14: 0.20379 | P14: 0.20379 | Q14: 0.20379
A15: Capex / revenue | B15: a.capex_pct | H15: 0.13155 | I15: 0.13155 | J15: 0.13155 | K15: 0.13155 | L15: 0.13155 | M15: 0.13155 | N15: 0.13155 | O15: 0.13155 | P15: 0.13155 | Q15: 0.13155
A16: Operating working capital / revenue | B16: a.nwc_pct | H16: 0.106679 | I16: 0.106679 | J16: 0.106679 | K16: 0.106679 | L16: 0.106679 | M16: 0.106679 | N16: 0.106679 | O16: 0.106679 | P16: 0.106679 | Q16: 0.106679
A17: Effective tax rate | B17: a.tax_rate | H17: 0.059 | I17: 0.059 | J17: 0.059 | K17: 0.059 | L17: 0.059 | M17: 0.059 | N17: 0.059 | O17: 0.059 | P17: 0.059 | Q17: 0.059
A18: Cost of debt (on opening debt) | B18: a.cost_of_debt | C18: 0.075
A19: Yield on opening cash | B19: a.cash_yield | C19: 0.02
A20: Net new borrowing | B20: a.net_borrowing | H20: 0 | I20: 0 | J20: 0 | K20: 0 | L20: 0 | M20: 0 | N20: 0 | O20: 0 | P20: 0 | Q20: 0
A21: Other non-operating items | B21: a.other_nonop | H21: 105.37707 | I21: 105.37707 | J21: 105.37707 | K21: 105.37707 | L21: 105.37707 | M21: 107.48461 | N21: 109.6343 | O21: 111.82699 | P21: 114.06353 | Q21: 116.3448
A22: Minorities' share of net profit | B22: a.minority_pct | H22: 0 | I22: 0 | J22: 0 | K22: 0 | L22: 0 | M22: 0 | N22: 0 | O22: 0 | P22: 0 | Q22: 0
A23: Dividend payout | B23: a.payout | H23: 0.2123 | I23: 0.2123 | J23: 0.2123 | K23: 0.2123 | L23: 0.2123 | M23: 0.2123 | N23: 0.2123 | O23: 0.2123 | P23: 0.2123 | Q23: 0.2123
A24: Change in share count | B24: a.share_change | H24: 0 | I24: 0 | J24: 0 | K24: 0 | L24: 0 | M24: 0 | N24: 0 | O24: 0 | P24: 0 | Q24: 0
A25: Terminal growth (DCF) | B25: a.terminal_growth | C25: 0
A26: Holding-company discount to SOTP | B26: a.holdco_discount | C26: 0.662462
A28: MODEL
A29: Revenue | B29: revenue | D29: 1445.5274 | E29: 1492.9989 | F29: 1200.1325 | G29: 1038.1703 | H29: =(G29*(1+H11)) | I29: =(H29*(1+I11)) | J29: =(I29*(1+J11)) | K29: =(J29*(1+K11)) | L29: =(K29*(1+L11)) | M29: =(L29*(1+M11)) | N29: =(M29*(1+N11)) | O29: =(N29*(1+O11)) | ... Q29: =(P29*(1+Q11))
A30: Cost of revenue | B30: cogs | D30: 923.6231 | E30: 1100.9528 | F30: 1068.9408 | G30: 934.49149 | H30: =(H29*(1-H12)) | I30: =(I29*(1-I12)) | J30: =(J29*(1-J12)) | K30: =(K29*(1-K12)) | L30: =(L29*(1-L12)) | M30: =(M29*(1-M12)) | N30: =(N29*(1-N12)) | O30: =(O29*(1-O12)) | ... Q30: =(Q29*(1-Q12))
A31: Gross profit | B31: gross_profit | D31: 521.90427 | E31: 392.04603 | F31: 131.19162 | G31: 103.67876 | H31: =(H29-H30) | I31: =(I29-I30) | J31: =(J29-J30) | K31: =(K29-K30) | L31: =(L29-L30) | M31: =(M29-M30) | N31: =(N29-N30) | O31: =(O29-O30) | ... Q31: =(Q29-Q30)
A32: SG&A and other opex | B32: opex | D32: 126.17262 | E32: 134.17259 | F32: 57.505347 | G32: 61.024162 | H32: =(H29*H13) | I32: =(I29*I13) | J32: =(J29*J13) | K32: =(K29*K13) | L32: =(L29*L13) | M32: =(M29*M13) | N32: =(N29*N13) | O32: =(O29*O13) | ... Q32: =(Q29*Q13)
A33: EBIT | B33: ebit | D33: 395.73165 | E33: 257.87344 | F33: 73.686271 | G33: 42.6546 | H33: =(H31-H32) | I33: =(I31-I32) | J33: =(J31-J32) | K33: =(K31-K32) | L33: =(L31-L32) | M33: =(M31-M32) | N33: =(N31-N32) | O33: =(O31-O32) | ... Q33: =(Q31-Q32)
A34: Depreciation & amortisation | B34: da | D34: 4.986805 | E34: 5.48014 | F34: 205.07883 | G34: 211.56525 | H34: =(H29*H14) | I34: =(I29*I14) | J34: =(J29*J14) | K34: =(K29*K14) | L34: =(L29*L14) | M34: =(M29*M14) | N34: =(N29*N14) | O34: =(O29*O14) | ... Q34: =(Q29*Q14)
A35: EBITDA | B35: ebitda | D35: 400.71845 | E35: 263.35358 | F35: 278.7651 | G35: 254.21985 | H35: =(H33+H34) | I35: =(I33+I34) | J35: =(J33+J34) | K35: =(K33+K34) | L35: =(L33+L34) | M35: =(M33+M34) | N35: =(N33+N34) | O35: =(O33+O34) | ... Q35: =(Q33+Q34)
A36: Interest expense | B36: interest_expense | D36: 52.481411 | E36: 106.10741 | F36: 109.80308 | G36: 76.554485 | H36: =(G56*$C$18) | I36: =(H56*$C$18) | J36: =(I56*$C$18) | K36: =(J56*$C$18) | L36: =(K56*$C$18) | M36: =(L56*$C$18) | N36: =(M56*$C$18) | O36: =(N56*$C$18) | ... Q36: =(P56*$C$18)
A37: Interest income | B37: interest_income | D37: 2.596132 | E37: 4.812848 | F37: 4.558293 | G37: 4.382377 | H37: =(G55*$C$19) | I37: =(H55*$C$19) | J37: =(I55*$C$19) | K37: =(J55*$C$19) | L37: =(K55*$C$19) | M37: =(L55*$C$19) | N37: =(M55*$C$19) | O37: =(N55*$C$19) | ... Q37: =(P55*$C$19)
A38: Other non-operating | B38: other_nonop | D38: 87.215074 | E38: 214.91204 | F38: 186.38059 | G38: 105.37707 | H38: =H21 | I38: =I21 | J38: =J21 | K38: =K21 | L38: =L21 | M38: =M21 | N38: =N21 | O38: =O21 | ... Q38: =Q21
A39: Profit before tax | B39: pbt | D39: 433.06144 | E39: 371.49092 | F39: 154.82207 | G39: 75.859561 | H39: =(((H33-H36)+H37)+H38) | I39: =(((I33-I36)+I37)+I38) | J39: =(((J33-J36)+J37)+J38) | K39: =(((K33-K36)+K37)+K38) | L39: =(((L33-L36)+L37)+L38) | M39: =(((M33-M36)+M37)+M38) | N39: =(((N33-N36)+N37)+N38) | O39: =(((O33-O36)+O37)+O38) | ... Q39: =(((Q33-Q36)+Q37)+Q38)
A40: Tax | B40: tax | D40: 91.157937 | E40: 55.86703 | F40: 15.480224 | G40: 5.378922 | H40: =(MAX(H39,0)*H17) | I40: =(MAX(I39,0)*I17) | J40: =(MAX(J39,0)*J17) | K40: =(MAX(K39,0)*K17) | L40: =(MAX(L39,0)*L17) | M40: =(MAX(M39,0)*M17) | N40: =(MAX(N39,0)*N17) | O40: =(MAX(O39,0)*O17) | ... Q40: =(MAX(Q39,0)*Q17)
A41: Net profit (incl. minorities) | B41: np | D41: 341.90351 | E41: 315.62389 | F41: 139.34185 | G41: 70.480639 | H41: =(H39-H40) | I41: =(I39-I40) | J41: =(J39-J40) | K41: =(K39-K40) | L41: =(L39-L40) | M41: =(M39-M40) | N41: =(N39-N40) | O41: =(O39-O40) | ... Q41: =(Q39-Q40)
A42: Minority interests | B42: minority | D42: 71.993581 | E42: 26.623336 | F42: -0.026664 | G42: -0.135678 | H42: =(H41*H22) | I42: =(I41*I22) | J42: =(J41*J22) | K42: =(K41*K22) | L42: =(L41*L22) | M42: =(M41*M22) | N42: =(N41*N22) | O42: =(O41*O22) | ... Q42: =(Q41*Q22)
A43: Net profit to parent | B43: np_parent | D43: 269.90993 | E43: 289.00056 | F43: 139.36851 | G43: 70.616317 | H43: =(H41-H42) | I43: =(I41-I42) | J43: =(J41-J42) | K43: =(K41-K42) | L43: =(L41-L42) | M43: =(M41-M42) | N43: =(N41-N42) | O43: =(O41-O42) | ... Q43: =(Q41-Q42)
A44: Shares outstanding (m) | B44: shares | D44: 2753.165 | E44: 2753.165 | F44: 2753.165 | G44: 2753.165 | H44: =(G44*(1+H24)) | I44: =(H44*(1+I24)) | J44: =(I44*(1+J24)) | K44: =(J44*(1+K24)) | L44: =(K44*(1+L24)) | M44: =(L44*(1+M24)) | N44: =(M44*(1+N24)) | O44: =(N44*(1+O24)) | ... Q44: =(P44*(1+Q24))
A45: EPS | B45: eps | D45: 0.098036233 | E45: 0.1049703 | F45: 0.050621199 | G45: 0.025649141 | H45: =(IF(H44=0,0,H43/H44)*$C$7) | I45: =(IF(I44=0,0,I43/I44)*$C$7) | J45: =(IF(J44=0,0,J43/J44)*$C$7) | K45: =(IF(K44=0,0,K43/K44)*$C$7) | L45: =(IF(L44=0,0,L43/L44)*$C$7) | M45: =(IF(M44=0,0,M43/M44)*$C$7) | N45: =(IF(N44=0,0,N43/N44)*$C$7) | O45: =(IF(O44=0,0,O43/O44)*$C$7) | ... Q45: =(IF(Q44=0,0,Q43/Q44)*$C$7)
A46: DPS (declared on the year) | B46: dps | D46: 0.026704052 | E46: 0.018178457 | F46: 0.0093522496 | G46: 0.0054445442 | H46: =(MAX(H45,0)*H23) | I46: =(MAX(I45,0)*I23) | J46: =(MAX(J45,0)*J23) | K46: =(MAX(K45,0)*K23) | L46: =(MAX(L45,0)*L23) | M46: =(MAX(M45,0)*M23) | N46: =(MAX(N45,0)*N23) | O46: =(MAX(O45,0)*O23) | ... Q46: =(MAX(Q45,0)*Q23)
A47: Dividends paid | B47: dividends_paid | D47: 66.504624 | E47: 97.1 | F47: 50.000025 | G47: 25 | H47: =IF($C$7=0,0,(G46*G44)/$C$7) | I47: =IF($C$7=0,0,(H46*H44)/$C$7) | J47: =IF($C$7=0,0,(I46*I44)/$C$7) | K47: =IF($C$7=0,0,(J46*J44)/$C$7) | L47: =IF($C$7=0,0,(K46*K44)/$C$7) | M47: =IF($C$7=0,0,(L46*L44)/$C$7) | N47: =IF($C$7=0,0,(M46*M44)/$C$7) | O47: =IF($C$7=0,0,(N46*N44)/$C$7) | ... Q47: =IF($C$7=0,0,(P46*P44)/$C$7)
A48: Capital expenditure | B48: capex | D48: 282.46125 | E48: 434.77648 | F48: 282.13345 | G48: 136.57573 | H48: =(H29*H15) | I48: =(I29*I15) | J48: =(J29*J15) | K48: =(K29*K15) | L48: =(L29*L15) | M48: =(M29*M15) | N48: =(N29*N15) | O48: =(O29*O15) | ... Q48: =(Q29*Q15)
A49: Change in working capital | B49: delta_nwc | E49: 23.836187 | F49: 28.069927 | G49: -0.521526 | H49: =(H54-G54) | I49: =(I54-H54) | J49: =(J54-I54) | K49: =(K54-J54) | L49: =(L54-K54) | M49: =(M54-L54) | N49: =(N54-M54) | O49: =(O54-N54) | ... Q49: =(Q54-P54)
A50: Free cash flow to firm | B50: fcff | E50: -234.03964 | F50: -38.805959 | G50: 115.14117 | H50: =((((H33*(1-H17))+H34)-H48)-H49) | I50: =((((I33*(1-I17))+I34)-I48)-I49) | J50: =((((J33*(1-J17))+J34)-J48)-J49) | K50: =((((K33*(1-K17))+K34)-K48)-K49) | L50: =((((L33*(1-L17))+L34)-L48)-L49) | M50: =((((M33*(1-M17))+M34)-M48)-M49) | N50: =((((N33*(1-N17))+N34)-N48)-N49) | O50: =((((O33*(1-O17))+O34)-O48)-O49) | ... Q50: =((((Q33*(1-Q17))+Q34)-Q48)-Q49)
A51: Net borrowing | B51: net_borrowing | E51: 101.43444 | F51: -63.846999 | G51: -7.221437 | H51: =H20 | I51: =I20 | J51: =J20 | K51: =K20 | L51: =L20 | M51: =M20 | N51: =N20 | O51: =O20 | ... Q51: =Q20
A52: Dividends to minorities | B52: minority_div | H52: =(MAX(G42,0)*H23) | I52: =(MAX(H42,0)*I23) | J52: =(MAX(I42,0)*J23) | K52: =(MAX(J42,0)*K23) | L52: =(MAX(K42,0)*L23) | M52: =(MAX(L42,0)*M23) | N52: =(MAX(M42,0)*N23) | O52: =(MAX(N42,0)*O23) | ... Q52: =(MAX(P42,0)*Q23)
A53: Free cash flow to equity | B53: fcfe | H53: =(((((H41+H34)-H48)-H49)+H51)-H52) | I53: =(((((I41+I34)-I48)-I49)+I51)-I52) | J53: =(((((J41+J34)-J48)-J49)+J51)-J52) | K53: =(((((K41+K34)-K48)-K49)+K51)-K52) | L53: =(((((L41+L34)-L48)-L49)+L51)-L52) | M53: =(((((M41+M34)-M48)-M49)+M51)-M52) | N53: =(((((N41+N34)-N48)-N49)+N51)-N52) | O53: =(((((O41+O34)-O48)-O49)+O51)-O52) | ... Q53: =(((((Q41+Q34)-Q48)-Q49)+Q51)-Q52)
A54: Operating working capital | B54: nwc | D54: 85.686938 | E54: 109.52312 | F54: 137.59305 | G54: 137.07153 | H54: =(H29*H16) | I54: =(I29*I16) | J54: =(J29*J16) | K54: =(K29*K16) | L54: =(L29*L16) | M54: =(M29*M16) | N54: =(N29*N16) | O54: =(O29*O16) | ... Q54: =(Q29*Q16)
A55: Cash & equivalents | B55: cash | D55: 221.63174 | E55: 188.64392 | F55: 170.31818 | G55: 202.36898 | H55: =(((((((G55+H41)+H34)-H48)-H49)+H51)-H47)-H52) | I55: =(((((((H55+I41)+I34)-I48)-I49)+I51)-I47)-I52) | J55: =(((((((I55+J41)+J34)-J48)-J49)+J51)-J47)-J52) | K55: =(((((((J55+K41)+K34)-K48)-K49)+K51)-K47)-K52) | L55: =(((((((K55+L41)+L34)-L48)-L49)+L51)-L47)-L52) | M55: =(((((((L55+M41)+M34)-M48)-M49)+M51)-M47)-M52) | N55: =(((((((M55+N41)+N34)-N48)-N49)+N51)-N47)-N52) | O55: =(((((((N55+O41)+O34)-O48)-O49)+O51)-O47)-O52) | ... Q55: =(((((((P55+Q41)+Q34)-Q48)-Q49)+Q51)-Q47)-Q52)
A56: Total debt | B56: debt | D56: 938.74204 | E56: 1040.1765 | F56: 976.32949 | G56: 969.10805 | H56: =(G56+H51) | I56: =(H56+I51) | J56: =(I56+J51) | K56: =(J56+K51) | L56: =(K56+L51) | M56: =(L56+M51) | N56: =(M56+N51) | O56: =(N56+O51) | ... Q56: =(P56+Q51)
A57: Fixed assets (net) | B57: ppe | D57: 696.71329 | E57: 848.80805 | F57: 844.1131 | G57: 836.34612 | H57: =((G57+H48)-H34) | I57: =((H57+I48)-I34) | J57: =((I57+J48)-J34) | K57: =((J57+K48)-K34) | L57: =((K57+L48)-L34) | M57: =((L57+M48)-M34) | N57: =((M57+N48)-N34) | O57: =((N57+O48)-O34) | ... Q57: =((P57+Q48)-Q34)
A58: Parent shareholders' equity | B58: equity | D58: 550.36276 | E58: 759.02103 | F58: 841.40373 | G58: 874.70597 | H58: =((G58+H43)-H47) | I58: =((H58+I43)-I47) | J58: =((I58+J43)-J47) | K58: =((J58+K43)-K47) | L58: =((K58+L43)-L47) | M58: =((L58+M43)-M47) | N58: =((M58+N43)-N47) | O58: =((N58+O43)-O47) | ... Q58: =((P58+Q43)-Q47)
A59: Minority interest (balance sheet) | B59: minority_bs | D59: 67.158519 | E59: -0.094066 | F59: 5.851168 | G59: 5.715422 | H59: =((G59+H42)-H52) | I59: =((H59+I42)-I52) | J59: =((I59+J42)-J52) | K59: =((J59+K42)-K52) | L59: =((K59+L42)-L52) | M59: =((L59+M42)-M52) | N59: =((M59+N42)-N52) | O59: =((N59+O42)-O52) | ... Q59: =((P59+Q42)-Q52)
A60: Other assets less other liabilities | B60: other_net | D60: 552.23136 | E60: 652.12837 | F60: 671.56006 | G60: 673.74282 | H60: =G60 | I60: =H60 | J60: =I60 | K60: =J60 | L60: =K60 | M60: =L60 | N60: =M60 | O60: =N60 | ... Q60: =P60
A61: Balance check (should be zero) | B61: bs_check | H61: =((((((H55+H54)+H57)+H60)-H56)-H58)-H59) | I61: =((((((I55+I54)+I57)+I60)-I56)-I58)-I59) | J61: =((((((J55+J54)+J57)+J60)-J56)-J58)-J59) | K61: =((((((K55+K54)+K57)+K60)-K56)-K58)-K59) | L61: =((((((L55+L54)+L57)+L60)-L56)-L58)-L59) | M61: =((((((M55+M54)+M57)+M60)-M56)-M58)-M59) | N61: =((((((N55+N54)+N57)+N60)-N56)-N58)-N59) | O61: =((((((O55+O54)+O57)+O60)-O56)-O58)-O59) | ... Q61: =((((((Q55+Q54)+Q57)+Q60)-Q56)-Q58)-Q59)
A62: Net debt (cash) | B62: net_debt | D62: 717.11031 | E62: 851.53257 | F62: 806.01131 | G62: 766.73908 | H62: =(H56-H55) | I62: =(I56-I55) | J62: =(J56-J55) | K62: =(K56-K55) | L62: =(L56-L55) | M62: =(M56-M55) | N62: =(N56-N55) | O62: =(O56-O55) | ... Q62: =(Q56-Q55)
A63: Book value per share | B63: bvps | D63: 0.19990184 | E63: 0.27569035 | F63: 0.30561326 | G63: 0.31770925 | H63: =(IF(H44=0,0,H58/H44)*$C$7) | I63: =(IF(I44=0,0,I58/I44)*$C$7) | J63: =(IF(J44=0,0,J58/J44)*$C$7) | K63: =(IF(K44=0,0,K58/K44)*$C$7) | L63: =(IF(L44=0,0,L58/L44)*$C$7) | M63: =(IF(M44=0,0,M58/M44)*$C$7) | N63: =(IF(N44=0,0,N58/N44)*$C$7) | O63: =(IF(O44=0,0,O58/O44)*$C$7) | ... Q63: =(IF(Q44=0,0,Q58/Q44)*$C$7)
A64: Revenue growth | B64: revenue_growth | E64: 0.032840253 | F64: -0.19615983 | G64: -0.1349536 | H64: =(IF(G29=0,0,H29/G29)-1) | I64: =(IF(H29=0,0,I29/H29)-1) | J64: =(IF(I29=0,0,J29/I29)-1) | K64: =(IF(J29=0,0,K29/J29)-1) | L64: =(IF(K29=0,0,L29/K29)-1) | M64: =(IF(L29=0,0,M29/L29)-1) | N64: =(IF(M29=0,0,N29/M29)-1) | O64: =(IF(N29=0,0,O29/N29)-1) | ... Q64: =(IF(P29=0,0,Q29/P29)-1)
A65: Gross margin | B65: gross_margin | D65: 0.36104766 | E65: 0.26258964 | F65: 0.10931428 | G65: 0.09986682 | H65: =IF(H29=0,0,H31/H29) | I65: =IF(I29=0,0,I31/I29) | J65: =IF(J29=0,0,J31/J29) | K65: =IF(K29=0,0,K31/K29) | L65: =IF(L29=0,0,L31/L29) | M65: =IF(M29=0,0,M31/M29) | N65: =IF(N29=0,0,N31/N29) | O65: =IF(O29=0,0,O31/O29) | ... Q65: =IF(Q29=0,0,Q31/Q29)
A66: EBITDA margin | B66: ebitda_margin | D66: 0.27721264 | E66: 0.17639235 | F66: 0.23227861 | G66: 0.24487298 | H66: =IF(H29=0,0,H35/H29) | I66: =IF(I29=0,0,I35/I29) | J66: =IF(J29=0,0,J35/J29) | K66: =IF(K29=0,0,K35/K29) | L66: =IF(L29=0,0,L35/L29) | M66: =IF(M29=0,0,M35/M29) | N66: =IF(N29=0,0,N35/N29) | O66: =IF(O29=0,0,O35/O29) | ... Q66: =IF(Q29=0,0,Q35/Q29)
A67: EBIT margin | B67: ebit_margin | D67: 0.27376282 | E67: 0.1727218 | F67: 0.061398449 | G67: 0.041086325 | H67: =IF(H29=0,0,H33/H29) | I67: =IF(I29=0,0,I33/I29) | J67: =IF(J29=0,0,J33/J29) | K67: =IF(K29=0,0,K33/K29) | L67: =IF(L29=0,0,L33/L29) | M67: =IF(M29=0,0,M33/M29) | N67: =IF(N29=0,0,N33/N29) | O67: =IF(O29=0,0,O33/O29) | ... Q67: =IF(Q29=0,0,Q33/Q29)
A68: Net margin | B68: np_margin | D68: 0.18672073 | E68: 0.19357051 | F68: 0.11612761 | G68: 0.068019977 | H68: =IF(H29=0,0,H43/H29) | I68: =IF(I29=0,0,I43/I29) | J68: =IF(J29=0,0,J43/J29) | K68: =IF(K29=0,0,K43/K29) | L68: =IF(L29=0,0,L43/L29) | M68: =IF(M29=0,0,M43/M29) | N68: =IF(N29=0,0,N43/N29) | O68: =IF(O29=0,0,O43/O29) | ... Q68: =IF(Q29=0,0,Q43/Q29)
A69: EPS growth | B69: eps_growth | E69: 0.070729637 | F69: -0.51775694 | G69: -0.49331226 | H69: =(IF(G45=0,0,H45/G45)-1) | I69: =(IF(H45=0,0,I45/H45)-1) | J69: =(IF(I45=0,0,J45/I45)-1) | K69: =(IF(J45=0,0,K45/J45)-1) | L69: =(IF(K45=0,0,L45/K45)-1) | M69: =(IF(L45=0,0,M45/L45)-1) | N69: =(IF(M45=0,0,N45/M45)-1) | O69: =(IF(N45=0,0,O45/N45)-1) | ... Q69: =(IF(P45=0,0,Q45/P45)-1)
A70: ROE | B70: roe | E70: 0.44142987 | F70: 0.1741644 | G70: 0.082298139 | H70: =IF(IF(2=0,0,(H58+G58)/2)=0,0,H43/IF(2=0,0,(H58+G58)/2)) | I70: =IF(IF(2=0,0,(I58+H58)/2)=0,0,I43/IF(2=0,0,(I58+H58)/2)) | J70: =IF(IF(2=0,0,(J58+I58)/2)=0,0,J43/IF(2=0,0,(J58+I58)/2)) | K70: =IF(IF(2=0,0,(K58+J58)/2)=0,0,K43/IF(2=0,0,(K58+J58)/2)) | L70: =IF(IF(2=0,0,(L58+K58)/2)=0,0,L43/IF(2=0,0,(L58+K58)/2)) | M70: =IF(IF(2=0,0,(M58+L58)/2)=0,0,M43/IF(2=0,0,(M58+L58)/2)) | N70: =IF(IF(2=0,0,(N58+M58)/2)=0,0,N43/IF(2=0,0,(N58+M58)/2)) | O70: =IF(IF(2=0,0,(O58+N58)/2)=0,0,O43/IF(2=0,0,(O58+N58)/2)) | ... Q70: =IF(IF(2=0,0,(Q58+P58)/2)=0,0,Q43/IF(2=0,0,(Q58+P58)/2))
A71: Net debt / EBITDA | B71: net_debt_ebitda | D71: 1.7895615 | E71: 3.2334194 | F71: 2.8913637 | G71: 3.0160473 | H71: =IF(H35=0,0,H62/H35) | I71: =IF(I35=0,0,I62/I35) | J71: =IF(J35=0,0,J62/J35) | K71: =IF(K35=0,0,K62/K35) | L71: =IF(L35=0,0,L62/L35) | M71: =IF(M35=0,0,M62/M35) | N71: =IF(N35=0,0,N62/N35) | O71: =IF(O35=0,0,O62/O35) | ... Q71: =IF(Q35=0,0,Q62/Q35)
A72: Payout ratio | B72: payout_ratio | D72: 0.27238962 | E72: 0.17317715 | F72: 0.18474967 | G72: 0.21227004 | H72: =IF(H45=0,0,H46/H45) | I72: =IF(I45=0,0,I46/I45) | J72: =IF(J45=0,0,J46/J45) | K72: =IF(K45=0,0,K46/K45) | L72: =IF(L45=0,0,L46/L45) | M72: =IF(M45=0,0,M46/M45) | N72: =IF(N45=0,0,N46/N45) | O72: =IF(O45=0,0,O46/O45) | ... Q72: =IF(Q45=0,0,Q46/Q45)
A73: Capex / revenue | B73: capex_revenue | D73: 0.1954036 | E73: 0.29121019 | F73: 0.23508526 | G73: 0.13155427 | H73: =IF(H29=0,0,H48/H29) | I73: =IF(I29=0,0,I48/I29) | J73: =IF(J29=0,0,J48/J29) | K73: =IF(K29=0,0,K48/K29) | L73: =IF(L29=0,0,L48/L29) | M73: =IF(M29=0,0,M48/M29) | N73: =IF(N29=0,0,N48/N29) | O73: =IF(O29=0,0,O48/O29) | ... Q73: =IF(Q29=0,0,Q48/Q29)
A75: VALUATION
A76: Last price (IDR) | C76: 2540
A77: Shares outstanding (m) | C77: 2753.165
A78: IDR per USD (spot) | C78: 18183
A79: Debt at balance-sheet date | C79: 922.34325
A80: Cash at balance-sheet date | C80: 217.01947
A81: Minority interest (book) | C81: 6.259814
A82: Associates & investments (book) | C82: 598.52166
A83: Post-balance-sheet & other items (sourced, probability-weighted) | C83: -6.259814
A84: Parent equity at balance-sheet date | C84: 888.41897
A85: Per-share factor | C85: 1
A86: Risk-free rate | C86: =Drivers!$C$8
A87: Less: default spread (IDR only) | C87: 0
A88: Mature ERP + Indonesia CRP | C88: =Drivers!$C$10+Drivers!$C$11
A89: Tax rate | C89: =Drivers!$C$13
A90: Unlevered beta (industry default (config)) | C90: 0.9
A91: Debt / equity (market) | C91: 2
A92: Levered beta | C92: =$C$90*(1+(1-$C$89)*$C$91)
A93: Explicit company premium | C93: 0
A94: Cost of equity | C94: =$C$86-$C$87+$C$92*$C$88+$C$93
A95: Pre-tax cost of debt | C95: =$C$86+Drivers!$C$12
A96: WACC | C96: =1/(1+$C$91)*$C$94+$C$91/(1+$C$91)*$C$95*(1-$C$89)
A97: Terminal growth (capped) | C97: 0
A99: Sum of the parts
A100: Value per share (IDR) — Sum of the parts (engine value) | C100: 2548.2796
A102: P/E
A103: Target multiple (own five-year average) | C103: 3.77447
A104: Metric (LTM, or next-12m DPS for yield) | C104: 70.616317
A105: Value per share (IDR) — P/E | C105: =MAX(0,$C$103*$C$104/$C$77*$C$85*$C$78)
A107: P/BV
A108: Target multiple (own five-year average) | C108: 0.775979
...

Sheet ADRO
A1: PT Alamtri Resources Indonesia Tbk (ADRO.JK) — Conglomerates & multi-sector holdings
A2: Units: USD m; per-share in USD unless marked IDR. Model asof 2026-10-29 · data 2026-10-26
A4: Line | C4: Scalar | D4: FY2022A | E4: FY2023A | F4: FY2024A | G4: FY2025A | H4: FY2026E | I4: FY2027E | J4: FY2028E | K4: FY2029E | L4: FY2030E | M4: FY2031E | N4: FY2032E | O4: FY2033E | P4: FY2034E | Q4: FY2035E
A6: PARAMETERS
A7: ps_factor | C7: 1
A8: vp_factor | C8: 1
A10: INPUTS (company assumptions)
A11: Revenue growth | B11: a.revenue_growth | H11: 0.1 | I11: -0.06 | J11: -0.03 | K11: -0.02 | L11: 0 | M11: 0 | N11: 0 | O11: 0 | P11: 0 | Q11: 0
A12: Gross margin at base input costs | B12: a.gross_margin | H12: 0.339852 | I12: 0.339852 | J12: 0.339852 | K12: 0.339852 | L12: 0.339852 | M12: 0.339852 | N12: 0.339852 | O12: 0.339852 | P12: 0.339852 | Q12: 0.339852
A13: SG&A / revenue | B13: a.opex_pct | H13: 0.057192 | I13: 0.057192 | J13: 0.057192 | K13: 0.057192 | L13: 0.057192 | M13: 0.057192 | N13: 0.057192 | O13: 0.057192 | P13: 0.057192 | Q13: 0.057192
A14: D&A / revenue | B14: a.da_pct | H14: 0.126756 | I14: 0.126756 | J14: 0.126756 | K14: 0.126756 | L14: 0.126756 | M14: 0.126756 | N14: 0.126756 | O14: 0.126756 | P14: 0.126756 | Q14: 0.126756
A15: Capex / revenue | B15: a.capex_pct | H15: 0.177 | I15: 0.16 | J15: 0.15 | K15: 0.14 | L15: 0.14 | M15: 0.14 | N15: 0.14 | O15: 0.14 | P15: 0.14 | Q15: 0.14
A16: Operating working capital / revenue | B16: a.nwc_pct | H16: -0.0927 | I16: -0.0927 | J16: -0.0927 | K16: -0.0927 | L16: -0.0927 | M16: -0.0927 | N16: -0.0927 | O16: -0.0927 | P16: -0.0927 | Q16: -0.0927
A17: Effective tax rate | B17: a.tax_rate | H17: 0.200202 | I17: 0.200202 | J17: 0.200202 | K17: 0.200202 | L17: 0.200202 | M17: 0.200202 | N17: 0.200202 | O17: 0.200202 | P17: 0.200202 | Q17: 0.200202
A18: Cost of debt (on opening debt) | B18: a.cost_of_debt | C18: 0.020375
A19: Yield on opening cash | B19: a.cash_yield | C19: 0.047925
A20: Net new borrowing | B20: a.net_borrowing | H20: 1118.124 | I20: 150 | J20: 150 | K20: 150 | L20: 150 | M20: 153 | N20: 156.06 | O20: 159.1812 | P20: 162.36482 | Q20: 165.61212
A21: Other non-operating items | B21: a.other_nonop | H21: 0 | I21: 0 | J21: 0 | K21: 0 | L21: 0 | M21: 0 | N21: 0 | O21: 0 | P21: 0 | Q21: 0
A22: Minorities' share of net profit | B22: a.minority_pct | H22: 0.086048 | I22: 0.086048 | J22: 0.086048 | K22: 0.086048 | L22: 0.086048 | M22: 0.086048 | N22: 0.086048 | O22: 0.086048 | P22: 0.086048 | Q22: 0.086048
A23: Dividend payout | B23: a.payout | H23: 0.9996 | I23: 0.8 | J23: 0.7 | K23: 0.6 | L23: 0.6 | M23: 0.6 | N23: 0.6 | O23: 0.6 | P23: 0.6 | Q23: 0.6
A24: Change in share count | B24: a.share_change | H24: 0 | I24: 0 | J24: 0 | K24: 0 | L24: 0 | M24: 0 | N24: 0 | O24: 0 | P24: 0 | Q24: 0
A25: Terminal growth (DCF) | B25: a.terminal_growth | C25: 0.02
A26: Holding-company discount to SOTP | B26: a.holdco_discount | C26: 0.3
A28: MODEL
A29: Revenue | B29: revenue | D29: 8102.399 | E29: 2135.412 | F29: 2078.689 | G29: 1874 | H29: =(G29*(1+H11)) | I29: =(H29*(1+I11)) | J29: =(I29*(1+J11)) | K29: =(J29*(1+K11)) | L29: =(K29*(1+L11)) | M29: =(L29*(1+M11)) | N29: =(M29*(1+N11)) | O29: =(N29*(1+O11)) | ... Q29: =(P29*(1+Q11))
A30: Cost of revenue | B30: cogs | D30: 3449.427 | E30: 1267.731 | F30: 1204.69 | G30: 1236.892 | H30: =(H29*(1-H12)) | I30: =(I29*(1-I12)) | J30: =(J29*(1-J12)) | K30: =(K29*(1-K12)) | L30: =(L29*(1-L12)) | M30: =(M29*(1-M12)) | N30: =(N29*(1-N12)) | O30: =(O29*(1-O12)) | ... Q30: =(Q29*(1-Q12))
A31: Gross profit | B31: gross_profit | D31: 4652.972 | E31: 867.681 | F31: 873.999 | G31: 636.636 | H31: =(H29-H30) | I31: =(I29-I30) | J31: =(J29-J30) | K31: =(K29-K30) | L31: =(L29-L30) | M31: =(M29-M30) | N31: =(N29-N30) | O31: =(O29-O30) | ... Q31: =(Q29-Q30)
A32: SG&A and other opex | B32: opex | D32: 375.974 | E32: 93.945 | F32: 140.357 | G32: 107.149 | H32: =(H29*H13) | I32: =(I29*I13) | J32: =(J29*J13) | K32: =(K29*K13) | L32: =(L29*L13) | M32: =(M29*M13) | N32: =(N29*N13) | O32: =(O29*O13) | ... Q32: =(Q29*Q13)
A33: EBIT | B33: ebit | D33: 4276.998 | E33: 773.736 | F33: 733.642 | G33: 529.487 | H33: =(H31-H32) | I33: =(I31-I32) | J33: =(J31-J32) | K33: =(K31-K32) | L33: =(L31-L32) | M33: =(M31-M32) | N33: =(N31-N32) | O33: =(O31-O32) | ... Q33: =(Q31-Q32)
A34: Depreciation & amortisation | B34: da | D34: 6.847 | E34: 4.893 | F34: 210.763 | G34: 237.474 | H34: =(H29*H14) | I34: =(I29*I14) | J34: =(J29*J14) | K34: =(K29*K14) | L34: =(L29*L14) | M34: =(M29*M14) | N34: =(N29*N14) | O34: =(O29*O14) | ... Q34: =(Q29*Q14)
A35: EBITDA | B35: ebitda | D35: 4283.845 | E35: 778.629 | F35: 944.405 | G35: 766.961 | H35: =(H33+H34) | I35: =(I33+I34) | J35: =(J33+J34) | K35: =(K33+K34) | L35: =(L33+L34) | M35: =(M33+M34) | N35: =(N33+N34) | O35: =(O33+O34) | ... Q35: =(Q33+Q34)
A36: Interest expense | B36: interest_expense | D36: 74.744 | E36: 60.059 | F36: 43.773 | G36: 11.814 | H36: =(G56*$C$18) | I36: =(H56*$C$18) | J36: =(I56*$C$18) | K36: =(J56*$C$18) | L36: =(K56*$C$18) | M36: =(L56*$C$18) | N36: =(M56*$C$18) | O36: =(N56*$C$18) | ... Q36: =(P56*$C$18)
A37: Interest income | B37: interest_income | D37: 47.397 | E37: 65.965 | F37: 118.218 | G37: 97.461 | H37: =(G55*$C$19) | I37: =(H55*$C$19) | J37: =(I55*$C$19) | K37: =(J55*$C$19) | L37: =(K55*$C$19) | M37: =(L55*$C$19) | N37: =(M55*$C$19) | O37: =(N55*$C$19) | ... Q37: =(P55*$C$19)
A38: Other non-operating | B38: other_nonop | D38: 226.568 | E38: 38.946 | F38: 1.733 | G38: -2.673 | H38: =H21 | I38: =I21 | J38: =J21 | K38: =K21 | L38: =L21 | M38: =M21 | N38: =N21 | O38: =O21 | ... Q38: =Q21
A39: Profit before tax | B39: pbt | D39: 4476.219 | E39: 818.588 | F39: 809.82 | G39: 612.461 | H39: =(((H33-H36)+H37)+H38) | I39: =(((I33-I36)+I37)+I38) | J39: =(((J33-J36)+J37)+J38) | K39: =(((K33-K36)+K37)+K38) | L39: =(((L33-L36)+L37)+L38) | M39: =(((M33-M36)+M37)+M38) | N39: =(((N33-N36)+N37)+N38) | O39: =(((O33-O36)+O37)+O38) | ... Q39: =(((Q33-Q36)+Q37)+Q38)
A40: Tax | B40: tax | D40: 1645.096 | E40: 165.282 | F40: 172.336 | G40: 122.616 | H40: =(MAX(H39,0)*H17) | I40: =(MAX(I39,0)*I17) | J40: =(MAX(J39,0)*J17) | K40: =(MAX(K39,0)*K17) | L40: =(MAX(L39,0)*L17) | M40: =(MAX(M39,0)*M17) | N40: =(MAX(N39,0)*N17) | O40: =(MAX(O39,0)*O17) | ... Q40: =(MAX(Q39,0)*Q17)
A41: Net profit (incl. minorities) | B41: np | D41: 2831.123 | E41: 1854.878 | F41: 1556.132 | G41: 489.845 | H41: =(H39-H40) | I41: =(I39-I40) | J41: =(J39-J40) | K41: =(K39-K40) | L41: =(L39-L40) | M41: =(M39-M40) | N41: =(N39-N40) | O41: =(O39-O40) | ... Q41: =(Q39-Q40)
A42: Minority interests | B42: minority | D42: 338.043 | E42: 213.441 | F42: 176.119 | G42: 42.151 | H42: =(H41*H22) | I42: =(I41*I22) | J42: =(J41*J22) | K42: =(K41*K22) | L42: =(L41*L22) | M42: =(M41*M22) | N42: =(N41*N22) | O42: =(O41*O22) | ... Q42: =(Q41*Q22)
A43: Net profit to parent | B43: np_parent | D43: 2493.08 | E43: 1641.437 | F43: 1380.013 | G43: 447.69422 | H43: =(H41-H42) | I43: =(I41-I42) | J43: =(J41-J42) | K43: =(K41-K42) | L43: =(L41-L42) | M43: =(M41-M42) | N43: =(N41-N42) | O43: =(O41-O42) | ... Q43: =(Q41-Q42)
A44: Shares outstanding (m) | B44: shares | D44: 30985.962 | E44: 30881.206 | F44: 30244.918 | G44: 28800.494 | H44: =(G44*(1+H24)) | I44: =(H44*(1+I24)) | J44: =(I44*(1+J24)) | K44: =(J44*(1+K24)) | L44: =(K44*(1+L24)) | M44: =(L44*(1+M24)) | N44: =(M44*(1+N24)) | O44: =(N44*(1+O24)) | ... Q44: =(P44*(1+Q24))
A45: EPS | B45: eps | D45: 0.08045837 | E45: 0.053153268 | F45: 0.045627929 | G45: 0.015544671 | H45: =(IF(H44=0,0,H43/H44)*$C$7) | I45: =(IF(I44=0,0,I43/I44)*$C$7) | J45: =(IF(J44=0,0,J43/J44)*$C$7) | K45: =(IF(K44=0,0,K43/K44)*$C$7) | L45: =(IF(L44=0,0,L43/L44)*$C$7) | M45: =(IF(M44=0,0,M43/M44)*$C$7) | N45: =(IF(N44=0,0,N43/N44)*$C$7) | O45: =(IF(O44=0,0,O43/O44)*$C$7) | ... Q45: =(IF(Q44=0,0,Q43/Q44)*$C$7)
A46: DPS (declared on the year) | B46: dps | D46: 0.045832071 | E46: 0.10532094 | F46: 0.01684 | G46: 0.01553 | H46: =(MAX(H45,0)*H23) | I46: =(MAX(I45,0)*I23) | J46: =(MAX(J45,0)*J23) | K46: =(MAX(K45,0)*K23) | L46: =(MAX(L45,0)*L23) | M46: =(MAX(M45,0)*M23) | N46: =(MAX(N45,0)*N23) | O46: =(MAX(O45,0)*O23) | ... Q46: =(MAX(Q45,0)*Q23)
A47: Dividends paid | B47: dividends_paid | D47: 650 | E47: 1000 | F47: 3429.396 | G47: 447.5 | H47: =IF($C$7=0,0,(G46*G44)/$C$7) | I47: =IF($C$7=0,0,(H46*H44)/$C$7) | J47: =IF($C$7=0,0,(I46*I44)/$C$7) | K47: =IF($C$7=0,0,(J46*J44)/$C$7) | L47: =IF($C$7=0,0,(K46*K44)/$C$7) | M47: =IF($C$7=0,0,(L46*L44)/$C$7) | N47: =IF($C$7=0,0,(M46*M44)/$C$7) | O47: =IF($C$7=0,0,(N46*N44)/$C$7) | ... Q47: =IF($C$7=0,0,(P46*P44)/$C$7)
A48: Capital expenditure | B48: capex | D48: 403.609 | E48: 587.773 | F48: 837.466 | G48: 797 | H48: =(H29*H15) | I48: =(I29*I15) | J48: =(J29*J15) | K48: =(K29*K15) | L48: =(L29*L15) | M48: =(M29*M15) | N48: =(N29*N15) | O48: =(O29*O15) | ... Q48: =(Q29*Q15)
A49: Change in working capital | B49: delta_nwc | E49: 880.845 | F49: 227.434 | G49: -157.17 | H49: =(H54-G54) | I49: =(I54-H54) | J49: =(J54-I54) | K49: =(K54-J54) | L49: =(L54-K54) | M49: =(M54-L54) | N49: =(N54-M54) | O49: =(O54-N54) | ... Q49: =(Q54-P54)
A50: Free cash flow to firm | B50: fcff | E50: -846.21488 | F50: -276.61973 | G50: 21.126572 | H50: =((((H33*(1-H17))+H34)-H48)-H49) | I50: =((((I33*(1-I17))+I34)-I48)-I49) | J50: =((((J33*(1-J17))+J34)-J48)-J49) | K50: =((((K33*(1-K17))+K34)-K48)-K49) | L50: =((((L33*(1-L17))+L34)-L48)-L49) | M50: =((((M33*(1-M17))+M34)-M48)-M49) | N50: =((((N33*(1-N17))+N34)-N48)-N49) | O50: =((((O33*(1-O17))+O34)-O48)-O49) | ... Q50: =((((Q33*(1-Q17))+Q34)-Q48)-Q49)
A51: Net borrowing | B51: net_borrowing | E51: -143.389 | F51: -859.411 | G51: 241.419 | H51: =H20 | I51: =I20 | J51: =J20 | K51: =K20 | L51: =L20 | M51: =M20 | N51: =N20 | O51: =O20 | ... Q51: =Q20
A52: Dividends to minorities | B52: minority_div | H52: =(MAX(G42,0)*H23) | I52: =(MAX(H42,0)*I23) | J52: =(MAX(I42,0)*J23) | K52: =(MAX(J42,0)*K23) | L52: =(MAX(K42,0)*L23) | M52: =(MAX(L42,0)*M23) | N52: =(MAX(M42,0)*N23) | O52: =(MAX(N42,0)*O23) | ... Q52: =(MAX(P42,0)*Q23)
A53: Free cash flow to equity | B53: fcfe | H53: =(((((H41+H34)-H48)-H49)+H51)-H52) | I53: =(((((I41+I34)-I48)-I49)+I51)-I52) | J53: =(((((J41+J34)-J48)-J49)+J51)-J52) | K53: =(((((K41+K34)-K48)-K49)+K51)-K52) | L53: =(((((L41+L34)-L48)-L49)+L51)-L52) | M53: =(((((M41+M34)-M48)-M49)+M51)-M52) | N53: =(((((N41+N34)-N48)-N49)+N51)-N52) | O53: =(((((O41+O34)-O48)-O49)+O51)-O52) | ... Q53: =(((((Q41+Q34)-Q48)-Q49)+Q51)-Q52)
A54: Operating working capital | B54: nwc | D54: -1124.784 | E54: -243.939 | F54: -16.505 | G54: -173.675 | H54: =(H29*H16) | I54: =(I29*I16) | J54: =(J29*J16) | K54: =(K29*K16) | L54: =(L29*L16) | M54: =(M29*M16) | N54: =(N29*N16) | O54: =(O29*O16) | ... Q54: =(Q29*Q16)
A55: Cash & equivalents | B55: cash | D55: 4172.281 | E55: 3359.503 | F55: 2033.611 | G55: 1580.309 | H55: =(((((((G55+H41)+H34)-H48)-H49)+H51)-H47)-H52) | I55: =(((((((H55+I41)+I34)-I48)-I49)+I51)-I47)-I52) | J55: =(((((((I55+J41)+J34)-J48)-J49)+J51)-J47)-J52) | K55: =(((((((J55+K41)+K34)-K48)-K49)+K51)-K47)-K52) | L55: =(((((((K55+L41)+L34)-L48)-L49)+L51)-L47)-L52) | M55: =(((((((L55+M41)+M34)-M48)-M49)+M51)-M47)-M52) | N55: =(((((((M55+N41)+N34)-N48)-N49)+N51)-N47)-N52) | O55: =(((((((N55+O41)+O34)-O48)-O49)+O51)-O47)-O52) | ... Q55: =(((((((P55+Q41)+Q34)-Q48)-Q49)+Q51)-Q47)-Q52)
A56: Total debt | B56: debt | D56: 1582.645 | E56: 1439.256 | F56: 579.845 | G56: 821.264 | H56: =(G56+H51) | I56: =(H56+I51) | J56: =(I56+J51) | K56: =(J56+K51) | L56: =(K56+L51) | M56: =(L56+M51) | N56: =(M56+N51) | O56: =(N56+O51) | ... Q56: =(P56+Q51)
A57: Fixed assets (net) | B57: ppe | D57: 2485.251 | E57: 2748.958 | F57: 2076.5 | G57: 2901.523 | H57: =((G57+H48)-H34) | I57: =((H57+I48)-I34) | J57: =((I57+J48)-J34) | K57: =((J57+K48)-K34) | L57: =((K57+L48)-L34) | M57: =((L57+M48)-M34) | N57: =((M57+N48)-N34) | O57: =((N57+O48)-O34) | ... Q57: =((P57+Q48)-Q34)
A58: Parent shareholders' equity | B58: equity | D58: 6024.6 | E58: 6772.664 | F58: 4926.856 | G58: 4485.423 | H58: =((G58+H43)-H47) | I58: =((H58+I43)-I47) | J58: =((I58+J43)-J47) | K58: =((J58+K43)-K47) | L58: =((K58+L43)-L47) | M58: =((L58+M43)-M47) | N58: =((M58+N43)-N47) | O58: =((N58+O43)-O47) | ... Q58: =((P58+Q43)-Q47)
A59: Minority interest (balance sheet) | B59: minority_bs | D59: 502.738 | E59: 636.086 | F59: 443.976 | G59: 518.53 | H59: =((G59+H42)-H52) | I59: =((H59+I42)-I52) | J59: =((I59+J42)-J52) | K59: =((J59+K42)-K52) | L59: =((K59+L42)-L52) | M59: =((L59+M42)-M52) | N59: =((M59+N42)-N52) | O59: =((N59+O42)-O52) | ... Q59: =((P59+Q42)-Q52)
A60: Other assets less other liabilities | B60: other_net | D60: 2577.235 | E60: 2983.484 | F60: 1857.071 | G60: 1517.06 | H60: =G60 | I60: =H60 | J60: =I60 | K60: =J60 | L60: =K60 | M60: =L60 | N60: =M60 | O60: =N60 | ... Q60: =P60
A61: Balance check (should be zero) | B61: bs_check | H61: =((((((H55+H54)+H57)+H60)-H56)-H58)-H59) | I61: =((((((I55+I54)+I57)+I60)-I56)-I58)-I59) | J61: =((((((J55+J54)+J57)+J60)-J56)-J58)-J59) | K61: =((((((K55+K54)+K57)+K60)-K56)-K58)-K59) | L61: =((((((L55+L54)+L57)+L60)-L56)-L58)-L59) | M61: =((((((M55+M54)+M57)+M60)-M56)-M58)-M59) | N61: =((((((N55+N54)+N57)+N60)-N56)-N58)-N59) | O61: =((((((O55+O54)+O57)+O60)-O56)-O58)-O59) | ... Q61: =((((((Q55+Q54)+Q57)+Q60)-Q56)-Q58)-Q59)
A62: Net debt (cash) | B62: net_debt | D62: -2589.636 | E62: -1920.247 | F62: -1453.766 | G62: -759.045 | H62: =(H56-H55) | I62: =(I56-I55) | J62: =(J56-J55) | K62: =(K56-K55) | L62: =(L56-L55) | M62: =(M56-M55) | N62: =(N56-N55) | O62: =(O56-O55) | ... Q62: =(Q56-Q55)
A63: Book value per share | B63: bvps | D63: 0.19442998 | E63: 0.21931346 | F63: 0.16289864 | G63: 0.15574118 | H63: =(IF(H44=0,0,H58/H44)*$C$7) | I63: =(IF(I44=0,0,I58/I44)*$C$7) | J63: =(IF(J44=0,0,J58/J44)*$C$7) | K63: =(IF(K44=0,0,K58/K44)*$C$7) | L63: =(IF(L44=0,0,L58/L44)*$C$7) | M63: =(IF(M44=0,0,M58/M44)*$C$7) | N63: =(IF(N44=0,0,N58/N44)*$C$7) | O63: =(IF(O44=0,0,O58/O44)*$C$7) | ... Q63: =(IF(Q44=0,0,Q58/Q44)*$C$7)
A64: Revenue growth | B64: revenue_growth | E64: -0.73644695 | F64: -0.026563024 | G64: -0.098470238 | H64: =(IF(G29=0,0,H29/G29)-1) | I64: =(IF(H29=0,0,I29/H29)-1) | J64: =(IF(I29=0,0,J29/I29)-1) | K64: =(IF(J29=0,0,K29/J29)-1) | L64: =(IF(K29=0,0,L29/K29)-1) | M64: =(IF(L29=0,0,M29/L29)-1) | N64: =(IF(M29=0,0,N29/M29)-1) | O64: =(IF(N29=0,0,O29/N29)-1) | ... Q64: =(IF(P29=0,0,Q29/P29)-1)
A65: Gross margin | B65: gross_margin | D65: 0.5742709 | E65: 0.40632955 | F65: 0.42045684 | G65: 0.33972038 | H65: =IF(H29=0,0,H31/H29) | I65: =IF(I29=0,0,I31/I29) | J65: =IF(J29=0,0,J31/J29) | K65: =IF(K29=0,0,K31/K29) | L65: =IF(L29=0,0,L31/L29) | M65: =IF(M29=0,0,M31/M29) | N65: =IF(N29=0,0,N31/N29) | O65: =IF(O29=0,0,O31/O29) | ... Q65: =IF(Q29=0,0,Q31/Q29)
A66: EBITDA margin | B66: ebitda_margin | D66: 0.52871316 | E66: 0.36462706 | F66: 0.45432722 | G66: 0.40926414 | H66: =IF(H29=0,0,H35/H29) | I66: =IF(I29=0,0,I35/I29) | J66: =IF(J29=0,0,J35/J29) | K66: =IF(K29=0,0,K35/K29) | L66: =IF(L29=0,0,L35/L29) | M66: =IF(M29=0,0,M35/M29) | N66: =IF(N29=0,0,N35/N29) | O66: =IF(O29=0,0,O35/O29) | ... Q66: =IF(Q29=0,0,Q35/Q29)
A67: EBIT margin | B67: ebit_margin | D67: 0.5278681 | E67: 0.3623357 | F67: 0.35293495 | G67: 0.28254376 | H67: =IF(H29=0,0,H33/H29) | I67: =IF(I29=0,0,I33/I29) | J67: =IF(J29=0,0,J33/J29) | K67: =IF(K29=0,0,K33/K29) | L67: =IF(L29=0,0,L33/L29) | M67: =IF(M29=0,0,M33/M29) | N67: =IF(N29=0,0,N33/N29) | O67: =IF(O29=0,0,O33/O29) | ... Q67: =IF(Q29=0,0,Q33/Q29)
A68: Net margin | B68: np_margin | D68: 0.30769652 | E68: 0.76867462 | F68: 0.66388623 | G68: 0.23889766 | H68: =IF(H29=0,0,H43/H29) | I68: =IF(I29=0,0,I43/I29) | J68: =IF(J29=0,0,J43/J29) | K68: =IF(K29=0,0,K43/K29) | L68: =IF(L29=0,0,L43/L29) | M68: =IF(M29=0,0,M43/M29) | N68: =IF(N29=0,0,N43/N29) | O68: =IF(O29=0,0,O43/O29) | ... Q68: =IF(Q29=0,0,Q43/Q29)
A69: EPS growth | B69: eps_growth | E69: -0.33936932 | F69: -0.14157809 | G69: -0.65931675 | H69: =(IF(G45=0,0,H45/G45)-1) | I69: =(IF(H45=0,0,I45/H45)-1) | J69: =(IF(I45=0,0,J45/I45)-1) | K69: =(IF(J45=0,0,K45/J45)-1) | L69: =(IF(K45=0,0,L45/K45)-1) | M69: =(IF(L45=0,0,M45/L45)-1) | N69: =(IF(M45=0,0,N45/M45)-1) | O69: =(IF(N45=0,0,O45/N45)-1) | ... Q69: =(IF(P45=0,0,Q45/P45)-1)
A70: ROE | B70: roe | E70: 0.25652936 | F70: 0.23590934 | G70: 0.095129823 | H70: =IF(IF(2=0,0,(H58+G58)/2)=0,0,H43/IF(2=0,0,(H58+G58)/2)) | I70: =IF(IF(2=0,0,(I58+H58)/2)=0,0,I43/IF(2=0,0,(I58+H58)/2)) | J70: =IF(IF(2=0,0,(J58+I58)/2)=0,0,J43/IF(2=0,0,(J58+I58)/2)) | K70: =IF(IF(2=0,0,(K58+J58)/2)=0,0,K43/IF(2=0,0,(K58+J58)/2)) | L70: =IF(IF(2=0,0,(L58+K58)/2)=0,0,L43/IF(2=0,0,(L58+K58)/2)) | M70: =IF(IF(2=0,0,(M58+L58)/2)=0,0,M43/IF(2=0,0,(M58+L58)/2)) | N70: =IF(IF(2=0,0,(N58+M58)/2)=0,0,N43/IF(2=0,0,(N58+M58)/2)) | O70: =IF(IF(2=0,0,(O58+N58)/2)=0,0,O43/IF(2=0,0,(O58+N58)/2)) | ... Q70: =IF(IF(2=0,0,(Q58+P58)/2)=0,0,Q43/IF(2=0,0,(Q58+P58)/2))
A71: Net debt / EBITDA | B71: net_debt_ebitda | D71: -0.60451207 | E71: -2.4661899 | F71: -1.5393459 | G71: -0.98967875 | H71: =IF(H35=0,0,H62/H35) | I71: =IF(I35=0,0,I62/I35) | J71: =IF(J35=0,0,J62/J35) | K71: =IF(K35=0,0,K62/K35) | L71: =IF(L35=0,0,L62/L35) | M71: =IF(M35=0,0,M62/M35) | N71: =IF(N35=0,0,N62/N35) | O71: =IF(O35=0,0,O62/O35) | ... Q71: =IF(Q35=0,0,Q62/Q35)
A72: Payout ratio | B72: payout_ratio | D72: 0.56963708 | E72: 1.9814574 | F72: 0.36907219 | G72: 0.99905617 | H72: =IF(H45=0,0,H46/H45) | I72: =IF(I45=0,0,I46/I45) | J72: =IF(J45=0,0,J46/J45) | K72: =IF(K45=0,0,K46/K45) | L72: =IF(L45=0,0,L46/L45) | M72: =IF(M45=0,0,M46/M45) | N72: =IF(N45=0,0,N46/N45) | O72: =IF(O45=0,0,O46/O45) | ... Q72: =IF(Q45=0,0,Q46/Q45)
A73: Capex / revenue | B73: capex_revenue | D73: 0.049813518 | E73: 0.2752504 | F73: 0.40288182 | G73: 0.42529349 | H73: =IF(H29=0,0,H48/H29) | I73: =IF(I29=0,0,I48/I29) | J73: =IF(J29=0,0,J48/J29) | K73: =IF(K29=0,0,K48/K29) | L73: =IF(L29=0,0,L48/L29) | M73: =IF(M29=0,0,M48/M29) | N73: =IF(N29=0,0,N48/N29) | O73: =IF(O29=0,0,O48/O29) | ... Q73: =IF(Q29=0,0,Q48/Q29)
A75: VALUATION
A76: Last price (IDR) | C76: 2460
A77: Shares outstanding (m) | C77: 28800.494
A78: IDR per USD (spot) | C78: 18183
A79: Debt at balance-sheet date | C79: 1939.388
A80: Cash at balance-sheet date | C80: 1587.927
A81: Minority interest (book) | C81: 518.405
A82: Associates & investments (book) | C82: 696.758
A83: Post-balance-sheet & other items (sourced, probability-weighted) | C83: 0
A84: Parent equity at balance-sheet date | C84: 4609.002
A85: Per-share factor | C85: 1
A86: Risk-free rate | C86: =Drivers!$C$8
A87: Less: default spread (IDR only) | C87: 0
A88: Mature ERP + Indonesia CRP | C88: =Drivers!$C$10+Drivers!$C$11
A89: Tax rate | C89: =Drivers!$C$13
A90: Unlevered beta (industry default (config)) | C90: 0.9
A91: Debt / equity (market) | C91: 0.49773158
A92: Levered beta | C92: =$C$90*(1+(1-$C$89)*$C$91)
A93: Explicit company premium | C93: 0
A94: Cost of equity | C94: =$C$86-$C$87+$C$92*$C$88+$C$93
A95: Pre-tax cost of debt | C95: =$C$86+Drivers!$C$12
A96: WACC | C96: =1/(1+$C$91)*$C$94+$C$91/(1+$C$91)*$C$95*(1-$C$89)
A97: Terminal growth (capped) | C97: 0.02
A99: Sum of the parts
A100: Value per share (IDR) — Sum of the parts (engine value) | C100: 2390.5378
A102: P/E
A103: Target multiple (own five-year average) | C103: 4.069228
A104: Metric (LTM, or next-12m DPS for yield) | C104: 447.69422
A105: Value per share (IDR) — P/E | C105: =MAX(0,$C$103*$C$104/$C$77*$C$85*$C$78)
A107: P/BV
A108: Target multiple (own five-year average) | C108: 0.901424
...

Sheet ASII
A1: PT Astra International Tbk (ASII.JK) — Conglomerates & multi-sector holdings
A2: Units: IDR bn; per-share in IDR unless marked IDR. Model asof 2026-10-29 · data 2026-10-26
A4: Line | C4: Scalar | D4: FY2022A | E4: FY2023A | F4: FY2024A | G4: FY2025A | H4: FY2026E | I4: FY2027E | J4: FY2028E | K4: FY2029E | L4: FY2030E | M4: FY2031E | N4: FY2032E | O4: FY2033E | P4: FY2034E | Q4: FY2035E
A6: PARAMETERS
A7: ps_factor | C7: 1000
A8: vp_factor | C8: 1
A10: INPUTS (company assumptions)
A11: Revenue growth | B11: a.revenue_growth | H11: 0.01 | I11: 0.05 | J11: 0.05 | K11: 0.05 | L11: 0.05 | M11: 0.05 | N11: 0.05 | O11: 0.05 | P11: 0.05 | Q11: 0.05
A12: Gross margin at base input costs | B12: a.gross_margin | H12: 0.2169 | I12: 0.220925 | J12: 0.220925 | K12: 0.220925 | L12: 0.220925 | M12: 0.220925 | N12: 0.220925 | O12: 0.220925 | P12: 0.220925 | Q12: 0.220925
A13: SG&A / revenue | B13: a.opex_pct | H13: 0.1112 | I13: 0.1084 | J13: 0.1084 | K13: 0.1084 | L13: 0.1084 | M13: 0.1084 | N13: 0.1084 | O13: 0.1084 | P13: 0.1084 | Q13: 0.1084
A14: D&A / revenue | B14: a.da_pct | H14: 0.055261 | I14: 0.055261 | J14: 0.055261 | K14: 0.055261 | L14: 0.055261 | M14: 0.055261 | N14: 0.055261 | O14: 0.055261 | P14: 0.055261 | Q14: 0.055261
A15: Capex / revenue | B15: a.capex_pct | H15: 0.053928 | I15: 0.053928 | J15: 0.053928 | K15: 0.053928 | L15: 0.053928 | M15: 0.053928 | N15: 0.053928 | O15: 0.053928 | P15: 0.053928 | Q15: 0.053928
A16: Operating working capital / revenue | B16: a.nwc_pct | H16: 0.140455 | I16: 0.140455 | J16: 0.140455 | K16: 0.140455 | L16: 0.140455 | M16: 0.140455 | N16: 0.140455 | O16: 0.140455 | P16: 0.140455 | Q16: 0.140455
A17: Effective tax rate | B17: a.tax_rate | H17: 0.184904 | I17: 0.184904 | J17: 0.184904 | K17: 0.184904 | L17: 0.184904 | M17: 0.184904 | N17: 0.184904 | O17: 0.184904 | P17: 0.184904 | Q17: 0.184904
A18: Cost of debt (on opening debt) | B18: a.cost_of_debt | C18: 0.040635
A19: Yield on opening cash | B19: a.cash_yield | C19: 0.067378
A20: Net new borrowing | B20: a.net_borrowing | H20: 0 | I20: 0 | J20: 0 | K20: 0 | L20: 0 | M20: 0 | N20: 0 | O20: 0 | P20: 0 | Q20: 0
A21: Other non-operating items | B21: a.other_nonop | H21: 11548 | I21: 10702 | J21: 10702 | K21: 10702 | L21: 10702 | M21: 10969.55 | N21: 11243.789 | O21: 11524.883 | P21: 11813.006 | Q21: 12108.331
A22: Minorities' share of net profit | B22: a.minority_pct | H22: 0.095 | I22: 0.115 | J22: 0.12 | K22: 0.12 | L22: 0.12 | M22: 0.12 | N22: 0.12 | O22: 0.12 | P22: 0.12 | Q22: 0.12
A23: Dividend payout | B23: a.payout | H23: 0.5 | I23: 0.5 | J23: 0.5 | K23: 0.5 | L23: 0.5 | M23: 0.5 | N23: 0.5 | O23: 0.5 | P23: 0.5 | Q23: 0.5
A24: Change in share count | B24: a.share_change | H24: -0.013 | I24: 0 | J24: 0 | K24: 0 | L24: 0 | M24: 0 | N24: 0 | O24: 0 | P24: 0 | Q24: 0
A25: Terminal growth (DCF) | B25: a.terminal_growth | C25: 0.04
A26: Holding-company discount to SOTP | B26: a.holdco_discount | C26: 0.25
A28: MODEL
A29: Revenue | B29: revenue | D29: 301379 | E29: 316565 | F29: 328480 | G29: 323392 | H29: =(G29*(1+H11)) | I29: =(H29*(1+I11)) | J29: =(I29*(1+J11)) | K29: =(J29*(1+K11)) | L29: =(K29*(1+L11)) | M29: =(L29*(1+M11)) | N29: =(M29*(1+N11)) | O29: =(N29*(1+O11)) | ... Q29: =(P29*(1+Q11))
A30: Cost of revenue | B30: cogs | D30: 231291 | E30: 243255 | F30: 255421 | G30: 251948 | H30: =(H29*(1-H12)) | I30: =(I29*(1-I12)) | J30: =(J29*(1-J12)) | K30: =(K29*(1-K12)) | L30: =(L29*(1-L12)) | M30: =(M29*(1-M12)) | N30: =(N29*(1-N12)) | O30: =(O29*(1-O12)) | ... Q30: =(Q29*(1-Q12))
A31: Gross profit | B31: gross_profit | D31: 70088 | E31: 73310 | F31: 73059 | G31: 71444 | H31: =(H29-H30) | I31: =(I29-I30) | J31: =(J29-J30) | K31: =(K29-K30) | L31: =(L29-L30) | M31: =(M29-M30) | N31: =(N29-N30) | O31: =(O29-O30) | ... Q31: =(Q29-Q30)
A32: SG&A and other opex | B32: opex | D32: 27887 | E32: 29042 | F32: 30659 | G32: 32779 | H32: =(H29*H13) | I32: =(I29*I13) | J32: =(J29*J13) | K32: =(K29*K13) | L32: =(L29*L13) | M32: =(M29*M13) | N32: =(N29*N13) | O32: =(O29*O13) | ... Q32: =(Q29*Q13)
A33: EBIT | B33: ebit | D33: 42201 | E33: 44268 | F33: 42400 | G33: 38665 | H33: =(H31-H32) | I33: =(I31-I32) | J33: =(J31-J32) | K33: =(K31-K32) | L33: =(L31-L32) | M33: =(M31-M32) | N33: =(N31-N32) | O33: =(O31-O32) | ... Q33: =(Q31-Q32)
A34: Depreciation & amortisation | B34: da | F34: 16696 | G34: 17871 | H34: =(H29*H14) | I34: =(I29*I14) | J34: =(J29*J14) | K34: =(K29*K14) | L34: =(L29*L14) | M34: =(M29*M14) | N34: =(N29*N14) | O34: =(O29*O14) | ... Q34: =(Q29*Q14)
A35: EBITDA | B35: ebitda | F35: 59096 | G35: 56536 | H35: =(H33+H34) | I35: =(I33+I34) | J35: =(J33+J34) | K35: =(K33+K34) | L35: =(L33+L34) | M35: =(M33+M34) | N35: =(N33+N34) | O35: =(O33+O34) | ... Q35: =(Q33+Q34)
A36: Interest expense | B36: interest_expense | D36: 2107 | E36: 3112 | F36: 3808 | G36: 3734 | H36: =(G56*$C$18) | I36: =(H56*$C$18) | J36: =(I56*$C$18) | K36: =(J56*$C$18) | L36: =(K56*$C$18) | M36: =(L56*$C$18) | N36: =(M56*$C$18) | O36: =(N56*$C$18) | ... Q36: =(P56*$C$18)
A37: Interest income | B37: interest_income | D37: 2535 | E37: 3053 | F37: 3289 | G37: 3655 | H37: =(G55*$C$19) | I37: =(H55*$C$19) | J37: =(I55*$C$19) | K37: =(J55*$C$19) | L37: =(K55*$C$19) | M37: =(L55*$C$19) | N37: =(M55*$C$19) | O37: =(N55*$C$19) | ... Q37: =(P55*$C$19)
A38: Other non-operating | B38: other_nonop | D38: 7761 | E38: 10520 | F38: 11120 | G38: 10702 | H38: =H21 | I38: =I21 | J38: =J21 | K38: =K21 | L38: =L21 | M38: =M21 | N38: =N21 | O38: =O21 | ... Q38: =Q21
A39: Profit before tax | B39: pbt | D39: 50390 | E39: 54729 | F39: 53001 | G39: 49288 | H39: =(((H33-H36)+H37)+H38) | I39: =(((I33-I36)+I37)+I38) | J39: =(((J33-J36)+J37)+J38) | K39: =(((K33-K36)+K37)+K38) | L39: =(((L33-L36)+L37)+L38) | M39: =(((M33-M36)+M37)+M38) | N39: =(((N33-N36)+N37)+N38) | O39: =(((O33-O36)+O37)+O38) | ... Q39: =(((Q33-Q36)+Q37)+Q38)
A40: Tax | B40: tax | D40: 9970 | E40: 10228 | F40: 9728 | G40: 9083 | H40: =(MAX(H39,0)*H17) | I40: =(MAX(I39,0)*I17) | J40: =(MAX(J39,0)*J17) | K40: =(MAX(K39,0)*K17) | L40: =(MAX(L39,0)*L17) | M40: =(MAX(M39,0)*M17) | N40: =(MAX(N39,0)*N17) | O40: =(MAX(O39,0)*O17) | ... Q40: =(MAX(Q39,0)*Q17)
A41: Net profit (incl. minorities) | B41: np | D41: 40420 | E41: 44501 | F41: 43273 | G41: 40205 | H41: =(H39-H40) | I41: =(I39-I40) | J41: =(J39-J40) | K41: =(K39-K40) | L41: =(L39-L40) | M41: =(M39-M40) | N41: =(N39-N40) | O41: =(O39-O40) | ... Q41: =(Q39-Q40)
A42: Minority interests | B42: minority | D42: 11476 | E42: 10662 | F42: 9372 | G42: 7436 | H42: =(H41*H22) | I42: =(I41*I22) | J42: =(J41*J22) | K42: =(K41*K22) | L42: =(L41*L22) | M42: =(M41*M22) | N42: =(N41*N22) | O42: =(O41*O22) | ... Q42: =(Q41*Q22)
A43: Net profit to parent | B43: np_parent | D43: 28944 | E43: 33839 | F43: 33901 | G43: 32769 | H43: =(H41-H42) | I43: =(I41-I42) | J43: =(J41-J42) | K43: =(K41-K42) | L43: =(L41-L42) | M43: =(M41-M42) | N43: =(N41-N42) | O43: =(O41-O42) | ... Q43: =(Q41-Q42)
A44: Shares outstanding (m) | B44: shares | D44: 40483.553 | E44: 40483.553 | F44: 40483.553 | G44: 40213.715 | H44: =(G44*(1+H24)) | I44: =(H44*(1+I24)) | J44: =(I44*(1+J24)) | K44: =(J44*(1+K24)) | L44: =(K44*(1+L24)) | M44: =(L44*(1+M24)) | N44: =(M44*(1+N24)) | O44: =(N44*(1+O24)) | ... Q44: =(P44*(1+Q24))
A45: EPS | B45: eps | D45: 714.95701 | E45: 835.87031 | F45: 837.40179 | G45: 814.87124 | H45: =(IF(H44=0,0,H43/H44)*$C$7) | I45: =(IF(I44=0,0,I43/I44)*$C$7) | J45: =(IF(J44=0,0,J43/J44)*$C$7) | K45: =(IF(K44=0,0,K43/K44)*$C$7) | L45: =(IF(L44=0,0,L43/L44)*$C$7) | M45: =(IF(M44=0,0,M43/M44)*$C$7) | N45: =(IF(N44=0,0,N43/N44)*$C$7) | O45: =(IF(O44=0,0,O43/O44)*$C$7) | ... Q45: =(IF(Q44=0,0,Q43/Q44)*$C$7)
A46: DPS (declared on the year) | B46: dps | D46: 650 | E46: 519 | F46: 406 | G46: 390 | H46: =(MAX(H45,0)*H23) | I46: =(MAX(I45,0)*I23) | J46: =(MAX(J45,0)*J23) | K46: =(MAX(K45,0)*K23) | L46: =(MAX(L45,0)*L23) | M46: =(MAX(M45,0)*M23) | N46: =(MAX(N45,0)*N23) | O46: =(MAX(O45,0)*O23) | ... Q46: =(MAX(Q45,0)*Q23)
A47: Dividends paid | B47: dividends_paid | D47: 11409 | E47: 26297 | F47: 20998 | G47: 16426 | H47: =IF($C$7=0,0,(G46*G44)/$C$7) | I47: =IF($C$7=0,0,(H46*H44)/$C$7) | J47: =IF($C$7=0,0,(I46*I44)/$C$7) | K47: =IF($C$7=0,0,(J46*J44)/$C$7) | L47: =IF($C$7=0,0,(K46*K44)/$C$7) | M47: =IF($C$7=0,0,(L46*L44)/$C$7) | N47: =IF($C$7=0,0,(M46*M44)/$C$7) | O47: =IF($C$7=0,0,(N46*N44)/$C$7) | ... Q47: =IF($C$7=0,0,(P46*P44)/$C$7)
A48: Capital expenditure | B48: capex | D48: 11855 | E48: 22098 | F48: 17508 | G48: 17440 | H48: =(H29*H15) | I48: =(I29*I15) | J48: =(J29*J15) | K48: =(K29*K15) | L48: =(L29*L15) | M48: =(M29*M15) | N48: =(N29*N15) | O48: =(O29*O15) | ... Q48: =(Q29*Q15)
A49: Change in working capital | B49: delta_nwc | E49: 4533 | F49: 7857 | G49: 5718 | H49: =(H54-G54) | I49: =(I54-H54) | J49: =(J54-I54) | K49: =(K54-J54) | L49: =(L54-K54) | M49: =(M54-L54) | N49: =(N54-M54) | O49: =(O54-N54) | ... Q49: =(Q54-P54)
A50: Free cash flow to firm | B50: fcff | F50: 25948.747 | G50: 26252.651 | H50: =((((H33*(1-H17))+H34)-H48)-H49) | I50: =((((I33*(1-I17))+I34)-I48)-I49) | J50: =((((J33*(1-J17))+J34)-J48)-J49) | K50: =((((K33*(1-K17))+K34)-K48)-K49) | L50: =((((L33*(1-L17))+L34)-L48)-L49) | M50: =((((M33*(1-M17))+M34)-M48)-M49) | N50: =((((N33*(1-N17))+N34)-N48)-N49) | O50: =((((O33*(1-O17))+O34)-O48)-O49) | ... Q50: =((((Q33*(1-Q17))+Q34)-Q48)-Q49)
A51: Net borrowing | B51: net_borrowing | E51: 22589 | F51: 7363 | G51: 9628 | H51: =H20 | I51: =I20 | J51: =J20 | K51: =K20 | L51: =L20 | M51: =M20 | N51: =N20 | O51: =O20 | ... Q51: =Q20
A52: Dividends to minorities | B52: minority_div | H52: =(MAX(G42,0)*H23) | I52: =(MAX(H42,0)*I23) | J52: =(MAX(I42,0)*J23) | K52: =(MAX(J42,0)*K23) | L52: =(MAX(K42,0)*L23) | M52: =(MAX(L42,0)*M23) | N52: =(MAX(M42,0)*N23) | O52: =(MAX(N42,0)*O23) | ... Q52: =(MAX(P42,0)*Q23)
A53: Free cash flow to equity | B53: fcfe | H53: =(((((H41+H34)-H48)-H49)+H51)-H52) | I53: =(((((I41+I34)-I48)-I49)+I51)-I52) | J53: =(((((J41+J34)-J48)-J49)+J51)-J52) | K53: =(((((K41+K34)-K48)-K49)+K51)-K52) | L53: =(((((L41+L34)-L48)-L49)+L51)-L52) | M53: =(((((M41+M34)-M48)-M49)+M51)-M52) | N53: =(((((N41+N34)-N48)-N49)+N51)-N52) | O53: =(((((O41+O34)-O48)-O49)+O51)-O52) | ... Q53: =(((((Q41+Q34)-Q48)-Q49)+Q51)-Q52)
A54: Operating working capital | B54: nwc | D54: 33708 | E54: 38241 | F54: 46098 | G54: 51816 | H54: =(H29*H16) | I54: =(I29*I16) | J54: =(J29*J16) | K54: =(K29*K16) | L54: =(L29*L16) | M54: =(M29*M16) | N54: =(N29*N16) | O54: =(O29*O16) | ... Q54: =(Q29*Q16)
A55: Cash & equivalents | B55: cash | D55: 61581 | E55: 41984 | F55: 49247 | G55: 53986 | H55: =(((((((G55+H41)+H34)-H48)-H49)+H51)-H47)-H52) | I55: =(((((((H55+I41)+I34)-I48)-I49)+I51)-I47)-I52) | J55: =(((((((I55+J41)+J34)-J48)-J49)+J51)-J47)-J52) | K55: =(((((((J55+K41)+K34)-K48)-K49)+K51)-K47)-K52) | L55: =(((((((K55+L41)+L34)-L48)-L49)+L51)-L47)-L52) | M55: =(((((((L55+M41)+M34)-M48)-M49)+M51)-M47)-M52) | N55: =(((((((M55+N41)+N34)-N48)-N49)+N51)-N47)-N52) | O55: =(((((((N55+O41)+O34)-O48)-O49)+O51)-O47)-O52) | ... Q55: =(((((((P55+Q41)+Q34)-Q48)-Q49)+Q51)-Q47)-Q52)
A56: Total debt | B56: debt | D56: 70721 | E56: 93310 | F56: 100673 | G56: 110301 | H56: =(G56+H51) | I56: =(H56+I51) | J56: =(I56+J51) | K56: =(J56+K51) | L56: =(K56+L51) | M56: =(L56+M51) | N56: =(M56+N51) | O56: =(N56+O51) | ... Q56: =(P56+Q51)
A57: Fixed assets (net) | B57: ppe | D57: 78751 | E57: 96846 | F57: 101911 | G57: 105960 | H57: =((G57+H48)-H34) | I57: =((H57+I48)-I34) | J57: =((I57+J48)-J34) | K57: =((J57+K48)-K34) | L57: =((K57+L48)-L34) | M57: =((L57+M48)-M34) | N57: =((M57+N48)-N34) | O57: =((N57+O48)-O34) | ... Q57: =((P57+Q48)-Q34)
A58: Parent shareholders' equity | B58: equity | D58: 192142 | E58: 198640 | F58: 213676 | G58: 228906 | H58: =((G58+H43)-H47) | I58: =((H58+I43)-I47) | J58: =((I58+J43)-J47) | K58: =((J58+K43)-K47) | L58: =((K58+L43)-L47) | M58: =((L58+M43)-M47) | N58: =((M58+N43)-N47) | O58: =((N58+O43)-O47) | ... Q58: =((P58+Q43)-Q47)
A59: Minority interest (balance sheet) | B59: minority_bs | D59: 51578 | E59: 51784 | F59: 58328 | G59: 61906 | H59: =((G59+H42)-H52) | I59: =((H59+I42)-I52) | J59: =((I59+J42)-J52) | K59: =((J59+K42)-K52) | L59: =((K59+L42)-L52) | M59: =((L59+M42)-M52) | N59: =((M59+N42)-N52) | O59: =((N59+O42)-O52) | ... Q59: =((P59+Q42)-Q52)
A60: Other assets less other liabilities | B60: other_net | D60: 140401 | E60: 166663 | F60: 175421 | G60: 189351 | H60: =G60 | I60: =H60 | J60: =I60 | K60: =J60 | L60: =K60 | M60: =L60 | N60: =M60 | O60: =N60 | ... Q60: =P60
A61: Balance check (should be zero) | B61: bs_check | H61: =((((((H55+H54)+H57)+H60)-H56)-H58)-H59) | I61: =((((((I55+I54)+I57)+I60)-I56)-I58)-I59) | J61: =((((((J55+J54)+J57)+J60)-J56)-J58)-J59) | K61: =((((((K55+K54)+K57)+K60)-K56)-K58)-K59) | L61: =((((((L55+L54)+L57)+L60)-L56)-L58)-L59) | M61: =((((((M55+M54)+M57)+M60)-M56)-M58)-M59) | N61: =((((((N55+N54)+N57)+N60)-N56)-N58)-N59) | O61: =((((((O55+O54)+O57)+O60)-O56)-O58)-O59) | ... Q61: =((((((Q55+Q54)+Q57)+Q60)-Q56)-Q58)-Q59)
A62: Net debt (cash) | B62: net_debt | D62: 9140 | E62: 51326 | F62: 51426 | G62: 56315 | H62: =(H56-H55) | I62: =(I56-I55) | J62: =(J56-J55) | K62: =(K56-K55) | L62: =(L56-L55) | M62: =(M56-M55) | N62: =(N56-N55) | O62: =(O56-O55) | ... Q62: =(Q56-Q55)
A63: Book value per share | B63: bvps | D63: 4746.1743 | E63: 4906.6839 | F63: 5278.094 | G63: 5692.237 | H63: =(IF(H44=0,0,H58/H44)*$C$7) | I63: =(IF(I44=0,0,I58/I44)*$C$7) | J63: =(IF(J44=0,0,J58/J44)*$C$7) | K63: =(IF(K44=0,0,K58/K44)*$C$7) | L63: =(IF(L44=0,0,L58/L44)*$C$7) | M63: =(IF(M44=0,0,M58/M44)*$C$7) | N63: =(IF(N44=0,0,N58/N44)*$C$7) | O63: =(IF(O44=0,0,O58/O44)*$C$7) | ... Q63: =(IF(Q44=0,0,Q58/Q44)*$C$7)
A64: Revenue growth | B64: revenue_growth | E64: 0.050388381 | F64: 0.0376384 | G64: -0.015489528 | H64: =(IF(G29=0,0,H29/G29)-1) | I64: =(IF(H29=0,0,I29/H29)-1) | J64: =(IF(I29=0,0,J29/I29)-1) | K64: =(IF(J29=0,0,K29/J29)-1) | L64: =(IF(K29=0,0,L29/K29)-1) | M64: =(IF(L29=0,0,M29/L29)-1) | N64: =(IF(M29=0,0,N29/M29)-1) | O64: =(IF(N29=0,0,O29/N29)-1) | ... Q64: =(IF(P29=0,0,Q29/P29)-1)
A65: Gross margin | B65: gross_margin | D65: 0.23255768 | E65: 0.23157961 | F65: 0.22241537 | G65: 0.22092074 | H65: =IF(H29=0,0,H31/H29) | I65: =IF(I29=0,0,I31/I29) | J65: =IF(J29=0,0,J31/J29) | K65: =IF(K29=0,0,K31/K29) | L65: =IF(L29=0,0,L31/L29) | M65: =IF(M29=0,0,M31/M29) | N65: =IF(N29=0,0,N31/N29) | O65: =IF(O29=0,0,O31/O29) | ... Q65: =IF(Q29=0,0,Q31/Q29)
A66: EBITDA margin | B66: ebitda_margin | F66: 0.17990745 | G66: 0.17482189 | H66: =IF(H29=0,0,H35/H29) | I66: =IF(I29=0,0,I35/I29) | J66: =IF(J29=0,0,J35/J29) | K66: =IF(K29=0,0,K35/K29) | L66: =IF(L29=0,0,L35/L29) | M66: =IF(M29=0,0,M35/M29) | N66: =IF(N29=0,0,N35/N29) | O66: =IF(O29=0,0,O35/O29) | ... Q66: =IF(Q29=0,0,Q35/Q29)
A67: EBIT margin | B67: ebit_margin | D67: 0.14002635 | E67: 0.13983858 | F67: 0.1290794 | G67: 0.11956078 | H67: =IF(H29=0,0,H33/H29) | I67: =IF(I29=0,0,I33/I29) | J67: =IF(J29=0,0,J33/J29) | K67: =IF(K29=0,0,K33/K29) | L67: =IF(L29=0,0,L33/L29) | M67: =IF(M29=0,0,M33/M29) | N67: =IF(N29=0,0,N33/N29) | O67: =IF(O29=0,0,O33/O29) | ... Q67: =IF(Q29=0,0,Q33/Q29)
A68: Net margin | B68: np_margin | D68: 0.096038543 | E68: 0.10689432 | F68: 0.10320567 | G68: 0.10132904 | H68: =IF(H29=0,0,H43/H29) | I68: =IF(I29=0,0,I43/I29) | J68: =IF(J29=0,0,J43/J29) | K68: =IF(K29=0,0,K43/K29) | L68: =IF(L29=0,0,L43/L29) | M68: =IF(M29=0,0,M43/M29) | N68: =IF(N29=0,0,N43/N29) | O68: =IF(O29=0,0,O43/O29) | ... Q68: =IF(Q29=0,0,Q43/Q29)
A69: EPS growth | B69: eps_growth | E69: 0.16911968 | F69: 0.0018322054 | G69: -0.026905311 | H69: =(IF(G45=0,0,H45/G45)-1) | I69: =(IF(H45=0,0,I45/H45)-1) | J69: =(IF(I45=0,0,J45/I45)-1) | K69: =(IF(J45=0,0,K45/J45)-1) | L69: =(IF(K45=0,0,L45/K45)-1) | M69: =(IF(L45=0,0,M45/L45)-1) | N69: =(IF(M45=0,0,N45/M45)-1) | O69: =(IF(N45=0,0,O45/N45)-1) | ... Q69: =(IF(P45=0,0,Q45/P45)-1)
A70: ROE | B70: roe | E70: 0.17318607 | F70: 0.16444184 | G70: 0.14808103 | H70: =IF(IF(2=0,0,(H58+G58)/2)=0,0,H43/IF(2=0,0,(H58+G58)/2)) | I70: =IF(IF(2=0,0,(I58+H58)/2)=0,0,I43/IF(2=0,0,(I58+H58)/2)) | J70: =IF(IF(2=0,0,(J58+I58)/2)=0,0,J43/IF(2=0,0,(J58+I58)/2)) | K70: =IF(IF(2=0,0,(K58+J58)/2)=0,0,K43/IF(2=0,0,(K58+J58)/2)) | L70: =IF(IF(2=0,0,(L58+K58)/2)=0,0,L43/IF(2=0,0,(L58+K58)/2)) | M70: =IF(IF(2=0,0,(M58+L58)/2)=0,0,M43/IF(2=0,0,(M58+L58)/2)) | N70: =IF(IF(2=0,0,(N58+M58)/2)=0,0,N43/IF(2=0,0,(N58+M58)/2)) | O70: =IF(IF(2=0,0,(O58+N58)/2)=0,0,O43/IF(2=0,0,(O58+N58)/2)) | ... Q70: =IF(IF(2=0,0,(Q58+P58)/2)=0,0,Q43/IF(2=0,0,(Q58+P58)/2))
A71: Net debt / EBITDA | B71: net_debt_ebitda | F71: 0.87021118 | G71: 0.99609099 | H71: =IF(H35=0,0,H62/H35) | I71: =IF(I35=0,0,I62/I35) | J71: =IF(J35=0,0,J62/J35) | K71: =IF(K35=0,0,K62/K35) | L71: =IF(L35=0,0,L62/L35) | M71: =IF(M35=0,0,M62/M35) | N71: =IF(N35=0,0,N62/N35) | O71: =IF(O35=0,0,O62/O35) | ... Q71: =IF(Q35=0,0,Q62/Q35)
A72: Payout ratio | B72: payout_ratio | D72: 0.90914558 | E72: 0.62090972 | F72: 0.48483297 | G72: 0.47860322 | H72: =IF(H45=0,0,H46/H45) | I72: =IF(I45=0,0,I46/I45) | J72: =IF(J45=0,0,J46/J45) | K72: =IF(K45=0,0,K46/K45) | L72: =IF(L45=0,0,L46/L45) | M72: =IF(M45=0,0,M46/M45) | N72: =IF(N45=0,0,N46/N45) | O72: =IF(O45=0,0,O46/O45) | ... Q72: =IF(Q45=0,0,Q46/Q45)
A73: Capex / revenue | B73: capex_revenue | D73: 0.039335853 | E73: 0.069805569 | F73: 0.053300049 | G73: 0.053928359 | H73: =IF(H29=0,0,H48/H29) | I73: =IF(I29=0,0,I48/I29) | J73: =IF(J29=0,0,J48/J29) | K73: =IF(K29=0,0,K48/K29) | L73: =IF(L29=0,0,L48/L29) | M73: =IF(M29=0,0,M48/M29) | N73: =IF(N29=0,0,N48/N29) | O73: =IF(O29=0,0,O48/O29) | ... Q73: =IF(Q29=0,0,Q48/Q29)
A75: VALUATION
A76: Last price (IDR) | C76: 4540
A77: Shares outstanding (m) | C77: 39920.061
A78: IDR per USD (spot) | C78: 18183
A79: Debt at balance-sheet date | C79: 119198
A80: Cash at balance-sheet date | C80: 47648
A81: Minority interest (book) | C81: 59776
A82: Associates & investments (book) | C82: 71856
A83: Post-balance-sheet & other items (sourced, probability-weighted) | C83: 0
A84: Parent equity at balance-sheet date | C84: 238103
A85: Per-share factor | C85: 1000
A86: Risk-free rate | C86: =Drivers!$C$7
A87: Less: default spread (IDR only) | C87: =Drivers!$C$9
A88: Mature ERP + Indonesia CRP | C88: =Drivers!$C$10+Drivers!$C$11
A89: Tax rate | C89: =Drivers!$C$13
A90: Unlevered beta (industry default (config)) | C90: 0.9
A91: Debt / equity (market) | C91: 0.65769103
A92: Levered beta | C92: =$C$90*(1+(1-$C$89)*$C$91)
A93: Explicit company premium | C93: 0
A94: Cost of equity | C94: =$C$86-$C$87+$C$92*$C$88+$C$93
A95: Pre-tax cost of debt | C95: =$C$86+Drivers!$C$12
A96: WACC | C96: =1/(1+$C$91)*$C$94+$C$91/(1+$C$91)*$C$95*(1-$C$89)
A97: Terminal growth (capped) | C97: 0.04
A99: Sum of the parts
A100: Value per share (IDR) — Sum of the parts (engine value) | C100: 4656.9578
A102: P/E
A103: Target multiple (own five-year average) | C103: 7.20138
A104: Metric (LTM, or next-12m DPS for yield) | C104: 32769
A105: Value per share (IDR) — P/E | C105: =MAX(0,$C$103*$C$104/$C$77*$C$85*1)
A107: P/BV
A108: Target multiple (own five-year average) | C108: 1.114466
...

Sheet BHIT
A1: PT MNC Asia Holding Tbk (BHIT.JK) — Conglomerates & multi-sector holdings
A2: Units: IDR bn; per-share in IDR unless marked IDR. Model asof 2026-10-29 · data 2026-10-27
A4: Line | C4: Scalar | D4: FY2022A | E4: FY2023A | F4: FY2024A | G4: FY2025A | H4: FY2026E | I4: FY2027E | J4: FY2028E | K4: FY2029E | L4: FY2030E | M4: FY2031E | N4: FY2032E | O4: FY2033E | P4: FY2034E | Q4: FY2035E
A6: PARAMETERS
A7: ps_factor | C7: 1000
A8: vp_factor | C8: 1
A10: INPUTS (company assumptions)
A11: Revenue growth | B11: a.revenue_growth | H11: -0.042023 | I11: 0 | J11: 0.0328 | K11: 0.0328 | L11: 0.0328 | M11: 0.0328 | N11: 0.0328 | O11: 0.0328 | P11: 0.0328 | Q11: 0.0328
A12: Gross margin at base input costs | B12: a.gross_margin | H12: 0.37572 | I12: 0.37572 | J12: 0.37572 | K12: 0.37572 | L12: 0.37572 | M12: 0.37572 | N12: 0.37572 | O12: 0.37572 | P12: 0.37572 | Q12: 0.37572
A13: SG&A / revenue | B13: a.opex_pct | H13: 0.2178 | I13: 0.2178 | J13: 0.2178 | K13: 0.2178 | L13: 0.2178 | M13: 0.2178 | N13: 0.2178 | O13: 0.2178 | P13: 0.2178 | Q13: 0.2178
A14: D&A / revenue | B14: a.da_pct | H14: 0.08946 | I14: 0.08946 | J14: 0.08946 | K14: 0.08946 | L14: 0.08946 | M14: 0.08946 | N14: 0.08946 | O14: 0.08946 | P14: 0.08946 | Q14: 0.08946
A15: Capex / revenue | B15: a.capex_pct | H15: 0.06242 | I15: 0.06242 | J15: 0.06242 | K15: 0.06242 | L15: 0.06242 | M15: 0.06242 | N15: 0.06242 | O15: 0.06242 | P15: 0.06242 | Q15: 0.06242
A16: Operating working capital / revenue | B16: a.nwc_pct | H16: -0.067516 | I16: -0.067516 | J16: -0.067516 | K16: -0.067516 | L16: -0.067516 | M16: -0.067516 | N16: -0.067516 | O16: -0.067516 | P16: -0.067516 | Q16: -0.067516
A17: Effective tax rate | B17: a.tax_rate | H17: 0.15229 | I17: 0.15229 | J17: 0.15229 | K17: 0.15229 | L17: 0.15229 | M17: 0.15229 | N17: 0.15229 | O17: 0.15229 | P17: 0.15229 | Q17: 0.15229
A18: Cost of debt (on opening debt) | B18: a.cost_of_debt | C18: 0.092545
A19: Yield on opening cash | B19: a.cash_yield | C19: 0.004067
A20: Net new borrowing | B20: a.net_borrowing | H20: 0 | I20: 0 | J20: 0 | K20: 0 | L20: 0 | M20: 0 | N20: 0 | O20: 0 | P20: 0 | Q20: 0
A21: Other non-operating items | B21: a.other_nonop | H21: -292.851 | I21: -292.851 | J21: -292.851 | K21: -292.851 | L21: -292.851 | M21: -300.17228 | N21: -307.67658 | O21: -315.3685 | P21: -323.25271 | Q21: -331.33403
A22: Minorities' share of net profit | B22: a.minority_pct | H22: 0.78118 | I22: 0.78118 | J22: 0.78118 | K22: 0.78118 | L22: 0.78118 | M22: 0.78118 | N22: 0.78118 | O22: 0.78118 | P22: 0.78118 | Q22: 0.78118
A23: Dividend payout | B23: a.payout | H23: 0 | I23: 0 | J23: 0 | K23: 0 | L23: 0 | M23: 0 | N23: 0 | O23: 0 | P23: 0 | Q23: 0
A24: Change in share count | B24: a.share_change | H24: 0 | I24: 0 | J24: 0 | K24: 0 | L24: 0 | M24: 0 | N24: 0 | O24: 0 | P24: 0 | Q24: 0
A25: Terminal growth (DCF) | B25: a.terminal_growth | C25: 0.0328
A26: Holding-company discount to SOTP | B26: a.holdco_discount | C26: 0.4
A28: MODEL
A29: Revenue | B29: revenue | D29: 18083.695 | E29: 15660.503 | F29: 15139.665 | G29: 14490.421 | H29: =(G29*(1+H11)) | I29: =(H29*(1+I11)) | J29: =(I29*(1+J11)) | K29: =(J29*(1+K11)) | L29: =(K29*(1+L11)) | M29: =(L29*(1+M11)) | N29: =(M29*(1+N11)) | O29: =(N29*(1+O11)) | ... Q29: =(P29*(1+Q11))
A30: Cost of revenue | B30: cogs | D30: 9275.283 | E30: 9357.258 | F30: 9166.35 | G30: 8732.33 | H30: =(H29*(1-H12)) | I30: =(I29*(1-I12)) | J30: =(J29*(1-J12)) | K30: =(K29*(1-K12)) | L30: =(L29*(1-L12)) | M30: =(M29*(1-M12)) | N30: =(N29*(1-N12)) | O30: =(O29*(1-O12)) | ... Q30: =(Q29*(1-Q12))
A31: Gross profit | B31: gross_profit | D31: 8808.412 | E31: 6303.245 | F31: 5973.315 | G31: 5758.091 | H31: =(H29-H30) | I31: =(I29-I30) | J31: =(J29-J30) | K31: =(K29-K30) | L31: =(L29-L30) | M31: =(M29-M30) | N31: =(N29-N30) | O31: =(O29-O30) | ... Q31: =(Q29-Q30)
A32: SG&A and other opex | B32: opex | D32: 3849.835 | E32: 3757.646 | F32: 3264.232 | G32: 3221.662 | H32: =(H29*H13) | I32: =(I29*I13) | J32: =(J29*J13) | K32: =(K29*K13) | L32: =(L29*L13) | M32: =(M29*M13) | N32: =(N29*N13) | O32: =(O29*O13) | ... Q32: =(Q29*Q13)
A33: EBIT | B33: ebit | D33: 4958.577 | E33: 2545.599 | F33: 2709.083 | G33: 2536.429 | H33: =(H31-H32) | I33: =(I31-I32) | J33: =(J31-J32) | K33: =(K31-K32) | L33: =(L31-L32) | M33: =(M31-M32) | N33: =(N31-N32) | O33: =(O31-O32) | ... Q33: =(Q31-Q32)
A34: Depreciation & amortisation | B34: da | D34: 524.315 | E34: 527.977 | F34: 1340.84 | G34: 1360.403 | H34: =(H29*H14) | I34: =(I29*I14) | J34: =(J29*J14) | K34: =(K29*K14) | L34: =(L29*L14) | M34: =(M29*M14) | N34: =(N29*N14) | O34: =(O29*O14) | ... Q34: =(Q29*Q14)
A35: EBITDA | B35: ebitda | D35: 5482.892 | E35: 3073.576 | F35: 4049.923 | G35: 3896.832 | H35: =(H33+H34) | I35: =(I33+I34) | J35: =(J33+J34) | K35: =(K33+K34) | L35: =(L33+L34) | M35: =(M33+M34) | N35: =(N33+N34) | O35: =(O33+O34) | ... Q35: =(Q33+Q34)
A36: Interest expense | B36: interest_expense | D36: 830.93 | E36: 985.193 | F36: 1189.784 | G36: 1115.351 | H36: =(G56*$C$18) | I36: =(H56*$C$18) | J36: =(I56*$C$18) | K36: =(J56*$C$18) | L36: =(K56*$C$18) | M36: =(L56*$C$18) | N36: =(M56*$C$18) | O36: =(N56*$C$18) | ... Q36: =(P56*$C$18)
A37: Interest income | B37: interest_income | D37: 40.071 | E37: 52.074 | F37: 39.978 | G37: 32.14 | H37: =(G55*$C$19) | I37: =(H55*$C$19) | J37: =(I55*$C$19) | K37: =(J55*$C$19) | L37: =(K55*$C$19) | M37: =(L55*$C$19) | N37: =(M55*$C$19) | O37: =(N55*$C$19) | ... Q37: =(P55*$C$19)
A38: Other non-operating | B38: other_nonop | D38: -653.738 | E38: -213.387 | F38: -320.118 | G38: 206.094 | H38: =H21 | I38: =I21 | J38: =J21 | K38: =K21 | L38: =L21 | M38: =M21 | N38: =N21 | O38: =O21 | ... Q38: =Q21
A39: Profit before tax | B39: pbt | D39: 3513.98 | E39: 1399.093 | F39: 1239.159 | G39: 1659.312 | H39: =(((H33-H36)+H37)+H38) | I39: =(((I33-I36)+I37)+I38) | J39: =(((J33-J36)+J37)+J38) | K39: =(((K33-K36)+K37)+K38) | L39: =(((L33-L36)+L37)+L38) | M39: =(((M33-M36)+M37)+M38) | N39: =(((N33-N36)+N37)+N38) | O39: =(((O33-O36)+O37)+O38) | ... Q39: =(((Q33-Q36)+Q37)+Q38)
A40: Tax | B40: tax | D40: 831.76 | E40: 165.62 | F40: 295.4 | G40: 252.687 | H40: =(MAX(H39,0)*H17) | I40: =(MAX(I39,0)*I17) | J40: =(MAX(J39,0)*J17) | K40: =(MAX(K39,0)*K17) | L40: =(MAX(L39,0)*L17) | M40: =(MAX(M39,0)*M17) | N40: =(MAX(N39,0)*N17) | O40: =(MAX(O39,0)*O17) | ... Q40: =(MAX(Q39,0)*Q17)
A41: Net profit (incl. minorities) | B41: np | D41: 2682.22 | E41: 1233.473 | F41: 943.759 | G41: 1406.625 | H41: =(H39-H40) | I41: =(I39-I40) | J41: =(J39-J40) | K41: =(K39-K40) | L41: =(L39-L40) | M41: =(M39-M40) | N41: =(N39-N40) | O41: =(O39-O40) | ... Q41: =(Q39-Q40)
A42: Minority interests | B42: minority | D42: 1951.941 | E42: 926.881 | F42: 753.739 | G42: 928.085 | H42: =(H41*H22) | I42: =(I41*I22) | J42: =(J41*J22) | K42: =(K41*K22) | L42: =(L41*L22) | M42: =(M41*M22) | N42: =(N41*N22) | O42: =(O41*O22) | ... Q42: =(Q41*Q22)
A43: Net profit to parent | B43: np_parent | D43: 730.279 | E43: 306.592 | F43: 190.02 | G43: 478.54 | H43: =(H41-H42) | I43: =(I41-I42) | J43: =(J41-J42) | K43: =(K41-K42) | L43: =(L41-L42) | M43: =(M41-M42) | N43: =(N41-N42) | O43: =(O41-O42) | ... Q43: =(Q41-Q42)
A44: Shares outstanding (m) | B44: shares | D44: 83542.742 | E44: 83542.742 | F44: 83542.742 | G44: 83542.742 | H44: =(G44*(1+H24)) | I44: =(H44*(1+I24)) | J44: =(I44*(1+J24)) | K44: =(J44*(1+K24)) | L44: =(K44*(1+L24)) | M44: =(L44*(1+M24)) | N44: =(M44*(1+N24)) | O44: =(N44*(1+O24)) | ... Q44: =(P44*(1+Q24))
A45: EPS | B45: eps | D45: 8.7413818 | E45: 3.6698819 | F45: 2.2745243 | G45: 5.7280859 | H45: =(IF(H44=0,0,H43/H44)*$C$7) | I45: =(IF(I44=0,0,I43/I44)*$C$7) | J45: =(IF(J44=0,0,J43/J44)*$C$7) | K45: =(IF(K44=0,0,K43/K44)*$C$7) | L45: =(IF(L44=0,0,L43/L44)*$C$7) | M45: =(IF(M44=0,0,M43/M44)*$C$7) | N45: =(IF(N44=0,0,N43/N44)*$C$7) | O45: =(IF(O44=0,0,O43/O44)*$C$7) | ... Q45: =(IF(Q44=0,0,Q43/Q44)*$C$7)
A46: DPS (declared on the year) | B46: dps | D46: 0 | E46: 0 | F46: 0 | G46: 0 | H46: =(MAX(H45,0)*H23) | I46: =(MAX(I45,0)*I23) | J46: =(MAX(J45,0)*J23) | K46: =(MAX(K45,0)*K23) | L46: =(MAX(L45,0)*L23) | M46: =(MAX(M45,0)*M23) | N46: =(MAX(N45,0)*N23) | O46: =(MAX(O45,0)*O23) | ... Q46: =(MAX(Q45,0)*Q23)
A47: Dividends paid | B47: dividends_paid | H47: =IF($C$7=0,0,(G46*G44)/$C$7) | I47: =IF($C$7=0,0,(H46*H44)/$C$7) | J47: =IF($C$7=0,0,(I46*I44)/$C$7) | K47: =IF($C$7=0,0,(J46*J44)/$C$7) | L47: =IF($C$7=0,0,(K46*K44)/$C$7) | M47: =IF($C$7=0,0,(L46*L44)/$C$7) | N47: =IF($C$7=0,0,(M46*M44)/$C$7) | O47: =IF($C$7=0,0,(N46*N44)/$C$7) | ... Q47: =IF($C$7=0,0,(P46*P44)/$C$7)
A48: Capital expenditure | B48: capex | D48: 1866.364 | E48: 2467.768 | F48: 1229.277 | G48: 904.524 | H48: =(H29*H15) | I48: =(I29*I15) | J48: =(J29*J15) | K48: =(K29*K15) | L48: =(L29*L15) | M48: =(M29*M15) | N48: =(N29*N15) | O48: =(O29*O15) | ... Q48: =(Q29*Q15)
A49: Change in working capital | B49: delta_nwc | E49: 1718.32 | F49: -3489.663 | G49: -821.014 | H49: =(H54-G54) | I49: =(I54-H54) | J49: =(J54-I54) | K49: =(K54-J54) | L49: =(L54-K54) | M49: =(M54-L54) | N49: =(N54-M54) | O49: =(O54-N54) | ... Q49: =(Q54-P54)
A50: Free cash flow to firm | B50: fcff | E50: -1413.8516 | F50: 5664.4975 | G50: 3427.0639 | H50: =((((H33*(1-H17))+H34)-H48)-H49) | I50: =((((I33*(1-I17))+I34)-I48)-I49) | J50: =((((J33*(1-J17))+J34)-J48)-J49) | K50: =((((K33*(1-K17))+K34)-K48)-K49) | L50: =((((L33*(1-L17))+L34)-L48)-L49) | M50: =((((M33*(1-M17))+M34)-M48)-M49) | N50: =((((N33*(1-N17))+N34)-N48)-N49) | O50: =((((O33*(1-O17))+O34)-O48)-O49) | ... Q50: =((((Q33*(1-Q17))+Q34)-Q48)-Q49)
A51: Net borrowing | B51: net_borrowing | E51: -42.599 | F51: -1150.654 | G51: 43.326 | H51: =H20 | I51: =I20 | J51: =J20 | K51: =K20 | L51: =L20 | M51: =M20 | N51: =N20 | O51: =O20 | ... Q51: =Q20
A52: Dividends to minorities | B52: minority_div | H52: =(MAX(G42,0)*H23) | I52: =(MAX(H42,0)*I23) | J52: =(MAX(I42,0)*J23) | K52: =(MAX(J42,0)*K23) | L52: =(MAX(K42,0)*L23) | M52: =(MAX(L42,0)*M23) | N52: =(MAX(M42,0)*N23) | O52: =(MAX(N42,0)*O23) | ... Q52: =(MAX(P42,0)*Q23)
A53: Free cash flow to equity | B53: fcfe | H53: =(((((H41+H34)-H48)-H49)+H51)-H52) | I53: =(((((I41+I34)-I48)-I49)+I51)-I52) | J53: =(((((J41+J34)-J48)-J49)+J51)-J52) | K53: =(((((K41+K34)-K48)-K49)+K51)-K52) | L53: =(((((L41+L34)-L48)-L49)+L51)-L52) | M53: =(((((M41+M34)-M48)-M49)+M51)-M52) | N53: =(((((N41+N34)-N48)-N49)+N51)-N52) | O53: =(((((O41+O34)-O48)-O49)+O51)-O52) | ... Q53: =(((((Q41+Q34)-Q48)-Q49)+Q51)-Q52)
A54: Operating working capital | B54: nwc | D54: -82.289 | E54: 1636.031 | F54: -1853.632 | G54: -2674.646 | H54: =(H29*H16) | I54: =(I29*I16) | J54: =(J29*J16) | K54: =(K29*K16) | L54: =(L29*L16) | M54: =(M29*M16) | N54: =(N29*N16) | O54: =(O29*O16) | ... Q54: =(Q29*Q16)
A55: Cash & equivalents | B55: cash | D55: 9343.791 | E55: 10020.75 | F55: 12188.175 | G55: 10579.309 | H55: =(((((((G55+H41)+H34)-H48)-H49)+H51)-H47)-H52) | I55: =(((((((H55+I41)+I34)-I48)-I49)+I51)-I47)-I52) | J55: =(((((((I55+J41)+J34)-J48)-J49)+J51)-J47)-J52) | K55: =(((((((J55+K41)+K34)-K48)-K49)+K51)-K47)-K52) | L55: =(((((((K55+L41)+L34)-L48)-L49)+L51)-L47)-L52) | M55: =(((((((L55+M41)+M34)-M48)-M49)+M51)-M47)-M52) | N55: =(((((((M55+N41)+N34)-N48)-N49)+N51)-N47)-N52) | O55: =(((((((N55+O41)+O34)-O48)-O49)+O51)-O47)-O52) | ... Q55: =(((((((P55+Q41)+Q34)-Q48)-Q49)+Q51)-Q47)-Q52)
A56: Total debt | B56: debt | D56: 12297.883 | E56: 12255.284 | F56: 11104.63 | G56: 11147.956 | H56: =(G56+H51) | I56: =(H56+I51) | J56: =(I56+J51) | K56: =(J56+K51) | L56: =(K56+L51) | M56: =(L56+M51) | N56: =(M56+N51) | O56: =(N56+O51) | ... Q56: =(P56+Q51)
A57: Fixed assets (net) | B57: ppe | D57: 18326.849 | E57: 14422.679 | F57: 15416.471 | G57: 13940.152 | H57: =((G57+H48)-H34) | I57: =((H57+I48)-I34) | J57: =((I57+J48)-J34) | K57: =((J57+K48)-K34) | L57: =((K57+L48)-L34) | M57: =((L57+M48)-M34) | N57: =((M57+N48)-N34) | O57: =((N57+O48)-O34) | ... Q57: =((P57+Q48)-Q34)
A58: Parent shareholders' equity | B58: equity | D58: 17038.624 | E58: 17839.694 | F58: 17518.553 | G58: 16686.254 | H58: =((G58+H43)-H47) | I58: =((H58+I43)-I47) | J58: =((I58+J43)-J47) | K58: =((J58+K43)-K47) | L58: =((K58+L43)-L47) | M58: =((L58+M43)-M47) | N58: =((M58+N43)-N47) | O58: =((N58+O43)-O47) | ... Q58: =((P58+Q43)-Q47)
A59: Minority interest (balance sheet) | B59: minority_bs | D59: 22393.624 | E59: 23458.275 | F59: 25285.267 | G59: 23728.674 | H59: =((G59+H42)-H52) | I59: =((H59+I42)-I52) | J59: =((I59+J42)-J52) | K59: =((J59+K42)-K52) | L59: =((K59+L42)-L52) | M59: =((L59+M42)-M52) | N59: =((M59+N42)-N52) | O59: =((N59+O42)-O52) | ... Q59: =((P59+Q42)-Q52)
A60: Other assets less other liabilities | B60: other_net | D60: 24141.78 | E60: 27473.793 | F60: 28157.436 | G60: 29718.069 | H60: =G60 | I60: =H60 | J60: =I60 | K60: =J60 | L60: =K60 | M60: =L60 | N60: =M60 | O60: =N60 | ... Q60: =P60
A61: Balance check (should be zero) | B61: bs_check | H61: =((((((H55+H54)+H57)+H60)-H56)-H58)-H59) | I61: =((((((I55+I54)+I57)+I60)-I56)-I58)-I59) | J61: =((((((J55+J54)+J57)+J60)-J56)-J58)-J59) | K61: =((((((K55+K54)+K57)+K60)-K56)-K58)-K59) | L61: =((((((L55+L54)+L57)+L60)-L56)-L58)-L59) | M61: =((((((M55+M54)+M57)+M60)-M56)-M58)-M59) | N61: =((((((N55+N54)+N57)+N60)-N56)-N58)-N59) | O61: =((((((O55+O54)+O57)+O60)-O56)-O58)-O59) | ... Q61: =((((((Q55+Q54)+Q57)+Q60)-Q56)-Q58)-Q59)
A62: Net debt (cash) | B62: net_debt | D62: 2954.092 | E62: 2234.534 | F62: -1083.545 | G62: 568.647 | H62: =(H56-H55) | I62: =(I56-I55) | J62: =(J56-J55) | K62: =(K56-K55) | L62: =(L56-L55) | M62: =(M56-M55) | N62: =(N56-N55) | O62: =(O56-O55) | ... Q62: =(Q56-Q55)
A63: Book value per share | B63: bvps | D63: 203.95098 | E63: 213.53972 | F63: 209.69569 | G63: 199.73314 | H63: =(IF(H44=0,0,H58/H44)*$C$7) | I63: =(IF(I44=0,0,I58/I44)*$C$7) | J63: =(IF(J44=0,0,J58/J44)*$C$7) | K63: =(IF(K44=0,0,K58/K44)*$C$7) | L63: =(IF(L44=0,0,L58/L44)*$C$7) | M63: =(IF(M44=0,0,M58/M44)*$C$7) | N63: =(IF(N44=0,0,N58/N44)*$C$7) | O63: =(IF(O44=0,0,O58/O44)*$C$7) | ... Q63: =(IF(Q44=0,0,Q58/Q44)*$C$7)
A64: Revenue growth | B64: revenue_growth | E64: -0.13399872 | F64: -0.033258063 | G64: -0.042883644 | H64: =(IF(G29=0,0,H29/G29)-1) | I64: =(IF(H29=0,0,I29/H29)-1) | J64: =(IF(I29=0,0,J29/I29)-1) | K64: =(IF(J29=0,0,K29/J29)-1) | L64: =(IF(K29=0,0,L29/K29)-1) | M64: =(IF(L29=0,0,M29/L29)-1) | N64: =(IF(M29=0,0,N29/M29)-1) | O64: =(IF(N29=0,0,O29/N29)-1) | ... Q64: =(IF(P29=0,0,Q29/P29)-1)
A65: Gross margin | B65: gross_margin | D65: 0.48709138 | E65: 0.40249314 | F65: 0.39454737 | G65: 0.39737224 | H65: =IF(H29=0,0,H31/H29) | I65: =IF(I29=0,0,I31/I29) | J65: =IF(J29=0,0,J31/J29) | K65: =IF(K29=0,0,K31/K29) | L65: =IF(L29=0,0,L31/L29) | M65: =IF(M29=0,0,M31/M29) | N65: =IF(N29=0,0,N31/N29) | O65: =IF(O29=0,0,O31/O29) | ... Q65: =IF(Q29=0,0,Q31/Q29)
A66: EBITDA margin | B66: ebitda_margin | D66: 0.30319534 | E66: 0.19626292 | F66: 0.26750414 | G66: 0.26892469 | H66: =IF(H29=0,0,H35/H29) | I66: =IF(I29=0,0,I35/I29) | J66: =IF(J29=0,0,J35/J29) | K66: =IF(K29=0,0,K35/K29) | L66: =IF(L29=0,0,L35/L29) | M66: =IF(M29=0,0,M35/M29) | N66: =IF(N29=0,0,N35/N29) | O66: =IF(O29=0,0,O35/O29) | ... Q66: =IF(Q29=0,0,Q35/Q29)
A67: EBIT margin | B67: ebit_margin | D67: 0.27420154 | E67: 0.16254899 | F67: 0.17893943 | G67: 0.17504177 | H67: =IF(H29=0,0,H33/H29) | I67: =IF(I29=0,0,I33/I29) | J67: =IF(J29=0,0,J33/J29) | K67: =IF(K29=0,0,K33/K29) | L67: =IF(L29=0,0,L33/L29) | M67: =IF(M29=0,0,M33/M29) | N67: =IF(N29=0,0,N33/N29) | O67: =IF(O29=0,0,O33/O29) | ... Q67: =IF(Q29=0,0,Q33/Q29)
A68: Net margin | B68: np_margin | D68: 0.040383285 | E68: 0.019577404 | F68: 0.012551136 | G68: 0.033024575 | H68: =IF(H29=0,0,H43/H29) | I68: =IF(I29=0,0,I43/I29) | J68: =IF(J29=0,0,J43/J29) | K68: =IF(K29=0,0,K43/K29) | L68: =IF(L29=0,0,L43/L29) | M68: =IF(M29=0,0,M43/M29) | N68: =IF(N29=0,0,N43/N29) | O68: =IF(O29=0,0,O43/O29) | ... Q68: =IF(Q29=0,0,Q43/Q29)
A69: EPS growth | B69: eps_growth | E69: -0.58017141 | F69: -0.38021866 | G69: 1.5183665 | H69: =(IF(G45=0,0,H45/G45)-1) | I69: =(IF(H45=0,0,I45/H45)-1) | J69: =(IF(I45=0,0,J45/I45)-1) | K69: =(IF(J45=0,0,K45/J45)-1) | L69: =(IF(K45=0,0,L45/K45)-1) | M69: =(IF(L45=0,0,M45/L45)-1) | N69: =(IF(M45=0,0,N45/M45)-1) | O69: =(IF(N45=0,0,O45/N45)-1) | ... Q69: =(IF(P45=0,0,Q45/P45)-1)
A70: ROE | B70: roe | E70: 0.017580664 | F70: 0.01074827 | G70: 0.027980862 | H70: =IF(IF(2=0,0,(H58+G58)/2)=0,0,H43/IF(2=0,0,(H58+G58)/2)) | I70: =IF(IF(2=0,0,(I58+H58)/2)=0,0,I43/IF(2=0,0,(I58+H58)/2)) | J70: =IF(IF(2=0,0,(J58+I58)/2)=0,0,J43/IF(2=0,0,(J58+I58)/2)) | K70: =IF(IF(2=0,0,(K58+J58)/2)=0,0,K43/IF(2=0,0,(K58+J58)/2)) | L70: =IF(IF(2=0,0,(L58+K58)/2)=0,0,L43/IF(2=0,0,(L58+K58)/2)) | M70: =IF(IF(2=0,0,(M58+L58)/2)=0,0,M43/IF(2=0,0,(M58+L58)/2)) | N70: =IF(IF(2=0,0,(N58+M58)/2)=0,0,N43/IF(2=0,0,(N58+M58)/2)) | O70: =IF(IF(2=0,0,(O58+N58)/2)=0,0,O43/IF(2=0,0,(O58+N58)/2)) | ... Q70: =IF(IF(2=0,0,(Q58+P58)/2)=0,0,Q43/IF(2=0,0,(Q58+P58)/2))
A71: Net debt / EBITDA | B71: net_debt_ebitda | D71: 0.53878355 | E71: 0.7270144 | F71: -0.26754706 | G71: 0.14592546 | H71: =IF(H35=0,0,H62/H35) | I71: =IF(I35=0,0,I62/I35) | J71: =IF(J35=0,0,J62/J35) | K71: =IF(K35=0,0,K62/K35) | L71: =IF(L35=0,0,L62/L35) | M71: =IF(M35=0,0,M62/M35) | N71: =IF(N35=0,0,N62/N35) | O71: =IF(O35=0,0,O62/O35) | ... Q71: =IF(Q35=0,0,Q62/Q35)
A72: Payout ratio | B72: payout_ratio | D72: 0 | E72: 0 | F72: 0 | G72: 0 | H72: =IF(H45=0,0,H46/H45) | I72: =IF(I45=0,0,I46/I45) | J72: =IF(J45=0,0,J46/J45) | K72: =IF(K45=0,0,K46/K45) | L72: =IF(L45=0,0,L46/L45) | M72: =IF(M45=0,0,M46/M45) | N72: =IF(N45=0,0,N46/N45) | O72: =IF(O45=0,0,O46/O45) | ... Q72: =IF(Q45=0,0,Q46/Q45)
A73: Capex / revenue | B73: capex_revenue | D73: 0.103207 | E73: 0.1575791 | F73: 0.081195786 | G73: 0.062422203 | H73: =IF(H29=0,0,H48/H29) | I73: =IF(I29=0,0,I48/I29) | J73: =IF(J29=0,0,J48/J29) | K73: =IF(K29=0,0,K48/K29) | L73: =IF(L29=0,0,L48/L29) | M73: =IF(M29=0,0,M48/M29) | N73: =IF(N29=0,0,N48/N29) | O73: =IF(O29=0,0,O48/O29) | ... Q73: =IF(Q29=0,0,Q48/Q29)
A75: VALUATION
A76: Last price (IDR) | C76: 18
A77: Shares outstanding (m) | C77: 83542.742
A78: IDR per USD (spot) | C78: 18183
A79: Debt at balance-sheet date | C79: 9654.585
A80: Cash at balance-sheet date | C80: 10315.724
A81: Minority interest (book) | C81: 22465.512
A82: Associates & investments (book) | C82: 6662.262
A83: Post-balance-sheet & other items (sourced, probability-weighted) | C83: 0
A84: Parent equity at balance-sheet date | C84: 16464.537
A85: Per-share factor | C85: 1000
A86: Risk-free rate | C86: =Drivers!$C$7
A87: Less: default spread (IDR only) | C87: =Drivers!$C$9
A88: Mature ERP + Indonesia CRP | C88: =Drivers!$C$10+Drivers!$C$11
A89: Tax rate | C89: =Drivers!$C$13
A90: Unlevered beta (industry default (config)) | C90: 0.9
A91: Debt / equity (market) | C91: 2
A92: Levered beta | C92: =$C$90*(1+(1-$C$89)*$C$91)
A93: Explicit company premium | C93: 0
A94: Cost of equity | C94: =$C$86-$C$87+$C$92*$C$88+$C$93
A95: Pre-tax cost of debt | C95: =$C$86+Drivers!$C$12
A96: WACC | C96: =1/(1+$C$91)*$C$94+$C$91/(1+$C$91)*$C$95*(1-$C$89)
A97: Terminal growth (capped) | C97: 0.0328
A99: Sum of the parts
A100: Value per share (IDR) — Sum of the parts (engine value) | C100: 57.666966
A102: P/E
A103: Target multiple (own five-year average) | C103: 10.475466
A104: Metric (LTM, or next-12m DPS for yield) | C104: 377.226
A105: Value per share (IDR) — P/E | C105: =MAX(0,$C$103*$C$104/$C$77*$C$85*1)
A107: P/BV
A108: Target multiple (own five-year average) | C108: 0.217757
...

Sheet BNBR
A1: PT Bakrie & Brothers Tbk (BNBR.JK) — Conglomerates & multi-sector holdings
A2: Units: IDR bn; per-share in IDR unless marked IDR. Model asof 2026-10-29 · data 2026-10-27
A4: Line | C4: Scalar | D4: FY2022A | E4: FY2023A | F4: FY2024A | G4: FY2025A | H4: FY2026E | I4: FY2027E | J4: FY2028E | K4: FY2029E | L4: FY2030E | M4: FY2031E | N4: FY2032E | O4: FY2033E | P4: FY2034E | Q4: FY2035E
A6: PARAMETERS
A7: ps_factor | C7: 1000
A8: vp_factor | C8: 1
A10: INPUTS (company assumptions)
A11: Revenue growth | B11: a.revenue_growth | H11: 0.38 | I11: 0.08 | J11: 0.06 | K11: 0.05 | L11: 0.04 | M11: 0.04 | N11: 0.04 | O11: 0.04 | P11: 0.04 | Q11: 0.04
A12: Gross margin at base input costs | B12: a.gross_margin | H12: 0.251 | I12: 0.251 | J12: 0.251 | K12: 0.251 | L12: 0.251 | M12: 0.251 | N12: 0.251 | O12: 0.251 | P12: 0.251 | Q12: 0.251
A13: SG&A / revenue | B13: a.opex_pct | H13: 0.142 | I13: 0.142 | J13: 0.142 | K13: 0.142 | L13: 0.142 | M13: 0.142 | N13: 0.142 | O13: 0.142 | P13: 0.142 | Q13: 0.142
A14: D&A / revenue | B14: a.da_pct | H14: 0.05 | I14: 0.05 | J14: 0.05 | K14: 0.05 | L14: 0.05 | M14: 0.05 | N14: 0.05 | O14: 0.05 | P14: 0.05 | Q14: 0.05
A15: Capex / revenue | B15: a.capex_pct | H15: 0.055 | I15: 0.055 | J15: 0.055 | K15: 0.055 | L15: 0.055 | M15: 0.055 | N15: 0.055 | O15: 0.055 | P15: 0.055 | Q15: 0.055
A16: Operating working capital / revenue | B16: a.nwc_pct | H16: 0.388 | I16: 0.388 | J16: 0.388 | K16: 0.388 | L16: 0.388 | M16: 0.388 | N16: 0.388 | O16: 0.388 | P16: 0.388 | Q16: 0.388
A17: Effective tax rate | B17: a.tax_rate | H17: 0.12 | I17: 0.12 | J17: 0.12 | K17: 0.12 | L17: 0.12 | M17: 0.12 | N17: 0.12 | O17: 0.12 | P17: 0.12 | Q17: 0.12
A18: Cost of debt (on opening debt) | B18: a.cost_of_debt | C18: 0.065
A19: Yield on opening cash | B19: a.cash_yield | C19: 0.055
A20: Net new borrowing | B20: a.net_borrowing | H20: 1000 | I20: 700 | J20: 650 | K20: 640 | L20: 630 | M20: 635.5 | N20: 651.3875 | O20: 667.67219 | P20: 684.36399 | Q20: 701.47309
A21: Other non-operating items | B21: a.other_nonop | H21: 0 | I21: 0 | J21: 0 | K21: 0 | L21: 0 | M21: 0 | N21: 0 | O21: 0 | P21: 0 | Q21: 0
A22: Minorities' share of net profit | B22: a.minority_pct | H22: 0.02 | I22: 0.02 | J22: 0.02 | K22: 0.02 | L22: 0.02 | M22: 0.02 | N22: 0.02 | O22: 0.02 | P22: 0.02 | Q22: 0.02
A23: Dividend payout | B23: a.payout | H23: 0 | I23: 0 | J23: 0 | K23: 0 | L23: 0 | M23: 0 | N23: 0 | O23: 0 | P23: 0 | Q23: 0
A24: Change in share count | B24: a.share_change | H24: 0.51851852 | I24: 0 | J24: 0 | K24: 0 | L24: 0 | M24: 0 | N24: 0 | O24: 0 | P24: 0 | Q24: 0
A25: Terminal growth (DCF) | B25: a.terminal_growth | C25: 0.04
A26: Holding-company discount to SOTP | B26: a.holdco_discount | C26: 0.38
A28: MODEL
A29: Revenue | B29: revenue | D29: 3626.696 | E29: 3759.484 | F29: 3869.905 | G29: 3742.973 | H29: =(G29*(1+H11)) | I29: =(H29*(1+I11)) | J29: =(I29*(1+J11)) | K29: =(J29*(1+K11)) | L29: =(K29*(1+L11)) | M29: =(L29*(1+M11)) | N29: =(M29*(1+N11)) | O29: =(N29*(1+O11)) | ... Q29: =(P29*(1+Q11))
A30: Cost of revenue | B30: cogs | D30: 2910.526 | E30: 2876.109 | F30: 3000.428 | G30: 2998.589 | H30: =(H29*(1-H12)) | I30: =(I29*(1-I12)) | J30: =(J29*(1-J12)) | K30: =(K29*(1-K12)) | L30: =(L29*(1-L12)) | M30: =(M29*(1-M12)) | N30: =(N29*(1-N12)) | O30: =(O29*(1-O12)) | ... Q30: =(Q29*(1-Q12))
A31: Gross profit | B31: gross_profit | D31: 716.17 | E31: 883.375 | F31: 869.477 | G31: 744.384 | H31: =(H29-H30) | I31: =(I29-I30) | J31: =(J29-J30) | K31: =(K29-K30) | L31: =(L29-L30) | M31: =(M29-M30) | N31: =(N29-N30) | O31: =(O29-O30) | ... Q31: =(Q29-Q30)
A32: SG&A and other opex | B32: opex | D32: 800.065 | E32: 567.174 | F32: 586.605 | G32: 627.521 | H32: =(H29*H13) | I32: =(I29*I13) | J32: =(J29*J13) | K32: =(K29*K13) | L32: =(L29*L13) | M32: =(M29*M13) | N32: =(N29*N13) | O32: =(O29*O13) | ... Q32: =(Q29*Q13)
A33: EBIT | B33: ebit | D33: -83.895 | E33: 316.201 | F33: 282.872 | G33: 116.863 | H33: =(H31-H32) | I33: =(I31-I32) | J33: =(J31-J32) | K33: =(K31-K32) | L33: =(L31-L32) | M33: =(M31-M32) | N33: =(N31-N32) | O33: =(O31-O32) | ... Q33: =(Q31-Q32)
A34: Depreciation & amortisation | B34: da | D34: 3.19 | E34: 5.514 | F34: 115.127 | G34: 171.363 | H34: =(H29*H14) | I34: =(I29*I14) | J34: =(J29*J14) | K34: =(K29*K14) | L34: =(L29*L14) | M34: =(M29*M14) | N34: =(N29*N14) | O34: =(O29*O14) | ... Q34: =(Q29*Q14)
A35: EBITDA | B35: ebitda | D35: -80.705 | E35: 321.715 | F35: 397.999 | G35: 288.226 | H35: =(H33+H34) | I35: =(I33+I34) | J35: =(J33+J34) | K35: =(K33+K34) | L35: =(L33+L34) | M35: =(M33+M34) | N35: =(N33+N34) | O35: =(O33+O34) | ... Q35: =(Q33+Q34)
A36: Interest expense | B36: interest_expense | D36: 56.361 | E36: 65.3 | F36: 54.837 | G36: 175.837 | H36: =(G56*$C$18) | I36: =(H56*$C$18) | J36: =(I56*$C$18) | K36: =(J56*$C$18) | L36: =(K56*$C$18) | M36: =(L56*$C$18) | N36: =(M56*$C$18) | O36: =(N56*$C$18) | ... Q36: =(P56*$C$18)
A37: Interest income | B37: interest_income | D37: 4.867 | E37: 12.703 | F37: 13.815 | G37: 93.544 | H37: =(G55*$C$19) | I37: =(H55*$C$19) | J37: =(I55*$C$19) | K37: =(J55*$C$19) | L37: =(K55*$C$19) | M37: =(L55*$C$19) | N37: =(M55*$C$19) | O37: =(N55*$C$19) | ... Q37: =(P55*$C$19)
A38: Other non-operating | B38: other_nonop | D38: 489.109 | E38: 54.364 | F38: 147.38 | G38: 484.262 | H38: =H21 | I38: =I21 | J38: =J21 | K38: =K21 | L38: =L21 | M38: =M21 | N38: =N21 | O38: =O21 | ... Q38: =Q21
A39: Profit before tax | B39: pbt | D39: 353.72 | E39: 317.968 | F39: 389.23 | G39: 518.832 | H39: =(((H33-H36)+H37)+H38) | I39: =(((I33-I36)+I37)+I38) | J39: =(((J33-J36)+J37)+J38) | K39: =(((K33-K36)+K37)+K38) | L39: =(((L33-L36)+L37)+L38) | M39: =(((M33-M36)+M37)+M38) | N39: =(((N33-N36)+N37)+N38) | O39: =(((O33-O36)+O37)+O38) | ... Q39: =(((Q33-Q36)+Q37)+Q38)
A40: Tax | B40: tax | D40: 47.559 | E40: 53.51 | F40: 53.182 | G40: 16.089 | H40: =(MAX(H39,0)*H17) | I40: =(MAX(I39,0)*I17) | J40: =(MAX(J39,0)*J17) | K40: =(MAX(K39,0)*K17) | L40: =(MAX(L39,0)*L17) | M40: =(MAX(M39,0)*M17) | N40: =(MAX(N39,0)*N17) | O40: =(MAX(O39,0)*O17) | ... Q40: =(MAX(Q39,0)*Q17)
A41: Net profit (incl. minorities) | B41: np | D41: 306.161 | E41: 264.458 | F41: 336.048 | G41: 502.743 | H41: =(H39-H40) | I41: =(I39-I40) | J41: =(J39-J40) | K41: =(K39-K40) | L41: =(L39-L40) | M41: =(M39-M40) | N41: =(N39-N40) | O41: =(O39-O40) | ... Q41: =(Q39-Q40)
A42: Minority interests | B42: minority | D42: 40.027 | E42: 26.99 | F42: 8.458 | G42: 8.891 | H42: =(H41*H22) | I42: =(I41*I22) | J42: =(J41*J22) | K42: =(K41*K22) | L42: =(L41*L22) | M42: =(M41*M22) | N42: =(N41*N22) | O42: =(O41*O22) | ... Q42: =(Q41*Q22)
A43: Net profit to parent | B43: np_parent | D43: 266.134 | E43: 237.468 | F43: 327.59 | G43: 493.852 | H43: =(H41-H42) | I43: =(I41-I42) | J43: =(J41-J42) | K43: =(K41-K42) | L43: =(L41-L42) | M43: =(M41-M42) | N43: =(N41-N42) | O43: =(O41-O42) | ... Q43: =(Q41-Q42)
A44: Shares outstanding (m) | B44: shares | D44: 23599.273 | E44: 185717.52 | F44: 201414.78 | G44: 173416.83 | H44: =(G44*(1+H24)) | I44: =(H44*(1+I24)) | J44: =(I44*(1+J24)) | K44: =(J44*(1+K24)) | L44: =(K44*(1+L24)) | M44: =(L44*(1+M24)) | N44: =(M44*(1+N24)) | O44: =(N44*(1+O24)) | ... Q44: =(P44*(1+Q24))
A45: EPS | B45: eps | D45: 11.277212 | E45: 1.2786516 | F45: 1.6264447 | G45: 2.8477743 | H45: =(IF(H44=0,0,H43/H44)*$C$7) | I45: =(IF(I44=0,0,I43/I44)*$C$7) | J45: =(IF(J44=0,0,J43/J44)*$C$7) | K45: =(IF(K44=0,0,K43/K44)*$C$7) | L45: =(IF(L44=0,0,L43/L44)*$C$7) | M45: =(IF(M44=0,0,M43/M44)*$C$7) | N45: =(IF(N44=0,0,N43/N44)*$C$7) | O45: =(IF(O44=0,0,O43/O44)*$C$7) | ... Q45: =(IF(Q44=0,0,Q43/Q44)*$C$7)
A46: DPS (declared on the year) | B46: dps | D46: 0 | E46: 0 | F46: 0 | G46: 0 | H46: =(MAX(H45,0)*H23) | I46: =(MAX(I45,0)*I23) | J46: =(MAX(J45,0)*J23) | K46: =(MAX(K45,0)*K23) | L46: =(MAX(L45,0)*L23) | M46: =(MAX(M45,0)*M23) | N46: =(MAX(N45,0)*N23) | O46: =(MAX(O45,0)*O23) | ... Q46: =(MAX(Q45,0)*Q23)
A47: Dividends paid | B47: dividends_paid | H47: =IF($C$7=0,0,(G46*G44)/$C$7) | I47: =IF($C$7=0,0,(H46*H44)/$C$7) | J47: =IF($C$7=0,0,(I46*I44)/$C$7) | K47: =IF($C$7=0,0,(J46*J44)/$C$7) | L47: =IF($C$7=0,0,(K46*K44)/$C$7) | M47: =IF($C$7=0,0,(L46*L44)/$C$7) | N47: =IF($C$7=0,0,(M46*M44)/$C$7) | O47: =IF($C$7=0,0,(N46*N44)/$C$7) | ... Q47: =IF($C$7=0,0,(P46*P44)/$C$7)
A48: Capital expenditure | B48: capex | D48: 52.943 | E48: 105.978 | F48: 364.186 | G48: 195.704 | H48: =(H29*H15) | I48: =(I29*I15) | J48: =(J29*J15) | K48: =(K29*K15) | L48: =(L29*L15) | M48: =(M29*M15) | N48: =(N29*N15) | O48: =(O29*O15) | ... Q48: =(Q29*Q15)
A49: Change in working capital | B49: delta_nwc | E49: 12108.694 | F49: 681.3 | G49: 99.136 | H49: =(H54-G54) | I49: =(I54-H54) | J49: =(J54-I54) | K49: =(K54-J54) | L49: =(L54-K54) | M49: =(M54-L54) | N49: =(N54-M54) | O49: =(O54-N54) | ... Q49: =(Q54-P54)
A50: Free cash flow to firm | B50: fcff | E50: -11946.17 | F50: -686.1369 | G50: -10.237926 | H50: =((((H33*(1-H17))+H34)-H48)-H49) | I50: =((((I33*(1-I17))+I34)-I48)-I49) | J50: =((((J33*(1-J17))+J34)-J48)-J49) | K50: =((((K33*(1-K17))+K34)-K48)-K49) | L50: =((((L33*(1-L17))+L34)-L48)-L49) | M50: =((((M33*(1-M17))+M34)-M48)-M49) | N50: =((((N33*(1-N17))+N34)-N48)-N49) | O50: =((((O33*(1-O17))+O34)-O48)-O49) | ... Q50: =((((Q33*(1-Q17))+Q34)-Q48)-Q49)
A51: Net borrowing | B51: net_borrowing | E51: 145.318 | F51: -951.393 | G51: 15515.103 | H51: =H20 | I51: =I20 | J51: =J20 | K51: =K20 | L51: =L20 | M51: =M20 | N51: =N20 | O51: =O20 | ... Q51: =Q20
A52: Dividends to minorities | B52: minority_div | H52: =(MAX(G42,0)*H23) | I52: =(MAX(H42,0)*I23) | J52: =(MAX(I42,0)*J23) | K52: =(MAX(J42,0)*K23) | L52: =(MAX(K42,0)*L23) | M52: =(MAX(L42,0)*M23) | N52: =(MAX(M42,0)*N23) | O52: =(MAX(N42,0)*O23) | ... Q52: =(MAX(P42,0)*Q23)
A53: Free cash flow to equity | B53: fcfe | H53: =(((((H41+H34)-H48)-H49)+H51)-H52) | I53: =(((((I41+I34)-I48)-I49)+I51)-I52) | J53: =(((((J41+J34)-J48)-J49)+J51)-J52) | K53: =(((((K41+K34)-K48)-K49)+K51)-K52) | L53: =(((((L41+L34)-L48)-L49)+L51)-L52) | M53: =(((((M41+M34)-M48)-M49)+M51)-M52) | N53: =(((((N41+N34)-N48)-N49)+N51)-N52) | O53: =(((((O41+O34)-O48)-O49)+O51)-O52) | ... Q53: =(((((Q41+Q34)-Q48)-Q49)+Q51)-Q52)
A54: Operating working capital | B54: nwc | D54: -11435.275 | E54: 673.419 | F54: 1354.719 | G54: 1453.855 | H54: =(H29*H16) | I54: =(I29*I16) | J54: =(J29*J16) | K54: =(K29*K16) | L54: =(L29*L16) | M54: =(M29*M16) | N54: =(N29*N16) | O54: =(O29*O16) | ... Q54: =(Q29*Q16)
A55: Cash & equivalents | B55: cash | D55: 12286.75 | E55: 1466.188 | F55: 1023.001 | G55: 1557.818 | H55: =(((((((G55+H41)+H34)-H48)-H49)+H51)-H47)-H52) | I55: =(((((((H55+I41)+I34)-I48)-I49)+I51)-I47)-I52) | J55: =(((((((I55+J41)+J34)-J48)-J49)+J51)-J47)-J52) | K55: =(((((((J55+K41)+K34)-K48)-K49)+K51)-K47)-K52) | L55: =(((((((K55+L41)+L34)-L48)-L49)+L51)-L47)-L52) | M55: =(((((((L55+M41)+M34)-M48)-M49)+M51)-M47)-M52) | N55: =(((((((M55+N41)+N34)-N48)-N49)+N51)-N47)-N52) | O55: =(((((((N55+O41)+O34)-O48)-O49)+O51)-O47)-O52) | ... Q55: =(((((((P55+Q41)+Q34)-Q48)-Q49)+Q51)-Q47)-Q52)
A56: Total debt | B56: debt | D56: 2039.306 | E56: 2184.624 | F56: 1233.231 | G56: 16748.334 | H56: =(G56+H51) | I56: =(H56+I51) | J56: =(I56+J51) | K56: =(J56+K51) | L56: =(K56+L51) | M56: =(L56+M51) | N56: =(M56+N51) | O56: =(N56+O51) | ... Q56: =(P56+Q51)
A57: Fixed assets (net) | B57: ppe | D57: 1749.054 | E57: 1789.682 | F57: 2164.861 | G57: 2274.582 | H57: =((G57+H48)-H34) | I57: =((H57+I48)-I34) | J57: =((I57+J48)-J34) | K57: =((J57+K48)-K34) | L57: =((K57+L48)-L34) | M57: =((L57+M48)-M34) | N57: =((M57+N48)-N34) | O57: =((N57+O48)-O34) | ... Q57: =((P57+Q48)-Q34)
A58: Parent shareholders' equity | B58: equity | D58: 1432.532 | E58: 2177.916 | F58: 3254.872 | G58: 3853.17 | H58: =((G58+H43)-H47) | I58: =((H58+I43)-I47) | J58: =((I58+J43)-J47) | K58: =((J58+K43)-K47) | L58: =((K58+L43)-L47) | M58: =((L58+M43)-M47) | N58: =((M58+N43)-N47) | O58: =((N58+O43)-O47) | ... Q58: =((P58+Q43)-Q47)
A59: Minority interest (balance sheet) | B59: minority_bs | D59: 93.716 | E59: 482.747 | F59: 656.794 | G59: 818.494 | H59: =((G59+H42)-H52) | I59: =((H59+I42)-I52) | J59: =((I59+J42)-J52) | K59: =((J59+K42)-K52) | L59: =((K59+L42)-L52) | M59: =((L59+M42)-M52) | N59: =((M59+N42)-N52) | O59: =((N59+O42)-O52) | ... Q59: =((P59+Q42)-Q52)
A60: Other assets less other liabilities | B60: other_net | D60: 965.025 | E60: 915.998 | F60: 602.316 | G60: 16133.743 | H60: =G60 | I60: =H60 | J60: =I60 | K60: =J60 | L60: =K60 | M60: =L60 | N60: =M60 | O60: =N60 | ... Q60: =P60
A61: Balance check (should be zero) | B61: bs_check | H61: =((((((H55+H54)+H57)+H60)-H56)-H58)-H59) | I61: =((((((I55+I54)+I57)+I60)-I56)-I58)-I59) | J61: =((((((J55+J54)+J57)+J60)-J56)-J58)-J59) | K61: =((((((K55+K54)+K57)+K60)-K56)-K58)-K59) | L61: =((((((L55+L54)+L57)+L60)-L56)-L58)-L59) | M61: =((((((M55+M54)+M57)+M60)-M56)-M58)-M59) | N61: =((((((N55+N54)+N57)+N60)-N56)-N58)-N59) | O61: =((((((O55+O54)+O57)+O60)-O56)-O58)-O59) | ... Q61: =((((((Q55+Q54)+Q57)+Q60)-Q56)-Q58)-Q59)
A62: Net debt (cash) | B62: net_debt | D62: -10247.444 | E62: 718.436 | F62: 210.23 | G62: 15190.516 | H62: =(H56-H55) | I62: =(I56-I55) | J62: =(J56-J55) | K62: =(K56-K55) | L62: =(L56-L55) | M62: =(M56-M55) | N62: =(N56-N55) | O62: =(O56-O55) | ... Q62: =(Q56-Q55)
A63: Book value per share | B63: bvps | D63: 60.702379 | E63: 11.727036 | F63: 16.160045 | G63: 22.219123 | H63: =(IF(H44=0,0,H58/H44)*$C$7) | I63: =(IF(I44=0,0,I58/I44)*$C$7) | J63: =(IF(J44=0,0,J58/J44)*$C$7) | K63: =(IF(K44=0,0,K58/K44)*$C$7) | L63: =(IF(L44=0,0,L58/L44)*$C$7) | M63: =(IF(M44=0,0,M58/M44)*$C$7) | N63: =(IF(N44=0,0,N58/N44)*$C$7) | O63: =(IF(O44=0,0,O58/O44)*$C$7) | ... Q63: =(IF(Q44=0,0,Q58/Q44)*$C$7)
A64: Revenue growth | B64: revenue_growth | E64: 0.036614042 | F64: 0.029371318 | G64: -0.032799772 | H64: =(IF(G29=0,0,H29/G29)-1) | I64: =(IF(H29=0,0,I29/H29)-1) | J64: =(IF(I29=0,0,J29/I29)-1) | K64: =(IF(J29=0,0,K29/J29)-1) | L64: =(IF(K29=0,0,L29/K29)-1) | M64: =(IF(L29=0,0,M29/L29)-1) | N64: =(IF(M29=0,0,N29/M29)-1) | O64: =(IF(N29=0,0,O29/N29)-1) | ... Q64: =(IF(P29=0,0,Q29/P29)-1)
A65: Gross margin | B65: gross_margin | D65: 0.19747175 | E65: 0.23497241 | F65: 0.22467657 | G65: 0.19887507 | H65: =IF(H29=0,0,H31/H29) | I65: =IF(I29=0,0,I31/I29) | J65: =IF(J29=0,0,J31/J29) | K65: =IF(K29=0,0,K31/K29) | L65: =IF(L29=0,0,L31/L29) | M65: =IF(M29=0,0,M31/M29) | N65: =IF(N29=0,0,N31/N29) | O65: =IF(O29=0,0,O31/O29) | ... Q65: =IF(Q29=0,0,Q31/Q29)
A66: EBITDA margin | B66: ebitda_margin | D66: -0.022253037 | E66: 0.085574244 | F66: 0.10284464 | G66: 0.077004563 | H66: =IF(H29=0,0,H35/H29) | I66: =IF(I29=0,0,I35/I29) | J66: =IF(J29=0,0,J35/J29) | K66: =IF(K29=0,0,K35/K29) | L66: =IF(L29=0,0,L35/L29) | M66: =IF(M29=0,0,M35/M29) | N66: =IF(N29=0,0,N35/N29) | O66: =IF(O29=0,0,O35/O29) | ... Q66: =IF(Q29=0,0,Q35/Q29)
A67: EBIT margin | B67: ebit_margin | D67: -0.023132625 | E67: 0.084107553 | F67: 0.073095334 | G67: 0.031221972 | H67: =IF(H29=0,0,H33/H29) | I67: =IF(I29=0,0,I33/I29) | J67: =IF(J29=0,0,J33/J29) | K67: =IF(K29=0,0,K33/K29) | L67: =IF(L29=0,0,L33/L29) | M67: =IF(M29=0,0,M33/M29) | N67: =IF(N29=0,0,N33/N29) | O67: =IF(O29=0,0,O33/O29) | ... Q67: =IF(Q29=0,0,Q33/Q29)
A68: Net margin | B68: np_margin | D68: 0.073381943 | E68: 0.063165051 | F68: 0.084650657 | G68: 0.13194111 | H68: =IF(H29=0,0,H43/H29) | I68: =IF(I29=0,0,I43/I29) | J68: =IF(J29=0,0,J43/J29) | K68: =IF(K29=0,0,K43/K29) | L68: =IF(L29=0,0,L43/L29) | M68: =IF(M29=0,0,M43/M29) | N68: =IF(N29=0,0,N43/N29) | O68: =IF(O29=0,0,O43/O29) | ... Q68: =IF(Q29=0,0,Q43/Q29)
A69: EPS growth | B69: eps_growth | E69: -0.88661634 | F69: 0.27199987 | G69: 0.75091987 | H69: =(IF(G45=0,0,H45/G45)-1) | I69: =(IF(H45=0,0,I45/H45)-1) | J69: =(IF(I45=0,0,J45/I45)-1) | K69: =(IF(J45=0,0,K45/J45)-1) | L69: =(IF(K45=0,0,L45/K45)-1) | M69: =(IF(L45=0,0,M45/L45)-1) | N69: =(IF(M45=0,0,N45/M45)-1) | O69: =(IF(N45=0,0,O45/N45)-1) | ... Q69: =(IF(P45=0,0,Q45/P45)-1)
A70: ROE | B70: roe | E70: 0.13154489 | F70: 0.12059738 | G70: 0.13895585 | H70: =IF(IF(2=0,0,(H58+G58)/2)=0,0,H43/IF(2=0,0,(H58+G58)/2)) | I70: =IF(IF(2=0,0,(I58+H58)/2)=0,0,I43/IF(2=0,0,(I58+H58)/2)) | J70: =IF(IF(2=0,0,(J58+I58)/2)=0,0,J43/IF(2=0,0,(J58+I58)/2)) | K70: =IF(IF(2=0,0,(K58+J58)/2)=0,0,K43/IF(2=0,0,(K58+J58)/2)) | L70: =IF(IF(2=0,0,(L58+K58)/2)=0,0,L43/IF(2=0,0,(L58+K58)/2)) | M70: =IF(IF(2=0,0,(M58+L58)/2)=0,0,M43/IF(2=0,0,(M58+L58)/2)) | N70: =IF(IF(2=0,0,(N58+M58)/2)=0,0,N43/IF(2=0,0,(N58+M58)/2)) | O70: =IF(IF(2=0,0,(O58+N58)/2)=0,0,O43/IF(2=0,0,(O58+N58)/2)) | ... Q70: =IF(IF(2=0,0,(Q58+P58)/2)=0,0,Q43/IF(2=0,0,(Q58+P58)/2))
A71: Net debt / EBITDA | B71: net_debt_ebitda | D71: 126.97409 | E71: 2.2331442 | F71: 0.52821741 | G71: 52.70349 | H71: =IF(H35=0,0,H62/H35) | I71: =IF(I35=0,0,I62/I35) | J71: =IF(J35=0,0,J62/J35) | K71: =IF(K35=0,0,K62/K35) | L71: =IF(L35=0,0,L62/L35) | M71: =IF(M35=0,0,M62/M35) | N71: =IF(N35=0,0,N62/N35) | O71: =IF(O35=0,0,O62/O35) | ... Q71: =IF(Q35=0,0,Q62/Q35)
A72: Payout ratio | B72: payout_ratio | D72: 0 | E72: 0 | F72: 0 | G72: 0 | H72: =IF(H45=0,0,H46/H45) | I72: =IF(I45=0,0,I46/I45) | J72: =IF(J45=0,0,J46/J45) | K72: =IF(K45=0,0,K46/K45) | L72: =IF(L45=0,0,L46/L45) | M72: =IF(M45=0,0,M46/M45) | N72: =IF(N45=0,0,N46/N45) | O72: =IF(O45=0,0,O46/O45) | ... Q72: =IF(Q45=0,0,Q46/Q45)
A73: Capex / revenue | B73: capex_revenue | D73: 0.014598136 | E73: 0.028189507 | F73: 0.09410722 | G73: 0.05228571 | H73: =IF(H29=0,0,H48/H29) | I73: =IF(I29=0,0,I48/I29) | J73: =IF(J29=0,0,J48/J29) | K73: =IF(K29=0,0,K48/K29) | L73: =IF(L29=0,0,L48/L29) | M73: =IF(M29=0,0,M48/M29) | N73: =IF(N29=0,0,N48/N29) | O73: =IF(O29=0,0,O48/O29) | ... Q73: =IF(Q29=0,0,Q48/Q29)
A75: VALUATION
A76: Last price (IDR) | C76: 51
A77: Shares outstanding (m) | C77: 263336.67
A78: IDR per USD (spot) | C78: 18183
A79: Debt at balance-sheet date | C79: 16968.639
A80: Cash at balance-sheet date | C80: 1432.62
A81: Minority interest (book) | C81: 821.887
A82: Associates & investments (book) | C82: 10
A83: Post-balance-sheet & other items (sourced, probability-weighted) | C83: 4543
A84: Parent equity at balance-sheet date | C84: 8470.09
A85: Per-share factor | C85: 1000
A86: Risk-free rate | C86: =Drivers!$C$7
A87: Less: default spread (IDR only) | C87: =Drivers!$C$9
A88: Mature ERP + Indonesia CRP | C88: =Drivers!$C$10+Drivers!$C$11
A89: Tax rate | C89: =Drivers!$C$13
A90: Unlevered beta (industry default (config)) | C90: 0.9
A91: Debt / equity (market) | C91: 1.6519066
A92: Levered beta | C92: =$C$90*(1+(1-$C$89)*$C$91)
A93: Explicit company premium | C93: 0
A94: Cost of equity | C94: =$C$86-$C$87+$C$92*$C$88+$C$93
A95: Pre-tax cost of debt | C95: =$C$86+Drivers!$C$12
A96: WACC | C96: =1/(1+$C$91)*$C$94+$C$91/(1+$C$91)*$C$95*(1-$C$89)
A97: Terminal growth (capped) | C97: 0.04
A99: Sum of the parts
A100: Value per share (IDR) — Sum of the parts (engine value) | C100: 19.767945
A102: P/BV
A103: Target multiple (peer median) | C103: 1.946731
A104: Metric (LTM, or next-12m DPS for yield) | C104: 8470.09
A105: Value per share (IDR) — P/BV | C105: =MAX(0,$C$103*$C$104/$C$77*$C$85*1)
A107: TARGET
A108: Weight: Sum of the parts | C108: 0.8
...

Sheet BRPT
A1: PT Barito Pacific Tbk (BRPT.JK) — Conglomerates & multi-sector holdings
A2: Units: USD m; per-share in USD unless marked IDR. Model asof 2026-10-29 · data 2026-10-27
A4: Line | C4: Scalar | D4: FY2022A | E4: FY2023A | F4: FY2024A | G4: FY2025A | H4: FY2026E | I4: FY2027E | J4: FY2028E | K4: FY2029E | L4: FY2030E | M4: FY2031E | N4: FY2032E | O4: FY2033E | P4: FY2034E | Q4: FY2035E
A6: PARAMETERS
A7: ps_factor | C7: 1
A8: vp_factor | C8: 1
A10: INPUTS (company assumptions)
A11: Revenue growth | B11: a.revenue_growth | H11: 0.3 | I11: 0.1 | J11: 0.07 | K11: 0.05 | L11: 0.04 | M11: 0.02 | N11: 0.02 | O11: 0.02 | P11: 0.02 | Q11: 0.02
A12: Gross margin at base input costs | B12: a.gross_margin | H12: 0.191901 | I12: 0.191901 | J12: 0.191901 | K12: 0.191901 | L12: 0.191901 | M12: 0.191901 | N12: 0.191901 | O12: 0.191901 | P12: 0.191901 | Q12: 0.191901
A13: SG&A / revenue | B13: a.opex_pct | H13: 0.111429 | I13: 0.111429 | J13: 0.111429 | K13: 0.111429 | L13: 0.111429 | M13: 0.111429 | N13: 0.111429 | O13: 0.111429 | P13: 0.111429 | Q13: 0.111429
A14: D&A / revenue | B14: a.da_pct | H14: 0.043116 | I14: 0.043116 | J14: 0.043116 | K14: 0.043116 | L14: 0.043116 | M14: 0.043116 | N14: 0.043116 | O14: 0.043116 | P14: 0.043116 | Q14: 0.043116
A15: Capex / revenue | B15: a.capex_pct | H15: 0.127661 | I15: 0.127661 | J15: 0.127661 | K15: 0.127661 | L15: 0.127661 | M15: 0.127661 | N15: 0.127661 | O15: 0.127661 | P15: 0.127661 | Q15: 0.127661
A16: Operating working capital / revenue | B16: a.nwc_pct | H16: 0.183589 | I16: 0.183589 | J16: 0.183589 | K16: 0.183589 | L16: 0.183589 | M16: 0.183589 | N16: 0.183589 | O16: 0.183589 | P16: 0.183589 | Q16: 0.183589
A17: Effective tax rate | B17: a.tax_rate | H17: 0.338994 | I17: 0.338994 | J17: 0.338994 | K17: 0.338994 | L17: 0.338994 | M17: 0.338994 | N17: 0.338994 | O17: 0.338994 | P17: 0.338994 | Q17: 0.338994
A18: Cost of debt (on opening debt) | B18: a.cost_of_debt | C18: 0.078279
A19: Yield on opening cash | B19: a.cash_yield | C19: 0.060805
A20: Net new borrowing | B20: a.net_borrowing | H20: 0 | I20: 0 | J20: 0 | K20: 0 | L20: 0 | M20: 0 | N20: 0 | O20: 0 | P20: 0 | Q20: 0
A21: Other non-operating items | B21: a.other_nonop | H21: 0 | I21: 0 | J21: 0 | K21: 0 | L21: 0 | M21: 0 | N21: 0 | O21: 0 | P21: 0 | Q21: 0
A22: Minorities' share of net profit | B22: a.minority_pct | H22: 0.658493 | I22: 0.658493 | J22: 0.658493 | K22: 0.658493 | L22: 0.658493 | M22: 0.658493 | N22: 0.658493 | O22: 0.658493 | P22: 0.658493 | Q22: 0.658493
A23: Dividend payout | B23: a.payout | H23: 1 | I23: 1 | J23: 1 | K23: 1 | L23: 1 | M23: 1 | N23: 1 | O23: 1 | P23: 1 | Q23: 1
A24: Change in share count | B24: a.share_change | H24: 0 | I24: 0 | J24: 0 | K24: 0 | L24: 0 | M24: 0 | N24: 0 | O24: 0 | P24: 0 | Q24: 0
A25: Terminal growth (DCF) | B25: a.terminal_growth | C25: 0.02
A26: Holding-company discount to SOTP | B26: a.holdco_discount | C26: 0.3
A28: MODEL
A29: Revenue | B29: revenue | D29: 2961.532 | E29: 2760.359 | F29: 2386.995 | G29: 7630.662 | H29: =(G29*(1+H11)) | I29: =(H29*(1+I11)) | J29: =(I29*(1+J11)) | K29: =(J29*(1+K11)) | L29: =(K29*(1+L11)) | M29: =(L29*(1+M11)) | N29: =(M29*(1+N11)) | O29: =(N29*(1+O11)) | ... Q29: =(P29*(1+Q11))
A30: Cost of revenue | B30: cogs | D30: 2515.859 | E30: 2202.219 | F30: 1666.836 | G30: 7082.758 | H30: =(H29*(1-H12)) | I30: =(I29*(1-I12)) | J30: =(J29*(1-J12)) | K30: =(K29*(1-K12)) | L30: =(L29*(1-L12)) | M30: =(M29*(1-M12)) | N30: =(N29*(1-N12)) | O30: =(O29*(1-O12)) | ... Q30: =(Q29*(1-Q12))
A31: Gross profit | B31: gross_profit | D31: 445.673 | E31: 558.14 | F31: 720.159 | G31: 547.904 | H31: =(H29-H30) | I31: =(I29-I30) | J31: =(J29-J30) | K31: =(K29-K30) | L31: =(L29-L30) | M31: =(M29-M30) | N31: =(N29-N30) | O31: =(O29-O30) | ... Q31: =(Q29-Q30)
A32: SG&A and other opex | B32: opex | D32: 177.859 | E32: 209.066 | F32: 381.684 | G32: 752.749 | H32: =(H29*H13) | I32: =(I29*I13) | J32: =(J29*J13) | K32: =(K29*K13) | L32: =(L29*L13) | M32: =(M29*M13) | N32: =(N29*N13) | O32: =(O29*O13) | ... Q32: =(Q29*Q13)
A33: EBIT | B33: ebit | D33: 267.814 | E33: 349.074 | F33: 338.475 | G33: -204.845 | H33: =(H31-H32) | I33: =(I31-I32) | J33: =(J31-J32) | K33: =(K31-K32) | L33: =(L31-L32) | M33: =(M31-M32) | N33: =(N31-N32) | O33: =(O31-O32) | ... Q33: =(Q31-Q32)
A34: Depreciation & amortisation | B34: da | D34: 2.533 | E34: 4.041 | F34: 208.64 | G34: 308.865 | H34: =(H29*H14) | I34: =(I29*I14) | J34: =(J29*J14) | K34: =(K29*K14) | L34: =(L29*L14) | M34: =(M29*M14) | N34: =(N29*N14) | O34: =(O29*O14) | ... Q34: =(Q29*Q14)
A35: EBITDA | B35: ebitda | D35: 270.347 | E35: 353.115 | F35: 547.115 | G35: 104.02 | H35: =(H33+H34) | I35: =(I33+I34) | J35: =(J33+J34) | K35: =(K33+K34) | L35: =(L33+L34) | M35: =(M33+M34) | N35: =(N33+N34) | O35: =(O33+O34) | ... Q35: =(Q33+Q34)
A36: Interest expense | B36: interest_expense | D36: 191.858 | E36: 300.843 | F36: 320.228 | G36: 390.532 | H36: =(G56*$C$18) | I36: =(H56*$C$18) | J36: =(I56*$C$18) | K36: =(J56*$C$18) | L36: =(K56*$C$18) | M36: =(L56*$C$18) | N36: =(M56*$C$18) | O36: =(N56*$C$18) | ... Q36: =(P56*$C$18)
A37: Interest income | B37: interest_income | D37: 30.265 | E37: 104.146 | F37: 128.811 | G37: 152.342 | H37: =(G55*$C$19) | I37: =(H55*$C$19) | J37: =(I55*$C$19) | K37: =(J55*$C$19) | L37: =(K55*$C$19) | M37: =(L55*$C$19) | N37: =(M55*$C$19) | O37: =(N55*$C$19) | ... Q37: =(P55*$C$19)
A38: Other non-operating | B38: other_nonop | D38: 49.202 | E38: 70.841 | F38: 85.638 | G38: 2046.023 | H38: =H21 | I38: =I21 | J38: =J21 | K38: =K21 | L38: =L21 | M38: =M21 | N38: =N21 | O38: =O21 | ... Q38: =Q21
A39: Profit before tax | B39: pbt | D39: 155.423 | E39: 223.218 | F39: 232.696 | G39: 1602.988 | H39: =(((H33-H36)+H37)+H38) | I39: =(((I33-I36)+I37)+I38) | J39: =(((J33-J36)+J37)+J38) | K39: =(((K33-K36)+K37)+K38) | L39: =(((L33-L36)+L37)+L38) | M39: =(((M33-M36)+M37)+M38) | N39: =(((N33-N36)+N37)+N38) | O39: =(((O33-O36)+O37)+O38) | ... Q39: =(((Q33-Q36)+Q37)+Q38)
A40: Tax | B40: tax | D40: 123.213 | E40: 123.442 | F40: 109.8 | G40: -12.646 | H40: =(MAX(H39,0)*H17) | I40: =(MAX(I39,0)*I17) | J40: =(MAX(J39,0)*J17) | K40: =(MAX(K39,0)*K17) | L40: =(MAX(L39,0)*L17) | M40: =(MAX(M39,0)*M17) | N40: =(MAX(N39,0)*N17) | O40: =(MAX(O39,0)*O17) | ... Q40: =(MAX(Q39,0)*Q17)
A41: Net profit (incl. minorities) | B41: np | D41: 32.21 | E41: 99.776 | F41: 122.896 | G41: 1615.634 | H41: =(H39-H40) | I41: =(I39-I40) | J41: =(J39-J40) | K41: =(K39-K40) | L41: =(L39-L40) | M41: =(M39-M40) | N41: =(N39-N40) | O41: =(O39-O40) | ... Q41: =(Q39-Q40)
A42: Minority interests | B42: minority | D42: 30.451 | E42: 73.66 | F42: 66.412 | G42: 1125.827 | H42: =(H41*H22) | I42: =(I41*I22) | J42: =(J41*J22) | K42: =(K41*K22) | L42: =(L41*L22) | M42: =(M41*M22) | N42: =(N41*N22) | O42: =(O41*O22) | ... Q42: =(Q41*Q22)
A43: Net profit to parent | B43: np_parent | D43: 1.759 | E43: 26.116 | F43: 56.484 | G43: 489.807 | H43: =(H41-H42) | I43: =(I41-I42) | J43: =(J41-J42) | K43: =(K41-K42) | L43: =(L41-L42) | M43: =(M41-M42) | N43: =(N41-N42) | O43: =(O41-O42) | ... Q43: =(Q41-Q42)
A44: Shares outstanding (m) | B44: shares | D44: 93711.466 | E44: 93711.466 | F44: 93708.446 | G44: 93711.741 | H44: =(G44*(1+H24)) | I44: =(H44*(1+I24)) | J44: =(I44*(1+J24)) | K44: =(J44*(1+K24)) | L44: =(K44*(1+L24)) | M44: =(L44*(1+M24)) | N44: =(M44*(1+N24)) | O44: =(N44*(1+O24)) | ... Q44: =(P44*(1+Q24))
A45: EPS | B45: eps | D45: 1.8770382e-05 | E45: 0.00027868521 | F45: 0.00060276317 | G45: 0.005226741 | H45: =(IF(H44=0,0,H43/H44)*$C$7) | I45: =(IF(I44=0,0,I43/I44)*$C$7) | J45: =(IF(J44=0,0,J43/J44)*$C$7) | K45: =(IF(K44=0,0,K43/K44)*$C$7) | L45: =(IF(L44=0,0,L43/L44)*$C$7) | M45: =(IF(M44=0,0,M43/M44)*$C$7) | N45: =(IF(N44=0,0,N43/N44)*$C$7) | O45: =(IF(O44=0,0,O43/O44)*$C$7) | ... Q45: =(IF(Q44=0,0,Q43/Q44)*$C$7)
A46: DPS (declared on the year) | B46: dps | D46: 0.00010538104 | E46: 5.341802e-05 | F46: 0 | G46: 9.0354268e-05 | H46: =(MAX(H45,0)*H23) | I46: =(MAX(I45,0)*I23) | J46: =(MAX(J45,0)*J23) | K46: =(MAX(K45,0)*K23) | L46: =(MAX(L45,0)*L23) | M46: =(MAX(M45,0)*M23) | N46: =(MAX(N45,0)*N23) | O46: =(MAX(O45,0)*O23) | ... Q46: =(MAX(Q45,0)*Q23)
A47: Dividends paid | B47: dividends_paid | D47: 78.771 | E47: 67.697 | F47: 73.367 | G47: 60.121 | H47: =IF($C$7=0,0,(G46*G44)/$C$7) | I47: =IF($C$7=0,0,(H46*H44)/$C$7) | J47: =IF($C$7=0,0,(I46*I44)/$C$7) | K47: =IF($C$7=0,0,(J46*J44)/$C$7) | L47: =IF($C$7=0,0,(K46*K44)/$C$7) | M47: =IF($C$7=0,0,(L46*L44)/$C$7) | N47: =IF($C$7=0,0,(M46*M44)/$C$7) | O47: =IF($C$7=0,0,(N46*N44)/$C$7) | ... Q47: =IF($C$7=0,0,(P46*P44)/$C$7)
A48: Capital expenditure | B48: capex | D48: 179.543 | E48: 123.988 | F48: 521.285 | G48: 913.247 | H48: =(H29*H15) | I48: =(I29*I15) | J48: =(J29*J15) | K48: =(K29*K15) | L48: =(L29*L15) | M48: =(M29*M15) | N48: =(N29*N15) | O48: =(O29*O15) | ... Q48: =(Q29*Q15)
A49: Change in working capital | B49: delta_nwc | E49: 8.441 | F49: 412.798 | G49: 192.245 | H49: =(H54-G54) | I49: =(I54-H54) | J49: =(J54-I54) | K49: =(K54-J54) | L49: =(L54-K54) | M49: =(M54-L54) | N49: =(N54-M54) | O49: =(O54-N54) | ... Q49: =(Q54-P54)
A50: Free cash flow to firm | B50: fcff | E50: 27.644253 | F50: -546.68091 | G50: -1003.088 | H50: =((((H33*(1-H17))+H34)-H48)-H49) | I50: =((((I33*(1-I17))+I34)-I48)-I49) | J50: =((((J33*(1-J17))+J34)-J48)-J49) | K50: =((((K33*(1-K17))+K34)-K48)-K49) | L50: =((((L33*(1-L17))+L34)-L48)-L49) | M50: =((((M33*(1-M17))+M34)-M48)-M49) | N50: =((((N33*(1-N17))+N34)-N48)-N49) | O50: =((((O33*(1-O17))+O34)-O48)-O49) | ... Q50: =((((Q33*(1-Q17))+Q34)-Q48)-Q49)
A51: Net borrowing | B51: net_borrowing | E51: 301.79 | F51: 370.665 | G51: 3465.454 | H51: =H20 | I51: =I20 | J51: =J20 | K51: =K20 | L51: =L20 | M51: =M20 | N51: =N20 | O51: =O20 | ... Q51: =Q20
A52: Dividends to minorities | B52: minority_div | H52: =(MAX(G42,0)*H23) | I52: =(MAX(H42,0)*I23) | J52: =(MAX(I42,0)*J23) | K52: =(MAX(J42,0)*K23) | L52: =(MAX(K42,0)*L23) | M52: =(MAX(L42,0)*M23) | N52: =(MAX(M42,0)*N23) | O52: =(MAX(N42,0)*O23) | ... Q52: =(MAX(P42,0)*Q23)
A53: Free cash flow to equity | B53: fcfe | H53: =(((((H41+H34)-H48)-H49)+H51)-H52) | I53: =(((((I41+I34)-I48)-I49)+I51)-I52) | J53: =(((((J41+J34)-J48)-J49)+J51)-J52) | K53: =(((((K41+K34)-K48)-K49)+K51)-K52) | L53: =(((((L41+L34)-L48)-L49)+L51)-L52) | M53: =(((((M41+M34)-M48)-M49)+M51)-M52) | N53: =(((((N41+N34)-N48)-N49)+N51)-N52) | O53: =(((((O41+O34)-O48)-O49)+O51)-O52) | ... Q53: =(((((Q41+Q34)-Q48)-Q49)+Q51)-Q52)
A54: Operating working capital | B54: nwc | D54: 318.812 | E54: 327.253 | F54: 740.051 | G54: 932.296 | H54: =(H29*H16) | I54: =(I29*I16) | J54: =(J29*J16) | K54: =(K29*K16) | L54: =(L29*L16) | M54: =(M29*M16) | N54: =(N29*N16) | O54: =(O29*O16) | ... Q54: =(Q29*Q16)
A55: Cash & equivalents | B55: cash | D55: 1980.83 | E55: 2453.115 | F55: 1970.032 | G55: 3565.203 | H55: =(((((((G55+H41)+H34)-H48)-H49)+H51)-H47)-H52) | I55: =(((((((H55+I41)+I34)-I48)-I49)+I51)-I47)-I52) | J55: =(((((((I55+J41)+J34)-J48)-J49)+J51)-J47)-J52) | K55: =(((((((J55+K41)+K34)-K48)-K49)+K51)-K47)-K52) | L55: =(((((((K55+L41)+L34)-L48)-L49)+L51)-L47)-L52) | M55: =(((((((L55+M41)+M34)-M48)-M49)+M51)-M47)-M52) | N55: =(((((((M55+N41)+N34)-N48)-N49)+N51)-N47)-N52) | O55: =(((((((N55+O41)+O34)-O48)-O49)+O51)-O47)-O52) | ... Q55: =(((((((P55+Q41)+Q34)-Q48)-Q49)+Q51)-Q47)-Q52)
A56: Total debt | B56: debt | D56: 3970.48 | E56: 4272.27 | F56: 4642.935 | G56: 8108.389 | H56: =(G56+H51) | I56: =(H56+I51) | J56: =(I56+J51) | K56: =(J56+K51) | L56: =(K56+L51) | M56: =(L56+M51) | N56: =(M56+N51) | O56: =(N56+O51) | ... Q56: =(P56+Q51)
A57: Fixed assets (net) | B57: ppe | D57: 3227.142 | E57: 3334.918 | F57: 3833.281 | G57: 6361.397 | H57: =((G57+H48)-H34) | I57: =((H57+I48)-I34) | J57: =((I57+J48)-J34) | K57: =((J57+K48)-K34) | L57: =((K57+L48)-L34) | M57: =((L57+M48)-M34) | N57: =((M57+N48)-N34) | O57: =((N57+O48)-O34) | ... Q57: =((P57+Q48)-Q34)
A58: Parent shareholders' equity | B58: equity | D58: 1579.95 | E58: 1688.393 | F58: 1727.829 | G58: 2243.416 | H58: =((G58+H43)-H47) | I58: =((H58+I43)-I47) | J58: =((I58+J43)-J47) | K58: =((J58+K43)-K47) | L58: =((K58+L43)-L47) | M58: =((L58+M43)-M47) | N58: =((M58+N43)-N47) | O58: =((N58+O43)-O47) | ... Q58: =((P58+Q43)-Q47)
A59: Minority interest (balance sheet) | B59: minority_bs | D59: 2141.947 | E59: 2423.536 | F59: 2460.156 | G59: 3802.216 | H59: =((G59+H42)-H52) | I59: =((H59+I42)-I52) | J59: =((I59+J42)-J52) | K59: =((J59+K42)-K52) | L59: =((K59+L42)-L52) | M59: =((L59+M42)-M52) | N59: =((M59+N42)-N52) | O59: =((N59+O42)-O52) | ... Q59: =((P59+Q42)-Q52)
A60: Other assets less other liabilities | B60: other_net | D60: 2165.593 | E60: 2268.913 | F60: 2287.556 | G60: 3295.125 | H60: =G60 | I60: =H60 | J60: =I60 | K60: =J60 | L60: =K60 | M60: =L60 | N60: =M60 | O60: =N60 | ... Q60: =P60
A61: Balance check (should be zero) | B61: bs_check | H61: =((((((H55+H54)+H57)+H60)-H56)-H58)-H59) | I61: =((((((I55+I54)+I57)+I60)-I56)-I58)-I59) | J61: =((((((J55+J54)+J57)+J60)-J56)-J58)-J59) | K61: =((((((K55+K54)+K57)+K60)-K56)-K58)-K59) | L61: =((((((L55+L54)+L57)+L60)-L56)-L58)-L59) | M61: =((((((M55+M54)+M57)+M60)-M56)-M58)-M59) | N61: =((((((N55+N54)+N57)+N60)-N56)-N58)-N59) | O61: =((((((O55+O54)+O57)+O60)-O56)-O58)-O59) | ... Q61: =((((((Q55+Q54)+Q57)+Q60)-Q56)-Q58)-Q59)
A62: Net debt (cash) | B62: net_debt | D62: 1989.65 | E62: 1819.155 | F62: 2672.903 | G62: 4543.186 | H62: =(H56-H55) | I62: =(I56-I55) | J62: =(J56-J55) | K62: =(K56-K55) | L62: =(L56-L55) | M62: =(M56-M55) | N62: =(N56-N55) | O62: =(O56-O55) | ... Q62: =(Q56-Q55)
A63: Book value per share | B63: bvps | D63: 0.01685973 | E63: 0.018016931 | F63: 0.018438349 | G63: 0.02393954 | H63: =(IF(H44=0,0,H58/H44)*$C$7) | I63: =(IF(I44=0,0,I58/I44)*$C$7) | J63: =(IF(J44=0,0,J58/J44)*$C$7) | K63: =(IF(K44=0,0,K58/K44)*$C$7) | L63: =(IF(L44=0,0,L58/L44)*$C$7) | M63: =(IF(M44=0,0,M58/M44)*$C$7) | N63: =(IF(N44=0,0,N58/N44)*$C$7) | O63: =(IF(O44=0,0,O58/O44)*$C$7) | ... Q63: =(IF(Q44=0,0,Q58/Q44)*$C$7)
A64: Revenue growth | B64: revenue_growth | E64: -0.067928694 | F64: -0.13525922 | G64: 2.196765 | H64: =(IF(G29=0,0,H29/G29)-1) | I64: =(IF(H29=0,0,I29/H29)-1) | J64: =(IF(I29=0,0,J29/I29)-1) | K64: =(IF(J29=0,0,K29/J29)-1) | L64: =(IF(K29=0,0,L29/K29)-1) | M64: =(IF(L29=0,0,M29/L29)-1) | N64: =(IF(M29=0,0,N29/M29)-1) | O64: =(IF(N29=0,0,O29/N29)-1) | ... Q64: =(IF(P29=0,0,Q29/P29)-1)
A65: Gross margin | B65: gross_margin | D65: 0.15048732 | E65: 0.20219834 | F65: 0.30170109 | G65: 0.071802944 | H65: =IF(H29=0,0,H31/H29) | I65: =IF(I29=0,0,I31/I29) | J65: =IF(J29=0,0,J31/J29) | K65: =IF(K29=0,0,K31/K29) | L65: =IF(L29=0,0,L31/L29) | M65: =IF(M29=0,0,M31/M29) | N65: =IF(N29=0,0,N31/N29) | O65: =IF(O29=0,0,O31/O29) | ... Q65: =IF(Q29=0,0,Q31/Q29)
A66: EBITDA margin | B66: ebitda_margin | D66: 0.091286199 | E66: 0.12792358 | F66: 0.2292066 | G66: 0.013631845 | H66: =IF(H29=0,0,H35/H29) | I66: =IF(I29=0,0,I35/I29) | J66: =IF(J29=0,0,J35/J29) | K66: =IF(K29=0,0,K35/K29) | L66: =IF(L29=0,0,L35/L29) | M66: =IF(M29=0,0,M35/M29) | N66: =IF(N29=0,0,N35/N29) | O66: =IF(O29=0,0,O35/O29) | ... Q66: =IF(Q29=0,0,Q35/Q29)
A67: EBIT margin | B67: ebit_margin | D67: 0.090430899 | E67: 0.12645964 | F67: 0.14179963 | G67: -0.026844984 | H67: =IF(H29=0,0,H33/H29) | I67: =IF(I29=0,0,I33/I29) | J67: =IF(J29=0,0,J33/J29) | K67: =IF(K29=0,0,K33/K29) | L67: =IF(L29=0,0,L33/L29) | M67: =IF(M29=0,0,M33/M29) | N67: =IF(N29=0,0,N33/N29) | O67: =IF(O29=0,0,O33/O29) | ... Q67: =IF(Q29=0,0,Q33/Q29)
A68: Net margin | B68: np_margin | D68: 0.00059394935 | E68: 0.0094610882 | F68: 0.023663225 | G68: 0.064189319 | H68: =IF(H29=0,0,H43/H29) | I68: =IF(I29=0,0,I43/I29) | J68: =IF(J29=0,0,J43/J29) | K68: =IF(K29=0,0,K43/K29) | L68: =IF(L29=0,0,L43/L29) | M68: =IF(M29=0,0,M43/M29) | N68: =IF(N29=0,0,N43/N29) | O68: =IF(O29=0,0,O43/O29) | ... Q68: =IF(Q29=0,0,Q43/Q29)
A69: EPS growth | B69: eps_growth | E69: 13.847072 | F69: 1.1628818 | G69: 7.6713012 | H69: =(IF(G45=0,0,H45/G45)-1) | I69: =(IF(H45=0,0,I45/H45)-1) | J69: =(IF(I45=0,0,J45/I45)-1) | K69: =(IF(J45=0,0,K45/J45)-1) | L69: =(IF(K45=0,0,L45/K45)-1) | M69: =(IF(L45=0,0,M45/L45)-1) | N69: =(IF(M45=0,0,N45/M45)-1) | O69: =(IF(N45=0,0,O45/N45)-1) | ... Q69: =(IF(P45=0,0,Q45/P45)-1)
A70: ROE | B70: roe | E70: 0.015981187 | F70: 0.033068109 | G70: 0.2466768 | H70: =IF(IF(2=0,0,(H58+G58)/2)=0,0,H43/IF(2=0,0,(H58+G58)/2)) | I70: =IF(IF(2=0,0,(I58+H58)/2)=0,0,I43/IF(2=0,0,(I58+H58)/2)) | J70: =IF(IF(2=0,0,(J58+I58)/2)=0,0,J43/IF(2=0,0,(J58+I58)/2)) | K70: =IF(IF(2=0,0,(K58+J58)/2)=0,0,K43/IF(2=0,0,(K58+J58)/2)) | L70: =IF(IF(2=0,0,(L58+K58)/2)=0,0,L43/IF(2=0,0,(L58+K58)/2)) | M70: =IF(IF(2=0,0,(M58+L58)/2)=0,0,M43/IF(2=0,0,(M58+L58)/2)) | N70: =IF(IF(2=0,0,(N58+M58)/2)=0,0,N43/IF(2=0,0,(N58+M58)/2)) | O70: =IF(IF(2=0,0,(O58+N58)/2)=0,0,O43/IF(2=0,0,(O58+N58)/2)) | ... Q70: =IF(IF(2=0,0,(Q58+P58)/2)=0,0,Q43/IF(2=0,0,(Q58+P58)/2))
A71: Net debt / EBITDA | B71: net_debt_ebitda | D71: 7.3596156 | E71: 5.1517353 | F71: 4.88545 | G71: 43.676082 | H71: =IF(H35=0,0,H62/H35) | I71: =IF(I35=0,0,I62/I35) | J71: =IF(J35=0,0,J62/J35) | K71: =IF(K35=0,0,K62/K35) | L71: =IF(L35=0,0,L62/L35) | M71: =IF(M35=0,0,M62/M35) | N71: =IF(N35=0,0,N62/N35) | O71: =IF(O35=0,0,O62/O35) | ... Q71: =IF(Q35=0,0,Q62/Q35)
A72: Payout ratio | B72: payout_ratio | D72: 5.6142194 | E72: 0.1916787 | F72: 0 | G72: 0.017286923 | H72: =IF(H45=0,0,H46/H45) | I72: =IF(I45=0,0,I46/I45) | J72: =IF(J45=0,0,J46/J45) | K72: =IF(K45=0,0,K46/K45) | L72: =IF(L45=0,0,L46/L45) | M72: =IF(M45=0,0,M46/M45) | N72: =IF(N45=0,0,N46/N45) | O72: =IF(O45=0,0,O46/O45) | ... Q72: =IF(Q45=0,0,Q46/Q45)
A73: Capex / revenue | B73: capex_revenue | D73: 0.060625041 | E73: 0.044917346 | F73: 0.21838546 | G73: 0.11968123 | H73: =IF(H29=0,0,H48/H29) | I73: =IF(I29=0,0,I48/I29) | J73: =IF(J29=0,0,J48/J29) | K73: =IF(K29=0,0,K48/K29) | L73: =IF(L29=0,0,L48/L29) | M73: =IF(M29=0,0,M48/M29) | N73: =IF(N29=0,0,N48/N29) | O73: =IF(O29=0,0,O48/O29) | ... Q73: =IF(Q29=0,0,Q48/Q29)
A75: VALUATION
A76: Last price (IDR) | C76: 1405
A77: Shares outstanding (m) | C77: 93711.741
A78: IDR per USD (spot) | C78: 18183
A79: Debt at balance-sheet date | C79: 8571.909
A80: Cash at balance-sheet date | C80: 3699.009
A81: Minority interest (book) | C81: 4060.05
A82: Associates & investments (book) | C82: 760.66
A83: Post-balance-sheet & other items (sourced, probability-weighted) | C83: 0
A84: Parent equity at balance-sheet date | C84: 2433.674
A85: Per-share factor | C85: 1
A86: Risk-free rate | C86: =Drivers!$C$8
A87: Less: default spread (IDR only) | C87: 0
A88: Mature ERP + Indonesia CRP | C88: =Drivers!$C$10+Drivers!$C$11
A89: Tax rate | C89: =Drivers!$C$13
A90: Unlevered beta (industry default (config)) | C90: 0.9
A91: Debt / equity (market) | C91: 1.1837848
A92: Levered beta | C92: =$C$90*(1+(1-$C$89)*$C$91)
A93: Explicit company premium | C93: 0
A94: Cost of equity | C94: =$C$86-$C$87+$C$92*$C$88+$C$93
A95: Pre-tax cost of debt | C95: =$C$86+Drivers!$C$12
A96: WACC | C96: =1/(1+$C$91)*$C$94+$C$91/(1+$C$91)*$C$95*(1-$C$89)
A97: Terminal growth (capped) | C97: 0.02
A99: Sum of the parts
A100: Value per share (IDR) — Sum of the parts (engine value) | C100: 946.28442
A102: P/E
A103: Target multiple (peer median (own history unavailable)) | C103: 8.560313
A104: Metric (LTM, or next-12m DPS for yield) | C104: 489.807
A105: Value per share (IDR) — P/E | C105: =MAX(0,$C$103*$C$104/$C$77*$C$85*$C$78)
A107: P/BV
A108: Target multiple (own five-year average) | C108: 4.737987
...

Sheet CUAN
A1: PT Petrindo Jaya Kreasi Tbk (CUAN.JK) — Conglomerates & multi-sector holdings
A2: Units: USD m; per-share in USD unless marked IDR. Model asof 2026-10-29 · data 2026-10-27
A4: Line | C4: Scalar | D4: FY2022A | E4: FY2023A | F4: FY2024A | G4: FY2025A | H4: FY2026E | I4: FY2027E | J4: FY2028E | K4: FY2029E | L4: FY2030E | M4: FY2031E | N4: FY2032E | O4: FY2033E | P4: FY2034E | Q4: FY2035E
A6: PARAMETERS
A7: ps_factor | C7: 1
A8: vp_factor | C8: 1
A10: INPUTS (company assumptions)
A11: Revenue growth | B11: a.revenue_growth | H11: 0.24 | I11: 0.12 | J11: 0.1 | K11: 0.08 | L11: 0.07 | M11: 0.06 | N11: 0.06 | O11: 0.06 | P11: 0.06 | Q11: 0.06
A12: Gross margin at base input costs | B12: a.gross_margin | H12: 0.1381 | I12: 0.1381 | J12: 0.1381 | K12: 0.1381 | L12: 0.1381 | M12: 0.1381 | N12: 0.1381 | O12: 0.1381 | P12: 0.1381 | Q12: 0.1381
A13: SG&A / revenue | B13: a.opex_pct | H13: 0.057314 | I13: 0.057314 | J13: 0.057314 | K13: 0.057314 | L13: 0.057314 | M13: 0.057314 | N13: 0.057314 | O13: 0.057314 | P13: 0.057314 | Q13: 0.057314
A14: D&A / revenue | B14: a.da_pct | H14: 0.1272 | I14: 0.1272 | J14: 0.1272 | K14: 0.1272 | L14: 0.1272 | M14: 0.1272 | N14: 0.1272 | O14: 0.1272 | P14: 0.1272 | Q14: 0.1272
A15: Capex / revenue | B15: a.capex_pct | H15: 0.1 | I15: 0.1 | J15: 0.1 | K15: 0.1 | L15: 0.1 | M15: 0.1 | N15: 0.1 | O15: 0.1 | P15: 0.1 | Q15: 0.1
A16: Operating working capital / revenue | B16: a.nwc_pct | H16: 0.189128 | I16: 0.189128 | J16: 0.189128 | K16: 0.189128 | L16: 0.189128 | M16: 0.189128 | N16: 0.189128 | O16: 0.189128 | P16: 0.189128 | Q16: 0.189128
A17: Effective tax rate | B17: a.tax_rate | H17: 0.38098 | I17: 0.38098 | J17: 0.38098 | K17: 0.38098 | L17: 0.38098 | M17: 0.38098 | N17: 0.38098 | O17: 0.38098 | P17: 0.38098 | Q17: 0.38098
A18: Cost of debt (on opening debt) | B18: a.cost_of_debt | C18: 0.085
A19: Yield on opening cash | B19: a.cash_yield | C19: 0.015
A20: Net new borrowing | B20: a.net_borrowing | H20: 0 | I20: 0 | J20: 0 | K20: 0 | L20: 0 | M20: 0 | N20: 0 | O20: 0 | P20: 0 | Q20: 0
A21: Other non-operating items | B21: a.other_nonop | H21: 0 | I21: 0 | J21: 0 | K21: 0 | L21: 0 | M21: 0 | N21: 0 | O21: 0 | P21: 0 | Q21: 0
A22: Minorities' share of net profit | B22: a.minority_pct | H22: 0.456174 | I22: 0.456174 | J22: 0.456174 | K22: 0.456174 | L22: 0.456174 | M22: 0.456174 | N22: 0.456174 | O22: 0.456174 | P22: 0.456174 | Q22: 0.456174
A23: Dividend payout | B23: a.payout | H23: 0.02 | I23: 0.02 | J23: 0.02 | K23: 0.02 | L23: 0.02 | M23: 0.02 | N23: 0.02 | O23: 0.02 | P23: 0.02 | Q23: 0.02
A24: Change in share count | B24: a.share_change | H24: 0 | I24: 0 | J24: 0 | K24: 0 | L24: 0 | M24: 0 | N24: 0 | O24: 0 | P24: 0 | Q24: 0
A25: Terminal growth (DCF) | B25: a.terminal_growth | C25: 0.02
A26: Holding-company discount to SOTP | B26: a.holdco_discount | C26: 0.3
A28: MODEL
A29: Revenue | B29: revenue | D29: 97.665446 | E29: 97.943 | F29: 801.723 | G29: 1215.618 | H29: =(G29*(1+H11)) | I29: =(H29*(1+I11)) | J29: =(I29*(1+J11)) | K29: =(J29*(1+K11)) | L29: =(K29*(1+L11)) | M29: =(L29*(1+M11)) | N29: =(M29*(1+N11)) | O29: =(N29*(1+O11)) | ... Q29: =(P29*(1+Q11))
A30: Cost of revenue | B30: cogs | D30: 28.191867 | E30: 60.725 | F30: 683.857 | G30: 1055.649 | H30: =(H29*(1-H12)) | I30: =(I29*(1-I12)) | J30: =(J29*(1-J12)) | K30: =(K29*(1-K12)) | L30: =(L29*(1-L12)) | M30: =(M29*(1-M12)) | N30: =(N29*(1-N12)) | O30: =(O29*(1-O12)) | ... Q30: =(Q29*(1-Q12))
A31: Gross profit | B31: gross_profit | D31: 69.473578 | E31: 37.218 | F31: 117.866 | G31: 159.969 | H31: =(H29-H30) | I31: =(I29-I30) | J31: =(J29-J30) | K31: =(K29-K30) | L31: =(L29-L30) | M31: =(M29-M30) | N31: =(N29-N30) | O31: =(O29-O30) | ... Q31: =(Q29-Q30)
A32: SG&A and other opex | B32: opex | D32: 20.983647 | E32: 16.226 | F32: 91.255 | G32: 134.645 | H32: =(H29*H13) | I32: =(I29*I13) | J32: =(J29*J13) | K32: =(K29*K13) | L32: =(L29*L13) | M32: =(M29*M13) | N32: =(N29*N13) | O32: =(O29*O13) | ... Q32: =(Q29*Q13)
A33: EBIT | B33: ebit | D33: 48.489931 | E33: 20.992 | F33: 26.611 | G33: 25.324 | H33: =(H31-H32) | I33: =(I31-I32) | J33: =(J31-J32) | K33: =(K31-K32) | L33: =(L31-L32) | M33: =(M31-M32) | N33: =(N31-N32) | O33: =(O31-O32) | ... Q33: =(Q31-Q32)
A34: Depreciation & amortisation | B34: da | D34: 0.009312828 | E34: 0.013 | F34: 99.857 | G34: 155.318 | H34: =(H29*H14) | I34: =(I29*I14) | J34: =(J29*J14) | K34: =(K29*K14) | L34: =(L29*L14) | M34: =(M29*M14) | N34: =(N29*N14) | O34: =(O29*O14) | ... Q34: =(Q29*Q14)
A35: EBITDA | B35: ebitda | D35: 48.499244 | E35: 21.005 | F35: 126.468 | G35: 180.642 | H35: =(H33+H34) | I35: =(I33+I34) | J35: =(J33+J34) | K35: =(K33+K34) | L35: =(L33+L34) | M35: =(M33+M34) | N35: =(N33+N34) | O35: =(O33+O34) | ... Q35: =(Q33+Q34)
A36: Interest expense | B36: interest_expense | D36: 0.85684659 | E36: 0.954 | F36: 46.127 | G36: 96.072 | H36: =(G56*$C$18) | I36: =(H56*$C$18) | J36: =(I56*$C$18) | K36: =(J56*$C$18) | L36: =(K56*$C$18) | M36: =(L56*$C$18) | N36: =(M56*$C$18) | O36: =(N56*$C$18) | ... Q36: =(P56*$C$18)
A37: Interest income | B37: interest_income | D37: 0.095691848 | E37: 1.118 | F37: 3.758 | G37: 6.263 | H37: =(G55*$C$19) | I37: =(H55*$C$19) | J37: =(I55*$C$19) | K37: =(J55*$C$19) | L37: =(K55*$C$19) | M37: =(L55*$C$19) | N37: =(M55*$C$19) | O37: =(N55*$C$19) | ... Q37: =(P55*$C$19)
A38: Other non-operating | B38: other_nonop | D38: -9.0205621e-16 | E38: -1.568 | F38: 186.798 | G38: 213.755 | H38: =H21 | I38: =I21 | J38: =J21 | K38: =K21 | L38: =L21 | M38: =M21 | N38: =N21 | O38: =O21 | ... Q38: =Q21
A39: Profit before tax | B39: pbt | D39: 47.728776 | E39: 19.588 | F39: 171.04 | G39: 149.27 | H39: =(((H33-H36)+H37)+H38) | I39: =(((I33-I36)+I37)+I38) | J39: =(((J33-J36)+J37)+J38) | K39: =(((K33-K36)+K37)+K38) | L39: =(((L33-L36)+L37)+L38) | M39: =(((M33-M36)+M37)+M38) | N39: =(((N33-N36)+N37)+N38) | O39: =(((O33-O36)+O37)+O38) | ... Q39: =(((Q33-Q36)+Q37)+Q38)
A40: Tax | B40: tax | D40: 11.578737 | E40: 4.338 | F40: 1.07 | G40: -2.725 | H40: =(MAX(H39,0)*H17) | I40: =(MAX(I39,0)*I17) | J40: =(MAX(J39,0)*J17) | K40: =(MAX(K39,0)*K17) | L40: =(MAX(L39,0)*L17) | M40: =(MAX(M39,0)*M17) | N40: =(MAX(N39,0)*N17) | O40: =(MAX(O39,0)*O17) | ... Q40: =(MAX(Q39,0)*Q17)
A41: Net profit (incl. minorities) | B41: np | D41: 36.15004 | E41: 15.25 | F41: 169.97 | G41: 151.995 | H41: =(H39-H40) | I41: =(I39-I40) | J41: =(J39-J40) | K41: =(K39-K40) | L41: =(L39-L40) | M41: =(M39-M40) | N41: =(N39-N40) | O41: =(O39-O40) | ... Q41: =(Q39-Q40)
A42: Minority interests | B42: minority | D42: -0.54461043 | E42: -0.371 | F42: 9.185 | G42: 17.428 | H42: =(H41*H22) | I42: =(I41*I22) | J42: =(J41*J22) | K42: =(K41*K22) | L42: =(L41*L22) | M42: =(M41*M22) | N42: =(N41*N22) | O42: =(O41*O22) | ... Q42: =(Q41*Q22)
A43: Net profit to parent | B43: np_parent | D43: 36.69465 | E43: 15.621 | F43: 160.785 | G43: 134.567 | H43: =(H41-H42) | I43: =(I41-I42) | J43: =(J41-J42) | K43: =(K41-K42) | L43: =(L41-L42) | M43: =(M41-M42) | N43: =(N41-N42) | O43: =(O41-O42) | ... Q43: =(Q41-Q42)
A44: Shares outstanding (m) | B44: shares | D44: 112418.9 | E44: 112418.9 | F44: 112418.9 | G44: 112418.9 | H44: =(G44*(1+H24)) | I44: =(H44*(1+I24)) | J44: =(I44*(1+J24)) | K44: =(J44*(1+K24)) | L44: =(K44*(1+L24)) | M44: =(L44*(1+M24)) | N44: =(M44*(1+N24)) | O44: =(N44*(1+O24)) | ... Q44: =(P44*(1+Q24))
A45: EPS | B45: eps | D45: 0.00032640997 | E45: 0.0001389535 | F45: 0.001430231 | G45: 0.001197014 | H45: =(IF(H44=0,0,H43/H44)*$C$7) | I45: =(IF(I44=0,0,I43/I44)*$C$7) | J45: =(IF(J44=0,0,J43/J44)*$C$7) | K45: =(IF(K44=0,0,K43/K44)*$C$7) | L45: =(IF(L44=0,0,L43/L44)*$C$7) | M45: =(IF(M44=0,0,M43/M44)*$C$7) | N45: =(IF(N44=0,0,N43/N44)*$C$7) | O45: =(IF(O44=0,0,O43/O44)*$C$7) | ... Q45: =(IF(Q44=0,0,Q43/Q44)*$C$7)
A46: DPS (declared on the year) | B46: dps | E46: 0 | F46: 1.9363688e-05 | G46: 0.00017791 | H46: =(MAX(H45,0)*H23) | I46: =(MAX(I45,0)*I23) | J46: =(MAX(J45,0)*J23) | K46: =(MAX(K45,0)*K23) | L46: =(MAX(L45,0)*L23) | M46: =(MAX(M45,0)*M23) | N46: =(MAX(N45,0)*N23) | O46: =(MAX(O45,0)*O23) | ... Q46: =(MAX(Q45,0)*Q23)
A47: Dividends paid | B47: dividends_paid | E47: 0 | F47: 2.232 | G47: 2 | H47: =IF($C$7=0,0,(G46*G44)/$C$7) | I47: =IF($C$7=0,0,(H46*H44)/$C$7) | J47: =IF($C$7=0,0,(I46*I44)/$C$7) | K47: =IF($C$7=0,0,(J46*J44)/$C$7) | L47: =IF($C$7=0,0,(K46*K44)/$C$7) | M47: =IF($C$7=0,0,(L46*L44)/$C$7) | N47: =IF($C$7=0,0,(M46*M44)/$C$7) | O47: =IF($C$7=0,0,(N46*N44)/$C$7) | ... Q47: =IF($C$7=0,0,(P46*P44)/$C$7)
A48: Capital expenditure | B48: capex | D48: 2.7012893 | E48: 11.787 | F48: 143.704 | G48: 436.073 | H48: =(H29*H15) | I48: =(I29*I15) | J48: =(J29*J15) | K48: =(K29*K15) | L48: =(L29*L15) | M48: =(M29*M15) | N48: =(N29*N15) | O48: =(O29*O15) | ... Q48: =(Q29*Q15)
A49: Change in working capital | B49: delta_nwc | E49: 57.113 | F49: 73.505 | G49: 12.989 | H49: =(H54-G54) | I49: =(I54-H54) | J49: =(J54-I54) | K49: =(K54-J54) | L49: =(L54-K54) | M49: =(M54-L54) | N49: =(N54-M54) | O49: =(O54-N54) | ... Q49: =(Q54-P54)
A50: Free cash flow to firm | B50: fcff | E50: -52.543933 | F50: -90.907474 | G50: -267.9577 | H50: =((((H33*(1-H17))+H34)-H48)-H49) | I50: =((((I33*(1-I17))+I34)-I48)-I49) | J50: =((((J33*(1-J17))+J34)-J48)-J49) | K50: =((((K33*(1-K17))+K34)-K48)-K49) | L50: =((((L33*(1-L17))+L34)-L48)-L49) | M50: =((((M33*(1-M17))+M34)-M48)-M49) | N50: =((((N33*(1-N17))+N34)-N48)-N49) | O50: =((((O33*(1-O17))+O34)-O48)-O49) | ... Q50: =((((Q33*(1-Q17))+Q34)-Q48)-Q49)
A51: Net borrowing | B51: net_borrowing | E51: 73.973 | F51: 742.401 | G51: 632.375 | H51: =H20 | I51: =I20 | J51: =J20 | K51: =K20 | L51: =L20 | M51: =M20 | N51: =N20 | O51: =O20 | ... Q51: =Q20
A52: Dividends to minorities | B52: minority_div | H52: =(MAX(G42,0)*H23) | I52: =(MAX(H42,0)*I23) | J52: =(MAX(I42,0)*J23) | K52: =(MAX(J42,0)*K23) | L52: =(MAX(K42,0)*L23) | M52: =(MAX(L42,0)*M23) | N52: =(MAX(M42,0)*N23) | O52: =(MAX(N42,0)*O23) | ... Q52: =(MAX(P42,0)*Q23)
A53: Free cash flow to equity | B53: fcfe | H53: =(((((H41+H34)-H48)-H49)+H51)-H52) | I53: =(((((I41+I34)-I48)-I49)+I51)-I52) | J53: =(((((J41+J34)-J48)-J49)+J51)-J52) | K53: =(((((K41+K34)-K48)-K49)+K51)-K52) | L53: =(((((L41+L34)-L48)-L49)+L51)-L52) | M53: =(((((M41+M34)-M48)-M49)+M51)-M52) | N53: =(((((N41+N34)-N48)-N49)+N51)-N52) | O53: =(((((O41+O34)-O48)-O49)+O51)-O52) | ... Q53: =(((((Q41+Q34)-Q48)-Q49)+Q51)-Q52)
A54: Operating working capital | B54: nwc | D54: 12.919 | E54: 70.032 | F54: 143.537 | G54: 156.526 | H54: =(H29*H16) | I54: =(I29*I16) | J54: =(J29*J16) | K54: =(K29*K16) | L54: =(L29*L16) | M54: =(M29*M16) | N54: =(N29*N16) | O54: =(O29*O16) | ... Q54: =(Q29*Q16)
A55: Cash & equivalents | B55: cash | D55: 16.193 | E55: 60.919 | F55: 304.163 | G55: 453.801 | H55: =(((((((G55+H41)+H34)-H48)-H49)+H51)-H47)-H52) | I55: =(((((((H55+I41)+I34)-I48)-I49)+I51)-I47)-I52) | J55: =(((((((I55+J41)+J34)-J48)-J49)+J51)-J47)-J52) | K55: =(((((((J55+K41)+K34)-K48)-K49)+K51)-K47)-K52) | L55: =(((((((K55+L41)+L34)-L48)-L49)+L51)-L47)-L52) | M55: =(((((((L55+M41)+M34)-M48)-M49)+M51)-M47)-M52) | N55: =(((((((M55+N41)+N34)-N48)-N49)+N51)-N47)-N52) | O55: =(((((((N55+O41)+O34)-O48)-O49)+O51)-O47)-O52) | ... Q55: =(((((((P55+Q41)+Q34)-Q48)-Q49)+Q51)-Q47)-Q52)
A56: Total debt | B56: debt | D56: 0 | E56: 73.973 | F56: 816.374 | G56: 1448.749 | H56: =(G56+H51) | I56: =(H56+I51) | J56: =(I56+J51) | K56: =(J56+K51) | L56: =(K56+L51) | M56: =(L56+M51) | N56: =(M56+N51) | O56: =(N56+O51) | ... Q56: =(P56+Q51)
A57: Fixed assets (net) | B57: ppe | D57: 51.416 | E57: 62.242 | F57: 903.902 | G57: 1390.681 | H57: =((G57+H48)-H34) | I57: =((H57+I48)-I34) | J57: =((I57+J48)-J34) | K57: =((J57+K48)-K34) | L57: =((K57+L48)-L34) | M57: =((L57+M48)-M34) | N57: =((M57+N48)-N34) | O57: =((N57+O48)-O34) | ... Q57: =((P57+Q48)-Q34)
A58: Parent shareholders' equity | B58: equity | D58: 69.748 | E58: 108.715 | F58: 306.151 | G58: 339.384 | H58: =((G58+H43)-H47) | I58: =((H58+I43)-I47) | J58: =((I58+J43)-J47) | K58: =((J58+K43)-K47) | L58: =((K58+L43)-L47) | M58: =((L58+M43)-M47) | N58: =((M58+N43)-N47) | O58: =((N58+O43)-O47) | ... Q58: =((P58+Q43)-Q47)
A59: Minority interest (balance sheet) | B59: minority_bs | D59: 11.326 | E59: 11.987 | F59: 259.748 | G59: 287.026 | H59: =((G59+H42)-H52) | I59: =((H59+I42)-I52) | J59: =((I59+J42)-J52) | K59: =((J59+K42)-K52) | L59: =((K59+L42)-L52) | M59: =((L59+M42)-M52) | N59: =((M59+N42)-N52) | O59: =((N59+O42)-O52) | ... Q59: =((P59+Q42)-Q52)
A60: Other assets less other liabilities | B60: other_net | D60: 0.546 | E60: 1.482 | F60: 30.671 | G60: 74.151 | H60: =G60 | I60: =H60 | J60: =I60 | K60: =J60 | L60: =K60 | M60: =L60 | N60: =M60 | O60: =N60 | ... Q60: =P60
A61: Balance check (should be zero) | B61: bs_check | H61: =((((((H55+H54)+H57)+H60)-H56)-H58)-H59) | I61: =((((((I55+I54)+I57)+I60)-I56)-I58)-I59) | J61: =((((((J55+J54)+J57)+J60)-J56)-J58)-J59) | K61: =((((((K55+K54)+K57)+K60)-K56)-K58)-K59) | L61: =((((((L55+L54)+L57)+L60)-L56)-L58)-L59) | M61: =((((((M55+M54)+M57)+M60)-M56)-M58)-M59) | N61: =((((((N55+N54)+N57)+N60)-N56)-N58)-N59) | O61: =((((((O55+O54)+O57)+O60)-O56)-O58)-O59) | ... Q61: =((((((Q55+Q54)+Q57)+Q60)-Q56)-Q58)-Q59)
A62: Net debt (cash) | B62: net_debt | D62: -16.193 | E62: 13.054 | F62: 512.211 | G62: 994.948 | H62: =(H56-H55) | I62: =(I56-I55) | J62: =(J56-J55) | K62: =(K56-K55) | L62: =(L56-L55) | M62: =(M56-M55) | N62: =(N56-N55) | O62: =(O56-O55) | ... Q62: =(Q56-Q55)
A63: Book value per share | B63: bvps | D63: 0.00062042948 | E63: 0.00096705269 | F63: 0.0027233054 | G63: 0.003018923 | H63: =(IF(H44=0,0,H58/H44)*$C$7) | I63: =(IF(I44=0,0,I58/I44)*$C$7) | J63: =(IF(J44=0,0,J58/J44)*$C$7) | K63: =(IF(K44=0,0,K58/K44)*$C$7) | L63: =(IF(L44=0,0,L58/L44)*$C$7) | M63: =(IF(M44=0,0,M58/M44)*$C$7) | N63: =(IF(N44=0,0,N58/N44)*$C$7) | O63: =(IF(O44=0,0,O58/O44)*$C$7) | ... Q63: =(IF(Q44=0,0,Q58/Q44)*$C$7)
A64: Revenue growth | B64: revenue_growth | E64: 0.0028418888 | F64: 7.185608 | G64: 0.51625686 | H64: =(IF(G29=0,0,H29/G29)-1) | I64: =(IF(H29=0,0,I29/H29)-1) | J64: =(IF(I29=0,0,J29/I29)-1) | K64: =(IF(J29=0,0,K29/J29)-1) | L64: =(IF(K29=0,0,L29/K29)-1) | M64: =(IF(L29=0,0,M29/L29)-1) | N64: =(IF(M29=0,0,N29/M29)-1) | O64: =(IF(N29=0,0,O29/N29)-1) | ... Q64: =(IF(P29=0,0,Q29/P29)-1)
A65: Gross margin | B65: gross_margin | D65: 0.71134246 | E65: 0.37999653 | F65: 0.14701586 | G65: 0.13159479 | H65: =IF(H29=0,0,H31/H29) | I65: =IF(I29=0,0,I31/I29) | J65: =IF(J29=0,0,J31/J29) | K65: =IF(K29=0,0,K31/K29) | L65: =IF(L29=0,0,L31/L29) | M65: =IF(M29=0,0,M31/M29) | N65: =IF(N29=0,0,N31/N29) | O65: =IF(O29=0,0,O31/O29) | ... Q65: =IF(Q29=0,0,Q31/Q29)
A66: EBITDA margin | B66: ebitda_margin | D66: 0.4965855 | E66: 0.21446147 | F66: 0.15774526 | G66: 0.14860096 | H66: =IF(H29=0,0,H35/H29) | I66: =IF(I29=0,0,I35/I29) | J66: =IF(J29=0,0,J35/J29) | K66: =IF(K29=0,0,K35/K29) | L66: =IF(L29=0,0,L35/L29) | M66: =IF(M29=0,0,M35/M29) | N66: =IF(N29=0,0,N35/N29) | O66: =IF(O29=0,0,O35/O29) | ... Q66: =IF(Q29=0,0,Q35/Q29)
A67: EBIT margin | B67: ebit_margin | D67: 0.49649014 | E67: 0.21432874 | F67: 0.033192262 | G67: 0.020832202 | H67: =IF(H29=0,0,H33/H29) | I67: =IF(I29=0,0,I33/I29) | J67: =IF(J29=0,0,J33/J29) | K67: =IF(K29=0,0,K33/K29) | L67: =IF(L29=0,0,L33/L29) | M67: =IF(M29=0,0,M33/M29) | N67: =IF(N29=0,0,N33/N29) | O67: =IF(O29=0,0,O33/O29) | ... Q67: =IF(Q29=0,0,Q33/Q29)
A68: Net margin | B68: np_margin | D68: 0.37571784 | E68: 0.15949072 | F68: 0.20054932 | G68: 0.11069843 | H68: =IF(H29=0,0,H43/H29) | I68: =IF(I29=0,0,I43/I29) | J68: =IF(J29=0,0,J43/J29) | K68: =IF(K29=0,0,K43/K29) | L68: =IF(L29=0,0,L43/L29) | M68: =IF(M29=0,0,M43/M29) | N68: =IF(N29=0,0,N43/N29) | O68: =IF(O29=0,0,O43/O29) | ... Q68: =IF(Q29=0,0,Q43/Q29)
A69: EPS growth | B69: eps_growth | E69: -0.57429762 | F69: 9.292875 | G69: -0.16306247 | H69: =(IF(G45=0,0,H45/G45)-1) | I69: =(IF(H45=0,0,I45/H45)-1) | J69: =(IF(I45=0,0,J45/I45)-1) | K69: =(IF(J45=0,0,K45/J45)-1) | L69: =(IF(K45=0,0,L45/K45)-1) | M69: =(IF(L45=0,0,M45/L45)-1) | N69: =(IF(M45=0,0,N45/M45)-1) | O69: =(IF(N45=0,0,O45/N45)-1) | ... Q69: =(IF(P45=0,0,Q45/P45)-1)
A70: ROE | B70: roe | E70: 0.1750615 | F70: 0.77511775 | G70: 0.4169162 | H70: =IF(IF(2=0,0,(H58+G58)/2)=0,0,H43/IF(2=0,0,(H58+G58)/2)) | I70: =IF(IF(2=0,0,(I58+H58)/2)=0,0,I43/IF(2=0,0,(I58+H58)/2)) | J70: =IF(IF(2=0,0,(J58+I58)/2)=0,0,J43/IF(2=0,0,(J58+I58)/2)) | K70: =IF(IF(2=0,0,(K58+J58)/2)=0,0,K43/IF(2=0,0,(K58+J58)/2)) | L70: =IF(IF(2=0,0,(L58+K58)/2)=0,0,L43/IF(2=0,0,(L58+K58)/2)) | M70: =IF(IF(2=0,0,(M58+L58)/2)=0,0,M43/IF(2=0,0,(M58+L58)/2)) | N70: =IF(IF(2=0,0,(N58+M58)/2)=0,0,N43/IF(2=0,0,(N58+M58)/2)) | O70: =IF(IF(2=0,0,(O58+N58)/2)=0,0,O43/IF(2=0,0,(O58+N58)/2)) | ... Q70: =IF(IF(2=0,0,(Q58+P58)/2)=0,0,Q43/IF(2=0,0,(Q58+P58)/2))
A71: Net debt / EBITDA | B71: net_debt_ebitda | D71: -0.33388149 | E71: 0.62147108 | F71: 4.0501234 | G71: 5.5078442 | H71: =IF(H35=0,0,H62/H35) | I71: =IF(I35=0,0,I62/I35) | J71: =IF(J35=0,0,J62/J35) | K71: =IF(K35=0,0,K62/K35) | L71: =IF(L35=0,0,L62/L35) | M71: =IF(M35=0,0,M62/M35) | N71: =IF(N35=0,0,N62/N35) | O71: =IF(O35=0,0,O62/O35) | ... Q71: =IF(Q35=0,0,Q62/Q35)
A72: Payout ratio | B72: payout_ratio | E72: 0 | F72: 0.013538853 | G72: 0.14862817 | H72: =IF(H45=0,0,H46/H45) | I72: =IF(I45=0,0,I46/I45) | J72: =IF(J45=0,0,J46/J45) | K72: =IF(K45=0,0,K46/K45) | L72: =IF(L45=0,0,L46/L45) | M72: =IF(M45=0,0,M46/M45) | N72: =IF(N45=0,0,N46/N45) | O72: =IF(O45=0,0,O46/O45) | ... Q72: =IF(Q45=0,0,Q46/Q45)
A73: Capex / revenue | B73: capex_revenue | D73: 0.027658598 | E73: 0.12034551 | F73: 0.17924395 | G73: 0.35872536 | H73: =IF(H29=0,0,H48/H29) | I73: =IF(I29=0,0,I48/I29) | J73: =IF(J29=0,0,J48/J29) | K73: =IF(K29=0,0,K48/K29) | L73: =IF(L29=0,0,L48/L29) | M73: =IF(M29=0,0,M48/M29) | N73: =IF(N29=0,0,N48/N29) | O73: =IF(O29=0,0,O48/O29) | ... Q73: =IF(Q29=0,0,Q48/Q29)
A75: VALUATION
A76: Last price (IDR) | C76: 505
A77: Shares outstanding (m) | C77: 112399.2
A78: IDR per USD (spot) | C78: 18183
A79: Debt at balance-sheet date | C79: 1426.519
A80: Cash at balance-sheet date | C80: 449.092
A81: Minority interest (book) | C81: 291.21
A82: Associates & investments (book) | C82: 33.982
A83: Post-balance-sheet & other items (sourced, probability-weighted) | C83: -20.2
A84: Parent equity at balance-sheet date | C84: 347.161
A85: Per-share factor | C85: 1
A86: Risk-free rate | C86: =Drivers!$C$8
A87: Less: default spread (IDR only) | C87: 0
A88: Mature ERP + Indonesia CRP | C88: =Drivers!$C$10+Drivers!$C$11
A89: Tax rate | C89: =Drivers!$C$13
A90: Unlevered beta (industry default (config)) | C90: 0.9
A91: Debt / equity (market) | C91: 0.45697086
A92: Levered beta | C92: =$C$90*(1+(1-$C$89)*$C$91)
A93: Explicit company premium | C93: 0
A94: Cost of equity | C94: =$C$86-$C$87+$C$92*$C$88+$C$93
A95: Pre-tax cost of debt | C95: =$C$86+Drivers!$C$12
A96: WACC | C96: =1/(1+$C$91)*$C$94+$C$91/(1+$C$91)*$C$95*(1-$C$89)
A97: Terminal growth (capped) | C97: 0.02
A99: Sum of the parts
A100: Value per share (IDR) — Sum of the parts (engine value) | C100: 39.31252
A102: P/BV
A103: Target multiple (peer median (own history unavailable)) | C103: 0.845401
A104: Metric (LTM, or next-12m DPS for yield) | C104: 347.161
A105: Value per share (IDR) — P/BV | C105: =MAX(0,$C$103*$C$104/$C$77*$C$85*$C$78)
A107: TARGET
A108: Weight: Sum of the parts | C108: 0.833333
...

Sheet DSSA
A1: PT Dian Swastatika Sentosa Tbk (DSSA.JK) — Conglomerates & multi-sector holdings
A2: Units: USD m; per-share in USD unless marked IDR. Model asof 2026-10-29 · data 2026-10-27
A4: Line | C4: Scalar | D4: FY2022A | E4: FY2023A | F4: FY2024A | G4: FY2025A | H4: FY2026E | I4: FY2027E | J4: FY2028E | K4: FY2029E | L4: FY2030E | M4: FY2031E | N4: FY2032E | O4: FY2033E | P4: FY2034E | Q4: FY2035E
A6: PARAMETERS
A7: ps_factor | C7: 1
A8: vp_factor | C8: 1
A10: INPUTS (company assumptions)
A11: Revenue growth | B11: a.revenue_growth | H11: 0.1 | I11: -0.05 | J11: -0.06 | K11: -0.06 | L11: -0.06 | M11: -0.05 | N11: -0.05 | O11: -0.05 | P11: -0.05 | Q11: -0.05
A12: Gross margin at base input costs | B12: a.gross_margin | H12: 0.337361 | I12: 0.337361 | J12: 0.337361 | K12: 0.337361 | L12: 0.337361 | M12: 0.337361 | N12: 0.337361 | O12: 0.337361 | P12: 0.337361 | Q12: 0.337361
A13: SG&A / revenue | B13: a.opex_pct | H13: 0.193723 | I13: 0.193723 | J13: 0.193723 | K13: 0.193723 | L13: 0.193723 | M13: 0.193723 | N13: 0.193723 | O13: 0.193723 | P13: 0.193723 | Q13: 0.193723
A14: D&A / revenue | B14: a.da_pct | H14: 0.028005 | I14: 0.028005 | J14: 0.028005 | K14: 0.028005 | L14: 0.028005 | M14: 0.028005 | N14: 0.028005 | O14: 0.028005 | P14: 0.028005 | Q14: 0.028005
A15: Capex / revenue | B15: a.capex_pct | H15: 0.167325 | I15: 0.167325 | J15: 0.167325 | K15: 0.167325 | L15: 0.167325 | M15: 0.167325 | N15: 0.167325 | O15: 0.167325 | P15: 0.167325 | Q15: 0.167325
A16: Operating working capital / revenue | B16: a.nwc_pct | H16: 0.155985 | I16: 0.155985 | J16: 0.155985 | K16: 0.155985 | L16: 0.155985 | M16: 0.155985 | N16: 0.155985 | O16: 0.155985 | P16: 0.155985 | Q16: 0.155985
A17: Effective tax rate | B17: a.tax_rate | H17: 0.241607 | I17: 0.241607 | J17: 0.241607 | K17: 0.241607 | L17: 0.241607 | M17: 0.241607 | N17: 0.241607 | O17: 0.241607 | P17: 0.241607 | Q17: 0.241607
A18: Cost of debt (on opening debt) | B18: a.cost_of_debt | C18: 0.066581
A19: Yield on opening cash | B19: a.cash_yield | C19: 0.07
A20: Net new borrowing | B20: a.net_borrowing | H20: 0 | I20: 0 | J20: 0 | K20: 0 | L20: 0 | M20: 0 | N20: 0 | O20: 0 | P20: 0 | Q20: 0
A21: Other non-operating items | B21: a.other_nonop | H21: 0 | I21: 0 | J21: 0 | K21: 0 | L21: 0 | M21: 0 | N21: 0 | O21: 0 | P21: 0 | Q21: 0
A22: Minorities' share of net profit | B22: a.minority_pct | H22: 0.43326 | I22: 0.43326 | J22: 0.43326 | K22: 0.43326 | L22: 0.43326 | M22: 0.43326 | N22: 0.43326 | O22: 0.43326 | P22: 0.43326 | Q22: 0.43326
A23: Dividend payout | B23: a.payout | H23: 0 | I23: 0 | J23: 0 | K23: 0 | L23: 0 | M23: 0 | N23: 0 | O23: 0 | P23: 0 | Q23: 0
A24: Change in share count | B24: a.share_change | H24: 0 | I24: 0 | J24: 0 | K24: 0 | L24: 0 | M24: 0 | N24: 0 | O24: 0 | P24: 0 | Q24: 0
A25: Terminal growth (DCF) | B25: a.terminal_growth | C25: 0.02
A26: Holding-company discount to SOTP | B26: a.holdco_discount | C26: 0.3
A28: MODEL
A29: Revenue | B29: revenue | D29: 5956.1058 | E29: 5014.66 | F29: 3017.796 | G29: 2791.2166 | H29: =(G29*(1+H11)) | I29: =(H29*(1+I11)) | J29: =(I29*(1+J11)) | K29: =(J29*(1+K11)) | L29: =(K29*(1+L11)) | M29: =(L29*(1+M11)) | N29: =(M29*(1+N11)) | O29: =(N29*(1+O11)) | ... Q29: =(P29*(1+Q11))
A30: Cost of revenue | B30: cogs | D30: 3318.0734 | E30: 2942.4005 | F30: 1789.3888 | G30: 1849.6 | H30: =(H29*(1-H12)) | I30: =(I29*(1-I12)) | J30: =(J29*(1-J12)) | K30: =(K29*(1-K12)) | L30: =(L29*(1-L12)) | M30: =(M29*(1-M12)) | N30: =(N29*(1-N12)) | O30: =(O29*(1-O12)) | ... Q30: =(Q29*(1-Q12))
A31: Gross profit | B31: gross_profit | D31: 2638.0324 | E31: 2072.2594 | F31: 1228.4072 | G31: 941.65602 | H31: =(H29-H30) | I31: =(I29-I30) | J31: =(J29-J30) | K31: =(K29-K30) | L31: =(L29-L30) | M31: =(M29-M30) | N31: =(N29-N30) | O31: =(O29-O30) | ... Q31: =(Q29-Q30)
A32: SG&A and other opex | B32: opex | D32: 860.90135 | E32: 817.47173 | F32: 577.6729 | G32: 540.7235 | H32: =(H29*H13) | I32: =(I29*I13) | J32: =(J29*J13) | K32: =(K29*K13) | L32: =(L29*L13) | M32: =(M29*M13) | N32: =(N29*N13) | O32: =(O29*O13) | ... Q32: =(Q29*Q13)
A33: EBIT | B33: ebit | D33: 1777.1311 | E33: 1254.7877 | F33: 650.73431 | G33: 400.93252 | H33: =(H31-H32) | I33: =(I31-I32) | J33: =(J31-J32) | K33: =(K31-K32) | L33: =(L31-L32) | M33: =(M31-M32) | N33: =(N31-N32) | O33: =(O31-O32) | ... Q33: =(Q31-Q32)
A34: Depreciation & amortisation | B34: da | D34: 14.25822 | E34: 14.185685 | F34: 83.646621 | G34: 78.164895 | H34: =(H29*H14) | I34: =(I29*I14) | J34: =(J29*J14) | K34: =(K29*K14) | L34: =(L29*L14) | M34: =(M29*M14) | N34: =(N29*N14) | O34: =(O29*O14) | ... Q34: =(Q29*Q14)
A35: EBITDA | B35: ebitda | D35: 1791.3893 | E35: 1268.9734 | F35: 734.38093 | G35: 479.09741 | H35: =(H33+H34) | I35: =(I33+I34) | J35: =(J33+J34) | K35: =(K33+K34) | L35: =(L33+L34) | M35: =(M33+M34) | N35: =(N33+N34) | O35: =(O33+O34) | ... Q35: =(Q33+Q34)
A36: Interest expense | B36: interest_expense | D36: 158.88822 | E36: 107.45761 | F36: 60.859253 | G36: 71.37262 | H36: =(G56*$C$18) | I36: =(H56*$C$18) | J36: =(I56*$C$18) | K36: =(J56*$C$18) | L36: =(K56*$C$18) | M36: =(L56*$C$18) | N36: =(M56*$C$18) | O36: =(N56*$C$18) | ... Q36: =(P56*$C$18)
A37: Interest income | B37: interest_income | D37: 24.584143 | E37: 42.939142 | F37: 67.108939 | G37: 90.367849 | H37: =(G55*$C$19) | I37: =(H55*$C$19) | J37: =(I55*$C$19) | K37: =(J55*$C$19) | L37: =(K55*$C$19) | M37: =(L55*$C$19) | N37: =(M55*$C$19) | O37: =(N55*$C$19) | ... Q37: =(P55*$C$19)
A38: Other non-operating | B38: other_nonop | D38: -42.478785 | E38: -9.199558 | F38: 53.259652 | G38: 44.156771 | H38: =H21 | I38: =I21 | J38: =J21 | K38: =K21 | L38: =L21 | M38: =M21 | N38: =N21 | O38: =O21 | ... Q38: =Q21
A39: Profit before tax | B39: pbt | D39: 1600.3482 | E39: 1181.0697 | F39: 710.24365 | G39: 464.08452 | H39: =(((H33-H36)+H37)+H38) | I39: =(((I33-I36)+I37)+I38) | J39: =(((J33-J36)+J37)+J38) | K39: =(((K33-K36)+K37)+K38) | L39: =(((L33-L36)+L37)+L38) | M39: =(((M33-M36)+M37)+M38) | N39: =(((N33-N36)+N37)+N38) | O39: =(((O33-O36)+O37)+O38) | ... Q39: =(((Q33-Q36)+Q37)+Q38)
A40: Tax | B40: tax | D40: 302.18462 | E40: 315.75617 | F40: 167.46316 | G40: 102.88364 | H40: =(MAX(H39,0)*H17) | I40: =(MAX(I39,0)*I17) | J40: =(MAX(J39,0)*J17) | K40: =(MAX(K39,0)*K17) | L40: =(MAX(L39,0)*L17) | M40: =(MAX(M39,0)*M17) | N40: =(MAX(N39,0)*N17) | O40: =(MAX(O39,0)*O17) | ... Q40: =(MAX(Q39,0)*Q17)
A41: Net profit (incl. minorities) | B41: np | D41: 1298.1636 | E41: 865.31352 | F41: 542.78049 | G41: 361.20087 | H41: =(H39-H40) | I41: =(I39-I40) | J41: =(J39-J40) | K41: =(K39-K40) | L41: =(L39-L40) | M41: =(M39-M40) | N41: =(N39-N40) | O41: =(O39-O40) | ... Q41: =(Q39-Q40)
A42: Minority interests | B42: minority | D42: 708.26627 | E42: 439.13433 | F42: 233.6957 | G42: 130.66173 | H42: =(H41*H22) | I42: =(I41*I22) | J42: =(J41*J22) | K42: =(K41*K22) | L42: =(L41*L22) | M42: =(M41*M22) | N42: =(N41*N22) | O42: =(O41*O22) | ... Q42: =(Q41*Q22)
A43: Net profit to parent | B43: np_parent | D43: 589.89732 | E43: 426.17919 | F43: 309.08479 | G43: 230.53914 | H43: =(H41-H42) | I43: =(I41-I42) | J43: =(J41-J42) | K43: =(K41-K42) | L43: =(L41-L42) | M43: =(M41-M42) | N43: =(N41-N42) | O43: =(O41-O42) | ... Q43: =(Q41-Q42)
A44: Shares outstanding (m) | B44: shares | D44: 192638.08 | E44: 154111.75 | F44: 154732.12 | G44: 154732.12 | H44: =(G44*(1+H24)) | I44: =(H44*(1+I24)) | J44: =(I44*(1+J24)) | K44: =(J44*(1+K24)) | L44: =(K44*(1+L24)) | M44: =(L44*(1+M24)) | N44: =(M44*(1+N24)) | O44: =(N44*(1+O24)) | ... Q44: =(P44*(1+Q24))
A45: EPS | B45: eps | D45: 0.0030622052 | E45: 0.0027653907 | F45: 0.0019975477 | G45: 0.0014899243 | H45: =(IF(H44=0,0,H43/H44)*$C$7) | I45: =(IF(I44=0,0,I43/I44)*$C$7) | J45: =(IF(J44=0,0,J43/J44)*$C$7) | K45: =(IF(K44=0,0,K43/K44)*$C$7) | L45: =(IF(L44=0,0,L43/L44)*$C$7) | M45: =(IF(M44=0,0,M43/M44)*$C$7) | N45: =(IF(N44=0,0,N43/N44)*$C$7) | O45: =(IF(O44=0,0,O43/O44)*$C$7) | ... Q45: =(IF(Q44=0,0,Q43/Q44)*$C$7)
A46: DPS (declared on the year) | B46: dps | D46: 0 | E46: 0 | F46: 0 | G46: 0 | H46: =(MAX(H45,0)*H23) | I46: =(MAX(I45,0)*I23) | J46: =(MAX(J45,0)*J23) | K46: =(MAX(K45,0)*K23) | L46: =(MAX(L45,0)*L23) | M46: =(MAX(M45,0)*M23) | N46: =(MAX(N45,0)*N23) | O46: =(MAX(O45,0)*O23) | ... Q46: =(MAX(Q45,0)*Q23)
A47: Dividends paid | B47: dividends_paid | H47: =IF($C$7=0,0,(G46*G44)/$C$7) | I47: =IF($C$7=0,0,(H46*H44)/$C$7) | J47: =IF($C$7=0,0,(I46*I44)/$C$7) | K47: =IF($C$7=0,0,(J46*J44)/$C$7) | L47: =IF($C$7=0,0,(K46*K44)/$C$7) | M47: =IF($C$7=0,0,(L46*L44)/$C$7) | N47: =IF($C$7=0,0,(M46*M44)/$C$7) | O47: =IF($C$7=0,0,(N46*N44)/$C$7) | ... Q47: =IF($C$7=0,0,(P46*P44)/$C$7)
A48: Capital expenditure | B48: capex | D48: 188.54124 | E48: 306.13337 | F48: 403.84397 | G48: 467.04918 | H48: =(H29*H15) | I48: =(I29*I15) | J48: =(J29*J15) | K48: =(K29*K15) | L48: =(L29*L15) | M48: =(M29*M15) | N48: =(N29*N15) | O48: =(O29*O15) | ... Q48: =(Q29*Q15)
A49: Change in working capital | B49: delta_nwc | E49: 319.75268 | F49: 316.47267 | G49: 22.532289 | H49: =(H54-G54) | I49: =(I54-H54) | J49: =(J54-I54) | K49: =(K54-J54) | L49: =(L54-K54) | M49: =(M54-L54) | N49: =(N54-M54) | O49: =(O54-N54) | ... Q49: =(Q54-P54)
A50: Free cash flow to firm | B50: fcff | E50: 307.62284 | F50: -139.36759 | G50: -99.367434 | H50: =((((H33*(1-H17))+H34)-H48)-H49) | I50: =((((I33*(1-I17))+I34)-I48)-I49) | J50: =((((J33*(1-J17))+J34)-J48)-J49) | K50: =((((K33*(1-K17))+K34)-K48)-K49) | L50: =((((L33*(1-L17))+L34)-L48)-L49) | M50: =((((M33*(1-M17))+M34)-M48)-M49) | N50: =((((N33*(1-N17))+N34)-N48)-N49) | O50: =((((O33*(1-O17))+O34)-O48)-O49) | ... Q50: =((((Q33*(1-Q17))+Q34)-Q48)-Q49)
A51: Net borrowing | B51: net_borrowing | E51: -830.21855 | F51: 409.45468 | G51: 269.83419 | H51: =H20 | I51: =I20 | J51: =J20 | K51: =K20 | L51: =L20 | M51: =M20 | N51: =N20 | O51: =O20 | ... Q51: =Q20
A52: Dividends to minorities | B52: minority_div | H52: =(MAX(G42,0)*H23) | I52: =(MAX(H42,0)*I23) | J52: =(MAX(I42,0)*J23) | K52: =(MAX(J42,0)*K23) | L52: =(MAX(K42,0)*L23) | M52: =(MAX(L42,0)*M23) | N52: =(MAX(M42,0)*N23) | O52: =(MAX(N42,0)*O23) | ... Q52: =(MAX(P42,0)*Q23)
A53: Free cash flow to equity | B53: fcfe | H53: =(((((H41+H34)-H48)-H49)+H51)-H52) | I53: =(((((I41+I34)-I48)-I49)+I51)-I52) | J53: =(((((J41+J34)-J48)-J49)+J51)-J52) | K53: =(((((K41+K34)-K48)-K49)+K51)-K52) | L53: =(((((L41+L34)-L48)-L49)+L51)-L52) | M53: =(((((M41+M34)-M48)-M49)+M51)-M52) | N53: =(((((N41+N34)-N48)-N49)+N51)-N52) | O53: =(((((O41+O34)-O48)-O49)+O51)-O52) | ... Q53: =(((((Q41+Q34)-Q48)-Q49)+Q51)-Q52)
A54: Operating working capital | B54: nwc | D54: -47.964531 | E54: 271.78814 | F54: 588.26081 | G54: 610.7931 | H54: =(H29*H16) | I54: =(I29*I16) | J54: =(J29*J16) | K54: =(K29*K16) | L54: =(L29*L16) | M54: =(M29*M16) | N54: =(N29*N16) | O54: =(O29*O16) | ... Q54: =(Q29*Q16)
A55: Cash & equivalents | B55: cash | D55: 1122.6854 | E55: 657.75375 | F55: 908.48203 | G55: 575.52618 | H55: =(((((((G55+H41)+H34)-H48)-H49)+H51)-H47)-H52) | I55: =(((((((H55+I41)+I34)-I48)-I49)+I51)-I47)-I52) | J55: =(((((((I55+J41)+J34)-J48)-J49)+J51)-J47)-J52) | K55: =(((((((J55+K41)+K34)-K48)-K49)+K51)-K47)-K52) | L55: =(((((((K55+L41)+L34)-L48)-L49)+L51)-L47)-L52) | M55: =(((((((L55+M41)+M34)-M48)-M49)+M51)-M47)-M52) | N55: =(((((((M55+N41)+N34)-N48)-N49)+N51)-N47)-N52) | O55: =(((((((N55+O41)+O34)-O48)-O49)+O51)-O47)-O52) | ... Q55: =(((((((P55+Q41)+Q34)-Q48)-Q49)+Q51)-Q47)-Q52)
A56: Total debt | B56: debt | D56: 1637.0937 | E56: 806.8751 | F56: 1216.3298 | G56: 1486.164 | H56: =(G56+H51) | I56: =(H56+I51) | J56: =(I56+J51) | K56: =(J56+K51) | L56: =(K56+L51) | M56: =(L56+M51) | N56: =(M56+N51) | O56: =(N56+O51) | ... Q56: =(P56+Q51)
A57: Fixed assets (net) | B57: ppe | D57: 3118.3319 | E57: 870.6443 | F57: 985.01679 | G57: 1356.2479 | H57: =((G57+H48)-H34) | I57: =((H57+I48)-I34) | J57: =((I57+J48)-J34) | K57: =((J57+K48)-K34) | L57: =((K57+L48)-L34) | M57: =((L57+M48)-M34) | N57: =((M57+N48)-N34) | O57: =((N57+O48)-O34) | ... Q57: =((P57+Q48)-Q34)
A58: Parent shareholders' equity | B58: equity | D58: 2072.6673 | E58: 1383.4245 | F58: 1608.4399 | G58: 1816.7713 | H58: =((G58+H43)-H47) | I58: =((H58+I43)-I47) | J58: =((I58+J43)-J47) | K58: =((J58+K43)-K47) | L58: =((K58+L43)-L47) | M58: =((L58+M43)-M47) | N58: =((M58+N43)-N47) | O58: =((N58+O43)-O47) | ... Q58: =((P58+Q43)-Q47)
A59: Minority interest (balance sheet) | B59: minority_bs | D59: 985.31806 | E59: 337.39065 | F59: 335.1395 | G59: 444.42635 | H59: =((G59+H42)-H52) | I59: =((H59+I42)-I52) | J59: =((I59+J42)-J52) | K59: =((J59+K42)-K52) | L59: =((K59+L42)-L52) | M59: =((L59+M42)-M52) | N59: =((M59+N42)-N52) | O59: =((N59+O42)-O52) | ... Q59: =((P59+Q42)-Q52)
A60: Other assets less other liabilities | B60: other_net | D60: 502.02628 | E60: 727.50409 | F60: 678.14954 | G60: 1204.7944 | H60: =G60 | I60: =H60 | J60: =I60 | K60: =J60 | L60: =K60 | M60: =L60 | N60: =M60 | O60: =N60 | ... Q60: =P60
A61: Balance check (should be zero) | B61: bs_check | H61: =((((((H55+H54)+H57)+H60)-H56)-H58)-H59) | I61: =((((((I55+I54)+I57)+I60)-I56)-I58)-I59) | J61: =((((((J55+J54)+J57)+J60)-J56)-J58)-J59) | K61: =((((((K55+K54)+K57)+K60)-K56)-K58)-K59) | L61: =((((((L55+L54)+L57)+L60)-L56)-L58)-L59) | M61: =((((((M55+M54)+M57)+M60)-M56)-M58)-M59) | N61: =((((((N55+N54)+N57)+N60)-N56)-N58)-N59) | O61: =((((((O55+O54)+O57)+O60)-O56)-O58)-O59) | ... Q61: =((((((Q55+Q54)+Q57)+Q60)-Q56)-Q58)-Q59)
A62: Net debt (cash) | B62: net_debt | D62: 514.40828 | E62: 149.12135 | F62: 307.84775 | G62: 910.63779 | H62: =(H56-H55) | I62: =(I56-I55) | J62: =(J56-J55) | K62: =(K56-K55) | L62: =(L56-L55) | M62: =(M56-M55) | N62: =(N56-N55) | O62: =(O56-O55) | ... Q62: =(Q56-Q55)
A63: Book value per share | B63: bvps | D63: 0.010759385 | E63: 0.0089767623 | F63: 0.010394997 | G63: 0.011741397 | H63: =(IF(H44=0,0,H58/H44)*$C$7) | I63: =(IF(I44=0,0,I58/I44)*$C$7) | J63: =(IF(J44=0,0,J58/J44)*$C$7) | K63: =(IF(K44=0,0,K58/K44)*$C$7) | L63: =(IF(L44=0,0,L58/L44)*$C$7) | M63: =(IF(M44=0,0,M58/M44)*$C$7) | N63: =(IF(N44=0,0,N58/N44)*$C$7) | O63: =(IF(O44=0,0,O58/O44)*$C$7) | ... Q63: =(IF(Q44=0,0,Q58/Q44)*$C$7)
A64: Revenue growth | B64: revenue_growth | E64: -0.15806399 | F64: -0.39820525 | G64: -0.075081097 | H64: =(IF(G29=0,0,H29/G29)-1) | I64: =(IF(H29=0,0,I29/H29)-1) | J64: =(IF(I29=0,0,J29/I29)-1) | K64: =(IF(J29=0,0,K29/J29)-1) | L64: =(IF(K29=0,0,L29/K29)-1) | M64: =(IF(L29=0,0,M29/L29)-1) | N64: =(IF(M29=0,0,N29/M29)-1) | O64: =(IF(N29=0,0,O29/N29)-1) | ... Q64: =(IF(P29=0,0,Q29/P29)-1)
A65: Gross margin | B65: gross_margin | D65: 0.44291229 | E65: 0.41324027 | F65: 0.40705442 | G65: 0.33736401 | H65: =IF(H29=0,0,H31/H29) | I65: =IF(I29=0,0,I31/I29) | J65: =IF(J29=0,0,J31/J29) | K65: =IF(K29=0,0,K31/K29) | L65: =IF(L29=0,0,L31/L29) | M65: =IF(M29=0,0,M31/M29) | N65: =IF(N29=0,0,N31/N29) | O65: =IF(O29=0,0,O31/O29) | ... Q65: =IF(Q29=0,0,Q31/Q29)
A66: EBITDA margin | B66: ebitda_margin | D66: 0.30076519 | E66: 0.25305273 | F66: 0.24335009 | G66: 0.17164466 | H66: =IF(H29=0,0,H35/H29) | I66: =IF(I29=0,0,I35/I29) | J66: =IF(J29=0,0,J35/J29) | K66: =IF(K29=0,0,K35/K29) | L66: =IF(L29=0,0,L35/L29) | M66: =IF(M29=0,0,M35/M29) | N66: =IF(N29=0,0,N35/N29) | O66: =IF(O29=0,0,O35/O29) | ... Q66: =IF(Q29=0,0,Q35/Q29)
A67: EBIT margin | B67: ebit_margin | D67: 0.29837131 | E67: 0.25022389 | F67: 0.2156323 | G67: 0.14364078 | H67: =IF(H29=0,0,H33/H29) | I67: =IF(I29=0,0,I33/I29) | J67: =IF(J29=0,0,J33/J29) | K67: =IF(K29=0,0,K33/K29) | L67: =IF(L29=0,0,L33/L29) | M67: =IF(M29=0,0,M33/M29) | N67: =IF(N29=0,0,N33/N29) | O67: =IF(O29=0,0,O33/O29) | ... Q67: =IF(Q29=0,0,Q33/Q29)
A68: Net margin | B68: np_margin | D68: 0.099040773 | E68: 0.084986658 | F68: 0.1024207 | G68: 0.082594501 | H68: =IF(H29=0,0,H43/H29) | I68: =IF(I29=0,0,I43/I29) | J68: =IF(J29=0,0,J43/J29) | K68: =IF(K29=0,0,K43/K29) | L68: =IF(L29=0,0,L43/L29) | M68: =IF(M29=0,0,M43/M29) | N68: =IF(N29=0,0,N43/N29) | O68: =IF(O29=0,0,O43/O29) | ... Q68: =IF(Q29=0,0,Q43/Q29)
A69: EPS growth | B69: eps_growth | E69: -0.096928346 | F69: -0.27766167 | G69: -0.25412331 | H69: =(IF(G45=0,0,H45/G45)-1) | I69: =(IF(H45=0,0,I45/H45)-1) | J69: =(IF(I45=0,0,J45/I45)-1) | K69: =(IF(J45=0,0,K45/J45)-1) | L69: =(IF(K45=0,0,L45/K45)-1) | M69: =(IF(L45=0,0,M45/L45)-1) | N69: =(IF(M45=0,0,N45/M45)-1) | O69: =(IF(N45=0,0,O45/N45)-1) | ... Q69: =(IF(P45=0,0,Q45/P45)-1)
A70: ROE | B70: roe | E70: 0.24662492 | F70: 0.20661684 | G70: 0.1346131 | H70: =IF(IF(2=0,0,(H58+G58)/2)=0,0,H43/IF(2=0,0,(H58+G58)/2)) | I70: =IF(IF(2=0,0,(I58+H58)/2)=0,0,I43/IF(2=0,0,(I58+H58)/2)) | J70: =IF(IF(2=0,0,(J58+I58)/2)=0,0,J43/IF(2=0,0,(J58+I58)/2)) | K70: =IF(IF(2=0,0,(K58+J58)/2)=0,0,K43/IF(2=0,0,(K58+J58)/2)) | L70: =IF(IF(2=0,0,(L58+K58)/2)=0,0,L43/IF(2=0,0,(L58+K58)/2)) | M70: =IF(IF(2=0,0,(M58+L58)/2)=0,0,M43/IF(2=0,0,(M58+L58)/2)) | N70: =IF(IF(2=0,0,(N58+M58)/2)=0,0,N43/IF(2=0,0,(N58+M58)/2)) | O70: =IF(IF(2=0,0,(O58+N58)/2)=0,0,O43/IF(2=0,0,(O58+N58)/2)) | ... Q70: =IF(IF(2=0,0,(Q58+P58)/2)=0,0,Q43/IF(2=0,0,(Q58+P58)/2))
A71: Net debt / EBITDA | B71: net_debt_ebitda | D71: 0.28715605 | E71: 0.11751338 | F71: 0.41919355 | G71: 1.9007362 | H71: =IF(H35=0,0,H62/H35) | I71: =IF(I35=0,0,I62/I35) | J71: =IF(J35=0,0,J62/J35) | K71: =IF(K35=0,0,K62/K35) | L71: =IF(L35=0,0,L62/L35) | M71: =IF(M35=0,0,M62/M35) | N71: =IF(N35=0,0,N62/N35) | O71: =IF(O35=0,0,O62/O35) | ... Q71: =IF(Q35=0,0,Q62/Q35)
A72: Payout ratio | B72: payout_ratio | D72: 0 | E72: 0 | F72: 0 | G72: 0 | H72: =IF(H45=0,0,H46/H45) | I72: =IF(I45=0,0,I46/I45) | J72: =IF(J45=0,0,J46/J45) | K72: =IF(K45=0,0,K46/K45) | L72: =IF(L45=0,0,L46/L45) | M72: =IF(M45=0,0,M46/M45) | N72: =IF(N45=0,0,N46/N45) | O72: =IF(O45=0,0,O46/O45) | ... Q72: =IF(Q45=0,0,Q46/Q45)
A73: Capex / revenue | B73: capex_revenue | D73: 0.031655119 | E73: 0.061047683 | F73: 0.13382083 | G73: 0.16732818 | H73: =IF(H29=0,0,H48/H29) | I73: =IF(I29=0,0,I48/I29) | J73: =IF(J29=0,0,J48/J29) | K73: =IF(K29=0,0,K48/K29) | L73: =IF(L29=0,0,L48/L29) | M73: =IF(M29=0,0,M48/M29) | N73: =IF(N29=0,0,N48/N29) | O73: =IF(O29=0,0,O48/O29) | ... Q73: =IF(Q29=0,0,Q48/Q29)
A75: VALUATION
A76: Last price (IDR) | C76: 750
A77: Shares outstanding (m) | C77: 154732.12
A78: IDR per USD (spot) | C78: 18183
A79: Debt at balance-sheet date | C79: 1911.111
A80: Cash at balance-sheet date | C80: 814.37669
A81: Minority interest (book) | C81: 954.03994
A82: Associates & investments (book) | C82: 6.479142
A83: Post-balance-sheet & other items (sourced, probability-weighted) | C83: 0
A84: Parent equity at balance-sheet date | C84: 2093.8835
A85: Per-share factor | C85: 1
A86: Risk-free rate | C86: =Drivers!$C$8
A87: Less: default spread (IDR only) | C87: 0
A88: Mature ERP + Indonesia CRP | C88: =Drivers!$C$10+Drivers!$C$11
A89: Tax rate | C89: =Drivers!$C$13
A90: Unlevered beta (industry default (config)) | C90: 0.9
A91: Debt / equity (market) | C91: 0.29943992
A92: Levered beta | C92: =$C$90*(1+(1-$C$89)*$C$91)
A93: Explicit company premium | C93: 0
A94: Cost of equity | C94: =$C$86-$C$87+$C$92*$C$88+$C$93
A95: Pre-tax cost of debt | C95: =$C$86+Drivers!$C$12
A96: WACC | C96: =1/(1+$C$91)*$C$94+$C$91/(1+$C$91)*$C$95*(1-$C$89)
A97: Terminal growth (capped) | C97: 0.02
A99: Sum of the parts
A100: Value per share (IDR) — Sum of the parts (engine value) | C100: 208.37026
A102: TARGET
A103: Weight: Sum of the parts | C103: 1
A104: Value today (weighted) | C104: =$C$100*$C$103
A105: DPS expected in next 12 months (IDR) | C105: 0
A106: Base-case 12-month value | C106: =MAX(0,$C$104*(1+$C$94)-$C$105)
A107: Bear probability | C107: 0.25
...

Sheet FOLK
A1: PT Multi Garam Utama Tbk (FOLK.JK) — Conglomerates & multi-sector holdings
A2: Units: IDR bn; per-share in IDR unless marked IDR. Model asof 2026-10-29 · data 2026-10-27
A4: Line | C4: Scalar | D4: FY2022A | E4: FY2023A | F4: FY2024A | G4: FY2025A | H4: FY2026E | I4: FY2027E | J4: FY2028E | K4: FY2029E | L4: FY2030E | M4: FY2031E | N4: FY2032E | O4: FY2033E | P4: FY2034E | Q4: FY2035E
A6: PARAMETERS
A7: ps_factor | C7: 1000
A8: vp_factor | C8: 1
A10: INPUTS (company assumptions)
A11: Revenue growth | B11: a.revenue_growth | H11: 0.02 | I11: 0.05 | J11: 0.05 | K11: 0.05 | L11: 0.05 | M11: 0.04 | N11: 0.04 | O11: 0.04 | P11: 0.04 | Q11: 0.04
A12: Gross margin at base input costs | B12: a.gross_margin | H12: 0.52 | I12: 0.52 | J12: 0.52 | K12: 0.52 | L12: 0.52 | M12: 0.52 | N12: 0.52 | O12: 0.52 | P12: 0.52 | Q12: 0.52
A13: SG&A / revenue | B13: a.opex_pct | H13: 1 | I13: 1 | J13: 1 | K13: 1 | L13: 1 | M13: 1 | N13: 1 | O13: 1 | P13: 1 | Q13: 1
A14: D&A / revenue | B14: a.da_pct | H14: 0.18 | I14: 0.18 | J14: 0.18 | K14: 0.18 | L14: 0.18 | M14: 0.18 | N14: 0.18 | O14: 0.18 | P14: 0.18 | Q14: 0.18
A15: Capex / revenue | B15: a.capex_pct | H15: 0.02 | I15: 0.02 | J15: 0.02 | K15: 0.02 | L15: 0.02 | M15: 0.02 | N15: 0.02 | O15: 0.02 | P15: 0.02 | Q15: 0.02
A16: Operating working capital / revenue | B16: a.nwc_pct | H16: 0 | I16: 0 | J16: 0 | K16: 0 | L16: 0 | M16: 0 | N16: 0 | O16: 0 | P16: 0 | Q16: 0
A17: Effective tax rate | B17: a.tax_rate | H17: 0 | I17: 0 | J17: 0 | K17: 0 | L17: 0 | M17: 0 | N17: 0 | O17: 0 | P17: 0 | Q17: 0
A18: Cost of debt (on opening debt) | B18: a.cost_of_debt | C18: 0
A19: Yield on opening cash | B19: a.cash_yield | C19: 0.055
A20: Net new borrowing | B20: a.net_borrowing | H20: 0 | I20: 0 | J20: 0 | K20: 0 | L20: 0 | M20: 0 | N20: 0 | O20: 0 | P20: 0 | Q20: 0
A21: Other non-operating items | B21: a.other_nonop | H21: 0 | I21: 0 | J21: 0 | K21: 0 | L21: 0 | M21: 0 | N21: 0 | O21: 0 | P21: 0 | Q21: 0
A22: Minorities' share of net profit | B22: a.minority_pct | H22: 0.27 | I22: 0.27 | J22: 0.27 | K22: 0.27 | L22: 0.27 | M22: 0.27 | N22: 0.27 | O22: 0.27 | P22: 0.27 | Q22: 0.27
A23: Dividend payout | B23: a.payout | H23: 0 | I23: 0 | J23: 0 | K23: 0 | L23: 0 | M23: 0 | N23: 0 | O23: 0 | P23: 0 | Q23: 0
A24: Change in share count | B24: a.share_change | H24: 0.0362 | I24: 0 | J24: 0 | K24: 0 | L24: 0 | M24: 0 | N24: 0 | O24: 0 | P24: 0 | Q24: 0
A25: Terminal growth (DCF) | B25: a.terminal_growth | C25: 0.04
A26: Holding-company discount to SOTP | B26: a.holdco_discount | C26: 0.3
A28: MODEL
A29: Revenue | B29: revenue | D29: 40.237613 | E29: 24.809592 | F29: 19.354231 | G29: 18.756716 | H29: =(G29*(1+H11)) | I29: =(H29*(1+I11)) | J29: =(I29*(1+J11)) | K29: =(J29*(1+K11)) | L29: =(K29*(1+L11)) | M29: =(L29*(1+M11)) | N29: =(M29*(1+N11)) | O29: =(N29*(1+O11)) | ... Q29: =(P29*(1+Q11))
A30: Cost of revenue | B30: cogs | D30: 16.31418 | E30: 17.752245 | F30: 10.90316 | G30: 8.9259937 | H30: =(H29*(1-H12)) | I30: =(I29*(1-I12)) | J30: =(J29*(1-J12)) | K30: =(K29*(1-K12)) | L30: =(L29*(1-L12)) | M30: =(M29*(1-M12)) | N30: =(N29*(1-N12)) | O30: =(O29*(1-O12)) | ... Q30: =(Q29*(1-Q12))
A31: Gross profit | B31: gross_profit | D31: 23.923433 | E31: 7.0573462 | F31: 8.4510709 | G31: 9.8307224 | H31: =(H29-H30) | I31: =(I29-I30) | J31: =(J29-J30) | K31: =(K29-K30) | L31: =(L29-L30) | M31: =(M29-M30) | N31: =(N29-N30) | O31: =(O29-O30) | ... Q31: =(Q29-Q30)
A32: SG&A and other opex | B32: opex | D32: 22.710809 | E32: 26.626909 | F32: 28.668657 | G32: 23.385558 | H32: =(H29*H13) | I32: =(I29*I13) | J32: =(J29*J13) | K32: =(K29*K13) | L32: =(L29*L13) | M32: =(M29*M13) | N32: =(N29*N13) | O32: =(O29*O13) | ... Q32: =(Q29*Q13)
A33: EBIT | B33: ebit | D33: 1.2126243 | E33: -19.569563 | F33: -20.217586 | G33: -13.554836 | H33: =(H31-H32) | I33: =(I31-I32) | J33: =(J31-J32) | K33: =(K31-K32) | L33: =(L31-L32) | M33: =(M31-M32) | N33: =(N31-N32) | O33: =(O31-O32) | ... Q33: =(Q31-Q32)
A34: Depreciation & amortisation | B34: da | D34: 0.89705653 | E34: 2.1802382 | F34: 3.4791438 | G34: 3.9318588 | H34: =(H29*H14) | I34: =(I29*I14) | J34: =(J29*J14) | K34: =(K29*K14) | L34: =(L29*L14) | M34: =(M29*M14) | N34: =(N29*N14) | O34: =(O29*O14) | ... Q34: =(Q29*Q14)
A35: EBITDA | B35: ebitda | D35: 2.1096808 | E35: -17.389325 | F35: -16.738442 | G35: -9.6229769 | H35: =(H33+H34) | I35: =(I33+I34) | J35: =(J33+J34) | K35: =(K33+K34) | L35: =(L33+L34) | M35: =(M33+M34) | N35: =(N33+N34) | O35: =(O33+O34) | ... Q35: =(Q33+Q34)
A36: Interest expense | B36: interest_expense | D36: 0.096128059 | E36: 0.17601561 | F36: 0.43406195 | G36: 0.8738956 | H36: =(G56*$C$18) | I36: =(H56*$C$18) | J36: =(I56*$C$18) | K36: =(J56*$C$18) | L36: =(K56*$C$18) | M36: =(L56*$C$18) | N36: =(M56*$C$18) | O36: =(N56*$C$18) | ... Q36: =(P56*$C$18)
A37: Interest income | B37: interest_income | D37: 0.29446668 | E37: 0.75877429 | F37: 0.57733364 | G37: 0.86106478 | H37: =(G55*$C$19) | I37: =(H55*$C$19) | J37: =(I55*$C$19) | K37: =(J55*$C$19) | L37: =(K55*$C$19) | M37: =(L55*$C$19) | N37: =(M55*$C$19) | O37: =(N55*$C$19) | ... Q37: =(P55*$C$19)
A38: Other non-operating | B38: other_nonop | D38: 3.9592419 | E38: 4.610569 | F38: -7.6333632 | G38: -6.6175718 | H38: =H21 | I38: =I21 | J38: =J21 | K38: =K21 | L38: =L21 | M38: =M21 | N38: =N21 | O38: =O21 | ... Q38: =Q21
A39: Profit before tax | B39: pbt | D39: 5.3702048 | E39: -14.376235 | F39: -27.707678 | G39: -20.185238 | H39: =(((H33-H36)+H37)+H38) | I39: =(((I33-I36)+I37)+I38) | J39: =(((J33-J36)+J37)+J38) | K39: =(((K33-K36)+K37)+K38) | L39: =(((L33-L36)+L37)+L38) | M39: =(((M33-M36)+M37)+M38) | N39: =(((N33-N36)+N37)+N38) | O39: =(((O33-O36)+O37)+O38) | ... Q39: =(((Q33-Q36)+Q37)+Q38)
A40: Tax | B40: tax | D40: 0.16886565 | E40: -0.03593765 | F40: -2.0254636 | G40: -1.4177821 | H40: =(MAX(H39,0)*H17) | I40: =(MAX(I39,0)*I17) | J40: =(MAX(J39,0)*J17) | K40: =(MAX(K39,0)*K17) | L40: =(MAX(L39,0)*L17) | M40: =(MAX(M39,0)*M17) | N40: =(MAX(N39,0)*N17) | O40: =(MAX(O39,0)*O17) | ... Q40: =(MAX(Q39,0)*Q17)
A41: Net profit (incl. minorities) | B41: np | D41: 5.2013391 | E41: -14.340298 | F41: -25.682214 | G41: -18.767456 | H41: =(H39-H40) | I41: =(I39-I40) | J41: =(J39-J40) | K41: =(K39-K40) | L41: =(L39-L40) | M41: =(M39-M40) | N41: =(N39-N40) | O41: =(O39-O40) | ... Q41: =(Q39-Q40)
A42: Minority interests | B42: minority | D42: 0.14468061 | E42: -3.6956137 | F42: -9.0210171 | G42: -5.0322769 | H42: =(H41*H22) | I42: =(I41*I22) | J42: =(J41*J22) | K42: =(K41*K22) | L42: =(L41*L22) | M42: =(M41*M22) | N42: =(N41*N22) | O42: =(O41*O22) | ... Q42: =(Q41*Q22)
A43: Net profit to parent | B43: np_parent | D43: 5.0566585 | E43: -10.644684 | F43: -16.661197 | G43: -13.735179 | H43: =(H41-H42) | I43: =(I41-I42) | J43: =(J41-J42) | K43: =(K41-K42) | L43: =(L41-L42) | M43: =(M41-M42) | N43: =(N41-N42) | O43: =(O41-O42) | ... Q43: =(Q41-Q42)
A44: Shares outstanding (m) | B44: shares | D44: 3948.1333 | E44: 3948.1333 | F44: 3948.1415 | G44: 3948.1415 | H44: =(G44*(1+H24)) | I44: =(H44*(1+I24)) | J44: =(I44*(1+J24)) | K44: =(J44*(1+K24)) | L44: =(K44*(1+L24)) | M44: =(L44*(1+M24)) | N44: =(M44*(1+N24)) | O44: =(N44*(1+O24)) | ... Q44: =(P44*(1+Q24))
A45: EPS | B45: eps | D45: 1.280772 | E45: -2.6961308 | F45: -4.2200101 | G45: -3.4788975 | H45: =(IF(H44=0,0,H43/H44)*$C$7) | I45: =(IF(I44=0,0,I43/I44)*$C$7) | J45: =(IF(J44=0,0,J43/J44)*$C$7) | K45: =(IF(K44=0,0,K43/K44)*$C$7) | L45: =(IF(L44=0,0,L43/L44)*$C$7) | M45: =(IF(M44=0,0,M43/M44)*$C$7) | N45: =(IF(N44=0,0,N43/N44)*$C$7) | O45: =(IF(O44=0,0,O43/O44)*$C$7) | ... Q45: =(IF(Q44=0,0,Q43/Q44)*$C$7)
A46: DPS (declared on the year) | B46: dps | E46: 0 | F46: 0 | G46: 0 | H46: =(MAX(H45,0)*H23) | I46: =(MAX(I45,0)*I23) | J46: =(MAX(J45,0)*J23) | K46: =(MAX(K45,0)*K23) | L46: =(MAX(L45,0)*L23) | M46: =(MAX(M45,0)*M23) | N46: =(MAX(N45,0)*N23) | O46: =(MAX(O45,0)*O23) | ... Q46: =(MAX(Q45,0)*Q23)
A47: Dividends paid | B47: dividends_paid | G47: 0.0015 | H47: =IF($C$7=0,0,(G46*G44)/$C$7) | I47: =IF($C$7=0,0,(H46*H44)/$C$7) | J47: =IF($C$7=0,0,(I46*I44)/$C$7) | K47: =IF($C$7=0,0,(J46*J44)/$C$7) | L47: =IF($C$7=0,0,(K46*K44)/$C$7) | M47: =IF($C$7=0,0,(L46*L44)/$C$7) | N47: =IF($C$7=0,0,(M46*M44)/$C$7) | O47: =IF($C$7=0,0,(N46*N44)/$C$7) | ... Q47: =IF($C$7=0,0,(P46*P44)/$C$7)
A48: Capital expenditure | B48: capex | D48: 1.6633685 | E48: 17.800438 | F48: 0.25959289 | G48: 0.10545299 | H48: =(H29*H15) | I48: =(I29*I15) | J48: =(J29*J15) | K48: =(K29*K15) | L48: =(L29*L15) | M48: =(M29*M15) | N48: =(N29*N15) | O48: =(O29*O15) | ... Q48: =(Q29*Q15)
A49: Change in working capital | B49: delta_nwc | E49: 12.606671 | F49: -19.134818 | G49: -12.929656 | H49: =(H54-G54) | I49: =(I54-H54) | J49: =(J54-I54) | K49: =(K54-J54) | L49: =(L54-K54) | M49: =(M54-L54) | N49: =(N54-M54) | O49: =(O54-N54) | ... Q49: =(Q54-P54)
A50: Free cash flow to firm | B50: fcff | E50: -47.747515 | F50: 3.614712 | G50: 4.1532986 | H50: =((((H33*(1-H17))+H34)-H48)-H49) | I50: =((((I33*(1-I17))+I34)-I48)-I49) | J50: =((((J33*(1-J17))+J34)-J48)-J49) | K50: =((((K33*(1-K17))+K34)-K48)-K49) | L50: =((((L33*(1-L17))+L34)-L48)-L49) | M50: =((((M33*(1-M17))+M34)-M48)-M49) | N50: =((((N33*(1-N17))+N34)-N48)-N49) | O50: =((((O33*(1-O17))+O34)-O48)-O49) | ... Q50: =((((Q33*(1-Q17))+Q34)-Q48)-Q49)
A51: Net borrowing | B51: net_borrowing | E51: 0.067805707 | F51: -0.67568994 | G51: -0.33852811 | H51: =H20 | I51: =I20 | J51: =J20 | K51: =K20 | L51: =L20 | M51: =M20 | N51: =N20 | O51: =O20 | ... Q51: =Q20
A52: Dividends to minorities | B52: minority_div | H52: =(MAX(G42,0)*H23) | I52: =(MAX(H42,0)*I23) | J52: =(MAX(I42,0)*J23) | K52: =(MAX(J42,0)*K23) | L52: =(MAX(K42,0)*L23) | M52: =(MAX(L42,0)*M23) | N52: =(MAX(M42,0)*N23) | O52: =(MAX(N42,0)*O23) | ... Q52: =(MAX(P42,0)*Q23)
A53: Free cash flow to equity | B53: fcfe | H53: =(((((H41+H34)-H48)-H49)+H51)-H52) | I53: =(((((I41+I34)-I48)-I49)+I51)-I52) | J53: =(((((J41+J34)-J48)-J49)+J51)-J52) | K53: =(((((K41+K34)-K48)-K49)+K51)-K52) | L53: =(((((L41+L34)-L48)-L49)+L51)-L52) | M53: =(((((M41+M34)-M48)-M49)+M51)-M52) | N53: =(((((N41+N34)-N48)-N49)+N51)-N52) | O53: =(((((O41+O34)-O48)-O49)+O51)-O52) | ... Q53: =(((((Q41+Q34)-Q48)-Q49)+Q51)-Q52)
A54: Operating working capital | B54: nwc | D54: 17.273241 | E54: 29.879912 | F54: 10.745094 | G54: -2.1845622 | H54: =(H29*H16) | I54: =(I29*I16) | J54: =(J29*J16) | K54: =(K29*K16) | L54: =(L29*L16) | M54: =(M29*M16) | N54: =(N29*N16) | O54: =(O29*O16) | ... Q54: =(Q29*Q16)
A55: Cash & equivalents | B55: cash | D55: 19.12754 | E55: 4.9323056 | F55: 2.0656692 | G55: 1.2473724 | H55: =(((((((G55+H41)+H34)-H48)-H49)+H51)-H47)-H52) | I55: =(((((((H55+I41)+I34)-I48)-I49)+I51)-I47)-I52) | J55: =(((((((I55+J41)+J34)-J48)-J49)+J51)-J47)-J52) | K55: =(((((((J55+K41)+K34)-K48)-K49)+K51)-K47)-K52) | L55: =(((((((K55+L41)+L34)-L48)-L49)+L51)-L47)-L52) | M55: =(((((((L55+M41)+M34)-M48)-M49)+M51)-M47)-M52) | N55: =(((((((M55+N41)+N34)-N48)-N49)+N51)-N47)-N52) | O55: =(((((((N55+O41)+O34)-O48)-O49)+O51)-O47)-O52) | ... Q55: =(((((((P55+Q41)+Q34)-Q48)-Q49)+Q51)-Q47)-Q52)
A56: Total debt | B56: debt | D56: 1.0349373 | E56: 1.102743 | F56: 0.4270531 | G56: 0.088524988 | H56: =(G56+H51) | I56: =(H56+I51) | J56: =(I56+J51) | K56: =(J56+K51) | L56: =(K56+L51) | M56: =(L56+M51) | N56: =(M56+N51) | O56: =(N56+O51) | ... Q56: =(P56+Q51)
A57: Fixed assets (net) | B57: ppe | D57: 3.3328139 | E57: 16.335261 | F57: 13.850082 | G57: 11.096151 | H57: =((G57+H48)-H34) | I57: =((H57+I48)-I34) | J57: =((I57+J48)-J34) | K57: =((J57+K48)-K34) | L57: =((K57+L48)-L34) | M57: =((L57+M48)-M34) | N57: =((M57+N48)-N34) | O57: =((N57+O48)-O34) | ... Q57: =((P57+Q48)-Q34)
A58: Parent shareholders' equity | B58: equity | D58: 70.464674 | E58: 112.07442 | F58: 95.428758 | G58: 81.715446 | H58: =((G58+H43)-H47) | I58: =((H58+I43)-I47) | J58: =((I58+J43)-J47) | K58: =((J58+K43)-K47) | L58: =((K58+L43)-L47) | M58: =((L58+M43)-M47) | N58: =((M58+N43)-N47) | O58: =((N58+O43)-O47) | ... Q58: =((P58+Q43)-Q47)
A59: Minority interest (balance sheet) | B59: minority_bs | D59: 2.1429065 | E59: -1.5604816 | F59: -10.573045 | G59: -15.5994 | H59: =((G59+H42)-H52) | I59: =((H59+I42)-I52) | J59: =((I59+J42)-J52) | K59: =((J59+K42)-K52) | L59: =((K59+L42)-L52) | M59: =((L59+M42)-M52) | N59: =((M59+N42)-N52) | O59: =((N59+O42)-O52) | ... Q59: =((P59+Q42)-Q52)
A60: Other assets less other liabilities | B60: other_net | D60: 33.908923 | E60: 60.4692 | F60: 58.621921 | G60: 56.045609 | H60: =G60 | I60: =H60 | J60: =I60 | K60: =J60 | L60: =K60 | M60: =L60 | N60: =M60 | O60: =N60 | ... Q60: =P60
A61: Balance check (should be zero) | B61: bs_check | H61: =((((((H55+H54)+H57)+H60)-H56)-H58)-H59) | I61: =((((((I55+I54)+I57)+I60)-I56)-I58)-I59) | J61: =((((((J55+J54)+J57)+J60)-J56)-J58)-J59) | K61: =((((((K55+K54)+K57)+K60)-K56)-K58)-K59) | L61: =((((((L55+L54)+L57)+L60)-L56)-L58)-L59) | M61: =((((((M55+M54)+M57)+M60)-M56)-M58)-M59) | N61: =((((((N55+N54)+N57)+N60)-N56)-N58)-N59) | O61: =((((((O55+O54)+O57)+O60)-O56)-O58)-O59) | ... Q61: =((((((Q55+Q54)+Q57)+Q60)-Q56)-Q58)-Q59)
A62: Net debt (cash) | B62: net_debt | D62: -18.092603 | E62: -3.8295625 | F62: -1.6386161 | G62: -1.1588474 | H62: =(H56-H55) | I62: =(I56-I55) | J62: =(J56-J55) | K62: =(K56-K55) | L62: =(L56-L55) | M62: =(M56-M55) | N62: =(N56-N55) | O62: =(O56-O55) | ... Q62: =(Q56-Q55)
A63: Book value per share | B63: bvps | D63: 17.847592 | E63: 28.386685 | F63: 24.170552 | G63: 20.697193 | H63: =(IF(H44=0,0,H58/H44)*$C$7) | I63: =(IF(I44=0,0,I58/I44)*$C$7) | J63: =(IF(J44=0,0,J58/J44)*$C$7) | K63: =(IF(K44=0,0,K58/K44)*$C$7) | L63: =(IF(L44=0,0,L58/L44)*$C$7) | M63: =(IF(M44=0,0,M58/M44)*$C$7) | N63: =(IF(N44=0,0,N58/N44)*$C$7) | O63: =(IF(O44=0,0,O58/O44)*$C$7) | ... Q63: =(IF(Q44=0,0,Q58/Q44)*$C$7)
A64: Revenue growth | B64: revenue_growth | E64: -0.38342288 | F64: -0.21988919 | G64: -0.030872554 | H64: =(IF(G29=0,0,H29/G29)-1) | I64: =(IF(H29=0,0,I29/H29)-1) | J64: =(IF(I29=0,0,J29/I29)-1) | K64: =(IF(J29=0,0,K29/J29)-1) | L64: =(IF(K29=0,0,L29/K29)-1) | M64: =(IF(L29=0,0,M29/L29)-1) | N64: =(IF(M29=0,0,N29/M29)-1) | O64: =(IF(N29=0,0,O29/N29)-1) | ... Q64: =(IF(P29=0,0,Q29/P29)-1)
A65: Gross margin | B65: gross_margin | D65: 0.59455399 | E65: 0.28446039 | F65: 0.43665238 | G65: 0.52411746 | H65: =IF(H29=0,0,H31/H29) | I65: =IF(I29=0,0,I31/I29) | J65: =IF(J29=0,0,J31/J29) | K65: =IF(K29=0,0,K31/K29) | L65: =IF(L29=0,0,L31/L29) | M65: =IF(M29=0,0,M31/M29) | N65: =IF(N29=0,0,N31/N29) | O65: =IF(O29=0,0,O31/O29) | ... Q65: =IF(Q29=0,0,Q31/Q29)
A66: EBITDA margin | B66: ebitda_margin | D66: 0.052430565 | E66: -0.70091137 | F66: -0.86484669 | G66: -0.51304166 | H66: =IF(H29=0,0,H35/H29) | I66: =IF(I29=0,0,I35/I29) | J66: =IF(J29=0,0,J35/J29) | K66: =IF(K29=0,0,K35/K29) | L66: =IF(L29=0,0,L35/L29) | M66: =IF(M29=0,0,M35/M29) | N66: =IF(N29=0,0,N35/N29) | O66: =IF(O29=0,0,O35/O29) | ... Q66: =IF(Q29=0,0,Q35/Q29)
A67: EBIT margin | B67: ebit_margin | D67: 0.030136585 | E67: -0.78879021 | F67: -1.0446081 | G67: -0.72266571 | H67: =IF(H29=0,0,H33/H29) | I67: =IF(I29=0,0,I33/I29) | J67: =IF(J29=0,0,J33/J29) | K67: =IF(K29=0,0,K33/K29) | L67: =IF(L29=0,0,L33/L29) | M67: =IF(M29=0,0,M33/M29) | N67: =IF(N29=0,0,N33/N29) | O67: =IF(O29=0,0,O33/O29) | ... Q67: =IF(Q29=0,0,Q33/Q29)
A68: Net margin | B68: np_margin | D68: 0.12566994 | E68: -0.42905518 | F68: -0.86085556 | G68: -0.7322806 | H68: =IF(H29=0,0,H43/H29) | I68: =IF(I29=0,0,I43/I29) | J68: =IF(J29=0,0,J43/J29) | K68: =IF(K29=0,0,K43/K29) | L68: =IF(L29=0,0,L43/L29) | M68: =IF(M29=0,0,M43/M29) | N68: =IF(N29=0,0,N43/N29) | O68: =IF(O29=0,0,O43/O29) | ... Q68: =IF(Q29=0,0,Q43/Q29)
A69: EPS growth | B69: eps_growth | E69: -3.1050826 | F69: 0.56520972 | G69: -0.1756187 | H69: =(IF(G45=0,0,H45/G45)-1) | I69: =(IF(H45=0,0,I45/H45)-1) | J69: =(IF(I45=0,0,J45/I45)-1) | K69: =(IF(J45=0,0,K45/J45)-1) | L69: =(IF(K45=0,0,L45/K45)-1) | M69: =(IF(L45=0,0,M45/L45)-1) | N69: =(IF(M45=0,0,N45/M45)-1) | O69: =(IF(N45=0,0,O45/N45)-1) | ... Q69: =(IF(P45=0,0,Q45/P45)-1)
A70: ROE | B70: roe | E70: -0.11662909 | F70: -0.16058739 | G70: -0.15507343 | H70: =IF(IF(2=0,0,(H58+G58)/2)=0,0,H43/IF(2=0,0,(H58+G58)/2)) | I70: =IF(IF(2=0,0,(I58+H58)/2)=0,0,I43/IF(2=0,0,(I58+H58)/2)) | J70: =IF(IF(2=0,0,(J58+I58)/2)=0,0,J43/IF(2=0,0,(J58+I58)/2)) | K70: =IF(IF(2=0,0,(K58+J58)/2)=0,0,K43/IF(2=0,0,(K58+J58)/2)) | L70: =IF(IF(2=0,0,(L58+K58)/2)=0,0,L43/IF(2=0,0,(L58+K58)/2)) | M70: =IF(IF(2=0,0,(M58+L58)/2)=0,0,M43/IF(2=0,0,(M58+L58)/2)) | N70: =IF(IF(2=0,0,(N58+M58)/2)=0,0,N43/IF(2=0,0,(N58+M58)/2)) | O70: =IF(IF(2=0,0,(O58+N58)/2)=0,0,O43/IF(2=0,0,(O58+N58)/2)) | ... Q70: =IF(IF(2=0,0,(Q58+P58)/2)=0,0,Q43/IF(2=0,0,(Q58+P58)/2))
A71: Net debt / EBITDA | B71: net_debt_ebitda | D71: -8.5759906 | E71: 0.22022491 | F71: 0.097895378 | G71: 0.12042504 | H71: =IF(H35=0,0,H62/H35) | I71: =IF(I35=0,0,I62/I35) | J71: =IF(J35=0,0,J62/J35) | K71: =IF(K35=0,0,K62/K35) | L71: =IF(L35=0,0,L62/L35) | M71: =IF(M35=0,0,M62/M35) | N71: =IF(N35=0,0,N62/N35) | O71: =IF(O35=0,0,O62/O35) | ... Q71: =IF(Q35=0,0,Q62/Q35)
A72: Payout ratio | B72: payout_ratio | E72: 0 | F72: 0 | G72: 0 | H72: =IF(H45=0,0,H46/H45) | I72: =IF(I45=0,0,I46/I45) | J72: =IF(J45=0,0,J46/J45) | K72: =IF(K45=0,0,K46/K45) | L72: =IF(L45=0,0,L46/L45) | M72: =IF(M45=0,0,M46/M45) | N72: =IF(N45=0,0,N46/N45) | O72: =IF(O45=0,0,O46/O45) | ... Q72: =IF(Q45=0,0,Q46/Q45)
A73: Capex / revenue | B73: capex_revenue | D73: 0.041338647 | E73: 0.71748212 | F73: 0.01341272 | G73: 0.0056221458 | H73: =IF(H29=0,0,H48/H29) | I73: =IF(I29=0,0,I48/I29) | J73: =IF(J29=0,0,J48/J29) | K73: =IF(K29=0,0,K48/K29) | L73: =IF(L29=0,0,L48/L29) | M73: =IF(M29=0,0,M48/M29) | N73: =IF(N29=0,0,N48/N29) | O73: =IF(O29=0,0,O48/O29) | ... Q73: =IF(Q29=0,0,Q48/Q29)
A75: VALUATION
A76: Last price (IDR) | C76: 78
A77: Shares outstanding (m) | C77: 4091.3575
A78: IDR per USD (spot) | C78: 18183
A79: Debt at balance-sheet date | C79: 0
A80: Cash at balance-sheet date | C80: 45.363686
A81: Minority interest (book) | C81: -15.884507
A82: Associates & investments (book) | C82: 0.99318962
A83: Post-balance-sheet & other items (sourced, probability-weighted) | C83: 0
A84: Parent equity at balance-sheet date | C84: 136.00411
A85: Per-share factor | C85: 1000
A86: Risk-free rate | C86: =Drivers!$C$7
A87: Less: default spread (IDR only) | C87: =Drivers!$C$9
A88: Mature ERP + Indonesia CRP | C88: =Drivers!$C$10+Drivers!$C$11
A89: Tax rate | C89: =Drivers!$C$13
A90: Unlevered beta (industry default (config)) | C90: 0.9
A91: Debt / equity (market) | C91: 0
A92: Levered beta | C92: =$C$90*(1+(1-$C$89)*$C$91)
A93: Explicit company premium | C93: 0
A94: Cost of equity | C94: =$C$86-$C$87+$C$92*$C$88+$C$93
A95: Pre-tax cost of debt | C95: =$C$86+Drivers!$C$12
A96: WACC | C96: =1/(1+$C$91)*$C$94+$C$91/(1+$C$91)*$C$95*(1-$C$89)
A97: Terminal growth (capped) | C97: 0.04
A99: Sum of the parts
A100: Value per share (IDR) — Sum of the parts (engine value) | C100: 20.157072
A102: TARGET
A103: Weight: Sum of the parts | C103: 1
A104: Value today (weighted) | C104: =$C$100*$C$103
A105: DPS expected in next 12 months (IDR) | C105: 0
A106: Base-case 12-month value | C106: =MAX(0,$C$104*(1+$C$94)-$C$105)
A107: Bear probability | C107: 0.25
...

Sheet IMJS
A1: PT Indomobil Multi Jasa Tbk (IMJS.JK) — Conglomerates & multi-sector holdings
A2: Units: IDR bn; per-share in IDR unless marked IDR. Model asof 2026-10-29 · data 2026-10-27
A4: Line | C4: Scalar | D4: FY2022A | E4: FY2023A | F4: FY2024A | G4: FY2025A | H4: FY2026E | I4: FY2027E | J4: FY2028E | K4: FY2029E | L4: FY2030E | M4: FY2031E | N4: FY2032E | O4: FY2033E | P4: FY2034E | Q4: FY2035E
A6: PARAMETERS
A7: ps_factor | C7: 1000
A8: vp_factor | C8: 1
A10: INPUTS (company assumptions)
A11: Revenue growth | B11: a.revenue_growth | H11: 0.18 | I11: 0.13 | J11: 0.11 | K11: 0.1 | L11: 0.1 | M11: 0.1 | N11: 0.1 | O11: 0.1 | P11: 0.1 | Q11: 0.1
A12: Gross margin at base input costs | B12: a.gross_margin | H12: 0.382 | I12: 0.382 | J12: 0.382 | K12: 0.382 | L12: 0.382 | M12: 0.382 | N12: 0.382 | O12: 0.382 | P12: 0.382 | Q12: 0.382
A13: SG&A / revenue | B13: a.opex_pct | H13: 0.205 | I13: 0.205 | J13: 0.205 | K13: 0.205 | L13: 0.205 | M13: 0.205 | N13: 0.205 | O13: 0.205 | P13: 0.205 | Q13: 0.205
A14: D&A / revenue | B14: a.da_pct | H14: 0.163 | I14: 0.163 | J14: 0.163 | K14: 0.163 | L14: 0.163 | M14: 0.163 | N14: 0.163 | O14: 0.163 | P14: 0.163 | Q14: 0.163
A15: Capex / revenue | B15: a.capex_pct | H15: 0.4 | I15: 0.4 | J15: 0.4 | K15: 0.4 | L15: 0.4 | M15: 0.4 | N15: 0.4 | O15: 0.4 | P15: 0.4 | Q15: 0.4
A16: Operating working capital / revenue | B16: a.nwc_pct | H16: 1.370792 | I16: 1.370792 | J16: 1.370792 | K16: 1.370792 | L16: 1.370792 | M16: 1.370792 | N16: 1.370792 | O16: 1.370792 | P16: 1.370792 | Q16: 1.370792
A17: Effective tax rate | B17: a.tax_rate | H17: 0.42 | I17: 0.42 | J17: 0.42 | K17: 0.42 | L17: 0.42 | M17: 0.42 | N17: 0.42 | O17: 0.42 | P17: 0.42 | Q17: 0.42
A18: Cost of debt (on opening debt) | B18: a.cost_of_debt | C18: 0.0374
A19: Yield on opening cash | B19: a.cash_yield | C19: 0.021156
A20: Net new borrowing | B20: a.net_borrowing | H20: 2900 | I20: 2800 | J20: 2900 | K20: 3050 | L20: 3350 | M20: 3690 | N20: 3782.25 | O20: 3876.8062 | P20: 3973.7264 | Q20: 4073.0696
A21: Other non-operating items | B21: a.other_nonop | H21: 30 | I21: 30 | J21: 30 | K21: 30 | L21: 30 | M21: 30.75 | N21: 31.51875 | O21: 32.306719 | P21: 33.114387 | Q21: 33.942246
A22: Minorities' share of net profit | B22: a.minority_pct | H22: 0 | I22: 0 | J22: 0 | K22: 0 | L22: 0 | M22: 0 | N22: 0 | O22: 0 | P22: 0 | Q22: 0
A23: Dividend payout | B23: a.payout | H23: 0.02269 | I23: 0.019512 | J23: 0.017233 | K23: 0.015535 | L23: 0.01388 | M23: 0.012403 | N23: 0.011103 | O23: 0.009887 | P23: 0.008768 | Q23: 0.007753
A24: Change in share count | B24: a.share_change | H24: 0 | I24: 0 | J24: 0 | K24: 0 | L24: 0 | M24: 0 | N24: 0 | O24: 0 | P24: 0 | Q24: 0
A25: Terminal growth (DCF) | B25: a.terminal_growth | C25: 0.04
A26: Holding-company discount to SOTP | B26: a.holdco_discount | C26: 0.6
A28: MODEL
A29: Revenue | B29: revenue | D29: 4825.4336 | E29: 5154.369 | F29: 5405.027 | G29: 5785.168 | H29: =(G29*(1+H11)) | I29: =(H29*(1+I11)) | J29: =(I29*(1+J11)) | K29: =(J29*(1+K11)) | L29: =(K29*(1+L11)) | M29: =(L29*(1+M11)) | N29: =(M29*(1+N11)) | O29: =(N29*(1+O11)) | ... Q29: =(P29*(1+Q11))
A30: Cost of revenue | B30: cogs | D30: 2835.2764 | E30: 3044.639 | F30: 3301.787 | G30: 3590.973 | H30: =(H29*(1-H12)) | I30: =(I29*(1-I12)) | J30: =(J29*(1-J12)) | K30: =(K29*(1-K12)) | L30: =(L29*(1-L12)) | M30: =(M29*(1-M12)) | N30: =(N29*(1-N12)) | O30: =(O29*(1-O12)) | ... Q30: =(Q29*(1-Q12))
A31: Gross profit | B31: gross_profit | D31: 1990.1572 | E31: 2109.73 | F31: 2103.24 | G31: 2194.195 | H31: =(H29-H30) | I31: =(I29-I30) | J31: =(J29-J30) | K31: =(K29-K30) | L31: =(L29-L30) | M31: =(M29-M30) | N31: =(N29-N30) | O31: =(O29-O30) | ... Q31: =(Q29-Q30)
A32: SG&A and other opex | B32: opex | D32: 1117.9349 | E32: 1251.718 | F32: 1147.356 | G32: 1074.07 | H32: =(H29*H13) | I32: =(I29*I13) | J32: =(J29*J13) | K32: =(K29*K13) | L32: =(L29*L13) | M32: =(M29*M13) | N32: =(N29*N13) | O32: =(O29*O13) | ... Q32: =(Q29*Q13)
A33: EBIT | B33: ebit | D33: 872.22224 | E33: 858.012 | F33: 1036.743 | G33: 969.816 | H33: =(H31-H32) | I33: =(I31-I32) | J33: =(J31-J32) | K33: =(K31-K32) | L33: =(L31-L32) | M33: =(M31-M32) | N33: =(N31-N32) | O33: =(O31-O32) | ... Q33: =(Q31-Q32)
A34: Depreciation & amortisation | B34: da | D34: 85.10971 | E34: 734.06 | F34: 808.565 | G34: 915.492 | H34: =(H29*H14) | I34: =(I29*I14) | J34: =(J29*J14) | K34: =(K29*K14) | L34: =(L29*L14) | M34: =(M29*M14) | N34: =(N29*N14) | O34: =(O29*O14) | ... Q34: =(Q29*Q14)
A35: EBITDA | B35: ebitda | D35: 957.33195 | E35: 1592.072 | F35: 1845.308 | G35: 1885.308 | H35: =(H33+H34) | I35: =(I33+I34) | J35: =(J33+J34) | K35: =(K33+K34) | L35: =(L33+L34) | M35: =(M33+M34) | N35: =(N33+N34) | O35: =(O33+O34) | ... Q35: =(Q33+Q34)
A36: Interest expense | B36: interest_expense | D36: 422.40458 | E36: 661.367 | F36: 890.597 | G36: 880.181 | H36: =(G56*$C$18) | I36: =(H56*$C$18) | J36: =(I56*$C$18) | K36: =(J56*$C$18) | L36: =(K56*$C$18) | M36: =(L56*$C$18) | N36: =(M56*$C$18) | O36: =(N56*$C$18) | ... Q36: =(P56*$C$18)
A37: Interest income | B37: interest_income | D37: 17.970743 | E37: 33.426 | F37: 53.323 | G37: 34.319 | H37: =(G55*$C$19) | I37: =(H55*$C$19) | J37: =(I55*$C$19) | K37: =(J55*$C$19) | L37: =(K55*$C$19) | M37: =(L55*$C$19) | N37: =(M55*$C$19) | O37: =(N55*$C$19) | ... Q37: =(P55*$C$19)
A38: Other non-operating | B38: other_nonop | D38: -293.57136 | E38: 105.932 | F38: 29.624 | G38: 29.798 | H38: =H21 | I38: =I21 | J38: =J21 | K38: =K21 | L38: =L21 | M38: =M21 | N38: =N21 | O38: =O21 | ... Q38: =Q21
A39: Profit before tax | B39: pbt | D39: 174.21704 | E39: 336.003 | F39: 229.093 | G39: 153.752 | H39: =(((H33-H36)+H37)+H38) | I39: =(((I33-I36)+I37)+I38) | J39: =(((J33-J36)+J37)+J38) | K39: =(((K33-K36)+K37)+K38) | L39: =(((L33-L36)+L37)+L38) | M39: =(((M33-M36)+M37)+M38) | N39: =(((N33-N36)+N37)+N38) | O39: =(((O33-O36)+O37)+O38) | ... Q39: =(((Q33-Q36)+Q37)+Q38)
A40: Tax | B40: tax | D40: 82.836215 | E40: 66.402 | F40: 98.792 | G40: 134.577 | H40: =(MAX(H39,0)*H17) | I40: =(MAX(I39,0)*I17) | J40: =(MAX(J39,0)*J17) | K40: =(MAX(K39,0)*K17) | L40: =(MAX(L39,0)*L17) | M40: =(MAX(M39,0)*M17) | N40: =(MAX(N39,0)*N17) | O40: =(MAX(O39,0)*O17) | ... Q40: =(MAX(Q39,0)*Q17)
A41: Net profit (incl. minorities) | B41: np | D41: 91.380829 | E41: 269.601 | F41: 130.301 | G41: 19.175 | H41: =(H39-H40) | I41: =(I39-I40) | J41: =(J39-J40) | K41: =(K39-K40) | L41: =(L39-L40) | M41: =(M39-M40) | N41: =(N39-N40) | O41: =(O39-O40) | ... Q41: =(Q39-Q40)
A42: Minority interests | B42: minority | D42: -53.628585 | E42: -64.097 | F42: -98.176 | G42: -103.68 | H42: =(H41*H22) | I42: =(I41*I22) | J42: =(J41*J22) | K42: =(K41*K22) | L42: =(L41*L22) | M42: =(M41*M22) | N42: =(N41*N22) | O42: =(O41*O22) | ... Q42: =(Q41*Q22)
A43: Net profit to parent | B43: np_parent | D43: 145.00941 | E43: 269.601 | F43: 130.301 | G43: 19.175 | H43: =(H41-H42) | I43: =(I41-I42) | J43: =(J41-J42) | K43: =(K41-K42) | L43: =(L41-L42) | M43: =(M41-M42) | N43: =(N41-N42) | O43: =(O41-O42) | ... Q43: =(Q41-Q42)
A44: Shares outstanding (m) | B44: shares | D44: 9695.0856 | E44: 9695.0856 | F44: 9695.0856 | G44: 10849.263 | H44: =(G44*(1+H24)) | I44: =(H44*(1+I24)) | J44: =(I44*(1+J24)) | K44: =(J44*(1+K24)) | L44: =(K44*(1+L24)) | M44: =(L44*(1+M24)) | N44: =(M44*(1+N24)) | O44: =(N44*(1+O24)) | ... Q44: =(P44*(1+Q24))
A45: EPS | B45: eps | D45: 14.957002 | E45: 27.808006 | F45: 13.439902 | G45: 1.7674012 | H45: =(IF(H44=0,0,H43/H44)*$C$7) | I45: =(IF(I44=0,0,I43/I44)*$C$7) | J45: =(IF(J44=0,0,J43/J44)*$C$7) | K45: =(IF(K44=0,0,K43/K44)*$C$7) | L45: =(IF(L44=0,0,L43/L44)*$C$7) | M45: =(IF(M44=0,0,M43/M44)*$C$7) | N45: =(IF(N44=0,0,N43/N44)*$C$7) | O45: =(IF(O44=0,0,O43/O44)*$C$7) | ... Q45: =(IF(Q44=0,0,Q43/Q44)*$C$7)
A46: DPS (declared on the year) | B46: dps | D46: 0.446325 | E46: 0.669488 | F46: 0.312428 | G46: 0.35 | H46: =(MAX(H45,0)*H23) | I46: =(MAX(I45,0)*I23) | J46: =(MAX(J45,0)*J23) | K46: =(MAX(K45,0)*K23) | L46: =(MAX(L45,0)*L23) | M46: =(MAX(M45,0)*M23) | N46: =(MAX(N45,0)*N23) | O46: =(MAX(O45,0)*O23) | ... Q46: =(MAX(Q45,0)*Q23)
A47: Dividends paid | B47: dividends_paid | D47: 2.1635813 | E47: 4.327 | F47: 6.491 | G47: 3.029 | H47: =IF($C$7=0,0,(G46*G44)/$C$7) | I47: =IF($C$7=0,0,(H46*H44)/$C$7) | J47: =IF($C$7=0,0,(I46*I44)/$C$7) | K47: =IF($C$7=0,0,(J46*J44)/$C$7) | L47: =IF($C$7=0,0,(K46*K44)/$C$7) | M47: =IF($C$7=0,0,(L46*L44)/$C$7) | N47: =IF($C$7=0,0,(M46*M44)/$C$7) | O47: =IF($C$7=0,0,(N46*N44)/$C$7) | ... Q47: =IF($C$7=0,0,(P46*P44)/$C$7)
A48: Capital expenditure | B48: capex | D48: 1371.7755 | E48: 1681.692 | F48: 1417.619 | G48: 2362.351 | H48: =(H29*H15) | I48: =(I29*I15) | J48: =(J29*J15) | K48: =(K29*K15) | L48: =(L29*L15) | M48: =(M29*M15) | N48: =(N29*N15) | O48: =(O29*O15) | ... Q48: =(Q29*Q15)
A49: Change in working capital | B49: delta_nwc | E49: 881.352 | F49: -210.582 | G49: 666.129 | H49: =(H54-G54) | I49: =(I54-H54) | J49: =(J54-I54) | K49: =(K54-J54) | L49: =(L54-K54) | M49: =(M54-L54) | N49: =(N54-M54) | O49: =(O54-N54) | ... Q49: =(Q54-P54)
A50: Free cash flow to firm | B50: fcff | E50: -1140.5351 | F50: 191.1953 | G50: -1992.0385 | H50: =((((H33*(1-H17))+H34)-H48)-H49) | I50: =((((I33*(1-I17))+I34)-I48)-I49) | J50: =((((J33*(1-J17))+J34)-J48)-J49) | K50: =((((K33*(1-K17))+K34)-K48)-K49) | L50: =((((L33*(1-L17))+L34)-L48)-L49) | M50: =((((M33*(1-M17))+M34)-M48)-M49) | N50: =((((N33*(1-N17))+N34)-N48)-N49) | O50: =((((O33*(1-O17))+O34)-O48)-O49) | ... Q50: =((((Q33*(1-Q17))+Q34)-Q48)-Q49)
A51: Net borrowing | B51: net_borrowing | E51: 1923.2589 | F51: 632.064 | G51: 2854.645 | H51: =H20 | I51: =I20 | J51: =J20 | K51: =K20 | L51: =L20 | M51: =M20 | N51: =N20 | O51: =O20 | ... Q51: =Q20
A52: Dividends to minorities | B52: minority_div | H52: =(MAX(G42,0)*H23) | I52: =(MAX(H42,0)*I23) | J52: =(MAX(I42,0)*J23) | K52: =(MAX(J42,0)*K23) | L52: =(MAX(K42,0)*L23) | M52: =(MAX(L42,0)*M23) | N52: =(MAX(M42,0)*N23) | O52: =(MAX(N42,0)*O23) | ... Q52: =(MAX(P42,0)*Q23)
A53: Free cash flow to equity | B53: fcfe | H53: =(((((H41+H34)-H48)-H49)+H51)-H52) | I53: =(((((I41+I34)-I48)-I49)+I51)-I52) | J53: =(((((J41+J34)-J48)-J49)+J51)-J52) | K53: =(((((K41+K34)-K48)-K49)+K51)-K52) | L53: =(((((L41+L34)-L48)-L49)+L51)-L52) | M53: =(((((M41+M34)-M48)-M49)+M51)-M52) | N53: =(((((N41+N34)-N48)-N49)+N51)-N52) | O53: =(((((O41+O34)-O48)-O49)+O51)-O52) | ... Q53: =(((((Q41+Q34)-Q48)-Q49)+Q51)-Q52)
A54: Operating working capital | B54: nwc | D54: 6498.153 | E54: 7379.505 | F54: 7168.923 | G54: 7835.052 | H54: =(H29*H16) | I54: =(I29*I16) | J54: =(J29*J16) | K54: =(K29*K16) | L54: =(L29*L16) | M54: =(M29*M16) | N54: =(N29*N16) | O54: =(O29*O16) | ... Q54: =(Q29*Q16)
A55: Cash & equivalents | B55: cash | D55: 2066.7409 | E55: 1670.661 | F55: 2231.71 | G55: 2077.414 | H55: =(((((((G55+H41)+H34)-H48)-H49)+H51)-H47)-H52) | I55: =(((((((H55+I41)+I34)-I48)-I49)+I51)-I47)-I52) | J55: =(((((((I55+J41)+J34)-J48)-J49)+J51)-J47)-J52) | K55: =(((((((J55+K41)+K34)-K48)-K49)+K51)-K47)-K52) | L55: =(((((((K55+L41)+L34)-L48)-L49)+L51)-L47)-L52) | M55: =(((((((L55+M41)+M34)-M48)-M49)+M51)-M47)-M52) | N55: =(((((((M55+N41)+N34)-N48)-N49)+N51)-N47)-N52) | O55: =(((((((N55+O41)+O34)-O48)-O49)+O51)-O47)-O52) | ... Q55: =(((((((P55+Q41)+Q34)-Q48)-Q49)+Q51)-Q47)-Q52)
A56: Total debt | B56: debt | D56: 21159.536 | E56: 23082.795 | F56: 23714.859 | G56: 26569.504 | H56: =(G56+H51) | I56: =(H56+I51) | J56: =(I56+J51) | K56: =(J56+K51) | L56: =(K56+L51) | M56: =(L56+M51) | N56: =(M56+N51) | O56: =(N56+O51) | ... Q56: =(P56+Q51)
A57: Fixed assets (net) | B57: ppe | D57: 9716.5765 | E57: 10048.888 | F57: 10197.513 | G57: 11079.765 | H57: =((G57+H48)-H34) | I57: =((H57+I48)-I34) | J57: =((I57+J48)-J34) | K57: =((J57+K48)-K34) | L57: =((K57+L48)-L34) | M57: =((L57+M48)-M34) | N57: =((M57+N48)-N34) | O57: =((N57+O48)-O34) | ... Q57: =((P57+Q48)-Q34)
A58: Parent shareholders' equity | B58: equity | D58: 3901.7119 | E58: 4342.553 | F58: 4521.338 | G58: 5001.59 | H58: =((G58+H43)-H47) | I58: =((H58+I43)-I47) | J58: =((I58+J43)-J47) | K58: =((J58+K43)-K47) | L58: =((K58+L43)-L47) | M58: =((L58+M43)-M47) | N58: =((M58+N43)-N47) | O58: =((N58+O43)-O47) | ... Q58: =((P58+Q43)-Q47)
A59: Minority interest (balance sheet) | B59: minority_bs | D59: 521.31956 | E59: 395.235 | F59: 175.594 | G59: 91.853 | H59: =((G59+H42)-H52) | I59: =((H59+I42)-I52) | J59: =((I59+J42)-J52) | K59: =((J59+K42)-K52) | L59: =((K59+L42)-L52) | M59: =((L59+M42)-M52) | N59: =((M59+N42)-N52) | O59: =((N59+O42)-O52) | ... Q59: =((P59+Q42)-Q52)
A60: Other assets less other liabilities | B60: other_net | D60: 7301.0973 | E60: 8721.529 | F60: 8813.645 | G60: 10670.716 | H60: =G60 | I60: =H60 | J60: =I60 | K60: =J60 | L60: =K60 | M60: =L60 | N60: =M60 | O60: =N60 | ... Q60: =P60
A61: Balance check (should be zero) | B61: bs_check | H61: =((((((H55+H54)+H57)+H60)-H56)-H58)-H59) | I61: =((((((I55+I54)+I57)+I60)-I56)-I58)-I59) | J61: =((((((J55+J54)+J57)+J60)-J56)-J58)-J59) | K61: =((((((K55+K54)+K57)+K60)-K56)-K58)-K59) | L61: =((((((L55+L54)+L57)+L60)-L56)-L58)-L59) | M61: =((((((M55+M54)+M57)+M60)-M56)-M58)-M59) | N61: =((((((N55+N54)+N57)+N60)-N56)-N58)-N59) | O61: =((((((O55+O54)+O57)+O60)-O56)-O58)-O59) | ... Q61: =((((((Q55+Q54)+Q57)+Q60)-Q56)-Q58)-Q59)
A62: Net debt (cash) | B62: net_debt | D62: 19092.795 | E62: 21412.134 | F62: 21483.149 | G62: 24492.09 | H62: =(H56-H55) | I62: =(I56-I55) | J62: =(J56-J55) | K62: =(K56-K55) | L62: =(L56-L55) | M62: =(M56-M55) | N62: =(N56-N55) | O62: =(O56-O55) | ... Q62: =(Q56-Q55)
A63: Book value per share | B63: bvps | D63: 402.44223 | E63: 447.9128 | F63: 466.35359 | G63: 461.00737 | H63: =(IF(H44=0,0,H58/H44)*$C$7) | I63: =(IF(I44=0,0,I58/I44)*$C$7) | J63: =(IF(J44=0,0,J58/J44)*$C$7) | K63: =(IF(K44=0,0,K58/K44)*$C$7) | L63: =(IF(L44=0,0,L58/L44)*$C$7) | M63: =(IF(M44=0,0,M58/M44)*$C$7) | N63: =(IF(N44=0,0,N58/N44)*$C$7) | O63: =(IF(O44=0,0,O58/O44)*$C$7) | ... Q63: =(IF(Q44=0,0,Q58/Q44)*$C$7)
A64: Revenue growth | B64: revenue_growth | E64: 0.068167024 | F64: 0.048630201 | G64: 0.070331009 | H64: =(IF(G29=0,0,H29/G29)-1) | I64: =(IF(H29=0,0,I29/H29)-1) | J64: =(IF(I29=0,0,J29/I29)-1) | K64: =(IF(J29=0,0,K29/J29)-1) | L64: =(IF(K29=0,0,L29/K29)-1) | M64: =(IF(L29=0,0,M29/L29)-1) | N64: =(IF(M29=0,0,N29/M29)-1) | O64: =(IF(N29=0,0,O29/N29)-1) | ... Q64: =(IF(P29=0,0,Q29/P29)-1)
A65: Gross margin | B65: gross_margin | D65: 0.41243075 | E65: 0.40930907 | F65: 0.38912664 | G65: 0.37927939 | H65: =IF(H29=0,0,H31/H29) | I65: =IF(I29=0,0,I31/I29) | J65: =IF(J29=0,0,J31/J29) | K65: =IF(K29=0,0,K31/K29) | L65: =IF(L29=0,0,L31/L29) | M65: =IF(M29=0,0,M31/M29) | N65: =IF(N29=0,0,N31/N29) | O65: =IF(O29=0,0,O31/O29) | ... Q65: =IF(Q29=0,0,Q31/Q29)
A66: EBITDA margin | B66: ebitda_margin | D66: 0.19839294 | E66: 0.30887816 | F66: 0.34140588 | G66: 0.32588647 | H66: =IF(H29=0,0,H35/H29) | I66: =IF(I29=0,0,I35/I29) | J66: =IF(J29=0,0,J35/J29) | K66: =IF(K29=0,0,K35/K29) | L66: =IF(L29=0,0,L35/L29) | M66: =IF(M29=0,0,M35/M29) | N66: =IF(N29=0,0,N35/N29) | O66: =IF(O29=0,0,O35/O29) | ... Q66: =IF(Q29=0,0,Q35/Q29)
A67: EBIT margin | B67: ebit_margin | D67: 0.18075521 | E67: 0.16646305 | F67: 0.19181088 | G67: 0.16763835 | H67: =IF(H29=0,0,H33/H29) | I67: =IF(I29=0,0,I33/I29) | J67: =IF(J29=0,0,J33/J29) | K67: =IF(K29=0,0,K33/K29) | L67: =IF(L29=0,0,L33/L29) | M67: =IF(M29=0,0,M33/M29) | N67: =IF(N29=0,0,N33/N29) | O67: =IF(O29=0,0,O33/O29) | ... Q67: =IF(Q29=0,0,Q33/Q29)
A68: Net margin | B68: np_margin | D68: 0.030051064 | E68: 0.052305336 | F68: 0.024107373 | G68: 0.0033145105 | H68: =IF(H29=0,0,H43/H29) | I68: =IF(I29=0,0,I43/I29) | J68: =IF(J29=0,0,J43/J29) | K68: =IF(K29=0,0,K43/K29) | L68: =IF(L29=0,0,L43/L29) | M68: =IF(M29=0,0,M43/M29) | N68: =IF(N29=0,0,N43/N29) | O68: =IF(O29=0,0,O43/O29) | ... Q68: =IF(Q29=0,0,Q43/Q29)
A69: EPS growth | B69: eps_growth | E69: 0.85919654 | F69: -0.51668948 | G69: -0.86849597 | H69: =(IF(G45=0,0,H45/G45)-1) | I69: =(IF(H45=0,0,I45/H45)-1) | J69: =(IF(I45=0,0,J45/I45)-1) | K69: =(IF(J45=0,0,K45/J45)-1) | L69: =(IF(K45=0,0,L45/K45)-1) | M69: =(IF(L45=0,0,M45/L45)-1) | N69: =(IF(M45=0,0,N45/M45)-1) | O69: =(IF(N45=0,0,O45/N45)-1) | ... Q69: =(IF(P45=0,0,Q45/P45)-1)
A70: ROE | B70: roe | E70: 0.065403284 | F70: 0.029400407 | G70: 0.0040271228 | H70: =IF(IF(2=0,0,(H58+G58)/2)=0,0,H43/IF(2=0,0,(H58+G58)/2)) | I70: =IF(IF(2=0,0,(I58+H58)/2)=0,0,I43/IF(2=0,0,(I58+H58)/2)) | J70: =IF(IF(2=0,0,(J58+I58)/2)=0,0,J43/IF(2=0,0,(J58+I58)/2)) | K70: =IF(IF(2=0,0,(K58+J58)/2)=0,0,K43/IF(2=0,0,(K58+J58)/2)) | L70: =IF(IF(2=0,0,(L58+K58)/2)=0,0,L43/IF(2=0,0,(L58+K58)/2)) | M70: =IF(IF(2=0,0,(M58+L58)/2)=0,0,M43/IF(2=0,0,(M58+L58)/2)) | N70: =IF(IF(2=0,0,(N58+M58)/2)=0,0,N43/IF(2=0,0,(N58+M58)/2)) | O70: =IF(IF(2=0,0,(O58+N58)/2)=0,0,O43/IF(2=0,0,(O58+N58)/2)) | ... Q70: =IF(IF(2=0,0,(Q58+P58)/2)=0,0,Q43/IF(2=0,0,(Q58+P58)/2))
A71: Net debt / EBITDA | B71: net_debt_ebitda | D71: 19.943756 | E71: 13.449225 | F71: 11.64204 | G71: 12.991029 | H71: =IF(H35=0,0,H62/H35) | I71: =IF(I35=0,0,I62/I35) | J71: =IF(J35=0,0,J62/J35) | K71: =IF(K35=0,0,K62/K35) | L71: =IF(L35=0,0,L62/L35) | M71: =IF(M35=0,0,M62/M35) | N71: =IF(N35=0,0,N62/N35) | O71: =IF(O35=0,0,O62/O35) | ... Q71: =IF(Q35=0,0,Q62/Q35)
A72: Payout ratio | B72: payout_ratio | D72: 0.029840539 | E72: 0.024075369 | F72: 0.023246301 | G72: 0.19803087 | H72: =IF(H45=0,0,H46/H45) | I72: =IF(I45=0,0,I46/I45) | J72: =IF(J45=0,0,J46/J45) | K72: =IF(K45=0,0,K46/K45) | L72: =IF(L45=0,0,L46/L45) | M72: =IF(M45=0,0,M46/M45) | N72: =IF(N45=0,0,N46/N45) | O72: =IF(O45=0,0,O46/O45) | ... Q72: =IF(Q45=0,0,Q46/Q45)
A73: Capex / revenue | B73: capex_revenue | D73: 0.28428025 | E73: 0.32626535 | F73: 0.26227788 | G73: 0.40834614 | H73: =IF(H29=0,0,H48/H29) | I73: =IF(I29=0,0,I48/I29) | J73: =IF(J29=0,0,J48/J29) | K73: =IF(K29=0,0,K48/K29) | L73: =IF(L29=0,0,L48/L29) | M73: =IF(M29=0,0,M48/M29) | N73: =IF(N29=0,0,N48/N29) | O73: =IF(O29=0,0,O48/O29) | ... Q73: =IF(Q29=0,0,Q48/Q29)
A75: VALUATION
A76: Last price (IDR) | C76: 150
A77: Shares outstanding (m) | C77: 10849.263
A78: IDR per USD (spot) | C78: 18183
A79: Debt at balance-sheet date | C79: 26948.708
A80: Cash at balance-sheet date | C80: 1551.543
A81: Minority interest (book) | C81: 43.254
A82: Associates & investments (book) | C82: 628.606
A83: Post-balance-sheet & other items (sourced, probability-weighted) | C83: 0
A84: Parent equity at balance-sheet date | C84: 5501.129
A85: Per-share factor | C85: 1000
A86: Risk-free rate | C86: =Drivers!$C$7
A87: Less: default spread (IDR only) | C87: =Drivers!$C$9
A88: Mature ERP + Indonesia CRP | C88: =Drivers!$C$10+Drivers!$C$11
A89: Tax rate | C89: =Drivers!$C$13
A90: Unlevered beta (industry default (config)) | C90: 0.9
A91: Debt / equity (market) | C91: 2
A92: Levered beta | C92: =$C$90*(1+(1-$C$89)*$C$91)
A93: Explicit company premium | C93: 0
A94: Cost of equity | C94: =$C$86-$C$87+$C$92*$C$88+$C$93
A95: Pre-tax cost of debt | C95: =$C$86+Drivers!$C$12
A96: WACC | C96: =1/(1+$C$91)*$C$94+$C$91/(1+$C$91)*$C$95*(1-$C$89)
A97: Terminal growth (capped) | C97: 0.04
A99: Sum of the parts
A100: Value per share (IDR) — Sum of the parts (engine value) | C100: 159.72765
A102: P/E
A103: Target multiple (own five-year average) | C103: 15.122018
A104: Metric (LTM, or next-12m DPS for yield) | C104: 19.175
A105: Value per share (IDR) — P/E | C105: =MAX(0,$C$103*$C$104/$C$77*$C$85*1)
A107: TARGET
A108: Weight: Sum of the parts | C108: 0.75
...

Sheet TOBA
A1: PT TBS Energi Utama Tbk (TOBA.JK) — Conglomerates & multi-sector holdings
A2: Units: USD m; per-share in USD unless marked IDR. Model asof 2026-10-29 · data 2026-10-26
A4: Line | C4: Scalar | D4: FY2022A | E4: FY2023A | F4: FY2024A | G4: FY2025A | H4: FY2026E | I4: FY2027E | J4: FY2028E | K4: FY2029E | L4: FY2030E | M4: FY2031E | N4: FY2032E | O4: FY2033E | P4: FY2034E | Q4: FY2035E
A6: PARAMETERS
A7: ps_factor | C7: 1
A8: vp_factor | C8: 1
A10: INPUTS (company assumptions)
