Workbook

Sheet README
A1: Six South — Plantations (palm oil) industry model
A2: Generated 2026-10-30T01:56:00+07:00 by the coverage engine. The engine (scripts/cov_engine.py) is the source of truth; this workbook is a live rendering of it.
A3: Colour key: blue = input or hard-coded history; black = formula; green = link to another sheet.
A4: Drivers: every deck variable these models read. Change one and every ticker tab and the Comps sheet recalculate (forecasts, cash flows, DCF value, base-case value, target, rating).
A5: Scenario (bear/bull) and sensitivity tables need full model re-runs and are engine values.
A6: Paper fund — research for education and process transparency, not investment advice.
A8: Tickers:
A9: JARR.JK — PT Jhonlin Agro Raya Tbk
A10: PGUN.JK — PT Pradiksi Gunatama Tbk

Sheet Drivers
A1: Driver decks (state/drivers) — edit a blue cell to flow it through every ticker tab
A3: Variable | B3: Key | C3: Unit / status | D3: FY2022A | E3: FY2023A | F3: FY2024A | G3: FY2025A | H3: FY2026E | I3: FY2027E | J3: FY2028E | K3: FY2029E | L3: FY2030E | M3: FY2031E | N3: FY2032E | O3: FY2033E | P3: FY2034E | Q3: FY2035E
A4: Crude palm oil (benchmark) | B4: d.agri.cpo | C4: USD/t · reviewed | E4: 886 | F4: 963 | G4: 1007 | H4: 1135 | I4: 1240 | J4: 1210 | K4: 1180 | L4: 1178.75 | M4: 1208.2188 | N4: 1238.4242 | O4: 1269.3848 | P4: 1301.1194 | Q4: 1333.6474
A5: IDR per USD | B5: m.usd_idr | C5: IDR/USD · reviewed | D5: 14843.177 | E5: 15228.8 | F5: 15846.238 | G5: 16448.093 | H5: 17570 | I5: 18350 | J5: 18600 | K5: 18850 | L5: 19093.137 | M5: 19186.731 | N5: 19280.784 | O5: 19375.297 | P5: 19470.274 | Q5: 19565.717
A7: Cost-of-capital scalars (macro deck)
A8: 10-year Indonesian government bond yield (IDR) | B8: m.rf_idr | C8: 0.0745 | D8: investor.id — "Yield SUN 7,45%, Saatnya Borong atau Tunggu Lebih Tinggi?" (25 Okt 2026 20:58 WIB; deck source S3); corroborated by kalderanews S1 (10Y SUN 7.41%
A9: 10-year US Treasury yield | B9: m.rf_usd | C9: 0.05009 | D9: Yahoo Finance ^TNX (US 10-year Treasury yield)
A10: Indonesia sovereign default spread (Damodaran) | B10: m.default_spread_id | C10: 0.0162 | D10: Damodaran country risk premiums (https://pages.stern.nyu.edu/~adamodar/New_Home_Page/datafile/ctryprem.html), page dated January 5, 2026, read 2026-10-29
A11: Mature-market equity risk premium (Damodaran) | B11: m.erp_mature | C11: 0.0423 | D11: Damodaran country risk premiums (https://pages.stern.nyu.edu/~adamodar/New_Home_Page/datafile/ctryprem.html), page dated January 5, 2026, read 2026-10-29
A12: Indonesia country risk premium (Damodaran) | B12: m.crp_id | C12: 0.0246 | D12: Damodaran country risk premiums (https://pages.stern.nyu.edu/~adamodar/New_Home_Page/datafile/ctryprem.html), page dated January 5, 2026, read 2026-10-29
A13: House pre-tax corporate debt spread over the risk-free | B13: m.debt_spread_corp | C13: 0.02 | D13: SEED house assumption pending the macro desk: 200 bp over the risk-free rate for an average IDX corporate borrower
A14: Indonesia statutory corporate income tax rate | B14: m.tax_rate_id | C14: 0.22 | D14: Law 7/2021 on Harmonisation of Tax Regulations (UU HPP): 22% corporate income tax from fiscal 2022

Sheet Comps
A1: Ticker | B1: Company | C1: Rating | D1: Target (IDR) | E1: Price (IDR) | F1: Exp. 12m TR | G1: Value today | H1: P/E FY+0 | I1: EV/EBITDA FY+0 | J1: Div. yield FY+0
A2: JARR.JK | B2: PT Jhonlin Agro Raya Tbk | C2: ='JARR'!$C$173 | D2: ='JARR'!$C$171 | E2: ='JARR'!$C$102 | F2: ='JARR'!$C$172 | G2: ='JARR'!$C$152 | H2: 54.645711 | I2: 29.428938 | J2: 0.00366
A3: PGUN.JK | B3: PT Pradiksi Gunatama Tbk | C3: ='PGUN'!$C$173 | D3: ='PGUN'!$C$171 | E3: ='PGUN'!$C$102 | F3: ='PGUN'!$C$172 | G3: ='PGUN'!$C$152 | H3: 256.25777 | I3: 123.93778 | J3: 0.000976

Sheet JARR
A1: PT Jhonlin Agro Raya Tbk (JARR.JK) — Plantations (palm oil)
A2: Units: IDR bn; per-share in IDR unless marked IDR. Model asof 2026-10-29 · data 2026-10-27
A4: Line | C4: Scalar | D4: FY2022A | E4: FY2023A | F4: FY2024A | G4: FY2025A | H4: FY2026E | I4: FY2027E | J4: FY2028E | K4: FY2029E | L4: FY2030E | M4: FY2031E | N4: FY2032E | O4: FY2033E | P4: FY2034E | Q4: FY2035E
A6: PARAMETERS
A7: horizon | C7: 10
A8: ps_factor | C8: 1000
A9: reserves | C9: 0
A10: unit_factor | C10: 0.001
A11: vp_factor | C11: 1
A13: INPUTS (company assumptions)
A14: Sales volume plan | B14: a.volume | H14: 220.26923 | I14: 220.26923 | J14: 220.26923 | K14: 220.26923 | L14: 220.26923 | M14: 220.26923 | N14: 220.26923 | O14: 220.26923 | P14: 220.26923 | Q14: 220.26923
A15: Realised price / benchmark | B15: a.realisation | H15: 1.1 | I15: 1.1 | J15: 1.1 | K15: 1.1 | L15: 1.1 | M15: 1.1 | N15: 1.1 | O15: 1.1 | P15: 1.1 | Q15: 1.1
A16: Share of volume under a price cap (e.g. DMO) | B16: a.capped_share | H16: 0 | I16: 0 | J16: 0 | K16: 0 | L16: 0 | M16: 0 | N16: 0 | O16: 0 | P16: 0 | Q16: 0
A17: Strip ratio (bcm per tonne) or cost-intensity factor | B17: a.strip_ratio | H17: 1 | I17: 1 | J17: 1 | K17: 1 | L17: 1 | M17: 1 | N17: 1 | O17: 1 | P17: 1 | Q17: 1
A18: Mining cost per bcm (or per unit when intensity is 1) | B18: a.cost_per_bcm | H18: 15269332 | I18: 15269332 | J18: 15269332 | K18: 15269332 | L18: 15269332 | M18: 15651065 | N18: 16042342 | O18: 16443400 | P18: 16854485 | Q18: 17275848
A19: Fuel share of mining cost | B19: a.fuel_share | C19: 0.75
A20: Other cash cost per unit (haul, barge, process) | B20: a.other_cost_unit | H20: 0 | I20: 95433.3 | J20: 193252.5 | K20: 293517.1 | L20: 396288.4 | M20: 501628.9 | N20: 609603 | O20: 720276.4 | P20: 833716.6 | Q20: 949992.8
A21: Royalty rate (flat regimes) | B21: a.royalty_rate | H21: 0 | I21: 0 | J21: 0 | K21: 0 | L21: 0 | M21: 0 | N21: 0 | O21: 0 | P21: 0 | Q21: 0
A22: Other revenue | B22: a.other_revenue | H22: 0 | I22: 0 | J22: 0 | K22: 0 | L22: 0 | M22: 0 | N22: 0 | O22: 0 | P22: 0 | Q22: 0
A23: Gross margin on other revenue | B23: a.other_margin | C23: 0.1
A24: D&A per unit (reporting currency) | B24: a.da_unit | H24: 750132 | I24: 750132 | J24: 750132 | K24: 750132 | L24: 750132 | M24: 768885.3 | N24: 788107.43 | O24: 807810.12 | P24: 828005.37 | Q24: 848705.51
A25: Sustaining capex per unit (reporting currency) | B25: a.capex_unit | H25: 664873 | I25: 664873 | J25: 664873 | K25: 664873 | L25: 664873 | M25: 681494.82 | N25: 698532.2 | O25: 715995.5 | P25: 733895.39 | Q25: 752242.77
A26: Other capex (expansion projects) | B26: a.capex_other | H26: 0 | I26: 0 | J26: 0 | K26: 0 | L26: 0 | M26: 0 | N26: 0 | O26: 0 | P26: 0 | Q26: 0
A27: Operating working capital / revenue | B27: a.nwc_pct | H27: 0.2712 | I27: 0.2712 | J27: 0.2712 | K27: 0.2712 | L27: 0.2712 | M27: 0.2712 | N27: 0.2712 | O27: 0.2712 | P27: 0.2712 | Q27: 0.2712
A28: Effective tax rate | B28: a.tax_rate | H28: 0.2186 | I28: 0.2186 | J28: 0.2186 | K28: 0.2186 | L28: 0.2186 | M28: 0.2186 | N28: 0.2186 | O28: 0.2186 | P28: 0.2186 | Q28: 0.2186
A29: Cost of debt (on opening debt) | B29: a.cost_of_debt | C29: 0.0667
A30: Yield on opening cash | B30: a.cash_yield | C30: 0.01
A31: Net new borrowing | B31: a.net_borrowing | H31: 0 | I31: 0 | J31: 0 | K31: 0 | L31: 0 | M31: 0 | N31: 0 | O31: 0 | P31: 0 | Q31: 0
A32: Other non-operating items | B32: a.other_nonop | H32: 0 | I32: 0 | J32: 0 | K32: 0 | L32: 0 | M32: 0 | N32: 0 | O32: 0 | P32: 0 | Q32: 0
A33: Minorities' share of net profit | B33: a.minority_pct | H33: 0 | I33: 0 | J33: 0 | K33: 0 | L33: 0 | M33: 0 | N33: 0 | O33: 0 | P33: 0 | Q33: 0
A34: Dividend payout | B34: a.payout | H34: 0.2 | I34: 0.2 | J34: 0.2 | K34: 0.2 | L34: 0.2 | M34: 0.2 | N34: 0.2 | O34: 0.2 | P34: 0.2 | Q34: 0.2
A35: Change in share count | B35: a.share_change | H35: 0 | I35: 0 | J35: 0 | K35: 0 | L35: 0 | M35: 0 | N35: 0 | O35: 0 | P35: 0 | Q35: 0
A36: Terminal growth (DCF) | B36: a.terminal_growth | C36: 0.04
A37: SG&A / revenue | B37: a.opex_pct | H37: 0.069 | I37: 0.069 | J37: 0.069 | K37: 0.069 | L37: 0.069 | M37: 0.069 | N37: 0.069 | O37: 0.069 | P37: 0.069 | Q37: 0.069
A39: MODEL
A40: Reserves remaining (close) | B40: reserves | H40: =MAX((G40-H41),0) | I40: =MAX((H40-I41),0) | J40: =MAX((I40-J41),0) | K40: =MAX((J40-K41),0) | L40: =MAX((K40-L41),0) | M40: =MAX((L40-M41),0) | N40: =MAX((M40-N41),0) | O40: =MAX((N40-O41),0) | ... Q40: =MAX((P40-Q41),0)
A41: Sales volume | B41: volume | G41: 220.26923 | H41: =IF(($C$9>0),MIN(H14,MAX(G40,0)),H14) | I41: =IF(($C$9>0),MIN(I14,MAX(H40,0)),I14) | J41: =IF(($C$9>0),MIN(J14,MAX(I40,0)),J14) | K41: =IF(($C$9>0),MIN(K14,MAX(J40,0)),K14) | L41: =IF(($C$9>0),MIN(L14,MAX(K40,0)),L14) | M41: =IF(($C$9>0),MIN(M14,MAX(L40,0)),M14) | N41: =IF(($C$9>0),MIN(N14,MAX(M40,0)),N14) | O41: =IF(($C$9>0),MIN(O14,MAX(N40,0)),O14) | ... Q41: =IF(($C$9>0),MIN(Q14,MAX(P40,0)),Q14)
A42: Benchmark price | B42: benchmark | H42: =Drivers!$H$4 | I42: =Drivers!$I$4 | J42: =Drivers!$J$4 | K42: =Drivers!$K$4 | L42: =Drivers!$L$4 | M42: =Drivers!$M$4 | N42: =Drivers!$N$4 | O42: =Drivers!$O$4 | P42: =Drivers!$P$4 | Q42: =Drivers!$Q$4
A43: Average selling price | B43: asp | H43: =(H15*H42) | I43: =(I15*I42) | J43: =(J15*J42) | K43: =(K15*K42) | L43: =(L15*L42) | M43: =(M15*M42) | N43: =(N15*N42) | O43: =(O15*O42) | ... Q43: =(Q15*Q42)
A44: Realisation vs benchmark | B44: realisation_line | H44: =IF(H42=0,0,H43/H42) | I44: =IF(I42=0,0,I43/I42) | J44: =IF(J42=0,0,J43/J42) | K44: =IF(K42=0,0,K43/K42) | L44: =IF(L42=0,0,L43/L42) | M44: =IF(M42=0,0,M43/M42) | N44: =IF(N42=0,0,N43/N42) | O44: =IF(O42=0,0,O43/O42) | ... Q44: =IF(Q42=0,0,Q43/Q42)
A45: Cash cost per unit (ex-royalty) | B45: unit_cost | H45: =(((H17*H18)*(1+($C$19*(IF(Drivers!$G$4=0,0,Drivers!$H$4/Drivers!$G$4)-1))))+H20) | I45: =(((I17*I18)*(1+($C$19*(IF(Drivers!$G$4=0,0,Drivers!$I$4/Drivers!$G$4)-1))))+I20) | J45: =(((J17*J18)*(1+($C$19*(IF(Drivers!$G$4=0,0,Drivers!$J$4/Drivers!$G$4)-1))))+J20) | K45: =(((K17*K18)*(1+($C$19*(IF(Drivers!$G$4=0,0,Drivers!$K$4/Drivers!$G$4)-1))))+K20) | L45: =(((L17*L18)*(1+($C$19*(IF(Drivers!$G$4=0,0,Drivers!$L$4/Drivers!$G$4)-1))))+L20) | M45: =(((M17*M18)*(1+($C$19*(IF(Drivers!$G$4=0,0,Drivers!$M$4/Drivers!$G$4)-1))))+M20) | N45: =(((N17*N18)*(1+($C$19*(IF(Drivers!$G$4=0,0,Drivers!$N$4/Drivers!$G$4)-1))))+N20) | O45: =(((O17*O18)*(1+($C$19*(IF(Drivers!$G$4=0,0,Drivers!$O$4/Drivers!$G$4)-1))))+O20) | P45: =(((P17*P18)*(1+($C$19*(IF(Drivers!$G$4=0,0,Drivers!$P$4/Drivers!$G$4)-1))))+P20) | Q45: =(((Q17*Q18)*(1+($C$19*(IF(Drivers!$G$4=0,0,Drivers!$Q$4/Drivers!$G$4)-1))))+Q20)
A46: Strip ratio | B46: strip_ratio_line | H46: =H17 | I46: =I17 | J46: =J17 | K46: =K17 | L46: =L17 | M46: =M17 | N46: =N17 | O46: =O17 | ... Q46: =Q17
A47: Royalty rate | B47: royalty_rate | H47: =H21 | I47: =I21 | J47: =J21 | K47: =K21 | L47: =L21 | M47: =M21 | N47: =N21 | O47: =O21 | ... Q47: =Q21
A48: EBITDA per unit (price currency) | B48: ebitda_per_unit | G48: 163.35876 | H48: =IF(IF(1000=0,0,((H41*$C$10)*Drivers!$H$5)/1000)=0,0,H61/IF(1000=0,0,((H41*$C$10)*Drivers!$H$5)/1000)) | I48: =IF(IF(1000=0,0,((I41*$C$10)*Drivers!$I$5)/1000)=0,0,I61/IF(1000=0,0,((I41*$C$10)*Drivers!$I$5)/1000)) | J48: =IF(IF(1000=0,0,((J41*$C$10)*Drivers!$J$5)/1000)=0,0,J61/IF(1000=0,0,((J41*$C$10)*Drivers!$J$5)/1000)) | K48: =IF(IF(1000=0,0,((K41*$C$10)*Drivers!$K$5)/1000)=0,0,K61/IF(1000=0,0,((K41*$C$10)*Drivers!$K$5)/1000)) | L48: =IF(IF(1000=0,0,((L41*$C$10)*Drivers!$L$5)/1000)=0,0,L61/IF(1000=0,0,((L41*$C$10)*Drivers!$L$5)/1000)) | M48: =IF(IF(1000=0,0,((M41*$C$10)*Drivers!$M$5)/1000)=0,0,M61/IF(1000=0,0,((M41*$C$10)*Drivers!$M$5)/1000)) | N48: =IF(IF(1000=0,0,((N41*$C$10)*Drivers!$N$5)/1000)=0,0,N61/IF(1000=0,0,((N41*$C$10)*Drivers!$N$5)/1000)) | O48: =IF(IF(1000=0,0,((O41*$C$10)*Drivers!$O$5)/1000)=0,0,O61/IF(1000=0,0,((O41*$C$10)*Drivers!$O$5)/1000)) | P48: =IF(IF(1000=0,0,((P41*$C$10)*Drivers!$P$5)/1000)=0,0,P61/IF(1000=0,0,((P41*$C$10)*Drivers!$P$5)/1000)) | Q48: =IF(IF(1000=0,0,((Q41*$C$10)*Drivers!$Q$5)/1000)=0,0,Q61/IF(1000=0,0,((Q41*$C$10)*Drivers!$Q$5)/1000))
A49: Cash cost + royalty per unit (price currency) | B49: cash_cost_money_per_unit | H49: =IF(IF(1000=0,0,((H41*$C$10)*Drivers!$H$5)/1000)=0,0,(H53+H52)/IF(1000=0,0,((H41*$C$10)*Drivers!$H$5)/1000)) | I49: =IF(IF(1000=0,0,((I41*$C$10)*Drivers!$I$5)/1000)=0,0,(I53+I52)/IF(1000=0,0,((I41*$C$10)*Drivers!$I$5)/1000)) | J49: =IF(IF(1000=0,0,((J41*$C$10)*Drivers!$J$5)/1000)=0,0,(J53+J52)/IF(1000=0,0,((J41*$C$10)*Drivers!$J$5)/1000)) | K49: =IF(IF(1000=0,0,((K41*$C$10)*Drivers!$K$5)/1000)=0,0,(K53+K52)/IF(1000=0,0,((K41*$C$10)*Drivers!$K$5)/1000)) | L49: =IF(IF(1000=0,0,((L41*$C$10)*Drivers!$L$5)/1000)=0,0,(L53+L52)/IF(1000=0,0,((L41*$C$10)*Drivers!$L$5)/1000)) | M49: =IF(IF(1000=0,0,((M41*$C$10)*Drivers!$M$5)/1000)=0,0,(M53+M52)/IF(1000=0,0,((M41*$C$10)*Drivers!$M$5)/1000)) | N49: =IF(IF(1000=0,0,((N41*$C$10)*Drivers!$N$5)/1000)=0,0,(N53+N52)/IF(1000=0,0,((N41*$C$10)*Drivers!$N$5)/1000)) | O49: =IF(IF(1000=0,0,((O41*$C$10)*Drivers!$O$5)/1000)=0,0,(O53+O52)/IF(1000=0,0,((O41*$C$10)*Drivers!$O$5)/1000)) | P49: =IF(IF(1000=0,0,((P41*$C$10)*Drivers!$P$5)/1000)=0,0,(P53+P52)/IF(1000=0,0,((P41*$C$10)*Drivers!$P$5)/1000)) | Q49: =IF(IF(1000=0,0,((Q41*$C$10)*Drivers!$Q$5)/1000)=0,0,(Q53+Q52)/IF(1000=0,0,((Q41*$C$10)*Drivers!$Q$5)/1000))
A50: Main product revenue | B50: revenue_main | H50: =IF(1000=0,0,(((H41*H43)*$C$10)*Drivers!$H$5)/1000) | I50: =IF(1000=0,0,(((I41*I43)*$C$10)*Drivers!$I$5)/1000) | J50: =IF(1000=0,0,(((J41*J43)*$C$10)*Drivers!$J$5)/1000) | K50: =IF(1000=0,0,(((K41*K43)*$C$10)*Drivers!$K$5)/1000) | L50: =IF(1000=0,0,(((L41*L43)*$C$10)*Drivers!$L$5)/1000) | M50: =IF(1000=0,0,(((M41*M43)*$C$10)*Drivers!$M$5)/1000) | N50: =IF(1000=0,0,(((N41*N43)*$C$10)*Drivers!$N$5)/1000) | O50: =IF(1000=0,0,(((O41*O43)*$C$10)*Drivers!$O$5)/1000) | P50: =IF(1000=0,0,(((P41*P43)*$C$10)*Drivers!$P$5)/1000) | Q50: =IF(1000=0,0,(((Q41*Q43)*$C$10)*Drivers!$Q$5)/1000)
A51: Other revenue | B51: other_revenue | H51: =H22 | I51: =I22 | J51: =J22 | K51: =K22 | L51: =L22 | M51: =M22 | N51: =N22 | O51: =O22 | ... Q51: =Q22
A52: Royalty | B52: royalty | H52: =(H50*H47) | I52: =(I50*I47) | J52: =(J50*J47) | K52: =(K50*K47) | L52: =(L50*L47) | M52: =(M50*M47) | N52: =(N50*N47) | O52: =(O50*O47) | ... Q52: =(Q50*Q47)
A53: Cash costs | B53: cash_cost | H53: =IF(1000=0,0,((H41*H45)*$C$10)/1000) | I53: =IF(1000=0,0,((I41*I45)*$C$10)/1000) | J53: =IF(1000=0,0,((J41*J45)*$C$10)/1000) | K53: =IF(1000=0,0,((K41*K45)*$C$10)/1000) | L53: =IF(1000=0,0,((L41*L45)*$C$10)/1000) | M53: =IF(1000=0,0,((M41*M45)*$C$10)/1000) | N53: =IF(1000=0,0,((N41*N45)*$C$10)/1000) | O53: =IF(1000=0,0,((O41*O45)*$C$10)/1000) | ... Q53: =IF(1000=0,0,((Q41*Q45)*$C$10)/1000)
A54: Cost of other revenue | B54: other_cogs | H54: =(H51*(1-$C$23)) | I54: =(I51*(1-$C$23)) | J54: =(J51*(1-$C$23)) | K54: =(K51*(1-$C$23)) | L54: =(L51*(1-$C$23)) | M54: =(M51*(1-$C$23)) | N54: =(N51*(1-$C$23)) | O54: =(O51*(1-$C$23)) | ... Q54: =(Q51*(1-$C$23))
A55: Revenue | B55: revenue | D55: 4642.341 | E55: 4442.2796 | F55: 3864.889 | G55: 4278.8848 | H55: =(H50+H51) | I55: =(I50+I51) | J55: =(J50+J51) | K55: =(K50+K51) | L55: =(L50+L51) | M55: =(M50+M51) | N55: =(N50+N51) | O55: =(O50+O51) | ... Q55: =(Q50+Q51)
A56: Cost of revenue | B56: cogs | D56: 4277.9072 | E56: 4057.0255 | F56: 3254.2877 | G56: 3528.595 | H56: =(((H53+H52)+H54)+H60) | I56: =(((I53+I52)+I54)+I60) | J56: =(((J53+J52)+J54)+J60) | K56: =(((K53+K52)+K54)+K60) | L56: =(((L53+L52)+L54)+L60) | M56: =(((M53+M52)+M54)+M60) | N56: =(((N53+N52)+N54)+N60) | O56: =(((O53+O52)+O54)+O60) | ... Q56: =(((Q53+Q52)+Q54)+Q60)
A57: Gross profit | B57: gross_profit | D57: 364.43382 | E57: 385.25412 | F57: 610.60136 | G57: 750.28984 | H57: =(H55-H56) | I57: =(I55-I56) | J57: =(J55-J56) | K57: =(K55-K56) | L57: =(L55-L56) | M57: =(M55-M56) | N57: =(N55-N56) | O57: =(O55-O56) | ... Q57: =(Q55-Q56)
A58: SG&A and other opex | B58: opex | D58: 121.91183 | E58: 119.60725 | F58: 194.69507 | G58: 295.33991 | H58: =(H55*H37) | I58: =(I55*I37) | J58: =(J55*J37) | K58: =(K55*K37) | L58: =(L55*L37) | M58: =(M55*M37) | N58: =(N55*N37) | O58: =(O55*O37) | ... Q58: =(Q55*Q37)
A59: EBIT | B59: ebit | D59: 242.52199 | E59: 265.64687 | F59: 415.90628 | G59: 454.94992 | H59: =(H57-H58) | I59: =(I57-I58) | J59: =(J57-J58) | K59: =(K57-K58) | L59: =(L57-L58) | M59: =(M57-M58) | N59: =(N57-N58) | O59: =(O57-O58) | ... Q59: =(Q57-Q58)
A60: Depreciation & amortisation | B60: da | D60: 3.2509844 | E60: 4.3611066 | F60: 133.53475 | G60: 136.90028 | H60: =IF(1000=0,0,((H41*H24)*$C$10)/1000) | I60: =IF(1000=0,0,((I41*I24)*$C$10)/1000) | J60: =IF(1000=0,0,((J41*J24)*$C$10)/1000) | K60: =IF(1000=0,0,((K41*K24)*$C$10)/1000) | L60: =IF(1000=0,0,((L41*L24)*$C$10)/1000) | M60: =IF(1000=0,0,((M41*M24)*$C$10)/1000) | N60: =IF(1000=0,0,((N41*N24)*$C$10)/1000) | O60: =IF(1000=0,0,((O41*O24)*$C$10)/1000) | ... Q60: =IF(1000=0,0,((Q41*Q24)*$C$10)/1000)
A61: EBITDA | B61: ebitda | D61: 245.77298 | E61: 270.00798 | F61: 549.44103 | G61: 591.8502 | H61: =(H59+H60) | I61: =(I59+I60) | J61: =(J59+J60) | K61: =(K59+K60) | L61: =(L59+L60) | M61: =(M59+M60) | N61: =(N59+N60) | O61: =(O59+O60) | ... Q61: =(Q59+Q60)
A62: Interest expense | B62: interest_expense | D62: 49.957649 | E62: 48.111414 | F62: 90.145257 | G62: 123.68328 | H62: =(G82*$C$29) | I62: =(H82*$C$29) | J62: =(I82*$C$29) | K62: =(J82*$C$29) | L62: =(K82*$C$29) | M62: =(L82*$C$29) | N62: =(M82*$C$29) | O62: =(N82*$C$29) | ... Q62: =(P82*$C$29)
A63: Interest income | B63: interest_income | D63: 0.82894533 | E63: 2.0082117 | F63: 2.7999254 | G63: 3.460562 | H63: =(G81*$C$30) | I63: =(H81*$C$30) | J63: =(I81*$C$30) | K63: =(J81*$C$30) | L63: =(K81*$C$30) | M63: =(L81*$C$30) | N63: =(M81*$C$30) | O63: =(N81*$C$30) | ... Q63: =(P81*$C$30)
A64: Other non-operating | B64: other_nonop | D64: 8.8311591 | E64: -2.3446613 | F64: 6.0405522 | G64: 8.866613 | H64: =H32 | I64: =I32 | J64: =J32 | K64: =K32 | L64: =L32 | M64: =M32 | N64: =N32 | O64: =O32 | ... Q64: =Q32
A65: Profit before tax | B65: pbt | D65: 202.22445 | E65: 217.19901 | F65: 334.6015 | G65: 343.59382 | H65: =(((H59-H62)+H63)+H64) | I65: =(((I59-I62)+I63)+I64) | J65: =(((J59-J62)+J63)+J64) | K65: =(((K59-K62)+K63)+K64) | L65: =(((L59-L62)+L63)+L64) | M65: =(((M59-M62)+M63)+M64) | N65: =(((N59-N62)+N63)+N64) | O65: =(((O59-O62)+O63)+O64) | ... Q65: =(((Q59-Q62)+Q63)+Q64)
A66: Tax | B66: tax | D66: 39.635319 | E66: 48.960811 | F66: 73.875971 | G66: 75.112542 | H66: =(MAX(H65,0)*H28) | I66: =(MAX(I65,0)*I28) | J66: =(MAX(J65,0)*J28) | K66: =(MAX(K65,0)*K28) | L66: =(MAX(L65,0)*L28) | M66: =(MAX(M65,0)*M28) | N66: =(MAX(N65,0)*N28) | O66: =(MAX(O65,0)*O28) | ... Q66: =(MAX(Q65,0)*Q28)
A67: Net profit (incl. minorities) | B67: np | D67: 41.68188 | E67: 77.266308 | F67: 260.72553 | G67: 268.48128 | H67: =(H65-H66) | I67: =(I65-I66) | J67: =(J65-J66) | K67: =(K65-K66) | L67: =(L65-L66) | M67: =(M65-M66) | N67: =(N65-N66) | O67: =(O65-O66) | ... Q67: =(Q65-Q66)
A68: Minority interests | B68: minority | D68: -1.0000036e-09 | E68: 0 | F68: 0 | G68: -9.9998942e-10 | H68: =(H67*H33) | I68: =(I67*I33) | J68: =(J67*J33) | K68: =(K67*K33) | L68: =(L67*L33) | M68: =(M67*M33) | N68: =(N67*N33) | O68: =(O67*O33) | ... Q68: =(Q67*Q33)
A69: Net profit to parent | B69: np_parent | D69: 41.68188 | E69: 77.266308 | F69: 260.72553 | G69: 268.48128 | H69: =(H67-H68) | I69: =(I67-I68) | J69: =(J67-J68) | K69: =(K67-K68) | L69: =(L67-L68) | M69: =(M67-M68) | N69: =(N67-N68) | O69: =(O67-O68) | ... Q69: =(Q67-Q68)
A70: Shares outstanding (m) | B70: shares | D70: 8000 | E70: 9230.665 | F70: 9230.665 | G70: 9230.665 | H70: =(G70*(1+H35)) | I70: =(H70*(1+I35)) | J70: =(I70*(1+J35)) | K70: =(J70*(1+K35)) | L70: =(K70*(1+L35)) | M70: =(L70*(1+M35)) | N70: =(M70*(1+N35)) | O70: =(N70*(1+O35)) | ... Q70: =(P70*(1+Q35))
A71: EPS | B71: eps | D71: 5.210235 | E71: 8.3706112 | F71: 28.245585 | G71: 29.0858 | H71: =(IF(H70=0,0,H69/H70)*$C$8) | I71: =(IF(I70=0,0,I69/I70)*$C$8) | J71: =(IF(J70=0,0,J69/J70)*$C$8) | K71: =(IF(K70=0,0,K69/K70)*$C$8) | L71: =(IF(L70=0,0,L69/L70)*$C$8) | M71: =(IF(M70=0,0,M69/M70)*$C$8) | N71: =(IF(N70=0,0,N69/N70)*$C$8) | O71: =(IF(O70=0,0,O69/O70)*$C$8) | ... Q71: =(IF(Q70=0,0,Q69/Q70)*$C$8)
A72: DPS (declared on the year) | B72: dps | D72: 0 | E72: 0 | F72: 5.65 | G72: 6.5 | H72: =(MAX(H71,0)*H34) | I72: =(MAX(I71,0)*I34) | J72: =(MAX(J71,0)*J34) | K72: =(MAX(K71,0)*K34) | L72: =(MAX(L71,0)*L34) | M72: =(MAX(M71,0)*M34) | N72: =(MAX(N71,0)*N34) | O72: =(MAX(O71,0)*O34) | ... Q72: =(MAX(Q71,0)*Q34)
A73: Dividends paid | B73: dividends_paid | G73: 52.153258 | H73: =IF($C$8=0,0,(G72*G70)/$C$8) | I73: =IF($C$8=0,0,(H72*H70)/$C$8) | J73: =IF($C$8=0,0,(I72*I70)/$C$8) | K73: =IF($C$8=0,0,(J72*J70)/$C$8) | L73: =IF($C$8=0,0,(K72*K70)/$C$8) | M73: =IF($C$8=0,0,(L72*L70)/$C$8) | N73: =IF($C$8=0,0,(M72*M70)/$C$8) | O73: =IF($C$8=0,0,(N72*N70)/$C$8) | ... Q73: =IF($C$8=0,0,(P72*P70)/$C$8)
A74: Capital expenditure | B74: capex | D74: 417.31951 | E74: 410.52904 | F74: 76.224514 | G74: 146.451 | H74: =(IF(1000=0,0,((H41*H25)*$C$10)/1000)+H26) | I74: =(IF(1000=0,0,((I41*I25)*$C$10)/1000)+I26) | J74: =(IF(1000=0,0,((J41*J25)*$C$10)/1000)+J26) | K74: =(IF(1000=0,0,((K41*K25)*$C$10)/1000)+K26) | L74: =(IF(1000=0,0,((L41*L25)*$C$10)/1000)+L26) | M74: =(IF(1000=0,0,((M41*M25)*$C$10)/1000)+M26) | N74: =(IF(1000=0,0,((N41*N25)*$C$10)/1000)+N26) | O74: =(IF(1000=0,0,((O41*O25)*$C$10)/1000)+O26) | ... Q74: =(IF(1000=0,0,((Q41*Q25)*$C$10)/1000)+Q26)
A75: Change in working capital | B75: delta_nwc | E75: 388.08009 | F75: 218.33475 | G75: 27.357304 | H75: =(H80-G80) | I75: =(I80-H80) | J75: =(J80-I80) | K75: =(K80-J80) | L75: =(L80-K80) | M75: =(M80-L80) | N75: =(N80-M80) | O75: =(O80-N80) | ... Q75: =(Q80-P80)
A76: Free cash flow to firm | B76: fcff | E76: -588.48304 | F76: 163.05468 | G76: 318.58596 | H76: =((((H59*(1-H28))+H60)-H74)-H75) | I76: =((((I59*(1-I28))+I60)-I74)-I75) | J76: =((((J59*(1-J28))+J60)-J74)-J75) | K76: =((((K59*(1-K28))+K60)-K74)-K75) | L76: =((((L59*(1-L28))+L60)-L74)-L75) | M76: =((((M59*(1-M28))+M60)-M74)-M75) | N76: =((((N59*(1-N28))+N60)-N74)-N75) | O76: =((((O59*(1-O28))+O60)-O74)-O75) | ... Q76: =((((Q59*(1-Q28))+Q60)-Q74)-Q75)
A77: Net borrowing | B77: net_borrowing | E77: 478.21852 | F77: -69.512753 | G77: -68.202629 | H77: =H31 | I77: =I31 | J77: =J31 | K77: =K31 | L77: =L31 | M77: =M31 | N77: =N31 | O77: =O31 | ... Q77: =Q31
A78: Dividends to minorities | B78: minority_div | H78: =(MAX(G68,0)*H34) | I78: =(MAX(H68,0)*I34) | J78: =(MAX(I68,0)*J34) | K78: =(MAX(J68,0)*K34) | L78: =(MAX(K68,0)*L34) | M78: =(MAX(L68,0)*M34) | N78: =(MAX(M68,0)*N34) | O78: =(MAX(N68,0)*O34) | ... Q78: =(MAX(P68,0)*Q34)
A79: Free cash flow to equity | B79: fcfe | H79: =(((((H67+H60)-H74)-H75)+H77)-H78) | I79: =(((((I67+I60)-I74)-I75)+I77)-I78) | J79: =(((((J67+J60)-J74)-J75)+J77)-J78) | K79: =(((((K67+K60)-K74)-K75)+K77)-K78) | L79: =(((((L67+L60)-L74)-L75)+L77)-L78) | M79: =(((((M67+M60)-M74)-M75)+M77)-M78) | N79: =(((((N67+N60)-N74)-N75)+N77)-N78) | O79: =(((((O67+O60)-O74)-O75)+O77)-O78) | ... Q79: =(((((Q67+Q60)-Q74)-Q75)+Q77)-Q78)
A80: Operating working capital | B80: nwc | D80: 526.43201 | E80: 914.51211 | F80: 1132.8469 | G80: 1160.2042 | H80: =(H55*H27) | I80: =(I55*I27) | J80: =(J55*J27) | K80: =(K55*K27) | L80: =(L55*L27) | M80: =(M55*M27) | N80: =(N55*N27) | O80: =(O55*O27) | ... Q80: =(Q55*Q27)
A81: Cash & equivalents | B81: cash | D81: 208.67116 | E81: 160.21761 | F81: 252.16043 | G81: 392.43806 | H81: =(((((((G81+H67)+H60)-H74)-H75)+H77)-H73)-H78) | I81: =(((((((H81+I67)+I60)-I74)-I75)+I77)-I73)-I78) | J81: =(((((((I81+J67)+J60)-J74)-J75)+J77)-J73)-J78) | K81: =(((((((J81+K67)+K60)-K74)-K75)+K77)-K73)-K78) | L81: =(((((((K81+L67)+L60)-L74)-L75)+L77)-L73)-L78) | M81: =(((((((L81+M67)+M60)-M74)-M75)+M77)-M73)-M78) | N81: =(((((((M81+N67)+N60)-N74)-N75)+N77)-N73)-N78) | O81: =(((((((N81+O67)+O60)-O74)-O75)+O77)-O73)-O78) | ... Q81: =(((((((P81+Q67)+Q60)-Q74)-Q75)+Q77)-Q73)-Q78)
A82: Total debt | B82: debt | D82: 1446.6129 | E82: 1924.8314 | F82: 1855.3187 | G82: 1787.1161 | H82: =(G82+H77) | I82: =(H82+I77) | J82: =(I82+J77) | K82: =(J82+K77) | L82: =(K82+L77) | M82: =(L82+M77) | N82: =(M82+N77) | O82: =(N82+O77) | ... Q82: =(P82+Q77)
A83: Fixed assets (net) | B83: ppe | D83: 1737.0603 | E83: 1884.8546 | F83: 1767.536 | G83: 1901.6317 | H83: =((G83+H74)-H60) | I83: =((H83+I74)-I60) | J83: =((I83+J74)-J60) | K83: =((J83+K74)-K60) | L83: =((K83+L74)-L60) | M83: =((L83+M74)-M60) | N83: =((M83+N74)-N60) | O83: =((N83+O74)-O60) | ... Q83: =((P83+Q74)-Q60)
A84: Parent shareholders' equity | B84: equity | D84: 1274.2641 | E84: 1441.5715 | F84: 1701.3629 | G84: 1917.0026 | H84: =((G84+H69)-H73) | I84: =((H84+I69)-I73) | J84: =((I84+J69)-J73) | K84: =((J84+K69)-K73) | L84: =((K84+L69)-L73) | M84: =((L84+M69)-M73) | N84: =((M84+N69)-N73) | O84: =((N84+O69)-O73) | ... Q84: =((P84+Q69)-Q73)
A85: Minority interest (balance sheet) | B85: minority_bs | D85: 0 | E85: 0 | F85: 0 | G85: 0 | H85: =((G85+H68)-H78) | I85: =((H85+I68)-I78) | J85: =((I85+J68)-J78) | K85: =((J85+K68)-K78) | L85: =((K85+L68)-L78) | M85: =((L85+M68)-M78) | N85: =((M85+N68)-N78) | O85: =((N85+O68)-O78) | ... Q85: =((P85+Q68)-Q78)
A86: Other assets less other liabilities | B86: other_net | D86: 248.71352 | E86: 406.81859 | F86: 404.13828 | G86: 249.84473 | H86: =G86 | I86: =H86 | J86: =I86 | K86: =J86 | L86: =K86 | M86: =L86 | N86: =M86 | O86: =N86 | ... Q86: =P86
A87: Balance check (should be zero) | B87: bs_check | H87: =((((((H81+H80)+H83)+H86)-H82)-H84)-H85) | I87: =((((((I81+I80)+I83)+I86)-I82)-I84)-I85) | J87: =((((((J81+J80)+J83)+J86)-J82)-J84)-J85) | K87: =((((((K81+K80)+K83)+K86)-K82)-K84)-K85) | L87: =((((((L81+L80)+L83)+L86)-L82)-L84)-L85) | M87: =((((((M81+M80)+M83)+M86)-M82)-M84)-M85) | N87: =((((((N81+N80)+N83)+N86)-N82)-N84)-N85) | O87: =((((((O81+O80)+O83)+O86)-O82)-O84)-O85) | ... Q87: =((((((Q81+Q80)+Q83)+Q86)-Q82)-Q84)-Q85)
A88: Net debt (cash) | B88: net_debt | D88: 1237.9418 | E88: 1764.6138 | F88: 1603.1583 | G88: 1394.678 | H88: =(H82-H81) | I88: =(I82-I81) | J88: =(J82-J81) | K88: =(K82-K81) | L88: =(L82-L81) | M88: =(M82-M81) | N88: =(N82-N81) | O88: =(O82-O81) | ... Q88: =(Q82-Q81)
A89: Book value per share | B89: bvps | D89: 159.28301 | E89: 156.17201 | F89: 184.31639 | G89: 207.67762 | H89: =(IF(H70=0,0,H84/H70)*$C$8) | I89: =(IF(I70=0,0,I84/I70)*$C$8) | J89: =(IF(J70=0,0,J84/J70)*$C$8) | K89: =(IF(K70=0,0,K84/K70)*$C$8) | L89: =(IF(L70=0,0,L84/L70)*$C$8) | M89: =(IF(M70=0,0,M84/M70)*$C$8) | N89: =(IF(N70=0,0,N84/N70)*$C$8) | O89: =(IF(O70=0,0,O84/O70)*$C$8) | ... Q89: =(IF(Q70=0,0,Q84/Q70)*$C$8)
A90: Revenue growth | B90: revenue_growth | E90: -0.043094927 | F90: -0.12997619 | G90: 0.10711712 | H90: =(IF(G55=0,0,H55/G55)-1) | I90: =(IF(H55=0,0,I55/H55)-1) | J90: =(IF(I55=0,0,J55/I55)-1) | K90: =(IF(J55=0,0,K55/J55)-1) | L90: =(IF(K55=0,0,L55/K55)-1) | M90: =(IF(L55=0,0,M55/L55)-1) | N90: =(IF(M55=0,0,N55/M55)-1) | O90: =(IF(N55=0,0,O55/N55)-1) | ... Q90: =(IF(P55=0,0,Q55/P55)-1)
A91: Gross margin | B91: gross_margin | D91: 0.078502165 | E91: 0.086724419 | F91: 0.15798677 | G91: 0.17534705 | H91: =IF(H55=0,0,H57/H55) | I91: =IF(I55=0,0,I57/I55) | J91: =IF(J55=0,0,J57/J55) | K91: =IF(K55=0,0,K57/K55) | L91: =IF(L55=0,0,L57/L55) | M91: =IF(M55=0,0,M57/M55) | N91: =IF(N55=0,0,N57/N55) | O91: =IF(O55=0,0,O57/O55) | ... Q91: =IF(Q55=0,0,Q57/Q55)
A92: EBITDA margin | B92: ebitda_margin | D92: 0.052941603 | E92: 0.060781401 | F92: 0.14216217 | G92: 0.1383188 | H92: =IF(H55=0,0,H61/H55) | I92: =IF(I55=0,0,I61/I55) | J92: =IF(J55=0,0,J61/J55) | K92: =IF(K55=0,0,K61/K55) | L92: =IF(L55=0,0,L61/L55) | M92: =IF(M55=0,0,M61/M55) | N92: =IF(N55=0,0,N61/N55) | O92: =IF(O55=0,0,O61/O55) | ... Q92: =IF(Q55=0,0,Q61/Q55)
A93: EBIT margin | B93: ebit_margin | D93: 0.052241313 | E93: 0.059799673 | F93: 0.10761144 | G93: 0.10632441 | H93: =IF(H55=0,0,H59/H55) | I93: =IF(I55=0,0,I59/I55) | J93: =IF(J55=0,0,J59/J55) | K93: =IF(K55=0,0,K59/K55) | L93: =IF(L55=0,0,L59/L55) | M93: =IF(M55=0,0,M59/M55) | N93: =IF(N55=0,0,N59/N55) | O93: =IF(O55=0,0,O59/O55) | ... Q93: =IF(Q55=0,0,Q59/Q55)
A94: Net margin | B94: np_margin | D94: 0.0089786339 | E94: 0.017393391 | F94: 0.06746003 | G94: 0.06274562 | H94: =IF(H55=0,0,H69/H55) | I94: =IF(I55=0,0,I69/I55) | J94: =IF(J55=0,0,J69/J55) | K94: =IF(K55=0,0,K69/K55) | L94: =IF(L55=0,0,L69/L55) | M94: =IF(M55=0,0,M69/M55) | N94: =IF(N55=0,0,N69/N55) | O94: =IF(O55=0,0,O69/O55) | ... Q94: =IF(Q55=0,0,Q69/Q55)
A95: EPS growth | B95: eps_growth | E95: 0.60657075 | F95: 2.3743754 | G95: 0.029746801 | H95: =(IF(G71=0,0,H71/G71)-1) | I95: =(IF(H71=0,0,I71/H71)-1) | J95: =(IF(I71=0,0,J71/I71)-1) | K95: =(IF(J71=0,0,K71/J71)-1) | L95: =(IF(K71=0,0,L71/K71)-1) | M95: =(IF(L71=0,0,M71/L71)-1) | N95: =(IF(M71=0,0,N71/M71)-1) | O95: =(IF(N71=0,0,O71/N71)-1) | ... Q95: =(IF(P71=0,0,Q71/P71)-1)
A96: ROE | B96: roe | E96: 0.056900578 | F96: 0.16591217 | G96: 0.14839921 | H96: =IF(IF(2=0,0,(H84+G84)/2)=0,0,H69/IF(2=0,0,(H84+G84)/2)) | I96: =IF(IF(2=0,0,(I84+H84)/2)=0,0,I69/IF(2=0,0,(I84+H84)/2)) | J96: =IF(IF(2=0,0,(J84+I84)/2)=0,0,J69/IF(2=0,0,(J84+I84)/2)) | K96: =IF(IF(2=0,0,(K84+J84)/2)=0,0,K69/IF(2=0,0,(K84+J84)/2)) | L96: =IF(IF(2=0,0,(L84+K84)/2)=0,0,L69/IF(2=0,0,(L84+K84)/2)) | M96: =IF(IF(2=0,0,(M84+L84)/2)=0,0,M69/IF(2=0,0,(M84+L84)/2)) | N96: =IF(IF(2=0,0,(N84+M84)/2)=0,0,N69/IF(2=0,0,(N84+M84)/2)) | O96: =IF(IF(2=0,0,(O84+N84)/2)=0,0,O69/IF(2=0,0,(O84+N84)/2)) | ... Q96: =IF(IF(2=0,0,(Q84+P84)/2)=0,0,Q69/IF(2=0,0,(Q84+P84)/2))
A97: Net debt / EBITDA | B97: net_debt_ebitda | D97: 5.036932 | E97: 6.5354136 | F97: 2.9177986 | G97: 2.3564713 | H97: =IF(H61=0,0,H88/H61) | I97: =IF(I61=0,0,I88/I61) | J97: =IF(J61=0,0,J88/J61) | K97: =IF(K61=0,0,K88/K61) | L97: =IF(L61=0,0,L88/L61) | M97: =IF(M61=0,0,M88/M61) | N97: =IF(N61=0,0,N88/N61) | O97: =IF(O61=0,0,O88/O61) | ... Q97: =IF(Q61=0,0,Q88/Q61)
A98: Payout ratio | B98: payout_ratio | D98: 0 | E98: 0 | F98: 0.20003126 | G98: 0.22347674 | H98: =IF(H71=0,0,H72/H71) | I98: =IF(I71=0,0,I72/I71) | J98: =IF(J71=0,0,J72/J71) | K98: =IF(K71=0,0,K72/K71) | L98: =IF(L71=0,0,L72/L71) | M98: =IF(M71=0,0,M72/M71) | N98: =IF(N71=0,0,N72/N71) | O98: =IF(O71=0,0,O72/O71) | ... Q98: =IF(Q71=0,0,Q72/Q71)
A99: Capex / revenue | B99: capex_revenue | D99: 0.089894195 | E99: 0.092414048 | F99: 0.019722303 | G99: 0.034226442 | H99: =IF(H55=0,0,H74/H55) | I99: =IF(I55=0,0,I74/I55) | J99: =IF(J55=0,0,J74/J55) | K99: =IF(K55=0,0,K74/K55) | L99: =IF(L55=0,0,L74/L55) | M99: =IF(M55=0,0,M74/M55) | N99: =IF(N55=0,0,N74/N55) | O99: =IF(O55=0,0,O74/O55) | ... Q99: =IF(Q55=0,0,Q74/Q55)
A101: VALUATION
A102: Last price (IDR) | C102: 2470
A103: Shares outstanding (m) | C103: 9230.665
A104: IDR per USD (spot) | C104: 18125
A105: Debt at balance-sheet date | C105: 1727.1161
...

Sheet PGUN
A1: PT Pradiksi Gunatama Tbk (PGUN.JK) — Plantations (palm oil)
A2: Units: IDR bn; per-share in IDR unless marked IDR. Model asof 2026-10-30 · data 2026-10-27
A4: Line | C4: Scalar | D4: FY2022A | E4: FY2023A | F4: FY2024A | G4: FY2025A | H4: FY2026E | I4: FY2027E | J4: FY2028E | K4: FY2029E | L4: FY2030E | M4: FY2031E | N4: FY2032E | O4: FY2033E
A6: PARAMETERS
A7: horizon | C7: 8
A8: ps_factor | C8: 1000
A9: reserves | C9: 0
A10: unit_factor | C10: 0.001
A11: vp_factor | C11: 1
A13: INPUTS (company assumptions)
A14: Sales volume plan | B14: a.volume | H14: 47.5 | I14: 50.5 | J14: 53.5 | K14: 56.5 | L14: 59.5 | M14: 66 | N14: 66 | O14: 66
A15: Realised price / benchmark | B15: a.realisation | H15: 0.79 | I15: 0.79 | J15: 0.79 | K15: 0.79 | L15: 0.79 | M15: 0.79 | N15: 0.79 | O15: 0.79
A16: Share of volume under a price cap (e.g. DMO) | B16: a.capped_share | H16: 0 | I16: 0 | J16: 0 | K16: 0 | L16: 0 | M16: 0 | N16: 0 | O16: 0
A17: Strip ratio (bcm per tonne) or cost-intensity factor | B17: a.strip_ratio | H17: 1 | I17: 1 | J17: 1 | K17: 1 | L17: 1 | M17: 1 | N17: 1 | O17: 1
A18: Mining cost per bcm (or per unit when intensity is 1) | B18: a.cost_per_bcm | H18: 7200000 | I18: 7380000 | J18: 7564500 | K18: 7753612.5 | L18: 7947452.8 | M18: 8610000 | N18: 8825250 | O18: 9045881.2
A19: Fuel share of mining cost | B19: a.fuel_share | C19: 0
A20: Other cash cost per unit (haul, barge, process) | B20: a.other_cost_unit | H20: 0 | I20: 0 | J20: 0 | K20: 0 | L20: 0 | M20: 0 | N20: 0 | O20: 0
A21: Royalty rate (flat regimes) | B21: a.royalty_rate | H21: 0 | I21: 0 | J21: 0 | K21: 0 | L21: 0 | M21: 0 | N21: 0 | O21: 0
A22: Other revenue | B22: a.other_revenue | H22: 88 | I22: 95 | J22: 101 | K22: 106 | L22: 110 | M22: 123 | N22: 126.075 | O22: 129.22687
A23: Gross margin on other revenue | B23: a.other_margin | C23: 0.65
A24: D&A per unit (reporting currency) | B24: a.da_unit | H24: 2600000 | I24: 2652000 | J24: 2705040 | K24: 2759140.8 | L24: 2814323.6 | M24: 3075000 | N24: 3151875 | O24: 3230671.9
A25: Sustaining capex per unit (reporting currency) | B25: a.capex_unit | H25: 2830000 | I25: 2900750 | J25: 2973268.8 | K25: 3047600.5 | L25: 3123790.5 | M25: 3280000 | N25: 3362000 | O25: 3446050
A26: Other capex (expansion projects) | B26: a.capex_other | H26: 0 | I26: 0 | J26: 0 | K26: 0 | L26: 0 | M26: 0 | N26: 0 | O26: 0
A27: Operating working capital / revenue | B27: a.nwc_pct | H27: 0.278361 | I27: 0.278361 | J27: 0.278361 | K27: 0.278361 | L27: 0.278361 | M27: 0.278361 | N27: 0.278361 | O27: 0.278361
A28: Effective tax rate | B28: a.tax_rate | H28: 0.215755 | I28: 0.215755 | J28: 0.215755 | K28: 0.215755 | L28: 0.215755 | M28: 0.215755 | N28: 0.215755 | O28: 0.215755
A29: Cost of debt (on opening debt) | B29: a.cost_of_debt | C29: 0.073861
A30: Yield on opening cash | B30: a.cash_yield | C30: 0.038322
A31: Net new borrowing | B31: a.net_borrowing | H31: -100 | I31: -20 | J31: 0 | K31: 0 | L31: 0 | M31: 0 | N31: 0 | O31: 0
A32: Other non-operating items | B32: a.other_nonop | H32: 0 | I32: 0 | J32: 0 | K32: 0 | L32: 0 | M32: 0 | N32: 0 | O32: 0
A33: Minorities' share of net profit | B33: a.minority_pct | H33: 0 | I33: 0 | J33: 0 | K33: 0 | L33: 0 | M33: 0 | N33: 0 | O33: 0
A34: Dividend payout | B34: a.payout | H34: 0.25 | I34: 0.25 | J34: 0.25 | K34: 0.25 | L34: 0.25 | M34: 0.25 | N34: 0.25 | O34: 0.25
A35: Change in share count | B35: a.share_change | H35: 0 | I35: 0 | J35: 0 | K35: 0 | L35: 0 | M35: 0 | N35: 0 | O35: 0
A36: Terminal growth (DCF) | B36: a.terminal_growth | C36: 0.04
A37: SG&A / revenue | B37: a.opex_pct | H37: 0.09 | I37: 0.09 | J37: 0.09 | K37: 0.09 | L37: 0.09 | M37: 0.09 | N37: 0.09 | O37: 0.09
A39: MODEL
A40: Reserves remaining (close) | B40: reserves | H40: =MAX((G40-H41),0) | I40: =MAX((H40-I41),0) | J40: =MAX((I40-J41),0) | K40: =MAX((J40-K41),0) | L40: =MAX((K40-L41),0) | M40: =MAX((L40-M41),0) | N40: =MAX((M40-N41),0) | O40: =MAX((N40-O41),0)
A41: Sales volume | B41: volume | F41: 53.108 | G41: 53.108 | H41: =IF(($C$9>0),MIN(H14,MAX(G40,0)),H14) | I41: =IF(($C$9>0),MIN(I14,MAX(H40,0)),I14) | J41: =IF(($C$9>0),MIN(J14,MAX(I40,0)),J14) | K41: =IF(($C$9>0),MIN(K14,MAX(J40,0)),K14) | L41: =IF(($C$9>0),MIN(L14,MAX(K40,0)),L14) | M41: =IF(($C$9>0),MIN(M14,MAX(L40,0)),M14) | N41: =IF(($C$9>0),MIN(N14,MAX(M40,0)),N14) | O41: =IF(($C$9>0),MIN(O14,MAX(N40,0)),O14)
A42: Benchmark price | B42: benchmark | H42: =Drivers!$H$4 | I42: =Drivers!$I$4 | J42: =Drivers!$J$4 | K42: =Drivers!$K$4 | L42: =Drivers!$L$4 | M42: =Drivers!$M$4 | N42: =Drivers!$N$4 | O42: =Drivers!$O$4
A43: Average selling price | B43: asp | H43: =(H15*H42) | I43: =(I15*I42) | J43: =(J15*J42) | K43: =(K15*K42) | L43: =(L15*L42) | M43: =(M15*M42) | N43: =(N15*N42) | O43: =(O15*O42)
A44: Realisation vs benchmark | B44: realisation_line | H44: =IF(H42=0,0,H43/H42) | I44: =IF(I42=0,0,I43/I42) | J44: =IF(J42=0,0,J43/J42) | K44: =IF(K42=0,0,K43/K42) | L44: =IF(L42=0,0,L43/L42) | M44: =IF(M42=0,0,M43/M42) | N44: =IF(N42=0,0,N43/N42) | O44: =IF(O42=0,0,O43/O42)
A45: Cash cost per unit (ex-royalty) | B45: unit_cost | H45: =((H17*H18)+H20) | I45: =((I17*I18)+I20) | J45: =((J17*J18)+J20) | K45: =((K17*K18)+K20) | L45: =((L17*L18)+L20) | M45: =((M17*M18)+M20) | N45: =((N17*N18)+N20) | O45: =((O17*O18)+O20)
A46: Strip ratio | B46: strip_ratio_line | H46: =H17 | I46: =I17 | J46: =J17 | K46: =K17 | L46: =L17 | M46: =M17 | N46: =N17 | O46: =O17
A47: Royalty rate | B47: royalty_rate | H47: =H21 | I47: =I21 | J47: =J21 | K47: =K21 | L47: =L21 | M47: =M21 | N47: =N21 | O47: =O21
A48: EBITDA per unit (price currency) | B48: ebitda_per_unit | F48: 292.48961 | G48: 388.59307 | H48: =IF(IF(1000=0,0,((H41*$C$10)*Drivers!$H$5)/1000)=0,0,H61/IF(1000=0,0,((H41*$C$10)*Drivers!$H$5)/1000)) | I48: =IF(IF(1000=0,0,((I41*$C$10)*Drivers!$I$5)/1000)=0,0,I61/IF(1000=0,0,((I41*$C$10)*Drivers!$I$5)/1000)) | J48: =IF(IF(1000=0,0,((J41*$C$10)*Drivers!$J$5)/1000)=0,0,J61/IF(1000=0,0,((J41*$C$10)*Drivers!$J$5)/1000)) | K48: =IF(IF(1000=0,0,((K41*$C$10)*Drivers!$K$5)/1000)=0,0,K61/IF(1000=0,0,((K41*$C$10)*Drivers!$K$5)/1000)) | L48: =IF(IF(1000=0,0,((L41*$C$10)*Drivers!$L$5)/1000)=0,0,L61/IF(1000=0,0,((L41*$C$10)*Drivers!$L$5)/1000)) | M48: =IF(IF(1000=0,0,((M41*$C$10)*Drivers!$M$5)/1000)=0,0,M61/IF(1000=0,0,((M41*$C$10)*Drivers!$M$5)/1000)) | N48: =IF(IF(1000=0,0,((N41*$C$10)*Drivers!$N$5)/1000)=0,0,N61/IF(1000=0,0,((N41*$C$10)*Drivers!$N$5)/1000)) | O48: =IF(IF(1000=0,0,((O41*$C$10)*Drivers!$O$5)/1000)=0,0,O61/IF(1000=0,0,((O41*$C$10)*Drivers!$O$5)/1000))
A49: Cash cost + royalty per unit (price currency) | B49: cash_cost_money_per_unit | H49: =IF(IF(1000=0,0,((H41*$C$10)*Drivers!$H$5)/1000)=0,0,(H53+H52)/IF(1000=0,0,((H41*$C$10)*Drivers!$H$5)/1000)) | I49: =IF(IF(1000=0,0,((I41*$C$10)*Drivers!$I$5)/1000)=0,0,(I53+I52)/IF(1000=0,0,((I41*$C$10)*Drivers!$I$5)/1000)) | J49: =IF(IF(1000=0,0,((J41*$C$10)*Drivers!$J$5)/1000)=0,0,(J53+J52)/IF(1000=0,0,((J41*$C$10)*Drivers!$J$5)/1000)) | K49: =IF(IF(1000=0,0,((K41*$C$10)*Drivers!$K$5)/1000)=0,0,(K53+K52)/IF(1000=0,0,((K41*$C$10)*Drivers!$K$5)/1000)) | L49: =IF(IF(1000=0,0,((L41*$C$10)*Drivers!$L$5)/1000)=0,0,(L53+L52)/IF(1000=0,0,((L41*$C$10)*Drivers!$L$5)/1000)) | M49: =IF(IF(1000=0,0,((M41*$C$10)*Drivers!$M$5)/1000)=0,0,(M53+M52)/IF(1000=0,0,((M41*$C$10)*Drivers!$M$5)/1000)) | N49: =IF(IF(1000=0,0,((N41*$C$10)*Drivers!$N$5)/1000)=0,0,(N53+N52)/IF(1000=0,0,((N41*$C$10)*Drivers!$N$5)/1000)) | O49: =IF(IF(1000=0,0,((O41*$C$10)*Drivers!$O$5)/1000)=0,0,(O53+O52)/IF(1000=0,0,((O41*$C$10)*Drivers!$O$5)/1000))
A50: Main product revenue | B50: revenue_main | H50: =IF(1000=0,0,(((H41*H43)*$C$10)*Drivers!$H$5)/1000) | I50: =IF(1000=0,0,(((I41*I43)*$C$10)*Drivers!$I$5)/1000) | J50: =IF(1000=0,0,(((J41*J43)*$C$10)*Drivers!$J$5)/1000) | K50: =IF(1000=0,0,(((K41*K43)*$C$10)*Drivers!$K$5)/1000) | L50: =IF(1000=0,0,(((L41*L43)*$C$10)*Drivers!$L$5)/1000) | M50: =IF(1000=0,0,(((M41*M43)*$C$10)*Drivers!$M$5)/1000) | N50: =IF(1000=0,0,(((N41*N43)*$C$10)*Drivers!$N$5)/1000) | O50: =IF(1000=0,0,(((O41*O43)*$C$10)*Drivers!$O$5)/1000)
A51: Other revenue | B51: other_revenue | H51: =H22 | I51: =I22 | J51: =J22 | K51: =K22 | L51: =L22 | M51: =M22 | N51: =N22 | O51: =O22
A52: Royalty | B52: royalty | H52: =(H50*H47) | I52: =(I50*I47) | J52: =(J50*J47) | K52: =(K50*K47) | L52: =(L50*L47) | M52: =(M50*M47) | N52: =(N50*N47) | O52: =(O50*O47)
A53: Cash costs | B53: cash_cost | H53: =IF(1000=0,0,((H41*H45)*$C$10)/1000) | I53: =IF(1000=0,0,((I41*I45)*$C$10)/1000) | J53: =IF(1000=0,0,((J41*J45)*$C$10)/1000) | K53: =IF(1000=0,0,((K41*K45)*$C$10)/1000) | L53: =IF(1000=0,0,((L41*L45)*$C$10)/1000) | M53: =IF(1000=0,0,((M41*M45)*$C$10)/1000) | N53: =IF(1000=0,0,((N41*N45)*$C$10)/1000) | O53: =IF(1000=0,0,((O41*O45)*$C$10)/1000)
A54: Cost of other revenue | B54: other_cogs | H54: =(H51*(1-$C$23)) | I54: =(I51*(1-$C$23)) | J54: =(J51*(1-$C$23)) | K54: =(K51*(1-$C$23)) | L54: =(L51*(1-$C$23)) | M54: =(M51*(1-$C$23)) | N54: =(N51*(1-$C$23)) | O54: =(O51*(1-$C$23))
A55: Revenue | B55: revenue | D55: 1007.3051 | E55: 868.45678 | F55: 738.56545 | G55: 792.7 | H55: =(H50+H51) | I55: =(I50+I51) | J55: =(J50+J51) | K55: =(K50+K51) | L55: =(L50+L51) | M55: =(M50+M51) | N55: =(N50+N51) | O55: =(O50+O51)
A56: Cost of revenue | B56: cogs | D56: 742.88399 | E56: 622.38233 | F56: 519.64968 | G56: 515.41998 | H56: =(((H53+H52)+H54)+H60) | I56: =(((I53+I52)+I54)+I60) | J56: =(((J53+J52)+J54)+J60) | K56: =(((K53+K52)+K54)+K60) | L56: =(((L53+L52)+L54)+L60) | M56: =(((M53+M52)+M54)+M60) | N56: =(((N53+N52)+N54)+N60) | O56: =(((O53+O52)+O54)+O60)
A57: Gross profit | B57: gross_profit | D57: 264.42107 | E57: 246.07445 | F57: 218.91577 | G57: 277.30429 | H57: =(H55-H56) | I57: =(I55-I56) | J57: =(J55-J56) | K57: =(K55-K56) | L57: =(L55-L56) | M57: =(M55-M56) | N57: =(N55-N56) | O57: =(O55-O56)
A58: SG&A and other opex | B58: opex | D58: 69.348857 | E58: 63.947381 | F58: 72.814043 | G58: 52.893573 | H58: =(H55*H37) | I58: =(I55*I37) | J58: =(J55*J37) | K58: =(K55*K37) | L58: =(L55*L37) | M58: =(M55*M37) | N58: =(N55*N37) | O58: =(O55*O37)
A59: EBIT | B59: ebit | D59: 195.07221 | E59: 182.12707 | F59: 146.10173 | G59: 224.41072 | H59: =(H57-H58) | I59: =(I57-I58) | J59: =(J57-J58) | K59: =(K57-K58) | L59: =(L57-L58) | M59: =(M57-M58) | N59: =(N57-N58) | O59: =(O57-O58)
A60: Depreciation & amortisation | B60: da | D60: 6.9289037 | E60: 2.2353494 | F60: 100.04641 | G60: 115.03516 | H60: =IF(1000=0,0,((H41*H24)*$C$10)/1000) | I60: =IF(1000=0,0,((I41*I24)*$C$10)/1000) | J60: =IF(1000=0,0,((J41*J24)*$C$10)/1000) | K60: =IF(1000=0,0,((K41*K24)*$C$10)/1000) | L60: =IF(1000=0,0,((L41*L24)*$C$10)/1000) | M60: =IF(1000=0,0,((M41*M24)*$C$10)/1000) | N60: =IF(1000=0,0,((N41*N24)*$C$10)/1000) | O60: =IF(1000=0,0,((O41*O24)*$C$10)/1000)
A61: EBITDA | B61: ebitda | D61: 202.00112 | E61: 184.36242 | F61: 246.14814 | G61: 339.44588 | H61: =(H59+H60) | I61: =(I59+I60) | J61: =(J59+J60) | K61: =(K59+K60) | L61: =(L59+L60) | M61: =(M59+M60) | N61: =(N59+N60) | O61: =(O59+O60)
A62: Interest expense | B62: interest_expense | D62: 62.60331 | E62: 50.408783 | F62: 43.836197 | G62: 35.098766 | H62: =(G82*$C$29) | I62: =(H82*$C$29) | J62: =(I82*$C$29) | K62: =(J82*$C$29) | L62: =(K82*$C$29) | M62: =(L82*$C$29) | N62: =(M82*$C$29) | O62: =(N82*$C$29)
A63: Interest income | B63: interest_income | D63: 0.065399736 | E63: 0.14821422 | F63: 0.61589435 | G63: 1.4615231 | H63: =(G81*$C$30) | I63: =(H81*$C$30) | J63: =(I81*$C$30) | K63: =(J81*$C$30) | L63: =(K81*$C$30) | M63: =(L81*$C$30) | N63: =(M81*$C$30) | O63: =(N81*$C$30)
A64: Other non-operating | B64: other_nonop | D64: 56.340901 | E64: 7.5325645 | F64: -1.058353 | G64: 8.3768595 | H64: =H32 | I64: =I32 | J64: =J32 | K64: =K32 | L64: =L32 | M64: =M32 | N64: =N32 | O64: =O32
A65: Profit before tax | B65: pbt | D65: 188.87521 | E65: 139.39906 | F65: 101.82307 | G65: 199.15034 | H65: =(((H59-H62)+H63)+H64) | I65: =(((I59-I62)+I63)+I64) | J65: =(((J59-J62)+J63)+J64) | K65: =(((K59-K62)+K63)+K64) | L65: =(((L59-L62)+L63)+L64) | M65: =(((M59-M62)+M63)+M64) | N65: =(((N59-N62)+N63)+N64) | O65: =(((O59-O62)+O63)+O64)
A66: Tax | B66: tax | D66: 21.62866 | E66: 31.342477 | F66: 22.64191 | G66: 39.842245 | H66: =(MAX(H65,0)*H28) | I66: =(MAX(I65,0)*I28) | J66: =(MAX(J65,0)*J28) | K66: =(MAX(K65,0)*K28) | L66: =(MAX(L65,0)*L28) | M66: =(MAX(M65,0)*M28) | N66: =(MAX(N65,0)*N28) | O66: =(MAX(O65,0)*O28)
A67: Net profit (incl. minorities) | B67: np | D67: 167.24655 | E67: 108.05659 | F67: 79.181163 | G67: 159.30809 | H67: =(H65-H66) | I67: =(I65-I66) | J67: =(J65-J66) | K67: =(K65-K66) | L67: =(L65-L66) | M67: =(M65-M66) | N67: =(N65-N66) | O67: =(O65-O66)
A68: Minority interests | B68: minority | D68: -4.9051103 | E68: 0 | F68: 0 | G68: 0 | H68: =(H67*H33) | I68: =(I67*I33) | J68: =(J67*J33) | K68: =(K67*K33) | L68: =(L67*L33) | M68: =(M67*M33) | N68: =(N67*N33) | O68: =(O67*O33)
A69: Net profit to parent | B69: np_parent | D69: 172.15166 | E69: 108.05659 | F69: 79.181163 | G69: 159.30809 | H69: =(H67-H68) | I69: =(I67-I68) | J69: =(J67-J68) | K69: =(K67-K68) | L69: =(L67-L68) | M69: =(M67-M68) | N69: =(N67-N68) | O69: =(O67-O68)
A70: Shares outstanding (m) | B70: shares | D70: 5737.8489 | E70: 5737.8489 | F70: 5737.8489 | G70: 5737.8489 | H70: =(G70*(1+H35)) | I70: =(H70*(1+I35)) | J70: =(I70*(1+J35)) | K70: =(J70*(1+K35)) | L70: =(K70*(1+L35)) | M70: =(L70*(1+M35)) | N70: =(M70*(1+N35)) | O70: =(N70*(1+O35))
A71: EPS | B71: eps | D71: 30.002821 | E71: 18.832247 | F71: 13.799799 | G71: 27.764428 | H71: =(IF(H70=0,0,H69/H70)*$C$8) | I71: =(IF(I70=0,0,I69/I70)*$C$8) | J71: =(IF(J70=0,0,J69/J70)*$C$8) | K71: =(IF(K70=0,0,K69/K70)*$C$8) | L71: =(IF(L70=0,0,L69/L70)*$C$8) | M71: =(IF(M70=0,0,M69/M70)*$C$8) | N71: =(IF(N70=0,0,N69/N70)*$C$8) | O71: =(IF(O70=0,0,O69/O70)*$C$8)
A72: DPS (declared on the year) | B72: dps | D72: 0 | E72: 0 | F72: 2.07 | G72: 6.97 | H72: =(MAX(H71,0)*H34) | I72: =(MAX(I71,0)*I34) | J72: =(MAX(J71,0)*J34) | K72: =(MAX(K71,0)*K34) | L72: =(MAX(L71,0)*L34) | M72: =(MAX(M71,0)*M34) | N72: =(MAX(N71,0)*N34) | O72: =(MAX(O71,0)*O34)
A73: Dividends paid | B73: dividends_paid | G73: 39.99 | H73: =IF($C$8=0,0,(G72*G70)/$C$8) | I73: =IF($C$8=0,0,(H72*H70)/$C$8) | J73: =IF($C$8=0,0,(I72*I70)/$C$8) | K73: =IF($C$8=0,0,(J72*J70)/$C$8) | L73: =IF($C$8=0,0,(K72*K70)/$C$8) | M73: =IF($C$8=0,0,(L72*L70)/$C$8) | N73: =IF($C$8=0,0,(M72*M70)/$C$8) | O73: =IF($C$8=0,0,(N72*N70)/$C$8)
A74: Capital expenditure | B74: capex | D74: 77.068733 | E74: 353.38057 | F74: 39.457096 | G74: 134.77146 | H74: =(IF(1000=0,0,((H41*H25)*$C$10)/1000)+H26) | I74: =(IF(1000=0,0,((I41*I25)*$C$10)/1000)+I26) | J74: =(IF(1000=0,0,((J41*J25)*$C$10)/1000)+J26) | K74: =(IF(1000=0,0,((K41*K25)*$C$10)/1000)+K26) | L74: =(IF(1000=0,0,((L41*L25)*$C$10)/1000)+L26) | M74: =(IF(1000=0,0,((M41*M25)*$C$10)/1000)+M26) | N74: =(IF(1000=0,0,((N41*N25)*$C$10)/1000)+N26) | O74: =(IF(1000=0,0,((O41*O25)*$C$10)/1000)+O26)
A75: Change in working capital | B75: delta_nwc | E75: -44.032153 | F75: 139.96799 | G75: -33.358822 | H75: =(H80-G80) | I75: =(I80-H80) | J75: =(J80-I80) | K75: =(K80-J80) | L75: =(L80-K80) | M75: =(M80-L80) | N75: =(N80-M80) | O75: =(O80-N80)
A76: Free cash flow to firm | B76: fcff | E76: -165.93544 | F76: 34.235108 | G76: 193.13738 | H76: =((((H59*(1-H28))+H60)-H74)-H75) | I76: =((((I59*(1-I28))+I60)-I74)-I75) | J76: =((((J59*(1-J28))+J60)-J74)-J75) | K76: =((((K59*(1-K28))+K60)-K74)-K75) | L76: =((((L59*(1-L28))+L60)-L74)-L75) | M76: =((((M59*(1-M28))+M60)-M74)-M75) | N76: =((((N59*(1-N28))+N60)-N74)-N75) | O76: =((((O59*(1-O28))+O60)-O74)-O75)
A77: Net borrowing | B77: net_borrowing | E77: -122.23757 | F77: -81.122064 | G77: -128.58405 | H77: =H31 | I77: =I31 | J77: =J31 | K77: =K31 | L77: =L31 | M77: =M31 | N77: =N31 | O77: =O31
A78: Dividends to minorities | B78: minority_div | H78: =(MAX(G68,0)*H34) | I78: =(MAX(H68,0)*I34) | J78: =(MAX(I68,0)*J34) | K78: =(MAX(J68,0)*K34) | L78: =(MAX(K68,0)*L34) | M78: =(MAX(L68,0)*M34) | N78: =(MAX(M68,0)*N34) | O78: =(MAX(N68,0)*O34)
A79: Free cash flow to equity | B79: fcfe | H79: =(((((H67+H60)-H74)-H75)+H77)-H78) | I79: =(((((I67+I60)-I74)-I75)+I77)-I78) | J79: =(((((J67+J60)-J74)-J75)+J77)-J78) | K79: =(((((K67+K60)-K74)-K75)+K77)-K78) | L79: =(((((L67+L60)-L74)-L75)+L77)-L78) | M79: =(((((M67+M60)-M74)-M75)+M77)-M78) | N79: =(((((N67+N60)-N74)-N75)+N77)-N78) | O79: =(((((O67+O60)-O74)-O75)+O77)-O78)
A80: Operating working capital | B80: nwc | D80: 179.7093 | E80: 135.67715 | F80: 275.64514 | G80: 242.28632 | H80: =(H55*H27) | I80: =(I55*I27) | J80: =(J55*J27) | K80: =(K55*K27) | L80: =(L55*L27) | M80: =(M55*M27) | N80: =(N55*N27) | O80: =(O55*O27)
A81: Cash & equivalents | B81: cash | D81: 35.899308 | E81: 75.587187 | F81: 14.232286 | G81: 6.4590053 | H81: =(((((((G81+H67)+H60)-H74)-H75)+H77)-H73)-H78) | I81: =(((((((H81+I67)+I60)-I74)-I75)+I77)-I73)-I78) | J81: =(((((((I81+J67)+J60)-J74)-J75)+J77)-J73)-J78) | K81: =(((((((J81+K67)+K60)-K74)-K75)+K77)-K73)-K78) | L81: =(((((((K81+L67)+L60)-L74)-L75)+L77)-L73)-L78) | M81: =(((((((L81+M67)+M60)-M74)-M75)+M77)-M73)-M78) | N81: =(((((((M81+N67)+N60)-N74)-N75)+N77)-N73)-N78) | O81: =(((((((N81+O67)+O60)-O74)-O75)+O77)-O73)-O78)
A82: Total debt | B82: debt | D82: 692.07898 | E82: 569.8414 | F82: 488.71934 | G82: 360.13528 | H82: =(G82+H77) | I82: =(H82+I77) | J82: =(I82+J77) | K82: =(J82+K77) | L82: =(K82+L77) | M82: =(L82+M77) | N82: =(M82+N77) | O82: =(N82+O77)
A83: Fixed assets (net) | B83: ppe | D83: 1960.8659 | E83: 2259.7 | F83: 2252.1804 | G83: 2189.3175 | H83: =((G83+H74)-H60) | I83: =((H83+I74)-I60) | J83: =((I83+J74)-J60) | K83: =((J83+K74)-K60) | L83: =((K83+L74)-L60) | M83: =((L83+M74)-M60) | N83: =((M83+N74)-N60) | O83: =((N83+O74)-O60)
A84: Parent shareholders' equity | B84: equity | D84: 1429.1661 | E84: 1626.0748 | F84: 1792.9518 | G84: 1918.7179 | H84: =((G84+H69)-H73) | I84: =((H84+I69)-I73) | J84: =((I84+J69)-J73) | K84: =((J84+K69)-K73) | L84: =((K84+L69)-L73) | M84: =((L84+M69)-M73) | N84: =((M84+N69)-N73) | O84: =((N84+O69)-O73)
A85: Minority interest (balance sheet) | B85: minority_bs | D85: 0 | E85: 0 | F85: 0 | G85: 0 | H85: =((G85+H68)-H78) | I85: =((H85+I68)-I78) | J85: =((I85+J68)-J78) | K85: =((J85+K68)-K78) | L85: =((K85+L68)-L78) | M85: =((L85+M68)-M78) | N85: =((M85+N68)-N78) | O85: =((N85+O68)-O78)
A86: Other assets less other liabilities | B86: other_net | D86: -55.229463 | E86: -275.04806 | F86: -260.38678 | G86: -159.20961 | H86: =G86 | I86: =H86 | J86: =I86 | K86: =J86 | L86: =K86 | M86: =L86 | N86: =M86 | O86: =N86
A87: Balance check (should be zero) | B87: bs_check | H87: =((((((H81+H80)+H83)+H86)-H82)-H84)-H85) | I87: =((((((I81+I80)+I83)+I86)-I82)-I84)-I85) | J87: =((((((J81+J80)+J83)+J86)-J82)-J84)-J85) | K87: =((((((K81+K80)+K83)+K86)-K82)-K84)-K85) | L87: =((((((L81+L80)+L83)+L86)-L82)-L84)-L85) | M87: =((((((M81+M80)+M83)+M86)-M82)-M84)-M85) | N87: =((((((N81+N80)+N83)+N86)-N82)-N84)-N85) | O87: =((((((O81+O80)+O83)+O86)-O82)-O84)-O85)
A88: Net debt (cash) | B88: net_debt | D88: 656.17967 | E88: 494.25422 | F88: 474.48705 | G88: 353.67628 | H88: =(H82-H81) | I88: =(I82-I81) | J88: =(J82-J81) | K88: =(K82-K81) | L88: =(L82-L81) | M88: =(M82-M81) | N88: =(N82-N81) | O88: =(O82-O81)
A89: Book value per share | B89: bvps | D89: 249.07699 | E89: 283.39451 | F89: 312.47804 | G89: 334.39673 | H89: =(IF(H70=0,0,H84/H70)*$C$8) | I89: =(IF(I70=0,0,I84/I70)*$C$8) | J89: =(IF(J70=0,0,J84/J70)*$C$8) | K89: =(IF(K70=0,0,K84/K70)*$C$8) | L89: =(IF(L70=0,0,L84/L70)*$C$8) | M89: =(IF(M70=0,0,M84/M70)*$C$8) | N89: =(IF(N70=0,0,N84/N70)*$C$8) | O89: =(IF(O70=0,0,O84/O70)*$C$8)
A90: Revenue growth | B90: revenue_growth | E90: -0.13784134 | F90: -0.14956568 | G90: 0.07329689 | H90: =(IF(G55=0,0,H55/G55)-1) | I90: =(IF(H55=0,0,I55/H55)-1) | J90: =(IF(I55=0,0,J55/I55)-1) | K90: =(IF(J55=0,0,K55/J55)-1) | L90: =(IF(K55=0,0,L55/K55)-1) | M90: =(IF(L55=0,0,M55/L55)-1) | N90: =(IF(M55=0,0,N55/M55)-1) | O90: =(IF(N55=0,0,O55/N55)-1)
A91: Gross margin | B91: gross_margin | D91: 0.26250347 | E91: 0.2833468 | F91: 0.29640673 | G91: 0.3498225 | H91: =IF(H55=0,0,H57/H55) | I91: =IF(I55=0,0,I57/I55) | J91: =IF(J55=0,0,J57/J55) | K91: =IF(K55=0,0,K57/K55) | L91: =IF(L55=0,0,L57/L55) | M91: =IF(M55=0,0,M57/M55) | N91: =IF(N55=0,0,N57/N55) | O91: =IF(O55=0,0,O57/O55)
A92: EBITDA margin | B92: ebitda_margin | D92: 0.20053619 | E92: 0.21228738 | F92: 0.33327871 | G92: 0.42821481 | H92: =IF(H55=0,0,H61/H55) | I92: =IF(I55=0,0,I61/I55) | J92: =IF(J55=0,0,J61/J55) | K92: =IF(K55=0,0,K61/K55) | L92: =IF(L55=0,0,L61/L55) | M92: =IF(M55=0,0,M61/M55) | N92: =IF(N55=0,0,N61/N55) | O92: =IF(O55=0,0,O61/O55)
A93: EBIT margin | B93: ebit_margin | D93: 0.19365753 | E93: 0.20971345 | F93: 0.19781826 | G93: 0.28309666 | H93: =IF(H55=0,0,H59/H55) | I93: =IF(I55=0,0,I59/I55) | J93: =IF(J55=0,0,J59/J55) | K93: =IF(K55=0,0,K59/K55) | L93: =IF(L55=0,0,L59/L55) | M93: =IF(M55=0,0,M59/M55) | N93: =IF(N55=0,0,N59/N55) | O93: =IF(O55=0,0,O59/O55)
A94: Net margin | B94: np_margin | D94: 0.1709032 | E94: 0.12442368 | F94: 0.10720941 | G94: 0.20096896 | H94: =IF(H55=0,0,H69/H55) | I94: =IF(I55=0,0,I69/I55) | J94: =IF(J55=0,0,J69/J55) | K94: =IF(K55=0,0,K69/K55) | L94: =IF(L55=0,0,L69/L55) | M94: =IF(M55=0,0,M69/M55) | N94: =IF(N55=0,0,N69/N55) | O94: =IF(O55=0,0,O69/O55)
A95: EPS growth | B95: eps_growth | E95: -0.37231747 | F95: -0.26722503 | G95: 1.0119443 | H95: =(IF(G71=0,0,H71/G71)-1) | I95: =(IF(H71=0,0,I71/H71)-1) | J95: =(IF(I71=0,0,J71/I71)-1) | K95: =(IF(J71=0,0,K71/J71)-1) | L95: =(IF(K71=0,0,L71/K71)-1) | M95: =(IF(L71=0,0,M71/L71)-1) | N95: =(IF(M71=0,0,N71/M71)-1) | O95: =(IF(N71=0,0,O71/N71)-1)
A96: ROE | B96: roe | E96: 0.070735231 | F96: 0.046317957 | G96: 0.085841741 | H96: =IF(IF(2=0,0,(H84+G84)/2)=0,0,H69/IF(2=0,0,(H84+G84)/2)) | I96: =IF(IF(2=0,0,(I84+H84)/2)=0,0,I69/IF(2=0,0,(I84+H84)/2)) | J96: =IF(IF(2=0,0,(J84+I84)/2)=0,0,J69/IF(2=0,0,(J84+I84)/2)) | K96: =IF(IF(2=0,0,(K84+J84)/2)=0,0,K69/IF(2=0,0,(K84+J84)/2)) | L96: =IF(IF(2=0,0,(L84+K84)/2)=0,0,L69/IF(2=0,0,(L84+K84)/2)) | M96: =IF(IF(2=0,0,(M84+L84)/2)=0,0,M69/IF(2=0,0,(M84+L84)/2)) | N96: =IF(IF(2=0,0,(N84+M84)/2)=0,0,N69/IF(2=0,0,(N84+M84)/2)) | O96: =IF(IF(2=0,0,(O84+N84)/2)=0,0,O69/IF(2=0,0,(O84+N84)/2))
A97: Net debt / EBITDA | B97: net_debt_ebitda | D97: 3.2483962 | E97: 2.6808838 | F97: 1.9276483 | G97: 1.0419224 | H97: =IF(H61=0,0,H88/H61) | I97: =IF(I61=0,0,I88/I61) | J97: =IF(J61=0,0,J88/J61) | K97: =IF(K61=0,0,K88/K61) | L97: =IF(L61=0,0,L88/L61) | M97: =IF(M61=0,0,M88/M61) | N97: =IF(N61=0,0,N88/N61) | O97: =IF(O61=0,0,O88/O61)
A98: Payout ratio | B98: payout_ratio | D98: 0 | E98: 0 | F98: 0.15000218 | G98: 0.25104065 | H98: =IF(H71=0,0,H72/H71) | I98: =IF(I71=0,0,I72/I71) | J98: =IF(J71=0,0,J72/J71) | K98: =IF(K71=0,0,K72/K71) | L98: =IF(L71=0,0,L72/L71) | M98: =IF(M71=0,0,M72/M71) | N98: =IF(N71=0,0,N72/N71) | O98: =IF(O71=0,0,O72/O71)
A99: Capex / revenue | B99: capex_revenue | D99: 0.076509824 | E99: 0.40690634 | F99: 0.053423967 | G99: 0.17001572 | H99: =IF(H55=0,0,H74/H55) | I99: =IF(I55=0,0,I74/I55) | J99: =IF(J55=0,0,J74/J55) | K99: =IF(K55=0,0,K74/K55) | L99: =IF(L55=0,0,L74/L55) | M99: =IF(M55=0,0,M74/M55) | N99: =IF(N55=0,0,N74/N55) | O99: =IF(O55=0,0,O74/O55)
A101: VALUATION
A102: Last price (IDR) | C102: 8350
A103: Shares outstanding (m) | C103: 5737.8489
A104: IDR per USD (spot) | C104: 18125
A105: Debt at balance-sheet date | C105: 257.82761
...
