Workbook

Sheet README
A1: Six South — Poultry, feed & protein industry model
A2: Generated 2026-10-27T10:28:09+07:00 by the coverage engine. The engine (scripts/cov_engine.py) is the source of truth; this workbook is a live rendering of it.
A3: Colour key: blue = input or hard-coded history; black = formula; green = link to another sheet.
A4: Drivers: every deck variable these models read. Change one and every ticker tab and the Comps sheet recalculate (forecasts, cash flows, DCF value, base-case value, target, rating).
A5: Scenario (bear/bull) and sensitivity tables need full model re-runs and are engine values.
A6: Paper fund — research for education and process transparency, not investment advice.
A8: Tickers:
A9: WMPP.JK — PT Widodo Makmur Perkasa Tbk

Sheet Drivers
A1: Driver decks (state/drivers) — edit a blue cell to flow it through every ticker tab
A3: Variable | B3: Key | C3: Unit / status | D3: FY2022A | E3: FY2023A | F3: FY2024A | G3: FY2025A | H3: FY2026E | I3: FY2027E | J3: FY2028E | K3: FY2029E | L3: FY2030E | M3: FY2031E | N3: FY2032E | O3: FY2033E | P3: FY2034E | Q3: FY2035E
A4: IDR per USD | B4: m.usd_idr | C4: IDR/USD · reviewed | D4: 14843.177 | E4: 15228.8 | F4: 15846.238 | G4: 16448.093 | H4: 17570 | I4: 18350 | J4: 18600 | K4: 18850 | L4: 19093.137 | M4: 19186.731 | N4: 19280.784 | O4: 19375.297 | P4: 19470.274 | Q4: 19565.717
A6: Cost-of-capital scalars (macro deck)
A7: 10-year Indonesian government bond yield (IDR) | B7: m.rf_idr | C7: 0.0745 | D7: investor.id — "Yield SUN 7,45%, Saatnya Borong atau Tunggu Lebih Tinggi?" (25 Okt 2026 20:58 WIB; deck source S3); corroborated by kalderanews S1 (10Y SUN 7.41%
A8: 10-year US Treasury yield | B8: m.rf_usd | C8: 0.04986 | D8: Yahoo Finance ^TNX (US 10-year Treasury yield)
A9: Indonesia sovereign default spread (Damodaran) | B9: m.default_spread_id | C9: 0.0162 | D9: Damodaran country risk premiums (https://pages.stern.nyu.edu/~adamodar/New_Home_Page/datafile/ctryprem.html), page dated January 5, 2026, read 2026-10-27
A10: Mature-market equity risk premium (Damodaran) | B10: m.erp_mature | C10: 0.0423 | D10: Damodaran country risk premiums (https://pages.stern.nyu.edu/~adamodar/New_Home_Page/datafile/ctryprem.html), page dated January 5, 2026, read 2026-10-27
A11: Indonesia country risk premium (Damodaran) | B11: m.crp_id | C11: 0.0246 | D11: Damodaran country risk premiums (https://pages.stern.nyu.edu/~adamodar/New_Home_Page/datafile/ctryprem.html), page dated January 5, 2026, read 2026-10-27
A12: House pre-tax corporate debt spread over the risk-free | B12: m.debt_spread_corp | C12: 0.02 | D12: SEED house assumption pending the macro desk: 200 bp over the risk-free rate for an average IDX corporate borrower
A13: Indonesia statutory corporate income tax rate | B13: m.tax_rate_id | C13: 0.22 | D13: Law 7/2021 on Harmonisation of Tax Regulations (UU HPP): 22% corporate income tax from fiscal 2022

Sheet Comps
A1: Ticker | B1: Company | C1: Rating | D1: Target (IDR) | E1: Price (IDR) | F1: Exp. 12m TR | G1: Value today | H1: P/E FY+0 | I1: EV/EBITDA FY+0 | J1: Div. yield FY+0
A2: WMPP.JK | B2: PT Widodo Makmur Perkasa Tbk | C2: ='WMPP'!$C$122 | D2: ='WMPP'!$C$120 | E2: ='WMPP'!$C$76 | F2: ='WMPP'!$C$121 | G2: ='WMPP'!$C$110 | I2: 316.39215 | J2: 0

Sheet WMPP
A1: PT Widodo Makmur Perkasa Tbk (WMPP.JK) — Conglomerates & multi-sector holdings
A2: Units: IDR bn; per-share in IDR unless marked IDR. Model asof 2026-10-27 · data 2026-10-26
A4: Line | C4: Scalar | D4: FY2022A | E4: FY2023A | F4: FY2024A | G4: FY2025A | H4: FY2026E | I4: FY2027E | J4: FY2028E | K4: FY2029E | L4: FY2030E | M4: FY2031E | N4: FY2032E | O4: FY2033E | P4: FY2034E | Q4: FY2035E
A6: PARAMETERS
A7: ps_factor | C7: 1000
A8: vp_factor | C8: 1
A10: INPUTS (company assumptions)
A11: Revenue growth | B11: a.revenue_growth | H11: 0.11 | I11: 0.1 | J11: 0.09 | K11: 0.085 | L11: 0.085 | M11: 0.05 | N11: 0.05 | O11: 0.05 | P11: 0.05 | Q11: 0.05
A12: Gross margin at base input costs | B12: a.gross_margin | H12: 0.011 | I12: 0.011 | J12: 0.011 | K12: 0.011 | L12: 0.011 | M12: 0.011 | N12: 0.011 | O12: 0.011 | P12: 0.011 | Q12: 0.011
A13: SG&A / revenue | B13: a.opex_pct | H13: 0.1024 | I13: 0.1024 | J13: 0.1024 | K13: 0.1024 | L13: 0.1024 | M13: 0.1024 | N13: 0.1024 | O13: 0.1024 | P13: 0.1024 | Q13: 0.1024
A14: D&A / revenue | B14: a.da_pct | H14: 0.1037 | I14: 0.1037 | J14: 0.1037 | K14: 0.1037 | L14: 0.1037 | M14: 0.1037 | N14: 0.1037 | O14: 0.1037 | P14: 0.1037 | Q14: 0.1037
A15: Capex / revenue | B15: a.capex_pct | H15: 0.006503 | I15: 0.006503 | J15: 0.006503 | K15: 0.006503 | L15: 0.006503 | M15: 0.006503 | N15: 0.006503 | O15: 0.006503 | P15: 0.006503 | Q15: 0.006503
A16: Operating working capital / revenue | B16: a.nwc_pct | H16: 0.642413 | I16: 0.642413 | J16: 0.642413 | K16: 0.642413 | L16: 0.642413 | M16: 0.642413 | N16: 0.642413 | O16: 0.642413 | P16: 0.642413 | Q16: 0.642413
A17: Effective tax rate | B17: a.tax_rate | H17: 0.1 | I17: 0.1 | J17: 0.1 | K17: 0.1 | L17: 0.1 | M17: 0.1 | N17: 0.1 | O17: 0.1 | P17: 0.1 | Q17: 0.1
A18: Cost of debt (on opening debt) | B18: a.cost_of_debt | C18: 0.063204
A19: Yield on opening cash | B19: a.cash_yield | C19: 0.005521
A20: Net new borrowing | B20: a.net_borrowing | H20: 0 | I20: 0 | J20: 0 | K20: 0 | L20: 0 | M20: 0 | N20: 0 | O20: 0 | P20: 0 | Q20: 0
A21: Other non-operating items | B21: a.other_nonop | H21: 0 | I21: 0 | J21: 0 | K21: 0 | L21: 0 | M21: 0 | N21: 0 | O21: 0 | P21: 0 | Q21: 0
A22: Minorities' share of net profit | B22: a.minority_pct | H22: 0.0501 | I22: 0.0501 | J22: 0.0501 | K22: 0.0501 | L22: 0.0501 | M22: 0.0501 | N22: 0.0501 | O22: 0.0501 | P22: 0.0501 | Q22: 0.0501
A23: Dividend payout | B23: a.payout | H23: 0 | I23: 0 | J23: 0 | K23: 0 | L23: 0 | M23: 0 | N23: 0 | O23: 0 | P23: 0 | Q23: 0
A24: Change in share count | B24: a.share_change | H24: 0 | I24: 0 | J24: 0 | K24: 0 | L24: 0 | M24: 0 | N24: 0 | O24: 0 | P24: 0 | Q24: 0
A25: Terminal growth (DCF) | B25: a.terminal_growth | C25: 0.03
A26: Holding-company discount to SOTP | B26: a.holdco_discount | C26: 0.35
A28: MODEL
A29: Revenue | B29: revenue | D29: 4390.0777 | E29: 907.22618 | F29: 572.92123 | G29: 1011.9009 | H29: =(G29*(1+H11)) | I29: =(H29*(1+I11)) | J29: =(I29*(1+J11)) | K29: =(J29*(1+K11)) | L29: =(K29*(1+L11)) | M29: =(L29*(1+M11)) | N29: =(M29*(1+N11)) | O29: =(N29*(1+O11)) | ... Q29: =(P29*(1+Q11))
A30: Cost of revenue | B30: cogs | D30: 4052.6474 | E30: 1277.5027 | F30: 668.19316 | G30: 1009.1141 | H30: =(H29*(1-H12)) | I30: =(I29*(1-I12)) | J30: =(J29*(1-J12)) | K30: =(K29*(1-K12)) | L30: =(L29*(1-L12)) | M30: =(M29*(1-M12)) | N30: =(N29*(1-N12)) | O30: =(O29*(1-O12)) | ... Q30: =(Q29*(1-Q12))
A31: Gross profit | B31: gross_profit | D31: 337.43027 | E31: -370.2765 | F31: -95.271931 | G31: 2.7868142 | H31: =(H29-H30) | I31: =(I29-I30) | J31: =(J29-J30) | K31: =(K29-K30) | L31: =(L29-L30) | M31: =(M29-M30) | N31: =(N29-N30) | O31: =(O29-O30) | ... Q31: =(Q29-Q30)
A32: SG&A and other opex | B32: opex | D32: 434.22193 | E32: 246.20884 | F32: 129.134 | G32: 103.64157 | H32: =(H29*H13) | I32: =(I29*I13) | J32: =(J29*J13) | K32: =(K29*K13) | L32: =(L29*L13) | M32: =(M29*M13) | N32: =(N29*N13) | O32: =(O29*O13) | ... Q32: =(Q29*Q13)
A33: EBIT | B33: ebit | D33: -96.791665 | E33: -616.48534 | F33: -224.40593 | G33: -100.85476 | H33: =(H31-H32) | I33: =(I31-I32) | J33: =(J31-J32) | K33: =(K31-K32) | L33: =(L31-L32) | M33: =(M31-M32) | N33: =(N31-N32) | O33: =(O31-O32) | ... Q33: =(Q31-Q32)
A34: Depreciation & amortisation | B34: da | D34: 52.144187 | E34: 62.744607 | F34: 101.47502 | G34: 104.92465 | H34: =(H29*H14) | I34: =(I29*I14) | J34: =(J29*J14) | K34: =(K29*K14) | L34: =(L29*L14) | M34: =(M29*M14) | N34: =(N29*N14) | O34: =(O29*O14) | ... Q34: =(Q29*Q14)
A35: EBITDA | B35: ebitda | D35: -44.647478 | E35: -553.74073 | F35: -122.93092 | G35: 4.0698941 | H35: =(H33+H34) | I35: =(I33+I34) | J35: =(J33+J34) | K35: =(K33+K34) | L35: =(L33+L34) | M35: =(M33+M34) | N35: =(N33+N34) | O35: =(O33+O34) | ... Q35: =(Q33+Q34)
A36: Interest expense | B36: interest_expense | D36: 262.59436 | E36: 243.81625 | F36: 198.0758 | G36: 106.90192 | H36: =(G56*$C$18) | I36: =(H56*$C$18) | J36: =(I56*$C$18) | K36: =(J56*$C$18) | L36: =(K56*$C$18) | M36: =(L56*$C$18) | N36: =(M56*$C$18) | O36: =(N56*$C$18) | ... Q36: =(P56*$C$18)
A37: Interest income | B37: interest_income | D37: 2.0556429 | E37: 0.90158414 | F37: 0.14103972 | G37: 0.044817023 | H37: =(G55*$C$19) | I37: =(H55*$C$19) | J37: =(I55*$C$19) | K37: =(J55*$C$19) | L37: =(K55*$C$19) | M37: =(L55*$C$19) | N37: =(M55*$C$19) | O37: =(N55*$C$19) | ... Q37: =(P55*$C$19)
A38: Other non-operating | B38: other_nonop | D38: -38.005425 | E38: -29.440547 | F38: -267.30452 | G38: -67.664474 | H38: =H21 | I38: =I21 | J38: =J21 | K38: =K21 | L38: =L21 | M38: =M21 | N38: =N21 | O38: =O21 | ... Q38: =Q21
A39: Profit before tax | B39: pbt | D39: -395.33581 | E39: -888.84055 | F39: -689.64522 | G39: -275.37633 | H39: =(((H33-H36)+H37)+H38) | I39: =(((I33-I36)+I37)+I38) | J39: =(((J33-J36)+J37)+J38) | K39: =(((K33-K36)+K37)+K38) | L39: =(((L33-L36)+L37)+L38) | M39: =(((M33-M36)+M37)+M38) | N39: =(((N33-N36)+N37)+N38) | O39: =(((O33-O36)+O37)+O38) | ... Q39: =(((Q33-Q36)+Q37)+Q38)
A40: Tax | B40: tax | D40: -78.264607 | E40: -7.9377804 | F40: -93.139438 | G40: -40.437581 | H40: =(MAX(H39,0)*H17) | I40: =(MAX(I39,0)*I17) | J40: =(MAX(J39,0)*J17) | K40: =(MAX(K39,0)*K17) | L40: =(MAX(L39,0)*L17) | M40: =(MAX(M39,0)*M17) | N40: =(MAX(N39,0)*N17) | O40: =(MAX(O39,0)*O17) | ... Q40: =(MAX(Q39,0)*Q17)
A41: Net profit (incl. minorities) | B41: np | D41: -317.0712 | E41: -880.90277 | F41: -596.50578 | G41: -234.93875 | H41: =(H39-H40) | I41: =(I39-I40) | J41: =(J39-J40) | K41: =(K39-K40) | L41: =(L39-L40) | M41: =(M39-M40) | N41: =(N39-N40) | O41: =(O39-O40) | ... Q41: =(Q39-Q40)
A42: Minority interests | B42: minority | D42: -9.4569728 | E42: -5.2762674 | F42: -28.72616 | G42: -22.590098 | H42: =(H41*H22) | I42: =(I41*I22) | J42: =(J41*J22) | K42: =(K41*K22) | L42: =(L41*L22) | M42: =(M41*M22) | N42: =(N41*N22) | O42: =(O41*O22) | ... Q42: =(Q41*Q22)
A43: Net profit to parent | B43: np_parent | D43: -307.61423 | E43: -875.6265 | F43: -567.77962 | G43: -212.34865 | H43: =(H41-H42) | I43: =(I41-I42) | J43: =(J41-J42) | K43: =(K41-K42) | L43: =(L41-L42) | M43: =(M41-M42) | N43: =(N41-N42) | O43: =(O41-O42) | ... Q43: =(Q41-Q42)
A44: Shares outstanding (m) | B44: shares | D44: 29419 | E44: 29419 | F44: 29419 | G44: 29419 | H44: =(G44*(1+H24)) | I44: =(H44*(1+I24)) | J44: =(I44*(1+J24)) | K44: =(J44*(1+K24)) | L44: =(K44*(1+L24)) | M44: =(L44*(1+M24)) | N44: =(M44*(1+N24)) | O44: =(N44*(1+O24)) | ... Q44: =(P44*(1+Q24))
A45: EPS | B45: eps | D45: -10.456311 | E45: -29.763979 | F45: -19.299759 | G45: -7.2180785 | H45: =(IF(H44=0,0,H43/H44)*$C$7) | I45: =(IF(I44=0,0,I43/I44)*$C$7) | J45: =(IF(J44=0,0,J43/J44)*$C$7) | K45: =(IF(K44=0,0,K43/K44)*$C$7) | L45: =(IF(L44=0,0,L43/L44)*$C$7) | M45: =(IF(M44=0,0,M43/M44)*$C$7) | N45: =(IF(N44=0,0,N43/N44)*$C$7) | O45: =(IF(O44=0,0,O43/O44)*$C$7) | ... Q45: =(IF(Q44=0,0,Q43/Q44)*$C$7)
A46: DPS (declared on the year) | B46: dps | D46: 0 | E46: 0 | F46: 0 | G46: 0 | H46: =(MAX(H45,0)*H23) | I46: =(MAX(I45,0)*I23) | J46: =(MAX(J45,0)*J23) | K46: =(MAX(K45,0)*K23) | L46: =(MAX(L45,0)*L23) | M46: =(MAX(M45,0)*M23) | N46: =(MAX(N45,0)*N23) | O46: =(MAX(O45,0)*O23) | ... Q46: =(MAX(Q45,0)*Q23)
A47: Dividends paid | B47: dividends_paid | H47: =IF($C$7=0,0,(G46*G44)/$C$7) | I47: =IF($C$7=0,0,(H46*H44)/$C$7) | J47: =IF($C$7=0,0,(I46*I44)/$C$7) | K47: =IF($C$7=0,0,(J46*J44)/$C$7) | L47: =IF($C$7=0,0,(K46*K44)/$C$7) | M47: =IF($C$7=0,0,(L46*L44)/$C$7) | N47: =IF($C$7=0,0,(M46*M44)/$C$7) | O47: =IF($C$7=0,0,(N46*N44)/$C$7) | ... Q47: =IF($C$7=0,0,(P46*P44)/$C$7)
A48: Capital expenditure | B48: capex | D48: 625.05649 | E48: 18.033073 | F48: 2.9837958 | G48: 6.5800333 | H48: =(H29*H15) | I48: =(I29*I15) | J48: =(J29*J15) | K48: =(K29*K15) | L48: =(L29*L15) | M48: =(M29*M15) | N48: =(N29*N15) | O48: =(O29*O15) | ... Q48: =(Q29*Q15)
A49: Change in working capital | B49: delta_nwc | E49: -742.91722 | F49: -394.84354 | G49: 8.5098526 | H49: =(H54-G54) | I49: =(I54-H54) | J49: =(J54-I54) | K49: =(K54-J54) | L49: =(L54-K54) | M49: =(M54-L54) | N49: =(N54-M54) | O49: =(O54-N54) | ... Q49: =(Q54-P54)
A50: Free cash flow to firm | B50: fcff | E50: 176.64893 | F50: 299.23578 | G50: 3.7900043 | H50: =((((H33*(1-H17))+H34)-H48)-H49) | I50: =((((I33*(1-I17))+I34)-I48)-I49) | J50: =((((J33*(1-J17))+J34)-J48)-J49) | K50: =((((K33*(1-K17))+K34)-K48)-K49) | L50: =((((L33*(1-L17))+L34)-L48)-L49) | M50: =((((M33*(1-M17))+M34)-M48)-M49) | N50: =((((N33*(1-N17))+N34)-N48)-N49) | O50: =((((O33*(1-O17))+O34)-O48)-O49) | ... Q50: =((((Q33*(1-Q17))+Q34)-Q48)-Q49)
A51: Net borrowing | B51: net_borrowing | E51: -155.47422 | F51: 63.653592 | G51: 182.86125 | H51: =H20 | I51: =I20 | J51: =J20 | K51: =K20 | L51: =L20 | M51: =M20 | N51: =N20 | O51: =O20 | ... Q51: =Q20
A52: Dividends to minorities | B52: minority_div | H52: =(MAX(G42,0)*H23) | I52: =(MAX(H42,0)*I23) | J52: =(MAX(I42,0)*J23) | K52: =(MAX(J42,0)*K23) | L52: =(MAX(K42,0)*L23) | M52: =(MAX(L42,0)*M23) | N52: =(MAX(M42,0)*N23) | O52: =(MAX(N42,0)*O23) | ... Q52: =(MAX(P42,0)*Q23)
A53: Free cash flow to equity | B53: fcfe | H53: =(((((H41+H34)-H48)-H49)+H51)-H52) | I53: =(((((I41+I34)-I48)-I49)+I51)-I52) | J53: =(((((J41+J34)-J48)-J49)+J51)-J52) | K53: =(((((K41+K34)-K48)-K49)+K51)-K52) | L53: =(((((L41+L34)-L48)-L49)+L51)-L52) | M53: =(((((M41+M34)-M48)-M49)+M51)-M52) | N53: =(((((N41+N34)-N48)-N49)+N51)-N52) | O53: =(((((O41+O34)-O48)-O49)+O51)-O52) | ... Q53: =(((((Q41+Q34)-Q48)-Q49)+Q51)-Q52)
A54: Operating working capital | B54: nwc | D54: 1779.3108 | E54: 1036.3936 | F54: 641.55008 | G54: 650.05993 | H54: =(H29*H16) | I54: =(I29*I16) | J54: =(J29*J16) | K54: =(K29*K16) | L54: =(L29*L16) | M54: =(M29*M16) | N54: =(N29*N16) | O54: =(O29*O16) | ... Q54: =(Q29*Q16)
A55: Cash & equivalents | B55: cash | D55: 171.15493 | E55: 28.002933 | F55: 7.1609128 | G55: 6.0373086 | H55: =(((((((G55+H41)+H34)-H48)-H49)+H51)-H47)-H52) | I55: =(((((((H55+I41)+I34)-I48)-I49)+I51)-I47)-I52) | J55: =(((((((I55+J41)+J34)-J48)-J49)+J51)-J47)-J52) | K55: =(((((((J55+K41)+K34)-K48)-K49)+K51)-K47)-K52) | L55: =(((((((K55+L41)+L34)-L48)-L49)+L51)-L47)-L52) | M55: =(((((((L55+M41)+M34)-M48)-M49)+M51)-M47)-M52) | N55: =(((((((M55+N41)+N34)-N48)-N49)+N51)-N47)-N52) | O55: =(((((((N55+O41)+O34)-O48)-O49)+O51)-O47)-O52) | ... Q55: =(((((((P55+Q41)+Q34)-Q48)-Q49)+Q51)-Q47)-Q52)
A56: Total debt | B56: debt | D56: 2969.9952 | E56: 2814.521 | F56: 2878.1745 | G56: 3061.0358 | H56: =(G56+H51) | I56: =(H56+I51) | J56: =(I56+J51) | K56: =(J56+K51) | L56: =(K56+L51) | M56: =(L56+M51) | N56: =(M56+N51) | O56: =(N56+O51) | ... Q56: =(P56+Q51)
A57: Fixed assets (net) | B57: ppe | D57: 2952.5916 | E57: 2853.2949 | F57: 2870.9306 | G57: 2813.0408 | H57: =((G57+H48)-H34) | I57: =((H57+I48)-I34) | J57: =((I57+J48)-J34) | K57: =((J57+K48)-K34) | L57: =((K57+L48)-L34) | M57: =((L57+M48)-M34) | N57: =((M57+N48)-N34) | O57: =((N57+O48)-O34) | ... Q57: =((P57+Q48)-Q34)
A58: Parent shareholders' equity | B58: equity | D58: 1798.6321 | E58: 924.86609 | F58: 424.58404 | G58: 254.65811 | H58: =((G58+H43)-H47) | I58: =((H58+I43)-I47) | J58: =((I58+J43)-J47) | K58: =((J58+K43)-K47) | L58: =((K58+L43)-L47) | M58: =((L58+M43)-M47) | N58: =((M58+N43)-N47) | O58: =((N58+O43)-O47) | ... Q58: =((P58+Q43)-Q47)
A59: Minority interest (balance sheet) | B59: minority_bs | D59: 298.51945 | E59: 293.32862 | F59: 268.73972 | G59: 247.4428 | H59: =((G59+H42)-H52) | I59: =((H59+I42)-I52) | J59: =((I59+J42)-J52) | K59: =((J59+K42)-K52) | L59: =((K59+L42)-L52) | M59: =((L59+M42)-M52) | N59: =((M59+N42)-N52) | O59: =((N59+O42)-O52) | ... Q59: =((P59+Q42)-Q52)
A60: Other assets less other liabilities | B60: other_net | D60: 164.08937 | E60: 115.02423 | F60: 51.85676 | G60: 93.998658 | H60: =G60 | I60: =H60 | J60: =I60 | K60: =J60 | L60: =K60 | M60: =L60 | N60: =M60 | O60: =N60 | ... Q60: =P60
A61: Balance check (should be zero) | B61: bs_check | H61: =((((((H55+H54)+H57)+H60)-H56)-H58)-H59) | I61: =((((((I55+I54)+I57)+I60)-I56)-I58)-I59) | J61: =((((((J55+J54)+J57)+J60)-J56)-J58)-J59) | K61: =((((((K55+K54)+K57)+K60)-K56)-K58)-K59) | L61: =((((((L55+L54)+L57)+L60)-L56)-L58)-L59) | M61: =((((((M55+M54)+M57)+M60)-M56)-M58)-M59) | N61: =((((((N55+N54)+N57)+N60)-N56)-N58)-N59) | O61: =((((((O55+O54)+O57)+O60)-O56)-O58)-O59) | ... Q61: =((((((Q55+Q54)+Q57)+Q60)-Q56)-Q58)-Q59)
A62: Net debt (cash) | B62: net_debt | D62: 2798.8402 | E62: 2786.518 | F62: 2871.0136 | G62: 3054.9985 | H62: =(H56-H55) | I62: =(I56-I55) | J62: =(J56-J55) | K62: =(K56-K55) | L62: =(L56-L55) | M62: =(M56-M55) | N62: =(N56-N55) | O62: =(O56-O55) | ... Q62: =(Q56-Q55)
A63: Book value per share | B63: bvps | D63: 61.13845 | E63: 31.437713 | F63: 14.432307 | G63: 8.6562462 | H63: =(IF(H44=0,0,H58/H44)*$C$7) | I63: =(IF(I44=0,0,I58/I44)*$C$7) | J63: =(IF(J44=0,0,J58/J44)*$C$7) | K63: =(IF(K44=0,0,K58/K44)*$C$7) | L63: =(IF(L44=0,0,L58/L44)*$C$7) | M63: =(IF(M44=0,0,M58/M44)*$C$7) | N63: =(IF(N44=0,0,N58/N44)*$C$7) | O63: =(IF(O44=0,0,O58/O44)*$C$7) | ... Q63: =(IF(Q44=0,0,Q58/Q44)*$C$7)
A64: Revenue growth | B64: revenue_growth | E64: -0.79334621 | F64: -0.36849129 | G64: 0.76621295 | H64: =(IF(G29=0,0,H29/G29)-1) | I64: =(IF(H29=0,0,I29/H29)-1) | J64: =(IF(I29=0,0,J29/I29)-1) | K64: =(IF(J29=0,0,K29/J29)-1) | L64: =(IF(K29=0,0,L29/K29)-1) | M64: =(IF(L29=0,0,M29/L29)-1) | N64: =(IF(M29=0,0,N29/M29)-1) | O64: =(IF(N29=0,0,O29/N29)-1) | ... Q64: =(IF(P29=0,0,Q29/P29)-1)
A65: Gross margin | B65: gross_margin | D65: 0.076862026 | E65: -0.40814133 | F65: -0.1662915 | G65: 0.0027540387 | H65: =IF(H29=0,0,H31/H29) | I65: =IF(I29=0,0,I31/I29) | J65: =IF(J29=0,0,J31/J29) | K65: =IF(K29=0,0,K31/K29) | L65: =IF(L29=0,0,L31/L29) | M65: =IF(M29=0,0,M31/M29) | N65: =IF(N29=0,0,N31/N29) | O65: =IF(O29=0,0,O31/O29) | ... Q65: =IF(Q29=0,0,Q31/Q29)
A66: EBITDA margin | B66: ebitda_margin | D66: -0.010170088 | E66: -0.61036679 | F66: -0.21456862 | G66: 0.0040220283 | H66: =IF(H29=0,0,H35/H29) | I66: =IF(I29=0,0,I35/I29) | J66: =IF(J29=0,0,J35/J29) | K66: =IF(K29=0,0,K35/K29) | L66: =IF(L29=0,0,L35/L29) | M66: =IF(M29=0,0,M35/M29) | N66: =IF(N29=0,0,N35/N29) | O66: =IF(O29=0,0,O35/O29) | ... Q66: =IF(Q29=0,0,Q35/Q29)
A67: EBIT margin | B67: ebit_margin | D67: -0.022047825 | E67: -0.67952772 | F67: -0.39168723 | G67: -0.099668611 | H67: =IF(H29=0,0,H33/H29) | I67: =IF(I29=0,0,I33/I29) | J67: =IF(J29=0,0,J33/J29) | K67: =IF(K29=0,0,K33/K29) | L67: =IF(L29=0,0,L33/L29) | M67: =IF(M29=0,0,M33/M29) | N67: =IF(N29=0,0,N33/N29) | O67: =IF(O29=0,0,O33/O29) | ... Q67: =IF(Q29=0,0,Q33/Q29)
A68: Net margin | B68: np_margin | D68: -0.070070338 | E68: -0.96516891 | F68: -0.99102562 | G68: -0.20985123 | H68: =IF(H29=0,0,H43/H29) | I68: =IF(I29=0,0,I43/I29) | J68: =IF(J29=0,0,J43/J29) | K68: =IF(K29=0,0,K43/K29) | L68: =IF(L29=0,0,L43/L29) | M68: =IF(M29=0,0,M43/M29) | N68: =IF(N29=0,0,N43/N29) | O68: =IF(O29=0,0,O43/O29) | ... Q68: =IF(Q29=0,0,Q43/Q29)
A69: EPS growth | B69: eps_growth | E69: 1.8465085 | F69: -0.35157328 | G69: -0.62600163 | H69: =(IF(G45=0,0,H45/G45)-1) | I69: =(IF(H45=0,0,I45/H45)-1) | J69: =(IF(I45=0,0,J45/I45)-1) | K69: =(IF(J45=0,0,K45/J45)-1) | L69: =(IF(K45=0,0,L45/K45)-1) | M69: =(IF(L45=0,0,M45/L45)-1) | N69: =(IF(M45=0,0,N45/M45)-1) | O69: =(IF(N45=0,0,O45/N45)-1) | ... Q69: =(IF(P45=0,0,Q45/P45)-1)
A70: ROE | B70: roe | E70: -0.64301604 | F70: -0.84149774 | G70: -0.6252517 | H70: =IF(IF(2=0,0,(H58+G58)/2)=0,0,H43/IF(2=0,0,(H58+G58)/2)) | I70: =IF(IF(2=0,0,(I58+H58)/2)=0,0,I43/IF(2=0,0,(I58+H58)/2)) | J70: =IF(IF(2=0,0,(J58+I58)/2)=0,0,J43/IF(2=0,0,(J58+I58)/2)) | K70: =IF(IF(2=0,0,(K58+J58)/2)=0,0,K43/IF(2=0,0,(K58+J58)/2)) | L70: =IF(IF(2=0,0,(L58+K58)/2)=0,0,L43/IF(2=0,0,(L58+K58)/2)) | M70: =IF(IF(2=0,0,(M58+L58)/2)=0,0,M43/IF(2=0,0,(M58+L58)/2)) | N70: =IF(IF(2=0,0,(N58+M58)/2)=0,0,N43/IF(2=0,0,(N58+M58)/2)) | O70: =IF(IF(2=0,0,(O58+N58)/2)=0,0,O43/IF(2=0,0,(O58+N58)/2)) | ... Q70: =IF(IF(2=0,0,(Q58+P58)/2)=0,0,Q43/IF(2=0,0,(Q58+P58)/2))
A71: Net debt / EBITDA | B71: net_debt_ebitda | D71: -62.687533 | E71: -5.032171 | F71: -23.354692 | G71: 750.63342 | H71: =IF(H35=0,0,H62/H35) | I71: =IF(I35=0,0,I62/I35) | J71: =IF(J35=0,0,J62/J35) | K71: =IF(K35=0,0,K62/K35) | L71: =IF(L35=0,0,L62/L35) | M71: =IF(M35=0,0,M62/M35) | N71: =IF(N35=0,0,N62/N35) | O71: =IF(O35=0,0,O62/O35) | ... Q71: =IF(Q35=0,0,Q62/Q35)
A72: Payout ratio | B72: payout_ratio | D72: 0 | E72: 0 | F72: 0 | G72: 0 | H72: =IF(H45=0,0,H46/H45) | I72: =IF(I45=0,0,I46/I45) | J72: =IF(J45=0,0,J46/J45) | K72: =IF(K45=0,0,K46/K45) | L72: =IF(L45=0,0,L46/L45) | M72: =IF(M45=0,0,M46/M45) | N72: =IF(N45=0,0,N46/N45) | O72: =IF(O45=0,0,O46/O45) | ... Q72: =IF(Q45=0,0,Q46/Q45)
A73: Capex / revenue | B73: capex_revenue | D73: 0.14237937 | E73: 0.019877152 | F73: 0.0052080384 | G73: 0.006502646 | H73: =IF(H29=0,0,H48/H29) | I73: =IF(I29=0,0,I48/I29) | J73: =IF(J29=0,0,J48/J29) | K73: =IF(K29=0,0,K48/K29) | L73: =IF(L29=0,0,L48/L29) | M73: =IF(M29=0,0,M48/M29) | N73: =IF(N29=0,0,N48/N29) | O73: =IF(O29=0,0,O48/O29) | ... Q73: =IF(Q29=0,0,Q48/Q29)
A75: VALUATION
A76: Last price (IDR) | C76: 25
A77: Shares outstanding (m) | C77: 29419
A78: IDR per USD (spot) | C78: 18110
A79: Debt at balance-sheet date | C79: 1890.9109
A80: Cash at balance-sheet date | C80: 26.191065
A81: Minority interest (book) | C81: 322.20694
A82: Associates & investments (book) | C82: 0
A83: Post-balance-sheet & other items (sourced, probability-weighted) | C83: 0
A84: Parent equity at balance-sheet date | C84: 390.14256
A85: Per-share factor | C85: 1000
A86: Risk-free rate | C86: =Drivers!$C$7
A87: Less: default spread (IDR only) | C87: =Drivers!$C$9
A88: Mature ERP + Indonesia CRP | C88: =Drivers!$C$10+Drivers!$C$11
A89: Tax rate | C89: =Drivers!$C$13
A90: Unlevered beta (industry default (config)) | C90: 0.9
A91: Debt / equity (market) | C91: 2
A92: Levered beta | C92: =$C$90*(1+(1-$C$89)*$C$91)
A93: Explicit company premium | C93: 0
A94: Cost of equity | C94: =$C$86-$C$87+$C$92*$C$88+$C$93
A95: Pre-tax cost of debt | C95: =$C$86+Drivers!$C$12
A96: WACC | C96: =1/(1+$C$91)*$C$94+$C$91/(1+$C$91)*$C$95*(1-$C$89)
A97: Terminal growth (capped) | C97: 0.03
A99: Sum of the parts
A100: Value per share (IDR) — Sum of the parts (engine value) | C100: 9.312716
A102: P/BV
A103: Target multiple (own five-year average) | C103: 1.254641
A104: Metric (LTM, or next-12m DPS for yield) | C104: 390.14256
A105: Value per share (IDR) — P/BV | C105: =MAX(0,$C$103*$C$104/$C$77*$C$85*1)
A107: TARGET
A108: Weight: Sum of the parts | C108: 0.8
...
