Workbook

Sheet README
A1: Six South — Gold, copper & base-metal miners industry model
A2: Generated 2026-10-31T18:43:22+07:00 by the coverage engine. The engine (scripts/cov_engine.py) is the source of truth; this workbook is a live rendering of it.
A3: Colour key: blue = input or hard-coded history; black = formula; green = link to another sheet.
A4: Drivers: every deck variable these models read. Change one and every ticker tab and the Comps sheet recalculate (forecasts, cash flows, DCF value, base-case value, target, rating).
A5: Scenario (bear/bull) and sensitivity tables need full model re-runs and are engine values.
A6: Paper fund — research for education and process transparency, not investment advice.
A8: Tickers:
A9: BRMS.JK — PT Bumi Resources Minerals Tbk

Sheet Drivers
A1: Driver decks (state/drivers) — edit a blue cell to flow it through every ticker tab
A3: Variable | B3: Key | C3: Unit / status | D3: FY2022A | E3: FY2023A | F3: FY2024A | G3: FY2025A | H3: FY2026E | I3: FY2027E | J3: FY2028E | K3: FY2029E | L3: FY2030E | M3: FY2031E | N3: FY2032E | O3: FY2033E | P3: FY2034E | Q3: FY2035E | R3: FY2036E | S3: FY2037E | T3: FY2038E | U3: FY2039E | V3: FY2040E | W3: FY2041E | X3: FY2042E | Y3: FY2043E | Z3: FY2044E | AA3: FY2045E | AB3: FY2046E | AC3: FY2047E | AD3: FY2048E | AE3: FY2049E | AF3: FY2050E
A4: IDR per USD | B4: m.usd_idr | C4: IDR/USD · reviewed | D4: 14843.177 | E4: 15228.8 | F4: 15846.238 | G4: 16448.093 | H4: 17570 | I4: 18350 | J4: 18600 | K4: 18850 | L4: 19093.137 | M4: 19186.731 | N4: 19280.784 | O4: 19375.297 | P4: 19470.274 | Q4: 19565.717 | R4: 19661.627 | S4: 19758.008 | T4: 19854.861 | U4: 19952.188 | V4: 20049.993 | W4: 20148.278 | X4: 20247.044 | Y4: 20346.294 | Z4: 20446.031 | AA4: 20546.256 | AB4: 20646.973 | AC4: 20748.184 | AD4: 20849.891 | AE4: 20952.096 | AF4: 21054.802
A5: Gold | B5: d.metals.gold | C5: USD/oz · reviewed | D5: 1805.1916 | E5: 1954.5195 | F5: 2404.7131 | G5: 3466.0889 | H5: 4493.75 | I5: 4300 | J5: 4300 | K5: 4300 | L5: 4386 | M5: 4473.72 | N5: 4563.1944 | O5: 4654.4583 | P5: 4747.5475 | Q5: 4842.4984 | R5: 4939.3484 | S5: 5038.1353 | T5: 5138.898 | U5: 5241.676 | V5: 5346.5095 | W5: 5453.4397 | X5: 5562.5085 | Y5: 5673.7587 | Z5: 5787.2339 | AA5: 5902.9785 | AB5: 6021.0381 | AC5: 6141.4589 | AD5: 6264.288 | AE5: 6389.5738 | AF5: 6517.3653
A6: Brent crude | B6: d.oil.brent | C6: USD/bbl · reviewed | D6: 98.9663 | E6: 82.1904 | F6: 79.8213 | G6: 68.1015 | H6: 96 | I6: 84 | J6: 80 | K6: 78 | L6: 76.5 | M6: 78.03 | N6: 79.5906 | O6: 81.182412 | P6: 82.80606 | Q6: 84.462181 | R6: 86.151425 | S6: 87.874454 | T6: 89.631943 | U6: 91.424581 | V6: 93.253073 | W6: 95.118135 | X6: 97.020497 | Y6: 98.960907 | Z6: 100.94013 | AA6: 102.95893 | AB6: 105.01811 | AC6: 107.11847 | AD6: 109.26084 | AE6: 111.44605 | AF6: 113.67498
A8: Cost-of-capital scalars (macro deck)
A9: 10-year Indonesian government bond yield (IDR) | B9: m.rf_idr | C9: 0.0745 | D9: investor.id — "Yield SUN 7,45%, Saatnya Borong atau Tunggu Lebih Tinggi?" (25 Okt 2026 20:58 WIB; deck source S3); corroborated by kalderanews S1 (10Y SUN 7.41%
A10: 10-year US Treasury yield | B10: m.rf_usd | C10: 0.04929 | D10: Yahoo Finance ^TNX (US 10-year Treasury yield)
A11: Indonesia sovereign default spread (Damodaran) | B11: m.default_spread_id | C11: 0.0162 | D11: Damodaran country risk premiums (https://pages.stern.nyu.edu/~adamodar/New_Home_Page/datafile/ctryprem.html), page dated January 5, 2026, read 2026-10-31
A12: Mature-market equity risk premium (Damodaran) | B12: m.erp_mature | C12: 0.0423 | D12: Damodaran country risk premiums (https://pages.stern.nyu.edu/~adamodar/New_Home_Page/datafile/ctryprem.html), page dated January 5, 2026, read 2026-10-31
A13: Indonesia country risk premium (Damodaran) | B13: m.crp_id | C13: 0.0246 | D13: Damodaran country risk premiums (https://pages.stern.nyu.edu/~adamodar/New_Home_Page/datafile/ctryprem.html), page dated January 5, 2026, read 2026-10-31
A14: House pre-tax corporate debt spread over the risk-free | B14: m.debt_spread_corp | C14: 0.02 | D14: SEED house assumption pending the macro desk: 200 bp over the risk-free rate for an average IDX corporate borrower
A15: Indonesia statutory corporate income tax rate | B15: m.tax_rate_id | C15: 0.22 | D15: Law 7/2021 on Harmonisation of Tax Regulations (UU HPP): 22% corporate income tax from fiscal 2022

Sheet Comps
A1: Ticker | B1: Company | C1: Rating | D1: Target (IDR) | E1: Price (IDR) | F1: Exp. 12m TR | G1: Value today | H1: P/E FY+0 | I1: EV/EBITDA FY+0 | J1: Div. yield FY+0
A2: BRMS.JK | B2: PT Bumi Resources Minerals Tbk | C2: ='BRMS'!$C$160 | D2: ='BRMS'!$C$158 | E2: ='BRMS'!$C$102 | F2: ='BRMS'!$C$159 | G2: ='BRMS'!$C$139 | H2: 45.126904 | I2: 23.790173 | J2: 0

Sheet BRMS
A1: PT Bumi Resources Minerals Tbk (BRMS.JK) — Gold, copper & base-metal miners
A2: Units: USD m; per-share in USD unless marked IDR. Model asof 2026-10-31 · data 2026-10-30
A4: Line | C4: Scalar | D4: FY2022A | E4: FY2023A | F4: FY2024A | G4: FY2025A | H4: FY2026E | I4: FY2027E | J4: FY2028E | K4: FY2029E | L4: FY2030E | M4: FY2031E | N4: FY2032E | O4: FY2033E | P4: FY2034E | Q4: FY2035E | R4: FY2036E | S4: FY2037E | T4: FY2038E | U4: FY2039E | V4: FY2040E | W4: FY2041E | X4: FY2042E | Y4: FY2043E | Z4: FY2044E | AA4: FY2045E | AB4: FY2046E | AC4: FY2047E | AD4: FY2048E | AE4: FY2049E | AF4: FY2050E
A6: PARAMETERS
A7: horizon | C7: 25
A8: ps_factor | C8: 1
A9: reserves | C9: 3500
A10: unit_factor | C10: 0.001
A11: vp_factor | C11: 1
A13: INPUTS (company assumptions)
A14: Sales volume plan | B14: a.volume | H14: 54.6 | I14: 80 | J14: 140 | K14: 165 | L14: 165 | M14: 165 | N14: 165 | O14: 165 | P14: 165 | Q14: 165 | R14: 165 | S14: 165 | T14: 165 | U14: 165 | V14: 165 | W14: 165 | X14: 165 | Y14: 165 | Z14: 165 | AA14: 165 | AB14: 165 | AC14: 165 | AD14: 165 | AE14: 165 | AF14: 165
A15: Realised price / benchmark | B15: a.realisation | H15: 0.9726 | I15: 0.9726 | J15: 0.9726 | K15: 0.9726 | L15: 0.9726 | M15: 0.9726 | N15: 0.9726 | O15: 0.9726 | P15: 0.9726 | Q15: 0.9726 | R15: 0.9726 | S15: 0.9726 | T15: 0.9726 | U15: 0.9726 | V15: 0.9726 | W15: 0.9726 | X15: 0.9726 | Y15: 0.9726 | Z15: 0.9726 | AA15: 0.9726 | AB15: 0.9726 | AC15: 0.9726 | AD15: 0.9726 | AE15: 0.9726 | AF15: 0.9726
A16: Share of volume under a price cap (e.g. DMO) | B16: a.capped_share | H16: 0 | I16: 0 | J16: 0 | K16: 0 | L16: 0 | M16: 0 | N16: 0 | O16: 0 | P16: 0 | Q16: 0 | R16: 0 | S16: 0 | T16: 0 | U16: 0 | V16: 0 | W16: 0 | X16: 0 | Y16: 0 | Z16: 0 | AA16: 0 | AB16: 0 | AC16: 0 | AD16: 0 | AE16: 0 | AF16: 0
A17: Strip ratio (bcm per tonne) or cost-intensity factor | B17: a.strip_ratio | H17: 1 | I17: 1 | J17: 1 | K17: 1 | L17: 1 | M17: 1 | N17: 1 | O17: 1 | P17: 1 | Q17: 1 | R17: 1 | S17: 1 | T17: 1 | U17: 1 | V17: 1 | W17: 1 | X17: 1 | Y17: 1 | Z17: 1 | AA17: 1 | AB17: 1 | AC17: 1 | AD17: 1 | AE17: 1 | AF17: 1
A18: Mining cost per bcm (or per unit when intensity is 1) | B18: a.cost_per_bcm | H18: 503.4 | I18: 503.4 | J18: 503.4 | K18: 503.4 | L18: 503.4 | M18: 513.468 | N18: 523.73736 | O18: 534.21211 | P18: 544.89635 | Q18: 555.79428 | R18: 566.91016 | S18: 578.24837 | T18: 589.81333 | U18: 601.6096 | V18: 613.64179 | W18: 625.91463 | X18: 638.43292 | Y18: 651.20158 | Z18: 664.22561 | AA18: 677.51012 | AB18: 691.06032 | AC18: 704.88153 | AD18: 718.97916 | AE18: 733.35874 | AF18: 748.02592
A19: Fuel share of mining cost | B19: a.fuel_share | C19: 0.3
A20: Other cash cost per unit (haul, barge, process) | B20: a.other_cost_unit | H20: 425.8 | I20: 425.8 | J20: 425.8 | K20: 425.8 | L20: 425.8 | M20: 434.316 | N20: 443.00232 | O20: 451.86237 | P20: 460.89961 | Q20: 470.11761 | R20: 479.51996 | S20: 489.11036 | T20: 498.89256 | U20: 508.87042 | V20: 519.04782 | W20: 529.42878 | X20: 540.01736 | Y20: 550.8177 | Z20: 561.83406 | AA20: 573.07074 | AB20: 584.53215 | AC20: 596.2228 | AD20: 608.14725 | AE20: 620.3102 | AF20: 632.7164
A21: Royalty rate (flat regimes) | B21: a.royalty_rate | H21: 0.16 | I21: 0.16 | J21: 0.16 | K21: 0.16 | L21: 0.16 | M21: 0.16 | N21: 0.16 | O21: 0.16 | P21: 0.16 | Q21: 0.16 | R21: 0.16 | S21: 0.16 | T21: 0.16 | U21: 0.16 | V21: 0.16 | W21: 0.16 | X21: 0.16 | Y21: 0.16 | Z21: 0.16 | AA21: 0.16 | AB21: 0.16 | AC21: 0.16 | AD21: 0.16 | AE21: 0.16 | AF21: 0.16
A22: Other revenue | B22: a.other_revenue | H22: 7 | I22: 7 | J22: 7 | K22: 7 | L22: 7 | M22: 7.14 | N22: 7.2828 | O22: 7.428456 | P22: 7.5770251 | Q22: 7.7285656 | R22: 7.8831369 | S22: 8.0407997 | T22: 8.2016157 | U22: 8.365648 | V22: 8.5329609 | W22: 8.7036202 | X22: 8.8776926 | Y22: 9.0552464 | Z22: 9.2363513 | AA22: 9.4210784 | AB22: 9.6094999 | AC22: 9.8016899 | AD22: 9.9977237 | AE22: 10.197678 | AF22: 10.401632
A23: Gross margin on other revenue | B23: a.other_margin | C23: 1
A24: D&A per unit (reporting currency) | B24: a.da_unit | H24: 126.1 | I24: 126.1 | J24: 126.1 | K24: 126.1 | L24: 126.1 | M24: 128.622 | N24: 131.19444 | O24: 133.81833 | P24: 136.4947 | Q24: 139.22459 | R24: 142.00908 | S24: 144.84926 | T24: 147.74625 | U24: 150.70117 | V24: 153.7152 | W24: 156.7895 | X24: 159.92529 | Y24: 163.1238 | Z24: 166.38627 | AA24: 169.714 | AB24: 173.10828 | AC24: 176.57044 | AD24: 180.10185 | AE24: 183.70389 | AF24: 187.37797
A25: Sustaining capex per unit (reporting currency) | B25: a.capex_unit | H25: 130 | I25: 130 | J25: 130 | K25: 130 | L25: 130 | M25: 132.6 | N25: 135.252 | O25: 137.95704 | P25: 140.71618 | Q25: 143.5305 | R25: 146.40111 | S25: 149.32914 | T25: 152.31572 | U25: 155.36203 | V25: 158.46927 | W25: 161.63866 | X25: 164.87143 | Y25: 168.16886 | Z25: 171.53224 | AA25: 174.96288 | AB25: 178.46214 | AC25: 182.03138 | AD25: 185.67201 | AE25: 189.38545 | AF25: 193.17316
A26: Other capex (expansion projects) | B26: a.capex_other | H26: 150 | I26: 200 | J26: 75 | K26: 0 | L26: 0 | M26: 0 | N26: 0 | O26: 0 | P26: 0 | Q26: 0 | R26: 0 | S26: 0 | T26: 0 | U26: 0 | V26: 0 | W26: 0 | X26: 0 | Y26: 0 | Z26: 0 | AA26: 0 | AB26: 0 | AC26: 0 | AD26: 0 | AE26: 0 | AF26: 0
A27: Operating working capital / revenue | B27: a.nwc_pct | H27: 0.04 | I27: 0.04 | J27: 0.04 | K27: 0.04 | L27: 0.04 | M27: 0.04 | N27: 0.04 | O27: 0.04 | P27: 0.04 | Q27: 0.04 | R27: 0.04 | S27: 0.04 | T27: 0.04 | U27: 0.04 | V27: 0.04 | W27: 0.04 | X27: 0.04 | Y27: 0.04 | Z27: 0.04 | AA27: 0.04 | AB27: 0.04 | AC27: 0.04 | AD27: 0.04 | AE27: 0.04 | AF27: 0.04
A28: Effective tax rate | B28: a.tax_rate | H28: 0.244 | I28: 0.244 | J28: 0.244 | K28: 0.244 | L28: 0.244 | M28: 0.244 | N28: 0.244 | O28: 0.244 | P28: 0.244 | Q28: 0.244 | R28: 0.244 | S28: 0.244 | T28: 0.244 | U28: 0.244 | V28: 0.244 | W28: 0.244 | X28: 0.244 | Y28: 0.244 | Z28: 0.244 | AA28: 0.244 | AB28: 0.244 | AC28: 0.244 | AD28: 0.244 | AE28: 0.244 | AF28: 0.244
A29: Cost of debt (on opening debt) | B29: a.cost_of_debt | C29: 0.12
A30: Yield on opening cash | B30: a.cash_yield | C30: 0.05
A31: Net new borrowing | B31: a.net_borrowing | H31: 117 | I31: 80 | J31: 30 | K31: 0 | L31: 0 | M31: 0 | N31: 0 | O31: 0 | P31: 0 | Q31: 0 | R31: 0 | S31: 0 | T31: 0 | U31: 0 | V31: 0 | W31: 0 | X31: 0 | Y31: 0 | Z31: 0 | AA31: 0 | AB31: 0 | AC31: 0 | AD31: 0 | AE31: 0 | AF31: 0
A32: Other non-operating items | B32: a.other_nonop | H32: 0 | I32: 0 | J32: 0 | K32: 0 | L32: 0 | M32: 0 | N32: 0 | O32: 0 | P32: 0 | Q32: 0 | R32: 0 | S32: 0 | T32: 0 | U32: 0 | V32: 0 | W32: 0 | X32: 0 | Y32: 0 | Z32: 0 | AA32: 0 | AB32: 0 | AC32: 0 | AD32: 0 | AE32: 0 | AF32: 0
A33: Minorities' share of net profit | B33: a.minority_pct | H33: 0.0164 | I33: 0.0164 | J33: 0.0164 | K33: 0.0164 | L33: 0.0164 | M33: 0.0164 | N33: 0.0164 | O33: 0.0164 | P33: 0.0164 | Q33: 0.0164 | R33: 0.0164 | S33: 0.0164 | T33: 0.0164 | U33: 0.0164 | V33: 0.0164 | W33: 0.0164 | X33: 0.0164 | Y33: 0.0164 | Z33: 0.0164 | AA33: 0.0164 | AB33: 0.0164 | AC33: 0.0164 | AD33: 0.0164 | AE33: 0.0164 | AF33: 0.0164
A34: Dividend payout | B34: a.payout | H34: 0 | I34: 0 | J34: 0 | K34: 0 | L34: 0 | M34: 0 | N34: 0 | O34: 0 | P34: 0 | Q34: 0 | R34: 0 | S34: 0 | T34: 0 | U34: 0 | V34: 0 | W34: 0 | X34: 0 | Y34: 0 | Z34: 0 | AA34: 0 | AB34: 0 | AC34: 0 | AD34: 0 | AE34: 0 | AF34: 0
A35: Change in share count | B35: a.share_change | H35: 0 | I35: 0 | J35: 0 | K35: 0 | L35: 0 | M35: 0 | N35: 0 | O35: 0 | P35: 0 | Q35: 0 | R35: 0 | S35: 0 | T35: 0 | U35: 0 | V35: 0 | W35: 0 | X35: 0 | Y35: 0 | Z35: 0 | AA35: 0 | AB35: 0 | AC35: 0 | AD35: 0 | AE35: 0 | AF35: 0
A36: Terminal growth (DCF) | B36: a.terminal_growth | C36: 0.02
A37: SG&A / revenue | B37: a.opex_pct | H37: 0.189 | I37: 0.189 | J37: 0.189 | K37: 0.189 | L37: 0.189 | M37: 0.189 | N37: 0.189 | O37: 0.189 | P37: 0.189 | Q37: 0.189 | R37: 0.189 | S37: 0.189 | T37: 0.189 | U37: 0.189 | V37: 0.189 | W37: 0.189 | X37: 0.189 | Y37: 0.189 | Z37: 0.189 | AA37: 0.189 | AB37: 0.189 | AC37: 0.189 | AD37: 0.189 | AE37: 0.189 | AF37: 0.189
A39: MODEL
A40: Reserves remaining (close) | B40: reserves | G40: 3500 | H40: =MAX((G40-H41),0) | I40: =MAX((H40-I41),0) | J40: =MAX((I40-J41),0) | K40: =MAX((J40-K41),0) | L40: =MAX((K40-L41),0) | M40: =MAX((L40-M41),0) | N40: =MAX((M40-N41),0) | O40: =MAX((N40-O41),0) | ... AF40: =MAX((AE40-AF41),0)
A41: Sales volume | B41: volume | F41: 64.983 | G41: 71.886 | H41: =IF(($C$9>0),MIN(H14,MAX(G40,0)),H14) | I41: =IF(($C$9>0),MIN(I14,MAX(H40,0)),I14) | J41: =IF(($C$9>0),MIN(J14,MAX(I40,0)),J14) | K41: =IF(($C$9>0),MIN(K14,MAX(J40,0)),K14) | L41: =IF(($C$9>0),MIN(L14,MAX(K40,0)),L14) | M41: =IF(($C$9>0),MIN(M14,MAX(L40,0)),M14) | N41: =IF(($C$9>0),MIN(N14,MAX(M40,0)),N14) | O41: =IF(($C$9>0),MIN(O14,MAX(N40,0)),O14) | ... AF41: =IF(($C$9>0),MIN(AF14,MAX(AE40,0)),AF14)
A42: Benchmark price | B42: benchmark | H42: =Drivers!$H$5 | I42: =Drivers!$I$5 | J42: =Drivers!$J$5 | K42: =Drivers!$K$5 | L42: =Drivers!$L$5 | M42: =Drivers!$M$5 | N42: =Drivers!$N$5 | O42: =Drivers!$O$5 | P42: =Drivers!$P$5 | Q42: =Drivers!$Q$5 | R42: =Drivers!$R$5 | S42: =Drivers!$S$5 | T42: =Drivers!$T$5 | U42: =Drivers!$U$5 | V42: =Drivers!$V$5 | W42: =Drivers!$W$5 | X42: =Drivers!$X$5 | Y42: =Drivers!$Y$5 | Z42: =Drivers!$Z$5 | AA42: =Drivers!$AA$5 | AB42: =Drivers!$AB$5 | AC42: =Drivers!$AC$5 | AD42: =Drivers!$AD$5 | AE42: =Drivers!$AE$5 | AF42: =Drivers!$AF$5
A43: Average selling price | B43: asp | F43: 2442 | G43: 3371 | H43: =(H15*H42) | I43: =(I15*I42) | J43: =(J15*J42) | K43: =(K15*K42) | L43: =(L15*L42) | M43: =(M15*M42) | N43: =(N15*N42) | O43: =(O15*O42) | ... AF43: =(AF15*AF42)
A44: Realisation vs benchmark | B44: realisation_line | H44: =IF(H42=0,0,H43/H42) | I44: =IF(I42=0,0,I43/I42) | J44: =IF(J42=0,0,J43/J42) | K44: =IF(K42=0,0,K43/K42) | L44: =IF(L42=0,0,L43/L42) | M44: =IF(M42=0,0,M43/M42) | N44: =IF(N42=0,0,N43/N42) | O44: =IF(O42=0,0,O43/O42) | ... AF44: =IF(AF42=0,0,AF43/AF42)
A45: Cash cost per unit (ex-royalty) | B45: unit_cost | H45: =(((H17*H18)*(1+($C$19*(IF(Drivers!$G$6=0,0,Drivers!$H$6/Drivers!$G$6)-1))))+H20) | I45: =(((I17*I18)*(1+($C$19*(IF(Drivers!$G$6=0,0,Drivers!$I$6/Drivers!$G$6)-1))))+I20) | J45: =(((J17*J18)*(1+($C$19*(IF(Drivers!$G$6=0,0,Drivers!$J$6/Drivers!$G$6)-1))))+J20) | K45: =(((K17*K18)*(1+($C$19*(IF(Drivers!$G$6=0,0,Drivers!$K$6/Drivers!$G$6)-1))))+K20) | L45: =(((L17*L18)*(1+($C$19*(IF(Drivers!$G$6=0,0,Drivers!$L$6/Drivers!$G$6)-1))))+L20) | M45: =(((M17*M18)*(1+($C$19*(IF(Drivers!$G$6=0,0,Drivers!$M$6/Drivers!$G$6)-1))))+M20) | N45: =(((N17*N18)*(1+($C$19*(IF(Drivers!$G$6=0,0,Drivers!$N$6/Drivers!$G$6)-1))))+N20) | O45: =(((O17*O18)*(1+($C$19*(IF(Drivers!$G$6=0,0,Drivers!$O$6/Drivers!$G$6)-1))))+O20) | P45: =(((P17*P18)*(1+($C$19*(IF(Drivers!$G$6=0,0,Drivers!$P$6/Drivers!$G$6)-1))))+P20) | Q45: =(((Q17*Q18)*(1+($C$19*(IF(Drivers!$G$6=0,0,Drivers!$Q$6/Drivers!$G$6)-1))))+Q20) | R45: =(((R17*R18)*(1+($C$19*(IF(Drivers!$G$6=0,0,Drivers!$R$6/Drivers!$G$6)-1))))+R20) | S45: =(((S17*S18)*(1+($C$19*(IF(Drivers!$G$6=0,0,Drivers!$S$6/Drivers!$G$6)-1))))+S20) | T45: =(((T17*T18)*(1+($C$19*(IF(Drivers!$G$6=0,0,Drivers!$T$6/Drivers!$G$6)-1))))+T20) | U45: =(((U17*U18)*(1+($C$19*(IF(Drivers!$G$6=0,0,Drivers!$U$6/Drivers!$G$6)-1))))+U20) | V45: =(((V17*V18)*(1+($C$19*(IF(Drivers!$G$6=0,0,Drivers!$V$6/Drivers!$G$6)-1))))+V20) | W45: =(((W17*W18)*(1+($C$19*(IF(Drivers!$G$6=0,0,Drivers!$W$6/Drivers!$G$6)-1))))+W20) | X45: =(((X17*X18)*(1+($C$19*(IF(Drivers!$G$6=0,0,Drivers!$X$6/Drivers!$G$6)-1))))+X20) | Y45: =(((Y17*Y18)*(1+($C$19*(IF(Drivers!$G$6=0,0,Drivers!$Y$6/Drivers!$G$6)-1))))+Y20) | Z45: =(((Z17*Z18)*(1+($C$19*(IF(Drivers!$G$6=0,0,Drivers!$Z$6/Drivers!$G$6)-1))))+Z20) | AA45: =(((AA17*AA18)*(1+($C$19*(IF(Drivers!$G$6=0,0,Drivers!$AA$6/Drivers!$G$6)-1))))+AA20) | AB45: =(((AB17*AB18)*(1+($C$19*(IF(Drivers!$G$6=0,0,Drivers!$AB$6/Drivers!$G$6)-1))))+AB20) | AC45: =(((AC17*AC18)*(1+($C$19*(IF(Drivers!$G$6=0,0,Drivers!$AC$6/Drivers!$G$6)-1))))+AC20) | AD45: =(((AD17*AD18)*(1+($C$19*(IF(Drivers!$G$6=0,0,Drivers!$AD$6/Drivers!$G$6)-1))))+AD20) | AE45: =(((AE17*AE18)*(1+($C$19*(IF(Drivers!$G$6=0,0,Drivers!$AE$6/Drivers!$G$6)-1))))+AE20) | AF45: =(((AF17*AF18)*(1+($C$19*(IF(Drivers!$G$6=0,0,Drivers!$AF$6/Drivers!$G$6)-1))))+AF20)
A46: Strip ratio | B46: strip_ratio_line | H46: =H17 | I46: =I17 | J46: =J17 | K46: =K17 | L46: =L17 | M46: =M17 | N46: =N17 | O46: =O17 | ... AF46: =AF17
A47: Royalty rate | B47: royalty_rate | H47: =H21 | I47: =I21 | J47: =J21 | K47: =K21 | L47: =L21 | M47: =M21 | N47: =N21 | O47: =O21 | ... AF47: =AF21
A48: EBITDA per unit (price currency) | B48: ebitda_per_unit | F48: 737.69415 | G48: 1381.9896 | H48: =IF((H41*$C$10)=0,0,H61/(H41*$C$10)) | I48: =IF((I41*$C$10)=0,0,I61/(I41*$C$10)) | J48: =IF((J41*$C$10)=0,0,J61/(J41*$C$10)) | K48: =IF((K41*$C$10)=0,0,K61/(K41*$C$10)) | L48: =IF((L41*$C$10)=0,0,L61/(L41*$C$10)) | M48: =IF((M41*$C$10)=0,0,M61/(M41*$C$10)) | N48: =IF((N41*$C$10)=0,0,N61/(N41*$C$10)) | O48: =IF((O41*$C$10)=0,0,O61/(O41*$C$10)) | ... AF48: =IF((AF41*$C$10)=0,0,AF61/(AF41*$C$10))
A49: Cash cost + royalty per unit (price currency) | B49: cash_cost_money_per_unit | H49: =IF((H41*$C$10)=0,0,(H53+H52)/(H41*$C$10)) | I49: =IF((I41*$C$10)=0,0,(I53+I52)/(I41*$C$10)) | J49: =IF((J41*$C$10)=0,0,(J53+J52)/(J41*$C$10)) | K49: =IF((K41*$C$10)=0,0,(K53+K52)/(K41*$C$10)) | L49: =IF((L41*$C$10)=0,0,(L53+L52)/(L41*$C$10)) | M49: =IF((M41*$C$10)=0,0,(M53+M52)/(M41*$C$10)) | N49: =IF((N41*$C$10)=0,0,(N53+N52)/(N41*$C$10)) | O49: =IF((O41*$C$10)=0,0,(O53+O52)/(O41*$C$10)) | ... AF49: =IF((AF41*$C$10)=0,0,(AF53+AF52)/(AF41*$C$10))
A50: Main product revenue | B50: revenue_main | H50: =((H41*H43)*$C$10) | I50: =((I41*I43)*$C$10) | J50: =((J41*J43)*$C$10) | K50: =((K41*K43)*$C$10) | L50: =((L41*L43)*$C$10) | M50: =((M41*M43)*$C$10) | N50: =((N41*N43)*$C$10) | O50: =((O41*O43)*$C$10) | ... AF50: =((AF41*AF43)*$C$10)
A51: Other revenue | B51: other_revenue | H51: =H22 | I51: =I22 | J51: =J22 | K51: =K22 | L51: =L22 | M51: =M22 | N51: =N22 | O51: =O22 | ... AF51: =AF22
A52: Royalty | B52: royalty | H52: =(H50*H47) | I52: =(I50*I47) | J52: =(J50*J47) | K52: =(K50*K47) | L52: =(L50*L47) | M52: =(M50*M47) | N52: =(N50*N47) | O52: =(O50*O47) | ... AF52: =(AF50*AF47)
A53: Cash costs | B53: cash_cost | H53: =((H41*H45)*$C$10) | I53: =((I41*I45)*$C$10) | J53: =((J41*J45)*$C$10) | K53: =((K41*K45)*$C$10) | L53: =((L41*L45)*$C$10) | M53: =((M41*M45)*$C$10) | N53: =((N41*N45)*$C$10) | O53: =((O41*O45)*$C$10) | ... AF53: =((AF41*AF45)*$C$10)
A54: Cost of other revenue | B54: other_cogs | H54: =(H51*(1-$C$23)) | I54: =(I51*(1-$C$23)) | J54: =(J51*(1-$C$23)) | K54: =(K51*(1-$C$23)) | L54: =(L51*(1-$C$23)) | M54: =(M51*(1-$C$23)) | N54: =(N51*(1-$C$23)) | O54: =(O51*(1-$C$23)) | ... AF54: =(AF51*(1-$C$23))
A55: Revenue | B55: revenue | D55: 11.644445 | E55: 46.637766 | F55: 162.34478 | G55: 249.35435 | H55: =(H50+H51) | I55: =(I50+I51) | J55: =(J50+J51) | K55: =(K50+K51) | L55: =(L50+L51) | M55: =(M50+M51) | N55: =(N50+N51) | O55: =(O50+O51) | ... AF55: =(AF50+AF51)
A56: Cost of revenue | B56: cogs | D56: 5.077708 | E56: 20.380893 | F56: 82.678906 | G56: 109.13027 | H56: =(((H53+H52)+H54)+H60) | I56: =(((I53+I52)+I54)+I60) | J56: =(((J53+J52)+J54)+J60) | K56: =(((K53+K52)+K54)+K60) | L56: =(((L53+L52)+L54)+L60) | M56: =(((M53+M52)+M54)+M60) | N56: =(((N53+N52)+N54)+N60) | O56: =(((O53+O52)+O54)+O60) | ... AF56: =(((AF53+AF52)+AF54)+AF60)
A57: Gross profit | B57: gross_profit | D57: 6.566737 | E57: 26.256873 | F57: 79.665872 | G57: 140.22408 | H57: =(H55-H56) | I57: =(I55-I56) | J57: =(J55-J56) | K57: =(K55-K56) | L57: =(L55-L56) | M57: =(M55-M56) | N57: =(N55-N56) | O57: =(O55-O56) | ... AF57: =(AF55-AF56)
A58: SG&A and other opex | B58: opex | D58: 5.503434 | E58: 9.157616 | F58: 36.864656 | G58: 47.041906 | H58: =(H55*H37) | I58: =(I55*I37) | J58: =(J55*J37) | K58: =(K55*K37) | L58: =(L55*L37) | M58: =(M55*M37) | N58: =(N55*N37) | O58: =(O55*O37) | ... AF58: =(AF55*AF37)
A59: EBIT | B59: ebit | D59: 1.063303 | E59: 17.099257 | F59: 42.801216 | G59: 93.182174 | H59: =(H57-H58) | I59: =(I57-I58) | J59: =(J57-J58) | K59: =(K57-K58) | L59: =(L57-L58) | M59: =(M57-M58) | N59: =(N57-N58) | O59: =(O57-O58) | ... AF59: =(AF57-AF58)
A60: Depreciation & amortisation | B60: da | D60: 0.819211 | E60: 0.423992 | F60: 5.136363 | G60: 6.163532 | H60: =((H41*H24)*$C$10) | I60: =((I41*I24)*$C$10) | J60: =((J41*J24)*$C$10) | K60: =((K41*K24)*$C$10) | L60: =((L41*L24)*$C$10) | M60: =((M41*M24)*$C$10) | N60: =((N41*N24)*$C$10) | O60: =((O41*O24)*$C$10) | ... AF60: =((AF41*AF24)*$C$10)
A61: EBITDA | B61: ebitda | D61: 1.882514 | E61: 17.523249 | F61: 47.937579 | G61: 99.345706 | H61: =(H59+H60) | I61: =(I59+I60) | J61: =(J59+J60) | K61: =(K59+K60) | L61: =(L59+L60) | M61: =(M59+M60) | N61: =(N59+N60) | O61: =(O59+O60) | ... AF61: =(AF59+AF60)
A62: Interest expense | B62: interest_expense | D62: 0.049753 | E62: 0.03175 | F62: 9.171797 | G62: 18.118051 | H62: =(G82*$C$29) | I62: =(H82*$C$29) | J62: =(I82*$C$29) | K62: =(J82*$C$29) | L62: =(K82*$C$29) | M62: =(L82*$C$29) | N62: =(M82*$C$29) | O62: =(N82*$C$29) | ... AF62: =(AE82*$C$29)
A63: Interest income | B63: interest_income | D63: 0.356032 | E63: 0.073526 | F63: 0.379018 | G63: 0.592702 | H63: =(G81*$C$30) | I63: =(H81*$C$30) | J63: =(I81*$C$30) | K63: =(J81*$C$30) | L63: =(K81*$C$30) | M63: =(L81*$C$30) | N63: =(M81*$C$30) | O63: =(N81*$C$30) | ... AF63: =(AE81*$C$30)
A64: Other non-operating | B64: other_nonop | D64: 31.173338 | E64: 0.31818 | F64: -0.015531 | G64: -9.390037 | H64: =H32 | I64: =I32 | J64: =J32 | K64: =K32 | L64: =L32 | M64: =M32 | N64: =N32 | O64: =O32 | ... AF64: =AF32
A65: Profit before tax | B65: pbt | D65: 32.54292 | E65: 17.459213 | F65: 33.992906 | G65: 66.266788 | H65: =(((H59-H62)+H63)+H64) | I65: =(((I59-I62)+I63)+I64) | J65: =(((J59-J62)+J63)+J64) | K65: =(((K59-K62)+K63)+K64) | L65: =(((L59-L62)+L63)+L64) | M65: =(((M59-M62)+M63)+M64) | N65: =(((N59-N62)+N63)+N64) | O65: =(((O59-O62)+O63)+O64) | ... AF65: =(((AF59-AF62)+AF63)+AF64)
A66: Tax | B66: tax | D66: 18.859134 | E66: 3.271162 | F66: 8.866261 | G66: 16.18046 | H66: =(MAX(H65,0)*H28) | I66: =(MAX(I65,0)*I28) | J66: =(MAX(J65,0)*J28) | K66: =(MAX(K65,0)*K28) | L66: =(MAX(L65,0)*L28) | M66: =(MAX(M65,0)*M28) | N66: =(MAX(N65,0)*N28) | O66: =(MAX(O65,0)*O28) | ... AF66: =(MAX(AF65,0)*AF28)
A67: Net profit (incl. minorities) | B67: np | D67: 13.683786 | E67: 14.188051 | F67: 25.126645 | G67: 50.086328 | H67: =(H65-H66) | I67: =(I65-I66) | J67: =(J65-J66) | K67: =(K65-K66) | L67: =(L65-L66) | M67: =(M65-M66) | N67: =(N65-N66) | O67: =(O65-O66) | ... AF67: =(AF65-AF66)
A68: Minority interests | B68: minority | D68: 0.027958 | E68: 0.268588 | F68: 0.719231 | G68: 0.076551 | H68: =(H67*H33) | I68: =(I67*I33) | J68: =(J67*J33) | K68: =(K67*K33) | L68: =(L67*L33) | M68: =(M67*M33) | N68: =(N67*N33) | O68: =(O67*O33) | ... AF68: =(AF67*AF33)
A69: Net profit to parent | B69: np_parent | D69: 13.655828 | E69: 13.919463 | F69: 24.407414 | G69: 50.009777 | H69: =(H67-H68) | I69: =(I67-I68) | J69: =(J67-J68) | K69: =(K67-K68) | L69: =(L67-L68) | M69: =(M67-M68) | N69: =(N67-N68) | O69: =(O67-O68) | ... AF69: =(AF67-AF68)
A70: Shares outstanding (m) | B70: shares | D70: 141784.04 | E70: 141784.04 | F70: 141784.04 | G70: 141784.04 | H70: =(G70*(1+H35)) | I70: =(H70*(1+I35)) | J70: =(I70*(1+J35)) | K70: =(J70*(1+K35)) | L70: =(K70*(1+L35)) | M70: =(L70*(1+M35)) | N70: =(M70*(1+N35)) | O70: =(N70*(1+O35)) | ... AF70: =(AE70*(1+AF35))
A71: EPS | B71: eps | D71: 9.6314282e-05 | E71: 9.8173694e-05 | F71: 0.000172145 | G71: 0.00035271796 | H71: =(IF(H70=0,0,H69/H70)*$C$8) | I71: =(IF(I70=0,0,I69/I70)*$C$8) | J71: =(IF(J70=0,0,J69/J70)*$C$8) | K71: =(IF(K70=0,0,K69/K70)*$C$8) | L71: =(IF(L70=0,0,L69/L70)*$C$8) | M71: =(IF(M70=0,0,M69/M70)*$C$8) | N71: =(IF(N70=0,0,N69/N70)*$C$8) | O71: =(IF(O70=0,0,O69/O70)*$C$8) | ... AF71: =(IF(AF70=0,0,AF69/AF70)*$C$8)
A72: DPS (declared on the year) | B72: dps | D72: 0 | E72: 0 | F72: 0 | G72: 0 | H72: =(MAX(H71,0)*H34) | I72: =(MAX(I71,0)*I34) | J72: =(MAX(J71,0)*J34) | K72: =(MAX(K71,0)*K34) | L72: =(MAX(L71,0)*L34) | M72: =(MAX(M71,0)*M34) | N72: =(MAX(N71,0)*N34) | O72: =(MAX(O71,0)*O34) | ... AF72: =(MAX(AF71,0)*AF34)
A73: Dividends paid | B73: dividends_paid | H73: =IF($C$8=0,0,(G72*G70)/$C$8) | I73: =IF($C$8=0,0,(H72*H70)/$C$8) | J73: =IF($C$8=0,0,(I72*I70)/$C$8) | K73: =IF($C$8=0,0,(J72*J70)/$C$8) | L73: =IF($C$8=0,0,(K72*K70)/$C$8) | M73: =IF($C$8=0,0,(L72*L70)/$C$8) | N73: =IF($C$8=0,0,(M72*M70)/$C$8) | O73: =IF($C$8=0,0,(N72*N70)/$C$8) | ... AF73: =IF($C$8=0,0,(AE72*AE70)/$C$8)
A74: Capital expenditure | B74: capex | D74: 127.14706 | E74: 36.88712 | F74: 19.71836 | G74: 69.184491 | H74: =(((H41*H25)*$C$10)+H26) | I74: =(((I41*I25)*$C$10)+I26) | J74: =(((J41*J25)*$C$10)+J26) | K74: =(((K41*K25)*$C$10)+K26) | L74: =(((L41*L25)*$C$10)+L26) | M74: =(((M41*M25)*$C$10)+M26) | N74: =(((N41*N25)*$C$10)+N26) | O74: =(((O41*O25)*$C$10)+O26) | ... AF74: =(((AF41*AF25)*$C$10)+AF26)
A75: Change in working capital | B75: delta_nwc | E75: -38.941368 | F75: 38.458805 | G75: 39.758526 | H75: =(H80-G80) | I75: =(I80-H80) | J75: =(J80-I80) | K75: =(K80-J80) | L75: =(L80-K80) | M75: =(M80-L80) | N75: =(N80-M80) | O75: =(O80-N80) | ... AF75: =(AF80-AE80)
A76: Free cash flow to firm | B76: fcff | E76: 16.373776 | F76: -21.40329 | G76: -32.349741 | H76: =((((H59*(1-H28))+H60)-H74)-H75) | I76: =((((I59*(1-I28))+I60)-I74)-I75) | J76: =((((J59*(1-J28))+J60)-J74)-J75) | K76: =((((K59*(1-K28))+K60)-K74)-K75) | L76: =((((L59*(1-L28))+L60)-L74)-L75) | M76: =((((M59*(1-M28))+M60)-M74)-M75) | N76: =((((N59*(1-N28))+N60)-N74)-N75) | O76: =((((O59*(1-O28))+O60)-O74)-O75) | ... AF76: =((((AF59*(1-AF28))+AF60)-AF74)-AF75)
A77: Net borrowing | B77: net_borrowing | E77: 2.5359 | F77: 38.61445 | G77: 84.920729 | H77: =H31 | I77: =I31 | J77: =J31 | K77: =K31 | L77: =L31 | M77: =M31 | N77: =N31 | O77: =O31 | ... AF77: =AF31
A78: Dividends to minorities | B78: minority_div | H78: =(MAX(G68,0)*H34) | I78: =(MAX(H68,0)*I34) | J78: =(MAX(I68,0)*J34) | K78: =(MAX(J68,0)*K34) | L78: =(MAX(K68,0)*L34) | M78: =(MAX(L68,0)*M34) | N78: =(MAX(M68,0)*N34) | O78: =(MAX(N68,0)*O34) | ... AF78: =(MAX(AE68,0)*AF34)
A79: Free cash flow to equity | B79: fcfe | H79: =(((((H67+H60)-H74)-H75)+H77)-H78) | I79: =(((((I67+I60)-I74)-I75)+I77)-I78) | J79: =(((((J67+J60)-J74)-J75)+J77)-J78) | K79: =(((((K67+K60)-K74)-K75)+K77)-K78) | L79: =(((((L67+L60)-L74)-L75)+L77)-L78) | M79: =(((((M67+M60)-M74)-M75)+M77)-M78) | N79: =(((((N67+N60)-N74)-N75)+N77)-N78) | O79: =(((((O67+O60)-O74)-O75)+O77)-O78) | ... AF79: =(((((AF67+AF60)-AF74)-AF75)+AF77)-AF78)
A80: Operating working capital | B80: nwc | D80: 116.93252 | E80: 77.99115 | F80: 116.44996 | G80: 156.20848 | H80: =(H55*H27) | I80: =(I55*I27) | J80: =(J55*J27) | K80: =(K55*K27) | L80: =(L55*L27) | M80: =(M55*M27) | N80: =(N55*N27) | O80: =(O55*O27) | ... AF80: =(AF55*AF27)
A81: Cash & equivalents | B81: cash | D81: 10.169549 | E81: 4.563747 | F81: 11.803906 | G81: 40.435499 | H81: =(((((((G81+H67)+H60)-H74)-H75)+H77)-H73)-H78) | I81: =(((((((H81+I67)+I60)-I74)-I75)+I77)-I73)-I78) | J81: =(((((((I81+J67)+J60)-J74)-J75)+J77)-J73)-J78) | K81: =(((((((J81+K67)+K60)-K74)-K75)+K77)-K73)-K78) | L81: =(((((((K81+L67)+L60)-L74)-L75)+L77)-L73)-L78) | M81: =(((((((L81+M67)+M60)-M74)-M75)+M77)-M73)-M78) | N81: =(((((((M81+N67)+N60)-N74)-N75)+N77)-N73)-N78) | O81: =(((((((N81+O67)+O60)-O74)-O75)+O77)-O73)-O78) | ... AF81: =(((((((AE81+AF67)+AF60)-AF74)-AF75)+AF77)-AF73)-AF78)
A82: Total debt | B82: debt | D82: 63.69458 | E82: 66.23048 | F82: 104.84493 | G82: 189.76566 | H82: =(G82+H77) | I82: =(H82+I77) | J82: =(I82+J77) | K82: =(J82+K77) | L82: =(K82+L77) | M82: =(L82+M77) | N82: =(M82+N77) | O82: =(N82+O77) | ... AF82: =(AE82+AF77)
A83: Fixed assets (net) | B83: ppe | D83: 525.0352 | E83: 576.55012 | F83: 595.16828 | G83: 652.84759 | H83: =((G83+H74)-H60) | I83: =((H83+I74)-I60) | J83: =((I83+J74)-J60) | K83: =((J83+K74)-K60) | L83: =((K83+L74)-L60) | M83: =((L83+M74)-M60) | N83: =((M83+N74)-N60) | O83: =((N83+O74)-O60) | ... AF83: =((AE83+AF74)-AF60)
A84: Parent shareholders' equity | B84: equity | D84: 1162.6296 | E84: 1176.5952 | F84: 1200.9918 | G84: 1250.9866 | H84: =((G84+H69)-H73) | I84: =((H84+I69)-I73) | J84: =((I84+J69)-J73) | K84: =((J84+K69)-K73) | L84: =((K84+L69)-L73) | M84: =((L84+M69)-M73) | N84: =((M84+N69)-N73) | O84: =((N84+O69)-O73) | ... AF84: =((AE84+AF69)-AF73)
A85: Minority interest (balance sheet) | B85: minority_bs | D85: -207.51204 | E85: -207.24391 | F85: -206.52518 | G85: -206.44863 | H85: =((G85+H68)-H78) | I85: =((H85+I68)-I78) | J85: =((I85+J68)-J78) | K85: =((J85+K68)-K78) | L85: =((K85+L68)-L78) | M85: =((L85+M68)-M78) | N85: =((M85+N68)-N78) | O85: =((N85+O68)-O78) | ... AF85: =((AE85+AF68)-AF78)
A86: Other assets less other liabilities | B86: other_net | D86: 366.67485 | E86: 376.47673 | F86: 375.8894 | G86: 384.81206 | H86: =G86 | I86: =H86 | J86: =I86 | K86: =J86 | L86: =K86 | M86: =L86 | N86: =M86 | O86: =N86 | ... AF86: =AE86
A87: Balance check (should be zero) | B87: bs_check | H87: =((((((H81+H80)+H83)+H86)-H82)-H84)-H85) | I87: =((((((I81+I80)+I83)+I86)-I82)-I84)-I85) | J87: =((((((J81+J80)+J83)+J86)-J82)-J84)-J85) | K87: =((((((K81+K80)+K83)+K86)-K82)-K84)-K85) | L87: =((((((L81+L80)+L83)+L86)-L82)-L84)-L85) | M87: =((((((M81+M80)+M83)+M86)-M82)-M84)-M85) | N87: =((((((N81+N80)+N83)+N86)-N82)-N84)-N85) | O87: =((((((O81+O80)+O83)+O86)-O82)-O84)-O85) | ... AF87: =((((((AF81+AF80)+AF83)+AF86)-AF82)-AF84)-AF85)
A88: Net debt (cash) | B88: net_debt | D88: 53.525031 | E88: 61.666733 | F88: 93.041024 | G88: 149.33016 | H88: =(H82-H81) | I88: =(I82-I81) | J88: =(J82-J81) | K88: =(K82-K81) | L88: =(L82-L81) | M88: =(M82-M81) | N88: =(N82-N81) | O88: =(O82-O81) | ... AF88: =(AF82-AF81)
A89: Book value per share | B89: bvps | D89: 0.0082000032 | E89: 0.0082985022 | F89: 0.0084705711 | G89: 0.0088231835 | H89: =(IF(H70=0,0,H84/H70)*$C$8) | I89: =(IF(I70=0,0,I84/I70)*$C$8) | J89: =(IF(J70=0,0,J84/J70)*$C$8) | K89: =(IF(K70=0,0,K84/K70)*$C$8) | L89: =(IF(L70=0,0,L84/L70)*$C$8) | M89: =(IF(M70=0,0,M84/M70)*$C$8) | N89: =(IF(N70=0,0,N84/N70)*$C$8) | O89: =(IF(O70=0,0,O84/O70)*$C$8) | ... AF89: =(IF(AF70=0,0,AF84/AF70)*$C$8)
A90: Revenue growth | B90: revenue_growth | E90: 3.0051515 | F90: 2.4809724 | G90: 0.53595548 | H90: =(IF(G55=0,0,H55/G55)-1) | I90: =(IF(H55=0,0,I55/H55)-1) | J90: =(IF(I55=0,0,J55/I55)-1) | K90: =(IF(J55=0,0,K55/J55)-1) | L90: =(IF(K55=0,0,L55/K55)-1) | M90: =(IF(L55=0,0,M55/L55)-1) | N90: =(IF(M55=0,0,N55/M55)-1) | O90: =(IF(N55=0,0,O55/N55)-1) | ... AF90: =(IF(AE55=0,0,AF55/AE55)-1)
A91: Gross margin | B91: gross_margin | D91: 0.56393731 | E91: 0.56299594 | F91: 0.49072026 | G91: 0.56234864 | H91: =IF(H55=0,0,H57/H55) | I91: =IF(I55=0,0,I57/I55) | J91: =IF(J55=0,0,J57/J55) | K91: =IF(K55=0,0,K57/K55) | L91: =IF(L55=0,0,L57/L55) | M91: =IF(M55=0,0,M57/M55) | N91: =IF(N55=0,0,N57/N55) | O91: =IF(O55=0,0,O57/O55) | ... AF91: =IF(AF55=0,0,AF57/AF55)
A92: EBITDA margin | B92: ebitda_margin | D92: 0.16166627 | E92: 0.37573088 | F92: 0.29528254 | G92: 0.39841176 | H92: =IF(H55=0,0,H61/H55) | I92: =IF(I55=0,0,I61/I55) | J92: =IF(J55=0,0,J61/J55) | K92: =IF(K55=0,0,K61/K55) | L92: =IF(L55=0,0,L61/L55) | M92: =IF(M55=0,0,M61/M55) | N92: =IF(N55=0,0,N61/N55) | O92: =IF(O55=0,0,O61/O55) | ... AF92: =IF(AF55=0,0,AF61/AF55)
A93: EBIT margin | B93: ebit_margin | D93: 0.091314185 | E93: 0.36663971 | F93: 0.26364393 | G93: 0.37369379 | H93: =IF(H55=0,0,H59/H55) | I93: =IF(I55=0,0,I59/I55) | J93: =IF(J55=0,0,J59/J55) | K93: =IF(K55=0,0,K59/K55) | L93: =IF(L55=0,0,L59/L55) | M93: =IF(M55=0,0,M59/M55) | N93: =IF(N55=0,0,N59/N55) | O93: =IF(O55=0,0,O59/O55) | ... AF93: =IF(AF55=0,0,AF59/AF55)
A94: Net margin | B94: np_margin | D94: 1.1727333 | E94: 0.29845904 | F94: 0.15034308 | G94: 0.20055707 | H94: =IF(H55=0,0,H69/H55) | I94: =IF(I55=0,0,I69/I55) | J94: =IF(J55=0,0,J69/J55) | K94: =IF(K55=0,0,K69/K55) | L94: =IF(L55=0,0,L69/L55) | M94: =IF(M55=0,0,M69/M55) | N94: =IF(N55=0,0,N69/N55) | O94: =IF(O55=0,0,O69/O55) | ... AF94: =IF(AF55=0,0,AF69/AF55)
A95: EPS growth | B95: eps_growth | E95: 0.019305676 | F95: 0.75347381 | G95: 1.0489585 | H95: =(IF(G71=0,0,H71/G71)-1) | I95: =(IF(H71=0,0,I71/H71)-1) | J95: =(IF(I71=0,0,J71/I71)-1) | K95: =(IF(J71=0,0,K71/J71)-1) | L95: =(IF(K71=0,0,L71/K71)-1) | M95: =(IF(L71=0,0,M71/L71)-1) | N95: =(IF(M71=0,0,N71/M71)-1) | O95: =(IF(N71=0,0,O71/N71)-1) | ... AF95: =(IF(AE71=0,0,AF71/AE71)-1)
A96: ROE | B96: roe | E96: 0.01190092 | F96: 0.020531248 | G96: 0.040791368 | H96: =IF(IF(2=0,0,(H84+G84)/2)=0,0,H69/IF(2=0,0,(H84+G84)/2)) | I96: =IF(IF(2=0,0,(I84+H84)/2)=0,0,I69/IF(2=0,0,(I84+H84)/2)) | J96: =IF(IF(2=0,0,(J84+I84)/2)=0,0,J69/IF(2=0,0,(J84+I84)/2)) | K96: =IF(IF(2=0,0,(K84+J84)/2)=0,0,K69/IF(2=0,0,(K84+J84)/2)) | L96: =IF(IF(2=0,0,(L84+K84)/2)=0,0,L69/IF(2=0,0,(L84+K84)/2)) | M96: =IF(IF(2=0,0,(M84+L84)/2)=0,0,M69/IF(2=0,0,(M84+L84)/2)) | N96: =IF(IF(2=0,0,(N84+M84)/2)=0,0,N69/IF(2=0,0,(N84+M84)/2)) | O96: =IF(IF(2=0,0,(O84+N84)/2)=0,0,O69/IF(2=0,0,(O84+N84)/2)) | ... AF96: =IF(IF(2=0,0,(AF84+AE84)/2)=0,0,AF69/IF(2=0,0,(AF84+AE84)/2))
A97: Net debt / EBITDA | B97: net_debt_ebitda | D97: 28.43274 | E97: 3.5191381 | F97: 1.9408787 | G97: 1.5031365 | H97: =IF(H61=0,0,H88/H61) | I97: =IF(I61=0,0,I88/I61) | J97: =IF(J61=0,0,J88/J61) | K97: =IF(K61=0,0,K88/K61) | L97: =IF(L61=0,0,L88/L61) | M97: =IF(M61=0,0,M88/M61) | N97: =IF(N61=0,0,N88/N61) | O97: =IF(O61=0,0,O88/O61) | ... AF97: =IF(AF61=0,0,AF88/AF61)
A98: Payout ratio | B98: payout_ratio | D98: 0 | E98: 0 | F98: 0 | G98: 0 | H98: =IF(H71=0,0,H72/H71) | I98: =IF(I71=0,0,I72/I71) | J98: =IF(J71=0,0,J72/J71) | K98: =IF(K71=0,0,K72/K71) | L98: =IF(L71=0,0,L72/L71) | M98: =IF(M71=0,0,M72/M71) | N98: =IF(N71=0,0,N72/N71) | O98: =IF(O71=0,0,O72/O71) | ... AF98: =IF(AF71=0,0,AF72/AF71)
A99: Capex / revenue | B99: capex_revenue | D99: 10.919117 | E99: 0.79092811 | F99: 0.12145977 | G99: 0.27745452 | H99: =IF(H55=0,0,H74/H55) | I99: =IF(I55=0,0,I74/I55) | J99: =IF(J55=0,0,J74/J55) | K99: =IF(K55=0,0,K74/K55) | L99: =IF(L55=0,0,L74/L55) | M99: =IF(M55=0,0,M74/M55) | N99: =IF(N55=0,0,N74/N55) | O99: =IF(O55=0,0,O74/O55) | ... AF99: =IF(AF55=0,0,AF74/AF55)
A101: VALUATION
A102: Last price (IDR) | C102: 340
A103: Shares outstanding (m) | C103: 141784.04
A104: IDR per USD (spot) | C104: 18120
A105: Debt at balance-sheet date | C105: 306.99473
...
